Workbook
Name Dept: '[1]1_New Hire'!#REF!
Name Dept: '[1]1_New Hire'!#REF!

Sheet 账单明细
G1: 收款通知书
G2: ADVISE ON COLLECTION
G3: 46174
A5: 公司名称：美诺电器有限公司.
A6: 序号 | B6: 姓名 | C6: 员工编号 | D6: 发生年月 | E6: 入职日期 | F6: 离职日期 | G6: 管理费 | H6: 当月社保基数 | I6: 当月公积金基数 | J6: 社保类 公司支付 Social Insurance Premiums Paid by Employer | S6: 公积金类 公司支付 Provident Fund Paid by Employer | T6: 公司合计 | U6: 社保类 个人支付 Social Insurance Premiums Paid by Employee | AA6: 公积金类 个人支付 Provident Fund Paid by Employee | AB6: 个人合计 | AC6: 实发工资 | AD6: 税前工资 | AE6: 13薪/奖金 | AF6: 其他 | AG6: 离职补尝金 | AH6: 总费用 | AI6: 附件税 | AJ6: 增值税 | AK6: 总计 | AL6: 备注 | AM6: 证件号码 | AN6: 社保缴纳地 | AO6: 所属公司 | AP6: 收入
A7: S/N | B7: Name | C7: Number | D7: YYYYMM | E7: Employment Start Date | F7: Employment Departure Date | G7: Adm Fee | H7: Social Insurance Base Amount of Current Month | I7: Provident Fund Base Amount of Current Month | J7: 养老保险 Endowment | K7: 医疗保险 Medical | L7: 失业保险 Unemploy-ment | M7: 工伤保险 Employment Injury | N7: 医疗生育保险 Medical Maternity | O7: 大病 Major Disease | P7: 保障金 Disabled people&Back pay Fund | Q7: 采暖费Heating Fee | R7: 社保工会费 Trade union fee | S7: 公积金 Provident Fund | T7: Subtotal of Employer Payment | U7: 养老保险 Endowment | V7: 医疗保险 Medical | W7: 失业保险 Unemploy-ment | X7: 工伤保险 Employment Injury | Y7: 生育保险 Maternity | Z7: 大病 Major Disease | AA7: 公积金 Provident Fund | AB7: Subtotal of Personal Payment | AL7: Remarks | AM7: ID Card | AN7: Location
A8: 1 | B8: 傅禄杰 | C8: MNCN00101 | D8: 202606 | E8: 2016-3-1 | G8: 595 | H8: 9902.6 | I8: 9902.6 | J8: =ROUND($H8*16%,2) -> 1584.42 | K8: =ROUNDDOWN(H8*9%,2) -> 891.23 | L8: =ROUND(H8*0.5%,2) -> 49.51 | M8: =ROUND(H8*0.32%,2) -> 31.69 | P8: =ROUND(H8*(1.5%*0.9),2) -> 133.69 | S8: =ROUND(I8*7%,0) -> 693 | T8: =ROUND(SUM(J8:S8),2) -> 3383.54 | U8: =ROUND(H8*8%,2) -> 792.21 | V8: =ROUND(H8*2%,2) -> 198.05 | W8: =ROUND(H8*0.5%,2) -> 49.51 | AA8: =ROUND(I8*7%,0) -> 693 | AB8: =ROUND(SUM(U8:AA8),2) -> 1732.77 | AC8: =VLOOKUP(AM:AM,工资明细!E:AP,38,0) -> 6306.12 | AD8: =VLOOKUP(AM:AM,工资明细!E:AH,30,0) -> 6400.11 | AH8: =ROUND(G8+T8+AB8+AD8+AF8+AG8+AE8,2) -> 12111.42 | AI8: =ROUND(AH8*(1/(1-0.78%)-1),2) -> 95.21 | AJ8: =ROUND(SUM(AH8:AI8)*6%,2) -> 732.4 | AK8: =ROUND(SUM(AH8:AJ8),2) -> 12939.03 | AM8: 310103198112094018 | AN8: 上海市 | AO8: 上海合杰 | AP8: =U8 -> 792.21 | AQ8: =V8+Z8 -> 198.05 | AR8: =W8 -> 49.51 | AS8: =AA8 -> 693
A9: 2 | B9: 刘星全 | C9: MNCN00263 | D9: 202606 | E9: 2016-4-13 | G9: 595 | H9: 14649.8 | I9: 14649.8 | J9: =ROUND($H9*16%,2) -> 2343.97 | K9: =ROUNDDOWN(H9*9%,2) -> 1318.48 | L9: =ROUND(H9*0.5%,2) -> 73.25 | M9: =ROUND(H9*0.32%,2) -> 46.88 | P9: =ROUND(H9*(1.5%*0.9),2) -> 197.77 | S9: =ROUND(I9*7%,0) -> 1025 | T9: =ROUND(SUM(J9:S9),2) -> 5005.35 | U9: =ROUND(H9*8%,2) -> 1171.98 | V9: =ROUND(H9*2%,2) -> 293 | W9: =ROUND(H9*0.5%,2) -> 73.25 | AA9: =ROUND(I9*7%,0) -> 1025 | AB9: =ROUND(SUM(U9:AA9),2) -> 2563.23 | AC9: =VLOOKUP(AM:AM,工资明细!E:AP,38,0) -> 9316.74 | AD9: =VLOOKUP(AM:AM,工资明细!E:AH,30,0) -> 9316.74 | AH9: =ROUND(G9+T9+AB9+AD9+AF9+AG9+AE9,2) -> 17480.32 | AI9: =ROUND(AH9*(1/(1-0.78%)-1),2) -> 137.42 | AJ9: =ROUND(SUM(AH9:AI9)*6%,2) -> 1057.06 | AK9: =ROUND(SUM(AH9:AJ9),2) -> 18674.8 | AM9: 37292519890401691X | AN9: 上海市 | AO9: 上海合杰 | AP9: =U9 -> 1171.98 | AQ9: =V9+Z9 -> 293 | AR9: =W9 -> 73.25 | AS9: =AA9 -> 1025
A10: 3 | B10: 卢晓香 | C10: MNCN00391 | D10: 202606 | E10: 2018-2-7 | G10: 595 | H10: 11167.4 | I10: 11167.4 | J10: =ROUND($H10*16%,2) -> 1786.78 | K10: =ROUND(H10*9%,2) -> 1005.07 | L10: =ROUND(H10*0.5%,2) -> 55.84 | M10: =ROUND(H10*0.32%,2) -> 35.74 | P10: =ROUND(H10*(1.5%*0.9),2) -> 150.76 | S10: =ROUND(I10*7%,0) -> 782 | T10: =ROUND(SUM(J10:S10),2) -> 3816.19 | U10: =ROUND(H10*8%,2) -> 893.39 | V10: =ROUND(H10*2%,2) -> 223.35 | W10: =ROUND(H10*0.5%,2) -> 55.84 | AA10: =ROUND(I10*7%,0) -> 782 | AB10: =ROUND(SUM(U10:AA10),2) -> 1954.58 | AC10: =VLOOKUP(AM:AM,工资明细!E:AP,38,0) -> 5921.19 | AD10: =VLOOKUP(AM:AM,工资明细!E:AH,30,0) -> 5921.19 | AH10: =ROUND(G10+T10+AB10+AD10+AF10+AG10+AE10,2) -> 12286.96 | AI10: =ROUND(AH10*(1/(1-0.78%)-1),2) -> 96.59 | AJ10: =ROUND(SUM(AH10:AI10)*6%,2) -> 743.01 | AK10: =ROUND(SUM(AH10:AJ10),2) -> 13126.56 | AM10: 422324198009156823 | AN10: 上海市 | AO10: 上海合杰 | AP10: =U10 -> 893.39 | AQ10: =V10+Z10 -> 223.35 | AR10: =W10 -> 55.84 | AS10: =AA10 -> 782
A11: 4 | B11: 秦懿 | C11: MNCN00369 | D11: 202606 | E11: 2017-10-9 | G11: 595 | H11: 9803.1 | I11: 9803.1 | J11: =ROUND($H11*16%,2) -> 1568.5 | K11: =ROUND(H11*9%,2) -> 882.28 | L11: =ROUND(H11*0.5%,2) -> 49.02 | M11: =ROUND(H11*0.32%,2) -> 31.37 | P11: =ROUND(H11*(1.5%*0.9),2) -> 132.34 | S11: =ROUND(I11*7%,0) -> 686 | T11: =ROUND(SUM(J11:S11),2) -> 3349.51 | U11: =ROUND(H11*8%,2) -> 784.25 | V11: =ROUND(H11*2%,2) -> 196.06 | W11: =ROUND(H11*0.5%,2) -> 49.02 | AA11: =ROUND(I11*7%,0) -> 686 | AB11: =ROUND(SUM(U11:AA11),2) -> 1715.33 | AC11: =VLOOKUP(AM:AM,工资明细!E:AP,38,0) -> 5379.19 | AD11: =VLOOKUP(AM:AM,工资明细!E:AH,30,0) -> 5379.19 | AH11: =ROUND(G11+T11+AB11+AD11+AF11+AG11+AE11,2) -> 11039.03 | AI11: =ROUND(AH11*(1/(1-0.78%)-1),2) -> 86.78 | AJ11: =ROUND(SUM(AH11:AI11)*6%,2) -> 667.55 | AK11: =ROUND(SUM(AH11:AJ11),2) -> 11793.36 | AM11: 310105198108060045 | AN11: 上海市 | AO11: 上海合杰 | AP11: =U11 -> 784.25 | AQ11: =V11+Z11 -> 196.06 | AR11: =W11 -> 49.02 | AS11: =AA11 -> 686
A12: 5 | B12: 周之绮 | C12: MNCN00390 | D12: 202606 | E12: 43136 | G12: 595 | H12: 17572.3 | I12: 17572.3 | J12: =ROUND($H12*16%,2) -> 2811.57 | K12: =ROUND(H12*9%,2) -> 1581.51 | L12: =ROUND(H12*0.5%,2) -> 87.86 | M12: =ROUND(H12*0.32%,2) -> 56.23 | P12: =ROUND(H12*(1.5%*0.9),2) -> 237.23 | S12: =ROUND(I12*7%,0) -> 1230 | T12: =ROUND(SUM(J12:S12),2) -> 6004.4 | U12: =ROUND(H12*8%,2) -> 1405.78 | V12: =ROUND(H12*2%,2) -> 351.45 | W12: =ROUND(H12*0.5%,2) -> 87.86 | AA12: =ROUND(I12*7%,0) -> 1230 | AB12: =ROUND(SUM(U12:AA12),2) -> 3075.09 | AC12: =VLOOKUP(AM:AM,工资明细!E:AP,38,0) -> 14293.88 | AD12: =VLOOKUP(AM:AM,工资明细!E:AH,30,0) -> 14300.84 | AH12: =ROUND(G12+T12+AB12+AD12+AF12+AG12+AE12,2) -> 23975.33 | AI12: =ROUND(AH12*(1/(1-0.78%)-1),2) -> 188.48 | AJ12: =ROUND(SUM(AH12:AI12)*6%,2) -> 1449.83 | AK12: =ROUND(SUM(AH12:AJ12),2) -> 25613.64 | AM12: 310107198302217221 | AN12: 上海市 | AO12: 上海合杰 | AP12: =U12 -> 1405.78 | AQ12: =V12+Z12 -> 351.45 | AR12: =W12 -> 87.86 | AS12: =AA12 -> 1230
A13: 6 | B13: 李旻天 | C13: MNCN00399 | D13: 202606 | E13: 43189 | G13: 595 | H13: 16112 | I13: 16112 | J13: =ROUND($H13*16%,2) -> 2577.92 | K13: =ROUND(H13*9%,2) -> 1450.08 | L13: =ROUND(H13*0.5%,2) -> 80.56 | M13: =ROUND(H13*0.32%,2) -> 51.56 | P13: =ROUND(H13*(1.5%*0.9),2) -> 217.51 | S13: =ROUND(I13*7%,0) -> 1128 | T13: =ROUND(SUM(J13:S13),2) -> 5505.63 | U13: =ROUND(H13*8%,2) -> 1288.96 | V13: =ROUND(H13*2%,2) -> 322.24 | W13: =ROUND(H13*0.5%,2) -> 80.56 | AA13: =ROUND(I13*7%,0) -> 1128 | AB13: =ROUND(SUM(U13:AA13),2) -> 2819.76 | AC13: =VLOOKUP(AM:AM,工资明细!E:AP,38,0) -> 11657.88 | AD13: =VLOOKUP(AM:AM,工资明细!E:AH,30,0) -> 11927.38 | AH13: =ROUND(G13+T13+AB13+AD13+AF13+AG13+AE13,2) -> 20847.77 | AI13: =ROUND(AH13*(1/(1-0.78%)-1),2) -> 163.89 | AJ13: =ROUND(SUM(AH13:AI13)*6%,2) -> 1260.7 | AK13: =ROUND(SUM(AH13:AJ13),2) -> 22272.36 | AM13: 310107198503120944 | AN13: 上海市 | AO13: 上海合杰 | AP13: =U13 -> 1288.96 | AQ13: =V13+Z13 -> 322.24 | AR13: =W13 -> 80.56 | AS13: =AA13 -> 1128
A14: 7 | B14: 陆立琴 | C14: MNCN00414 | D14: 202606 | E14: 43236 | G14: 595 | H14: 7460 | I14: 7405.3 | J14: =ROUND($H14*16%,2) -> 1193.6 | K14: =ROUND(H14*9%,2) -> 671.4 | L14: =ROUND(H14*0.5%,2) -> 37.3 | M14: =ROUND(H14*0.32%,2) -> 23.87 | P14: =ROUND(H14*(1.5%*0.9),2) -> 100.71 | S14: =ROUND(I14*7%,0) -> 518 | T14: =ROUND(SUM(J14:S14),2) -> 2544.88 | U14: =ROUND(H14*8%,2) -> 596.8 | V14: =ROUND(H14*2%,2) -> 149.2 | W14: =ROUND(H14*0.5%,2) -> 37.3 | AA14: =ROUND(I14*7%,0) -> 518 | AB14: =ROUND(SUM(U14:AA14),2) -> 1301.3 | AC14: =VLOOKUP(AM:AM,工资明细!E:AP,38,0) -> 5516.01 | AD14: =VLOOKUP(AM:AM,工资明细!E:AH,30,0) -> 5516.01 | AH14: =ROUND(G14+T14+AB14+AD14+AF14+AG14+AE14,2) -> 9957.19 | AI14: =ROUND(AH14*(1/(1-0.78%)-1),2) -> 78.28 | AJ14: =ROUND(SUM(AH14:AI14)*6%,2) -> 602.13 | AK14: =ROUND(SUM(AH14:AJ14),2) -> 10637.6 | AM14: 320924198001065721 | AN14: 上海市 | AO14: 上海合杰 | AP14: =U14 -> 596.8 | AQ14: =V14+Z14 -> 149.2 | AR14: =W14 -> 37.3 | AS14: =AA14 -> 518
A15: 8 | B15: 王金栋 | C15: MNCN00163 | D15: 202606 | E15: 2016-3-1 | G15: 595 | H15: 29348 | I15: 29348 | J15: =ROUND(H15*16%,2) -> 4695.68 | K15: =ROUND(H15*9.8%,2) -> 2876.1 | L15: =ROUND(H15*0.5%,2) -> 146.74 | M15: =ROUND(H15*0.32%,2) -> 93.91 | P15: =ROUND(H15*1.5%,2) -> 440.22 | S15: =ROUND(I15*12%,0) -> 3522 | T15: =ROUND(SUM(J15:S15),2) -> 11774.65 | U15: =ROUND(H15*8%,2) -> 2347.84 | V15: =ROUND(H15*2%,2) -> 586.96 | W15: =ROUND(H15*0.5%,2) -> 146.74 | Z15: 3 | AA15: =S15 -> 3522 | AB15: =ROUND(SUM(U15:AA15),2) -> 6606.54 | AC15: =VLOOKUP(AM:AM,工资明细!E:AP,38,0) -> 2540 | AD15: =VLOOKUP(AM:AM,工资明细!E:AH,30,0) -> 2540 | AH15: =ROUND(G15+T15+AB15+AD15+AF15+AG15+AE15,2) -> 21516.19 | AI15: =ROUND(AH15*(1/(1-0.78%)-1),2) -> 169.15 | AJ15: =ROUND(SUM(AH15:AI15)*6%,2) -> 1301.12 | AK15: =ROUND(SUM(AH15:AJ15),2) -> 22986.46 | AM15: 110223198702142714 | AN15: 北京市 | AO15: 北京合杰 | AP15: =U15 -> 2347.84 | AQ15: =V15+Z15 -> 589.96 | AR15: =W15 -> 146.74 | AS15: =AA15 -> 3522
A16: 9 | B16: 徐乐 | C16: MNCN00238 | D16: 202606 | E16: 2016-3-1 | G16: 595 | H16: 27346 | I16: 27346 | J16: =ROUND(H16*16%,2) -> 4375.36 | K16: =ROUND(H16*9.8%,2) -> 2679.91 | L16: =ROUND(H16*0.5%,2) -> 136.73 | M16: =ROUND(H16*0.32%,2) -> 87.51 | P16: =ROUND(H16*1.5%,2) -> 410.19 | S16: =ROUND(I16*12%,0) -> 3282 | T16: =ROUND(SUM(J16:S16),2) -> 10971.7 | U16: =ROUND(H16*8%,2) -> 2187.68 | V16: =ROUND(H16*2%,2) -> 546.92 | W16: =ROUND(H16*0.5%,2) -> 136.73 | Z16: 3 | AA16: =S16 -> 3282 | AB16: =ROUND(SUM(U16:AA16),2) -> 6156.33 | AC16: =VLOOKUP(AM:AM,工资明细!E:AP,38,0) -> 5765.02 | AD16: =VLOOKUP(AM:AM,工资明细!E:AH,30,0) -> 6030.89 | AH16: =ROUND(G16+T16+AB16+AD16+AF16+AG16+AE16,2) -> 23753.92 | AI16: =ROUND(AH16*(1/(1-0.78%)-1),2) -> 186.74 | AJ16: =ROUND(SUM(AH16:AI16)*6%,2) -> 1436.44 | AK16: =ROUND(SUM(AH16:AJ16),2) -> 25377.1 | AM16: 110222198702056027 | AN16: 北京市 | AO16: 北京合杰 | AP16: =U16 -> 2187.68 | AQ16: =V16+Z16 -> 549.92 | AR16: =W16 -> 136.73 | AS16: =AA16 -> 3282
A17: 10 | B17: 吕静雯 | C17: MNCN00461 | D17: 202606 | E17: 44301 | G17: 595 | H17: 29678 | I17: 29678 | J17: =ROUND(H17*16%,2) -> 4748.48 | K17: =ROUND(H17*9.8%,2) -> 2908.44 | L17: =ROUND(H17*0.5%,2) -> 148.39 | M17: =ROUND(H17*0.32%,2) -> 94.97 | P17: =ROUND(H17*1.5%,2) -> 445.17 | S17: =ROUND(I17*12%,0) -> 3561 | T17: =ROUND(SUM(J17:S17),2) -> 11906.45 | U17: =ROUND(H17*8%,2) -> 2374.24 | V17: =ROUND(H17*2%,2) -> 593.56 | W17: =ROUND(H17*0.5%,2) -> 148.39 | Z17: 3 | AA17: =S17 -> 3561 | AB17: =ROUND(SUM(U17:AA17),2) -> 6680.19 | AC17: =VLOOKUP(AM:AM,工资明细!E:AP,38,0) -> 4310.52 | AD17: =VLOOKUP(AM:AM,工资明细!E:AH,30,0) -> 4651.18 | AH17: =ROUND(G17+T17+AB17+AD17+AF17+AG17+AE17,2) -> 23832.82 | AI17: =ROUND(AH17*(1/(1-0.78%)-1),2) -> 187.36 | AJ17: =ROUND(SUM(AH17:AI17)*6%,2) -> 1441.21 | AK17: =ROUND(SUM(AH17:AJ17),2) -> 25461.39 | AM17: 130181198905025229 | AN17: 北京市 | AO17: 北京合杰 | AP17: =U17 -> 2374.24 | AQ17: =V17+Z17 -> 596.56 | AR17: =W17 -> 148.39 | AS17: =AA17 -> 3561
A18: 11 | B18: 张晨 | C18: MNCN00553 | D18: 202606 | E18: 44301 | G18: 595 | H18: 7230 | I18: 7230 | J18: =ROUND(H18*16%,2) -> 1156.8 | K18: =ROUND(H18*9.8%,2) -> 708.54 | L18: =ROUND(H18*0.5%,2) -> 36.15 | M18: =ROUND(H18*0.32%,2) -> 23.14 | P18: =ROUND(H18*1.5%,2) -> 108.45 | S18: =ROUND(I18*12%,0) -> 868 | T18: =ROUND(SUM(J18:S18),2) -> 2901.08 | U18: =ROUND(H18*8%,2) -> 578.4 | V18: =ROUND(H18*2%,2) -> 144.6 | W18: =ROUND(H18*0.5%,2) -> 36.15 | Z18: 3 | AA18: =S18 -> 868 | AB18: =ROUND(SUM(U18:AA18),2) -> 1630.15 | AC18: =VLOOKUP(AM:AM,工资明细!E:AP,38,0) -> 7804.78 | AD18: =VLOOKUP(AM:AM,工资明细!E:AH,30,0) -> 7804.78 | AH18: =ROUND(G18+T18+AB18+AD18+AF18+AG18+AE18,2) -> 12931.01 | AI18: =ROUND(AH18*(1/(1-0.78%)-1),2) -> 101.65 | AJ18: =ROUND(SUM(AH18:AI18)*6%,2) -> 781.96 | AK18: =ROUND(SUM(AH18:AJ18),2) -> 13814.62 | AM18: 11010219811008041X | AN18: 北京市 | AO18: 北京合杰 | AP18: =U18 -> 578.4 | AQ18: =V18+Z18 -> 147.6 | AR18: =W18 -> 36.15 | AS18: =AA18 -> 868
A19: 12 | B19: 贾璞 | C19: MNCN00552 | D19: 202606 | E19: 44301 | G19: 595 | H19: 12502 | I19: 12502 | J19: =ROUND(H19*16%,2) -> 2000.32 | K19: =ROUND(H19*9.8%,2) -> 1225.2 | L19: =ROUND(H19*0.5%,2) -> 62.51 | M19: =ROUND(H19*0.32%,2) -> 40.01 | P19: =ROUND(H19*1.5%,2) -> 187.53 | S19: =ROUND(I19*12%,0) -> 1500 | T19: =ROUND(SUM(J19:S19),2) -> 5015.57 | U19: =ROUND(H19*8%,2) -> 1000.16 | V19: =ROUND(H19*2%,2) -> 250.04 | W19: =ROUND(H19*0.5%,2) -> 62.51 | Z19: 3 | AA19: =S19 -> 1500 | AB19: =ROUND(SUM(U19:AA19),2) -> 2815.71 | AC19: =VLOOKUP(AM:AM,工资明细!E:AP,38,0) -> 11590.83 | AD19: =VLOOKUP(AM:AM,工资明细!E:AH,30,0) -> 12636.01 | AH19: =ROUND(G19+T19+AB19+AD19+AF19+AG19+AE19,2) -> 21062.29 | AI19: =ROUND(AH19*(1/(1-0.78%)-1),2) -> 165.58 | AJ19: =ROUND(SUM(AH19:AI19)*6%,2) -> 1273.67 | AK19: =ROUND(SUM(AH19:AJ19),2) -> 22501.54 | AM19: 130624198708032411 | AN19: 北京市 | AO19: 北京合杰 | AP19: =U19 -> 1000.16 | AQ19: =V19+Z19 -> 253.04 | AR19: =W19 -> 62.51 | AS19: =AA19 -> 1500
A20: 13 | B20: 韩英 | C20: MNCN00226 | D20: 202606 | E20: 2016-3-1 | G20: 595 | H20: 23864 | I20: 21696 | J20: =ROUND($H20*16%,2) -> 3818.24 | K20: =ROUND($H20*7%,2) -> 1670.48 | L20: =ROUND(H20*0.5%,2) -> 119.32 | M20: =ROUND($H20*0.4%,2) -> 95.46 | N20: =ROUND($H20*0.8%,2) -> 190.91 | S20: =ROUND(I20*12%,0) -> 2604 | T20: =ROUND(SUM(J20:S20),2) -> 8498.41 | U20: =ROUND($H20*8%,2) -> 1909.12 | V20: =ROUND($H20*2%,2) -> 477.28 | W20: =ROUND($H20*0.5%,2) -> 119.32 | Z20: 10 | AA20: =S20 -> 2604 | AB20: =ROUND(SUM(U20:AA20),2) -> 5119.72 | AC20: =VLOOKUP(AM:AM,工资明细!E:AP,38,0) -> 8187.29 | AD20: =VLOOKUP(AM:AM,工资明细!E:AH,30,0) -> 8776.96 | AH20: =ROUND(G20+T20+AB20+AD20+AF20+AG20+AE20,2) -> 22990.09 | AI20: =ROUND(AH20*(1/(1-0.78%)-1),2) -> 180.73 | AJ20: =ROUND(SUM(AH20:AI20)*6%,2) -> 1390.25 | AK20: =ROUND(SUM(AH20:AJ20),2) -> 24561.07 | AM20: 320123197712131022 | AN20: 南京市 | AO20: 上海合杰 | AP20: =U20 -> 1909.12 | AQ20: =V20+Z20 -> 487.28 | AR20: =W20 -> 119.32 | AS20: =AA20 -> 2604
A21: 14 | B21: 沈国伟 | C21: MNCN00246 | D21: 202606 | E21: 2016-3-1 | G21: 595 | H21: 16997.91 | I21: 13128.87 | J21: =ROUND($H21*16%,2) -> 2719.67 | K21: =ROUND($H21*9.5%,2) -> 1614.8 | L21: =ROUND(H21*0.5%,2) -> 84.99 | M21: =ROUND(H21*0.2%,2) -> 34 | P21: =ROUND(H21*1.5%,2) -> 254.97 | S21: 1575 | T21: =ROUND(SUM(J21:S21),2) -> 6283.43 | U21: =ROUND($H21*8%,2) -> 1359.83 | V21: =ROUND($H21*2%,2) -> 339.96 | W21: =ROUND($H21*0.5%,2) -> 84.99 | AA21: =S21 -> 1575 | AB21: =ROUND(SUM(U21:AA21),2) -> 3359.78 | AC21: =VLOOKUP(AM:AM,工资明细!E:AP,38,0) -> 6578.64 | AD21: =VLOOKUP(AM:AM,工资明细!E:AH,30,0) -> 6578.64 | AH21: =ROUND(G21+T21+AB21+AD21+AF21+AG21+AE21,2) -> 16816.85 | AI21: =ROUND(AH21*(1/(1-0.78%)-1),2) -> 132.2 | AJ21: =ROUND(SUM(AH21:AI21)*6%,2) -> 1016.94 | AK21: =ROUND(SUM(AH21:AJ21),2) -> 17965.99 | AM21: 330184198807080319 | AN21: 杭州市 | AO21: 合杰区域分公司 | AP21: =U21 -> 1359.83 | AQ21: =V21+Z21 -> 339.96 | AR21: =W21 -> 84.99 | AS21: =AA21 -> 1575
A22: 15 | B22: 周华荣 | C22: MNCN00281 | D22: 202606 | E22: 2016-7-1 | G22: 595 | H22: 7464 | I22: 7932 | J22: =ROUND($H22*16%,2) -> 1194.24 | K22: =ROUND(H22*10.5%,2) -> 783.72 | L22: =ROUND(H22*0.5%,2) -> 37.32 | M22: =ROUND(H22*0.4%,2) -> 29.86 | P22: =ROUND(H22*1.5%,2) -> 111.96 | S22: =ROUND(I22*11%,0) -> 873 | T22: =ROUND(SUM(J22:S22),2) -> 3030.1 | U22: =ROUND(H22*8%,2) -> 597.12 | V22: =ROUND(H22*2%,2) -> 149.28 | W22: =ROUND(H22*0.5%,2) -> 37.32 | Z22: 21 | AA22: =S22 -> 873 | AB22: =ROUND(SUM(U22:AA22),2) -> 1677.72 | AC22: =VLOOKUP(AM:AM,工资明细!E:AP,38,0) -> 5546.15 | AD22: =VLOOKUP(AM:AM,工资明细!E:AH,30,0) -> 5546.15 | AH22: =ROUND(G22+T22+AB22+AD22+AF22+AG22+AE22,2) -> 10848.97 | AI22: =ROUND(AH22*(1/(1-0.78%)-1),2) -> 85.29 | AJ22: =ROUND(SUM(AH22:AI22)*6%,2) -> 656.06 | AK22: =ROUND(SUM(AH22:AJ22),2) -> 11590.32 | AM22: 420822198801105563 | AN22: 天津市 | AO22: 合杰区域分公司 | AP22: =U22 -> 597.12 | AQ22: =V22+Z22 -> 170.28 | AR22: =W22 -> 37.32 | AS22: =AA22 -> 873
A23: 16 | B23: 李爱芳 | C23: MNCN00300 | D23: 202606 | E23: 2016-12-17 | G23: 595 | H23: 9488 | I23: 7203.65 | J23: =ROUND($H23*16%,2) -> 1518.08 | K23: =ROUND(H23*6%,2) -> 569.28 | L23: =ROUND($H23*0.5%,2) -> 47.44 | M23: =ROUND($H23*0.4%,2) -> 37.95 | N23: =ROUND($H23*0.8%,2) -> 75.9 | S23: =ROUND(I23*8%,2) -> 576.29 | T23: =ROUND(SUM(J23:S23),2) -> 2824.94 | U23: =ROUND($H23*8%,2) -> 759.04 | V23: =ROUND($H23*2%,2) -> 189.76 | W23: =ROUND($H23*0.5%,2) -> 47.44 | Z23: 5 | AA23: =S23 -> 576.29 | AB23: =ROUND(SUM(U23:AA23),2) -> 1577.53 | AC23: =VLOOKUP(AM:AM,工资明细!E:AP,38,0) -> 8969.56 | AD23: =VLOOKUP(AM:AM,工资明细!E:AH,30,0) -> 9111.31 | AH23: =ROUND(G23+T23+AB23+AD23+AF23+AG23+AE23,2) -> 14108.78 | AI23: =ROUND(AH23*(1/(1-0.78%)-1),2) -> 110.91 | AJ23: =ROUND(SUM(AH23:AI23)*6%,2) -> 853.18 | AK23: =ROUND(SUM(AH23:AJ23),2) -> 15072.87 | AM23: 320981197710083482 | AN23: 苏州园区 | AO23: 上海合杰 | AP23: =U23 -> 759.04 | AQ23: =V23+Z23 -> 194.76 | AR23: =W23 -> 47.44 | AS23: =AA23 -> 576.29
A24: 17 | B24: 程琪 | C24: MNCN00355 | D24: 202606 | E24: 2017-8-16 | G24: 595 | H24: 11666 | I24: 11666.12 | J24: =ROUND($H24*16%,2) -> 1866.56 | K24: =ROUND($H24*8.7%,2) -> 1014.94 | L24: =ROUND($H24*0.7%,2) -> 81.66 | M24: =ROUND($H24*0.2%,2) -> 23.33 | P24: =ROUND(H24*1.5%,2) -> 174.99 | S24: =ROUND($I24*8%,2) -> 933.29 | T24: =ROUND(SUM(J24:S24),2) -> 4094.77 | U24: =ROUND($H24*8%,2) -> 933.28 | V24: =ROUND($H24*2%,2) -> 233.32 | W24: =ROUND($H24*0.3%,2) -> 35 | Z24: 7 | AA24: =S24 -> 933.29 | AB24: =ROUND(SUM(U24:AA24),2) -> 2141.89 | AC24: =VLOOKUP(AM:AM,工资明细!E:AP,38,0) -> 7718.13 | AD24: =VLOOKUP(AM:AM,工资明细!E:AH,30,0) -> 7858.39 | AH24: =ROUND(G24+T24+AB24+AD24+AF24+AG24+AE24,2) -> 14690.05 | AI24: =ROUND(AH24*(1/(1-0.78%)-1),2) -> 115.48 | AJ24: =ROUND(SUM(AH24:AI24)*6%,2) -> 888.33 | AK24: =ROUND(SUM(AH24:AJ24),2) -> 15693.86 | AM24: 42010219880908082x | AN24: 武汉市 | AO24: 合杰区域分公司 | AP24: =U24 -> 933.28 | AQ24: =V24+Z24 -> 240.32 | AR24: =W24 -> 35 | AS24: =AA24 -> 933.29
B25: 贾锐 | D25: 202605 | E25: 43103 | G25: 595 | H25: 2761 | I25: 10640 | J25: =ROUND(H25*16%,2) -> 441.76 | K25: =ROUND(H25*7.55%,2) -> 208.46 | L25: =ROUND(H25*0.6%,2) -> 16.57 | M25: =ROUND(H25*0.4%,2) -> 11.04 | O25: =ROUND(H25*0.75%,2) -> 20.71 | P25: =ROUND(H25*1.5%,2) -> 41.42 | T25: =ROUND(SUM(J25:S25),2) -> 739.96 | U25: =ROUND(H25*8%,2) -> 220.88 | V25: =ROUND(H25*2%,2) -> 55.22 | W25: =ROUND(H25*0.4%,2) -> 11.04 | AA25: =S25 -> 0 | AB25: =ROUND(SUM(U25:AA25),2) -> 287.14 | AH25: =ROUND(G25+T25+AB25+AD25+AF25+AG25+AE25,2) -> 1622.1 | AI25: =ROUND(AH25*(1/(1-0.78%)-1),2) -> 12.75 | AJ25: =ROUND(SUM(AH25:AI25)*6%,2) -> 98.09 | AK25: =ROUND(SUM(AH25:AJ25),2) -> 1732.94 | AL25: 5月基数差异费用 | AM25: 510104198710260016 | AN25: 成都市 | AO25: 成都合杰 | AP25: =U25 -> 220.88 | AQ25: =V25+Z25 -> 55.22 | AR25: =W25 -> 11.04 | AS25: =AA25 -> 0
A26: 18 | B26: 贾锐 | C26: MNCN00381 | D26: 202606 | E26: 43103 | G26: 595 | H26: 6809 | I26: 10640 | J26: =ROUND(H26*16%,2) -> 1089.44 | K26: =ROUND(H26*7.55%,2) -> 514.08 | L26: =ROUND(H26*0.6%,2) -> 40.85 | M26: =ROUND(H26*0.4%,2) -> 27.24 | O26: =ROUND(H26*0.75%,2) -> 51.07 | P26: =ROUND(H26*1.5%,2) -> 102.14 | S26: =ROUNDUP(I26*6%,0) -> 639 | T26: =ROUND(SUM(J26:S26),2) -> 2463.82 | U26: =ROUND(H26*8%,2) -> 544.72 | V26: =ROUND(H26*2%,2) -> 136.18 | W26: =ROUND(H26*0.4%,2) -> 27.24 | AA26: =S26 -> 639 | AB26: =ROUND(SUM(U26:AA26),2) -> 1347.14 | AC26: =VLOOKUP(AM:AM,工资明细!E:AP,38,0) -> 6153.37 | AD26: =VLOOKUP(AM:AM,工资明细!E:AH,30,0) -> 6225.63 | AH26: =ROUND(G26+T26+AB26+AD26+AF26+AG26+AE26,2) -> 10631.59 | AI26: =ROUND(AH26*(1/(1-0.78%)-1),2) -> 83.58 | AJ26: =ROUND(SUM(AH26:AI26)*6%,2) -> 642.91 | AK26: =ROUND(SUM(AH26:AJ26),2) -> 11358.08 | AM26: 510104198710260016 | AN26: 成都市 | AO26: 成都合杰 | AP26: =U26 -> 544.72 | AQ26: =V26+Z26 -> 136.18 | AR26: =W26 -> 27.24 | AS26: =AA26 -> 639
A27: 19 | B27: 胡伟 | C27: MNCN00400 | D27: 202606 | E27: 43199 | G27: 595 | H27: 8994 | I27: 9958 | J27: =ROUND(H27*16%,2) -> 1439.04 | K27: =ROUND($H27*8.5%,2) -> 764.49 | L27: =ROUND($H27*0.5%,2) -> 44.97 | M27: =ROUND($H27*0.6%,2) -> 53.96 | O27: =ROUND(H27*1.5%,2) -> 134.91 | P27: =ROUND(H27*1.5%,2) -> 134.91 | S27: =ROUND(I27*5%,0) -> 498 | T27: =ROUND(SUM(J27:S27),2) -> 3070.28 | U27: =ROUND($H27*8%,2) -> 719.52 | V27: =ROUND($H27*2%,2) -> 179.88 | W27: =ROUND($H27*0.5%,2) -> 44.97 | Z27: 5 | AA27: =S27 -> 498 | AB27: =ROUND(SUM(U27:AA27),2) -> 1447.37 | AC27: =VLOOKUP(AM:AM,工资明细!E:AP,38,0) -> 4511.63 | AD27: =VLOOKUP(AM:AM,工资明细!E:AH,30,0) -> 4511.63 | AH27: =ROUND(G27+T27+AB27+AD27+AF27+AG27+AE27,2) -> 9624.28 | AI27: =ROUND(AH27*(1/(1-0.78%)-1),2) -> 75.66 | AJ27: =ROUND(SUM(AH27:AI27)*6%,2) -> 582 | AK27: =ROUND(SUM(AH27:AJ27),2) -> 10281.94 | AM27: 513029198606282471 | AN27: 重庆市 | AO27: 合杰区域分公司 | AP27: =U27 -> 719.52 | AQ27: =V27+Z27 -> 184.88 | AR27: =W27 -> 44.97 | AS27: =AA27 -> 498
A28: 20 | B28: 王李赫 | C28: MNCN00412 | D28: 202606 | E28: 43224 | G28: 595 | H28: 14912.07 | I28: 17105.25 | J28: =ROUND(H28*16%,2) -> 2385.93 | K28: =ROUND(H28*7%,2) -> 1043.84 | L28: =ROUND(H28*0.7%,2) -> 104.38 | M28: =ROUND(H28*0.32%,2) -> 47.72 | O28: 6.4 | P28: =ROUND(H28*1.5%,2) -> 223.68 | S28: =ROUND(I28*5%,0) -> 855 | T28: =ROUND(SUM(J28:S28),2) -> 4666.95 | U28: =ROUND(H28*8%,2) -> 1192.97 | V28: =ROUND(H28*2%,2) -> 298.24 | W28: =ROUND(H28*0.3%,2) -> 44.74 | Z28: 1.6 | AA28: =S28 -> 855 | AB28: =ROUND(SUM(U28:AA28),2) -> 2392.55 | AC28: =VLOOKUP(AM:AM,工资明细!E:AP,38,0) -> 10202.36 | AD28: =VLOOKUP(AM:AM,工资明细!E:AH,30,0) -> 10250.42 | AH28: =ROUND(G28+T28+AB28+AD28+AF28+AG28+AE28,2) -> 17904.92 | AI28: =ROUND(AH28*(1/(1-0.78%)-1),2) -> 140.76 | AJ28: =ROUND(SUM(AH28:AI28)*6%,2) -> 1082.74 | AK28: =ROUND(SUM(AH28:AJ28),2) -> 19128.42 | AM28: 610102198811072314 | AN28: 西安市 | AO28: 合杰区域分公司 | AP28: =U28 -> 1192.97 | AQ28: =V28+Z28 -> 299.84 | AR28: =W28 -> 44.74 | AS28: =AA28 -> 855
A29: 21 | B29: 王平 | C29: MNCN00424 | D29: 202606 | E29: 43244 | G29: 595 | H29: 9616.5 | I29: 11565.75 | J29: =ROUND(H29*16%,2) -> 1538.64 | K29: =ROUND(H29*7%,2) -> 673.16 | L29: =ROUND(H29*0.7%,2) -> 67.32 | M29: =ROUND(H29*0.32%,2) -> 30.77 | O29: 6.4 | P29: =ROUND(H29*1.5%,2) -> 144.25 | S29: =ROUND(I29*5%,0) -> 578 | T29: =ROUND(SUM(J29:S29),2) -> 3038.54 | U29: =ROUND(H29*8%,2) -> 769.32 | V29: =ROUND(H29*2%,2) -> 192.33 | W29: =ROUND(H29*0.3%,2) -> 28.85 | Z29: 1.6 | AA29: =S29 -> 578 | AB29: =ROUND(SUM(U29:AA29),2) -> 1570.1 | AC29: =VLOOKUP(AM:AM,工资明细!E:AP,38,0) -> 4914.25 | AD29: =VLOOKUP(AM:AM,工资明细!E:AH,30,0) -> 4960.16 | AH29: =ROUND(G29+T29+AB29+AD29+AF29+AG29+AE29,2) -> 10163.8 | AI29: =ROUND(AH29*(1/(1-0.78%)-1),2) -> 79.9 | AJ29: =ROUND(SUM(AH29:AI29)*6%,2) -> 614.62 | AK29: =ROUND(SUM(AH29:AJ29),2) -> 10858.32 | AM29: 610424199508080038 | AN29: 西安市 | AO29: 合杰区域分公司 | AP29: =U29 -> 769.32 | AQ29: =V29+Z29 -> 193.93 | AR29: =W29 -> 28.85 | AS29: =AA29 -> 578
A30: 22 | B30: 祝荣丹 | C30: MNCN00444 | D30: 202606 | E30: 43359 | G30: 595 | H30: 9436 | I30: 9436 | J30: =ROUND(H30*16%,2) -> 1509.76 | K30: =ROUND(H30*6.85%,2) -> 646.37 | L30: =ROUND(H30*0.8%,2) -> 75.49 | M30: =ROUND(H30*0.4%,2) -> 37.74 | P30: =ROUND(H30*1.5%,2) -> 141.54 | S30: =ROUND(I30*7%,0) -> 661 | T30: =ROUND(SUM(J30:S30),2) -> 3071.9 | U30: =ROUND(H30*8%,2) -> 754.88 | V30: =ROUND(H30*2%,2) -> 188.72 | W30: =ROUND(H30*0.2%,2) -> 18.87 | AA30: =S30 -> 661 | AB30: =ROUND(SUM(U30:AA30),2) -> 1623.47 | AC30: =VLOOKUP(AM:AM,工资明细!E:AP,38,0) -> 4449.13 | AD30: =VLOOKUP(AM:AM,工资明细!E:AH,30,0) -> 4449.13 | AH30: =ROUND(G30+T30+AB30+AD30+AF30+AG30+AE30,2) -> 9739.5 | AI30: =ROUND(AH30*(1/(1-0.78%)-1),2) -> 76.57 | AJ30: =ROUND(SUM(AH30:AI30)*6%,2) -> 588.96 | AK30: =ROUND(SUM(AH30:AJ30),2) -> 10405.03 | AM30: 440923199101235762 | AN30: 广州市 | AO30: 合杰区域分公司 | AP30: =U30 -> 754.88 | AQ30: =V30+Z30 -> 188.72 | AR30: =W30 -> 18.87 | AS30: =AA30 -> 661
A31: 23 | B31: 刘明杰 | C31: MNCN00447 | D31: 202606 | E31: 43360 | G31: 595 | H31: 17048 | I31: 18473 | J31: =ROUND($H31*16%,2) -> 2727.68 | K31: =ROUND($H31*8.5%,2) -> 1449.08 | L31: =ROUND($H31*0.5%,2) -> 85.24 | M31: =ROUND($H31*0.6%,2) -> 102.29 | O31: =ROUND(H31*1.5%,2) -> 255.72 | P31: =ROUND(H31*1.5%,2) -> 255.72 | S31: =ROUND(I31*5%,0) -> 924 | T31: =ROUND(SUM(J31:S31),2) -> 5799.73 | U31: =ROUND($H31*8%,2) -> 1363.84 | V31: =ROUND($H31*2%,2) -> 340.96 | W31: =ROUND($H31*0.5%,2) -> 85.24 | Z31: 5 | AA31: =S31 -> 924 | AB31: =ROUND(SUM(U31:AA31),2) -> 2719.04 | AC31: =VLOOKUP(AM:AM,工资明细!E:AP,38,0) -> 9565.04 | AD31: =VLOOKUP(AM:AM,工资明细!E:AH,30,0) -> 10374.38 | AH31: =ROUND(G31+T31+AB31+AD31+AF31+AG31+AE31,2) -> 19488.15 | AI31: =ROUND(AH31*(1/(1-0.78%)-1),2) -> 153.2 | AJ31: =ROUND(SUM(AH31:AI31)*6%,2) -> 1178.48 | AK31: =ROUND(SUM(AH31:AJ31),2) -> 20819.83 | AM31: 500108199010022613 | AN31: 重庆市 | AO31: 合杰区域分公司 | AP31: =U31 -> 1363.84 | AQ31: =V31+Z31 -> 345.96 | AR31: =W31 -> 85.24 | AS31: =AA31 -> 924
A32: 24 | B32: 王译 | C32: MNCN00448 | D32: 202606 | E32: 43360 | G32: 595 | H32: 5981 | I32: 7545 | J32: =ROUND($H32*16%,2) -> 956.96 | K32: =ROUND($H32*8.5%,2) -> 508.39 | L32: =ROUND($H32*0.5%,2) -> 29.91 | M32: =ROUND($H32*0.6%,2) -> 35.89 | O32: =ROUND(H32*1.5%,2) -> 89.72 | P32: =ROUND(H32*1.5%,2) -> 89.72 | S32: =ROUND(I32*5%,0) -> 377 | T32: =ROUND(SUM(J32:S32),2) -> 2087.59 | U32: =ROUND($H32*8%,2) -> 478.48 | V32: =ROUND($H32*2%,2) -> 119.62 | W32: =ROUND($H32*0.5%,2) -> 29.91 | Z32: 5 | AA32: =S32 -> 377 | AB32: =ROUND(SUM(U32:AA32),2) -> 1010.01 | AC32: =VLOOKUP(AM:AM,工资明细!E:AP,38,0) -> 3972.75 | AD32: =VLOOKUP(AM:AM,工资明细!E:AH,30,0) -> 3972.75 | AH32: =ROUND(G32+T32+AB32+AD32+AF32+AG32+AE32,2) -> 7665.35 | AI32: =ROUND(AH32*(1/(1-0.78%)-1),2) -> 60.26 | AJ32: =ROUND(SUM(AH32:AI32)*6%,2) -> 463.54 | AK32: =ROUND(SUM(AH32:AJ32),2) -> 8189.15 | AM32: 500109199008271924 | AN32: 重庆市 | AO32: 合杰区域分公司 | AP32: =U32 -> 478.48 | AQ32: =V32+Z32 -> 124.62 | AR32: =W32 -> 29.91 | AS32: =AA32 -> 377
A33: 25 | B33: 孙亮 | C33: MNCN00445 | D33: 202606 | E33: 43360 | G33: 595 | H33: 14540 | I33: 15170.08 | J33: =ROUND(H33*16%,2) -> 2326.4 | K33: =ROUND(H33*8%,2) -> 1163.2 | L33: =ROUND(H33*0.7%,2) -> 101.78 | M33: =ROUND(H33*0.16%,2) -> 23.26 | P33: =ROUND(H33*1.5%,2) -> 218.1 | S33: =ROUND(I33*5%,0) -> 759 | T33: =ROUND(SUM(J33:S33),2) -> 4591.74 | U33: =ROUND(H33*8%,2) -> 1163.2 | V33: =ROUND(H33*2%,2) -> 290.8 | W33: =ROUND(H33*0.3%,2) -> 43.62 | AA33: =S33 -> 759 | AB33: =ROUND(SUM(U33:AA33),2) -> 2256.62 | AC33: =VLOOKUP(AM:AM,工资明细!E:AP,38,0) -> 10665.99 | AD33: =VLOOKUP(AM:AM,工资明细!E:AH,30,0) -> 10705.76 | AH33: =ROUND(G33+T33+AB33+AD33+AF33+AG33+AE33,2) -> 18149.12 | AI33: =ROUND(AH33*(1/(1-0.78%)-1),2) -> 142.68 | AJ33: =ROUND(SUM(AH33:AI33)*6%,2) -> 1097.51 | AK33: =ROUND(SUM(AH33:AJ33),2) -> 19389.31 | AM33: 370205198604191016 | AN33: 青岛市 | AO33: 合杰区域分公司 | AP33: =U33 -> 1163.2 | AQ33: =V33+Z33 -> 290.8 | AR33: =W33 -> 43.62 | AS33: =AA33 -> 759
A34: 26 | B34: 胡蔷薇 | C34: MNCN00446 | D34: 202606 | E34: 43360 | G34: 595 | H34: 10007 | I34: 11152.91 | J34: =ROUND(H34*16%,2) -> 1601.12 | K34: =ROUND(H34*8%,2) -> 800.56 | L34: =ROUND(H34*0.7%,2) -> 70.05 | M34: =ROUND(H34*0.16%,2) -> 16.01 | P34: =ROUND(H34*1.5%,2) -> 150.11 | S34: =ROUND(I34*5%,0) -> 558 | T34: =ROUND(SUM(J34:S34),2) -> 3195.85 | U34: =ROUND(H34*8%,2) -> 800.56 | V34: =ROUND(H34*2%,2) -> 200.14 | W34: =ROUND(H34*0.3%,2) -> 30.02 | AA34: =S34 -> 558 | AB34: =ROUND(SUM(U34:AA34),2) -> 1588.72 | AC34: =VLOOKUP(AM:AM,工资明细!E:AP,38,0) -> 9198.87 | AD34: =VLOOKUP(AM:AM,工资明细!E:AH,30,0) -> 9198.87 | AH34: =ROUND(G34+T34+AB34+AD34+AF34+AG34+AE34,2) -> 14578.44 | AI34: =ROUND(AH34*(1/(1-0.78%)-1),2) -> 114.61 | AJ34: =ROUND(SUM(AH34:AI34)*6%,2) -> 881.58 | AK34: =ROUND(SUM(AH34:AJ34),2) -> 15574.63 | AM34: 420921198704155525 | AN34: 青岛市 | AO34: 合杰区域分公司 | AP34: =U34 -> 800.56 | AQ34: =V34+Z34 -> 200.14 | AR34: =W34 -> 30.02 | AS34: =AA34 -> 558
A35: 27 | B35: 沈鸿鹏 | C35: MNCN00450 | D35: 202606 | E35: 43372 | G35: 595 | H35: 10173 | I35: 10032.59 | J35: =ROUND(H35*16%,2) -> 1627.68 | K35: =ROUND(H35*8%,2) -> 813.84 | L35: =ROUND(H35*0.7%,2) -> 71.21 | M35: =ROUND(H35*0.16%,2) -> 16.28 | P35: =ROUND(H35*1.5%,2) -> 152.6 | S35: =ROUND(I35*5%,0) -> 502 | T35: =ROUND(SUM(J35:S35),2) -> 3183.61 | U35: =ROUND(H35*8%,2) -> 813.84 | V35: =ROUND(H35*2%,2) -> 203.46 | W35: =ROUND(H35*0.3%,2) -> 30.52 | AA35: =S35 -> 502 | AB35: =ROUND(SUM(U35:AA35),2) -> 1549.82 | AC35: =VLOOKUP(AM:AM,工资明细!E:AP,38,0) -> 5199.86 | AD35: =VLOOKUP(AM:AM,工资明细!E:AH,30,0) -> 5199.86 | AH35: =ROUND(G35+T35+AB35+AD35+AF35+AG35+AE35,2) -> 10528.29 | AI35: =ROUND(AH35*(1/(1-0.78%)-1),2) -> 82.77 | AJ35: =ROUND(SUM(AH35:AI35)*6%,2) -> 636.66 | AK35: =ROUND(SUM(AH35:AJ35),2) -> 11247.72 | AM35: 220284198807302313 | AN35: 青岛市 | AO35: 合杰区域分公司 | AP35: =U35 -> 813.84 | AQ35: =V35+Z35 -> 203.46 | AR35: =W35 -> 30.52 | AS35: =AA35 -> 502
A36: 28 | B36: 张洁 | C36: MNCN00452 | D36: 202606 | E36: 43382 | G36: 595 | H36: 14420 | I36: 13440 | J36: =ROUND($H36*16%,2) -> 2307.2 | K36: =ROUND($H36*7%,2) -> 1009.4 | L36: =ROUND($H36*0.5%,2) -> 72.1 | M36: =ROUND($H36*0.4%,2) -> 57.68 | N36: =ROUND($H36*0.8%,2) -> 115.36 | S36: =ROUND(I36*12%,0) -> 1613 | T36: =ROUND(SUM(J36:S36),2) -> 5174.74 | U36: =ROUND($H36*8%,2) -> 1153.6 | V36: =ROUND($H36*2%,2) -> 288.4 | W36: =ROUND($H36*0.5%,2) -> 72.1 | Z36: 10 | AA36: =S36 -> 1613 | AB36: =ROUND(SUM(U36:AA36),2) -> 3137.1 | AC36: =VLOOKUP(AM:AM,工资明细!E:AP,38,0) -> 6049.86 | AD36: =VLOOKUP(AM:AM,工资明细!E:AH,30,0) -> 6049.86 | AH36: =ROUND(G36+T36+AB36+AD36+AF36+AG36+AE36,2) -> 14956.7 | AI36: =ROUND(AH36*(1/(1-0.78%)-1),2) -> 117.58 | AJ36: =ROUND(SUM(AH36:AI36)*6%,2) -> 904.46 | AK36: =ROUND(SUM(AH36:AJ36),2) -> 15978.74 | AM36: 320106198205172442 | AN36: 南京市 | AO36: 上海合杰 | AP36: =U36 -> 1153.6 | AQ36: =V36+Z36 -> 298.4 | AR36: =W36 -> 72.1 | AS36: =AA36 -> 1613
A37: 29 | B37: 王广春 | C37: MNCN00459 | D37: 202606 | E37: 43524 | G37: 595 | H37: 15418 | I37: 16073 | J37: =ROUND($H37*16%,2) -> 2466.88 | K37: =ROUND($H37*7%,2) -> 1079.26 | L37: =ROUND($H37*0.5%,2) -> 77.09 | M37: =ROUND($H37*0.4%,2) -> 61.67 | N37: =ROUND($H37*0.8%,2) -> 123.34 | S37: =ROUND(I37*12%,0) -> 1929 | T37: =ROUND(SUM(J37:S37),2) -> 5737.24 | U37: =ROUND($H37*8%,2) -> 1233.44 | V37: =ROUND($H37*2%,2) -> 308.36 | W37: =ROUND($H37*0.5%,2) -> 77.09 | Z37: 10 | AA37: =S37 -> 1929 | AB37: =ROUND(SUM(U37:AA37),2) -> 3557.89 | AC37: =VLOOKUP(AM:AM,工资明细!E:AP,38,0) -> 21228.4 | AD37: =VLOOKUP(AM:AM,工资明细!E:AH,30,0) -> 21553.04 | AH37: =ROUND(G37+T37+AB37+AD37+AF37+AG37+AE37,2) -> 31443.17 | AI37: =ROUND(AH37*(1/(1-0.78%)-1),2) -> 247.18 | AJ37: =ROUND(SUM(AH37:AI37)*6%,2) -> 1901.42 | AK37: =ROUND(SUM(AH37:AJ37),2) -> 33591.77 | AM37: 320922199702083617 | AN37: 南京市 | AO37: 上海合杰 | AP37: =U37 -> 1233.44 | AQ37: =V37+Z37 -> 318.36 | AR37: =W37 -> 77.09 | AS37: =AA37 -> 1929
A38: 30 | B38: 王雪娇 | C38: MNCN00477 | D38: 202606 | E38: 43689 | G38: 595 | H38: 21253 | I38: 24921 | J38: =ROUND($H38*16%,2) -> 3400.48 | K38: =ROUND($H38*7%,2) -> 1487.71 | L38: =ROUND($H38*0.5%,2) -> 106.27 | M38: =ROUND($H38*1.1%,2) -> 233.78 | N38: =ROUND($H38*0.8%,2) -> 170.02 | S38: =ROUND(I38*8%,0) -> 1994 | T38: =ROUND(SUM(J38:S38),2) -> 7392.26 | U38: =ROUND($H38*8%,2) -> 1700.24 | V38: =ROUND($H38*2%,2) -> 425.06 | W38: =ROUND($H38*0.5%,2) -> 106.27 | Z38: 5 | AA38: =S38 -> 1994 | AB38: =ROUND(SUM(U38:AA38),2) -> 4230.57 | AC38: =VLOOKUP(AM:AM,工资明细!E:AP,38,0) -> 5065.42 | AD38: =VLOOKUP(AM:AM,工资明细!E:AH,30,0) -> 5198.29 | AH38: =ROUND(G38+T38+AB38+AD38+AF38+AG38+AE38,2) -> 17416.12 | AI38: =ROUND(AH38*(1/(1-0.78%)-1),2) -> 136.91 | AJ38: =ROUND(SUM(AH38:AI38)*6%,2) -> 1053.18 | AK38: =ROUND(SUM(AH38:AJ38),2) -> 18606.21 | AM38: 340823198402105888 | AN38: 张家港市 | AO38: 上海合杰 | AP38: =U38 -> 1700.24 | AQ38: =V38+Z38 -> 430.06 | AR38: =W38 -> 106.27 | AS38: =AA38 -> 1994
A39: 31 | B39: 赵徐 | C39: MNCN00478 | D39: 202606 | E39: 43690 | G39: 595 | H39: 24619 | I39: 26520 | J39: =ROUND($H39*16%,2) -> 3939.04 | K39: =ROUND($H39*7%,2) -> 1723.33 | L39: =ROUND($H39*0.5%,2) -> 123.1 | M39: =ROUND($H39*1.1%,2) -> 270.81 | N39: =ROUND($H39*0.8%,2) -> 196.95 | S39: =ROUND(I39*8%,0) -> 2122 | T39: =ROUND(SUM(J39:S39),2) -> 8375.23 | U39: =ROUND($H39*8%,2) -> 1969.52 | V39: =ROUND($H39*2%,2) -> 492.38 | W39: =ROUND($H39*0.5%,2) -> 123.1 | Z39: 5 | AA39: =S39 -> 2122 | AB39: =ROUND(SUM(U39:AA39),2) -> 4712 | AC39: =VLOOKUP(AM:AM,工资明细!E:AP,38,0) -> 5900.4 | AD39: =VLOOKUP(AM:AM,工资明细!E:AH,30,0) -> 6524 | AH39: =ROUND(G39+T39+AB39+AD39+AF39+AG39+AE39,2) -> 20206.23 | AI39: =ROUND(AH39*(1/(1-0.78%)-1),2) -> 158.85 | AJ39: =ROUND(SUM(AH39:AI39)*6%,2) -> 1221.9 | AK39: =ROUND(SUM(AH39:AJ39),2) -> 21586.98 | AM39: 340421198706282854 | AN39: 张家港市 | AO39: 上海合杰 | AP39: =U39 -> 1969.52 | AQ39: =V39+Z39 -> 497.38 | AR39: =W39 -> 123.1 | AS39: =AA39 -> 2122
A40: 32 | B40: 郭思玉 | C40: MNCN00479 | D40: 202606 | E40: 43697 | G40: 595 | H40: 11591.63 | I40: 11277.12 | J40: =ROUND(H40*16%,2) -> 1854.66 | K40: =ROUND(H40*7%,2) -> 811.41 | L40: =ROUND(H40*0.7%,2) -> 81.14 | M40: =ROUND(H40*0.32%,2) -> 37.09 | O40: 6.4 | P40: =ROUND(H40*1.5%,2) -> 173.87 | S40: =ROUND(I40*5%,0) -> 564 | T40: =ROUND(SUM(J40:S40),2) -> 3528.57 | U40: =ROUND(H40*8%,2) -> 927.33 | V40: =ROUND(H40*2%,2) -> 231.83 | W40: =ROUND(H40*0.3%,2) -> 34.77 | Z40: 1.6 | AA40: =S40 -> 564 | AB40: =ROUND(SUM(U40:AA40),2) -> 1759.53 | AC40: =VLOOKUP(AM:AM,工资明细!E:AP,38,0) -> 7511.03 | AD40: =VLOOKUP(AM:AM,工资明细!E:AH,30,0) -> 7643.11 | AH40: =ROUND(G40+T40+AB40+AD40+AF40+AG40+AE40,2) -> 13526.21 | AI40: =ROUND(AH40*(1/(1-0.78%)-1),2) -> 106.33 | AJ40: =ROUND(SUM(AH40:AI40)*6%,2) -> 817.95 | AK40: =ROUND(SUM(AH40:AJ40),2) -> 14450.49 | AM40: 622827199610250384 | AN40: 西安市 | AO40: 合杰区域分公司 | AP40: =U40 -> 927.33 | AQ40: =V40+Z40 -> 233.43 | AR40: =W40 -> 34.77 | AS40: =AA40 -> 564
A41: 33 | B41: 葛梦影 | C41: MNCN00480 | D41: 202606 | E41: 43697 | G41: 595 | H41: 7460 | I41: 6754.8 | J41: =ROUND($H41*16%,2) -> 1193.6 | K41: =ROUND(H41*9%,2) -> 671.4 | L41: =ROUND(H41*0.5%,2) -> 37.3 | M41: =ROUND(H41*0.32%,2) -> 23.87 | P41: =ROUND(H41*(1.5%*0.9),2) -> 100.71 | S41: =ROUND(I41*7%,0) -> 473 | T41: =ROUND(SUM(J41:S41),2) -> 2499.88 | U41: =ROUND(H41*8%,2) -> 596.8 | V41: =ROUND(H41*2%,2) -> 149.2 | W41: =ROUND(H41*0.5%,2) -> 37.3 | AA41: =ROUND(I41*7%,0) -> 473 | AB41: =ROUND(SUM(U41:AA41),2) -> 1256.3 | AC41: =VLOOKUP(AM:AM,工资明细!E:AP,38,0) -> 4736.77 | AD41: =VLOOKUP(AM:AM,工资明细!E:AH,30,0) -> 4743.7 | AH41: =ROUND(G41+T41+AB41+AD41+AF41+AG41+AE41,2) -> 9094.88 | AI41: =ROUND(AH41*(1/(1-0.78%)-1),2) -> 71.5 | AJ41: =ROUND(SUM(AH41:AI41)*6%,2) -> 549.98 | AK41: =ROUND(SUM(AH41:AJ41),2) -> 9716.36 | AM41: 320283199108137568 | AN41: 上海市 | AO41: 上海合杰 | AP41: =U41 -> 596.8 | AQ41: =V41+Z41 -> 149.2 | AR41: =W41 -> 37.3 | AS41: =AA41 -> 473
A42: 34 | B42: 聂贝 | C42: MNCN00488 | D42: 202606 | E42: 43728 | G42: 595 | H42: 9746.5 | I42: 9746.5 | J42: =ROUND($H42*16%,2) -> 1559.44 | K42: =ROUNDDOWN(H42*9%,2) -> 877.18 | L42: =ROUND(H42*0.5%,2) -> 48.73 | M42: =ROUND(H42*0.32%,2) -> 31.19 | P42: =ROUND(H42*(1.5%*0.9),2) -> 131.58 | S42: =ROUND(I42*7%,0) -> 682 | T42: =ROUND(SUM(J42:S42),2) -> 3330.12 | U42: =ROUND(H42*8%,2) -> 779.72 | V42: =ROUND(H42*2%,2) -> 194.93 | W42: =ROUND(H42*0.5%,2) -> 48.73 | AA42: =ROUND(I42*7%,0) -> 682 | AB42: =ROUND(SUM(U42:AA42),2) -> 1705.38 | AC42: =VLOOKUP(AM:AM,工资明细!E:AP,38,0) -> 3952.93 | AD42: =VLOOKUP(AM:AM,工资明细!E:AH,30,0) -> 3952.93 | AH42: =ROUND(G42+T42+AB42+AD42+AF42+AG42+AE42,2) -> 9583.43 | AI42: =ROUND(AH42*(1/(1-0.78%)-1),2) -> 75.34 | AJ42: =ROUND(SUM(AH42:AI42)*6%,2) -> 579.53 | AK42: =ROUND(SUM(AH42:AJ42),2) -> 10238.3 | AM42: 430221199003075221 | AN42: 上海市 | AO42: 上海合杰 | AP42: =U42 -> 779.72 | AQ42: =V42+Z42 -> 194.93 | AR42: =W42 -> 48.73 | AS42: =AA42 -> 682
A43: 35 | B43: 黄炳金 | C43: MNCN00490 | D43: 202606 | E43: 43747 | G43: 595 | H43: 8182 | I43: 8182 | J43: =ROUND($H43*16%,2) -> 1309.12 | K43: =ROUND($H43*5.5%,2) -> 450.01 | L43: =ROUND($H43*0.8%,2) -> 65.46 | M43: =ROUND($H43*0.4%,2) -> 32.73 | S43: =ROUND(I43*5%,0) -> 409 | T43: =ROUND(SUM(J43:S43),2) -> 2266.32 | U43: =ROUND($H43*8%,2) -> 654.56 | V43: =ROUND(H43*2%,2) -> 163.64 | W43: =ROUND($H43*0.2%,2) -> 16.36 | AA43: =S43 -> 409 | AB43: =ROUND(SUM(U43:AA43),2) -> 1243.56 | AC43: =VLOOKUP(AM:AM,工资明细!E:AP,38,0) -> 5088.34 | AD43: =VLOOKUP(AM:AM,工资明细!E:AH,30,0) -> 5088.34 | AH43: =ROUND(G43+T43+AB43+AD43+AF43+AG43+AE43,2) -> 9193.22 | AI43: =ROUND(AH43*(1/(1-0.78%)-1),2) -> 72.27 | AJ43: =ROUND(SUM(AH43:AI43)*6%,2) -> 555.93 | AK43: =ROUND(SUM(AH43:AJ43),2) -> 9821.42 | AM43: 45042119951105101x | AN43: 佛山市 | AO43: 上海合杰 | AP43: =U43 -> 654.56 | AQ43: =V43+Z43 -> 163.64 | AR43: =W43 -> 16.36 | AS43: =AA43 -> 409
A44: 36 | B44: 张露文 | C44: MNCN00491 | D44: 202606 | E44: 43751 | G44: 595 | H44: 7788 | I44: 7788 | J44: =ROUND($H44*16%,2) -> 1246.08 | K44: =ROUND($H44*5.5%,2) -> 428.34 | L44: =ROUND($H44*0.8%,2) -> 62.3 | M44: =ROUND($H44*0.4%,2) -> 31.15 | S44: =ROUND(I44*5%,0) -> 389 | T44: =ROUND(SUM(J44:S44),2) -> 2156.87 | U44: =ROUND($H44*8%,2) -> 623.04 | V44: =ROUND(H44*2%,2) -> 155.76 | W44: =ROUND($H44*0.2%,2) -> 15.58 | AA44: =S44 -> 389 | AB44: =ROUND(SUM(U44:AA44),2) -> 1183.38 | AC44: =VLOOKUP(AM:AM,工资明细!E:AP,38,0) -> 4513.31 | AD44: =VLOOKUP(AM:AM,工资明细!E:AH,30,0) -> 4520.07 | AH44: =ROUND(G44+T44+AB44+AD44+AF44+AG44+AE44,2) -> 8455.32 | AI44: =ROUND(AH44*(1/(1-0.78%)-1),2) -> 66.47 | AJ44: =ROUND(SUM(AH44:AI44)*6%,2) -> 511.31 | AK44: =ROUND(SUM(AH44:AJ44),2) -> 9033.1 | AM44: 441283199312171024 | AN44: 佛山市 | AO44: 上海合杰 | AP44: =U44 -> 623.04 | AQ44: =V44+Z44 -> 155.76 | AR44: =W44 -> 15.58 | AS44: =AA44 -> 389
A45: 37 | B45: 林辉 | C45: MNCN00515 | D45: 202606 | E45: 44004 | G45: 595 | H45: 13515.9 | I45: 13515.9 | J45: =ROUND($H45*16%,2) -> 2162.54 | K45: =ROUND(H45*9%,2) -> 1216.43 | L45: =ROUND(H45*0.5%,2) -> 67.58 | M45: =ROUND(H45*0.32%,2) -> 43.25 | P45: =ROUND(H45*(1.5%*0.9),2) -> 182.46 | S45: =ROUND(I45*7%,0) -> 946 | T45: =ROUND(SUM(J45:S45),2) -> 4618.26 | U45: =ROUND(H45*8%,2) -> 1081.27 | V45: =ROUND(H45*2%,2) -> 270.32 | W45: =ROUND(H45*0.5%,2) -> 67.58 | AA45: =ROUND(I45*7%,0) -> 946 | AB45: =ROUND(SUM(U45:AA45),2) -> 2365.17 | AC45: =VLOOKUP(AM:AM,工资明细!E:AP,38,0) -> 12758.54 | AD45: =VLOOKUP(AM:AM,工资明细!E:AH,30,0) -> 12947.94 | AH45: =ROUND(G45+T45+AB45+AD45+AF45+AG45+AE45,2) -> 20526.37 | AI45: =ROUND(AH45*(1/(1-0.78%)-1),2) -> 161.36 | AJ45: =ROUND(SUM(AH45:AI45)*6%,2) -> 1241.26 | AK45: =ROUND(SUM(AH45:AJ45),2) -> 21928.99 | AM45: 310115197803192515 | AN45: 上海市 | AO45: 上海合杰 | AP45: =U45 -> 1081.27 | AQ45: =V45+Z45 -> 270.32 | AR45: =W45 -> 67.58 | AS45: =AA45 -> 946
A46: 38 | B46: 刘丽微 | C46: MNCN00517 | D46: 202606 | E46: 44004 | G46: 595 | H46: 8688.16 | I46: 8628 | J46: =ROUND($H46*16%,2) -> 1390.11 | K46: =ROUND($H46*9%,2) -> 781.93 | L46: =ROUND(H46*0.5%,2) -> 43.44 | M46: =ROUND(H46*0.9%,2) -> 78.19 | O46: =ROUND(H46*0.2%,2) -> 17.38 | S46: =ROUND(I46*7%,2) -> 603.96 | T46: =ROUND(SUM(J46:S46),2) -> 2915.01 | U46: =ROUND($H46*8%,2) -> 695.05 | V46: =ROUND($H46*2%,2) -> 173.76 | W46: =ROUND(H46*0.5%,2) -> 43.44 | Z46: =ROUND(H46*0.1%,2) -> 8.69 | AA46: =S46 -> 603.96 | AB46: =ROUND(SUM(U46:AA46),2) -> 1524.9 | AC46: =VLOOKUP(AM:AM,工资明细!E:AP,38,0) -> 5118.54 | AD46: =VLOOKUP(AM:AM,工资明细!E:AH,30,0) -> 5160.28 | AH46: =ROUND(G46+T46+AB46+AD46+AF46+AG46+AE46,2) -> 10195.19 | AI46: =ROUND(AH46*(1/(1-0.78%)-1),2) -> 80.15 | AJ46: =ROUND(SUM(AH46:AI46)*6%,2) -> 616.52 | AK46: =ROUND(SUM(AH46:AJ46),2) -> 10891.86 | AM46: 210323198908074066 | AN46: 大连市 | AO46: 上海合杰 | AP46: =U46 -> 695.05 | AQ46: =V46+Z46 -> 182.45 | AR46: =W46 -> 43.44 | AS46: =AA46 -> 603.96
A47: 39 | B47: 姚远 | C47: MNCN00521 | D47: 202606 | E47: 44013 | G47: 595 | H47: 12147.33 | I47: 11901 | J47: =ROUND($H47*16%,2) -> 1943.57 | K47: =ROUND($H47*9%,2) -> 1093.26 | L47: =ROUND(H47*0.5%,2) -> 60.74 | M47: =ROUND(H47*0.9%,2) -> 109.33 | O47: =ROUND(H47*0.2%,2) -> 24.29 | Q47: 102.23 | S47: =ROUND(I47*7%,2) -> 833.07 | T47: =ROUND(SUM(J47:S47),2) -> 4166.49 | U47: =ROUND(H47*8%,2) -> 971.79 | V47: =ROUND($H47*2%,2) -> 242.95 | W47: =ROUND(H47*0.5%,2) -> 60.74 | Z47: =ROUND(H47*0.1%,2) -> 12.15 | AA47: =S47 -> 833.07 | AB47: =ROUND(SUM(U47:AA47),2) -> 2120.7 | AC47: =VLOOKUP(AM:AM,工资明细!E:AP,38,0) -> 10270.78 | AD47: =VLOOKUP(AM:AM,工资明细!E:AH,30,0) -> 10499.39 | AH47: =ROUND(G47+T47+AB47+AD47+AF47+AG47+AE47,2) -> 17381.58 | AI47: =ROUND(AH47*(1/(1-0.78%)-1),2) -> 136.64 | AJ47: =ROUND(SUM(AH47:AI47)*6%,2) -> 1051.09 | AK47: =ROUND(SUM(AH47:AJ47),2) -> 18569.31 | AM47: 211302198202250020 | AN47: 大连市 | AO47: 上海合杰 | AP47: =U47 -> 971.79 | AQ47: =V47+Z47 -> 255.1 | AR47: =W47 -> 60.74 | AS47: =AA47 -> 833.07
A48: 40 | B48: 赵凌云 | C48: MNCN00536 | D48: 202606 | E48: 44130 | G48: 595 | H48: 8181 | I48: 8803 | J48: =ROUND($H48*16%,2) -> 1308.96 | K48: =ROUND($H48*8.5%,2) -> 695.39 | L48: =ROUND($H48*0.5%,2) -> 40.91 | M48: =ROUND($H48*0.6%,2) -> 49.09 | O48: =ROUND(H48*1.5%,2) -> 122.72 | P48: =ROUND(H48*1.5%,2) -> 122.72 | S48: =ROUND(I48*5%,0) -> 440 | T48: =ROUND(SUM(J48:S48),2) -> 2779.79 | U48: =ROUND($H48*8%,2) -> 654.48 | V48: =ROUND($H48*2%,2) -> 163.62 | W48: =ROUND($H48*0.5%,2) -> 40.91 | Z48: 5 | AA48: =S48 -> 440 | AB48: =ROUND(SUM(U48:AA48),2) -> 1304.01 | AC48: =VLOOKUP(AM:AM,工资明细!E:AP,38,0) -> 3576.63 | AD48: =VLOOKUP(AM:AM,工资明细!E:AH,30,0) -> 3576.63 | AH48: =ROUND(G48+T48+AB48+AD48+AF48+AG48+AE48,2) -> 8255.43 | AI48: =ROUND(AH48*(1/(1-0.78%)-1),2) -> 64.9 | AJ48: =ROUND(SUM(AH48:AI48)*6%,2) -> 499.22 | AK48: =ROUND(SUM(AH48:AJ48),2) -> 8819.55 | AM48: 511321198801061483 | AN48: 重庆市 | AO48: 合杰区域分公司 | AP48: =U48 -> 654.48 | AQ48: =V48+Z48 -> 168.62 | AR48: =W48 -> 40.91 | AS48: =AA48 -> 440
A49: 41 | B49: 陈世益 | C49: MNCN00537 | D49: 202606 | E49: 44130 | G49: 595 | H49: 9812 | I49: 11224 | J49: =ROUND($H49*16%,2) -> 1569.92 | K49: =ROUND($H49*8.5%,2) -> 834.02 | L49: =ROUND($H49*0.5%,2) -> 49.06 | M49: =ROUND($H49*0.6%,2) -> 58.87 | O49: =ROUND(H49*1.5%,2) -> 147.18 | P49: =ROUND(H49*1.5%,2) -> 147.18 | S49: =ROUND(I49*5%,0) -> 561 | T49: =ROUND(SUM(J49:S49),2) -> 3367.23 | U49: =ROUND($H49*8%,2) -> 784.96 | V49: =ROUND($H49*2%,2) -> 196.24 | W49: =ROUND($H49*0.5%,2) -> 49.06 | Z49: 5 | AA49: =S49 -> 561 | AB49: =ROUND(SUM(U49:AA49),2) -> 1596.26 | AC49: =VLOOKUP(AM:AM,工资明细!E:AP,38,0) -> 4618.27 | AD49: =VLOOKUP(AM:AM,工资明细!E:AH,30,0) -> 4655.83 | AH49: =ROUND(G49+T49+AB49+AD49+AF49+AG49+AE49,2) -> 10214.32 | AI49: =ROUND(AH49*(1/(1-0.78%)-1),2) -> 80.3 | AJ49: =ROUND(SUM(AH49:AI49)*6%,2) -> 617.68 | AK49: =ROUND(SUM(AH49:AJ49),2) -> 10912.3 | AM49: 500224199208282854 | AN49: 重庆市 | AO49: 合杰区域分公司 | AP49: =U49 -> 784.96 | AQ49: =V49+Z49 -> 201.24 | AR49: =W49 -> 49.06 | AS49: =AA49 -> 561
A50: 42 | B50: 罗丽丽 | C50: MNCN00541 | D50: 202606 | E50: 44197 | G50: 595 | H50: 5899 | I50: 6149 | J50: =ROUND($H50*16%,2) -> 943.84 | K50: =ROUND($H50*8.5%,2) -> 501.42 | L50: =ROUND($H50*0.5%,2) -> 29.5 | M50: =ROUND($H50*0.6%,2) -> 35.39 | O50: =ROUND(H50*1.5%,2) -> 88.49 | P50: =ROUND(H50*1.5%,2) -> 88.49 | S50: =ROUND(I50*5%,0) -> 307 | T50: =ROUND(SUM(J50:S50),2) -> 1994.13 | U50: =ROUND($H50*8%,2) -> 471.92 | V50: =ROUND($H50*2%,2) -> 117.98 | W50: =ROUND($H50*0.5%,2) -> 29.5 | Z50: 5 | AA50: =S50 -> 307 | AB50: =ROUND(SUM(U50:AA50),2) -> 931.4 | AC50: =VLOOKUP(AM:AM,工资明细!E:AP,38,0) -> 5133.93 | AD50: =VLOOKUP(AM:AM,工资明细!E:AH,30,0) -> 5133.93 | AH50: =ROUND(G50+T50+AB50+AD50+AF50+AG50+AE50,2) -> 8654.46 | AI50: =ROUND(AH50*(1/(1-0.78%)-1),2) -> 68.04 | AJ50: =ROUND(SUM(AH50:AI50)*6%,2) -> 523.35 | AK50: =ROUND(SUM(AH50:AJ50),2) -> 9245.85 | AM50: 513023198808152183 | AN50: 重庆市 | AO50: 合杰区域分公司 | AP50: =U50 -> 471.92 | AQ50: =V50+Z50 -> 122.98 | AR50: =W50 -> 29.5 | AS50: =AA50 -> 307
A51: 43 | B51: 汤黎 | C51: MNCN00542 | D51: 202606 | E51: 44197 | G51: 595 | H51: 5963 | I51: 7610 | J51: =ROUND($H51*16%,2) -> 954.08 | K51: =ROUND($H51*8.5%,2) -> 506.86 | L51: =ROUND($H51*0.5%,2) -> 29.82 | M51: =ROUND($H51*0.6%,2) -> 35.78 | O51: =ROUND(H51*1.5%,2) -> 89.45 | P51: =ROUND(H51*1.5%,2) -> 89.45 | S51: =ROUND(I51*5%,0) -> 381 | T51: =ROUND(SUM(J51:S51),2) -> 2086.44 | U51: =ROUND($H51*8%,2) -> 477.04 | V51: =ROUND($H51*2%,2) -> 119.26 | W51: =ROUND($H51*0.5%,2) -> 29.82 | Z51: 5 | AA51: =S51 -> 381 | AB51: =ROUND(SUM(U51:AA51),2) -> 1012.12 | AC51: =VLOOKUP(AM:AM,工资明细!E:AP,38,0) -> 4070.79 | AD51: =VLOOKUP(AM:AM,工资明细!E:AH,30,0) -> 4070.79 | AH51: =ROUND(G51+T51+AB51+AD51+AF51+AG51+AE51,2) -> 7764.35 | AI51: =ROUND(AH51*(1/(1-0.78%)-1),2) -> 61.04 | AJ51: =ROUND(SUM(AH51:AI51)*6%,2) -> 469.52 | AK51: =ROUND(SUM(AH51:AJ51),2) -> 8294.91 | AM51: 513001198108140220 | AN51: 重庆市 | AO51: 合杰区域分公司 | AP51: =U51 -> 477.04 | AQ51: =V51+Z51 -> 124.26 | AR51: =W51 -> 29.82 | AS51: =AA51 -> 381
A52: 44 | B52: 王玉婷 | C52: MNCN00547 | D52: 202606 | E52: 44262 | G52: 595 | H52: 7776.49 | I52: 7602 | J52: =ROUND($H52*16%,2) -> 1244.24 | K52: =ROUND($H52*9%,2) -> 699.88 | L52: =ROUND(H52*0.5%,2) -> 38.88 | M52: =ROUND(H52*0.9%,2) -> 69.99 | O52: =ROUND(H52*0.2%,2) -> 15.55 | S52: =ROUND(I52*7%,2) -> 532.14 | T52: =ROUND(SUM(J52:S52),2) -> 2600.68 | U52: =ROUND(H52*8%,2) -> 622.12 | V52: =ROUND($H52*2%,2) -> 155.53 | W52: =ROUND(H52*0.5%,2) -> 38.88 | Z52: =ROUND(H52*0.1%,2) -> 7.78 | AA52: =S52 -> 532.14 | AB52: =ROUND(SUM(U52:AA52),2) -> 1356.45 | AC52: =VLOOKUP(AM:AM,工资明细!E:AP,38,0) -> 6152.75 | AD52: =VLOOKUP(AM:AM,工资明细!E:AH,30,0) -> 6152.75 | AH52: =ROUND(G52+T52+AB52+AD52+AF52+AG52+AE52,2) -> 10704.88 | AI52: =ROUND(AH52*(1/(1-0.78%)-1),2) -> 84.15 | AJ52: =ROUND(SUM(AH52:AI52)*6%,2) -> 647.34 | AK52: =ROUND(SUM(AH52:AJ52),2) -> 11436.37 | AM52: 210282198711178747 | AN52: 大连市 | AO52: 上海合杰 | AP52: =U52 -> 622.12 | AQ52: =V52+Z52 -> 163.31 | AR52: =W52 -> 38.88 | AS52: =AA52 -> 532.14
A53: 45 | B53: 李思帆 | C53: MNCN00559 | D53: 202606 | E53: 44333 | G53: 595 | H53: 17696.4 | I53: 17696.4 | J53: =ROUND($H53*16%,2) -> 2831.42 | K53: =ROUNDDOWN(H53*9%,2) -> 1592.67 | L53: =ROUND(H53*0.5%,2) -> 88.48 | M53: =ROUND(H53*0.32%,2) -> 56.63 | P53: =ROUND(H53*(1.5%*0.9),2) -> 238.9 | S53: =ROUND(I53*7%,0) -> 1239 | T53: =ROUND(SUM(J53:S53),2) -> 6047.1 | U53: =ROUND(H53*8%,2) -> 1415.71 | V53: =ROUND(H53*2%,2) -> 353.93 | W53: =ROUND(H53*0.5%,2) -> 88.48 | AA53: =ROUND(I53*7%,0) -> 1239 | AB53: =ROUND(SUM(U53:AA53),2) -> 3097.12 | AC53: =VLOOKUP(AM:AM,工资明细!E:AP,38,0) -> 5052.88 | AD53: =VLOOKUP(AM:AM,工资明细!E:AH,30,0) -> 5402.88 | AH53: =ROUND(G53+T53+AB53+AD53+AF53+AG53+AE53,2) -> 15142.1 | AI53: =ROUND(AH53*(1/(1-0.78%)-1),2) -> 119.04 | AJ53: =ROUND(SUM(AH53:AI53)*6%,2) -> 915.67 | AK53: =ROUND(SUM(AH53:AJ53),2) -> 16176.81 | AM53: 411503199709176324 | AN53: 上海市 | AO53: 上海合杰 | AP53: =U53 -> 1415.71 | AQ53: =V53+Z53 -> 353.93 | AR53: =W53 -> 88.48 | AS53: =AA53 -> 1239
A54: 46 | B54: 刘培培 | C54: MNCN00564 | D54: 202606 | E54: 44351 | G54: 595 | H54: 9418.6 | I54: 9418.6 | J54: =ROUND($H54*16%,2) -> 1506.98 | K54: =ROUND(H54*9%,2) -> 847.67 | L54: =ROUND(H54*0.5%,2) -> 47.09 | M54: =ROUND(H54*0.32%,2) -> 30.14 | P54: =ROUND(H54*(1.5%*0.9),2) -> 127.15 | S54: =ROUND(I54*7%,0) -> 659 | T54: =ROUND(SUM(J54:S54),2) -> 3218.03 | U54: =ROUND(H54*8%,2) -> 753.49 | V54: =ROUND(H54*2%,2) -> 188.37 | W54: =ROUND(H54*0.5%,2) -> 47.09 | AA54: =ROUND(I54*7%,0) -> 659 | AB54: =ROUND(SUM(U54:AA54),2) -> 1647.95 | AC54: =VLOOKUP(AM:AM,工资明细!E:AP,38,0) -> 4094.86 | AD54: =VLOOKUP(AM:AM,工资明细!E:AH,30,0) -> 4094.86 | AH54: =ROUND(G54+T54+AB54+AD54+AF54+AG54+AE54,2) -> 9555.84 | AI54: =ROUND(AH54*(1/(1-0.78%)-1),2) -> 75.12 | AJ54: =ROUND(SUM(AH54:AI54)*6%,2) -> 577.86 | AK54: =ROUND(SUM(AH54:AJ54),2) -> 10208.82 | AM54: 320623198910194368 | AN54: 上海市 | AO54: 上海合杰 | AP54: =U54 -> 753.49 | AQ54: =V54+Z54 -> 188.37 | AR54: =W54 -> 47.09 | AS54: =AA54 -> 659
A55: 47 | B55: 黄蕾 | C55: MNCN00567 | D55: 202606 | E55: 44350 | G55: 595 | H55: 9714.9 | I55: 9714.9 | J55: =ROUND($H55*16%,2) -> 1554.38 | K55: =ROUND(H55*9%,2) -> 874.34 | L55: =ROUND(H55*0.5%,2) -> 48.57 | M55: =ROUND(H55*0.32%,2) -> 31.09 | P55: =ROUND(H55*(1.5%*0.9),2) -> 131.15 | S55: =ROUND(I55*7%,0) -> 680 | T55: =ROUND(SUM(J55:S55),2) -> 3319.53 | U55: =ROUND(H55*8%,2) -> 777.19 | V55: =ROUND(H55*2%,2) -> 194.3 | W55: =ROUND(H55*0.5%,2) -> 48.57 | AA55: =ROUND(I55*7%,0) -> 680 | AB55: =ROUND(SUM(U55:AA55),2) -> 1700.06 | AC55: =VLOOKUP(AM:AM,工资明细!E:AP,38,0) -> 5359.05 | AD55: =VLOOKUP(AM:AM,工资明细!E:AH,30,0) -> 5359.05 | AH55: =ROUND(G55+T55+AB55+AD55+AF55+AG55+AE55,2) -> 10973.64 | AI55: =ROUND(AH55*(1/(1-0.78%)-1),2) -> 86.27 | AJ55: =ROUND(SUM(AH55:AI55)*6%,2) -> 663.59 | AK55: =ROUND(SUM(AH55:AJ55),2) -> 11723.5 | AM55: 310108197808254048 | AN55: 上海市 | AO55: 上海合杰 | AP55: =U55 -> 777.19 | AQ55: =V55+Z55 -> 194.3 | AR55: =W55 -> 48.57 | AS55: =AA55 -> 680
A56: 48 | B56: 张陆敏 | C56: MNCN00576 | D56: 202606 | E56: 44378 | G56: 595 | H56: 7812.2 | I56: 7812.2 | J56: =ROUND($H56*16%,2) -> 1249.95 | K56: =ROUND(H56*9%,2) -> 703.1 | L56: =ROUND(H56*0.5%,2) -> 39.06 | M56: =ROUND(H56*0.32%,2) -> 25 | P56: =ROUND(H56*(1.5%*0.9),2) -> 105.46 | S56: =ROUND(I56*7%,0) -> 547 | T56: =ROUND(SUM(J56:S56),2) -> 2669.57 | U56: =ROUND(H56*8%,2) -> 624.98 | V56: =ROUND(H56*2%,2) -> 156.24 | W56: =ROUND(H56*0.5%,2) -> 39.06 | AA56: =ROUND(I56*7%,0) -> 547 | AB56: =ROUND(SUM(U56:AA56),2) -> 1367.28 | AC56: =VLOOKUP(AM:AM,工资明细!E:AP,38,0) -> 7103.01 | AD56: =VLOOKUP(AM:AM,工资明细!E:AH,30,0) -> 7137.03 | AH56: =ROUND(G56+T56+AB56+AD56+AF56+AG56+AE56,2) -> 11768.88 | AI56: =ROUND(AH56*(1/(1-0.78%)-1),2) -> 92.52 | AJ56: =ROUND(SUM(AH56:AI56)*6%,2) -> 711.68 | AK56: =ROUND(SUM(AH56:AJ56),2) -> 12573.08 | AM56: 31011019830528513x | AN56: 上海市 | AO56: 上海合杰 | AP56: =U56 -> 624.98 | AQ56: =V56+Z56 -> 156.24 | AR56: =W56 -> 39.06 | AS56: =AA56 -> 547
A57: 49 | B57: 黄欢 | C57: MNCN00577 | D57: 202606 | E57: 44383 | G57: 595 | H57: 13599.14 | I57: 12462.84 | J57: =ROUND($H57*16%,2) -> 2175.86 | K57: =ROUND($H57*9.5%,2) -> 1291.92 | L57: =ROUND(H57*0.5%,2) -> 68 | M57: =ROUND(H57*0.2%,2) -> 27.2 | P57: =ROUND(H57*1.5%,2) -> 203.99 | S57: 1496 | T57: =ROUND(SUM(J57:S57),2) -> 5262.97 | U57: =ROUND($H57*8%,2) -> 1087.93 | V57: =ROUND($H57*2%,2) -> 271.98 | W57: =ROUND($H57*0.5%,2) -> 68 | AA57: =S57 -> 1496 | AB57: =ROUND(SUM(U57:AA57),2) -> 2923.91 | AC57: =VLOOKUP(AM:AM,工资明细!E:AP,38,0) -> 7902.4 | AD57: =VLOOKUP(AM:AM,工资明细!E:AH,30,0) -> 8549.77 | AH57: =ROUND(G57+T57+AB57+AD57+AF57+AG57+AE57,2) -> 17331.65 | AI57: =ROUND(AH57*(1/(1-0.78%)-1),2) -> 136.25 | AJ57: =ROUND(SUM(AH57:AI57)*6%,2) -> 1048.07 | AK57: =ROUND(SUM(AH57:AJ57),2) -> 18515.97 | AM57: 34012319851229364X | AN57: 杭州市 | AO57: 合杰区域分公司 | AP57: =U57 -> 1087.93 | AQ57: =V57+Z57 -> 271.98 | AR57: =W57 -> 68 | AS57: =AA57 -> 1496
A58: 50 | B58: 张春彩 | C58: MNCN00578 | D58: 202606 | E58: 44383 | G58: 595 | H58: 13849.46 | I58: 11488.18 | J58: =ROUND($H58*16%,2) -> 2215.91 | K58: =ROUND($H58*9.5%,2) -> 1315.7 | L58: =ROUND(H58*0.5%,2) -> 69.25 | M58: =ROUND(H58*0.2%,2) -> 27.7 | P58: =ROUND(H58*1.5%,2) -> 207.74 | S58: 1379 | T58: =ROUND(SUM(J58:S58),2) -> 5215.3 | U58: =ROUND($H58*8%,2) -> 1107.96 | V58: =ROUND($H58*2%,2) -> 276.99 | W58: =ROUND($H58*0.5%,2) -> 69.25 | AA58: =S58 -> 1379 | AB58: =ROUND(SUM(U58:AA58),2) -> 2833.2 | AC58: =VLOOKUP(AM:AM,工资明细!E:AP,38,0) -> 5403.2 | AD58: =VLOOKUP(AM:AM,工资明细!E:AH,30,0) -> 5698.16 | AH58: =ROUND(G58+T58+AB58+AD58+AF58+AG58+AE58,2) -> 14341.66 | AI58: =ROUND(AH58*(1/(1-0.78%)-1),2) -> 112.74 | AJ58: =ROUND(SUM(AH58:AI58)*6%,2) -> 867.26 | AK58: =ROUND(SUM(AH58:AJ58),2) -> 15321.66 | AM58: 341021198002026720 | AN58: 杭州市 | AO58: 合杰区域分公司 | AP58: =U58 -> 1107.96 | AQ58: =V58+Z58 -> 276.99 | AR58: =W58 -> 69.25 | AS58: =AA58 -> 1379
A59: 51 | B59: 苏敏 | C59: MNCN00580 | D59: 202606 | E59: 44397 | G59: 595 | H59: 15630.4 | I59: 15630.4 | J59: =ROUND($H59*16%,2) -> 2500.86 | K59: =ROUNDDOWN(H59*9%,2) -> 1406.73 | L59: =ROUND(H59*0.5%,2) -> 78.15 | M59: =ROUND(H59*0.32%,2) -> 50.02 | P59: =ROUND(H59*(1.5%*0.9),2) -> 211.01 | S59: =ROUND(I59*7%,0) -> 1094 | T59: =ROUND(SUM(J59:S59),2) -> 5340.77 | U59: =ROUND(H59*8%,2) -> 1250.43 | V59: =ROUND(H59*2%,2) -> 312.61 | W59: =ROUND(H59*0.5%,2) -> 78.15 | AA59: =ROUND(I59*7%,0) -> 1094 | AB59: =ROUND(SUM(U59:AA59),2) -> 2735.19 | AC59: =VLOOKUP(AM:AM,工资明细!E:AP,38,0) -> 5585.5 | AD59: =VLOOKUP(AM:AM,工资明细!E:AH,30,0) -> 5954.47 | AH59: =ROUND(G59+T59+AB59+AD59+AF59+AG59+AE59,2) -> 14625.43 | AI59: =ROUND(AH59*(1/(1-0.78%)-1),2) -> 114.98 | AJ59: =ROUND(SUM(AH59:AI59)*6%,2) -> 884.42 | AK59: =ROUND(SUM(AH59:AJ59),2) -> 15624.83 | AM59: 532123200004070025 | AN59: 上海市 | AO59: 上海合杰 | AP59: =U59 -> 1250.43 | AQ59: =V59+Z59 -> 312.61 | AR59: =W59 -> 78.15 | AS59: =AA59 -> 1094
A60: 52 | B60: 杨吕明 | C60: MNCN00590 | D60: 202606 | E60: 44441 | G60: 595 | H60: 8964.85 | I60: 8965 | J60: =ROUND($H60*16%,2) -> 1434.38 | K60: =ROUND($H60*6.4%,2) -> 573.75 | L60: =ROUND(H60*0.5%,2) -> 44.82 | M60: =ROUND(H60*0.4%,2) -> 35.86 | P60: =ROUND(H60*1.5%,2) -> 134.47 | S60: =ROUND(I60*5%,0) -> 448 | T60: =ROUND(SUM(J60:S60),2) -> 2671.28 | U60: =ROUND(H60*8%,2) -> 717.19 | V60: =ROUND(H60*2%,2) -> 179.3 | W60: =ROUND(H60*0.5%,2) -> 44.82 | AA60: =S60 -> 448 | AB60: =ROUND(SUM(U60:AA60),2) -> 1389.31 | AC60: =VLOOKUP(AM:AM,工资明细!E:AP,38,0) -> 7228.48 | AD60: =VLOOKUP(AM:AM,工资明细!E:AH,30,0) -> 7340.37 | AH60: =ROUND(G60+T60+AB60+AD60+AF60+AG60+AE60,2) -> 11995.96 | AI60: =ROUND(AH60*(1/(1-0.78%)-1),2) -> 94.3 | AJ60: =ROUND(SUM(AH60:AI60)*6%,2) -> 725.42 | AK60: =ROUND(SUM(AH60:AJ60),2) -> 12815.68 | AM60: 340825198510252319 | AN60: 合肥市 | AO60: 合杰区域分公司 | AP60: =U60 -> 717.19 | AQ60: =V60+Z60 -> 179.3 | AR60: =W60 -> 44.82 | AS60: =AA60 -> 448
A61: 53 | B61: 胡敏 | C61: MNCN00595 | D61: 202606 | E61: 44453 | G61: 595 | H61: 14729.3 | I61: 14729.3 | J61: =ROUND($H61*16%,2) -> 2356.69 | K61: =ROUND(H61*9%,2) -> 1325.64 | L61: =ROUND(H61*0.5%,2) -> 73.65 | M61: =ROUND(H61*0.32%,2) -> 47.13 | P61: =ROUND(H61*(1.5%*0.9),2) -> 198.85 | S61: =ROUND(I61*7%,0) -> 1031 | T61: =ROUND(SUM(J61:S61),2) -> 5032.96 | U61: =ROUND(H61*8%,2) -> 1178.34 | V61: =ROUND(H61*2%,2) -> 294.59 | W61: =ROUND(H61*0.5%,2) -> 73.65 | AA61: =ROUND(I61*7%,0) -> 1031 | AB61: =ROUND(SUM(U61:AA61),2) -> 2577.58 | AC61: =VLOOKUP(AM:AM,工资明细!E:AP,38,0) -> 6822.34 | AD61: =VLOOKUP(AM:AM,工资明细!E:AH,30,0) -> 6822.34 | AH61: =ROUND(G61+T61+AB61+AD61+AF61+AG61+AE61,2) -> 15027.88 | AI61: =ROUND(AH61*(1/(1-0.78%)-1),2) -> 118.14 | AJ61: =ROUND(SUM(AH61:AI61)*6%,2) -> 908.76 | AK61: =ROUND(SUM(AH61:AJ61),2) -> 16054.78 | AM61: 310110198101283722 | AN61: 上海市 | AO61: 上海合杰 | AP61: =U61 -> 1178.34 | AQ61: =V61+Z61 -> 294.59 | AR61: =W61 -> 73.65 | AS61: =AA61 -> 1031
A62: 54 | B62: 杜文伟 | C62: MNCN00602 | D62: 202606 | E62: 44501 | G62: 595 | H62: 22320.5 | I62: 22320.5 | J62: =ROUND($H62*16%,2) -> 3571.28 | K62: =ROUNDDOWN(H62*9%,2) -> 2008.84 | L62: =ROUND(H62*0.5%,2) -> 111.6 | M62: =ROUND(H62*0.32%,2) -> 71.43 | P62: =ROUND(H62*(1.5%*0.9),2) -> 301.33 | S62: =ROUND(I62*7%,0) -> 1562 | T62: =ROUND(SUM(J62:S62),2) -> 7626.48 | U62: =ROUND(H62*8%,2) -> 1785.64 | V62: =ROUND(H62*2%,2) -> 446.41 | W62: =ROUND(H62*0.5%,2) -> 111.6 | AA62: =ROUND(I62*7%,0) -> 1562 | AB62: =ROUND(SUM(U62:AA62),2) -> 3905.65 | AC62: =VLOOKUP(AM:AM,工资明细!E:AP,38,0) -> 10723.51 | AD62: =VLOOKUP(AM:AM,工资明细!E:AH,30,0) -> 11793.41 | AH62: =ROUND(G62+T62+AB62+AD62+AF62+AG62+AE62,2) -> 23920.54 | AI62: =ROUND(AH62*(1/(1-0.78%)-1),2) -> 188.05 | AJ62: =ROUND(SUM(AH62:AI62)*6%,2) -> 1446.52 | AK62: =ROUND(SUM(AH62:AJ62),2) -> 25555.11 | AM62: 310115198212077755 | AN62: 上海市 | AO62: 上海合杰 | AP62: =U62 -> 1785.64 | AQ62: =V62+Z62 -> 446.41 | AR62: =W62 -> 111.6 | AS62: =AA62 -> 1562
A63: 55 | B63: 张燕 | C63: MNCN00603 | D63: 202606 | E63: 44504 | G63: 595 | H63: 14740.1 | I63: 14740.1 | J63: =ROUND($H63*16%,2) -> 2358.42 | K63: =ROUND(H63*9%,2) -> 1326.61 | L63: =ROUND(H63*0.5%,2) -> 73.7 | M63: =ROUND(H63*0.32%,2) -> 47.17 | P63: =ROUND(H63*(1.5%*0.9),2) -> 198.99 | S63: =ROUND(I63*7%,0) -> 1032 | T63: =ROUND(SUM(J63:S63),2) -> 5036.89 | U63: =ROUND(H63*8%,2) -> 1179.21 | V63: =ROUND(H63*2%,2) -> 294.8 | W63: =ROUND(H63*0.5%,2) -> 73.7 | AA63: =ROUND(I63*7%,0) -> 1032 | AB63: =ROUND(SUM(U63:AA63),2) -> 2579.71 | AC63: =VLOOKUP(AM:AM,工资明细!E:AP,38,0) -> 7245.09 | AD63: =VLOOKUP(AM:AM,工资明细!E:AH,30,0) -> 7245.09 | AH63: =ROUND(G63+T63+AB63+AD63+AF63+AG63+AE63,2) -> 15456.69 | AI63: =ROUND(AH63*(1/(1-0.78%)-1),2) -> 121.51 | AJ63: =ROUND(SUM(AH63:AI63)*6%,2) -> 934.69 | AK63: =ROUND(SUM(AH63:AJ63),2) -> 16512.89 | AM63: 36252519820225002x | AN63: 上海市 | AO63: 上海合杰 | AP63: =U63 -> 1179.21 | AQ63: =V63+Z63 -> 294.8 | AR63: =W63 -> 73.7 | AS63: =AA63 -> 1032
A64: 56 | B64: 李磊 | C64: MNCN00617 | D64: 202606 | E64: 44629 | G64: 595 | H64: 8842.6 | I64: 8842.6 | J64: =ROUND($H64*16%,2) -> 1414.82 | K64: =ROUND(H64*9%,2) -> 795.83 | L64: =ROUND(H64*0.5%,2) -> 44.21 | M64: =ROUND(H64*0.32%,2) -> 28.3 | P64: =ROUND(H64*(1.5%*0.9),2) -> 119.38 | S64: =ROUND(I64*7%,0) -> 619 | T64: =ROUND(SUM(J64:S64),2) -> 3021.54 | U64: =ROUND(H64*8%,2) -> 707.41 | V64: =ROUND(H64*2%,2) -> 176.85 | W64: =ROUND(H64*0.5%,2) -> 44.21 | AA64: =ROUND(I64*7%,0) -> 619 | AB64: =ROUND(SUM(U64:AA64),2) -> 1547.47 | AC64: =VLOOKUP(AM:AM,工资明细!E:AP,38,0) -> 9609.47 | AD64: =VLOOKUP(AM:AM,工资明细!E:AH,30,0) -> 10261.96 | AH64: =ROUND(G64+T64+AB64+AD64+AF64+AG64+AE64,2) -> 15425.97 | AI64: =ROUND(AH64*(1/(1-0.78%)-1),2) -> 121.27 | AJ64: =ROUND(SUM(AH64:AI64)*6%,2) -> 932.83 | AK64: =ROUND(SUM(AH64:AJ64),2) -> 16480.07 | AM64: 510322198910194715 | AN64: 上海市 | AO64: 上海合杰 | AP64: =U64 -> 707.41 | AQ64: =V64+Z64 -> 176.85 | AR64: =W64 -> 44.21 | AS64: =AA64 -> 619
A65: 57 | B65: 阳杰 | C65: MNCN00625 | D65: 202606 | E65: 44676 | G65: 595 | H65: 10609 | I65: 10609.21 | J65: =ROUND($H65*16%,2) -> 1697.44 | K65: =ROUND($H65*8.7%,2) -> 922.98 | L65: =ROUND($H65*0.7%,2) -> 74.26 | M65: =ROUND($H65*0.2%,2) -> 21.22 | P65: =ROUND(H65*1.5%,2) -> 159.14 | S65: =ROUND(I65*8%,2) -> 848.74 | T65: =ROUND(SUM(J65:S65),2) -> 3723.78 | U65: =ROUND($H65*8%,2) -> 848.72 | V65: =ROUND($H65*2%,2) -> 212.18 | W65: =ROUND($H65*0.3%,2) -> 31.83 | Z65: 7 | AA65: =S65 -> 848.74 | AB65: =ROUND(SUM(U65:AA65),2) -> 1948.47 | AC65: =VLOOKUP(AM:AM,工资明细!E:AP,38,0) -> 4474.63 | AD65: =VLOOKUP(AM:AM,工资明细!E:AH,30,0) -> 4474.63 | AH65: =ROUND(G65+T65+AB65+AD65+AF65+AG65+AE65,2) -> 10741.88 | AI65: =ROUND(AH65*(1/(1-0.78%)-1),2) -> 84.45 | AJ65: =ROUND(SUM(AH65:AI65)*6%,2) -> 649.58 | AK65: =ROUND(SUM(AH65:AJ65),2) -> 11475.91 | AM65: 429006199501020014 | AN65: 武汉市 | AO65: 合杰区域分公司 | AP65: =U65 -> 848.72 | AQ65: =V65+Z65 -> 219.18 | AR65: =W65 -> 31.83 | AS65: =AA65 -> 848.74
A66: 58 | B66: 肖若竹 | C66: MNCN00646 | D66: 202606 | E66: 44783 | G66: 595 | H66: 7684 | I66: 7684 | J66: =ROUND(H66*16%,2) -> 1229.44 | K66: =ROUND(H66*6.85%,2) -> 526.35 | L66: =ROUND(H66*0.8%,2) -> 61.47 | M66: =ROUND(H66*0.4%,2) -> 30.74 | P66: =ROUND(H66*1.5%,2) -> 115.26 | S66: =ROUND(I66*7%,0) -> 538 | T66: =ROUND(SUM(J66:S66),2) -> 2501.26 | U66: =ROUND(H66*8%,2) -> 614.72 | V66: =ROUND(H66*2%,2) -> 153.68 | W66: =ROUND(H66*0.2%,2) -> 15.37 | AA66: =S66 -> 538 | AB66: =SUM(U66:AA66) -> 1321.77 | AC66: =VLOOKUP(AM:AM,工资明细!E:AP,38,0) -> 6293.82 | AD66: =VLOOKUP(AM:AM,工资明细!E:AH,30,0) -> 6374.71 | AH66: =ROUND(G66+T66+AB66+AD66+AF66+AG66+AE66,2) -> 10792.74 | AI66: =ROUND(AH66*(1/(1-0.78%)-1),2) -> 84.85 | AJ66: =ROUND(SUM(AH66:AI66)*6%,2) -> 652.66 | AK66: =ROUND(SUM(AH66:AJ66),2) -> 11530.25 | AM66: 130225199509230043 | AN66: 广州市 | AO66: 合杰区域分公司 | AP66: =U66 -> 614.72 | AQ66: =V66+Z66 -> 153.68 | AR66: =W66 -> 15.37 | AS66: =AA66 -> 538
B67: 何雯 | D67: 202605 | E67: 44823 | G67: 595 | H67: -411 | I67: 8212 | J67: =ROUND(H67*16%,2) -> -65.76 | K67: =ROUND(H67*7.55%,2) -> -31.03 | L67: =ROUND(H67*0.6%,2) -> -2.47 | M67: =ROUND(H67*0.4%,2) -> -1.64 | O67: =ROUND(H67*0.75%,2) -> -3.08 | P67: =ROUND(H67*1.5%,2) -> -6.17 | T67: =ROUND(SUM(J67:S67),2) -> -110.15 | U67: =ROUND(H67*8%,2) -> -32.88 | V67: =ROUND(H67*2%,2) -> -8.22 | W67: =ROUND(H67*0.4%,2) -> -1.64 | AA67: =S67 -> 0 | AB67: =ROUND(SUM(U67:AA67),2) -> -42.74 | AH67: =ROUND(G67+T67+AB67+AD67+AF67+AG67+AE67,2) -> 442.11 | AI67: =ROUND(AH67*(1/(1-0.78%)-1),2) -> 3.48 | AJ67: =ROUND(SUM(AH67:AI67)*6%,2) -> 26.74 | AK67: =ROUND(SUM(AH67:AJ67),2) -> 472.33 | AL67: 退基数差异5月基数差异费用 | AM67: 510106198710121449 | AN67: 成都市 | AO67: 成都合杰 | AP67: =U67 -> -32.88 | AQ67: =V67+Z67 -> -8.22 | AR67: =W67 -> -1.64 | AS67: =AA67 -> 0
A68: 59 | B68: 何雯 | C68: MNCN00656 | D68: 202606 | E68: 44823 | G68: 595 | H68: 9468 | I68: 8212 | J68: =ROUND(H68*16%,2) -> 1514.88 | K68: =ROUND(H68*7.55%,2) -> 714.83 | L68: =ROUND(H68*0.6%,2) -> 56.81 | M68: =ROUND(H68*0.4%,2) -> 37.87 | O68: =ROUND(H68*0.75%,2) -> 71.01 | P68: =ROUND(H68*1.5%,2) -> 142.02 | S68: =ROUNDUP(I68*6%,0) -> 493 | T68: =ROUND(SUM(J68:S68),2) -> 3030.42 | U68: =ROUND(H68*8%,2) -> 757.44 | V68: =ROUND(H68*2%,2) -> 189.36 | W68: =ROUND(H68*0.4%,2) -> 37.87 | AA68: =S68 -> 493 | AB68: =ROUND(SUM(U68:AA68),2) -> 1477.67 | AC68: =VLOOKUP(AM:AM,工资明细!E:AP,38,0) -> 4300.41 | AD68: =VLOOKUP(AM:AM,工资明细!E:AH,30,0) -> 4319.22 | AH68: =ROUND(G68+T68+AB68+AD68+AF68+AG68+AE68,2) -> 9422.31 | AI68: =ROUND(AH68*(1/(1-0.78%)-1),2) -> 74.07 | AJ68: =ROUND(SUM(AH68:AI68)*6%,2) -> 569.78 | AK68: =ROUND(SUM(AH68:AJ68),2) -> 10066.16 | AM68: 510106198710121449 | AN68: 成都市 | AO68: 成都合杰 | AP68: =U68 -> 757.44 | AQ68: =V68+Z68 -> 189.36 | AR68: =W68 -> 37.87 | AS68: =AA68 -> 493
A69: 60 | B69: 李芳 | C69: MNCN00661 | D69: 202606 | E69: 44833 | G69: 595 | H69: 8941.63 | I69: 8942 | J69: =ROUND(H69*16%,2) -> 1430.66 | K69: =ROUND(H69*6.8%,2) -> 608.03 | L69: =ROUND(H69*0.5%,2) -> 44.71 | M69: =ROUND(H69*0.2%,2) -> 17.88 | O69: 23.74 | P69: =ROUND(H69*1.5%,2) -> 134.12 | R69: 10.73 | S69: =ROUND(I69*12%,0) -> 1073 | T69: =ROUND(SUM(J69:S69),2) -> 3342.87 | U69: =ROUND(H69*8%,2) -> 715.33 | V69: =ROUND(H69*2%,2) -> 178.83 | W69: =ROUND(H69*0.5%,2) -> 44.71 | Z69: 15.82 | AA69: =S69 -> 1073 | AB69: =ROUND(SUM(U69:AA69),2) -> 2027.69 | AC69: =VLOOKUP(AM:AM,工资明细!E:AP,38,0) -> 4551.43 | AD69: =VLOOKUP(AM:AM,工资明细!E:AH,30,0) -> 4592.1 | AH69: =ROUND(G69+T69+AB69+AD69+AF69+AG69+AE69,2) -> 10557.66 | AI69: =ROUND(AH69*(1/(1-0.78%)-1),2) -> 83 | AJ69: =ROUND(SUM(AH69:AI69)*6%,2) -> 638.44 | AK69: =ROUND(SUM(AH69:AJ69),2) -> 11279.1 | AM69: 360121199309283548 | AN69: 南昌市 | AO69: 合杰区域分公司 | AP69: =U69 -> 715.33 | AQ69: =V69+Z69 -> 194.65 | AR69: =W69 -> 44.71 | AS69: =AA69 -> 1073
A70: 61 | B70: 朱健 | C70: MNCN00663 | D70: 202606 | E70: 44845 | G70: 595 | H70: 7703.29 | I70: 7703 | J70: =ROUND(H70*16%,2) -> 1232.53 | K70: =ROUND(H70*6.8%,2) -> 523.82 | L70: =ROUND(H70*0.5%,2) -> 38.52 | M70: =ROUND(H70*0.2%,2) -> 15.41 | O70: 23.74 | P70: =ROUND(H70*1.5%,2) -> 115.55 | R70: 9.24 | S70: =ROUND(I70*12%,0) -> 924 | T70: =ROUND(SUM(J70:S70),2) -> 2882.81 | U70: =ROUND(H70*8%,2) -> 616.26 | V70: =ROUND(H70*2%,2) -> 154.07 | W70: =ROUND(H70*0.5%,2) -> 38.52 | Z70: 15.82 | AA70: =S70 -> 924 | AB70: =ROUND(SUM(U70:AA70),2) -> 1748.67 | AC70: =VLOOKUP(AM:AM,工资明细!E:AP,38,0) -> 7924.25 | AD70: =VLOOKUP(AM:AM,工资明细!E:AH,30,0) -> 7924.25 | AH70: =ROUND(G70+T70+AB70+AD70+AF70+AG70+AE70,2) -> 13150.73 | AI70: =ROUND(AH70*(1/(1-0.78%)-1),2) -> 103.38 | AJ70: =ROUND(SUM(AH70:AI70)*6%,2) -> 795.25 | AK70: =ROUND(SUM(AH70:AJ70),2) -> 14049.36 | AM70: 360481198502284030 | AN70: 南昌市 | AO70: 合杰区域分公司 | AP70: =U70 -> 616.26 | AQ70: =V70+Z70 -> 169.89 | AR70: =W70 -> 38.52 | AS70: =AA70 -> 924
A71: 62 | B71: 董琪 | C71: MNCN00667 | D71: 202606 | E71: 44878 | G71: 595 | H71: 8217 | I71: 8217.41 | J71: =ROUND($H71*16%,2) -> 1314.72 | K71: =ROUND($H71*8.7%,2) -> 714.88 | L71: =ROUND($H71*0.7%,2) -> 57.52 | M71: =ROUND($H71*0.2%,2) -> 16.43 | P71: =ROUND(H71*1.5%,2) -> 123.26 | S71: =ROUND($I71*8%,2) -> 657.39 | T71: =ROUND(SUM(J71:S71),2) -> 2884.2 | U71: =ROUND($H71*8%,2) -> 657.36 | V71: =ROUND($H71*2%,2) -> 164.34 | W71: =ROUND($H71*0.3%,2) -> 24.65 | Z71: 7 | AA71: =S71 -> 657.39 | AB71: =ROUND(SUM(U71:AA71),2) -> 1510.74 | AC71: =VLOOKUP(AM:AM,工资明细!E:AP,38,0) -> 3408.27 | AD71: =VLOOKUP(AM:AM,工资明细!E:AH,30,0) -> 3408.27 | AH71: =ROUND(G71+T71+AB71+AD71+AF71+AG71+AE71,2) -> 8398.21 | AI71: =ROUND(AH71*(1/(1-0.78%)-1),2) -> 66.02 | AJ71: =ROUND(SUM(AH71:AI71)*6%,2) -> 507.85 | AK71: =ROUND(SUM(AH71:AJ71),2) -> 8972.08 | AM71: 421181198909180429 | AN71: 武汉市 | AO71: 合杰区域分公司 | AP71: =U71 -> 657.36 | AQ71: =V71+Z71 -> 171.34 | AR71: =W71 -> 24.65 | AS71: =AA71 -> 657.39
B72: 王琳 | D72: 202605 | E72: 44879 | G72: 595 | H72: -9534 | I72: 10502 | J72: =ROUND(H72*16%,2) -> -1525.44 | K72: =ROUND(H72*7.55%,2) -> -719.82 | L72: =ROUND(H72*0.6%,2) -> -57.2 | M72: =ROUND(H72*0.4%,2) -> -38.14 | O72: =ROUND(H72*0.75%,2) -> -71.51 | P72: =ROUND(H72*1.5%,2) -> -143.01 | T72: =ROUND(SUM(J72:S72),2) -> -2555.12 | U72: =ROUND(H72*8%,2) -> -762.72 | V72: =ROUND(H72*2%,2) -> -190.68 | W72: =ROUND(H72*0.4%,2) -> -38.14 | AA72: =S72 -> 0 | AB72: =ROUND(SUM(U72:AA72),2) -> -991.54 | AH72: =ROUND(G72+T72+AB72+AD72+AF72+AG72+AE72,2) -> -2951.66 | AI72: =ROUND(AH72*(1/(1-0.78%)-1),2) -> -23.2 | AJ72: =ROUND(SUM(AH72:AI72)*6%,2) -> -178.49 | AK72: =ROUND(SUM(AH72:AJ72),2) -> -3153.35 | AL72: 退基数差异5月基数差异费用 | AM72: 230119198905161023 | AN72: 成都市 | AO72: 成都合杰 | AP72: =U72 -> -762.72 | AQ72: =V72+Z72 -> -190.68 | AR72: =W72 -> -38.14 | AS72: =AA72 -> 0
A73: 63 | B73: 王琳 | C73: MNCN00668 | D73: 202606 | E73: 44879 | G73: 595 | H73: 12664 | I73: 10502 | J73: =ROUND(H73*16%,2) -> 2026.24 | K73: =ROUND(H73*7.55%,2) -> 956.13 | L73: =ROUND(H73*0.6%,2) -> 75.98 | M73: =ROUND(H73*0.4%,2) -> 50.66 | O73: =ROUND(H73*0.75%,2) -> 94.98 | P73: =ROUND(H73*1.5%,2) -> 189.96 | S73: =ROUNDUP(I73*6%,0) -> 631 | T73: =ROUND(SUM(J73:S73),2) -> 4024.95 | U73: =ROUND(H73*8%,2) -> 1013.12 | V73: =ROUND(H73*2%,2) -> 253.28 | W73: =ROUND(H73*0.4%,2) -> 50.66 | AA73: =S73 -> 631 | AB73: =ROUND(SUM(U73:AA73),2) -> 1948.06 | AC73: =VLOOKUP(AM:AM,工资明细!E:AP,38,0) -> 6113.14 | AD73: =VLOOKUP(AM:AM,工资明细!E:AH,30,0) -> 6222.41 | AH73: =ROUND(G73+T73+AB73+AD73+AF73+AG73+AE73,2) -> 12790.42 | AI73: =ROUND(AH73*(1/(1-0.78%)-1),2) -> 100.55 | AJ73: =ROUND(SUM(AH73:AI73)*6%,2) -> 773.46 | AK73: =ROUND(SUM(AH73:AJ73),2) -> 13664.43 | AM73: 230119198905161023 | AN73: 成都市 | AO73: 成都合杰 | AP73: =U73 -> 1013.12 | AQ73: =V73+Z73 -> 253.28 | AR73: =W73 -> 50.66 | AS73: =AA73 -> 631
A74: 64 | B74: 周峰 | C74: MNCN00673 | D74: 202606 | E74: 44922 | G74: 595 | H74: 7299 | I74: 8421 | J74: =ROUND($H74*16%,2) -> 1167.84 | K74: =ROUND($H74*8.5%,2) -> 620.42 | L74: =ROUND($H74*0.5%,2) -> 36.5 | M74: =ROUND($H74*0.6%,2) -> 43.79 | O74: =ROUND(H74*1.5%,2) -> 109.49 | P74: =ROUND(H74*1.5%,2) -> 109.49 | S74: =ROUND(I74*5%,0) -> 421 | T74: =ROUND(SUM(J74:S74),2) -> 2508.53 | U74: =ROUND($H74*8%,2) -> 583.92 | V74: =ROUND($H74*2%,2) -> 145.98 | W74: =ROUND($H74*0.5%,2) -> 36.5 | Z74: 5 | AA74: =S74 -> 421 | AB74: =ROUND(SUM(U74:AA74),2) -> 1192.4 | AC74: =VLOOKUP(AM:AM,工资明细!E:AP,38,0) -> 4073.12 | AD74: =VLOOKUP(AM:AM,工资明细!E:AH,30,0) -> 4073.12 | AH74: =ROUND(G74+T74+AB74+AD74+AF74+AG74+AE74,2) -> 8369.05 | AI74: =ROUND(AH74*(1/(1-0.78%)-1),2) -> 65.79 | AJ74: =ROUND(SUM(AH74:AI74)*6%,2) -> 506.09 | AK74: =ROUND(SUM(AH74:AJ74),2) -> 8940.93 | AM74: 500382198603225336 | AN74: 重庆市 | AO74: 合杰区域分公司 | AP74: =U74 -> 583.92 | AQ74: =V74+Z74 -> 150.98 | AR74: =W74 -> 36.5 | AS74: =AA74 -> 421
A75: 65 | B75: 王丹 | C75: MNCN00677 | D75: 202606 | E75: 44986 | G75: 595 | H75: 8520 | I75: 8520 | J75: =ROUND(H75*16%,2) -> 1363.2 | K75: =ROUND(H75*9.8%,2) -> 834.96 | L75: =ROUND(H75*0.5%,2) -> 42.6 | M75: =ROUND(H75*0.32%,2) -> 27.26 | P75: =ROUND(H75*1.5%,2) -> 127.8 | S75: =ROUND(I75*12%,0) -> 1022 | T75: =ROUND(SUM(J75:S75),2) -> 3417.82 | U75: =ROUND(H75*8%,2) -> 681.6 | V75: =ROUND(H75*2%,2) -> 170.4 | W75: =ROUND(H75*0.5%,2) -> 42.6 | Z75: 3 | AA75: =S75 -> 1022 | AB75: =ROUND(SUM(U75:AA75),2) -> 1919.6 | AC75: =VLOOKUP(AM:AM,工资明细!E:AP,38,0) -> 3932.12 | AD75: =VLOOKUP(AM:AM,工资明细!E:AH,30,0) -> 3932.12 | AH75: =ROUND(G75+T75+AB75+AD75+AF75+AG75+AE75,2) -> 9864.54 | AI75: =ROUND(AH75*(1/(1-0.78%)-1),2) -> 77.55 | AJ75: =ROUND(SUM(AH75:AI75)*6%,2) -> 596.53 | AK75: =ROUND(SUM(AH75:AJ75),2) -> 10538.62 | AM75: 131121199101201441 | AN75: 北京市 | AO75: 北京合杰 | AP75: =U75 -> 681.6 | AQ75: =V75+Z75 -> 173.4 | AR75: =W75 -> 42.6 | AS75: =AA75 -> 1022
A76: 66 | B76: 熊蒙蒙 | C76: MNCN00679 | D76: 202606 | E76: 44999 | G76: 595 | H76: 16322.5 | I76: 16322.5 | J76: =ROUND($H76*16%,2) -> 2611.6 | K76: =ROUNDDOWN(H76*9%,2) -> 1469.02 | L76: =ROUND(H76*0.5%,2) -> 81.61 | M76: =ROUND(H76*0.32%,2) -> 52.23 | P76: =ROUND(H76*(1.5%*0.9),2) -> 220.35 | S76: =ROUND(I76*7%,0) -> 1143 | T76: =ROUND(SUM(J76:S76),2) -> 5577.81 | U76: =ROUND(H76*8%,2) -> 1305.8 | V76: =ROUND(H76*2%,2) -> 326.45 | W76: =ROUND(H76*0.5%,2) -> 81.61 | AA76: =ROUND(I76*7%,0) -> 1143 | AB76: =ROUND(SUM(U76:AA76),2) -> 2856.86 | AC76: =VLOOKUP(AM:AM,工资明细!E:AP,38,0) -> 5293.14 | AD76: =VLOOKUP(AM:AM,工资明细!E:AH,30,0) -> 5643.14 | AH76: =ROUND(G76+T76+AB76+AD76+AF76+AG76+AE76,2) -> 14672.81 | AI76: =ROUND(AH76*(1/(1-0.78%)-1),2) -> 115.35 | AJ76: =ROUND(SUM(AH76:AI76)*6%,2) -> 887.29 | AK76: =ROUND(SUM(AH76:AJ76),2) -> 15675.45 | AM76: 321323199806203649 | AN76: 上海市 | AO76: 上海合杰 | AP76: =U76 -> 1305.8 | AQ76: =V76+Z76 -> 326.45 | AR76: =W76 -> 81.61 | AS76: =AA76 -> 1143
A77: 67 | B77: 陈传波 | C77: MNCN00681 | D77: 202606 | E77: 45017 | G77: 595 | H77: 8181 | I77: 8180.51 | J77: =ROUND($H77*16%,2) -> 1308.96 | K77: =ROUND($H77*8.7%,2) -> 711.75 | L77: =ROUND($H77*0.7%,2) -> 57.27 | M77: =ROUND($H77*0.2%,2) -> 16.36 | P77: =ROUND(H77*1.5%,2) -> 122.72 | S77: =ROUND($I77*8%,2) -> 654.44 | T77: =ROUND(SUM(J77:S77),2) -> 2871.5 | U77: =ROUND($H77*8%,2) -> 654.48 | V77: =ROUND($H77*2%,2) -> 163.62 | W77: =ROUND($H77*0.3%,2) -> 24.54 | Z77: 7 | AA77: =S77 -> 654.44 | AB77: =ROUND(SUM(U77:AA77),2) -> 1504.08 | AC77: =VLOOKUP(AM:AM,工资明细!E:AP,38,0) -> 6882.13 | AD77: =VLOOKUP(AM:AM,工资明细!E:AH,30,0) -> 6882.13 | AH77: =ROUND(G77+T77+AB77+AD77+AF77+AG77+AE77,2) -> 11852.71 | AI77: =ROUND(AH77*(1/(1-0.78%)-1),2) -> 93.18 | AJ77: =ROUND(SUM(AH77:AI77)*6%,2) -> 716.75 | AK77: =ROUND(SUM(AH77:AJ77),2) -> 12662.64 | AM77: 420683198510200554 | AN77: 武汉市 | AO77: 合杰区域分公司 | AP77: =U77 -> 654.48 | AQ77: =V77+Z77 -> 170.62 | AR77: =W77 -> 24.54 | AS77: =AA77 -> 654.44
B78: 罗莎莎 | D78: 202605 | E78: 45231 | G78: 595 | H78: -1256 | I78: 12272 | J78: =ROUND(H78*16%,2) -> -200.96 | K78: =ROUND(H78*7.55%,2) -> -94.83 | L78: =ROUND(H78*0.6%,2) -> -7.54 | M78: =ROUND(H78*0.4%,2) -> -5.02 | O78: =ROUND(H78*0.75%,2) -> -9.42 | P78: =ROUND(H78*1.5%,2) -> -18.84 | T78: =ROUND(SUM(J78:S78),2) -> -336.61 | U78: =ROUND(H78*8%,2) -> -100.48 | V78: =ROUND(H78*2%,2) -> -25.12 | W78: =ROUND(H78*0.4%,2) -> -5.02 | AA78: =S78 -> 0 | AB78: =ROUND(SUM(U78:AA78),2) -> -130.62 | AH78: =ROUND(G78+T78+AB78+AD78+AF78+AG78+AE78,2) -> 127.77 | AI78: =ROUND(AH78*(1/(1-0.78%)-1),2) -> 1 | AJ78: =ROUND(SUM(AH78:AI78)*6%,2) -> 7.73 | AK78: =ROUND(SUM(AH78:AJ78),2) -> 136.5 | AL78: 退基数差异5月基数差异费用 | AM78: 51072419900424082X | AN78: 成都市 | AO78: 成都合杰 | AP78: =U78 -> -100.48 | AQ78: =V78+Z78 -> -25.12 | AR78: =W78 -> -5.02 | AS78: =AA78 -> 0
A79: 68 | B79: 罗莎莎 | C79: MNCN00695 | D79: 202606 | E79: 45231 | G79: 595 | H79: 10907 | I79: 12272 | J79: =ROUND(H79*16%,2) -> 1745.12 | K79: =ROUND(H79*7.55%,2) -> 823.48 | L79: =ROUND(H79*0.6%,2) -> 65.44 | M79: =ROUND(H79*0.4%,2) -> 43.63 | O79: =ROUND(H79*0.75%,2) -> 81.8 | P79: =ROUND(H79*1.5%,2) -> 163.61 | S79: =ROUNDUP(I79*6%,0) -> 737 | T79: =ROUND(SUM(J79:S79),2) -> 3660.08 | U79: =ROUND(H79*8%,2) -> 872.56 | V79: =ROUND(H79*2%,2) -> 218.14 | W79: =ROUND(H79*0.4%,2) -> 43.63 | AA79: =S79 -> 737 | AB79: =ROUND(SUM(U79:AA79),2) -> 1871.33 | AC79: =VLOOKUP(AM:AM,工资明细!E:AP,38,0) -> 10315.27 | AD79: =VLOOKUP(AM:AM,工资明细!E:AH,30,0) -> 10693.26 | AH79: =ROUND(G79+T79+AB79+AD79+AF79+AG79+AE79,2) -> 16819.67 | AI79: =ROUND(AH79*(1/(1-0.78%)-1),2) -> 132.22 | AJ79: =ROUND(SUM(AH79:AI79)*6%,2) -> 1017.11 | AK79: =ROUND(SUM(AH79:AJ79),2) -> 17969 | AM79: 51072419900424082X | AN79: 成都市 | AO79: 成都合杰 | AP79: =U79 -> 872.56 | AQ79: =V79+Z79 -> 218.14 | AR79: =W79 -> 43.63 | AS79: =AA79 -> 737
A80: 69 | B80: 姚顾周 | C80: MNCN00696 | D80: 202606 | E80: 45231 | G80: 595 | H80: 9020.56 | I80: 9020.56 | J80: =ROUND(H80*17%,2) -> 1533.5 | K80: =ROUND(H80*6%,2) -> 541.23 | L80: =ROUND(H80*0.8%,2) -> 72.16 | M80: =ROUND(H80*0.4%,2) -> 36.08 | N80: =ROUND(9020.56*0.5%,2) -> 45.1 | P80: 41.19 | S80: =ROUNDUP(I80*7%,2) -> 631.44 | T80: =ROUND(SUM(J80:S80),2) -> 2900.7 | U80: =ROUND(H80*8%,2) -> 721.64 | V80: =ROUND(H80*2%,2) -> 180.41 | W80: =ROUND(H80*0.2%,2) -> 18.04 | AA80: =S80 -> 631.44 | AB80: =ROUND(SUM(U80:AA80),2) -> 1551.53 | AC80: =VLOOKUP(AM:AM,工资明细!E:AP,38,0) -> 9685.8 | AD80: =VLOOKUP(AM:AM,工资明细!E:AH,30,0) -> 9775.09 | AH80: =ROUND(G80+T80+AB80+AD80+AF80+AG80+AE80,2) -> 14822.32 | AI80: =ROUND(AH80*(1/(1-0.78%)-1),2) -> 116.52 | AJ80: =ROUND(SUM(AH80:AI80)*6%,2) -> 896.33 | AK80: =ROUND(SUM(AH80:AJ80),2) -> 15835.17 | AM80: 42108719830930323X | AN80: 深圳市 | AO80: 深圳合杰 | AP80: =U80 -> 721.64 | AQ80: =V80+Z80 -> 180.41 | AR80: =W80 -> 18.04 | AS80: =AA80 -> 631.44
A81: 70 | B81: 张嵩扬 | C81: MNCN00697 | D81: 202606 | E81: 45274 | G81: 595 | H81: 9927 | I81: 9927 | J81: =ROUND(H81*16%,2) -> 1588.32 | K81: =ROUND(H81*9.8%,2) -> 972.85 | L81: =ROUND(H81*0.5%,2) -> 49.64 | M81: =ROUND(H81*0.32%,2) -> 31.77 | P81: =ROUND(H81*1.5%,2) -> 148.91 | S81: =ROUND(I81*12%,0) -> 1191 | T81: =ROUND(SUM(J81:S81),2) -> 3982.49 | U81: =ROUND(H81*8%,2) -> 794.16 | V81: =ROUND(H81*2%,2) -> 198.54 | W81: =ROUND(H81*0.5%,2) -> 49.64 | Z81: 3 | AA81: =S81 -> 1191 | AB81: =ROUND(SUM(U81:AA81),2) -> 2236.34 | AC81: =VLOOKUP(AM:AM,工资明细!E:AP,38,0) -> 8179.43 | AD81: =VLOOKUP(AM:AM,工资明细!E:AH,30,0) -> 8346.93 | AH81: =ROUND(G81+T81+AB81+AD81+AF81+AG81+AE81,2) -> 15160.76 | AI81: =ROUND(AH81*(1/(1-0.78%)-1),2) -> 119.18 | AJ81: =ROUND(SUM(AH81:AI81)*6%,2) -> 916.8 | AK81: =ROUND(SUM(AH81:AJ81),2) -> 16196.74 | AM81: 220521198212290027 | AN81: 北京市 | AO81: 北京合杰 | AP81: =U81 -> 794.16 | AQ81: =V81+Z81 -> 201.54 | AR81: =W81 -> 49.64 | AS81: =AA81 -> 1191
A82: 71 | B82: 邓怡青 | C82: MNCN00704 | D82: 202606 | E82: 45397 | G82: 595 | H82: 6596.18 | I82: 6596 | J82: =ROUND(H82*16%,2) -> 1055.39 | K82: =ROUND(H82*6.8%,2) -> 448.54 | L82: =ROUND(H82*0.5%,2) -> 32.98 | M82: =ROUND(H82*0.2%,2) -> 13.19 | O82: 23.74 | P82: =ROUND(H82*1.5%,2) -> 98.94 | R82: 7.92 | S82: =ROUND(I82*12%,0) -> 792 | T82: =ROUND(SUM(J82:S82),2) -> 2472.7 | U82: =ROUND(H82*8%,2) -> 527.69 | V82: =ROUND(H82*2%,2) -> 131.92 | W82: =ROUND(H82*0.5%,2) -> 32.98 | Z82: 15.82 | AA82: =S82 -> 792 | AB82: =ROUND(SUM(U82:AA82),2) -> 1500.41 | AC82: =VLOOKUP(AM:AM,工资明细!E:AP,38,0) -> 20248.81 | AD82: =VLOOKUP(AM:AM,工资明细!E:AH,30,0) -> 20614.75 | AH82: =ROUND(G82+T82+AB82+AD82+AF82+AG82+AE82,2) -> 25182.86 | AI82: =ROUND(AH82*(1/(1-0.78%)-1),2) -> 197.97 | AJ82: =ROUND(SUM(AH82:AI82)*6%,2) -> 1522.85 | AK82: =ROUND(SUM(AH82:AJ82),2) -> 26903.68 | AM82: 360105199208251213 | AN82: 南昌市 | AO82: 合杰区域分公司 | AP82: =U82 -> 527.69 | AQ82: =V82+Z82 -> 147.74 | AR82: =W82 -> 32.98 | AS82: =AA82 -> 792
A83: 72 | B83: 李琳 | C83: MNCN00707 | D83: 202606 | E83: 45434 | G83: 595 | H83: 6792 | I83: 6791.82 | J83: =ROUND($H83*16%,2) -> 1086.72 | K83: =ROUND(H83*8.7%,2) -> 590.9 | L83: =ROUND($H83*0.7%,2) -> 47.54 | M83: =ROUND($H83*0.2%,2) -> 13.58 | P83: =ROUND(H83*1.5%,2) -> 101.88 | S83: =ROUND($I83*8%,2) -> 543.35 | T83: =ROUND(SUM(J83:S83),2) -> 2383.97 | U83: =ROUND($H83*8%,2) -> 543.36 | V83: =ROUND(H83*2%,2) -> 135.84 | W83: =ROUND($H83*0.3%,2) -> 20.38 | Z83: 7 | AA83: =S83 -> 543.35 | AB83: =ROUND(SUM(U83:AA83),2) -> 1249.93 | AC83: =VLOOKUP(AM:AM,工资明细!E:AP,38,0) -> 6456.5 | AD83: =VLOOKUP(AM:AM,工资明细!E:AH,30,0) -> 6540.2 | AH83: =ROUND(G83+T83+AB83+AD83+AF83+AG83+AE83,2) -> 10769.1 | AI83: =ROUND(AH83*(1/(1-0.78%)-1),2) -> 84.66 | AJ83: =ROUND(SUM(AH83:AI83)*6%,2) -> 651.23 | AK83: =ROUND(SUM(AH83:AJ83),2) -> 11504.99 | AM83: 420116199710180487 | AN83: 武汉市 | AO83: 合杰区域分公司 | AP83: =U83 -> 543.36 | AQ83: =V83+Z83 -> 142.84 | AR83: =W83 -> 20.38 | AS83: =AA83 -> 543.35
A84: 73 | B84: 郭圣杰 | C84: MNCN00718 | D84: 202606 | E84: 45761 | G84: 595 | H84: 4498 | I84: 3600 | J84: =ROUND($H84*16%,2) -> 719.68 | K84: =ROUND(4498*8.7%,2) -> 391.33 | L84: =ROUND($H84*0.7%,2) -> 31.49 | M84: =ROUND($H84*0.2%,2) -> 9 | P84: =ROUND(H84*1.5%,2) -> 67.47 | S84: =ROUND(I84*8%,2) -> 288 | T84: =ROUND(SUM(J84:S84),2) -> 1506.97 | U84: =ROUND($H84*8%,2) -> 359.84 | V84: =ROUND(4498*2%,2) -> 89.96 | W84: =ROUND($H84*0.3%,2) -> 13.49 | Z84: 7 | AA84: =S84 -> 288 | AB84: =ROUND(SUM(U84:AA84),2) -> 758.29 | AC84: =VLOOKUP(AM:AM,工资明细!E:AP,38,0) -> 3874.02 | AD84: =VLOOKUP(AM:AM,工资明细!E:AH,30,0) -> 3874.02 | AH84: =ROUND(G84+T84+AB84+AD84+AF84+AG84+AE84,2) -> 6734.28 | AI84: =ROUND(AH84*(1/(1-0.78%)-1),2) -> 52.94 | AJ84: =ROUND(SUM(AH84:AI84)*6%,2) -> 407.23 | AK84: =ROUND(SUM(AH84:AJ84),2) -> 7194.45 | AM84: 420116200212250011 | AN84: 武汉市 | AO84: 合杰区域分公司 | AP84: =U84 -> 359.84 | AQ84: =V84+Z84 -> 96.96 | AR84: =W84 -> 13.49 | AS84: =AA84 -> 288
A85: 74 | B85: 鲁业全 | C85: MNCN00285 | D85: 202606 | E85: 45826 | G85: 595 | H85: 4775 | I85: 4600 | J85: =ROUND(H85*16%,2) -> 764 | K85: =ROUND(6727*6%,2) -> 403.62 | L85: =ROUND(4600*0.8%,2) -> 36.8 | M85: =ROUND(I85*0.4%,2) -> 18.4 | N85: =ROUND(6727*0.5%,2) -> 33.64 | P85: 41.19 | S85: =ROUNDUP(I85*7%,2) -> 322 | T85: =ROUND(SUM(J85:S85),2) -> 1619.65 | U85: =ROUND(H85*8%,2) -> 382 | V85: =ROUND(6727*2%,2) -> 134.54 | W85: =ROUND(I85*0.2%,2) -> 9.2 | AA85: =S85 -> 322 | AB85: =ROUND(SUM(U85:AA85),2) -> 847.74 | AC85: =VLOOKUP(AM:AM,工资明细!E:AP,38,0) -> 11941 | AD85: =VLOOKUP(AM:AM,工资明细!E:AH,30,0) -> 11941 | AH85: =ROUND(G85+T85+AB85+AD85+AF85+AG85+AE85,2) -> 15003.39 | AI85: =ROUND(AH85*(1/(1-0.78%)-1),2) -> 117.95 | AJ85: =ROUND(SUM(AH85:AI85)*6%,2) -> 907.28 | AK85: =ROUND(SUM(AH85:AJ85),2) -> 16028.62 | AM85: 513030198906301035 | AN85: 深圳市 | AO85: 深圳合杰 | AP85: =U85 -> 382 | AQ85: =V85+Z85 -> 134.54 | AR85: =W85 -> 9.2 | AS85: =AA85 -> 322
A86: 75 | B86: 王永维 | C86: MNCN00723 | D86: 202606 | E86: 45875 | G86: 595 | H86: 7162 | I86: 4600 | J86: =ROUND(H86*16%,2) -> 1145.92 | K86: =ROUND(H86*9.8%,2) -> 701.88 | L86: =ROUND(H86*0.5%,2) -> 35.81 | M86: =ROUND(H86*0.32%,2) -> 22.92 | P86: =ROUND(H86*1.5%,2) -> 107.43 | S86: =ROUND(I86*12%,0) -> 552 | T86: =ROUND(SUM(J86:S86),2) -> 2565.96 | U86: =ROUND(H86*8%,2) -> 572.96 | V86: =ROUND(H86*2%,2) -> 143.24 | W86: =ROUND(H86*0.5%,2) -> 35.81 | Z86: 3 | AA86: =S86 -> 552 | AB86: =ROUND(SUM(U86:AA86),2) -> 1307.01 | AC86: =VLOOKUP(AM:AM,工资明细!E:AP,38,0) -> 5891.96 | AD86: =VLOOKUP(AM:AM,工资明细!E:AH,30,0) -> 5891.96 | AH86: =ROUND(G86+T86+AB86+AD86+AF86+AG86+AE86,2) -> 10359.93 | AI86: =ROUND(AH86*(1/(1-0.78%)-1),2) -> 81.44 | AJ86: =ROUND(SUM(AH86:AI86)*6%,2) -> 626.48 | AK86: =ROUND(SUM(AH86:AJ86),2) -> 11067.85 | AM86: 130721199007055830 | AN86: 北京市 | AO86: 北京合杰 | AP86: =U86 -> 572.96 | AQ86: =V86+Z86 -> 146.24 | AR86: =W86 -> 35.81 | AS86: =AA86 -> 552
A87: 76 | B87: 张欢欢 | C87: MNCN00725 | D87: 202606 | E87: 45930 | G87: 595 | H87: 6620 | I87: 4952 | J87: =ROUND($H87*16%,2) -> 1059.2 | K87: =ROUND($H87*7%,2) -> 463.4 | L87: =ROUND($H87*0.5%,2) -> 33.1 | M87: =ROUND($H87*1.1%,2) -> 72.82 | N87: =ROUND($H87*0.8%,2) -> 52.96 | S87: =ROUNDUP(I87*8%,0) -> 397 | T87: =ROUND(SUM(J87:S87),2) -> 2078.48 | U87: =ROUND($H87*8%,2) -> 529.6 | V87: =ROUND($H87*2%,2) -> 132.4 | W87: =ROUND($H87*0.5%,2) -> 33.1 | Z87: 5 | AA87: =S87 -> 397 | AB87: =ROUND(SUM(U87:AA87),2) -> 1097.1 | AC87: =VLOOKUP(AM:AM,工资明细!E:AP,38,0) -> 6200.8 | AD87: =VLOOKUP(AM:AM,工资明细!E:AH,30,0) -> 6271.87 | AH87: =ROUND(G87+T87+AB87+AD87+AF87+AG87+AE87,2) -> 10042.45 | AI87: =ROUND(AH87*(1/(1-0.78%)-1),2) -> 78.95 | AJ87: =ROUND(SUM(AH87:AI87)*6%,2) -> 607.28 | AK87: =ROUND(SUM(AH87:AJ87),2) -> 10728.68 | AM87: 342221199203055081 | AN87: 张家港市 | AO87: 上海合杰 | AP87: =U87 -> 529.6 | AQ87: =V87+Z87 -> 137.4 | AR87: =W87 -> 33.1 | AS87: =AA87 -> 397
A88: 77 | B88: 杨利芳 | C88: MNCN00727 | D88: 202606 | E88: 45992 | G88: 595 | H88: 5124 | I88: 3600 | J88: =ROUND($H88*16%,2) -> 819.84 | K88: =ROUND(H88*10.5%,2) -> 538.02 | L88: =ROUND(H88*0.5%,2) -> 25.62 | M88: =ROUND(H88*0.4%,2) -> 20.5 | P88: =ROUND(H88*1.5%,2) -> 76.86 | S88: =ROUND(I88*11%,0) -> 396 | T88: =ROUND(SUM(J88:S88),2) -> 1876.84 | U88: =ROUND(H88*8%,2) -> 409.92 | V88: =ROUND(H88*2%,2) -> 102.48 | W88: =ROUND(H88*0.5%,2) -> 25.62 | Z88: 21 | AA88: =S88 -> 396 | AB88: =ROUND(SUM(U88:AA88),2) -> 955.02 | AC88: =VLOOKUP(AM:AM,工资明细!E:AP,38,0) -> 7279.43 | AD88: =VLOOKUP(AM:AM,工资明细!E:AH,30,0) -> 7379.46 | AH88: =ROUND(G88+T88+AB88+AD88+AF88+AG88+AE88,2) -> 10806.32 | AI88: =ROUND(AH88*(1/(1-0.78%)-1),2) -> 84.95 | AJ88: =ROUND(SUM(AH88:AI88)*6%,2) -> 653.48 | AK88: =ROUND(SUM(AH88:AJ88),2) -> 11544.75 | AM88: 410326198808163746 | AN88: 天津市 | AO88: 合杰区域分公司 | AP88: =U88 -> 409.92 | AQ88: =V88+Z88 -> 123.48 | AR88: =W88 -> 25.62 | AS88: =AA88 -> 396
A89: 78 | B89: 潘莉文 | C89: MNCN00737 | D89: 202606 | E89: 46113 | G89: 595 | H89: 7460 | I89: 3800 | J89: =ROUND($H89*16%,2) -> 1193.6 | K89: =ROUND(H89*9%,2) -> 671.4 | L89: =ROUND(H89*0.5%,2) -> 37.3 | M89: =ROUND(H89*0.32%,2) -> 23.87 | P89: =ROUND(H89*(1.5%*0.9),2) -> 100.71 | S89: =ROUND(I89*7%,0) -> 266 | T89: =ROUND(SUM(J89:S89),2) -> 2292.88 | U89: =ROUND(H89*8%,2) -> 596.8 | V89: =ROUND(H89*2%,2) -> 149.2 | W89: =ROUND(H89*0.5%,2) -> 37.3 | AA89: =S89 -> 266 | AB89: =ROUND(SUM(U89:AA89),2) -> 1049.3 | AC89: =VLOOKUP(AM:AM,工资明细!E:AP,38,0) -> 6268.8 | AD89: =VLOOKUP(AM:AM,工资明细!E:AH,30,0) -> 6268.8 | AH89: =ROUND(G89+T89+AB89+AD89+AF89+AG89+AE89,2) -> 10205.98 | AI89: =ROUND(AH89*(1/(1-0.78%)-1),2) -> 80.23 | AJ89: =ROUND(SUM(AH89:AI89)*6%,2) -> 617.17 | AK89: =ROUND(SUM(AH89:AJ89),2) -> 10903.38 | AM89: 341124199404044023 | AN89: 上海市 | AO89: 上海合杰 | AP89: =U89 -> 596.8 | AQ89: =V89+Z89 -> 149.2 | AR89: =W89 -> 37.3 | AS89: =AA89 -> 266
A90: 79 | B90: 冯莉 | C90: MNCN00739 | D90: 202606 | E90: 46129 | G90: 595 | H90: 4498 | I90: 3600 | J90: =ROUND($H90*16%,2) -> 719.68 | K90: =ROUND(4498*8.7%,2) -> 391.33 | L90: =ROUND($H90*0.7%,2) -> 31.49 | M90: =ROUND($H90*0.2%,2) -> 9 | P90: =ROUND(H90*1.5%,2) -> 67.47 | S90: =ROUND(I90*8%,2) -> 288 | T90: =ROUND(SUM(J90:S90),2) -> 1506.97 | U90: =ROUND($H90*8%,2) -> 359.84 | V90: =ROUND(4498*2%,2) -> 89.96 | W90: =ROUND($H90*0.3%,2) -> 13.49 | Z90: 7 | AA90: =S90 -> 288 | AB90: =ROUND(SUM(U90:AA90),2) -> 758.29 | AC90: =VLOOKUP(AM:AM,工资明细!E:AP,38,0) -> 5555.5 | AD90: =VLOOKUP(AM:AM,工资明细!E:AH,30,0) -> 5555.5 | AH90: =ROUND(G90+T90+AB90+AD90+AF90+AG90+AE90,2) -> 8415.76 | AI90: =ROUND(AH90*(1/(1-0.78%)-1),2) -> 66.16 | AJ90: =ROUND(SUM(AH90:AI90)*6%,2) -> 508.92 | AK90: =ROUND(SUM(AH90:AJ90),2) -> 8990.84 | AM90: 420114198702065422 | AN90: 武汉市 | AO90: 合杰区域分公司 | AP90: =U90 -> 359.84 | AQ90: =V90+Z90 -> 96.96 | AR90: =W90 -> 13.49 | AS90: =AA90 -> 288
A91: 80 | B91: 丁家恒 | C91: MNCN00740 | D91: 202606 | E91: 46131 | F91: 46181 | G91: =ROUND(595/31*8,2) -> 153.55 | H91: 4498 | I91: 3600 | J91: =-ROUND($H91*16%,2)*2 -> -1439.36 | K91: =-ROUND(4498*8.7%,2)*2 -> -782.66 | L91: =-ROUND($H91*0.7%,2)*2 -> -62.98 | M91: =-ROUND($H91*0.2%,2)*2 -> -18 | P91: =-ROUND(H91*1.5%,2)*2 -> -134.94 | S91: =ROUND(I91*8%,2) -> 288 | T91: =ROUND(SUM(J91:S91),2) -> -2149.94 | U91: =-ROUND($H91*8%,2)*2 -> -719.68 | V91: =-ROUND(4498*2%,2)*2 -> -179.92 | W91: =-ROUND($H91*0.3%,2)*2 -> -26.98 | Z91: -14 | AA91: =S91 -> 288 | AB91: =ROUND(SUM(U91:AA91),2) -> -652.58 | AC91: =VLOOKUP(AM:AM,工资明细!E:AP,38,0) -> 4400.85 | AD91: =VLOOKUP(AM:AM,工资明细!E:AH,30,0) -> 4400.85 | AH91: =ROUND(G91+T91+AB91+AD91+AF91+AG91+AE91,2) -> 1751.88 | AI91: =ROUND(AH91*(1/(1-0.78%)-1),2) -> 13.77 | AJ91: =ROUND(SUM(AH91:AI91)*6%,2) -> 105.94 | AK91: =ROUND(SUM(AH91:AJ91),2) -> 1871.59 | AL91: 退4-5月 | AM91: 420923199511134397 | AN91: 武汉市 | AO91: 合杰区域分公司 | AP91: =U91 -> -719.68 | AQ91: =V91+Z91 -> -193.92 | AR91: =W91 -> -26.98 | AS91: =AA91 -> 288
A92: 81 | B92: 魏华 | C92: MNCN00741 | D92: 202606 | E92: 46132 | G92: 595 | H92: 4359 | I92: 3600 | J92: =ROUND($H92*16%,2) -> 697.44 | K92: =ROUND(4846*8.45%,2) -> 409.49 | L92: =ROUND($H92*0.5%,2) -> 21.8 | M92: =ROUND($H92*0.4%,2) -> 17.44 | P92: =ROUND(H92*1.5%,2) -> 65.39 | R92: =ROUND(4846*0.15%,2) -> 7.27 | S92: =ROUND(I92*12%,0) -> 432 | T92: =ROUND(SUM(J92:S92),2) -> 1650.83 | U92: =ROUND($H92*8%,2) -> 348.72 | V92: =ROUND(4846*2%,2) -> 96.92 | W92: =ROUND($H92*0.5%,2) -> 21.8 | AA92: =S92 -> 432 | AB92: =ROUND(SUM(U92:AA92),2) -> 899.44 | AC92: =VLOOKUP(AM:AM,工资明细!E:AP,38,0) -> 5100.56 | AD92: =VLOOKUP(AM:AM,工资明细!E:AH,30,0) -> 5100.56 | AH92: =ROUND(G92+T92+AB92+AD92+AF92+AG92+AE92,2) -> 8245.83 | AI92: =ROUND(AH92*(1/(1-0.78%)-1),2) -> 64.82 | AJ92: =ROUND(SUM(AH92:AI92)*6%,2) -> 498.64 | AK92: =ROUND(SUM(AH92:AJ92),2) -> 8809.29 | AM92: 210114198602035120 | AN92: 沈阳市 | AO92: 合杰区域分公司 | AP92: =U92 -> 348.72 | AQ92: =V92+Z92 -> 96.92 | AR92: =W92 -> 21.8 | AS92: =AA92 -> 432
A93: 82 | B93: 刘玉栋 | C93: MNCN00742 | D93: 202606 | E93: 46133 | G93: 595 | H93: 5124 | I93: 3600 | J93: =ROUND($H93*16%,2) -> 819.84 | K93: =ROUND(H93*10.5%,2) -> 538.02 | L93: =ROUND(H93*0.5%,2) -> 25.62 | M93: =ROUND(H93*0.4%,2) -> 20.5 | P93: =ROUND(H93*1.5%,2) -> 76.86 | S93: =ROUND(I93*11%,0) -> 396 | T93: =ROUND(SUM(J93:S93),2) -> 1876.84 | U93: =ROUND(H93*8%,2) -> 409.92 | V93: =ROUND(H93*2%,2) -> 102.48 | W93: =ROUND(H93*0.5%,2) -> 25.62 | Z93: 21 | AA93: =S93 -> 396 | AB93: =ROUND(SUM(U93:AA93),2) -> 955.02 | AC93: =VLOOKUP(AM:AM,工资明细!E:AP,38,0) -> 6138.08 | AD93: =VLOOKUP(AM:AM,工资明细!E:AH,30,0) -> 6138.08 | AH93: =ROUND(G93+T93+AB93+AD93+AF93+AG93+AE93,2) -> 9564.94 | AI93: =ROUND(AH93*(1/(1-0.78%)-1),2) -> 75.19 | AJ93: =ROUND(SUM(AH93:AI93)*6%,2) -> 578.41 | AK93: =ROUND(SUM(AH93:AJ93),2) -> 10218.54 | AM93: 120105199601302115 | AN93: 天津市 | AO93: 合杰区域分公司 | AP93: =U93 -> 409.92 | AQ93: =V93+Z93 -> 123.48 | AR93: =W93 -> 25.62 | AS93: =AA93 -> 396
A94: 83 | B94: 马艳华 | D94: 202606 | E94: 46174 | G94: 207 | H94: 17000 | I94: 17000 | J94: =ROUND($H94*16%,2) -> 2720 | K94: =ROUND(H94*9%,2) -> 1530 | L94: =ROUND(H94*0.5%,2) -> 85 | M94: =ROUND(H94*0.32%,2) -> 54.4 | P94: =ROUND(H94*(1.5%*0.9),2) -> 229.5 | S94: =ROUND(I94*7%,0) -> 1190 | T94: =ROUND(SUM(J94:S94),2) -> 5808.9 | U94: =ROUND(H94*8%,2) -> 1360 | V94: =ROUND(H94*2%,2) -> 340 | W94: =ROUND(H94*0.5%,2) -> 85 | AA94: =S94 -> 1190 | AB94: =ROUND(SUM(U94:AA94),2) -> 2975 | AC94: =VLOOKUP(AM:AM,工资明细!E:AP,38,0) -> 13754.25 | AD94: =VLOOKUP(AM:AM,工资明细!E:AH,30,0) -> 14025 | AH94: =ROUND(G94+T94+AB94+AD94+AF94+AG94+AE94,2) -> 23015.9 | AI94: =ROUND(AH94*(1/(1-0.78%)-1),2) -> 180.94 | AJ94: =ROUND(SUM(AH94:AI94)*6%,2) -> 1391.81 | AK94: =ROUND(SUM(AH94:AJ94),2) -> 24588.65 | AM94: 310113198004211726 | AN94: 上海市 | AO94: 上海合杰 | AP94: =U94 -> 1360 | AQ94: =V94+Z94 -> 340 | AR94: =W94 -> 85 | AS94: =AA94 -> 1190
A95: 84 | B95: 何娜玉 | D95: 202606 | E95: 46160 | G95: =ROUND((207+40),2) -> 247 | AB95: =ROUND(SUM(U95:AA95),2) -> 0 | AC95: =VLOOKUP(AM:AM,工资明细!E:AP,38,0) -> 3030 | AD95: =VLOOKUP(AM:AM,工资明细!E:AH,30,0) -> 3030 | AH95: =ROUND(G95+T95+AB95+AD95+AF95+AG95+AE95,2) -> 3277 | AI95: =ROUND(AH95*(1/(1-0.78%)-1),2) -> 25.76 | AJ95: =ROUND(SUM(AH95:AI95)*6%,2) -> 198.17 | AK95: =ROUND(SUM(AH95:AJ95),2) -> 3500.93 | AM95: 341623200209068042 | AN95: 上海市 | AO95: 上海合杰 | AP95: =U95 -> 0 | AQ95: =V95+Z95 -> 0 | AR95: =W95 -> 0 | AS95: =AA95 -> 0
A96: 85 | B96: 李玉文 | C96: MNCN00593 | D96: 202606 | E96: 44453 | F96: 46155 | AC96: =VLOOKUP(AM:AM,工资明细!E:AP,38,0) -> 3092.49 | AD96: =VLOOKUP(AM:AM,工资明细!E:AH,30,0) -> 3092.49 | AH96: =ROUND(G96+T96+AB96+AD96+AF96+AG96+AE96,2) -> 3092.49 | AI96: =ROUND(AH96*(1/(1-0.78%)-1),2) -> 24.31 | AJ96: =ROUND(SUM(AH96:AI96)*6%,2) -> 187.01 | AK96: =ROUND(SUM(AH96:AJ96),2) -> 3303.81 | AM96: 220421199508174147 | AN96: 北京市 | AO96: 北京合杰
A97: 86 | B97: 白雪杰 | C97: MNCN00608 | D97: 202606 | E97: 44557 | F97: 46155 | AC97: =VLOOKUP(AM:AM,工资明细!E:AP,38,0) -> 15024.55 | AD97: =VLOOKUP(AM:AM,工资明细!E:AH,30,0) -> 15418.84 | AH97: =ROUND(G97+T97+AB97+AD97+AF97+AG97+AE97,2) -> 15418.84 | AI97: =ROUND(AH97*(1/(1-0.78%)-1),2) -> 121.21 | AJ97: =ROUND(SUM(AH97:AI97)*6%,2) -> 932.4 | AK97: =ROUND(SUM(AH97:AJ97),2) -> 16472.45 | AM97: 130824198307310047 | AN97: 北京市 | AO97: 北京合杰
A98: 87 | B98: 魏园园 | C98: MNCN00618 | D98: 202606 | E98: 44630 | F98: 46155 | AC98: =VLOOKUP(AM:AM,工资明细!E:AP,38,0) -> 3092.49 | AD98: =VLOOKUP(AM:AM,工资明细!E:AH,30,0) -> 3092.49 | AH98: =ROUND(G98+T98+AB98+AD98+AF98+AG98+AE98,2) -> 3092.49 | AI98: =ROUND(AH98*(1/(1-0.78%)-1),2) -> 24.31 | AJ98: =ROUND(SUM(AH98:AI98)*6%,2) -> 187.01 | AK98: =ROUND(SUM(AH98:AJ98),2) -> 3303.81 | AM98: 420325199710041927 | AN98: 北京市 | AO98: 北京合杰
A99: 88 | B99: 张瑜婷 | C99: MNCN00689 | D99: 202606 | E99: 45108 | F99: 46173 | AC99: =VLOOKUP(AM:AM,工资明细!E:AP,38,0) -> 1474.65 | AD99: =VLOOKUP(AM:AM,工资明细!E:AH,30,0) -> 1474.65 | AH99: =ROUND(G99+T99+AB99+AD99+AF99+AG99+AE99,2) -> 1474.65 | AI99: =ROUND(AH99*(1/(1-0.78%)-1),2) -> 11.59 | AJ99: =ROUND(SUM(AH99:AI99)*6%,2) -> 89.17 | AK99: =ROUND(SUM(AH99:AJ99),2) -> 1575.41 | AM99: 360734199804210025 | AN99: 南昌市 | AO99: 合杰区域分
A100: 89 | B100: 周丹 | C100: MNCN00699 | D100: 202606 | E100: 45384 | F100: 46155 | AC100: =VLOOKUP(AM:AM,工资明细!E:AP,38,0) -> 3092.49 | AD100: =VLOOKUP(AM:AM,工资明细!E:AH,30,0) -> 3092.49 | AH100: =ROUND(G100+T100+AB100+AD100+AF100+AG100+AE100,2) -> 3092.49 | AI100: =ROUND(AH100*(1/(1-0.78%)-1),2) -> 24.31 | AJ100: =ROUND(SUM(AH100:AI100)*6%,2) -> 187.01 | AK100: =ROUND(SUM(AH100:AJ100),2) -> 3303.81 | AM100: 110222198511116824 | AN100: 北京市 | AO100: 北京合杰
A101: 90 | B101: 徐殊 | C101: MNCN00717 | D101: 202606 | E101: 45734 | F101: 46173 | AC101: =VLOOKUP(AM:AM,工资明细!E:AP,38,0) -> 1521.2 | AD101: =VLOOKUP(AM:AM,工资明细!E:AH,30,0) -> 1521.2 | AH101: =ROUND(G101+T101+AB101+AD101+AF101+AG101+AE101,2) -> 1521.2 | AI101: =ROUND(AH101*(1/(1-0.78%)-1),2) -> 11.96 | AJ101: =ROUND(SUM(AH101:AI101)*6%,2) -> 91.99 | AK101: =ROUND(SUM(AH101:AJ101),2) -> 1625.15 | AM101: 36012120000506144X | AN101: 南昌市 | AO101: 合杰区域分
...

Sheet 工资明细
A1: 序号 | B1: 月份 | C1: 员工编码 | D1: 中文姓名 | E1: 身份证号码 | F1: 岗位 | G1: 工作地 | H1: 最低工资 | I1: 入职时间 | J1: 离职日期 | K1: 基本工资 | L1: 出勤工资调整 | M1: 职位津贴 | N1: 店员工龄津贴 | O1: 延时加班 | P1: 周末加班 | Q1: 节假日加班 | R1: 加班工资 | S1: 病假扣资 | T1: 事假扣资 | U1: 产假扣资 | V1: 月度销售提成 | W1: 绩效评估奖金 | X1: 税前调整 | Y1: 未休年假折算 | Z1: 公司垫付社保工资 | AA1: 公司承担税 | AB1: 最低工资标准 | AC1: 应发工资 | AD1: 个人养老 | AE1: 个人医疗 | AF1: 个人失业 | AG1: 个人公积金 | AH1: 税前工资 | AI1: 工资个税 | AJ1: 计税调整项 | AK1: 13薪奖金/年终奖 | AL1: 奖金个税 | AM1: 收入合计 | AN1: 离职补偿金 | AO1: 生育津贴/一次性伤残就业补助金 | AP1: 实发工资 | AQ1: 当年累计发放月数 | AR1: 当年累计收入 | AS1: 当年累计税 | AT1: 专项抵扣 | AU1: 备注
A2: 1 | B2: 202606 | C2: MNCN00246 | D2: 沈国伟 | E2: 330184198807080319 | F2: 高级销售顾问 | G2: 杭州 | H2: 2660 | I2: 42430 | K2: 5000 | N2: 1000 | O2: 0 | Q2: 16 | R2: =ROUND(K2/174*SUM(O2*1.5+P2*2+Q2*3),2) -> 1379.31 | V2: 2559.11 | AC2: =ROUND(SUM(SUM(K2:N2)+SUM(R2:AB2)),2) -> 9938.42 | AD2: 1359.83 | AE2: 339.96 | AF2: 84.99 | AG2: 1575 | AH2: =AC2-AD2-AE2-AF2-AG2 -> 6578.64 | AI2: =MAX(ROUND(MAX((AH2+AR2-5000*AQ2-AT2)*{0.03,0.1,0.2,0.25,0.3,0.35,0.45}-{0,2520,16920,31920,52920,85920,181920},0)-AS2,2),0) -> 0 | AL2: =ROUND(LOOKUP(MAX(0.0001,AK2/12),{0;6;24;50;70;110;160}*500+0.0001,5*MAX(0,AK2)*{0.6;2;4;5;6;7;9}%-10*{0;21;141;266;441;716;1516}),2) -> 0 | AM2: =AC2+AK2+AJ2 -> 9938.42 | AP2: =ROUND(AH2-AI2+AK2-AL2+AO2+AN2,2) -> 6578.64 | AQ2: 6 | AR2: 61678.95 | AS2: 491.4 | AT2: 42000 | AU2: 合杰区域分
A3: 2 | B3: 202606 | C3: MNCN00101 | D3: 傅禄杰 | E3: 310103198112094018 | F3: 高级销售顾问 | G3: 上海 | H3: 2740 | I3: 42430 | K3: 4600 | N3: 1000 | O3: 0 | Q3: 20 | R3: =ROUND(K3/174*SUM(O3*1.5+P3*2+Q3*3),2) -> 1586.21 | V3: 946.67 | AC3: =ROUND(SUM(SUM(K3:N3)+SUM(R3:AB3)),2) -> 8132.88 | AD3: 792.21 | AE3: 198.05 | AF3: 49.51 | AG3: 693 | AH3: =AC3-AD3-AE3-AF3-AG3 -> 6400.11 | AI3: =MAX(ROUND(MAX((AH3+AR3-5000*AQ3-AT3)*{0.03,0.1,0.2,0.25,0.3,0.35,0.45}-{0,2520,16920,31920,52920,85920,181920},0)-AS3,2),0) -> 93.99 | AL3: =ROUND(LOOKUP(MAX(0.0001,AK3/12),{0;6;24;50;70;110;160}*500+0.0001,5*MAX(0,AK3)*{0.6;2;4;5;6;7;9}%-10*{0;21;141;266;441;716;1516}),2) -> 0 | AM3: =AC3+AK3+AJ3 -> 8132.88 | AP3: =ROUND(AH3-AI3+AK3-AL3+AO3+AN3,2) -> 6306.12 | AQ3: 6 | AR3: 33002.48 | AS3: 188.09 | AT3: 0 | AU3: 上海合杰
A4: 3 | B4: 202606 | C4: MNCN00226 | D4: 韩英 | E4: 320123197712131022 | F4: 销售主管 | G4: 南京 | H4: 2660 | I4: 42430 | K4: 7300 | N4: 1000 | O4: 0 | Q4: 16 | R4: =ROUND(K4/174*SUM(O4*1.5+P4*2+Q4*3),2) -> 2013.79 | V4: 3582.89 | AC4: =ROUND(SUM(SUM(K4:N4)+SUM(R4:AB4)),2) -> 13896.68 | AD4: 1909.12 | AE4: 487.28 | AF4: 119.32 | AG4: 2604 | AH4: =AC4-AD4-AE4-AF4-AG4 -> 8776.96 | AI4: =MAX(ROUND(MAX((AH4+AR4-5000*AQ4-AT4)*{0.03,0.1,0.2,0.25,0.3,0.35,0.45}-{0,2520,16920,31920,52920,85920,181920},0)-AS4,2),0) -> 589.67 | AL4: =ROUND(LOOKUP(MAX(0.0001,AK4/12),{0;6;24;50;70;110;160}*500+0.0001,5*MAX(0,AK4)*{0.6;2;4;5;6;7;9}%-10*{0;21;141;266;441;716;1516}),2) -> 0 | AM4: =AC4+AK4+AJ4 -> 13896.68 | AP4: =ROUND(AH4-AI4+AK4-AL4+AO4+AN4,2) -> 8187.29 | AQ4: 6 | AR4: 83956.8 | AS4: 1363.71 | AT4: 18000 | AU4: 上海合杰
A5: 4 | B5: 202606 | C5: MNCN00163 | D5: 王金栋 | E5: 110223198702142714 | F5: 销售顾问 | G5: 北京 | H5: 2540 | I5: 42430 | K5: 3800 | N5: 1000 | O5: 0 | Q5: 12 | R5: =ROUND(K5/174*SUM(O5*1.5+P5*2+Q5*3),2) -> 786.21 | V5: 3374.34 | AB5: 185.99 | AC5: =ROUND(SUM(SUM(K5:N5)+SUM(R5:AB5)),2) -> 9146.54 | AD5: 2347.84 | AE5: 589.96 | AF5: 146.74 | AG5: 3522 | AH5: =AC5-AD5-AE5-AF5-AG5 -> 2540 | AI5: =MAX(ROUND(MAX((AH5+AR5-5000*AQ5-AT5)*{0.03,0.1,0.2,0.25,0.3,0.35,0.45}-{0,2520,16920,31920,52920,85920,181920},0)-AS5,2),0) -> 0 | AL5: =ROUND(LOOKUP(MAX(0.0001,AK5/12),{0;6;24;50;70;110;160}*500+0.0001,5*MAX(0,AK5)*{0.6;2;4;5;6;7;9}%-10*{0;21;141;266;441;716;1516}),2) -> 0 | AM5: =AC5+AK5+AJ5 -> 9146.54 | AP5: =ROUND(AH5-AI5+AK5-AL5+AO5+AN5,2) -> 2540 | AQ5: 6 | AR5: 50372.48 | AS5: 231.42 | AT5: 18000 | AU5: 北京合杰
A6: 5 | B6: 202606 | C6: MNCN00238 | D6: 徐乐 | E6: 110222198702056027 | F6: 高级销售顾问 | G6: 北京 | H6: 2540 | I6: 42430 | K6: 7300 | N6: 1000 | O6: 4 | Q6: 13 | R6: =ROUND(K6/174*SUM(O6*1.5+P6*2+Q6*3),2) -> 1887.93 | V6: 1999.29 | AC6: =ROUND(SUM(SUM(K6:N6)+SUM(R6:AB6)),2) -> 12187.22 | AD6: 2187.68 | AE6: 549.92 | AF6: 136.73 | AG6: 3282 | AH6: =AC6-AD6-AE6-AF6-AG6 -> 6030.89 | AI6: =MAX(ROUND(MAX((AH6+AR6-5000*AQ6-AT6)*{0.03,0.1,0.2,0.25,0.3,0.35,0.45}-{0,2520,16920,31920,52920,85920,181920},0)-AS6,2),0) -> 265.87 | AL6: =ROUND(LOOKUP(MAX(0.0001,AK6/12),{0;6;24;50;70;110;160}*500+0.0001,5*MAX(0,AK6)*{0.6;2;4;5;6;7;9}%-10*{0;21;141;266;441;716;1516}),2) -> 0 | AM6: =AC6+AK6+AJ6 -> 12187.22 | AP6: =ROUND(AH6-AI6+AK6-AL6+AO6+AN6,2) -> 5765.02 | AQ6: 6 | AR6: 60687.03 | AS6: 885.92 | AT6: 0 | AU6: 北京合杰
A7: 6 | B7: 202606 | C7: MNCN00263 | D7: 刘星全 | E7: 37292519890401691X | F7: 销售顾问 | G7: 上海 | H7: 2740 | I7: 42473 | K7: 3800 | N7: 1000 | O7: 7.5 | Q7: 11.5 | R7: =ROUND(K7/174*SUM(O7*1.5+P7*2+Q7*3),2) -> 999.14 | V7: 6080.83 | AC7: =ROUND(SUM(SUM(K7:N7)+SUM(R7:AB7)),2) -> 11879.97 | AD7: 1171.98 | AE7: 293 | AF7: 73.25 | AG7: 1025 | AH7: =AC7-AD7-AE7-AF7-AG7 -> 9316.74 | AI7: =MAX(ROUND(MAX((AH7+AR7-5000*AQ7-AT7)*{0.03,0.1,0.2,0.25,0.3,0.35,0.45}-{0,2520,16920,31920,52920,85920,181920},0)-AS7,2),0) -> 0 | AL7: =ROUND(LOOKUP(MAX(0.0001,AK7/12),{0;6;24;50;70;110;160}*500+0.0001,5*MAX(0,AK7)*{0.6;2;4;5;6;7;9}%-10*{0;21;141;266;441;716;1516}),2) -> 0 | AM7: =AC7+AK7+AJ7 -> 11879.97 | AP7: =ROUND(AH7-AI7+AK7-AL7+AO7+AN7,2) -> 9316.74 | AQ7: 6 | AR7: 42215.24 | AS7: 192.23 | AT7: 27000 | AU7: 上海合杰
A8: 7 | B8: 202606 | C8: MNCN00281 | D8: 周华荣 | E8: 420822198801105563 | F8: 销售顾问 | G8: 天津 | H8: 2510 | I8: 42552 | K8: 4000 | N8: 900 | O8: 0 | Q8: 15.5 | R8: =ROUND(K8/174*SUM(O8*1.5+P8*2+Q8*3),2) -> 1068.97 | V8: 1254.9 | AC8: =ROUND(SUM(SUM(K8:N8)+SUM(R8:AB8)),2) -> 7223.87 | AD8: 597.12 | AE8: 170.28 | AF8: 37.32 | AG8: 873 | AH8: =AC8-AD8-AE8-AF8-AG8 -> 5546.15 | AI8: =MAX(ROUND(MAX((AH8+AR8-5000*AQ8-AT8)*{0.03,0.1,0.2,0.25,0.3,0.35,0.45}-{0,2520,16920,31920,52920,85920,181920},0)-AS8,2),0) -> 0 | AL8: =ROUND(LOOKUP(MAX(0.0001,AK8/12),{0;6;24;50;70;110;160}*500+0.0001,5*MAX(0,AK8)*{0.6;2;4;5;6;7;9}%-10*{0;21;141;266;441;716;1516}),2) -> 0 | AM8: =AC8+AK8+AJ8 -> 7223.87 | AP8: =ROUND(AH8-AI8+AK8-AL8+AO8+AN8,2) -> 5546.15 | AQ8: 6 | AR8: 25771.34 | AS8: 47.01 | AT8: 0 | AU8: 合杰区域分
A9: 8 | B9: 202606 | C9: MNCN00300 | D9: 李爱芳 | E9: 320981197710083482 | F9: 销售顾问 | G9: 苏州 | H9: 2660 | I9: 42721 | K9: 3600 | N9: 900 | O9: 0 | Q9: 20 | R9: =ROUND(K9/174*SUM(O9*1.5+P9*2+Q9*3),2) -> 1241.38 | V9: 3447.46 | W9: 1500 | AC9: =ROUND(SUM(SUM(K9:N9)+SUM(R9:AB9)),2) -> 10688.84 | AD9: 759.04 | AE9: 194.76 | AF9: 47.44 | AG9: 576.29 | AH9: =AC9-AD9-AE9-AF9-AG9 -> 9111.31 | AI9: =MAX(ROUND(MAX((AH9+AR9-5000*AQ9-AT9)*{0.03,0.1,0.2,0.25,0.3,0.35,0.45}-{0,2520,16920,31920,52920,85920,181920},0)-AS9,2),0) -> 141.75 | AL9: =ROUND(LOOKUP(MAX(0.0001,AK9/12),{0;6;24;50;70;110;160}*500+0.0001,5*MAX(0,AK9)*{0.6;2;4;5;6;7;9}%-10*{0;21;141;266;441;716;1516}),2) -> 0 | AM9: =AC9+AK9+AJ9 -> 10688.84 | AP9: =ROUND(AH9-AI9+AK9-AL9+AO9+AN9,2) -> 8969.56 | AQ9: 6 | AR9: 33121.89 | AS9: 225.25 | AT9: 0 | AU9: 上海合杰
A10: 9 | B10: 202606 | C10: MNCN00355 | D10: 程琪 | E10: 42010219880908082X | F10: 高级销售顾问 | G10: 武汉 | H10: 2400 | I10: 42963 | K10: 5000 | N10: 800 | O10: 0 | Q10: 11.5 | R10: =ROUND(K10/174*SUM(O10*1.5+P10*2+Q10*3),2) -> 991.38 | V10: 3208.9 | AC10: =ROUND(SUM(SUM(K10:N10)+SUM(R10:AB10)),2) -> 10000.28 | AD10: 933.28 | AE10: 240.32 | AF10: 35 | AG10: 933.29 | AH10: =AC10-AD10-AE10-AF10-AG10 -> 7858.39 | AI10: =MAX(ROUND(MAX((AH10+AR10-5000*AQ10-AT10)*{0.03,0.1,0.2,0.25,0.3,0.35,0.45}-{0,2520,16920,31920,52920,85920,181920},0)-AS10,2),0) -> 140.26 | AL10: =ROUND(LOOKUP(MAX(0.0001,AK10/12),{0;6;24;50;70;110;160}*500+0.0001,5*MAX(0,AK10)*{0.6;2;4;5;6;7;9}%-10*{0;21;141;266;441;716;1516}),2) -> 0 | AM10: =AC10+AK10+AJ10 -> 10000.28 | AP10: =ROUND(AH10-AI10+AK10-AL10+AO10+AN10,2) -> 7718.13 | AQ10: 6 | AR10: 29504.24 | AS10: 80.62 | AT10: 0 | AU10: 合杰区域分
A11: 10 | B11: 202606 | C11: MNCN00369 | D11: 秦懿 | E11: 310105198108060045 | F11: 高级销售顾问 | G11: 上海 | H11: 2740 | I11: 43017 | K11: 4600 | N11: 800 | O11: 11 | Q11: 11 | R11: =ROUND(K11/174*SUM(O11*1.5+P11*2+Q11*3),2) -> 1308.62 | V11: 385.9 | AC11: =ROUND(SUM(SUM(K11:N11)+SUM(R11:AB11)),2) -> 7094.52 | AD11: 784.25 | AE11: 196.06 | AF11: 49.02 | AG11: 686 | AH11: =AC11-AD11-AE11-AF11-AG11 -> 5379.19 | AI11: =MAX(ROUND(MAX((AH11+AR11-5000*AQ11-AT11)*{0.03,0.1,0.2,0.25,0.3,0.35,0.45}-{0,2520,16920,31920,52920,85920,181920},0)-AS11,2),0) -> 0 | AL11: =ROUND(LOOKUP(MAX(0.0001,AK11/12),{0;6;24;50;70;110;160}*500+0.0001,5*MAX(0,AK11)*{0.6;2;4;5;6;7;9}%-10*{0;21;141;266;441;716;1516}),2) -> 0 | AM11: =AC11+AK11+AJ11 -> 7094.52 | AP11: =ROUND(AH11-AI11+AK11-AL11+AO11+AN11,2) -> 5379.19 | AQ11: 6 | AR11: 38053.44 | AS11: 276.67 | AT11: 18000 | AU11: 上海合杰
A12: 11 | B12: 202606 | C12: MNCN00381 | D12: 贾锐 | E12: 510104198710260016 | F12: 销售顾问 | G12: 成都 | H12: 2330 | I12: 43103 | K12: 3600 | N12: 800 | O12: 8 | Q12: 16 | R12: =ROUND(K12/174*SUM(O12*1.5+P12*2+Q12*3),2) -> 1241.38 | V12: 718.53 | W12: 1500 | AC12: =ROUND(SUM(SUM(K12:N12)+SUM(R12:AB12)),2) -> 7859.91 | AD12: 765.6 | AE12: 191.4 | AF12: 38.28 | AG12: 639 | AH12: =AC12-AD12-AE12-AF12-AG12 -> 6225.63 | AI12: =MAX(ROUND(MAX((AH12+AR12-5000*AQ12-AT12)*{0.03,0.1,0.2,0.25,0.3,0.35,0.45}-{0,2520,16920,31920,52920,85920,181920},0)-AS12,2),0) -> 72.26 | AL12: =ROUND(LOOKUP(MAX(0.0001,AK12/12),{0;6;24;50;70;110;160}*500+0.0001,5*MAX(0,AK12)*{0.6;2;4;5;6;7;9}%-10*{0;21;141;266;441;716;1516}),2) -> 0 | AM12: =AC12+AK12+AJ12 -> 7859.91 | AP12: =ROUND(AH12-AI12+AK12-AL12+AO12+AN12,2) -> 6153.37 | AQ12: 6 | AR12: 31788.12 | AS12: 168.15 | AT12: 0 | AU12: 成都合杰
A13: 12 | B13: 202606 | C13: MNCN00390 | D13: 周之绮 | E13: 310107198302217221 | F13: 销售顾问 | G13: 上海 | H13: 2740 | I13: 43136 | K13: 3800 | N13: 800 | O13: 6.5 | Q13: 11.5 | R13: =ROUND(K13/174*SUM(O13*1.5+P13*2+Q13*3),2) -> 966.38 | V13: 11809.55 | AC13: =ROUND(SUM(SUM(K13:N13)+SUM(R13:AB13)),2) -> 17375.93 | AD13: 1405.78 | AE13: 351.45 | AF13: 87.86 | AG13: 1230 | AH13: =AC13-AD13-AE13-AF13-AG13 -> 14300.84 | AI13: =MAX(ROUND(MAX((AH13+AR13-5000*AQ13-AT13)*{0.03,0.1,0.2,0.25,0.3,0.35,0.45}-{0,2520,16920,31920,52920,85920,181920},0)-AS13,2),0) -> 6.96 | AL13: =ROUND(LOOKUP(MAX(0.0001,AK13/12),{0;6;24;50;70;110;160}*500+0.0001,5*MAX(0,AK13)*{0.6;2;4;5;6;7;9}%-10*{0;21;141;266;441;716;1516}),2) -> 0 | AM13: =AC13+AK13+AJ13 -> 17375.93 | AP13: =ROUND(AH13-AI13+AK13-AL13+AO13+AN13,2) -> 14293.88 | AQ13: 6 | AR13: 48857.89 | AS13: 447.8 | AT13: 18000 | AU13: 上海合杰
A14: 13 | B14: 202606 | C14: MNCN00391 | D14: 卢晓香 | E14: 422324198009156823 | F14: 高级销售顾问 | G14: 上海 | H14: 2740 | I14: 43138 | K14: 4600 | N14: 800 | O14: 0 | Q14: 10 | R14: =ROUND(K14/174*SUM(O14*1.5+P14*2+Q14*3),2) -> 793.1 | V14: 1682.67 | AC14: =ROUND(SUM(SUM(K14:N14)+SUM(R14:AB14)),2) -> 7875.77 | AD14: 893.39 | AE14: 223.35 | AF14: 55.84 | AG14: 782 | AH14: =AC14-AD14-AE14-AF14-AG14 -> 5921.19 | AI14: =MAX(ROUND(MAX((AH14+AR14-5000*AQ14-AT14)*{0.03,0.1,0.2,0.25,0.3,0.35,0.45}-{0,2520,16920,31920,52920,85920,181920},0)-AS14,2),0) -> 0 | AL14: =ROUND(LOOKUP(MAX(0.0001,AK14/12),{0;6;24;50;70;110;160}*500+0.0001,5*MAX(0,AK14)*{0.6;2;4;5;6;7;9}%-10*{0;21;141;266;441;716;1516}),2) -> 0 | AM14: =AC14+AK14+AJ14 -> 7875.77 | AP14: =ROUND(AH14-AI14+AK14-AL14+AO14+AN14,2) -> 5921.19 | AQ14: 6 | AR14: 37345.62 | AS14: 115.66 | AT14: 15000 | AU14: 上海合杰
A15: 14 | B15: 202606 | C15: MNCN00399 | D15: 李旻天 | E15: 310107198503120944 | F15: 资深销售主管 | G15: 上海 | H15: 2740 | I15: 43189 | K15: 7800 | N15: 800 | O15: 0 | Q15: 9 | R15: =ROUND(K15/174*SUM(O15*1.5+P15*2+Q15*3),2) -> 1210.34 | V15: 4936.8 | AC15: =ROUND(SUM(SUM(K15:N15)+SUM(R15:AB15)),2) -> 14747.14 | AD15: 1288.96 | AE15: 322.24 | AF15: 80.56 | AG15: 1128 | AH15: =AC15-AD15-AE15-AF15-AG15 -> 11927.38 | AI15: =MAX(ROUND(MAX((AH15+AR15-5000*AQ15-AT15)*{0.03,0.1,0.2,0.25,0.3,0.35,0.45}-{0,2520,16920,31920,52920,85920,181920},0)-AS15,2),0) -> 269.5 | AL15: =ROUND(LOOKUP(MAX(0.0001,AK15/12),{0;6;24;50;70;110;160}*500+0.0001,5*MAX(0,AK15)*{0.6;2;4;5;6;7;9}%-10*{0;21;141;266;441;716;1516}),2) -> 0 | AM15: =AC15+AK15+AJ15 -> 14747.14 | AP15: =ROUND(AH15-AI15+AK15-AL15+AO15+AN15,2) -> 11657.88 | AQ15: 6 | AR15: 73031.01 | AS15: 906.34 | AT15: 18000 | AU15: 上海合杰
A16: 15 | B16: 202606 | C16: MNCN00400 | D16: 胡伟 | E16: 513029198606282471 | F16: 销售顾问 | G16: 重庆 | H16: 2330 | I16: 43199 | K16: 4000 | N16: 800 | O16: 0 | Q16: 11 | R16: =ROUND(K16/174*SUM(O16*1.5+P16*2+Q16*3),2) -> 758.62 | V16: 400.38 | AC16: =ROUND(SUM(SUM(K16:N16)+SUM(R16:AB16)),2) -> 5959 | AD16: 719.52 | AE16: 184.88 | AF16: 44.97 | AG16: 498 | AH16: =AC16-AD16-AE16-AF16-AG16 -> 4511.63 | AI16: =MAX(ROUND(MAX((AH16+AR16-5000*AQ16-AT16)*{0.03,0.1,0.2,0.25,0.3,0.35,0.45}-{0,2520,16920,31920,52920,85920,181920},0)-AS16,2),0) -> 0 | AL16: =ROUND(LOOKUP(MAX(0.0001,AK16/12),{0;6;24;50;70;110;160}*500+0.0001,5*MAX(0,AK16)*{0.6;2;4;5;6;7;9}%-10*{0;21;141;266;441;716;1516}),2) -> 0 | AM16: =AC16+AK16+AJ16 -> 5959 | AP16: =ROUND(AH16-AI16+AK16-AL16+AO16+AN16,2) -> 4511.63 | AQ16: 6 | AR16: 34298.4 | AS16: 277.93 | AT16: 27000 | AU16: 合杰区域分
A17: 16 | B17: 202606 | C17: MNCN00412 | D17: 王李赫 | E17: 610102198811072314 | F17: 销售主管 | G17: 西安 | H17: 2376 | I17: 43224 | K17: 7800 | N17: 800 | O17: 0 | Q17: 0 | R17: =ROUND(K17/174*SUM(O17*1.5+P17*2+Q17*3),2) -> 0 | V17: 4042.97 | AC17: =ROUND(SUM(SUM(K17:N17)+SUM(R17:AB17)),2) -> 12642.97 | AD17: 1192.97 | AE17: 299.84 | AF17: 44.74 | AG17: 855 | AH17: =AC17-AD17-AE17-AF17-AG17 -> 10250.42 | AI17: =MAX(ROUND(MAX((AH17+AR17-5000*AQ17-AT17)*{0.03,0.1,0.2,0.25,0.3,0.35,0.45}-{0,2520,16920,31920,52920,85920,181920},0)-AS17,2),0) -> 48.06 | AL17: =ROUND(LOOKUP(MAX(0.0001,AK17/12),{0;6;24;50;70;110;160}*500+0.0001,5*MAX(0,AK17)*{0.6;2;4;5;6;7;9}%-10*{0;21;141;266;441;716;1516}),2) -> 0 | AM17: =AC17+AK17+AJ17 -> 12642.97 | AP17: =ROUND(AH17-AI17+AK17-AL17+AO17+AN17,2) -> 10202.36 | AQ17: 6 | AR17: 58109.85 | AS17: 22.75 | AT17: 36000 | AU17: 合杰区域分
A18: 17 | B18: 202606 | C18: MNCN00414 | D18: 陆立琴 | E18: 320924198001065721 | F18: 销售顾问 | G18: 上海 | H18: 2740 | I18: 43236 | K18: 3800 | N18: 800 | O18: 3 | Q18: 11 | R18: =ROUND(K18/174*SUM(O18*1.5+P18*2+Q18*3),2) -> 818.97 | V18: 1398.34 | AC18: =ROUND(SUM(SUM(K18:N18)+SUM(R18:AB18)),2) -> 6817.31 | AD18: 596.8 | AE18: 149.2 | AF18: 37.3 | AG18: 518 | AH18: =AC18-AD18-AE18-AF18-AG18 -> 5516.01 | AI18: =MAX(ROUND(MAX((AH18+AR18-5000*AQ18-AT18)*{0.03,0.1,0.2,0.25,0.3,0.35,0.45}-{0,2520,16920,31920,52920,85920,181920},0)-AS18,2),0) -> 0 | AL18: =ROUND(LOOKUP(MAX(0.0001,AK18/12),{0;6;24;50;70;110;160}*500+0.0001,5*MAX(0,AK18)*{0.6;2;4;5;6;7;9}%-10*{0;21;141;266;441;716;1516}),2) -> 0 | AM18: =AC18+AK18+AJ18 -> 6817.31 | AP18: =ROUND(AH18-AI18+AK18-AL18+AO18+AN18,2) -> 5516.01 | AQ18: 6 | AR18: 28188.33 | AS18: 184.52 | AT18: 0 | AU18: 上海合杰
A19: 18 | B19: 202606 | C19: MNCN00424 | D19: 王平 | E19: 610424199508080038 | F19: 销售顾问 | G19: 西安 | H19: 2376 | I19: 43244 | K19: 4000 | N19: 800 | O19: 0 | Q19: 0 | R19: =ROUND(K19/174*SUM(O19*1.5+P19*2+Q19*3),2) -> 0 | V19: 1730.26 | AC19: =ROUND(SUM(SUM(K19:N19)+SUM(R19:AB19)),2) -> 6530.26 | AD19: 769.32 | AE19: 193.93 | AF19: 28.85 | AG19: 578 | AH19: =AC19-AD19-AE19-AF19-AG19 -> 4960.16 | AI19: =MAX(ROUND(MAX((AH19+AR19-5000*AQ19-AT19)*{0.03,0.1,0.2,0.25,0.3,0.35,0.45}-{0,2520,16920,31920,52920,85920,181920},0)-AS19,2),0) -> 45.91 | AL19: =ROUND(LOOKUP(MAX(0.0001,AK19/12),{0;6;24;50;70;110;160}*500+0.0001,5*MAX(0,AK19)*{0.6;2;4;5;6;7;9}%-10*{0;21;141;266;441;716;1516}),2) -> 0 | AM19: =AC19+AK19+AJ19 -> 6530.26 | AP19: =ROUND(AH19-AI19+AK19-AL19+AO19+AN19,2) -> 4914.25 | AQ19: 6 | AR19: 32518.8 | AS19: 178.46 | AT19: 0 | AU19: 合杰区域分
A20: 19 | B20: 202606 | C20: MNCN00444 | D20: 祝荣丹 | E20: 440923199101235762 | F20: 销售顾问 | G20: 广州 | H20: 2500 | I20: 43359 | K20: 4200 | N20: 700 | O20: 0 | Q20: 16 | R20: =ROUND(K20/174*SUM(O20*1.5+P20*2+Q20*3),2) -> 1158.62 | V20: 13.98 | AC20: =ROUND(SUM(SUM(K20:N20)+SUM(R20:AB20)),2) -> 6072.6 | AD20: 754.88 | AE20: 188.72 | AF20: 18.87 | AG20: 661 | AH20: =AC20-AD20-AE20-AF20-AG20 -> 4449.13 | AI20: =MAX(ROUND(MAX((AH20+AR20-5000*AQ20-AT20)*{0.03,0.1,0.2,0.25,0.3,0.35,0.45}-{0,2520,16920,31920,52920,85920,181920},0)-AS20,2),0) -> 0 | AL20: =ROUND(LOOKUP(MAX(0.0001,AK20/12),{0;6;24;50;70;110;160}*500+0.0001,5*MAX(0,AK20)*{0.6;2;4;5;6;7;9}%-10*{0;21;141;266;441;716;1516}),2) -> 0 | AM20: =AC20+AK20+AJ20 -> 6072.6 | AP20: =ROUND(AH20-AI20+AK20-AL20+AO20+AN20,2) -> 4449.13 | AQ20: 6 | AR20: 35228.93 | AS20: 314.67 | AT20: 0 | AU20: 合杰区域分
A21: 20 | B21: 202606 | C21: MNCN00447 | D21: 刘明杰 | E21: 500108199010022613 | F21: 资深销售主管 | G21: 重庆 | H21: 2330 | I21: 43360 | K21: 7900 | N21: 700 | O21: 33 | Q21: 16 | R21: =ROUND(K21/174*SUM(O21*1.5+P21*2+Q21*3),2) -> 4426.72 | V21: 66.7 | AC21: =ROUND(SUM(SUM(K21:N21)+SUM(R21:AB21)),2) -> 13093.42 | AD21: 1363.84 | AE21: 345.96 | AF21: 85.24 | AG21: 924 | AH21: =AC21-AD21-AE21-AF21-AG21 -> 10374.38 | AI21: =MAX(ROUND(MAX((AH21+AR21-5000*AQ21-AT21)*{0.03,0.1,0.2,0.25,0.3,0.35,0.45}-{0,2520,16920,31920,52920,85920,181920},0)-AS21,2),0) -> 809.34 | AL21: =ROUND(LOOKUP(MAX(0.0001,AK21/12),{0;6;24;50;70;110;160}*500+0.0001,5*MAX(0,AK21)*{0.6;2;4;5;6;7;9}%-10*{0;21;141;266;441;716;1516}),2) -> 0 | AM21: =AC21+AK21+AJ21 -> 13093.42 | AP21: =ROUND(AH21-AI21+AK21-AL21+AO21+AN21,2) -> 9565.04 | AQ21: 6 | AR21: 65262.66 | AS21: 1234.36 | AT21: 0 | AU21: 合杰区域分
A22: 21 | B22: 202606 | C22: MNCN00448 | D22: 王译 | E22: 500109199008271924 | F22: 销售顾问 | G22: 重庆 | H22: 2330 | I22: 43360 | K22: 3600 | N22: 700 | O22: 0 | Q22: 11 | R22: =ROUND(K22/174*SUM(O22*1.5+P22*2+Q22*3),2) -> 682.76 | AC22: =ROUND(SUM(SUM(K22:N22)+SUM(R22:AB22)),2) -> 4982.76 | AD22: 478.48 | AE22: 124.62 | AF22: 29.91 | AG22: 377 | AH22: =AC22-AD22-AE22-AF22-AG22 -> 3972.75 | AI22: =MAX(ROUND(MAX((AH22+AR22-5000*AQ22-AT22)*{0.03,0.1,0.2,0.25,0.3,0.35,0.45}-{0,2520,16920,31920,52920,85920,181920},0)-AS22,2),0) -> 0 | AL22: =ROUND(LOOKUP(MAX(0.0001,AK22/12),{0;6;24;50;70;110;160}*500+0.0001,5*MAX(0,AK22)*{0.6;2;4;5;6;7;9}%-10*{0;21;141;266;441;716;1516}),2) -> 0 | AM22: =AC22+AK22+AJ22 -> 4982.76 | AP22: =ROUND(AH22-AI22+AK22-AL22+AO22+AN22,2) -> 3972.75 | AQ22: 6 | AR22: 23913.74 | AS22: 84.65 | AT22: 0 | AU22: 合杰区域分
A23: 22 | B23: 202606 | C23: MNCN00445 | D23: 孙亮 | E23: 370205198604191016 | F23: 资深销售主管 | G23: 青岛 | H23: 2400 | I23: 43360 | K23: 8800 | N23: 700 | O23: 4 | Q23: 13 | R23: =ROUND(K23/174*SUM(O23*1.5+P23*2+Q23*3),2) -> 2275.86 | V23: 1186.52 | AC23: =ROUND(SUM(SUM(K23:N23)+SUM(R23:AB23)),2) -> 12962.38 | AD23: 1163.2 | AE23: 290.8 | AF23: 43.62 | AG23: 759 | AH23: =AC23-AD23-AE23-AF23-AG23 -> 10705.76 | AI23: =MAX(ROUND(MAX((AH23+AR23-5000*AQ23-AT23)*{0.03,0.1,0.2,0.25,0.3,0.35,0.45}-{0,2520,16920,31920,52920,85920,181920},0)-AS23,2),0) -> 39.77 | AL23: =ROUND(LOOKUP(MAX(0.0001,AK23/12),{0;6;24;50;70;110;160}*500+0.0001,5*MAX(0,AK23)*{0.6;2;4;5;6;7;9}%-10*{0;21;141;266;441;716;1516}),2) -> 0 | AM23: =AC23+AK23+AJ23 -> 12962.38 | AP23: =ROUND(AH23-AI23+AK23-AL23+AO23+AN23,2) -> 10665.99 | AQ23: 6 | AR23: 61445.77 | AS23: 324.78 | AT23: 30000 | AU23: 合杰区域分
A24: 23 | B24: 202606 | C24: MNCN00446 | D24: 胡蔷薇 | E24: 420921198704155525 | F24: 高级销售顾问 | G24: 青岛 | H24: 2400 | I24: 43360 | K24: 4400 | N24: 700 | O24: 0 | Q24: 13 | R24: =ROUND(K24/174*SUM(O24*1.5+P24*2+Q24*3),2) -> 986.21 | V24: 4701.38 | AC24: =ROUND(SUM(SUM(K24:N24)+SUM(R24:AB24)),2) -> 10787.59 | AD24: 800.56 | AE24: 200.14 | AF24: 30.02 | AG24: 558 | AH24: =AC24-AD24-AE24-AF24-AG24 -> 9198.87 | AI24: =MAX(ROUND(MAX((AH24+AR24-5000*AQ24-AT24)*{0.03,0.1,0.2,0.25,0.3,0.35,0.45}-{0,2520,16920,31920,52920,85920,181920},0)-AS24,2),0) -> 0 | AL24: =ROUND(LOOKUP(MAX(0.0001,AK24/12),{0;6;24;50;70;110;160}*500+0.0001,5*MAX(0,AK24)*{0.6;2;4;5;6;7;9}%-10*{0;21;141;266;441;716;1516}),2) -> 0 | AM24: =AC24+AK24+AJ24 -> 10787.59 | AP24: =ROUND(AH24-AI24+AK24-AL24+AO24+AN24,2) -> 9198.87 | AQ24: 6 | AR24: 40918.77 | AS24: 172.26 | AT24: 15000 | AU24: 合杰区域分
A25: 24 | B25: 202606 | C25: MNCN00450 | D25: 沈鸿鹏 | E25: 220284198807302313 | F25: 销售顾问 | G25: 青岛 | H25: 2400 | I25: 43372 | K25: 4000 | N25: 700 | O25: 0 | Q25: 13 | R25: =ROUND(K25/174*SUM(O25*1.5+P25*2+Q25*3),2) -> 896.55 | V25: 1153.13 | AC25: =ROUND(SUM(SUM(K25:N25)+SUM(R25:AB25)),2) -> 6749.68 | AD25: 813.84 | AE25: 203.46 | AF25: 30.52 | AG25: 502 | AH25: =AC25-AD25-AE25-AF25-AG25 -> 5199.86 | AI25: =MAX(ROUND(MAX((AH25+AR25-5000*AQ25-AT25)*{0.03,0.1,0.2,0.25,0.3,0.35,0.45}-{0,2520,16920,31920,52920,85920,181920},0)-AS25,2),0) -> 0 | AL25: =ROUND(LOOKUP(MAX(0.0001,AK25/12),{0;6;24;50;70;110;160}*500+0.0001,5*MAX(0,AK25)*{0.6;2;4;5;6;7;9}%-10*{0;21;141;266;441;716;1516}),2) -> 0 | AM25: =AC25+AK25+AJ25 -> 6749.68 | AP25: =ROUND(AH25-AI25+AK25-AL25+AO25+AN25,2) -> 5199.86 | AQ25: 6 | AR25: 34362.27 | AS25: 94.55 | AT25: 18000 | AU25: 合杰区域分
A26: 25 | B26: 202606 | C26: MNCN00452 | D26: 张洁 | E26: 320106198205172442 | F26: 销售顾问 | G26: 南京 | H26: 2660 | I26: 43382 | K26: 3600 | N26: 700 | O26: 0 | Q26: 8.5 | R26: =ROUND(K26/174*SUM(O26*1.5+P26*2+Q26*3),2) -> 527.59 | V26: 4359.37 | AC26: =ROUND(SUM(SUM(K26:N26)+SUM(R26:AB26)),2) -> 9186.96 | AD26: 1153.6 | AE26: 298.4 | AF26: 72.1 | AG26: 1613 | AH26: =AC26-AD26-AE26-AF26-AG26 -> 6049.86 | AI26: =MAX(ROUND(MAX((AH26+AR26-5000*AQ26-AT26)*{0.03,0.1,0.2,0.25,0.3,0.35,0.45}-{0,2520,16920,31920,52920,85920,181920},0)-AS26,2),0) -> 0 | AL26: =ROUND(LOOKUP(MAX(0.0001,AK26/12),{0;6;24;50;70;110;160}*500+0.0001,5*MAX(0,AK26)*{0.6;2;4;5;6;7;9}%-10*{0;21;141;266;441;716;1516}),2) -> 0 | AM26: =AC26+AK26+AJ26 -> 9186.96 | AP26: =ROUND(AH26-AI26+AK26-AL26+AO26+AN26,2) -> 6049.86 | AQ26: 6 | AR26: 43757.2 | AS26: 413.88 | AT26: 21000 | AU26: 上海合杰
A27: 26 | B27: 202606 | C27: MNCN00459 | D27: 王广春 | E27: 320922199702083617 | F27: 销售顾问 | G27: 南京 | H27: 2660 | I27: 43524 | K27: 3600 | N27: 700 | O27: 0 | Q27: 16.5 | R27: =ROUND(K27/174*SUM(O27*1.5+P27*2+Q27*3),2) -> 1024.14 | V27: 19786.79 | AC27: =ROUND(SUM(SUM(K27:N27)+SUM(R27:AB27)),2) -> 25110.93 | AD27: 1233.44 | AE27: 318.36 | AF27: 77.09 | AG27: 1929 | AH27: =AC27-AD27-AE27-AF27-AG27 -> 21553.04 | AI27: =MAX(ROUND(MAX((AH27+AR27-5000*AQ27-AT27)*{0.03,0.1,0.2,0.25,0.3,0.35,0.45}-{0,2520,16920,31920,52920,85920,181920},0)-AS27,2),0) -> 324.64 | AL27: =ROUND(LOOKUP(MAX(0.0001,AK27/12),{0;6;24;50;70;110;160}*500+0.0001,5*MAX(0,AK27)*{0.6;2;4;5;6;7;9}%-10*{0;21;141;266;441;716;1516}),2) -> 0 | AM27: =AC27+AK27+AJ27 -> 25110.93 | AP27: =ROUND(AH27-AI27+AK27-AL27+AO27+AN27,2) -> 21228.4 | AQ27: 6 | AR27: 50537 | AS27: 398.06 | AT27: 18000 | AU27: 上海合杰
A28: 27 | B28: 202606 | C28: MNCN00461 | D28: 吕静雯 | E28: 130181198905025229 | F28: 高级销售顾问 | G28: 北京 | H28: 2540 | I28: 43542 | K28: 4600 | N28: 700 | O28: 0 | Q28: 12 | R28: =ROUND(K28/174*SUM(O28*1.5+P28*2+Q28*3),2) -> 951.72 | V28: 5079.65 | AC28: =ROUND(SUM(SUM(K28:N28)+SUM(R28:AB28)),2) -> 11331.37 | AD28: 2374.24 | AE28: 596.56 | AF28: 148.39 | AG28: 3561 | AH28: =AC28-AD28-AE28-AF28-AG28 -> 4651.18 | AI28: =MAX(ROUND(MAX((AH28+AR28-5000*AQ28-AT28)*{0.03,0.1,0.2,0.25,0.3,0.35,0.45}-{0,2520,16920,31920,52920,85920,181920},0)-AS28,2),0) -> 340.66 | AL28: =ROUND(LOOKUP(MAX(0.0001,AK28/12),{0;6;24;50;70;110;160}*500+0.0001,5*MAX(0,AK28)*{0.6;2;4;5;6;7;9}%-10*{0;21;141;266;441;716;1516}),2) -> 0 | AM28: =AC28+AK28+AJ28 -> 11331.37 | AP28: =ROUND(AH28-AI28+AK28-AL28+AO28+AN28,2) -> 4310.52 | AQ28: 6 | AR28: 63501.95 | AS28: 954.65 | AT28: 0 | AU28: 北京合杰
A29: 28 | B29: 202606 | C29: MNCN00477 | D29: 王雪娇 | E29: 340823198402105888 | F29: 销售顾问 | G29: 张家港 | H29: 2660 | I29: 43689 | K29: 4000 | N29: 600 | O29: 40 | Q29: 24 | R29: =ROUND(K29/174*SUM(O29*1.5+P29*2+Q29*3),2) -> 3034.48 | V29: 1794.38 | AC29: =ROUND(SUM(SUM(K29:N29)+SUM(R29:AB29)),2) -> 9428.86 | AD29: 1700.24 | AE29: 430.06 | AF29: 106.27 | AG29: 1994 | AH29: =AC29-AD29-AE29-AF29-AG29 -> 5198.29 | AI29: =MAX(ROUND(MAX((AH29+AR29-5000*AQ29-AT29)*{0.03,0.1,0.2,0.25,0.3,0.35,0.45}-{0,2520,16920,31920,52920,85920,181920},0)-AS29,2),0) -> 132.87 | AL29: =ROUND(LOOKUP(MAX(0.0001,AK29/12),{0;6;24;50;70;110;160}*500+0.0001,5*MAX(0,AK29)*{0.6;2;4;5;6;7;9}%-10*{0;21;141;266;441;716;1516}),2) -> 0 | AM29: =AC29+AK29+AJ29 -> 9428.86 | AP29: =ROUND(AH29-AI29+AK29-AL29+AO29+AN29,2) -> 5065.42 | AQ29: 6 | AR29: 53801.9 | AS29: 737.14 | AT29: 0 | AU29: 上海合杰
A30: 29 | B30: 202606 | C30: MNCN00478 | D30: 赵徐 | E30: 340421198706282854 | F30: 销售顾问 | G30: 张家港 | H30: 2660 | I30: 43690 | K30: 4000 | N30: 600 | O30: 40 | Q30: 24 | R30: =ROUND(K30/174*SUM(O30*1.5+P30*2+Q30*3),2) -> 3034.48 | V30: 3601.52 | AC30: =ROUND(SUM(SUM(K30:N30)+SUM(R30:AB30)),2) -> 11236 | AD30: 1969.52 | AE30: 497.38 | AF30: 123.1 | AG30: 2122 | AH30: =AC30-AD30-AE30-AF30-AG30 -> 6524 | AI30: =MAX(ROUND(MAX((AH30+AR30-5000*AQ30-AT30)*{0.03,0.1,0.2,0.25,0.3,0.35,0.45}-{0,2520,16920,31920,52920,85920,181920},0)-AS30,2),0) -> 623.6 | AL30: =ROUND(LOOKUP(MAX(0.0001,AK30/12),{0;6;24;50;70;110;160}*500+0.0001,5*MAX(0,AK30)*{0.6;2;4;5;6;7;9}%-10*{0;21;141;266;441;716;1516}),2) -> 0 | AM30: =AC30+AK30+AJ30 -> 11236 | AP30: =ROUND(AH30-AI30+AK30-AL30+AO30+AN30,2) -> 5900.4 | AQ30: 6 | AR30: 65756.18 | AS30: 1084.42 | AT30: 0 | AU30: 上海合杰
A31: 30 | B31: 202606 | C31: MNCN00479 | D31: 郭思玉 | E31: 622827199610250384 | F31: 高级销售顾问 | G31: 西安 | H31: 2376 | I31: 43697 | K31: 4400 | N31: 600 | O31: 0 | Q31: 0 | R31: =ROUND(K31/174*SUM(O31*1.5+P31*2+Q31*3),2) -> 0 | V31: 4402.64 | AC31: =ROUND(SUM(SUM(K31:N31)+SUM(R31:AB31)),2) -> 9402.64 | AD31: 927.33 | AE31: 233.43 | AF31: 34.77 | AG31: 564 | AH31: =AC31-AD31-AE31-AF31-AG31 -> 7643.11 | AI31: =MAX(ROUND(MAX((AH31+AR31-5000*AQ31-AT31)*{0.03,0.1,0.2,0.25,0.3,0.35,0.45}-{0,2520,16920,31920,52920,85920,181920},0)-AS31,2),0) -> 132.08 | AL31: =ROUND(LOOKUP(MAX(0.0001,AK31/12),{0;6;24;50;70;110;160}*500+0.0001,5*MAX(0,AK31)*{0.6;2;4;5;6;7;9}%-10*{0;21;141;266;441;716;1516}),2) -> 0 | AM31: =AC31+AK31+AJ31 -> 9402.64 | AP31: =ROUND(AH31-AI31+AK31-AL31+AO31+AN31,2) -> 7511.03 | AQ31: 6 | AR31: 47465.4 | AS31: 621.18 | AT31: 0 | AU31: 合杰区域分
A32: 31 | B32: 202606 | C32: MNCN00480 | D32: 葛梦影 | E32: 320283199108137568 | F32: 前台 | G32: 上海 | H32: 2740 | I32: 43697 | K32: 6000 | O32: 0 | Q32: 0 | R32: =ROUND(K32/174*SUM(O32*1.5+P32*2+Q32*3),2) -> 0 | AC32: =ROUND(SUM(SUM(K32:N32)+SUM(R32:AB32)),2) -> 6000 | AD32: 596.8 | AE32: 149.2 | AF32: 37.3 | AG32: 473 | AH32: =AC32-AD32-AE32-AF32-AG32 -> 4743.7 | AI32: =MAX(ROUND(MAX((AH32+AR32-5000*AQ32-AT32)*{0.03,0.1,0.2,0.25,0.3,0.35,0.45}-{0,2520,16920,31920,52920,85920,181920},0)-AS32,2),0) -> 6.93 | AL32: =ROUND(LOOKUP(MAX(0.0001,AK32/12),{0;6;24;50;70;110;160}*500+0.0001,5*MAX(0,AK32)*{0.6;2;4;5;6;7;9}%-10*{0;21;141;266;441;716;1516}),2) -> 0 | AM32: =AC32+AK32+AJ32 -> 6000 | AP32: =ROUND(AH32-AI32+AK32-AL32+AO32+AN32,2) -> 4736.77 | AQ32: 6 | AR32: 28031.91 | AS32: 76.34 | AT32: 0 | AU32: 上海合杰
A33: 32 | B33: 202606 | C33: MNCN00488 | D33: 聂贝 | E33: 430221199003075221 | F33: 销售顾问 | G33: 上海 | H33: 2740 | I33: 43728 | K33: 4200 | N33: 600 | O33: 7.5 | Q33: 13 | R33: =ROUND(K33/174*SUM(O33*1.5+P33*2+Q33*3),2) -> 1212.93 | V33: 7.74 | Z33: -362.36 | AC33: =ROUND(SUM(SUM(K33:N33)+SUM(R33:AB33)),2) -> 5658.31 | AD33: 779.72 | AE33: 194.93 | AF33: 48.73 | AG33: 682 | AH33: =AC33-AD33-AE33-AF33-AG33 -> 3952.93 | AI33: =MAX(ROUND(MAX((AH33+AR33-5000*AQ33-AT33)*{0.03,0.1,0.2,0.25,0.3,0.35,0.45}-{0,2520,16920,31920,52920,85920,181920},0)-AS33,2),0) -> 0 | AL33: =ROUND(LOOKUP(MAX(0.0001,AK33/12),{0;6;24;50;70;110;160}*500+0.0001,5*MAX(0,AK33)*{0.6;2;4;5;6;7;9}%-10*{0;21;141;266;441;716;1516}),2) -> 0 | AM33: =AC33+AK33+AJ33 -> 5658.31 | AP33: =ROUND(AH33-AI33+AK33-AL33+AO33+AN33,2) -> 3952.93 | AQ33: 6 | AR33: 19634 | AS33: 0 | AT33: 27000 | AU33: 上海合杰
A34: 33 | B34: 202606 | C34: MNCN00490 | D34: 黄炳金 | E34: 45042119951105101X | F34: 销售顾问 | G34: 佛山 | H34: 2080 | I34: 43747 | K34: 4000 | N34: 600 | O34: 3 | Q34: 16 | R34: =ROUND(K34/174*SUM(O34*1.5+P34*2+Q34*3),2) -> 1206.9 | V34: 525 | AC34: =ROUND(SUM(SUM(K34:N34)+SUM(R34:AB34)),2) -> 6331.9 | AD34: 654.56 | AE34: 163.64 | AF34: 16.36 | AG34: 409 | AH34: =AC34-AD34-AE34-AF34-AG34 -> 5088.34 | AI34: =MAX(ROUND(MAX((AH34+AR34-5000*AQ34-AT34)*{0.03,0.1,0.2,0.25,0.3,0.35,0.45}-{0,2520,16920,31920,52920,85920,181920},0)-AS34,2),0) -> 0 | AL34: =ROUND(LOOKUP(MAX(0.0001,AK34/12),{0;6;24;50;70;110;160}*500+0.0001,5*MAX(0,AK34)*{0.6;2;4;5;6;7;9}%-10*{0;21;141;266;441;716;1516}),2) -> 0 | AM34: =AC34+AK34+AJ34 -> 6331.9 | AP34: =ROUND(AH34-AI34+AK34-AL34+AO34+AN34,2) -> 5088.34 | AQ34: 6 | AR34: 35555.52 | AS34: 135.82 | AT34: 18000 | AU34: 上海合杰
A35: 34 | B35: 202606 | C35: MNCN00491 | D35: 张露文 | E35: 441283199312171024 | F35: 销售顾问 | G35: 佛山 | H35: 2080 | I35: 43751 | K35: 4000 | N35: 600 | O35: 0 | Q35: 16 | R35: =ROUND(K35/174*SUM(O35*1.5+P35*2+Q35*3),2) -> 1103.45 | AC35: =ROUND(SUM(SUM(K35:N35)+SUM(R35:AB35)),2) -> 5703.45 | AD35: 623.04 | AE35: 155.76 | AF35: 15.58 | AG35: 389 | AH35: =AC35-AD35-AE35-AF35-AG35 -> 4520.07 | AI35: =MAX(ROUND(MAX((AH35+AR35-5000*AQ35-AT35)*{0.03,0.1,0.2,0.25,0.3,0.35,0.45}-{0,2520,16920,31920,52920,85920,181920},0)-AS35,2),0) -> 6.76 | AL35: =ROUND(LOOKUP(MAX(0.0001,AK35/12),{0;6;24;50;70;110;160}*500+0.0001,5*MAX(0,AK35)*{0.6;2;4;5;6;7;9}%-10*{0;21;141;266;441;716;1516}),2) -> 0 | AM35: =AC35+AK35+AJ35 -> 5703.45 | AP35: =ROUND(AH35-AI35+AK35-AL35+AO35+AN35,2) -> 4513.31 | AQ35: 6 | AR35: 29202 | AS35: 104.9 | AT35: 0 | AU35: 上海合杰
A36: 35 | B36: 202606 | C36: MNCN00515 | D36: 林辉 | E36: 310115197803192515 | F36: 销售顾问 | G36: 上海 | H36: 2740 | I36: 44004 | K36: 4200 | N36: 530 | O36: 6.5 | Q36: 11.75 | R36: =ROUND(K36/174*SUM(O36*1.5+P36*2+Q36*3),2) -> 1086.21 | V36: 9496.9 | AC36: =ROUND(SUM(SUM(K36:N36)+SUM(R36:AB36)),2) -> 15313.11 | AD36: 1081.27 | AE36: 270.32 | AF36: 67.58 | AG36: 946 | AH36: =AC36-AD36-AE36-AF36-AG36 -> 12947.94 | AI36: =MAX(ROUND(MAX((AH36+AR36-5000*AQ36-AT36)*{0.03,0.1,0.2,0.25,0.3,0.35,0.45}-{0,2520,16920,31920,52920,85920,181920},0)-AS36,2),0) -> 189.4 | AL36: =ROUND(LOOKUP(MAX(0.0001,AK36/12),{0;6;24;50;70;110;160}*500+0.0001,5*MAX(0,AK36)*{0.6;2;4;5;6;7;9}%-10*{0;21;141;266;441;716;1516}),2) -> 0 | AM36: =AC36+AK36+AJ36 -> 15313.11 | AP36: =ROUND(AH36-AI36+AK36-AL36+AO36+AN36,2) -> 12758.54 | AQ36: 6 | AR36: 74419.98 | AS36: 811.64 | AT36: 24000 | AU36: 上海合杰
A37: 36 | B37: 202606 | C37: MNCN00517 | D37: 刘丽微 | E37: 210323198908074066 | F37: 销售顾问 | G37: 大连 | H37: 2230 | I37: 44004 | K37: 4000 | N37: 530 | O37: 0 | Q37: 12 | R37: =ROUND(K37/174*SUM(O37*1.5+P37*2+Q37*3),2) -> 827.59 | V37: 1327.59 | AC37: =ROUND(SUM(SUM(K37:N37)+SUM(R37:AB37)),2) -> 6685.18 | AD37: 695.05 | AE37: 182.45 | AF37: 43.44 | AG37: 603.96 | AH37: =AC37-AD37-AE37-AF37-AG37 -> 5160.28 | AI37: =MAX(ROUND(MAX((AH37+AR37-5000*AQ37-AT37)*{0.03,0.1,0.2,0.25,0.3,0.35,0.45}-{0,2520,16920,31920,52920,85920,181920},0)-AS37,2),0) -> 41.74 | AL37: =ROUND(LOOKUP(MAX(0.0001,AK37/12),{0;6;24;50;70;110;160}*500+0.0001,5*MAX(0,AK37)*{0.6;2;4;5;6;7;9}%-10*{0;21;141;266;441;716;1516}),2) -> 0 | AM37: =AC37+AK37+AJ37 -> 6685.18 | AP37: =ROUND(AH37-AI37+AK37-AL37+AO37+AN37,2) -> 5118.54 | AQ37: 6 | AR37: 30341.21 | AS37: 123.3 | AT37: 0 | AU37: 上海合杰
A38: 37 | B38: 202606 | C38: MNCN00521 | D38: 姚远 | E38: 211302198202250020 | F38: 销售主管 | G38: 大连 | H38: 2230 | I38: 44013 | K38: 7000 | N38: 500 | O38: 0 | Q38: 20 | R38: =ROUND(K38/174*SUM(O38*1.5+P38*2+Q38*3),2) -> 2413.79 | V38: 2706.3 | AC38: =ROUND(SUM(SUM(K38:N38)+SUM(R38:AB38)),2) -> 12620.09 | AD38: 971.79 | AE38: 255.1 | AF38: 60.74 | AG38: 833.07 | AH38: =AC38-AD38-AE38-AF38-AG38 -> 10499.39 | AI38: =MAX(ROUND(MAX((AH38+AR38-5000*AQ38-AT38)*{0.03,0.1,0.2,0.25,0.3,0.35,0.45}-{0,2520,16920,31920,52920,85920,181920},0)-AS38,2),0) -> 228.61 | AL38: =ROUND(LOOKUP(MAX(0.0001,AK38/12),{0;6;24;50;70;110;160}*500+0.0001,5*MAX(0,AK38)*{0.6;2;4;5;6;7;9}%-10*{0;21;141;266;441;716;1516}),2) -> 0 | AM38: =AC38+AK38+AJ38 -> 12620.09 | AP38: =ROUND(AH38-AI38+AK38-AL38+AO38+AN38,2) -> 10270.78 | AQ38: 6 | AR38: 50742.53 | AS38: 708.65 | AT38: 0 | AU38: 上海合杰
A39: 38 | B39: 202606 | C39: MNCN00536 | D39: 赵凌云 | E39: 511321198801061483 | F39: 销售顾问 | G39: 重庆 | H39: 2330 | I39: 44130 | K39: 3600 | N39: 500 | O39: 3 | Q39: 11 | R39: =ROUND(K39/174*SUM(O39*1.5+P39*2+Q39*3),2) -> 775.86 | V39: 4.78 | AC39: =ROUND(SUM(SUM(K39:N39)+SUM(R39:AB39)),2) -> 4880.64 | AD39: 654.48 | AE39: 168.62 | AF39: 40.91 | AG39: 440 | AH39: =AC39-AD39-AE39-AF39-AG39 -> 3576.63 | AI39: =MAX(ROUND(MAX((AH39+AR39-5000*AQ39-AT39)*{0.03,0.1,0.2,0.25,0.3,0.35,0.45}-{0,2520,16920,31920,52920,85920,181920},0)-AS39,2),0) -> 0 | AL39: =ROUND(LOOKUP(MAX(0.0001,AK39/12),{0;6;24;50;70;110;160}*500+0.0001,5*MAX(0,AK39)*{0.6;2;4;5;6;7;9}%-10*{0;21;141;266;441;716;1516}),2) -> 0 | AM39: =AC39+AK39+AJ39 -> 4880.64 | AP39: =ROUND(AH39-AI39+AK39-AL39+AO39+AN39,2) -> 3576.63 | AQ39: 6 | AR39: 28603.22 | AS39: 171.39 | AT39: 0 | AU39: 合杰区域分
A40: 39 | B40: 202606 | C40: MNCN00537 | D40: 陈世益 | E40: 500224199208282854 | F40: 销售顾问 | G40: 重庆 | H40: 2330 | I40: 44130 | K40: 4000 | N40: 500 | O40: 3 | Q40: 22 | R40: =ROUND(K40/174*SUM(O40*1.5+P40*2+Q40*3),2) -> 1620.69 | V40: 131.4 | AC40: =ROUND(SUM(SUM(K40:N40)+SUM(R40:AB40)),2) -> 6252.09 | AD40: 784.96 | AE40: 201.24 | AF40: 49.06 | AG40: 561 | AH40: =AC40-AD40-AE40-AF40-AG40 -> 4655.83 | AI40: =MAX(ROUND(MAX((AH40+AR40-5000*AQ40-AT40)*{0.03,0.1,0.2,0.25,0.3,0.35,0.45}-{0,2520,16920,31920,52920,85920,181920},0)-AS40,2),0) -> 37.56 | AL40: =ROUND(LOOKUP(MAX(0.0001,AK40/12),{0;6;24;50;70;110;160}*500+0.0001,5*MAX(0,AK40)*{0.6;2;4;5;6;7;9}%-10*{0;21;141;266;441;716;1516}),2) -> 0 | AM40: =AC40+AK40+AJ40 -> 6252.09 | AP40: =ROUND(AH40-AI40+AK40-AL40+AO40+AN40,2) -> 4618.27 | AQ40: 6 | AR40: 35077.16 | AS40: 254.43 | AT40: 0 | AU40: 合杰区域分
A41: 40 | B41: 202606 | C41: MNCN00541 | D41: 罗丽丽 | E41: 513023198808152183 | F41: 销售顾问 | G41: 重庆 | H41: 2330 | I41: 44197 | K41: 3600 | N41: 500 | O41: 3 | Q41: 11 | R41: =ROUND(K41/174*SUM(O41*1.5+P41*2+Q41*3),2) -> 775.86 | V41: 1189.47 | AC41: =ROUND(SUM(SUM(K41:N41)+SUM(R41:AB41)),2) -> 6065.33 | AD41: 471.92 | AE41: 122.98 | AF41: 29.5 | AG41: 307 | AH41: =AC41-AD41-AE41-AF41-AG41 -> 5133.93 | AI41: =MAX(ROUND(MAX((AH41+AR41-5000*AQ41-AT41)*{0.03,0.1,0.2,0.25,0.3,0.35,0.45}-{0,2520,16920,31920,52920,85920,181920},0)-AS41,2),0) -> 0 | AL41: =ROUND(LOOKUP(MAX(0.0001,AK41/12),{0;6;24;50;70;110;160}*500+0.0001,5*MAX(0,AK41)*{0.6;2;4;5;6;7;9}%-10*{0;21;141;266;441;716;1516}),2) -> 0 | AM41: =AC41+AK41+AJ41 -> 6065.33 | AP41: =ROUND(AH41-AI41+AK41-AL41+AO41+AN41,2) -> 5133.93 | AQ41: 6 | AR41: 27788.41 | AS41: 168.16 | AT41: 0 | AU41: 合杰区域分
A42: 41 | B42: 202606 | C42: MNCN00542 | D42: 汤黎 | E42: 513001198108140220 | F42: 销售顾问 | G42: 重庆 | H42: 2330 | I42: 44197 | K42: 3600 | N42: 500 | O42: 0 | Q42: 11 | R42: =ROUND(K42/174*SUM(O42*1.5+P42*2+Q42*3),2) -> 682.76 | V42: 300.15 | AC42: =ROUND(SUM(SUM(K42:N42)+SUM(R42:AB42)),2) -> 5082.91 | AD42: 477.04 | AE42: 124.26 | AF42: 29.82 | AG42: 381 | AH42: =AC42-AD42-AE42-AF42-AG42 -> 4070.79 | AI42: =MAX(ROUND(MAX((AH42+AR42-5000*AQ42-AT42)*{0.03,0.1,0.2,0.25,0.3,0.35,0.45}-{0,2520,16920,31920,52920,85920,181920},0)-AS42,2),0) -> 0 | AL42: =ROUND(LOOKUP(MAX(0.0001,AK42/12),{0;6;24;50;70;110;160}*500+0.0001,5*MAX(0,AK42)*{0.6;2;4;5;6;7;9}%-10*{0;21;141;266;441;716;1516}),2) -> 0 | AM42: =AC42+AK42+AJ42 -> 5082.91 | AP42: =ROUND(AH42-AI42+AK42-AL42+AO42+AN42,2) -> 4070.79 | AQ42: 6 | AR42: 27791.12 | AS42: 110.47 | AT42: 0 | AU42: 合杰区域分
A43: 42 | B43: 202606 | C43: MNCN00547 | D43: 王玉婷 | E43: 210282198711178747 | F43: 销售顾问 | G43: 大连 | H43: 2230 | I43: 44262 | K43: 4000 | N43: 500 | O43: 0 | Q43: 20 | R43: =ROUND(K43/174*SUM(O43*1.5+P43*2+Q43*3),2) -> 1379.31 | V43: 1629.89 | AC43: =ROUND(SUM(SUM(K43:N43)+SUM(R43:AB43)),2) -> 7509.2 | AD43: 622.12 | AE43: 163.31 | AF43: 38.88 | AG43: 532.14 | AH43: =AC43-AD43-AE43-AF43-AG43 -> 6152.75 | AI43: =MAX(ROUND(MAX((AH43+AR43-5000*AQ43-AT43)*{0.03,0.1,0.2,0.25,0.3,0.35,0.45}-{0,2520,16920,31920,52920,85920,181920},0)-AS43,2),0) -> 0 | AL43: =ROUND(LOOKUP(MAX(0.0001,AK43/12),{0;6;24;50;70;110;160}*500+0.0001,5*MAX(0,AK43)*{0.6;2;4;5;6;7;9}%-10*{0;21;141;266;441;716;1516}),2) -> 0 | AM43: =AC43+AK43+AJ43 -> 7509.2 | AP43: =ROUND(AH43-AI43+AK43-AL43+AO43+AN43,2) -> 6152.75 | AQ43: 6 | AR43: 31770.26 | AS43: 198.71 | AT43: 6000 | AU43: 上海合杰
A44: 43 | B44: 202606 | C44: MNCN00553 | D44: 张晨 | E44: 11010219811008041X | F44: 高级销售顾问 | G44: 北京 | H44: 2540 | I44: 44301 | K44: 4600 | N44: 500 | O44: 32 | Q44: 16 | R44: =ROUND(K44/174*SUM(O44*1.5+P44*2+Q44*3),2) -> 2537.93 | V44: 297 | W44: 1500 | AC44: =ROUND(SUM(SUM(K44:N44)+SUM(R44:AB44)),2) -> 9434.93 | AD44: 578.4 | AE44: 147.6 | AF44: 36.15 | AG44: 868 | AH44: =AC44-AD44-AE44-AF44-AG44 -> 7804.78 | AI44: =MAX(ROUND(MAX((AH44+AR44-5000*AQ44-AT44)*{0.03,0.1,0.2,0.25,0.3,0.35,0.45}-{0,2520,16920,31920,52920,85920,181920},0)-AS44,2),0) -> 0 | AL44: =ROUND(LOOKUP(MAX(0.0001,AK44/12),{0;6;24;50;70;110;160}*500+0.0001,5*MAX(0,AK44)*{0.6;2;4;5;6;7;9}%-10*{0;21;141;266;441;716;1516}),2) -> 0 | AM44: =AC44+AK44+AJ44 -> 9434.93 | AP44: =ROUND(AH44-AI44+AK44-AL44+AO44+AN44,2) -> 7804.78 | AQ44: 6 | AR44: 49192.15 | AS44: 303.38 | AT44: 30000 | AU44: 北京合杰
A45: 44 | B45: 202606 | C45: MNCN00552 | D45: 贾璞 | E45: 130624198708032411 | F45: 销售主管 | G45: 北京 | H45: 2540 | I45: 44301 | K45: 8300 | N45: 500 | O45: 40 | Q45: 16 | R45: =ROUND(K45/174*SUM(O45*1.5+P45*2+Q45*3),2) -> 5151.72 | W45: 1500 | AC45: =ROUND(SUM(SUM(K45:N45)+SUM(R45:AB45)),2) -> 15451.72 | AD45: 1000.16 | AE45: 253.04 | AF45: 62.51 | AG45: 1500 | AH45: =AC45-AD45-AE45-AF45-AG45 -> 12636.01 | AI45: =MAX(ROUND(MAX((AH45+AR45-5000*AQ45-AT45)*{0.03,0.1,0.2,0.25,0.3,0.35,0.45}-{0,2520,16920,31920,52920,85920,181920},0)-AS45,2),0) -> 1045.18 | AL45: =ROUND(LOOKUP(MAX(0.0001,AK45/12),{0;6;24;50;70;110;160}*500+0.0001,5*MAX(0,AK45)*{0.6;2;4;5;6;7;9}%-10*{0;21;141;266;441;716;1516}),2) -> 0 | AM45: =AC45+AK45+AJ45 -> 15451.72 | AP45: =ROUND(AH45-AI45+AK45-AL45+AO45+AN45,2) -> 11590.83 | AQ45: 6 | AR45: 70508.45 | AS45: 1749.27 | AT45: 0 | AU45: 北京合杰
A46: 45 | B46: 202606 | C46: MNCN00559 | D46: 李思帆 | E46: 411503199709176324 | F46: 电商客服 | G46: 上海 | H46: 2740 | I46: 44333 | K46: 5500 | O46: 0 | Q46: 0 | R46: =ROUND(K46/174*SUM(O46*1.5+P46*2+Q46*3),2) -> 0 | V46: 3000 | AC46: =ROUND(SUM(SUM(K46:N46)+SUM(R46:AB46)),2) -> 8500 | AD46: 1415.71 | AE46: 353.93 | AF46: 88.48 | AG46: 1239 | AH46: =AC46-AD46-AE46-AF46-AG46 -> 5402.88 | AI46: =MAX(ROUND(MAX((AH46+AR46-5000*AQ46-AT46)*{0.03,0.1,0.2,0.25,0.3,0.35,0.45}-{0,2520,16920,31920,52920,85920,181920},0)-AS46,2),0) -> 350 | AL46: =ROUND(LOOKUP(MAX(0.0001,AK46/12),{0;6;24;50;70;110;160}*500+0.0001,5*MAX(0,AK46)*{0.6;2;4;5;6;7;9}%-10*{0;21;141;266;441;716;1516}),2) -> 0 | AM46: =AC46+AK46+AJ46 -> 8500 | AP46: =ROUND(AH46-AI46+AK46-AL46+AO46+AN46,2) -> 5052.88 | AQ46: 6 | AR46: 98672.22 | AS46: 4537.51 | AT46: 0 | AU46: 上海合杰
A47: 46 | B47: 202606 | C47: MNCN00564 | D47: 刘培培 | E47: 320623198910194368 | F47: 销售顾问 | G47: 上海 | H47: 2740 | I47: 44351 | K47: 4200 | N47: 490 | O47: 0 | Q47: 10 | R47: =ROUND(K47/174*SUM(O47*1.5+P47*2+Q47*3),2) -> 724.14 | V47: 328.67 | AC47: =ROUND(SUM(SUM(K47:N47)+SUM(R47:AB47)),2) -> 5742.81 | AD47: 753.49 | AE47: 188.37 | AF47: 47.09 | AG47: 659 | AH47: =AC47-AD47-AE47-AF47-AG47 -> 4094.86 | AI47: =MAX(ROUND(MAX((AH47+AR47-5000*AQ47-AT47)*{0.03,0.1,0.2,0.25,0.3,0.35,0.45}-{0,2520,16920,31920,52920,85920,181920},0)-AS47,2),0) -> 0 | AL47: =ROUND(LOOKUP(MAX(0.0001,AK47/12),{0;6;24;50;70;110;160}*500+0.0001,5*MAX(0,AK47)*{0.6;2;4;5;6;7;9}%-10*{0;21;141;266;441;716;1516}),2) -> 0 | AM47: =AC47+AK47+AJ47 -> 5742.81 | AP47: =ROUND(AH47-AI47+AK47-AL47+AO47+AN47,2) -> 4094.86 | AQ47: 6 | AR47: 23147.07 | AS47: 72.74 | AT47: 0 | AU47: 上海合杰
A48: 47 | B48: 202606 | C48: MNCN00567 | D48: 黄蕾 | E48: 310108197808254048 | F48: 销售顾问 | G48: 上海 | H48: 2740 | I48: 44350 | K48: 4200 | N48: 493.33 | O48: 6.5 | Q48: 13 | R48: =ROUND(K48/174*SUM(O48*1.5+P48*2+Q48*3),2) -> 1176.72 | V48: 1189.06 | AC48: =ROUND(SUM(SUM(K48:N48)+SUM(R48:AB48)),2) -> 7059.11 | AD48: 777.19 | AE48: 194.3 | AF48: 48.57 | AG48: 680 | AH48: =AC48-AD48-AE48-AF48-AG48 -> 5359.05 | AI48: =MAX(ROUND(MAX((AH48+AR48-5000*AQ48-AT48)*{0.03,0.1,0.2,0.25,0.3,0.35,0.45}-{0,2520,16920,31920,52920,85920,181920},0)-AS48,2),0) -> 0 | AL48: =ROUND(LOOKUP(MAX(0.0001,AK48/12),{0;6;24;50;70;110;160}*500+0.0001,5*MAX(0,AK48)*{0.6;2;4;5;6;7;9}%-10*{0;21;141;266;441;716;1516}),2) -> 0 | AM48: =AC48+AK48+AJ48 -> 7059.11 | AP48: =ROUND(AH48-AI48+AK48-AL48+AO48+AN48,2) -> 5359.05 | AQ48: 6 | AR48: 34001.48 | AS48: 242.86 | AT48: 12000 | AU48: 上海合杰
A49: 48 | B49: 202606 | C49: MNCN00576 | D49: 张陆敏 | E49: 31011019830528513X | F49: 销售顾问 | G49: 上海 | H49: 2740 | I49: 44378 | K49: 4200 | N49: 400 | O49: 29.5 | Q49: 27.5 | R49: =ROUND(K49/174*SUM(O49*1.5+P49*2+Q49*3),2) -> 3059.48 | V49: 344.83 | W49: 500 | AC49: =ROUND(SUM(SUM(K49:N49)+SUM(R49:AB49)),2) -> 8504.31 | AD49: 624.98 | AE49: 156.24 | AF49: 39.06 | AG49: 547 | AH49: =AC49-AD49-AE49-AF49-AG49 -> 7137.03 | AI49: =MAX(ROUND(MAX((AH49+AR49-5000*AQ49-AT49)*{0.03,0.1,0.2,0.25,0.3,0.35,0.45}-{0,2520,16920,31920,52920,85920,181920},0)-AS49,2),0) -> 34.02 | AL49: =ROUND(LOOKUP(MAX(0.0001,AK49/12),{0;6;24;50;70;110;160}*500+0.0001,5*MAX(0,AK49)*{0.6;2;4;5;6;7;9}%-10*{0;21;141;266;441;716;1516}),2) -> 0 | AM49: =AC49+AK49+AJ49 -> 8504.31 | AP49: =ROUND(AH49-AI49+AK49-AL49+AO49+AN49,2) -> 7103.01 | AQ49: 6 | AR49: 28693.85 | AS49: 140.91 | AT49: 0 | AU49: 上海合杰
A50: 49 | B50: 202606 | C50: MNCN00577 | D50: 黄欢 | E50: 34012319851229364X | F50: 销售顾问 | G50: 杭州 | H50: 2660 | I50: 44383 | K50: 4000 | N50: 400 | O50: 0 | Q50: 16 | R50: =ROUND(K50/174*SUM(O50*1.5+P50*2+Q50*3),2) -> 1103.45 | V50: 5970.23 | AC50: =ROUND(SUM(SUM(K50:N50)+SUM(R50:AB50)),2) -> 11473.68 | AD50: 1087.93 | AE50: 271.98 | AF50: 68 | AG50: 1496 | AH50: =AC50-AD50-AE50-AF50-AG50 -> 8549.77 | AI50: =MAX(ROUND(MAX((AH50+AR50-5000*AQ50-AT50)*{0.03,0.1,0.2,0.25,0.3,0.35,0.45}-{0,2520,16920,31920,52920,85920,181920},0)-AS50,2),0) -> 647.37 | AL50: =ROUND(LOOKUP(MAX(0.0001,AK50/12),{0;6;24;50;70;110;160}*500+0.0001,5*MAX(0,AK50)*{0.6;2;4;5;6;7;9}%-10*{0;21;141;266;441;716;1516}),2) -> 0 | AM50: =AC50+AK50+AJ50 -> 11473.68 | AP50: =ROUND(AH50-AI50+AK50-AL50+AO50+AN50,2) -> 7902.4 | AQ50: 6 | AR50: 64931.7 | AS50: 1180.78 | AT50: 0 | AU50: 合杰区域分
A51: 50 | B51: 202606 | C51: MNCN00578 | D51: 张春彩 | E51: 341021198002026720 | F51: 销售顾问 | G51: 杭州 | H51: 2660 | I51: 44383 | K51: 4000 | N51: 400 | O51: 0 | Q51: 16 | R51: =ROUND(K51/174*SUM(O51*1.5+P51*2+Q51*3),2) -> 1103.45 | V51: 3027.91 | AC51: =ROUND(SUM(SUM(K51:N51)+SUM(R51:AB51)),2) -> 8531.36 | AD51: 1107.96 | AE51: 276.99 | AF51: 69.25 | AG51: 1379 | AH51: =AC51-AD51-AE51-AF51-AG51 -> 5698.16 | AI51: =MAX(ROUND(MAX((AH51+AR51-5000*AQ51-AT51)*{0.03,0.1,0.2,0.25,0.3,0.35,0.45}-{0,2520,16920,31920,52920,85920,181920},0)-AS51,2),0) -> 294.96 | AL51: =ROUND(LOOKUP(MAX(0.0001,AK51/12),{0;6;24;50;70;110;160}*500+0.0001,5*MAX(0,AK51)*{0.6;2;4;5;6;7;9}%-10*{0;21;141;266;441;716;1516}),2) -> 0 | AM51: =AC51+AK51+AJ51 -> 8531.36 | AP51: =ROUND(AH51-AI51+AK51-AL51+AO51+AN51,2) -> 5403.2 | AQ51: 6 | AR51: 63002.16 | AS51: 1055.07 | AT51: 0 | AU51: 合杰区域分
A52: 51 | B52: 202606 | C52: MNCN00580 | D52: 苏敏 | E52: 532123200004070025 | F52: 电商客服 | G52: 上海 | H52: 2740 | I52: 44397 | K52: 5000 | O52: 0 | Q52: 8 | R52: =ROUND(K52/174*SUM(O52*1.5+P52*2+Q52*3),2) -> 689.66 | V52: 3000 | AC52: =ROUND(SUM(SUM(K52:N52)+SUM(R52:AB52)),2) -> 8689.66 | AD52: 1250.43 | AE52: 312.61 | AF52: 78.15 | AG52: 1094 | AH52: =AC52-AD52-AE52-AF52-AG52 -> 5954.47 | AI52: =MAX(ROUND(MAX((AH52+AR52-5000*AQ52-AT52)*{0.03,0.1,0.2,0.25,0.3,0.35,0.45}-{0,2520,16920,31920,52920,85920,181920},0)-AS52,2),0) -> 368.97 | AL52: =ROUND(LOOKUP(MAX(0.0001,AK52/12),{0;6;24;50;70;110;160}*500+0.0001,5*MAX(0,AK52)*{0.6;2;4;5;6;7;9}%-10*{0;21;141;266;441;716;1516}),2) -> 0 | AM52: =AC52+AK52+AJ52 -> 8689.66 | AP52: =ROUND(AH52-AI52+AK52-AL52+AO52+AN52,2) -> 5585.5 | AQ52: 6 | AR52: 67234.62 | AS52: 1429.94 | AT52: 0 | AU52: 上海合杰
A53: 52 | B53: 202606 | C53: MNCN00590 | D53: 杨吕明 | E53: 340825198510252319 | F53: 高级销售顾问 | G53: 合肥 | H53: 2320 | I53: 44441 | K53: 4400 | N53: 400 | O53: 0 | Q53: 24 | R53: =ROUND(K53/174*SUM(O53*1.5+P53*2+Q53*3),2) -> 1820.69 | V53: 608.99 | W53: 1500 | AC53: =ROUND(SUM(SUM(K53:N53)+SUM(R53:AB53)),2) -> 8729.68 | AD53: 717.19 | AE53: 179.3 | AF53: 44.82 | AG53: 448 | AH53: =AC53-AD53-AE53-AF53-AG53 -> 7340.37 | AI53: =MAX(ROUND(MAX((AH53+AR53-5000*AQ53-AT53)*{0.03,0.1,0.2,0.25,0.3,0.35,0.45}-{0,2520,16920,31920,52920,85920,181920},0)-AS53,2),0) -> 111.89 | AL53: =ROUND(LOOKUP(MAX(0.0001,AK53/12),{0;6;24;50;70;110;160}*500+0.0001,5*MAX(0,AK53)*{0.6;2;4;5;6;7;9}%-10*{0;21;141;266;441;716;1516}),2) -> 0 | AM53: =AC53+AK53+AJ53 -> 8729.68 | AP53: =ROUND(AH53-AI53+AK53-AL53+AO53+AN53,2) -> 7228.48 | AQ53: 4 | AR53: 20591.69 | AS53: 126.07 | AT53: 0 | AU53: 合杰区域分
A54: 53 | B54: 202606 | C54: MNCN00593 | D54: 李玉文 | E54: 220421199508174147 | F54: 销售顾问 | G54: 北京 | H54: 2540 | I54: 44453 | J54: 46155 | K54: 3800 | L54: =-K54 -> -3800 | O54: 0 | Q54: 20 | R54: =ROUND(K54/174*SUM(O54*1.5+P54*2+Q54*3),2) -> 1310.34 | V54: 1782.15 | AC54: =ROUND(SUM(SUM(K54:N54)+SUM(R54:AB54)),2) -> 3092.49 | AH54: =AC54-AD54-AE54-AF54-AG54 -> 3092.49 | AI54: =MAX(ROUND(MAX((AH54+AR54-5000*AQ54-AT54)*{0.03,0.1,0.2,0.25,0.3,0.35,0.45}-{0,2520,16920,31920,52920,85920,181920},0)-AS54,2),0) -> 0 | AL54: =ROUND(LOOKUP(MAX(0.0001,AK54/12),{0;6;24;50;70;110;160}*500+0.0001,5*MAX(0,AK54)*{0.6;2;4;5;6;7;9}%-10*{0;21;141;266;441;716;1516}),2) -> 0 | AM54: =AC54+AK54+AJ54 -> 3092.49 | AP54: =ROUND(AH54-AI54+AK54-AL54+AO54+AN54,2) -> 3092.49 | AQ54: 6 | AR54: 20364.49 | AS54: 50.67 | AT54: 0 | AU54: 北京合杰
A55: 54 | B55: 202606 | C55: MNCN00595 | D55: 胡敏 | E55: 310110198101283722 | F55: 销售顾问 | G55: 上海 | H55: 2740 | I55: 44453 | K55: 4200 | N55: 400 | O55: 9 | Q55: 18 | R55: =ROUND(K55/174*SUM(O55*1.5+P55*2+Q55*3),2) -> 1629.31 | V55: 3170.61 | AC55: =ROUND(SUM(SUM(K55:N55)+SUM(R55:AB55)),2) -> 9399.92 | AD55: 1178.34 | AE55: 294.59 | AF55: 73.65 | AG55: 1031 | AH55: =AC55-AD55-AE55-AF55-AG55 -> 6822.34 | AI55: =MAX(ROUND(MAX((AH55+AR55-5000*AQ55-AT55)*{0.03,0.1,0.2,0.25,0.3,0.35,0.45}-{0,2520,16920,31920,52920,85920,181920},0)-AS55,2),0) -> 0 | AL55: =ROUND(LOOKUP(MAX(0.0001,AK55/12),{0;6;24;50;70;110;160}*500+0.0001,5*MAX(0,AK55)*{0.6;2;4;5;6;7;9}%-10*{0;21;141;266;441;716;1516}),2) -> 0 | AM55: =AC55+AK55+AJ55 -> 9399.92 | AP55: =ROUND(AH55-AI55+AK55-AL55+AO55+AN55,2) -> 6822.34 | AQ55: 6 | AR55: 55050.78 | AS55: 556.62 | AT55: 18000 | AU55: 上海合杰
A56: 55 | B56: 202606 | C56: MNCN00602 | D56: 杜文伟 | E56: 310115198212077755 | F56: 销售顾问 | G56: 上海 | H56: 2740 | I56: 44501 | K56: 3800 | N56: 400 | O56: 0 | Q56: 10 | R56: =ROUND(K56/174*SUM(O56*1.5+P56*2+Q56*3),2) -> 655.17 | V56: 10843.89 | AC56: =ROUND(SUM(SUM(K56:N56)+SUM(R56:AB56)),2) -> 15699.06 | AD56: 1785.64 | AE56: 446.41 | AF56: 111.6 | AG56: 1562 | AH56: =AC56-AD56-AE56-AF56-AG56 -> 11793.41 | AI56: =MAX(ROUND(MAX((AH56+AR56-5000*AQ56-AT56)*{0.03,0.1,0.2,0.25,0.3,0.35,0.45}-{0,2520,16920,31920,52920,85920,181920},0)-AS56,2),0) -> 1069.9 | AL56: =ROUND(LOOKUP(MAX(0.0001,AK56/12),{0;6;24;50;70;110;160}*500+0.0001,5*MAX(0,AK56)*{0.6;2;4;5;6;7;9}%-10*{0;21;141;266;441;716;1516}),2) -> 0 | AM56: =AC56+AK56+AJ56 -> 15699.06 | AP56: =ROUND(AH56-AI56+AK56-AL56+AO56+AN56,2) -> 10723.51 | AQ56: 6 | AR56: 99561.73 | AS56: 4545.61 | AT56: 0 | AU56: 上海合杰
A57: 56 | B57: 202606 | C57: MNCN00603 | D57: 张燕 | E57: 36252519820225002X | F57: 销售顾问 | G57: 上海 | H57: 2740 | I57: 44504 | K57: 4200 | N57: 400 | O57: 0 | Q57: 9 | R57: =ROUND(K57/174*SUM(O57*1.5+P57*2+Q57*3),2) -> 651.72 | V57: 4573.08 | AC57: =ROUND(SUM(SUM(K57:N57)+SUM(R57:AB57)),2) -> 9824.8 | AD57: 1179.21 | AE57: 294.8 | AF57: 73.7 | AG57: 1032 | AH57: =AC57-AD57-AE57-AF57-AG57 -> 7245.09 | AI57: =MAX(ROUND(MAX((AH57+AR57-5000*AQ57-AT57)*{0.03,0.1,0.2,0.25,0.3,0.35,0.45}-{0,2520,16920,31920,52920,85920,181920},0)-AS57,2),0) -> 0 | AL57: =ROUND(LOOKUP(MAX(0.0001,AK57/12),{0;6;24;50;70;110;160}*500+0.0001,5*MAX(0,AK57)*{0.6;2;4;5;6;7;9}%-10*{0;21;141;266;441;716;1516}),2) -> 0 | AM57: =AC57+AK57+AJ57 -> 9824.8 | AP57: =ROUND(AH57-AI57+AK57-AL57+AO57+AN57,2) -> 7245.09 | AQ57: 6 | AR57: 57656.72 | AS57: 671.13 | AT57: 20994 | AU57: 上海合杰
A58: 57 | B58: 202606 | C58: MNCN00608 | D58: 白雪杰 | E58: 130824198307310047 | F58: 销售主管 | G58: 北京 | H58: 2540 | I58: 44557 | J58: 46155 | K58: 8000 | L58: =-K58 -> -8000 | O58: 0 | Q58: 20 | R58: =ROUND(K58/174*SUM(O58*1.5+P58*2+Q58*3),2) -> 2758.62 | V58: 12660.22 | AC58: =ROUND(SUM(SUM(K58:N58)+SUM(R58:AB58)),2) -> 15418.84 | AH58: =AC58-AD58-AE58-AF58-AG58 -> 15418.84 | AI58: =MAX(ROUND(MAX((AH58+AR58-5000*AQ58-AT58)*{0.03,0.1,0.2,0.25,0.3,0.35,0.45}-{0,2520,16920,31920,52920,85920,181920},0)-AS58,2),0) -> 394.29 | AL58: =ROUND(LOOKUP(MAX(0.0001,AK58/12),{0;6;24;50;70;110;160}*500+0.0001,5*MAX(0,AK58)*{0.6;2;4;5;6;7;9}%-10*{0;21;141;266;441;716;1516}),2) -> 0 | AM58: =AC58+AK58+AJ58 -> 15418.84 | AP58: =ROUND(AH58-AI58+AK58-AL58+AO58+AN58,2) -> 15024.55 | AQ58: 6 | AR58: 48329.47 | AS58: 618.16 | AT58: 0 | AU58: 北京合杰
A59: 58 | B59: 202606 | C59: MNCN00617 | D59: 李磊 | E59: 510322198910194715 | F59: 销售顾问 | G59: 上海 | H59: 2740 | I59: 44629 | K59: 3800 | N59: 400 | O59: 11.25 | Q59: 11.75 | R59: =ROUND(K59/174*SUM(O59*1.5+P59*2+Q59*3),2) -> 1138.36 | V59: 6471.07 | AC59: =ROUND(SUM(SUM(K59:N59)+SUM(R59:AB59)),2) -> 11809.43 | AD59: 707.41 | AE59: 176.85 | AF59: 44.21 | AG59: 619 | AH59: =AC59-AD59-AE59-AF59-AG59 -> 10261.96 | AI59: =MAX(ROUND(MAX((AH59+AR59-5000*AQ59-AT59)*{0.03,0.1,0.2,0.25,0.3,0.35,0.45}-{0,2520,16920,31920,52920,85920,181920},0)-AS59,2),0) -> 652.49 | AL59: =ROUND(LOOKUP(MAX(0.0001,AK59/12),{0;6;24;50;70;110;160}*500+0.0001,5*MAX(0,AK59)*{0.6;2;4;5;6;7;9}%-10*{0;21;141;266;441;716;1516}),2) -> 0 | AM59: =AC59+AK59+AJ59 -> 11809.43 | AP59: =ROUND(AH59-AI59+AK59-AL59+AO59+AN59,2) -> 9609.47 | AQ59: 6 | AR59: 62141.03 | AS59: 1067.81 | AT59: 0 | AU59: 上海合杰
A60: 59 | B60: 202606 | C60: MNCN00618 | D60: 魏园园 | E60: 420325199710041927 | F60: 销售顾问 | G60: 北京 | H60: 2540 | I60: 44630 | J60: 46155 | K60: 3800 | L60: =-K60 -> -3800 | O60: 0 | Q60: 20 | R60: =ROUND(K60/174*SUM(O60*1.5+P60*2+Q60*3),2) -> 1310.34 | V60: 1782.15 | AC60: =ROUND(SUM(SUM(K60:N60)+SUM(R60:AB60)),2) -> 3092.49 | AH60: =AC60-AD60-AE60-AF60-AG60 -> 3092.49 | AI60: =MAX(ROUND(MAX((AH60+AR60-5000*AQ60-AT60)*{0.03,0.1,0.2,0.25,0.3,0.35,0.45}-{0,2520,16920,31920,52920,85920,181920},0)-AS60,2),0) -> 0 | AL60: =ROUND(LOOKUP(MAX(0.0001,AK60/12),{0;6;24;50;70;110;160}*500+0.0001,5*MAX(0,AK60)*{0.6;2;4;5;6;7;9}%-10*{0;21;141;266;441;716;1516}),2) -> 0 | AM60: =AC60+AK60+AJ60 -> 3092.49 | AP60: =ROUND(AH60-AI60+AK60-AL60+AO60+AN60,2) -> 3092.49 | AQ60: 6 | AR60: 20361.74 | AS60: 53.44 | AT60: 0 | AU60: 北京合杰
A61: 60 | B61: 202606 | C61: MNCN00625 | D61: 阳杰 | E61: 429006199501020014 | F61: 销售顾问 | G61: 武汉 | H61: 2400 | I61: 44676 | K61: 4000 | N61: 400 | O61: 0 | Q61: 20 | R61: =ROUND(K61/174*SUM(O61*1.5+P61*2+Q61*3),2) -> 1379.31 | V61: 643.79 | AC61: =ROUND(SUM(SUM(K61:N61)+SUM(R61:AB61)),2) -> 6423.1 | AD61: 848.72 | AE61: 219.18 | AF61: 31.83 | AG61: 848.74 | AH61: =AC61-AD61-AE61-AF61-AG61 -> 4474.63 | AI61: =MAX(ROUND(MAX((AH61+AR61-5000*AQ61-AT61)*{0.03,0.1,0.2,0.25,0.3,0.35,0.45}-{0,2520,16920,31920,52920,85920,181920},0)-AS61,2),0) -> 0 | AL61: =ROUND(LOOKUP(MAX(0.0001,AK61/12),{0;6;24;50;70;110;160}*500+0.0001,5*MAX(0,AK61)*{0.6;2;4;5;6;7;9}%-10*{0;21;141;266;441;716;1516}),2) -> 0 | AM61: =AC61+AK61+AJ61 -> 6423.1 | AP61: =ROUND(AH61-AI61+AK61-AL61+AO61+AN61,2) -> 4474.63 | AQ61: 6 | AR61: 41081.9 | AS61: 479.39 | AT61: 0 | AU61: 合杰区域分
A62: 61 | B62: 202606 | C62: MNCN00646 | D62: 肖若竹 | E62: 130225199509230043 | F62: 销售顾问 | G62: 广州 | H62: 2500 | I62: 44783 | K62: 3800 | N62: 300 | O62: 0 | Q62: 16 | R62: =ROUND(K62/174*SUM(O62*1.5+P62*2+Q62*3),2) -> 1048.28 | V62: 1048.2 | W62: 1500 | AC62: =ROUND(SUM(SUM(K62:N62)+SUM(R62:AB62)),2) -> 7696.48 | AD62: 614.72 | AE62: 153.68 | AF62: 15.37 | AG62: 538 | AH62: =AC62-AD62-AE62-AF62-AG62 -> 6374.71 | AI62: =MAX(ROUND(MAX((AH62+AR62-5000*AQ62-AT62)*{0.03,0.1,0.2,0.25,0.3,0.35,0.45}-{0,2520,16920,31920,52920,85920,181920},0)-AS62,2),0) -> 80.89 | AL62: =ROUND(LOOKUP(MAX(0.0001,AK62/12),{0;6;24;50;70;110;160}*500+0.0001,5*MAX(0,AK62)*{0.6;2;4;5;6;7;9}%-10*{0;21;141;266;441;716;1516}),2) -> 0 | AM62: =AC62+AK62+AJ62 -> 7696.48 | AP62: =ROUND(AH62-AI62+AK62-AL62+AO62+AN62,2) -> 6293.82 | AQ62: 6 | AR62: 31024.36 | AS62: 141.08 | AT62: 0 | AU62: 合杰区域分
A63: 62 | B63: 202606 | C63: MNCN00656 | D63: 何雯 | E63: 510106198710121449 | F63: 销售顾问 | G63: 成都 | H63: 2330 | I63: 44823 | K63: 3600 | N63: 300 | O63: 15 | Q63: 16 | R63: =ROUND(K63/174*SUM(O63*1.5+P63*2+Q63*3),2) -> 1458.62 | V63: 395.53 | AC63: =ROUND(SUM(SUM(K63:N63)+SUM(R63:AB63)),2) -> 5754.15 | AD63: 724.56 | AE63: 181.14 | AF63: 36.23 | AG63: 493 | AH63: =AC63-AD63-AE63-AF63-AG63 -> 4319.22 | AI63: =MAX(ROUND(MAX((AH63+AR63-5000*AQ63-AT63)*{0.03,0.1,0.2,0.25,0.3,0.35,0.45}-{0,2520,16920,31920,52920,85920,181920},0)-AS63,2),0) -> 18.81 | AL63: =ROUND(LOOKUP(MAX(0.0001,AK63/12),{0;6;24;50;70;110;160}*500+0.0001,5*MAX(0,AK63)*{0.6;2;4;5;6;7;9}%-10*{0;21;141;266;441;716;1516}),2) -> 0 | AM63: =AC63+AK63+AJ63 -> 5754.15 | AP63: =ROUND(AH63-AI63+AK63-AL63+AO63+AN63,2) -> 4300.41 | AQ63: 6 | AR63: 42977.93 | AS63: 500.1 | AT63: 0 | AU63: 成都合杰
A64: 63 | B64: 202606 | C64: MNCN00661 | D64: 李芳 | E64: 360121199309283548 | F64: 高级销售顾问 | G64: 南昌 | H64: 2240 | I64: 44833 | K64: 4400 | N64: 300 | O64: 13.5 | Q64: 17.5 | R64: =ROUND(K64/174*SUM(O64*1.5+P64*2+Q64*3),2) -> 1839.66 | V64: 80.13 | AC64: =ROUND(SUM(SUM(K64:N64)+SUM(R64:AB64)),2) -> 6619.79 | AD64: 715.33 | AE64: 194.65 | AF64: 44.71 | AG64: 1073 | AH64: =AC64-AD64-AE64-AF64-AG64 -> 4592.1 | AI64: =MAX(ROUND(MAX((AH64+AR64-5000*AQ64-AT64)*{0.03,0.1,0.2,0.25,0.3,0.35,0.45}-{0,2520,16920,31920,52920,85920,181920},0)-AS64,2),0) -> 40.67 | AL64: =ROUND(LOOKUP(MAX(0.0001,AK64/12),{0;6;24;50;70;110;160}*500+0.0001,5*MAX(0,AK64)*{0.6;2;4;5;6;7;9}%-10*{0;21;141;266;441;716;1516}),2) -> 0 | AM64: =AC64+AK64+AJ64 -> 6619.79 | AP64: =ROUND(AH64-AI64+AK64-AL64+AO64+AN64,2) -> 4551.43 | AQ64: 6 | AR64: 35077.74 | AS64: 249.43 | AT64: 0 | AU64: 合杰区域分
A65: 64 | B65: 202606 | C65: MNCN00663 | D65: 朱健 | E65: 360481198502284030 | F65: 销售顾问 | G65: 南昌 | H65: 2240 | I65: 44845 | K65: 3600 | N65: 300 | O65: 19.5 | Q65: 17 | R65: =ROUND(K65/174*SUM(O65*1.5+P65*2+Q65*3),2) -> 1660.34 | V65: 4112.58 | AC65: =ROUND(SUM(SUM(K65:N65)+SUM(R65:AB65)),2) -> 9672.92 | AD65: 616.26 | AE65: 169.89 | AF65: 38.52 | AG65: 924 | AH65: =AC65-AD65-AE65-AF65-AG65 -> 7924.25 | AI65: =MAX(ROUND(MAX((AH65+AR65-5000*AQ65-AT65)*{0.03,0.1,0.2,0.25,0.3,0.35,0.45}-{0,2520,16920,31920,52920,85920,181920},0)-AS65,2),0) -> 0 | AL65: =ROUND(LOOKUP(MAX(0.0001,AK65/12),{0;6;24;50;70;110;160}*500+0.0001,5*MAX(0,AK65)*{0.6;2;4;5;6;7;9}%-10*{0;21;141;266;441;716;1516}),2) -> 0 | AM65: =AC65+AK65+AJ65 -> 9672.92 | AP65: =ROUND(AH65-AI65+AK65-AL65+AO65+AN65,2) -> 7924.25 | AQ65: 6 | AR65: 25691.77 | AS65: 111.76 | AT65: 0 | AU65: 合杰区域分
A66: 65 | B66: 202606 | C66: MNCN00667 | D66: 董琪 | E66: 421181198909180429 | F66: 销售顾问 | G66: 武汉 | H66: 2400 | I66: 44878 | K66: 3600 | N66: 300 | O66: 0 | Q66: 0 | R66: =ROUND(K66/174*SUM(O66*1.5+P66*2+Q66*3),2) -> 0 | V66: 1019.01 | AC66: =ROUND(SUM(SUM(K66:N66)+SUM(R66:AB66)),2) -> 4919.01 | AD66: 657.36 | AE66: 171.34 | AF66: 24.65 | AG66: 657.39 | AH66: =AC66-AD66-AE66-AF66-AG66 -> 3408.27 | AI66: =MAX(ROUND(MAX((AH66+AR66-5000*AQ66-AT66)*{0.03,0.1,0.2,0.25,0.3,0.35,0.45}-{0,2520,16920,31920,52920,85920,181920},0)-AS66,2),0) -> 0 | AL66: =ROUND(LOOKUP(MAX(0.0001,AK66/12),{0;6;24;50;70;110;160}*500+0.0001,5*MAX(0,AK66)*{0.6;2;4;5;6;7;9}%-10*{0;21;141;266;441;716;1516}),2) -> 0 | AM66: =AC66+AK66+AJ66 -> 4919.01 | AP66: =ROUND(AH66-AI66+AK66-AL66+AO66+AN66,2) -> 3408.27 | AQ66: 6 | AR66: 34592.47 | AS66: 242.45 | AT66: 0 | AU66: 合杰区域分
A67: 66 | B67: 202606 | C67: MNCN00668 | D67: 王琳 | E67: 230119198905161023 | F67: 销售顾问 | G67: 成都 | H67: 2330 | I67: 44879 | K67: 3600 | N67: 300 | O67: 19 | Q67: 16 | R67: =ROUND(K67/174*SUM(O67*1.5+P67*2+Q67*3),2) -> 1582.76 | V67: 1696.17 | AC67: =ROUND(SUM(SUM(K67:N67)+SUM(R67:AB67)),2) -> 7178.93 | AD67: 250.4 | AE67: 62.6 | AF67: 12.52 | AG67: 631 | AH67: =AC67-AD67-AE67-AF67-AG67 -> 6222.41 | AI67: =MAX(ROUND(MAX((AH67+AR67-5000*AQ67-AT67)*{0.03,0.1,0.2,0.25,0.3,0.35,0.45}-{0,2520,16920,31920,52920,85920,181920},0)-AS67,2),0) -> 109.27 | AL67: =ROUND(LOOKUP(MAX(0.0001,AK67/12),{0;6;24;50;70;110;160}*500+0.0001,5*MAX(0,AK67)*{0.6;2;4;5;6;7;9}%-10*{0;21;141;266;441;716;1516}),2) -> 0 | AM67: =AC67+AK67+AJ67 -> 7178.93 | AP67: =ROUND(AH67-AI67+AK67-AL67+AO67+AN67,2) -> 6113.14 | AQ67: 6 | AR67: 56190.08 | AS67: 863.1 | AT67: 0 | AU67: 成都合杰
A68: 67 | B68: 202606 | C68: MNCN00673 | D68: 周峰 | E68: 500382198603225336 | F68: 销售顾问 | G68: 重庆 | H68: 2330 | I68: 44922 | K68: 3600 | N68: 300 | O68: 0 | Q68: 22 | R68: =ROUND(K68/174*SUM(O68*1.5+P68*2+Q68*3),2) -> 1365.52 | AC68: =ROUND(SUM(SUM(K68:N68)+SUM(R68:AB68)),2) -> 5265.52 | AD68: 583.92 | AE68: 150.98 | AF68: 36.5 | AG68: 421 | AH68: =AC68-AD68-AE68-AF68-AG68 -> 4073.12 | AI68: =MAX(ROUND(MAX((AH68+AR68-5000*AQ68-AT68)*{0.03,0.1,0.2,0.25,0.3,0.35,0.45}-{0,2520,16920,31920,52920,85920,181920},0)-AS68,2),0) -> 0 | AL68: =ROUND(LOOKUP(MAX(0.0001,AK68/12),{0;6;24;50;70;110;160}*500+0.0001,5*MAX(0,AK68)*{0.6;2;4;5;6;7;9}%-10*{0;21;141;266;441;716;1516}),2) -> 0 | AM68: =AC68+AK68+AJ68 -> 5265.52 | AP68: =ROUND(AH68-AI68+AK68-AL68+AO68+AN68,2) -> 4073.12 | AQ68: 6 | AR68: 27466.35 | AS68: 175.64 | AT68: 0 | AU68: 合杰区域分
A69: 68 | B69: 202606 | C69: MNCN00677 | D69: 王丹 | E69: 131121199101201441 | F69: 高级销售顾问 | G69: 北京 | H69: 2540 | I69: 44986 | K69: 4600 | N69: 300 | O69: 0 | Q69: 12 | R69: =ROUND(K69/174*SUM(O69*1.5+P69*2+Q69*3),2) -> 951.72 | AC69: =ROUND(SUM(SUM(K69:N69)+SUM(R69:AB69)),2) -> 5851.72 | AD69: 681.6 | AE69: 173.4 | AF69: 42.6 | AG69: 1022 | AH69: =AC69-AD69-AE69-AF69-AG69 -> 3932.12 | AI69: =MAX(ROUND(MAX((AH69+AR69-5000*AQ69-AT69)*{0.03,0.1,0.2,0.25,0.3,0.35,0.45}-{0,2520,16920,31920,52920,85920,181920},0)-AS69,2),0) -> 0 | AL69: =ROUND(LOOKUP(MAX(0.0001,AK69/12),{0;6;24;50;70;110;160}*500+0.0001,5*MAX(0,AK69)*{0.6;2;4;5;6;7;9}%-10*{0;21;141;266;441;716;1516}),2) -> 0 | AM69: =AC69+AK69+AJ69 -> 5851.72 | AP69: =ROUND(AH69-AI69+AK69-AL69+AO69+AN69,2) -> 3932.12 | AQ69: 6 | AR69: 25268.72 | AS69: 111.24 | AT69: 0 | AU69: 北京合杰
A70: 69 | B70: 202606 | C70: MNCN00679 | D70: 熊蒙蒙 | E70: 321323199806203649 | F70: 电商客服 | G70: 上海 | H70: 2740 | I70: 44999 | K70: 5500 | O70: 0 | Q70: 0 | R70: =ROUND(K70/174*SUM(O70*1.5+P70*2+Q70*3),2) -> 0 | V70: 3000 | AC70: =ROUND(SUM(SUM(K70:N70)+SUM(R70:AB70)),2) -> 8500 | AD70: 1305.8 | AE70: 326.45 | AF70: 81.61 | AG70: 1143 | AH70: =AC70-AD70-AE70-AF70-AG70 -> 5643.14 | AI70: =MAX(ROUND(MAX((AH70+AR70-5000*AQ70-AT70)*{0.03,0.1,0.2,0.25,0.3,0.35,0.45}-{0,2520,16920,31920,52920,85920,181920},0)-AS70,2),0) -> 350 | AL70: =ROUND(LOOKUP(MAX(0.0001,AK70/12),{0;6;24;50;70;110;160}*500+0.0001,5*MAX(0,AK70)*{0.6;2;4;5;6;7;9}%-10*{0;21;141;266;441;716;1516}),2) -> 0 | AM70: =AC70+AK70+AJ70 -> 8500 | AP70: =ROUND(AH70-AI70+AK70-AL70+AO70+AN70,2) -> 5293.14 | AQ70: 6 | AR70: 68202.98 | AS70: 1514.61 | AT70: 0 | AU70: 上海合杰
A71: 70 | B71: 202606 | C71: MNCN00681 | D71: 陈传波 | E71: 420683198510200554 | F71: 销售顾问 | G71: 武汉 | H71: 2400 | I71: 45017 | K71: 3600 | N71: 300 | O71: 32 | Q71: 16 | R71: =ROUND(K71/174*SUM(O71*1.5+P71*2+Q71*3),2) -> 1986.21 | V71: 1000 | W71: 1500 | AC71: =ROUND(SUM(SUM(K71:N71)+SUM(R71:AB71)),2) -> 8386.21 | AD71: 654.48 | AE71: 170.62 | AF71: 24.54 | AG71: 654.44 | AH71: =AC71-AD71-AE71-AF71-AG71 -> 6882.13 | AI71: =MAX(ROUND(MAX((AH71+AR71-5000*AQ71-AT71)*{0.03,0.1,0.2,0.25,0.3,0.35,0.45}-{0,2520,16920,31920,52920,85920,181920},0)-AS71,2),0) -> 0 | AL71: =ROUND(LOOKUP(MAX(0.0001,AK71/12),{0;6;24;50;70;110;160}*500+0.0001,5*MAX(0,AK71)*{0.6;2;4;5;6;7;9}%-10*{0;21;141;266;441;716;1516}),2) -> 0 | AM71: =AC71+AK71+AJ71 -> 8386.21 | AP71: =ROUND(AH71-AI71+AK71-AL71+AO71+AN71,2) -> 6882.13 | AQ71: 6 | AR71: 32274.64 | AS71: 79.35 | AT71: 14991 | AU71: 合杰区域分
A72: 71 | B72: 202606 | C72: MNCN00689 | D72: 张瑜婷 | E72: 360734199804210025 | F72: 销售顾问 | G72: 南昌 | H72: 2240 | I72: 45108 | J72: 46173 | K72: 3600 | L72: =-K72 -> -3600 | O72: 13 | Q72: 17 | R72: =ROUND(K72/174*SUM(O72*1.5+P72*2+Q72*3),2) -> 1458.62 | V72: 16.03 | AC72: =ROUND(SUM(SUM(K72:N72)+SUM(R72:AB72)),2) -> 1474.65 | AH72: =AC72-AD72-AE72-AF72-AG72 -> 1474.65 | AI72: =MAX(ROUND(MAX((AH72+AR72-5000*AQ72-AT72)*{0.03,0.1,0.2,0.25,0.3,0.35,0.45}-{0,2520,16920,31920,52920,85920,181920},0)-AS72,2),0) -> 0 | AL72: =ROUND(LOOKUP(MAX(0.0001,AK72/12),{0;6;24;50;70;110;160}*500+0.0001,5*MAX(0,AK72)*{0.6;2;4;5;6;7;9}%-10*{0;21;141;266;441;716;1516}),2) -> 0 | AM72: =AC72+AK72+AJ72 -> 1474.65 | AP72: =ROUND(AH72-AI72+AK72-AL72+AO72+AN72,2) -> 1474.65 | AQ72: 6 | AR72: 29220.45 | AS72: 128.82 | AT72: 0 | AU72: 合杰区域分
A73: 72 | B73: 202606 | C73: MNCN00695 | D73: 罗莎莎 | E73: 51072419900424082X | F73: 销售主管 | G73: 成都 | H73: 2330 | I73: 45231 | K73: 8000 | N73: 200 | O73: 20 | Q73: 16 | R73: =ROUND(K73/174*SUM(O73*1.5+P73*2+Q73*3),2) -> 3586.21 | V73: 647.76 | AC73: =ROUND(SUM(SUM(K73:N73)+SUM(R73:AB73)),2) -> 12433.97 | AD73: 772.08 | AE73: 193.02 | AF73: 38.61 | AG73: 737 | AH73: =AC73-AD73-AE73-AF73-AG73 -> 10693.26 | AI73: =MAX(ROUND(MAX((AH73+AR73-5000*AQ73-AT73)*{0.03,0.1,0.2,0.25,0.3,0.35,0.45}-{0,2520,16920,31920,52920,85920,181920},0)-AS73,2),0) -> 377.99 | AL73: =ROUND(LOOKUP(MAX(0.0001,AK73/12),{0;6;24;50;70;110;160}*500+0.0001,5*MAX(0,AK73)*{0.6;2;4;5;6;7;9}%-10*{0;21;141;266;441;716;1516}),2) -> 0 | AM73: =AC73+AK73+AJ73 -> 12433.97 | AP73: =ROUND(AH73-AI73+AK73-AL73+AO73+AN73,2) -> 10315.27 | AQ73: 6 | AR73: 63724.61 | AS73: 943.8 | AT73: 6000 | AU73: 成都合杰
A74: 73 | B74: 202606 | C74: MNCN00696 | D74: 姚顾周 | E74: 42108719830930323X | F74: 销售顾问 | G74: 深圳 | H74: 2520 | I74: 45231 | K74: 4200 | N74: 200 | O74: 0 | Q74: 16 | R74: =ROUND(K74/174*SUM(O74*1.5+P74*2+Q74*3),2) -> 1158.62 | V74: 5768 | AC74: =ROUND(SUM(SUM(K74:N74)+SUM(R74:AB74)),2) -> 11326.62 | AD74: 721.64 | AE74: 180.41 | AF74: 18.04 | AG74: 631.44 | AH74: =AC74-AD74-AE74-AF74-AG74 -> 9775.09 | AI74: =MAX(ROUND(MAX((AH74+AR74-5000*AQ74-AT74)*{0.03,0.1,0.2,0.25,0.3,0.35,0.45}-{0,2520,16920,31920,52920,85920,181920},0)-AS74,2),0) -> 89.29 | AL74: =ROUND(LOOKUP(MAX(0.0001,AK74/12),{0;6;24;50;70;110;160}*500+0.0001,5*MAX(0,AK74)*{0.6;2;4;5;6;7;9}%-10*{0;21;141;266;441;716;1516}),2) -> 0 | AM74: =AC74+AK74+AJ74 -> 11326.62 | AP74: =ROUND(AH74-AI74+AK74-AL74+AO74+AN74,2) -> 9685.8 | AQ74: 6 | AR74: 55908.26 | AS74: 711.21 | AT74: 9000 | AU74: 深圳合杰
A75: 74 | B75: 202606 | C75: MNCN00697 | D75: 张嵩扬 | E75: 220521198212290027 | F75: 销售主管 | G75: 北京 | H75: 2540 | I75: 45274 | K75: 8000 | N75: 200 | O75: 0 | Q75: 12 | R75: =ROUND(K75/174*SUM(O75*1.5+P75*2+Q75*3),2) -> 1655.17 | V75: 728.1 | AC75: =ROUND(SUM(SUM(K75:N75)+SUM(R75:AB75)),2) -> 10583.27 | AD75: 794.16 | AE75: 201.54 | AF75: 49.64 | AG75: 1191 | AH75: =AC75-AD75-AE75-AF75-AG75 -> 8346.93 | AI75: =MAX(ROUND(MAX((AH75+AR75-5000*AQ75-AT75)*{0.03,0.1,0.2,0.25,0.3,0.35,0.45}-{0,2520,16920,31920,52920,85920,181920},0)-AS75,2),0) -> 167.5 | AL75: =ROUND(LOOKUP(MAX(0.0001,AK75/12),{0;6;24;50;70;110;160}*500+0.0001,5*MAX(0,AK75)*{0.6;2;4;5;6;7;9}%-10*{0;21;141;266;441;716;1516}),2) -> 0 | AM75: =AC75+AK75+AJ75 -> 10583.27 | AP75: =ROUND(AH75-AI75+AK75-AL75+AO75+AN75,2) -> 8179.43 | AQ75: 6 | AR75: 42242.96 | AS75: 450.2 | AT75: 0 | AU75: 北京合杰
A76: 75 | B76: 202606 | C76: MNCN00699 | D76: 周丹 | E76: 110222198511116824 | F76: 销售顾问 | G76: 北京 | H76: 2540 | I76: 45384 | J76: 46155 | K76: 3800 | L76: =-K76 -> -3800 | O76: 0 | Q76: 20 | R76: =ROUND(K76/174*SUM(O76*1.5+P76*2+Q76*3),2) -> 1310.34 | V76: 1782.15 | AC76: =ROUND(SUM(SUM(K76:N76)+SUM(R76:AB76)),2) -> 3092.49 | AH76: =AC76-AD76-AE76-AF76-AG76 -> 3092.49 | AI76: =MAX(ROUND(MAX((AH76+AR76-5000*AQ76-AT76)*{0.03,0.1,0.2,0.25,0.3,0.35,0.45}-{0,2520,16920,31920,52920,85920,181920},0)-AS76,2),0) -> 0 | AL76: =ROUND(LOOKUP(MAX(0.0001,AK76/12),{0;6;24;50;70;110;160}*500+0.0001,5*MAX(0,AK76)*{0.6;2;4;5;6;7;9}%-10*{0;21;141;266;441;716;1516}),2) -> 0 | AM76: =AC76+AK76+AJ76 -> 3092.49 | AP76: =ROUND(AH76-AI76+AK76-AL76+AO76+AN76,2) -> 3092.49 | AQ76: 6 | AR76: 33086.39 | AS76: 374.37 | AT76: 0 | AU76: 北京合杰
A77: 76 | B77: 202606 | C77: MNCN00704 | D77: 邓怡青 | E77: 360105199208251213 | F77: 销售顾问 | G77: 南昌 | H77: 2240 | I77: 45397 | K77: 3600 | N77: 200 | O77: 19.5 | Q77: 17 | R77: =ROUND(K77/174*SUM(O77*1.5+P77*2+Q77*3),2) -> 1660.34 | V77: 16654.82 | AC77: =ROUND(SUM(SUM(K77:N77)+SUM(R77:AB77)),2) -> 22115.16 | AD77: 527.69 | AE77: 147.74 | AF77: 32.98 | AG77: 792 | AH77: =AC77-AD77-AE77-AF77-AG77 -> 20614.75 | AI77: =MAX(ROUND(MAX((AH77+AR77-5000*AQ77-AT77)*{0.03,0.1,0.2,0.25,0.3,0.35,0.45}-{0,2520,16920,31920,52920,85920,181920},0)-AS77,2),0) -> 365.94 | AL77: =ROUND(LOOKUP(MAX(0.0001,AK77/12),{0;6;24;50;70;110;160}*500+0.0001,5*MAX(0,AK77)*{0.6;2;4;5;6;7;9}%-10*{0;21;141;266;441;716;1516}),2) -> 0 | AM77: =AC77+AK77+AJ77 -> 22115.16 | AP77: =ROUND(AH77-AI77+AK77-AL77+AO77+AN77,2) -> 20248.81 | AQ77: 6 | AR77: 27409.38 | AS77: 174.78 | AT77: 0 | AU77: 合杰区域分
A78: 77 | B78: 202606 | C78: MNCN00707 | D78: 李琳 | E78: 420116199710180487 | F78: 高级销售顾问 | G78: 武汉 | H78: 2400 | I78: 45434 | K78: 4400 | N78: 200 | O78: 3 | Q78: 16 | R78: =ROUND(K78/174*SUM(O78*1.5+P78*2+Q78*3),2) -> 1327.59 | V78: 1862.54 | AC78: =ROUND(SUM(SUM(K78:N78)+SUM(R78:AB78)),2) -> 7790.13 | AD78: 543.36 | AE78: 142.84 | AF78: 20.38 | AG78: 543.35 | AH78: =AC78-AD78-AE78-AF78-AG78 -> 6540.2 | AI78: =MAX(ROUND(MAX((AH78+AR78-5000*AQ78-AT78)*{0.03,0.1,0.2,0.25,0.3,0.35,0.45}-{0,2520,16920,31920,52920,85920,181920},0)-AS78,2),0) -> 83.7 | AL78: =ROUND(LOOKUP(MAX(0.0001,AK78/12),{0;6;24;50;70;110;160}*500+0.0001,5*MAX(0,AK78)*{0.6;2;4;5;6;7;9}%-10*{0;21;141;266;441;716;1516}),2) -> 0 | AM78: =AC78+AK78+AJ78 -> 7790.13 | AP78: =ROUND(AH78-AI78+AK78-AL78+AO78+AN78,2) -> 6456.5 | AQ78: 6 | AR78: 54299.2 | AS78: 841.48 | AT78: 0 | AU78: 合杰区域分
A79: 78 | B79: 202606 | C79: MNCN00717 | D79: 徐殊 | E79: 36012120000506144X | F79: 销售顾问 | G79: 南昌 | H79: 2240 | I79: 45734 | J79: 46173 | K79: 3600 | L79: =-K79 -> -3600 | O79: 13.5 | Q79: 17.5 | R79: =ROUND(K79/174*SUM(O79*1.5+P79*2+Q79*3),2) -> 1505.17 | V79: 16.03 | AC79: =ROUND(SUM(SUM(K79:N79)+SUM(R79:AB79)),2) -> 1521.2 | AH79: =AC79-AD79-AE79-AF79-AG79 -> 1521.2 | AI79: =MAX(ROUND(MAX((AH79+AR79-5000*AQ79-AT79)*{0.03,0.1,0.2,0.25,0.3,0.35,0.45}-{0,2520,16920,31920,52920,85920,181920},0)-AS79,2),0) -> 0 | AL79: =ROUND(LOOKUP(MAX(0.0001,AK79/12),{0;6;24;50;70;110;160}*500+0.0001,5*MAX(0,AK79)*{0.6;2;4;5;6;7;9}%-10*{0;21;141;266;441;716;1516}),2) -> 0 | AM79: =AC79+AK79+AJ79 -> 1521.2 | AP79: =ROUND(AH79-AI79+AK79-AL79+AO79+AN79,2) -> 1521.2 | AQ79: 6 | AR79: 29311.71 | AS79: 103.3 | AT79: 0 | AU79: 合杰区域分
A80: 79 | B80: 202606 | C80: MNCN00718 | D80: 郭圣杰 | E80: 420116200212250011 | F80: 销售顾问 | G80: 武汉 | H80: 2400 | I80: 45761 | K80: 3600 | N80: 100 | O80: 0 | Q80: 11.5 | R80: =ROUND(K80/174*SUM(O80*1.5+P80*2+Q80*3),2) -> 713.79 | V80: 218.52 | AC80: =ROUND(SUM(SUM(K80:N80)+SUM(R80:AB80)),2) -> 4632.31 | AD80: 359.84 | AE80: 96.96 | AF80: 13.49 | AG80: 288 | AH80: =AC80-AD80-AE80-AF80-AG80 -> 3874.02 | AI80: =MAX(ROUND(MAX((AH80+AR80-5000*AQ80-AT80)*{0.03,0.1,0.2,0.25,0.3,0.35,0.45}-{0,2520,16920,31920,52920,85920,181920},0)-AS80,2),0) -> 0 | AL80: =ROUND(LOOKUP(MAX(0.0001,AK80/12),{0;6;24;50;70;110;160}*500+0.0001,5*MAX(0,AK80)*{0.6;2;4;5;6;7;9}%-10*{0;21;141;266;441;716;1516}),2) -> 0 | AM80: =AC80+AK80+AJ80 -> 4632.31 | AP80: =ROUND(AH80-AI80+AK80-AL80+AO80+AN80,2) -> 3874.02 | AQ80: 6 | AR80: 21557.75 | AS80: 0 | AT80: 0 | AU80: 合杰区域分
A81: 80 | B81: 202606 | C81: MNCN00285 | D81: 鲁业全 | E81: 513030198906301035 | F81: 高级销售顾问 | G81: 深圳 | H81: 2520 | I81: 45826 | K81: 4600 | N81: 43.33 | O81: 32 | Q81: 16 | R81: =ROUND(K81/174*SUM(O81*1.5+P81*2+Q81*3),2) -> 2537.93 | V81: 4107.48 | W81: 1500 | AC81: =ROUND(SUM(SUM(K81:N81)+SUM(R81:AB81)),2) -> 12788.74 | AD81: 382 | AE81: 134.54 | AF81: 9.2 | AG81: 322 | AH81: =AC81-AD81-AE81-AF81-AG81 -> 11941 | AI81: =MAX(ROUND(MAX((AH81+AR81-5000*AQ81-AT81)*{0.03,0.1,0.2,0.25,0.3,0.35,0.45}-{0,2520,16920,31920,52920,85920,181920},0)-AS81,2),0) -> 0 | AL81: =ROUND(LOOKUP(MAX(0.0001,AK81/12),{0;6;24;50;70;110;160}*500+0.0001,5*MAX(0,AK81)*{0.6;2;4;5;6;7;9}%-10*{0;21;141;266;441;716;1516}),2) -> 0 | AM81: =AC81+AK81+AJ81 -> 12788.74 | AP81: =ROUND(AH81-AI81+AK81-AL81+AO81+AN81,2) -> 11941 | AQ81: 6 | AR81: 53548.75 | AS81: 640.03 | AT81: 36000 | AU81: 深圳合杰
A82: 81 | B82: 202606 | C82: MNCN00723 | D82: 王永维 | E82: 130721199007055830 | F82: 高级销售顾问 | G82: 北京 | H82: 2540 | I82: 45875 | K82: 4600 | O82: 0 | Q82: 16 | R82: =ROUND(K82/174*SUM(O82*1.5+P82*2+Q82*3),2) -> 1268.97 | V82: 1330 | AC82: =ROUND(SUM(SUM(K82:N82)+SUM(R82:AB82)),2) -> 7198.97 | AD82: 572.96 | AE82: 146.24 | AF82: 35.81 | AG82: 552 | AH82: =AC82-AD82-AE82-AF82-AG82 -> 5891.96 | AI82: =MAX(ROUND(MAX((AH82+AR82-5000*AQ82-AT82)*{0.03,0.1,0.2,0.25,0.3,0.35,0.45}-{0,2520,16920,31920,52920,85920,181920},0)-AS82,2),0) -> 0 | AL82: =ROUND(LOOKUP(MAX(0.0001,AK82/12),{0;6;24;50;70;110;160}*500+0.0001,5*MAX(0,AK82)*{0.6;2;4;5;6;7;9}%-10*{0;21;141;266;441;716;1516}),2) -> 0 | AM82: =AC82+AK82+AJ82 -> 7198.97 | AP82: =ROUND(AH82-AI82+AK82-AL82+AO82+AN82,2) -> 5891.96 | AQ82: 6 | AR82: 20633.29 | AS82: 21.56 | AT82: 0 | AU82: 北京合杰
A83: 82 | B83: 202606 | C83: MNCN00725 | D83: 张欢欢 | E83: 342221199203055081 | F83: 销售顾问 | G83: 张家港 | H83: 2660 | I83: 45930 | K83: 3600 | O83: 17 | Q83: 20 | R83: =ROUND(K83/174*SUM(O83*1.5+P83*2+Q83*3),2) -> 1768.97 | V83: 2000 | AC83: =ROUND(SUM(SUM(K83:N83)+SUM(R83:AB83)),2) -> 7368.97 | AD83: 529.6 | AE83: 137.4 | AF83: 33.1 | AG83: 397 | AH83: =AC83-AD83-AE83-AF83-AG83 -> 6271.87 | AI83: =MAX(ROUND(MAX((AH83+AR83-5000*AQ83-AT83)*{0.03,0.1,0.2,0.25,0.3,0.35,0.45}-{0,2520,16920,31920,52920,85920,181920},0)-AS83,2),0) -> 71.07 | AL83: =ROUND(LOOKUP(MAX(0.0001,AK83/12),{0;6;24;50;70;110;160}*500+0.0001,5*MAX(0,AK83)*{0.6;2;4;5;6;7;9}%-10*{0;21;141;266;441;716;1516}),2) -> 0 | AM83: =AC83+AK83+AJ83 -> 7368.97 | AP83: =ROUND(AH83-AI83+AK83-AL83+AO83+AN83,2) -> 6200.8 | AQ83: 6 | AR83: 33598.55 | AS83: 225.04 | AT83: 0 | AU83: 上海合杰
A84: 83 | B84: 202606 | C84: MNCN00727 | D84: 杨利芳 | E84: 410326198808163746 | F84: 销售顾问 | G84: 天津 | H84: 2510 | I84: 45992 | K84: 3600 | O84: 40 | Q84: 16 | R84: =ROUND(K84/174*SUM(O84*1.5+P84*2+Q84*3),2) -> 2234.48 | V84: 1000 | W84: 1500 | AC84: =ROUND(SUM(SUM(K84:N84)+SUM(R84:AB84)),2) -> 8334.48 | AD84: 409.92 | AE84: 123.48 | AF84: 25.62 | AG84: 396 | AH84: =AC84-AD84-AE84-AF84-AG84 -> 7379.46 | AI84: =MAX(ROUND(MAX((AH84+AR84-5000*AQ84-AT84)*{0.03,0.1,0.2,0.25,0.3,0.35,0.45}-{0,2520,16920,31920,52920,85920,181920},0)-AS84,2),0) -> 100.03 | AL84: =ROUND(LOOKUP(MAX(0.0001,AK84/12),{0;6;24;50;70;110;160}*500+0.0001,5*MAX(0,AK84)*{0.6;2;4;5;6;7;9}%-10*{0;21;141;266;441;716;1516}),2) -> 0 | AM84: =AC84+AK84+AJ84 -> 8334.48 | AP84: =ROUND(AH84-AI84+AK84-AL84+AO84+AN84,2) -> 7279.43 | AQ84: 6 | AR84: 34110.65 | AS84: 244.67 | AT84: 0 | AU84: 合杰区域分
A85: 84 | B85: 202606 | C85: MNCN00729 | D85: 江婷婷 | E85: 445281199201232120 | F85: 销售顾问 | G85: 深圳 | H85: 2520 | I85: 46015 | J85: 46157 | K85: 3800 | L85: =-K85 -> -3800 | O85: 0 | Q85: 16 | R85: =ROUND(K85/174*SUM(O85*1.5+P85*2+Q85*3),2) -> 1048.28 | V85: 89.7 | AC85: =ROUND(SUM(SUM(K85:N85)+SUM(R85:AB85)),2) -> 1137.98 | AH85: =AC85-AD85-AE85-AF85-AG85 -> 1137.98 | AI85: =MAX(ROUND(MAX((AH85+AR85-5000*AQ85-AT85)*{0.03,0.1,0.2,0.25,0.3,0.35,0.45}-{0,2520,16920,31920,52920,85920,181920},0)-AS85,2),0) -> 0 | AL85: =ROUND(LOOKUP(MAX(0.0001,AK85/12),{0;6;24;50;70;110;160}*500+0.0001,5*MAX(0,AK85)*{0.6;2;4;5;6;7;9}%-10*{0;21;141;266;441;716;1516}),2) -> 0 | AM85: =AC85+AK85+AJ85 -> 1137.98 | AP85: =ROUND(AH85-AI85+AK85-AL85+AO85+AN85,2) -> 1137.98 | AQ85: 6 | AR85: 26356.49 | AS85: 106.23 | AT85: 0 | AU85: 深圳合杰
A86: 85 | B86: 202606 | C86: MNCN00737 | D86: 潘莉文 | E86: 341124199404044023 | F86: 销售顾问 | G86: 上海 | H86: 2740 | I86: 46113 | K86: 3800 | O86: 24.5 | Q86: 27.5 | R86: =ROUND(K86/174*SUM(O86*1.5+P86*2+Q86*3),2) -> 2604.31 | V86: 413.79 | W86: 500 | AC86: =ROUND(SUM(SUM(K86:N86)+SUM(R86:AB86)),2) -> 7318.1 | AD86: 596.8 | AE86: 149.2 | AF86: 37.3 | AG86: 266 | AH86: =AC86-AD86-AE86-AF86-AG86 -> 6268.8 | AI86: =MAX(ROUND(MAX((AH86+AR86-5000*AQ86-AT86)*{0.03,0.1,0.2,0.25,0.3,0.35,0.45}-{0,2520,16920,31920,52920,85920,181920},0)-AS86,2),0) -> 0 | AL86: =ROUND(LOOKUP(MAX(0.0001,AK86/12),{0;6;24;50;70;110;160}*500+0.0001,5*MAX(0,AK86)*{0.6;2;4;5;6;7;9}%-10*{0;21;141;266;441;716;1516}),2) -> 0 | AM86: =AC86+AK86+AJ86 -> 7318.1 | AP86: =ROUND(AH86-AI86+AK86-AL86+AO86+AN86,2) -> 6268.8 | AQ86: 3 | AR86: 6375.99 | AS86: 0 | AT86: 0 | AU86: 上海合杰
A87: 86 | B87: 202606 | C87: MNCN00739 | D87: 冯莉 | E87: 420114198702065422 | F87: 销售顾问 | G87: 武汉 | H87: 2400 | I87: 46129 | K87: 3600 | O87: 0 | Q87: 11.5 | R87: =ROUND(K87/174*SUM(O87*1.5+P87*2+Q87*3),2) -> 713.79 | V87: 2000 | AC87: =ROUND(SUM(SUM(K87:N87)+SUM(R87:AB87)),2) -> 6313.79 | AD87: 359.84 | AE87: 96.96 | AF87: 13.49 | AG87: 288 | AH87: =AC87-AD87-AE87-AF87-AG87 -> 5555.5 | AI87: =MAX(ROUND(MAX((AH87+AR87-5000*AQ87-AT87)*{0.03,0.1,0.2,0.25,0.3,0.35,0.45}-{0,2520,16920,31920,52920,85920,181920},0)-AS87,2),0) -> 0 | AL87: =ROUND(LOOKUP(MAX(0.0001,AK87/12),{0;6;24;50;70;110;160}*500+0.0001,5*MAX(0,AK87)*{0.6;2;4;5;6;7;9}%-10*{0;21;141;266;441;716;1516}),2) -> 0 | AM87: =AC87+AK87+AJ87 -> 6313.79 | AP87: =ROUND(AH87-AI87+AK87-AL87+AO87+AN87,2) -> 5555.5 | AQ87: 3 | AR87: 5611.25 | AS87: 0 | AT87: 0 | AU87: 合杰区域分
A88: 87 | B88: 202606 | C88: MNCN00740 | D88: 丁家恒 | E88: 420923199511134397 | F88: 销售顾问 | G88: 武汉 | H88: 2400 | I88: 46131 | J88: 46181 | K88: 3600 | L88: -2565.52 | O88: 0 | Q88: 11.5 | R88: =ROUND(K88/174*SUM(O88*1.5+P88*2+Q88*3),2) -> 713.79 | V88: 2000 | AC88: =ROUND(SUM(SUM(K88:N88)+SUM(R88:AB88)),2) -> 3748.27 | AD88: -719.68 | AE88: -193.92 | AF88: -26.98 | AG88: 288 | AH88: =AC88-AD88-AE88-AF88-AG88 -> 4400.85 | AI88: =MAX(ROUND(MAX((AH88+AR88-5000*AQ88-AT88)*{0.03,0.1,0.2,0.25,0.3,0.35,0.45}-{0,2520,16920,31920,52920,85920,181920},0)-AS88,2),0) -> 0 | AL88: =ROUND(LOOKUP(MAX(0.0001,AK88/12),{0;6;24;50;70;110;160}*500+0.0001,5*MAX(0,AK88)*{0.6;2;4;5;6;7;9}%-10*{0;21;141;266;441;716;1516}),2) -> 0 | AM88: =AC88+AK88+AJ88 -> 3748.27 | AP88: =ROUND(AH88-AI88+AK88-AL88+AO88+AN88,2) -> 4400.85 | AQ88: 3 | AR88: 5214.12 | AS88: 0 | AT88: 0 | AU88: 合杰区域分
A89: 88 | B89: 202606 | C89: MNCN00741 | D89: 魏华 | E89: 210114198602035120 | F89: 销售顾问 | G89: 沈阳 | H89: 2230 | I89: 46132 | K89: 3600 | O89: 29 | Q89: 0 | R89: =ROUND(K89/174*SUM(O89*1.5+P89*2+Q89*3),2) -> 900 | W89: 1500 | AC89: =ROUND(SUM(SUM(K89:N89)+SUM(R89:AB89)),2) -> 6000 | AD89: 348.72 | AE89: 96.92 | AF89: 21.8 | AG89: 432 | AH89: =AC89-AD89-AE89-AF89-AG89 -> 5100.56 | AI89: =MAX(ROUND(MAX((AH89+AR89-5000*AQ89-AT89)*{0.03,0.1,0.2,0.25,0.3,0.35,0.45}-{0,2520,16920,31920,52920,85920,181920},0)-AS89,2),0) -> 0 | AL89: =ROUND(LOOKUP(MAX(0.0001,AK89/12),{0;6;24;50;70;110;160}*500+0.0001,5*MAX(0,AK89)*{0.6;2;4;5;6;7;9}%-10*{0;21;141;266;441;716;1516}),2) -> 0 | AM89: =AC89+AK89+AJ89 -> 6000 | AP89: =ROUND(AH89-AI89+AK89-AL89+AO89+AN89,2) -> 5100.56 | AQ89: 3 | AR89: 4124.22 | AS89: 0 | AT89: 0 | AU89: 合杰区域分
A90: 89 | B90: 202606 | C90: MNCN00742 | D90: 刘玉栋 | E90: 120105199601302115 | F90: 销售顾问 | G90: 天津 | H90: 2510 | I90: 46133 | K90: 3600 | O90: 0 | Q90: 16 | R90: =ROUND(K90/174*SUM(O90*1.5+P90*2+Q90*3),2) -> 993.1 | V90: 1000 | W90: 1500 | AC90: =ROUND(SUM(SUM(K90:N90)+SUM(R90:AB90)),2) -> 7093.1 | AD90: 409.92 | AE90: 123.48 | AF90: 25.62 | AG90: 396 | AH90: =AC90-AD90-AE90-AF90-AG90 -> 6138.08 | AI90: =MAX(ROUND(MAX((AH90+AR90-5000*AQ90-AT90)*{0.03,0.1,0.2,0.25,0.3,0.35,0.45}-{0,2520,16920,31920,52920,85920,181920},0)-AS90,2),0) -> 0 | AL90: =ROUND(LOOKUP(MAX(0.0001,AK90/12),{0;6;24;50;70;110;160}*500+0.0001,5*MAX(0,AK90)*{0.6;2;4;5;6;7;9}%-10*{0;21;141;266;441;716;1516}),2) -> 0 | AM90: =AC90+AK90+AJ90 -> 7093.1 | AP90: =ROUND(AH90-AI90+AK90-AL90+AO90+AN90,2) -> 6138.08 | AQ90: 3 | AR90: 5621.96 | AS90: 0 | AT90: 0 | AU90: 合杰区域分
A91: 90 | B91: 202606 | D91: 马艳华 | E91: 310113198004211726 | G91: 上海 | H91: 2740 | I91: 46174 | K91: 17000 | R91: =ROUND(K91/174*SUM(O91*1.5+P91*2+Q91*3),2) -> 0 | AC91: =ROUND(SUM(SUM(K91:N91)+SUM(R91:AB91)),2) -> 17000 | AD91: 1360 | AE91: 340 | AF91: 85 | AG91: 1190 | AH91: =AC91-AD91-AE91-AF91-AG91 -> 14025 | AI91: =MAX(ROUND(MAX((AH91+AR91-5000*AQ91-AT91)*{0.03,0.1,0.2,0.25,0.3,0.35,0.45}-{0,2520,16920,31920,52920,85920,181920},0)-AS91,2),0) -> 270.75 | AL91: =ROUND(LOOKUP(MAX(0.0001,AK91/12),{0;6;24;50;70;110;160}*500+0.0001,5*MAX(0,AK91)*{0.6;2;4;5;6;7;9}%-10*{0;21;141;266;441;716;1516}),2) -> 0 | AM91: =AC91+AK91+AJ91 -> 17000 | AP91: =ROUND(AH91-AI91+AK91-AL91+AO91+AN91,2) -> 13754.25 | AQ91: 1 | AT91: 0 | AU91: 上海合杰
A92: 91 | B92: 202606 | D92: 何娜玉 | E92: 341623200209068042 | G92: 上海 | H92: 2740 | I92: 46160 | K92: 3030 | R92: =ROUND(K92/174*SUM(O92*1.5+P92*2+Q92*3),2) -> 0 | AC92: =ROUND(SUM(SUM(K92:N92)+SUM(R92:AB92)),2) -> 3030 | AH92: =AC92-AD92-AE92-AF92-AG92 -> 3030 | AI92: =MAX(ROUND(MAX((AH92+AR92-5000*AQ92-AT92)*{0.03,0.1,0.2,0.25,0.3,0.35,0.45}-{0,2520,16920,31920,52920,85920,181920},0)-AS92,2),0) -> 0 | AL92: =ROUND(LOOKUP(MAX(0.0001,AK92/12),{0;6;24;50;70;110;160}*500+0.0001,5*MAX(0,AK92)*{0.6;2;4;5;6;7;9}%-10*{0;21;141;266;441;716;1516}),2) -> 0 | AM92: =AC92+AK92+AJ92 -> 3030 | AP92: =ROUND(AH92-AI92+AK92-AL92+AO92+AN92,2) -> 3030 | AQ92: 1 | AT92: 0 | AU92: 上海合杰
K93: =SUBTOTAL(9,K2:K92) -> 422830 | L93: =SUBTOTAL(9,L2:L92) -> -32965.52 | M93: =SUBTOTAL(9,M2:M92) -> 0 | N93: 39704.08 | O93: =SUBTOTAL(9,O2:O92) -> 621.75 | P93: =SUBTOTAL(9,P2:P92) -> 0 | Q93: =SUBTOTAL(9,Q2:Q92) -> 1247 | R93: =SUBTOTAL(9,R2:R92) -> 120389.2 | S93: =SUBTOTAL(9,S2:S92) -> 0 | T93: =SUBTOTAL(9,T2:T92) -> 0 | U93: =SUBTOTAL(9,U2:U92) -> 0 | V93: =SUBTOTAL(9,V2:V92) -> 230705.26 | ... AP93: =SUBTOTAL(9,AP2:AP92) -> 614115.03

Sheet Sheet7
A1: 聂贝
A2: 社保 | B2: 695.67
A3: 工资 | B3: 7970.36
A4: 1月扣回 | B4: 354.62
A5: 2月扣回 | B5: 341.05
A6: 3月扣回 | B6: 375.98
A7: 4月扣回 | B7: 403.24
A8: 5月扣回 | B8: 354.62
A9: 6月扣回 | B9: -362.36
B10: 6836.52
