Workbook

Sheet Tax rate table
B2: Yearly tax rate table
B3: Taxable income range | D3: Tax Rate | E3: Quick Calculation Deduction
B4: 0 | C4: 36000 | D4: 0.03 | E4: 0
B5: 36000.01 | C5: 144000 | D5: 0.1 | E5: 2520
B6: 144000.01 | C6: 300000 | D6: 0.2 | E6: 16920
B7: 300000.01 | C7: 420000 | D7: 0.25 | E7: 31920
B8: 420000.01 | C8: 660000 | D8: 0.3 | E8: 52920
B9: 660000.01 | C9: 960000 | D9: 0.35 | E9: 85920
B10: 960000.01 | C10: 1200000000 | D10: 0.45 | E10: 181920
B11: Apply to China tax resident
B12: - A foreign individual being regarded as China non-domiciled individual will become a China resident if he/she has resided in mainland China for 183 days or more in a calendar year
B13: - In counting the days residing in China, the day of stay in China lasting for less than 24 hours will not be counted
B16: Monthly tax rate table
B17: Taxable income range | D17: Tax Rate | E17: Quick Calculation Deduction
B18: 0 | C18: 3000 | D18: 0.03 | E18: 0
B19: 3000.01 | C19: 12000 | D19: 0.1 | E19: 210
B20: 12000.01 | C20: 25000 | D20: 0.2 | E20: 1410
B21: 25000.01 | C21: 35000 | D21: 0.25 | E21: 2660
B22: 35000.01 | C22: 55000 | D22: 0.3 | E22: 4410
B23: 55000.01 | C23: 80000 | D23: 0.35 | E23: 7160
B24: 80000.01 | C24: 100000000 | D24: 0.45 | E24: 15160
B25: Apply to China tax non-resident
B26: - A foreign individual being regarded as China non-domiciled individual will become a China non-resident if he/she has resided in mainland China for less than 183 days in a calendar year
B27: - In counting the days residing in China, the day of stay in China lasting for less than 24 hours will not be counted
B30: *If you have any questions about tax policy or payroll calculation details, please contact HR Local Service team:
B31: Sherry Chen
B32: 021-52880407
B33: sherry_3.chen@boehringer-ingelheim.com

Sheet Salary details
B1: 马云 Yun Ma Y2026 Payslip
B2: Employee ID | C2: &=DT.雇员编号
B3: Employee Name | C3: &=DT.雇员姓名
B4: Legal entity | C4: BICHC
B5: Department | C5: HP-Medicine
B6: Passport No. | C6: 683277300
B8: Items | C8: &=DT.月份(horizontal,shift,copystyle) | E8: 46082 | F8: 46113 | G8: 46143 | H8: 46174 | I8: 46204 | J8: 46235 | K8: 46266 | L8: 46296 | M8: 46327 | N8: 46357
B9: Monthly salary
B10: Monthly Base Salary | C10: &=DT.基本工资(horizontal,shift,copystyle)
B11: Salary Balance
B12: Unpaid Leave Deduction
B13: Sick Leave Deduction
B14: Over-use Annual Leave Deductio
B15: Supplementary Housing Allowance | C15: 0
B16: Meal Allowance | C16: 506
B17: Transportation Allowance | C17: 726
B18: Cash Allowance | C18: 0
B19: Relocation Allowance | C19: 0
B20: AH Position Allowance | C20: 0
B21: Position Premium | C21: 0
B22: High temperature allowance | C22: 0
B23: Car Allowance | C23: 0
B24: Overtime | C24: 0
B25: Shift Allowance | C25: 0
B26: Sign-on Bonus | C26: 0
... B35: Year-end Bonus(Gross) | C35: 0
B36: Total Gross Income | C36: =SUM(C10:C35) -> 1232 | E36: =SUM(E10:E35) -> 0 | F36: =SUM(F10:F35) -> 0 | G36: =SUM(G10:G35) -> 0 | H36: =SUM(H10:H35) -> 0 | I36: =SUM(I10:I35) -> 0 | J36: =SUM(J10:J35) -> 0 | K36: =SUM(K10:K35) -> 0 | L36: =SUM(L10:L35) -> 0 | ... N36: =SUM(N10:N35) -> 0
B37: Total individual social insurance | C37: 0 | E37: 0 | F37: 0 | G37: 0 | H37: 0 | I37: 0 | J37: 0 | K37: 0 | L37: 0 | M37: 0 | N37: 0
B38: YTD Special additional deductions | C38: 0 | E38: 0 | F38: 0 | G38: 0 | H38: 0 | I38: 0 | J38: 0 | K38: 0 | L38: 0 | M38: 0 | N38: 0
B39: YTD taxable income | C39: =C36-C37-C38-5000*MONTH(C8) -> #VALUE! | E39: =SUM($C$36:E36,$C$55:D$56,SUM($C$61:D63))-SUM($C$37:E37)-E38-5000*MONTH(E8) -> -13768 | F39: =SUM($C$36:F36,$C$55:E$56,SUM($C$61:E63))-SUM($C$37:F37)-F38-5000*MONTH(F8) -> -18768 | G39: =SUM($C$36:G36,$C$55:F$56,SUM($C$61:F63))-SUM($C$37:G37)-G38-5000*MONTH(G8) -> -23768 | H39: =SUM($C$36:H36,$C$55:G$56,SUM($C$61:G63))-SUM($C$37:H37)-H38-5000*MONTH(H8) -> -28768 | I39: =SUM($C$36:I36,$C$55:H$56,SUM($C$61:H63),C43:H43)-SUM($C$37:I37)-I38-5000*MONTH(I8) -> -33759.12 | J39: =SUM($C$36:J36,$C$55:I$56,SUM($C$61:I63),D43:I43)-SUM($C$37:J37)-J38-5000*MONTH(J8) -> -38759.12 | K39: =SUM($C$36:K36,$C$55:J$56,SUM($C$61:J63),E43:J43)-SUM($C$37:K37)-K38-5000*MONTH(K8) -> -43759.12 | L39: =SUM($C$36:L36,$C$55:K$56,SUM($C$61:K63),F43:K43)-SUM($C$37:L37)-L38-5000*MONTH(L8) -> -48759.12 | M39: =SUM($C$36:M36,$C$55:L$56,SUM($C$61:L63),G43:L43)-SUM($C$37:M37)-M38-5000*MONTH(M8) -> -53759.12 | N39: =SUM($C$36:N36,$C$55:M$56,SUM($C$61:M63),H43:M43)-SUM($C$37:N37)-N38-5000*MONTH(N8) -> -58759.12
B40: Tax Rate | C40: =LOOKUP(C39,'Tax rate table'!$B$4:$C$10,'Tax rate table'!$D$4:$D$10) -> #VALUE! | E40: =LOOKUP(E39,'Tax rate table'!$B$4:$C$10,'Tax rate table'!$D$4:$D$10) -> #N/A | F40: =LOOKUP(F39,'Tax rate table'!$B$4:$C$10,'Tax rate table'!$D$4:$D$10) -> #N/A | G40: =LOOKUP(G39,'Tax rate table'!$B$4:$C$10,'Tax rate table'!$D$4:$D$10) -> #N/A | H40: =LOOKUP(H39,'Tax rate table'!$B$4:$C$10,'Tax rate table'!$D$4:$D$10) -> #N/A | I40: =LOOKUP(I39,'Tax rate table'!$B$4:$C$10,'Tax rate table'!$D$4:$D$10) -> #N/A | J40: =LOOKUP(J39,'Tax rate table'!$B$4:$C$10,'Tax rate table'!$D$4:$D$10) -> #N/A | K40: =LOOKUP(K39,'Tax rate table'!$B$4:$C$10,'Tax rate table'!$D$4:$D$10) -> #N/A | L40: =LOOKUP(L39,'Tax rate table'!$B$4:$C$10,'Tax rate table'!$D$4:$D$10) -> #N/A | ... N40: =LOOKUP(N39,'Tax rate table'!$B$4:$C$10,'Tax rate table'!$D$4:$D$10) -> #N/A
B41: Quick Calculation Deduction | C41: =LOOKUP(C39,'Tax rate table'!$B$4:$C$10,'Tax rate table'!$E$4:$E$10) -> #VALUE! | E41: =LOOKUP(E39,'Tax rate table'!$B$4:$C$10,'Tax rate table'!$E$4:$E$10) -> #N/A | F41: =LOOKUP(F39,'Tax rate table'!$B$4:$C$10,'Tax rate table'!$E$4:$E$10) -> #N/A | G41: =LOOKUP(G39,'Tax rate table'!$B$4:$C$10,'Tax rate table'!$E$4:$E$10) -> #N/A | H41: =LOOKUP(H39,'Tax rate table'!$B$4:$C$10,'Tax rate table'!$E$4:$E$10) -> #N/A | I41: =LOOKUP(I39,'Tax rate table'!$B$4:$C$10,'Tax rate table'!$E$4:$E$10) -> #N/A | J41: =LOOKUP(J39,'Tax rate table'!$B$4:$C$10,'Tax rate table'!$E$4:$E$10) -> #N/A | K41: =LOOKUP(K39,'Tax rate table'!$B$4:$C$10,'Tax rate table'!$E$4:$E$10) -> #N/A | L41: =LOOKUP(L39,'Tax rate table'!$B$4:$C$10,'Tax rate table'!$E$4:$E$10) -> #N/A | ... N41: =LOOKUP(N39,'Tax rate table'!$B$4:$C$10,'Tax rate table'!$E$4:$E$10) -> #N/A
B42: Individual Income Tax (Monthly) | C42: =ROUND(C39*C40-C41,2) -> #VALUE! | E42: =ROUND(E39*E40-E41,2)-SUM($C$42:D42)-SUM(C57:D58)-SUM($C$64:D66) -> #N/A | F42: =ROUND(F39*F40-F41,2)-SUM($C$42:E42)-SUM($C$64:E66) -> #N/A | G42: =ROUND(G39*G40-G41,2)-SUM($C$42:F42)-SUM(C57:F58)-SUM($C$64:F66) -> #N/A | H42: =ROUND(H39*H40-H41,2)-SUM($C$42:G42)-SUM(D57:G58)-SUM($C$64:G66) -> #N/A | I42: =ROUND(I39*I40-I41,2)-SUM($C$42:H42)-SUM(C57:H58)-SUM($C$64:H66)-SUM(C44:H44) -> #N/A | J42: =ROUND(J39*J40-J41,2)-SUM($C$42:I42)-SUM(D57:I58)-SUM($C$64:I66)-SUM(D44:I44) -> #N/A | K42: =ROUND(K39*K40-K41,2)-SUM($C$42:J42)-SUM(E57:J58)-SUM($C$64:J66)-SUM(E44:J44) -> #N/A | L42: =ROUND(L39*L40-L41,2)-SUM($C$42:K42)-SUM(F57:K58)-SUM($C$64:K66)-SUM(F44:K44) -> #N/A | M42: =ROUND(M39*M40-M41,2)-SUM($C$42:L42)-SUM(G57:L58)-SUM($C$64:L66)-SUM(G44:L44) -> #N/A | N42: =ROUND(N39*N40-N41,2)-SUM($C$42:M42)-SUM($C$57:M58)-SUM($C$64:M66)-SUM($C$44:M44) -> #N/A
B43: Annual meeting Prize | C43: 0 | E43: 0 | F43: 0 | G43: 0 | H43: 8.88 | I43: 0 | J43: 0 | K43: 0 | N43: 38
B44: Annual meeting Prize (Tax) | C44: 0 | E44: 0 | F44: 0 | G44: 0 | H44: =IF(H43=0,SUM($C$42:H42)+SUM(D57:G58)+SUM($C$64:G66),IF(H43+H39-36000<=0,(H43+H39)*3%,(IF(H434+H39-144000<=0,(H43+H39)*10%-2520,(IF(H434+H39-300000<=0,(H43+H39)*20%-16920,(IF(H434+H39-420000<=0,(H43+H39)*25%-31920,(IF(H434+H39-660000<=0,(H43+H39)*30%-52920,(IF(H434+H39-960000<=0,(H43+H39)*35%-85920,(IF(H434+H39-960000<=0,(H43+H39)*35%-7160,(H43+H39)*45%-181920))))))))))))))-SUM($C$42:H42)-SUM(D57:G58)-SUM($C$64:G66) -> #VALUE! | I44: =IF(I43=0,SUM($C$42:I42)+SUM(E57:H58)+SUM($C$64:H66),IF(I43+I39-36000<=0,(I43+I39)*3%,(IF(I434+I39-144000<=0,(I43+I39)*10%-2520,(IF(I434+I39-300000<=0,(I43+I39)*20%-16920,(IF(I434+I39-420000<=0,(I43+I39)*25%-31920,(IF(I434+I39-660000<=0,(I43+I39)*30%-52920,(IF(I434+I39-960000<=0,(I43+I39)*35%-85920,(IF(I434+I39-960000<=0,(I43+I39)*35%-7160,(I43+I39)*45%-181920))))))))))))))-SUM($C$42:I42)-SUM(E57:H58)-SUM($C$64:H66) -> #VALUE! | J44: =IF(J43=0,SUM($C$42:J42)+SUM(F57:I58)+SUM($C$64:I66),IF(J43+J39-36000<=0,(J43+J39)*3%,(IF(J434+J39-144000<=0,(J43+J39)*10%-2520,(IF(J434+J39-300000<=0,(J43+J39)*20%-16920,(IF(J434+J39-420000<=0,(J43+J39)*25%-31920,(IF(J434+J39-660000<=0,(J43+J39)*30%-52920,(IF(J434+J39-960000<=0,(J43+J39)*35%-85920,(IF(J434+J39-960000<=0,(J43+J39)*35%-7160,(J43+J39)*45%-181920))))))))))))))-SUM($C$42:J42)-SUM(F57:I58)-SUM($C$64:I66) -> #VALUE! | K44: =IF(K43=0,SUM($C$42:K42)+SUM(G57:J58)+SUM($C$64:J66),IF(K43+K39-36000<=0,(K43+K39)*3%,(IF(K434+K39-144000<=0,(K43+K39)*10%-2520,(IF(K434+K39-300000<=0,(K43+K39)*20%-16920,(IF(K434+K39-420000<=0,(K43+K39)*25%-31920,(IF(K434+K39-660000<=0,(K43+K39)*30%-52920,(IF(K434+K39-960000<=0,(K43+K39)*35%-85920,(IF(K434+K39-960000<=0,(K43+K39)*35%-7160,(K43+K39)*45%-181920))))))))))))))-SUM($C$42:K42)-SUM(G57:J58)-SUM($C$64:J66) -> #VALUE! | L44: =IF(L43=0,SUM($C$42:L42)+SUM(H57:K58)+SUM($C$64:K66),IF(L43+L39-36000<=0,(L43+L39)*3%,(IF(L434+L39-144000<=0,(L43+L39)*10%-2520,(IF(L434+L39-300000<=0,(L43+L39)*20%-16920,(IF(L434+L39-420000<=0,(L43+L39)*25%-31920,(IF(L434+L39-660000<=0,(L43+L39)*30%-52920,(IF(L434+L39-960000<=0,(L43+L39)*35%-85920,(IF(L434+L39-960000<=0,(L43+L39)*35%-7160,(L43+L39)*45%-181920))))))))))))))-SUM($C$42:L42)-SUM(H57:K58)-SUM($C$64:K66) -> #VALUE! | M44: =IF(M43=0,SUM($C$42:M42)+SUM(I57:L58)+SUM($C$64:L66),IF(M43+M39-36000<=0,(M43+M39)*3%,(IF(M434+M39-144000<=0,(M43+M39)*10%-2520,(IF(M434+M39-300000<=0,(M43+M39)*20%-16920,(IF(M434+M39-420000<=0,(M43+M39)*25%-31920,(IF(M434+M39-660000<=0,(M43+M39)*30%-52920,(IF(M434+M39-960000<=0,(M43+M39)*35%-85920,(IF(M434+M39-960000<=0,(M43+M39)*35%-7160,(M43+M39)*45%-181920))))))))))))))-SUM($C$42:M42)-SUM(I57:L58)-SUM($C$64:L66) -> #VALUE! | N44: =IF(N43=0,SUM($C$42:N42)+SUM($C$57:M58)+SUM($C$64:M66),IF(N43+N39-36000<=0,(N43+N39)*3%,(IF(N43+N39-144000<=0,(N43+N39)*10%-2520,(IF(N43+N39-300000<=0,(N43+N39)*20%-16920,(IF(N43+N39-420000<=0,(N43+N39)*25%-31920,(IF(N43+N39-660000<=0,(N43+N39)*30%-52920,(IF(N43+N39-960000<=0,(N43+N39)*35%-85920,(IF(N43+N39-960000<=0,(N43+N39)*35%-7160,(N43+N39)*45%-181920))))))))))))))-SUM($C$42:N42)-SUM($C$57:M58)-SUM($C$64:M66)-SUM($C$44:M44) -> #VALUE!
B45: VPR | C45: 0 | E45: 0 | F45: 239709.6 | G45: 0 | H45: 0 | I45: 0 | J45: 0 | K45: 0 | L45: 0 | M45: 0 | N45: 0
B46: Donation | C46: 0
B47: VPR(Tax) | C47: =IF(C45=0,0,IF(C45/12-3000<=0,C45*3%,(IF(C45/12-12000<=0,C45*10%-210,(IF(C45/12-25000<=0,C45*20%-1410,(IF(C45/12-35000<=0,C45*25%-2660,(IF(C45/12-55000<=0,C45*30%-4410,(IF(C45/12-80000<=0,C45*35%-7160,(IF(C45/12-80000<=0,C45*35%-7160,C45*45%-15160)))))))))))))) -> 0 | E47: =IF(E45=0,0,IF(E45/12-3000<=0,E45*3%,(IF(E45/12-12000<=0,E45*10%-210,(IF(E45/12-25000<=0,E45*20%-1410,(IF(E45/12-35000<=0,E45*25%-2660,(IF(E45/12-55000<=0,E45*30%-4410,(IF(E45/12-80000<=0,E45*35%-7160,(IF(E45/12-80000<=0,E45*35%-7160,E45*45%-15160)))))))))))))) -> 0 | F47: =IF(F45=0,0,IF(F45/12-3000<=0,F45*3%,(IF(F45/12-12000<=0,F45*10%-210,(IF(F45/12-25000<=0,F45*20%-1410,(IF(F45/12-35000<=0,F45*25%-2660,(IF(F45/12-55000<=0,F45*30%-4410,(IF(F45/12-80000<=0,F45*35%-7160,(IF(F45/12-80000<=0,F45*35%-7160,F45*45%-15160)))))))))))))) -> 46531.92 | G47: =IF(G45=0,0,IF(G45/12-3000<=0,G45*3%,(IF(G45/12-12000<=0,G45*10%-210,(IF(G45/12-25000<=0,G45*20%-1410,(IF(G45/12-35000<=0,G45*25%-2660,(IF(G45/12-55000<=0,G45*30%-4410,(IF(G45/12-80000<=0,G45*35%-7160,(IF(G45/12-80000<=0,G45*35%-7160,G45*45%-15160)))))))))))))) -> 0 | H47: =IF(H45=0,0,IF(H45/12-3000<=0,H45*3%,(IF(H45/12-12000<=0,H45*10%-210,(IF(H45/12-25000<=0,H45*20%-1410,(IF(H45/12-35000<=0,H45*25%-2660,(IF(H45/12-55000<=0,H45*30%-4410,(IF(H45/12-80000<=0,H45*35%-7160,(IF(H45/12-80000<=0,H45*35%-7160,H45*45%-15160)))))))))))))) -> 0 | I47: =IF(I45=0,0,IF(I45/12-3000<=0,I45*3%,(IF(I45/12-12000<=0,I45*10%-210,(IF(I45/12-25000<=0,I45*20%-1410,(IF(I45/12-35000<=0,I45*25%-2660,(IF(I45/12-55000<=0,I45*30%-4410,(IF(I45/12-80000<=0,I45*35%-7160,(IF(I45/12-80000<=0,I45*35%-7160,I45*45%-15160)))))))))))))) -> 0 | J47: =IF(J45=0,0,IF(J45/12-3000<=0,J45*3%,(IF(J45/12-12000<=0,J45*10%-210,(IF(J45/12-25000<=0,J45*20%-1410,(IF(J45/12-35000<=0,J45*25%-2660,(IF(J45/12-55000<=0,J45*30%-4410,(IF(J45/12-80000<=0,J45*35%-7160,(IF(J45/12-80000<=0,J45*35%-7160,J45*45%-15160)))))))))))))) -> 0 | K47: =IF(K45=0,0,IF(K45/12-3000<=0,K45*3%,(IF(K45/12-12000<=0,K45*10%-210,(IF(K45/12-25000<=0,K45*20%-1410,(IF(K45/12-35000<=0,K45*25%-2660,(IF(K45/12-55000<=0,K45*30%-4410,(IF(K45/12-80000<=0,K45*35%-7160,(IF(K45/12-80000<=0,K45*35%-7160,K45*45%-15160)))))))))))))) -> 0 | L47: =IF(L45=0,0,IF(L45/12-3000<=0,L45*3%,(IF(L45/12-12000<=0,L45*10%-210,(IF(L45/12-25000<=0,L45*20%-1410,(IF(L45/12-35000<=0,L45*25%-2660,(IF(L45/12-55000<=0,L45*30%-4410,(IF(L45/12-80000<=0,L45*35%-7160,(IF(L45/12-80000<=0,L45*35%-7160,L45*45%-15160)))))))))))))) -> 0 | ... N47: =IF(N45=0,0,IF(N45/12-3000<=0,N45*3%,(IF(N45/12-12000<=0,N45*10%-210,(IF(N45/12-25000<=0,N45*20%-1410,(IF(N45/12-35000<=0,N45*25%-2660,(IF(N45/12-55000<=0,N45*30%-4410,(IF(N45/12-80000<=0,N45*35%-7160,(IF(N45/12-80000<=0,N45*35%-7160,N45*45%-15160)))))))))))))) -> 0
B48: Year-end Bonus | C48: 0 | E48: 0 | F48: 0 | G48: 0 | I48: 0 | J48: 0 | K48: 0 | L48: 0 | M48: 0 | N48: 0
B49: Year-end Bonus(Tax) | C49: =IF(C48=0,0,IF(C48/12-3000<=0,C48*3%,(IF(C48/12-12000<=0,C48*10%-210,(IF(C48/12-25000<=0,C48*20%-1410,(IF(C48/12-35000<=0,C48*25%-2660,(IF(C48/12-55000<=0,C48*30%-4410,(IF(C48/12-80000<=0,C48*35%-7160,(IF(C48/12-80000<=0,C48*35%-7160,C48*45%-15160)))))))))))))) -> 0 | E49: =IF(E48=0,0,IF(E48/12-3000<=0,E48*3%,(IF(E48/12-12000<=0,E48*10%-210,(IF(E48/12-25000<=0,E48*20%-1410,(IF(E48/12-35000<=0,E48*25%-2660,(IF(E48/12-55000<=0,E48*30%-4410,(IF(E48/12-80000<=0,E48*35%-7160,(IF(E48/12-80000<=0,E48*35%-7160,E48*45%-15160)))))))))))))) -> 0 | F49: =IF(F48=0,0,IF(F48/12-3000<=0,F48*3%,(IF(F48/12-12000<=0,F48*10%-210,(IF(F48/12-25000<=0,F48*20%-1410,(IF(F48/12-35000<=0,F48*25%-2660,(IF(F48/12-55000<=0,F48*30%-4410,(IF(F48/12-80000<=0,F48*35%-7160,(IF(F48/12-80000<=0,F48*35%-7160,F48*45%-15160)))))))))))))) -> 0 | G49: =IF(G48=0,0,IF(G48/12-3000<=0,G48*3%,(IF(G48/12-12000<=0,G48*10%-210,(IF(G48/12-25000<=0,G48*20%-1410,(IF(G48/12-35000<=0,G48*25%-2660,(IF(G48/12-55000<=0,G48*30%-4410,(IF(G48/12-80000<=0,G48*35%-7160,(IF(G48/12-80000<=0,G48*35%-7160,G48*45%-15160)))))))))))))) -> 0 | I49: =IF(I48=0,0,IF(I48/12-3000<=0,I48*3%,(IF(I48/12-12000<=0,I48*10%-210,(IF(I48/12-25000<=0,I48*20%-1410,(IF(I48/12-35000<=0,I48*25%-2660,(IF(I48/12-55000<=0,I48*30%-4410,(IF(I48/12-80000<=0,I48*35%-7160,(IF(I48/12-80000<=0,I48*35%-7160,I48*45%-15160)))))))))))))) -> 0 | J49: =IF(J48=0,0,IF(J48/12-3000<=0,J48*3%,(IF(J48/12-12000<=0,J48*10%-210,(IF(J48/12-25000<=0,J48*20%-1410,(IF(J48/12-35000<=0,J48*25%-2660,(IF(J48/12-55000<=0,J48*30%-4410,(IF(J48/12-80000<=0,J48*35%-7160,(IF(J48/12-80000<=0,J48*35%-7160,J48*45%-15160)))))))))))))) -> 0 | K49: =IF(K48=0,0,IF(K48/12-3000<=0,K48*3%,(IF(K48/12-12000<=0,K48*10%-210,(IF(K48/12-25000<=0,K48*20%-1410,(IF(K48/12-35000<=0,K48*25%-2660,(IF(K48/12-55000<=0,K48*30%-4410,(IF(K48/12-80000<=0,K48*35%-7160,(IF(K48/12-80000<=0,K48*35%-7160,K48*45%-15160)))))))))))))) -> 0 | L49: 0 | M49: 0 | N49: 0
B50: Adjustment after tax | C50: 0 | E50: 0 | F50: 0 | G50: 0 | I50: 0 | J50: 0 | K50: 0 | L50: 0 | M50: 0 | N50: -60
B51: Flex adjustment after tax | C51: 0 | E51: 0 | F51: 0 | G51: 0 | I51: 0 | J51: 0 | K51: 0 | L51: 0 | M51: 0 | N51: 0
B52: Net Income | C52: =C36-C37-C42+C45-C47+C50+C51+C48-C49 -> #VALUE! | E52: =E36-E37-E42+E45-E47+E50+E51 -> #N/A | F52: =F36-F37-F42+F45-F47+F50+F51 -> #N/A | G52: =G36-G37-G42+G45-G47+G50+G51 -> #N/A | H52: =H36-H37-H42+H45-H47+H50+H51-H44 -> #N/A | I52: =I36-I37-I42+I45-I47+I50+I51-I44 -> #N/A | J52: =J36-J37-J42+J45-J47+J50+J51-J44 -> #N/A | K52: =K36-K37-K42+K45-K47+K50+K51-K44 -> #N/A | L52: =L36-L37-L42+L45-L47+L50+L51-L44 -> #N/A | M52: =M36-M37-M42+M45-M47+M50+M51-M44 -> #N/A | N52: =N36-N37-N42+N45-N47+N50+N51-N44 -> #N/A
B54: Yearly benefit (EE bears tax)
B55: Flexible Benefit | C55: 0 | D55: 0
B56: Wealth Plan | C56: 0 | D56: 0
B57: Tax for Flexible Benefit | C57: {=ROUND(MAX((C39+C55)*{0.03,0.1,0.2,0.25,0.3,0.35,0.45}-{0,2520,16920,31920,52920,85920,181920},0),2)-(C42)} -> #VALUE! | D57: {=ROUND(MAX((D39+D55)*{0.03,0.1,0.2,0.25,0.3,0.35,0.45}-{0,2520,16920,31920,52920,85920,181920},0),2)-SUM($C$42,$C$57:$C$58,$C$64:$C$66)-(D42)} -> #VALUE! | E57: {=ROUND(MAX((E39+E55)*{0.03,0.1,0.2,0.25,0.3,0.35,0.45}-{0,2520,16920,31920,52920,85920,181920},0),2)-SUM($C$42:D42,$C$57:D57,$C$58:D58,$C$64:D64,$C$65:D65,$C$66:D66)-(E42)} -> #VALUE! | F57: {=ROUND(MAX((F39+F55)*{0.03,0.1,0.2,0.25,0.3,0.35,0.45}-{0,2520,16920,31920,52920,85920,181920},0),2)-SUM($C$42:E42,$C$57:E57,$C$58:E58,$C$64:E64,$C$65:E65,$C$66:E66)-(F42)} -> #VALUE! | G57: {=ROUND(MAX((G39+G55)*{0.03,0.1,0.2,0.25,0.3,0.35,0.45}-{0,2520,16920,31920,52920,85920,181920},0),2)-SUM($C$42:F42,$C$57:F57,$C$58:F58,$C$64:F64,$C$65:F65,$C$66:F66)-(G42)} -> #VALUE! | H57: {=ROUND(MAX((H39+H55)*{0.03,0.1,0.2,0.25,0.3,0.35,0.45}-{0,2520,16920,31920,52920,85920,181920},0),2)-SUM($C$42:G42,$C$57:G57,$C$58:G58,$C$64:G64,$C$65:G65,$C$66:G66)-(H42)} -> #VALUE! | I57: {=ROUND(MAX((I39+I55)*{0.03,0.1,0.2,0.25,0.3,0.35,0.45}-{0,2520,16920,31920,52920,85920,181920},0),2)-SUM($C$42:H42,$C$44:H44,$C$57:H57,$C$58:H58,$C$64:H64,$C$65:H65,$C$66:H66)-(I42)} -> #VALUE! | J57: {=ROUND(MAX((J39+J55)*{0.03,0.1,0.2,0.25,0.3,0.35,0.45}-{0,2520,16920,31920,52920,85920,181920},0),2)-SUM($C$42:I42,$C$44:I44,$C$57:I57,$C$58:I58,$C$64:I64,$C$65:I65,$C$66:I66)-(J42)} -> #VALUE! | K57: {=ROUND(MAX((K39+K55)*{0.03,0.1,0.2,0.25,0.3,0.35,0.45}-{0,2520,16920,31920,52920,85920,181920},0),2)-SUM($C$42:J42,$C$44:J44,$C$57:J57,$C$58:J58,$C$64:J64,$C$65:J65,$C$66:J66)-(K42)} -> #VALUE! | L57: {=ROUND(MAX((L39+L55)*{0.03,0.1,0.2,0.25,0.3,0.35,0.45}-{0,2520,16920,31920,52920,85920,181920},0),2)-SUM($C$42:K42,$C$44:K44,$C$57:K57,$C$58:K58,$C$64:K64,$C$65:K65,$C$66:K66)-(L42)} -> #VALUE! | M57: {=ROUND(MAX((M39+M55)*{0.03,0.1,0.2,0.25,0.3,0.35,0.45}-{0,2520,16920,31920,52920,85920,181920},0),2)-SUM($C$42:L42,$C$44:L44,$C$57:L57,$C$58:L58,$C$64:L64,$C$65:L65,$C$66:L66)-(M42)} -> #VALUE! | N57: {=ROUND(MAX((N39+N55)*{0.03,0.1,0.2,0.25,0.3,0.35,0.45}-{0,2520,16920,31920,52920,85920,181920},0),2)-SUM($C$42:M42,$C$44:M44,$C$57:M57,$C$58:M58,$C$64:M64,$C$65:M65,$C$66:M66)-(N42)} -> #VALUE!
B58: Tax for Wealth Plan | C58: {=ROUND(MAX((C39+C55+C56)*{0.03,0.1,0.2,0.25,0.3,0.35,0.45}-{0,2520,16920,31920,52920,85920,181920},0),2)-(C42+C57)} -> #VALUE! | D58: {=ROUND(MAX((D39+D55+D56)*{0.03,0.1,0.2,0.25,0.3,0.35,0.45}-{0,2520,16920,31920,52920,85920,181920},0),2)-SUM($C$42,$C$57,$C$58,$C$64,$C$65,$C$66)-(D42+D57)} -> #VALUE! | E58: {=ROUND(MAX((E39+E55+E56)*{0.03,0.1,0.2,0.25,0.3,0.35,0.45}-{0,2520,16920,31920,52920,85920,181920},0),2)-SUM($C$42:D42,$C$57:D57,$C$58:D58,$C$64:D64,$C$65:D65,$C$66:D66)-(E42+E57)} -> #VALUE! | F58: {=ROUND(MAX((F39+F55+F56)*{0.03,0.1,0.2,0.25,0.3,0.35,0.45}-{0,2520,16920,31920,52920,85920,181920},0),2)-SUM($C$42:E42,$C$57:E57,$C$58:E58,$C$64:E64,$C$65:E65,$C$66:E66)-(F42+F57)} -> #VALUE! | G58: {=ROUND(MAX((G39+G55+G56)*{0.03,0.1,0.2,0.25,0.3,0.35,0.45}-{0,2520,16920,31920,52920,85920,181920},0),2)-SUM($C$42:F42,$C$57:F57,$C$58:F58,$C$64:F64,$C$65:F65,$C$66:F66)-(G42+G57)} -> #VALUE! | H58: {=ROUND(MAX((H39+H55+H56)*{0.03,0.1,0.2,0.25,0.3,0.35,0.45}-{0,2520,16920,31920,52920,85920,181920},0),2)-SUM($C$42:G42,$C$57:G57,$C$58:G58,$C$64:G64,$C$65:G65,$C$66:G66)-(H42+H57)} -> #VALUE! | I58: {=ROUND(MAX((I39+I55+I56)*{0.03,0.1,0.2,0.25,0.3,0.35,0.45}-{0,2520,16920,31920,52920,85920,181920},0),2)-SUM($C$42:H42,$C$44:H44,$C$57:H57,$C$58:H58,$C$64:H64,$C$65:H65,$C$66:H66)-(I42+I57)} -> #VALUE! | J58: {=ROUND(MAX((J39+J55+J56)*{0.03,0.1,0.2,0.25,0.3,0.35,0.45}-{0,2520,16920,31920,52920,85920,181920},0),2)-SUM($C$42:I42,$C$44:I44,$C$57:I57,$C$58:I58,$C$64:I64,$C$65:I65,$C$66:I66)-(J42+J57)} -> #VALUE! | K58: {=ROUND(MAX((K39+K55+K56)*{0.03,0.1,0.2,0.25,0.3,0.35,0.45}-{0,2520,16920,31920,52920,85920,181920},0),2)-SUM($C$42:J42,$C$44:J44,$C$57:J57,$C$58:J58,$C$64:J64,$C$65:J65,$C$66:J66)-(K42+K57)} -> #VALUE! | L58: {=ROUND(MAX((L39+L55+L56)*{0.03,0.1,0.2,0.25,0.3,0.35,0.45}-{0,2520,16920,31920,52920,85920,181920},0),2)-SUM($C$42:K42,$C$44:K44,$C$57:K57,$C$58:K58,$C$64:K64,$C$65:K65,$C$66:K66)-(L42+L57)} -> #VALUE! | M58: {=ROUND(MAX((M39+M55+M56)*{0.03,0.1,0.2,0.25,0.3,0.35,0.45}-{0,2520,16920,31920,52920,85920,181920},0),2)-SUM($C$42:L42,$C$44:L44,$C$57:L57,$C$58:L58,$C$64:L64,$C$65:L65,$C$66:L66)-(M42+M57)} -> #VALUE! | N58: {=ROUND(MAX((N39+N55+N56)*{0.03,0.1,0.2,0.25,0.3,0.35,0.45}-{0,2520,16920,31920,52920,85920,181920},0),2)-SUM($C$42:M42,$C$44:M44,$C$57:M57,$C$58:M58,$C$64:M64,$C$65:M65,$C$66:M66)-(N42+N57)} -> #VALUE!
B60: Yearly benefit (ER bears tax)
B61: Medical examinations fee | C61: 0
B62: Commercial insurance fee | C62: 0
B63: Long term service award | C63: 0
B64: Tax for medical examinations fee | C64: {=ROUND(MAX((C39+C55+C56+C61)*{0.03,0.1,0.2,0.25,0.3,0.35,0.45}-{0,2520,16920,31920,52920,85920,181920},0),2)-(C42+C57+C58)} -> #VALUE! | D64: {=ROUND(MAX((D39+D55+D56+D61)*{0.03,0.1,0.2,0.25,0.3,0.35,0.45}-{0,2520,16920,31920,52920,85920,181920},0),2)-SUM($C$42,$C$57,$C$58,$C$64,$C$65,$C$66)-(D42+D57+D58)} -> #VALUE! | E64: {=ROUND(MAX((E39+E55+E56+E61)*{0.03,0.1,0.2,0.25,0.3,0.35,0.45}-{0,2520,16920,31920,52920,85920,181920},0),2)-SUM($C$42:D42,$C$57:D57,$C$58:D58,$C$64:D64,$C$65:D65,$C$66:D66)-(E42+E57+E58)} -> #VALUE! | F64: {=ROUND(MAX((F39+F55+F56+F61)*{0.03,0.1,0.2,0.25,0.3,0.35,0.45}-{0,2520,16920,31920,52920,85920,181920},0),2)-SUM($C$42:E42,$C$57:E57,$C$58:E58,$C$64:E64,$C$65:E65,$C$66:E66)-(F42+F57+F58)} -> #VALUE! | G64: {=ROUND(MAX((G39+G55+G56+G61)*{0.03,0.1,0.2,0.25,0.3,0.35,0.45}-{0,2520,16920,31920,52920,85920,181920},0),2)-SUM($C$42:F42,$C$57:F57,$C$58:F58,$C$64:F64,$C$65:F65,$C$66:F66)-(G42+G57+G58)} -> #VALUE! | H64: {=ROUND(MAX((H39+H43+H55+H56+H61)*{0.03,0.1,0.2,0.25,0.3,0.35,0.45}-{0,2520,16920,31920,52920,85920,181920},0),2)-SUM($C$42:G42,$C$57:G57,$C$58:G58,$C$64:G64,$C$65:G65,$C$66:G66)-(H42+H44+H57+H58)} -> #VALUE! | I64: {=ROUND(MAX((I39+I55+I56+I61)*{0.03,0.1,0.2,0.25,0.3,0.35,0.45}-{0,2520,16920,31920,52920,85920,181920},0),2)-SUM($C$42:H42,$C$44:H44,$C$57:H57,$C$58:H58,$C$64:H64,$C$65:H65,$C$66:H66)-(I42+I57+I58)} -> #VALUE! | J64: {=ROUND(MAX((J39+J55+J56+J61)*{0.03,0.1,0.2,0.25,0.3,0.35,0.45}-{0,2520,16920,31920,52920,85920,181920},0),2)-SUM($C$42:I42,$C$44:I44,$C$57:I57,$C$58:I58,$C$64:I64,$C$65:I65,$C$66:I66)-(J42+J57+J58)} -> #VALUE! | K64: {=ROUND(MAX((K39+K55+K56+K61)*{0.03,0.1,0.2,0.25,0.3,0.35,0.45}-{0,2520,16920,31920,52920,85920,181920},0),2)-SUM($C$42:J42,$C$44:J44,$C$57:J57,$C$58:J58,$C$64:J64,$C$65:J65,$C$66:J66)-(K42+K57+K58)} -> #VALUE! | L64: {=ROUND(MAX((L39+L55+L56+L61)*{0.03,0.1,0.2,0.25,0.3,0.35,0.45}-{0,2520,16920,31920,52920,85920,181920},0),2)-SUM($C$42:K42,$C$44:K44,$C$57:K57,$C$58:K58,$C$64:K64,$C$65:K65,$C$66:K66)-(L42+L57+L58)} -> #VALUE! | M64: {=ROUND(MAX((M39+M55+M56+M61)*{0.03,0.1,0.2,0.25,0.3,0.35,0.45}-{0,2520,16920,31920,52920,85920,181920},0),2)-SUM($C$42:L42,$C$44:L44,$C$57:L57,$C$58:L58,$C$64:L64,$C$65:L65,$C$66:L66)-(M42+M57+M58)} -> #VALUE! | N64: {=ROUND(MAX((N39+N55+N56+N61)*{0.03,0.1,0.2,0.25,0.3,0.35,0.45}-{0,2520,16920,31920,52920,85920,181920},0),2)-SUM($C$42:M42,$C$44:M44,$C$57:M57,$C$58:M58,$C$64:M64,$C$65:M65,$C$66:M66)-(N42+N57+N58)} -> #VALUE!
B65: Tax for commercial insurance fee | C65: {=ROUND(MAX((C39+C55+C56+C61+C62)*{0.03,0.1,0.2,0.25,0.3,0.35,0.45}-{0,2520,16920,31920,52920,85920,181920},0),2)-(C42+C57+C58+C64)} -> #VALUE! | D65: {=ROUND(MAX((D39+D55+D56+D61+D62)*{0.03,0.1,0.2,0.25,0.3,0.35,0.45}-{0,2520,16920,31920,52920,85920,181920},0),2)-SUM($C$42,$C$57,$C$58,$C$64,$C$65,$C$66)-(D42+D57+D58+D64)} -> #VALUE! | E65: {=ROUND(MAX((E39+E55+E56+E61+E62)*{0.03,0.1,0.2,0.25,0.3,0.35,0.45}-{0,2520,16920,31920,52920,85920,181920},0),2)-SUM($C$42:D42,$C$57:D57,$C$58:D58,$C$64:D64,$C$65:D65,$C$66:D66)-(E42+E57+E58+E64)} -> #VALUE! | F65: {=ROUND(MAX((F39+F55+F56+F61+F62)*{0.03,0.1,0.2,0.25,0.3,0.35,0.45}-{0,2520,16920,31920,52920,85920,181920},0),2)-SUM($C$42:E42,$C$57:E57,$C$58:E58,$C$64:E64,$C$65:E65,$C$66:E66)-(F42+F57+F58+F64)} -> #VALUE! | G65: {=ROUND(MAX((G39+G55+G56+G61+G62)*{0.03,0.1,0.2,0.25,0.3,0.35,0.45}-{0,2520,16920,31920,52920,85920,181920},0),2)-SUM($C$42:F42,$C$57:F57,$C$58:F58,$C$64:F64,$C$65:F65,$C$66:F66)-(G42+G57+G58+G64)} -> #VALUE! | H65: {=ROUND(MAX((H39+H43+H55+H56+H61+H62)*{0.03,0.1,0.2,0.25,0.3,0.35,0.45}-{0,2520,16920,31920,52920,85920,181920},0),2)-SUM($C$42:G42,$C$57:G57,$C$58:G58,$C$64:G64,$C$65:G65,$C$66:G66)-(H42+H57+H44+H58+H64)} -> #VALUE! | I65: {=ROUND(MAX((I39+I55+I56+I61+I62)*{0.03,0.1,0.2,0.25,0.3,0.35,0.45}-{0,2520,16920,31920,52920,85920,181920},0),2)-SUM($C$42:H42,$C$44:H44,$C$57:H57,$C$58:H58,$C$64:H64,$C$65:H65,$C$66:H66)-(I42+I57+I58+I64)} -> #VALUE! | J65: {=ROUND(MAX((J39+J55+J56+J61+J62)*{0.03,0.1,0.2,0.25,0.3,0.35,0.45}-{0,2520,16920,31920,52920,85920,181920},0),2)-SUM($C$42:I42,$C$44:I44,$C$57:I57,$C$58:I58,$C$64:I64,$C$65:I65,$C$66:I66)-(J42+J57+J58+J64)} -> #VALUE! | K65: {=ROUND(MAX((K39+K55+K56+K61+K62)*{0.03,0.1,0.2,0.25,0.3,0.35,0.45}-{0,2520,16920,31920,52920,85920,181920},0),2)-SUM($C$42:J42,$C$44:J44,$C$57:J57,$C$58:J58,$C$64:J64,$C$65:J65,$C$66:J66)-(K42+K57+K58+K64)} -> #VALUE! | L65: {=ROUND(MAX((L39+L55+L56+L61+L62)*{0.03,0.1,0.2,0.25,0.3,0.35,0.45}-{0,2520,16920,31920,52920,85920,181920},0),2)-SUM($C$42:K42,$C$44:K44,$C$57:K57,$C$58:K58,$C$64:K64,$C$65:K65,$C$66:K66)-(L42+L57+L58+L64)} -> #VALUE! | M65: {=ROUND(MAX((M39+M55+M56+M61+M62)*{0.03,0.1,0.2,0.25,0.3,0.35,0.45}-{0,2520,16920,31920,52920,85920,181920},0),2)-SUM($C$42:L42,$C$44:L44,$C$57:L57,$C$58:L58,$C$64:L64,$C$65:L65,$C$66:L66)-(M42+M57+M58+M64)} -> #VALUE! | N65: {=ROUND(MAX((N39+N55+N56+N61+N62)*{0.03,0.1,0.2,0.25,0.3,0.35,0.45}-{0,2520,16920,31920,52920,85920,181920},0),2)-SUM($C$42:M42,$C$44:M44,$C$57:M57,$C$58:M58,$C$64:M64,$C$65:M65,$C$66:M66)-(N42+N57+N58+N64)} -> #VALUE!
B66: Tax for long term service award | C66: {=ROUND(MAX((C39+C55+C56+C61+C62+C63)*{0.03,0.1,0.2,0.25,0.3,0.35,0.45}-{0,2520,16920,31920,52920,85920,181920},0),2)-(C42+C57+C58+C64+C65)} -> #VALUE! | D66: {=ROUND(MAX((D39+D55+D56+D61+D62+D63)*{0.03,0.1,0.2,0.25,0.3,0.35,0.45}-{0,2520,16920,31920,52920,85920,181920},0),2)-SUM($C$42,$C$57,$C$58,$C$64,$C$65,$C$66)-(D42+D57+D58+D64+D65)} -> #VALUE! | E66: {=ROUND(MAX((E39+E55+E56+E61+E62+E63)*{0.03,0.1,0.2,0.25,0.3,0.35,0.45}-{0,2520,16920,31920,52920,85920,181920},0),2)-SUM($C$42:D42,$C$57:D57,$C$58:D58,$C$64:D64,$C$65:D65,$C$66:D66)-(E42+E57+E58+E64+E65)} -> #VALUE! | F66: {=ROUND(MAX((F39+F55+F56+F61+F62+F63)*{0.03,0.1,0.2,0.25,0.3,0.35,0.45}-{0,2520,16920,31920,52920,85920,181920},0),2)-SUM($C$42:E42,$C$57:E57,$C$58:E58,$C$64:E64,$C$65:E65,$C$66:E66)-(F42+F57+F58+F64+F65)} -> #VALUE! | G66: {=ROUND(MAX((G39+G55+G56+G61+G62+G63)*{0.03,0.1,0.2,0.25,0.3,0.35,0.45}-{0,2520,16920,31920,52920,85920,181920},0),2)-SUM($C$42:F42,$C$57:F57,$C$58:F58,$C$64:F64,$C$65:F65,$C$66:F66)-(G42+G57+G58+G64+G65)} -> #VALUE! | H66: {=ROUND(MAX((H39+H43+H55+H56+H61+H62+H63)*{0.03,0.1,0.2,0.25,0.3,0.35,0.45}-{0,2520,16920,31920,52920,85920,181920},0),2)-SUM($C$42:G42,$C$57:G57,$C$58:G58,$C$64:G64,$C$65:G65,$C$66:G66)-(H42+H44+H57+H58+H64+H65)} -> #VALUE! | I66: {=ROUND(MAX((I39+I55+I56+I61+I62+I63)*{0.03,0.1,0.2,0.25,0.3,0.35,0.45}-{0,2520,16920,31920,52920,85920,181920},0),2)-SUM($C$42:H42,$C$44:H44,$C$57:H57,$C$58:H58,$C$64:H64,$C$65:H65,$C$66:H66)-(I42+I57+I58+I64+I65)} -> #VALUE! | J66: {=ROUND(MAX((J39+J55+J56+J61+J62+J63)*{0.03,0.1,0.2,0.25,0.3,0.35,0.45}-{0,2520,16920,31920,52920,85920,181920},0),2)-SUM($C$42:I42,$C$44:I44,$C$57:I57,$C$58:I58,$C$64:I64,$C$65:I65,$C$66:I66)-(J42+J57+J58+J64+J65)} -> #VALUE! | K66: {=ROUND(MAX((K39+K55+K56+K61+K62+K63)*{0.03,0.1,0.2,0.25,0.3,0.35,0.45}-{0,2520,16920,31920,52920,85920,181920},0),2)-SUM($C$42:J42,$C$44:J44,$C$57:J57,$C$58:J58,$C$64:J64,$C$65:J65,$C$66:J66)-(K42+K57+K58+K64+K65)} -> #VALUE! | L66: {=ROUND(MAX((L39+L55+L56+L61+L62+L63)*{0.03,0.1,0.2,0.25,0.3,0.35,0.45}-{0,2520,16920,31920,52920,85920,181920},0),2)-SUM($C$42:K42,$C$44:K44,$C$57:K57,$C$58:K58,$C$64:K64,$C$65:K65,$C$66:K66)-(L42+L57+L58+L64+L65)} -> #VALUE! | M66: {=ROUND(MAX((M39+M55+M56+M61+M62+M63)*{0.03,0.1,0.2,0.25,0.3,0.35,0.45}-{0,2520,16920,31920,52920,85920,181920},0),2)-SUM($C$42:L42,$C$44:L44,$C$57:L57,$C$58:L58,$C$64:L64,$C$65:L65,$C$66:L66)-(M42+M57+M58+M64+M65)} -> #VALUE! | N66: {=ROUND(MAX((N39+N55+N56+N61+N62+N63)*{0.03,0.1,0.2,0.25,0.3,0.35,0.45}-{0,2520,16920,31920,52920,85920,181920},0),2)-SUM($C$42:M42,$C$44:M44,$C$57:M57,$C$58:M58,$C$64:M64,$C$65:M65,$C$66:M66)-(N42+N57+N58+N64+N65)} -> #VALUE!
B68: Monthly gross income and tax for annual tax filing and reconciliation
B69: Gross | C69: =C36+C55+C56+C61+C62+C63 -> 1232 | D69: =D36+D55+D56+D61+D62+D63 -> 0 | E69: =E36+E55+E56+E61+E62+E63 -> 0 | F69: =F36+F55+F56+F61+F62+F63 -> 0 | G69: =G36+G55+G56+G61+G62+G63 -> 0 | H69: =H36+H43+H55+H56+H61+H62+H63 -> 8.88 | I69: =I36+I55+I56+I61+I62+I63 -> 0 | J69: =J36+J55+J56+J61+J62+J63 -> 0 | K69: =K36+K55+K56+K61+K62+K63 -> 0 | L69: =L36+L55+L56+L61+L62+L63 -> 0 | M69: =M36+M55+M56+M61+M62+M63 -> 0 | N69: =N36+N43+N55+N56+N61+N62+N63 -> 38
B70: Tax | C70: =C42+C57+C58+C64+C65+C66 -> #VALUE! | D70: =D42+D57+D58+D64+D65+D66 -> #VALUE! | E70: =E42+E57+E58+E64+E65+E66 -> #N/A | F70: =F42+F57+F58+F64+F65+F66 -> #N/A | G70: =G42+G57+G58+G64+G65+G66 -> #N/A | H70: =H42+H44+H57+H58+H64+H65+H66 -> #N/A | I70: =I42+I44+I57+I58+I64+I65+I66 -> #N/A | J70: =J42+J44+J57+J58+J64+J65+J66 -> #N/A | K70: =K42+K44+K57+K58+K64+K65+K66 -> #N/A | L70: =L42+L44+L57+L58+L64+L65+L66 -> #N/A | M70: =M42+M44+M57+M58+M64+M65+M66 -> #N/A | N70: =N42+N44+N57+N58+N64+N65+N66 -> #N/A
