Workbook
Name 证件类型: [1]填表说明!$A$6:$A$17

Sheet 付款通知书
A2: 上海外服合杰企业服务有限公司
A3: 收款通知书
A4: ADVISE ON COLLECTION
A5: 46082
A7: 公司名称：中粮福临门食品营销有限公司上海分公司
A8: 纳税人识别号： | B8: 91310104MA1FR47R6D
A9: 客户开户银行： | B9: 中信银行北京中粮广场支行
A10: 费用详情 长促KA
A11: 工资人数 | D11: =长促工资明细!A39 -> 34 | E11: NKA | F11: LKA | G11: DT
A12: HC | D12: =D11 -> 34 | E12: =COUNTIFS(长促工资明细!$J:$J,付款通知书!$E$11) -> 34 | F12: =COUNTIFS(长促工资明细!$J:$J,付款通知书!$F$11) -> 0 | G12: =COUNTIFS(长促工资明细!$J:$J,付款通知书!$G$11) -> 0
A13: 2026年3月工资 | D13: =长促工资明细!BO40 -> 114589.63 | E13: =SUMIFS(长促工资明细!$BO:$BO,长促工资明细!$J:$J,付款通知书!$E$11) -> 114589.63 | F13: =SUMIFS(长促工资明细!$BO:$BO,长促工资明细!$J:$J,付款通知书!$F$11) -> 0 | G13: =SUMIFS(长促工资明细!$BO:$BO,长促工资明细!$J:$J,付款通知书!$G$11) -> 0
A14: 2026年4月社保 | D14: =社保公积金账单!CH40+社保公积金账单!CI40 -> 92121.98 | E14: =SUMIFS(社保公积金账单!$CL:$CL,社保公积金账单!$E:$E,付款通知书!$E$11) -> 89412.51 | F14: =SUMIFS(社保公积金账单!$CL:$CL,社保公积金账单!$E:$E,付款通知书!$F$11) -> 0 | G14: =SUMIFS(社保公积金账单!$CL:$CL,社保公积金账单!$E:$E,付款通知书!$G$11) -> 0
A15: 2026年4月公积金 | D15: =社保公积金账单!CJ40+社保公积金账单!CK40 -> 12808 | E15: =SUMIFS(社保公积金账单!$CM:$CM,社保公积金账单!$E:$E,$E$11) -> 12424 | F15: =SUMIFS(社保公积金账单!$CM:$CM,社保公积金账单!$E:$E,$F$11) -> 0 | G15: =SUMIFS(社保公积金账单!$CM:$CM,社保公积金账单!$E:$E,G11) -> 0
A16: 管理费 | D16: =ROUND((D13+D14+D15)*0.02,2) -> 4390.39 | E16: =ROUND((E13+E14+E15)*0.02,2) -> 4328.52 | F16: =ROUND((F13+F14+F15)*0.02,2) -> 0 | G16: =ROUND((G13+G14+G15)*0.02,2) -> 0
A17: 2026年3月雇主责任险 | D17: =社保公积金账单!G40 -> 649.11 | E17: =SUMIFS(社保公积金账单!$G:$G,社保公积金账单!$E:$E,付款通知书!$E$11) -> 629.44 | F17: =SUMIFS(社保公积金账单!$G:$G,社保公积金账单!$E:$E,付款通知书!$F$11) -> 0 | G17: =SUMIFS(社保公积金账单!$G:$G,社保公积金账单!$E:$E,付款通知书!$G$11) -> 0
A18: 发票税金 | D18: =ROUND(SUM(D13:D17)*6.78%,2) -> 15225.11 | E18: =ROUND(SUM(E13:E17)*6.78%,2) -> 15009.84 | F18: =ROUND(SUM(F13:F17)*6.78%,2) -> 0 | G18: =ROUND(SUM(G13:G17)*6.78%,2) -> 0
A19: 请款金额 | D19: =ROUND(D13+D14+D15+D16+D17+D18,2) -> 239784.22 | E19: =ROUND(E13+E14+E15+E16+E17+E18,2) -> 236393.94 | F19: =ROUND(F13+F14+F15+F16+F17+F18,2) -> 0 | G19: =ROUND(G13+G14+G15+G16+G17+G18,2) -> 0
A20: Total | D20: =D19 -> 239784.22
D21: =D20/1.06 -> 226211.53
D22: =D20/1.06 -> 226211.53
D23: =ROUND(D20/1.06,2) -> 226211.53
A24: 大写金额： | B24: =IF(D20<=0,,"人民币"&IF(INT(D20)=0,,TEXT(INT(D20),"[dbnum2]")&"圆")&IF(INT(D20*10)-INT(D20)*10=0,IF(INT(D20)*(INT(D20*100)-INT(D20*10)*10)=0,"","零"),TEXT(INT(D20*10)-INT(D20)*10,"[dbnum2]")&"角")&IF((INT(D20*100)-INT(D20*10)*10)=0,"整",TEXT((INT(D20*100)-INT(D20*10)*10),"[dbnum2]")&"分")) -> 人民币贰拾叁万玖仟柒佰捌拾肆圆贰角贰分 | E24: =E19/1.06 -> 223013.15 | F24: =F19/1.06 -> 0 | G24: =G19/1.06 -> 0
D25: =D20/1.06 -> 226211.53
A26: 户名：上海外服合杰企业服务有限公司 | D26: =D19/1.06 -> 226211.53
A27: 开户银行：中国工商银行上海市金钟支行
A28: 人民币银行帐号：RMB 1001199409006536383

Sheet 长促工资明细
A4: 序号 | B4: 大区 | C4: 省区 | D4: 城市群 | E4: 城市 | F4: 导购类型 | G4: 姓名 | H4: 身份证号 | I4: 联系电话 | J4: 渠道 （NKA/LKA/DT） | K4: 系统性质 （直营/经销） | L4: 门店系统 | M4: SFA编码 | N4: 门店名称 | O4: 入职时间 | P4: 离职时间 | Q4: 基本工资 | AB4: 销售提成 | AI4: 月度补贴 | AL4: 其它补贴 | AQ4: 其它奖金 | AT4: 报销费用 | AU4: 其他费用 | AV4: 薪资补差 | AW4: 应发工资合计 | AX4: 备注 （最低工资标准） | AY4: 第三方公司名称 | AZ4: 社保个人 | BA4: 公积金个人 | BB4: 其他收入 | BC4: 四金后合计（不包含交通补贴/餐补/加班费/报销） | BD4: 工资调整 | BE4: 税前工资合计 | BF4: 截止上月合并计税工资 | BG4: 截止上月个税 | BH4: 累计专项抵扣 | BI4: 专项扣除 | BJ4: 截止本月合计计税工资 | BK4: 个税 | BL4: 累计个税 | BM4: 实发工资 | BN4: 经济补偿金 | BO4: 请款工资
Q5: 基本工资 | R5: 入职年限 | S5: 工龄补贴 | T5: 应上班天数 | U5: 实际上班天数 | V5: 病假（天） | W5: 事假（天） | X5: 补扣款 | Y5: 本月应发工资 | Z5: 加班（天） | AA5: 加班工资 | AB5: 总体目标销量（箱） | AC5: 总体实际销量（箱） | AD5: 总体产品销量达成率 | AE5: 提成金额 | AF5: 扣除提成金额 | AG5: 扣除OTO提成金额 | AH5: 本月实际提成金额 | AI5: 话费补贴基数 | AJ5: 交通补贴基数 | AK5: 月度补贴合计 | AL5: 生日补贴 | AM5: 餐补 | AN5: 大店补贴 | AO5: 其他补贴类型 | AP5: 其他补贴金额 | AQ5: 白糖奖金 | AR5: 激励名称 | AS5: 激励奖金 | BH5: 累计专项抵扣
A6: 1 | B6: 江沪 | C6: 上海KA | D6: 上海 | E6: 上海 | F6: 单导长促 | G6: 赵志炜 | H6: 340826197611081813 | I6: 13062613935 | J6: NKA | K6: 直营 | L6: 欧发 | M6: 238976848 | N6: 大润发曹安店 | O6: 43539 | Q6: 2690 | R6: 6 | S6: 0 | T6: 15 | U6: 15 | V6: 0 | W6: 0 | X6: 0 | Y6: 2690 | Z6: 0 | AA6: 0 | AB6: 172.39 | AC6: 245.83333 | AD6: 1.4260301 | AE6: 1761.5833 | AF6: 0 | AG6: 235.75 | AH6: 1525.8333 | AI6: 0 | AJ6: 80 | AK6: 80 | AL6: 0 | AM6: 150 | AQ6: 0 | AW6: 4445.83 | AX6: 2740 | AY6: 上海合杰 | AZ6: 783.3 | BA6: 188 | BB6: 0 | BC6: =ROUND(AW6-AZ6-BA6+BB6-AA6-AK6-AT6-AM6,2) -> 3244.53 | BD6: =ROUND(IF(T6=U6,IF((BC6-BB6)<AX6,AX6-(BC6-BB6),0)),2) -> 0 | BE6: =ROUND(AW6-AZ6-BA6+BB6+BD6,2) -> 3474.53 | BF6: -13371.5 | BG6: 0 | BH6: 14000 | BI6: 10500 | BJ6: =ROUND(BF6+BE6-5000-(BH6-BI6),2) -> -18396.97 | BK6: =ROUND(MAX(BJ6*{0.03,0.1,0.2,0.25,0.3,0.35,0.45}-{0,2520,16920,31920,52920,85920,181920}-BG6,0),2) -> 0 | BL6: =BG6+BK6 -> 0 | BM6: =ROUND(BE6-BK6,2) -> 3474.53 | BN6: 0 | BO6: =BE6+BN6 -> 3474.53 | BP6: =AZ6+BA6 -> 971.3 | BQ6: =AS6+AU6 -> 0 | BR6: =VLOOKUP(H6,社保公积金账单!D:D,1,0) -> 340826197611081813 | BS6: =T6-U6 -> 0
A7: 2 | B7: 江沪 | C7: 上海KA | D7: 上海 | E7: 上海 | F7: 单导长促 | G7: 周汝娜 | H7: 342422198208101764 | I7: 15821656046 | J7: NKA | K7: 直营 | L7: 欧发 | M7: 238976840 | N7: 大润发春申店 | O7: 45174 | Q7: 2690 | R7: 2 | S7: 0 | T7: 16 | U7: 16 | V7: 0 | W7: 0 | X7: 0 | Y7: 2690 | Z7: 0 | AA7: 0 | AB7: 301.66 | AC7: 365.77778 | AD7: 1.2125498 | AE7: 3026.3333 | AF7: 0 | AG7: 558.54167 | AH7: 1233.8958 | AI7: 0 | AJ7: 80 | AK7: 80 | AL7: 0 | AM7: 160 | AQ7: 0 | AW7: 4163.9 | AX7: 2740 | AY7: 上海合杰 | AZ7: 783.3 | BA7: 188 | BB7: 0 | BC7: =ROUND(AW7-AZ7-BA7+BB7-AA7-AK7-AT7-AM7,2) -> 2952.6 | BD7: =ROUND(IF(T7=U7,IF((BC7-BB7)<AX7,AX7-(BC7-BB7),0)),2) -> 0 | BE7: =ROUND(AW7-AZ7-BA7+BB7+BD7,2) -> 3192.6 | BF7: -4303.27 | BG7: 0 | BH7: 0 | BI7: 0 | BJ7: =ROUND(BF7+BE7-5000-(BH7-BI7),2) -> -6110.67 | BK7: =ROUND(MAX(BJ7*{0.03,0.1,0.2,0.25,0.3,0.35,0.45}-{0,2520,16920,31920,52920,85920,181920}-BG7,0),2) -> 0 | BL7: =BG7+BK7 -> 0 | BM7: =ROUND(BE7-BK7,2) -> 3192.6 | BN7: 0 | BO7: =BE7+BN7 -> 3192.6 | BP7: =AZ7+BA7 -> 971.3 | BQ7: =AS7+AU7 -> 0 | BR7: =VLOOKUP(H7,社保公积金账单!D:D,1,0) -> 342422198208101764 | BS7: =T7-U7 -> 0
A8: 3 | B8: 江沪 | C8: 上海KA | D8: 上海 | E8: 上海 | F8: 单导长促 | G8: 余应红 | H8: 342423197801132301 | I8: 13482821470 | J8: NKA | K8: 直营 | L8: 欧发 | M8: 238976840 | N8: 大润发春申店 | O8: 44386 | Q8: 2690 | R8: 4 | S8: 0 | T8: 22 | U8: 22 | V8: 0 | W8: 0 | X8: 0 | Y8: 2690 | Z8: 0 | AA8: 0 | AB8: 301.66 | AC8: 365.77778 | AD8: 1.2125498 | AE8: 3026.3333 | AF8: 0 | AG8: 558.54167 | AH8: 1233.8958 | AI8: 0 | AJ8: 80 | AK8: 80 | AL8: 0 | AM8: 220 | AQ8: 0 | AW8: 4223.9 | AX8: 2740 | AY8: 上海合杰 | AZ8: 783.3 | BA8: 188 | BB8: 0 | BC8: =ROUND(AW8-AZ8-BA8+BB8-AA8-AK8-AT8-AM8,2) -> 2952.6 | BD8: =ROUND(IF(T8=U8,IF((BC8-BB8)<AX8,AX8-(BC8-BB8),0)),2) -> 0 | BE8: =ROUND(AW8-AZ8-BA8+BB8+BD8,2) -> 3252.6 | BF8: -4603.25 | BG8: 0 | BH8: 0 | BI8: 0 | BJ8: =ROUND(BF8+BE8-5000-(BH8-BI8),2) -> -6350.65 | BK8: =ROUND(MAX(BJ8*{0.03,0.1,0.2,0.25,0.3,0.35,0.45}-{0,2520,16920,31920,52920,85920,181920}-BG8,0),2) -> 0 | BL8: =BG8+BK8 -> 0 | BM8: =ROUND(BE8-BK8,2) -> 3252.6 | BN8: 0 | BO8: =BE8+BN8 -> 3252.6 | BP8: =AZ8+BA8 -> 971.3 | BQ8: =AS8+AU8 -> 0 | BR8: =VLOOKUP(H8,社保公积金账单!D:D,1,0) -> 342423197801132301 | BS8: =T8-U8 -> 0
A9: 4 | B9: 江沪 | C9: 上海KA | D9: 上海 | E9: 上海 | F9: 单导长促 | G9: 姚玉环 | H9: 342422198302204882 | I9: 15000908642 | J9: NKA | K9: 直营 | L9: 欧发 | M9: 238976842 | N9: 大润发奉贤店 | O9: 45931 | Q9: 2740 | R9: 0 | S9: 0 | T9: 16 | U9: 16 | V9: 0 | W9: 0 | X9: 0 | Y9: 2740 | Z9: 0 | AA9: 0 | AB9: 463.73 | AC9: 601.86111 | AD9: 1.2978697 | AE9: 4168.1667 | AF9: 0 | AG9: 764.375 | AH9: 1701.8958 | AI9: 0 | AJ9: 80 | AK9: 80 | AL9: 0 | AM9: 160 | AQ9: 0 | AW9: 4681.9 | AX9: 2740 | AY9: 上海合杰 | AZ9: 783.3 | BA9: 192 | BB9: 0 | BC9: =ROUND(AW9-AZ9-BA9+BB9-AA9-AK9-AT9-AM9,2) -> 3466.6 | BD9: =ROUND(IF(T9=U9,IF((BC9-BB9)<AX9,AX9-(BC9-BB9),0)),2) -> 0 | BE9: =ROUND(AW9-AZ9-BA9+BB9+BD9,2) -> 3706.6 | BF9: -1638.15 | BG9: 0 | BH9: 0 | BI9: 0 | BJ9: =ROUND(BF9+BE9-5000-(BH9-BI9),2) -> -2931.55 | BK9: =ROUND(MAX(BJ9*{0.03,0.1,0.2,0.25,0.3,0.35,0.45}-{0,2520,16920,31920,52920,85920,181920}-BG9,0),2) -> 0 | BL9: =BG9+BK9 -> 0 | BM9: =ROUND(BE9-BK9,2) -> 3706.6 | BN9: 0 | BO9: =BE9+BN9 -> 3706.6 | BP9: =AZ9+BA9 -> 975.3 | BQ9: =AS9+AU9 -> 0 | BR9: =VLOOKUP(H9,社保公积金账单!D:D,1,0) -> 342422198302204882 | BS9: =T9-U9 -> 0
A10: 5 | B10: 江沪 | C10: 上海KA | D10: 上海 | E10: 上海 | F10: 单导长促 | G10: 雷年枝 | H10: 342501198810062263 | I10: 17701878392 | J10: NKA | K10: 直营 | L10: 欧发 | M10: 238976842 | N10: 大润发奉贤店 | O10: 45200 | Q10: 2690 | R10: 2 | S10: 0 | T10: 22 | U10: 22 | V10: 0 | W10: 0 | X10: 0 | Y10: 2690 | Z10: 0 | AA10: 0 | AB10: 463.73 | AC10: 601.86111 | AD10: 1.2978697 | AE10: 4168.1667 | AF10: 0 | AG10: 764.375 | AH10: 1701.8958 | AI10: 0 | AJ10: 80 | AK10: 80 | AL10: 0 | AM10: 210 | AQ10: 0 | AW10: 4681.9 | AX10: 2740 | AY10: 上海合杰 | AZ10: 783.3 | BA10: 188 | BB10: 0 | BC10: =ROUND(AW10-AZ10-BA10+BB10-AA10-AK10-AT10-AM10,2) -> 3420.6 | BD10: =ROUND(IF(T10=U10,IF((BC10-BB10)<AX10,AX10-(BC10-BB10),0)),2) -> 0 | BE10: =ROUND(AW10-AZ10-BA10+BB10+BD10,2) -> 3710.6 | BF10: -1457.41 | BG10: 0 | BH10: 0 | BI10: 0 | BJ10: =ROUND(BF10+BE10-5000-(BH10-BI10),2) -> -2746.81 | BK10: =ROUND(MAX(BJ10*{0.03,0.1,0.2,0.25,0.3,0.35,0.45}-{0,2520,16920,31920,52920,85920,181920}-BG10,0),2) -> 0 | BL10: =BG10+BK10 -> 0 | BM10: =ROUND(BE10-BK10,2) -> 3710.6 | BN10: 0 | BO10: =BE10+BN10 -> 3710.6 | BP10: =AZ10+BA10 -> 971.3 | BQ10: =AS10+AU10 -> 0 | BR10: =VLOOKUP(H10,社保公积金账单!D:D,1,0) -> 342501198810062263 | BS10: =T10-U10 -> 0
A11: 6 | B11: 江沪 | C11: 上海KA | D11: 上海 | E11: 上海 | F11: 单导长促 | G11: 张孝娟 | H11: 341226198305202763 | I11: 18221607434 | J11: NKA | K11: 直营 | L11: 欧发 | M11: 238976846 | N11: 大润发华漕店 | O11: 44568 | Q11: 2690 | R11: 4 | S11: 0 | T11: 16 | U11: 16 | V11: 0 | W11: 0 | X11: 0 | Y11: 2690 | Z11: 0 | AA11: 0 | AB11: 228.74 | AC11: 364.55556 | AD11: 1.5937552 | AE11: 2338.6667 | AF11: 382.125 | AG11: 391.66667 | AH11: 782.4375 | AI11: 0 | AJ11: 80 | AK11: 80 | AL11: 0 | AM11: 160 | AQ11: 0 | AW11: 3712.44 | AX11: 2740 | AY11: 上海合杰 | AZ11: 783.3 | BA11: 188 | BB11: 0 | BC11: =ROUND(AW11-AZ11-BA11+BB11-AA11-AK11-AT11-AM11,2) -> 2501.14 | BD11: =ROUND(IF(T11=U11,IF((BC11-BB11)<AX11,AX11-(BC11-BB11),0)),2) -> 238.86 | BE11: =ROUND(AW11-AZ11-BA11+BB11+BD11,2) -> 2980 | BF11: -5107.34 | BG11: 0 | BH11: 0 | BI11: 0 | BJ11: =ROUND(BF11+BE11-5000-(BH11-BI11),2) -> -7127.34 | BK11: =ROUND(MAX(BJ11*{0.03,0.1,0.2,0.25,0.3,0.35,0.45}-{0,2520,16920,31920,52920,85920,181920}-BG11,0),2) -> 0 | BL11: =BG11+BK11 -> 0 | BM11: =ROUND(BE11-BK11,2) -> 2980 | BN11: 0 | BO11: =BE11+BN11 -> 2980 | BP11: =AZ11+BA11 -> 971.3 | BQ11: =AS11+AU11 -> 0 | BR11: =VLOOKUP(H11,社保公积金账单!D:D,1,0) -> 341226198305202763 | BS11: =T11-U11 -> 0
A12: 7 | B12: 江沪 | C12: 上海KA | D12: 上海 | E12: 上海 | F12: 单导长促 | G12: 郭胜霞 | H12: 320925197905205821 | I12: 13764138280 | J12: NKA | K12: 直营 | L12: 欧发 | M12: 238976854 | N12: 大润发华漕店 | O12: 42736 | Q12: 2690 | R12: 9 | S12: 0 | T12: 22 | U12: 22 | V12: 0 | W12: 0 | X12: 0 | Y12: 2690 | Z12: 0 | AA12: 0 | AB12: 228.74 | AC12: 364.55556 | AD12: 1.5937552 | AE12: 2338.6667 | AF12: 382.125 | AG12: 391.66667 | AH12: 782.4375 | AI12: 0 | AJ12: 80 | AK12: 80 | AL12: 0 | AM12: 220 | AQ12: 0 | AW12: 3772.44 | AX12: 2740 | AY12: 上海合杰 | AZ12: 783.3 | BA12: 188 | BB12: 0 | BC12: =ROUND(AW12-AZ12-BA12+BB12-AA12-AK12-AT12-AM12,2) -> 2501.14 | BD12: =ROUND(IF(T12=U12,IF((BC12-BB12)<AX12,AX12-(BC12-BB12),0)),2) -> 238.86 | BE12: =ROUND(AW12-AZ12-BA12+BB12+BD12,2) -> 3040 | BF12: -4407.32 | BG12: 0 | BH12: 0 | BI12: 0 | BJ12: =ROUND(BF12+BE12-5000-(BH12-BI12),2) -> -6367.32 | BK12: =ROUND(MAX(BJ12*{0.03,0.1,0.2,0.25,0.3,0.35,0.45}-{0,2520,16920,31920,52920,85920,181920}-BG12,0),2) -> 0 | BL12: =BG12+BK12 -> 0 | BM12: =ROUND(BE12-BK12,2) -> 3040 | BN12: 0 | BO12: =BE12+BN12 -> 3040 | BP12: =AZ12+BA12 -> 971.3 | BQ12: =AS12+AU12 -> 0 | BR12: =VLOOKUP(H12,社保公积金账单!D:D,1,0) -> 320925197905205821 | BS12: =T12-U12 -> 0
A13: 8 | B13: 江沪 | C13: 上海KA | D13: 上海 | E13: 上海 | F13: 单导长促 | G13: 施美花 | H13: 310230198305175169 | I13: 13795364351 | J13: NKA | K13: 直营 | L13: 欧发 | M13: 238976864 | N13: 大润发康桥店 | O13: 43611 | Q13: 2690 | R13: 6 | S13: 0 | T13: 22 | U13: 22 | V13: 0 | W13: 0 | X13: 0 | Y13: 2690 | Z13: 0 | AA13: 0 | AB13: 286.2 | AC13: 347.08333 | AD13: 1.21273 | AE13: 2799.6667 | AF13: 0 | AG13: 529.20833 | AH13: 1135.2292 | AI13: 0 | AJ13: 80 | AK13: 80 | AL13: 0 | AM13: 220 | AQ13: 0 | AW13: 4125.23 | AX13: 2740 | AY13: 上海合杰 | AZ13: 783.3 | BA13: 188 | BB13: 0 | BC13: =ROUND(AW13-AZ13-BA13+BB13-AA13-AK13-AT13-AM13,2) -> 2853.93 | BD13: =ROUND(IF(T13=U13,IF((BC13-BB13)<AX13,AX13-(BC13-BB13),0)),2) -> 0 | BE13: =ROUND(AW13-AZ13-BA13+BB13+BD13,2) -> 3153.93 | BF13: -4474.9 | BG13: 0 | BH13: 0 | BI13: 0 | BJ13: =ROUND(BF13+BE13-5000-(BH13-BI13),2) -> -6320.97 | BK13: =ROUND(MAX(BJ13*{0.03,0.1,0.2,0.25,0.3,0.35,0.45}-{0,2520,16920,31920,52920,85920,181920}-BG13,0),2) -> 0 | BL13: =BG13+BK13 -> 0 | BM13: =ROUND(BE13-BK13,2) -> 3153.93 | BN13: 0 | BO13: =BE13+BN13 -> 3153.93 | BP13: =AZ13+BA13 -> 971.3 | BQ13: =AS13+AU13 -> 0 | BR13: =VLOOKUP(H13,社保公积金账单!D:D,1,0) -> 310230198305175169 | BS13: =T13-U13 -> 0
A14: 9 | B14: 江沪 | C14: 上海KA | D14: 上海 | E14: 上海 | F14: 单导长促 | G14: 孙艳 | H14: 34120319890120316X | I14: 15021248502 | J14: NKA | K14: 直营 | L14: 欧发 | M14: 238976864 | N14: 大润发康桥店 | O14: 44721 | Q14: 2690 | R14: 3 | S14: 0 | T14: 16 | U14: 16 | V14: 0 | W14: 0 | X14: 0 | Y14: 2690 | Z14: 0 | AA14: 0 | AB14: 286.2 | AC14: 347.08333 | AD14: 1.21273 | AE14: 2799.6667 | AF14: 0 | AG14: 529.20833 | AH14: 1135.2292 | AI14: 0 | AJ14: 80 | AK14: 80 | AL14: 0 | AM14: 160 | AQ14: 0 | AW14: 4065.23 | AX14: 2740 | AY14: 上海合杰 | AZ14: 783.3 | BA14: 188 | BB14: 0 | BC14: =ROUND(AW14-AZ14-BA14+BB14-AA14-AK14-AT14-AM14,2) -> 2853.93 | BD14: =ROUND(IF(T14=U14,IF((BC14-BB14)<AX14,AX14-(BC14-BB14),0)),2) -> 0 | BE14: =ROUND(AW14-AZ14-BA14+BB14+BD14,2) -> 3093.93 | BF14: -4192.85 | BG14: 0 | BH14: 0 | BI14: 0 | BJ14: =ROUND(BF14+BE14-5000-(BH14-BI14),2) -> -6098.92 | BK14: =ROUND(MAX(BJ14*{0.03,0.1,0.2,0.25,0.3,0.35,0.45}-{0,2520,16920,31920,52920,85920,181920}-BG14,0),2) -> 0 | BL14: =BG14+BK14 -> 0 | BM14: =ROUND(BE14-BK14,2) -> 3093.93 | BN14: 0 | BO14: =BE14+BN14 -> 3093.93 | BP14: =AZ14+BA14 -> 971.3 | BQ14: =AS14+AU14 -> 0 | BR14: =VLOOKUP(H14,社保公积金账单!D:D,1,0) -> 34120319890120316X | BS14: =T14-U14 -> 0
A15: 10 | B15: 江沪 | C15: 上海KA | D15: 上海 | E15: 上海 | F15: 单导长促 | G15: 董燕芳 | H15: 31022519780512504X | I15: 13917656516 | J15: NKA | K15: 直营 | L15: 欧发 | M15: 238976870 | N15: 大润发泥城店 | O15: 44958 | Q15: 2690 | R15: 3 | S15: 0 | T15: 16 | U15: 16 | V15: 0 | W15: 0 | X15: 0 | Y15: 2690 | Z15: 0 | AA15: 0 | AB15: 164.93 | AC15: 151.61111 | AD15: 0.9192452 | AE15: 1023.3333 | AF15: 0 | AG15: 161.125 | AH15: 862.20833 | AI15: 0 | AJ15: 80 | AK15: 80 | AL15: 0 | AM15: 160 | AQ15: 0 | AW15: 3792.21 | AX15: 2740 | AY15: 上海合杰 | AZ15: 783.3 | BA15: 188 | BB15: 0 | BC15: =ROUND(AW15-AZ15-BA15+BB15-AA15-AK15-AT15-AM15,2) -> 2580.91 | BD15: =ROUND(IF(T15=U15,IF((BC15-BB15)<AX15,AX15-(BC15-BB15),0)),2) -> 159.09 | BE15: =ROUND(AW15-AZ15-BA15+BB15+BD15,2) -> 2980 | BF15: -3584.73 | BG15: 0 | BH15: 0 | BI15: 0 | BJ15: =ROUND(BF15+BE15-5000-(BH15-BI15),2) -> -5604.73 | BK15: =ROUND(MAX(BJ15*{0.03,0.1,0.2,0.25,0.3,0.35,0.45}-{0,2520,16920,31920,52920,85920,181920}-BG15,0),2) -> 0 | BL15: =BG15+BK15 -> 0 | BM15: =ROUND(BE15-BK15,2) -> 2980 | BN15: 0 | BO15: =BE15+BN15 -> 2980 | BP15: =AZ15+BA15 -> 971.3 | BQ15: =AS15+AU15 -> 0 | BR15: =VLOOKUP(H15,社保公积金账单!D:D,1,0) -> 31022519780512504X | BS15: =T15-U15 -> 0
A16: 11 | B16: 江沪 | C16: 上海KA | D16: 上海 | E16: 上海 | F16: 单导长促 | G16: 过苗苗 | H16: 341224198812281328 | I16: 18221675997 | J16: NKA | K16: 直营 | L16: 欧发 | M16: 238976860 | N16: 大润发平型关店 | O16: 44348 | Q16: 2690 | R16: 4 | S16: 0 | T16: 16 | U16: 16 | V16: 0 | W16: 0 | X16: 0 | Y16: 2690 | Z16: 0 | AA16: 0 | AB16: 162.04 | AC16: 248.13889 | AD16: 1.5313434 | AE16: 1702.8333 | AF16: 0 | AG16: 187.45833 | AH16: 1515.375 | AI16: 0 | AJ16: 80 | AK16: 80 | AL16: 0 | AM16: 140 | AQ16: 0 | AW16: 4425.38 | AX16: 2740 | AY16: 上海合杰 | AZ16: 783.3 | BA16: 188 | BB16: 0 | BC16: =ROUND(AW16-AZ16-BA16+BB16-AA16-AK16-AT16-AM16,2) -> 3234.08 | BD16: =ROUND(IF(T16=U16,IF((BC16-BB16)<AX16,AX16-(BC16-BB16),0)),2) -> 0 | BE16: =ROUND(AW16-AZ16-BA16+BB16+BD16,2) -> 3454.08 | BF16: -3857.34 | BG16: 0 | BH16: 0 | BI16: 0 | BJ16: =ROUND(BF16+BE16-5000-(BH16-BI16),2) -> -5403.26 | BK16: =ROUND(MAX(BJ16*{0.03,0.1,0.2,0.25,0.3,0.35,0.45}-{0,2520,16920,31920,52920,85920,181920}-BG16,0),2) -> 0 | BL16: =BG16+BK16 -> 0 | BM16: =ROUND(BE16-BK16,2) -> 3454.08 | BN16: 0 | BO16: =BE16+BN16 -> 3454.08 | BP16: =AZ16+BA16 -> 971.3 | BQ16: =AS16+AU16 -> 0 | BR16: =VLOOKUP(H16,社保公积金账单!D:D,1,0) -> 341224198812281328 | BS16: =T16-U16 -> 0
A17: 12 | B17: 江沪 | C17: 上海KA | D17: 上海 | E17: 上海 | F17: 单导长促 | G17: 戈艳青 | H17: 32082319780513524X | I17: 13918265808 | J17: NKA | K17: 直营 | L17: 欧发 | M17: 238976844 | N17: 大润发泗泾店 | O17: 41738 | Q17: 2690 | R17: 11 | S17: 0 | T17: 16 | U17: 16 | V17: 0 | W17: 0 | X17: 0 | Y17: 2690 | Z17: 0 | AA17: 0 | AB17: 215.49 | AC17: 268.80556 | AD17: 1.2474155 | AE17: 1773.1667 | AF17: -154 | AG17: 326.29167 | AH17: 800.4375 | AI17: 0 | AJ17: 80 | AK17: 80 | AL17: 0 | AM17: 160 | AQ17: 0 | AW17: 3730.44 | AX17: 2740 | AY17: 上海合杰 | AZ17: 783.3 | BA17: 188 | BB17: 0 | BC17: =ROUND(AW17-AZ17-BA17+BB17-AA17-AK17-AT17-AM17,2) -> 2519.14 | BD17: =ROUND(IF(T17=U17,IF((BC17-BB17)<AX17,AX17-(BC17-BB17),0)),2) -> 220.86 | BE17: =ROUND(AW17-AZ17-BA17+BB17+BD17,2) -> 2980 | BF17: -5470.7 | BG17: 0 | BH17: 0 | BI17: 0 | BJ17: =ROUND(BF17+BE17-5000-(BH17-BI17),2) -> -7490.7 | BK17: =ROUND(MAX(BJ17*{0.03,0.1,0.2,0.25,0.3,0.35,0.45}-{0,2520,16920,31920,52920,85920,181920}-BG17,0),2) -> 0 | BL17: =BG17+BK17 -> 0 | BM17: =ROUND(BE17-BK17,2) -> 2980 | BN17: 0 | BO17: =BE17+BN17 -> 2980 | BP17: =AZ17+BA17 -> 971.3 | BQ17: =AS17+AU17 -> 0 | BR17: =VLOOKUP(H17,社保公积金账单!D:D,1,0) -> 32082319780513524X | BS17: =T17-U17 -> 0
A18: 13 | B18: 江沪 | C18: 上海KA | D18: 上海 | E18: 上海 | F18: 单导长促 | G18: 杜以花 | H18: 371122198002227829 | I18: 13917635644 | J18: NKA | K18: 直营 | L18: 欧发 | M18: 238976844 | N18: 大润发泗泾店 | O18: 44743 | Q18: 2690 | R18: 3 | S18: 0 | T18: 22 | U18: 19 | V18: 3 | W18: 0 | X18: 261.54545 | Y18: 2584.7273 | Z18: 0 | AA18: 0 | AB18: 215.49 | AC18: 268.80556 | AD18: 1.2474155 | AE18: 1773.1667 | AF18: -154 | AG18: 326.29167 | AH18: 800.44 | AI18: 0 | AJ18: 69.090909 | AK18: 69.090909 | AL18: 0 | AM18: 190 | AQ18: 0 | AW18: 3644.26 | AX18: 2740 | AY18: 上海合杰 | AZ18: 783.3 | BA18: 188 | BB18: 0 | BC18: =ROUND(AW18-AZ18-BA18+BB18-AA18-AK18-AT18-AM18,2) -> 2413.87 | BD18: =ROUND(IF(T18=U18,IF((BC18-BB18)<AX18,AX18-(BC18-BB18),0)),2) -> 0 | BE18: =ROUND(AW18-AZ18-BA18+BB18+BD18,2) -> 2672.96 | BF18: -6222.04 | BG18: 0 | BH18: 0 | BI18: 0 | BJ18: =ROUND(BF18+BE18-5000-(BH18-BI18),2) -> -8549.08 | BK18: =ROUND(MAX(BJ18*{0.03,0.1,0.2,0.25,0.3,0.35,0.45}-{0,2520,16920,31920,52920,85920,181920}-BG18,0),2) -> 0 | BL18: =BG18+BK18 -> 0 | BM18: =ROUND(BE18-BK18,2) -> 2672.96 | BN18: 0 | BO18: =BE18+BN18 -> 2672.96 | BP18: =AZ18+BA18 -> 971.3 | BQ18: =AS18+AU18 -> 0 | BR18: =VLOOKUP(H18,社保公积金账单!D:D,1,0) -> 371122198002227829 | BS18: =T18-U18 -> 3
A19: 14 | B19: 江沪 | C19: 上海KA | D19: 上海 | E19: 上海 | F19: 单导长促 | G19: 车文秀 | H19: 341623199710154424 | I19: 15801898274 | J19: NKA | K19: 直营 | L19: 欧发 | M19: 238976838 | N19: 大润发松江店 | O19: 43412 | Q19: 2690 | R19: 7 | S19: 0 | T19: 16 | U19: 16 | V19: 0 | W19: 0 | X19: 0 | Y19: 2690 | Z19: 0 | AA19: 0 | AB19: 668.32 | AC19: 710.91667 | AD19: 1.0637369 | AE19: 6292.3333 | AF19: -343.125 | AG19: 975.66667 | AH19: 2829.8958 | AI19: 0 | AJ19: 80 | AK19: 80 | AL19: 0 | AM19: 160 | AQ19: 0 | AW19: 5759.9 | AX19: 2740 | AY19: 上海合杰 | AZ19: 783.3 | BA19: 188 | BB19: 0 | BC19: =ROUND(AW19-AZ19-BA19+BB19-AA19-AK19-AT19-AM19,2) -> 4548.6 | BD19: =ROUND(IF(T19=U19,IF((BC19-BB19)<AX19,AX19-(BC19-BB19),0)),2) -> 0 | BE19: =ROUND(AW19-AZ19-BA19+BB19+BD19,2) -> 4788.6 | BF19: 2709.46 | BG19: 81.28 | BH19: 0 | BI19: 0 | BJ19: =ROUND(BF19+BE19-5000-(BH19-BI19),2) -> 2498.06 | BK19: =ROUND(MAX(BJ19*{0.03,0.1,0.2,0.25,0.3,0.35,0.45}-{0,2520,16920,31920,52920,85920,181920}-BG19,0),2) -> 0 | BL19: =BG19+BK19 -> 81.28 | BM19: =ROUND(BE19-BK19,2) -> 4788.6 | BN19: 0 | BO19: =BE19+BN19 -> 4788.6 | BP19: =AZ19+BA19 -> 971.3 | BQ19: =AS19+AU19 -> 0 | BR19: =VLOOKUP(H19,社保公积金账单!D:D,1,0) -> 341623199710154424 | BS19: =T19-U19 -> 0
A20: 15 | B20: 江沪 | C20: 上海KA | D20: 上海 | E20: 上海 | F20: 单导长促 | G20: 魏永慧 | H20: 511121197511274186 | I20: 15601859520 | J20: NKA | K20: 直营 | L20: 欧发 | M20: 238976838 | N20: 大润发松江店 | O20: 44323 | Q20: 2690 | R20: 4 | S20: 0 | T20: 22 | U20: 22 | V20: 0 | W20: 0 | X20: 0 | Y20: 2690 | Z20: 0 | AA20: 0 | AB20: 668.32 | AC20: 710.91667 | AD20: 1.0637369 | AE20: 6292.3333 | AF20: -343.125 | AG20: 975.66667 | AH20: 2829.8958 | AI20: 0 | AJ20: 80 | AK20: 80 | AL20: 0 | AM20: 220 | AQ20: 0 | AW20: 5819.9 | AX20: 2740 | AY20: 上海合杰 | AZ20: 783.3 | BA20: 188 | BB20: 0 | BC20: =ROUND(AW20-AZ20-BA20+BB20-AA20-AK20-AT20-AM20,2) -> 4548.6 | BD20: =ROUND(IF(T20=U20,IF((BC20-BB20)<AX20,AX20-(BC20-BB20),0)),2) -> 0 | BE20: =ROUND(AW20-AZ20-BA20+BB20+BD20,2) -> 4848.6 | BF20: 3025.23 | BG20: 90.76 | BH20: 0 | BI20: 0 | BJ20: =ROUND(BF20+BE20-5000-(BH20-BI20),2) -> 2873.83 | BK20: =ROUND(MAX(BJ20*{0.03,0.1,0.2,0.25,0.3,0.35,0.45}-{0,2520,16920,31920,52920,85920,181920}-BG20,0),2) -> 0 | BL20: =BG20+BK20 -> 90.76 | BM20: =ROUND(BE20-BK20,2) -> 4848.6 | BN20: 0 | BO20: =BE20+BN20 -> 4848.6 | BP20: =AZ20+BA20 -> 971.3 | BQ20: =AS20+AU20 -> 0 | BR20: =VLOOKUP(H20,社保公积金账单!D:D,1,0) -> 511121197511274186 | BS20: =T20-U20 -> 0
A21: 16 | B21: 江沪 | C21: 上海KA | D21: 上海 | E21: 上海 | F21: 单导长促 | G21: 李永杰 | H21: 410923198302047231 | I21: 15286921996 | J21: NKA | K21: 直营 | L21: 欧发 | M21: 238976858 | N21: 大润发杨浦店 | O21: 43476 | Q21: 2690 | R21: 7 | S21: 0 | T21: 16 | U21: 16 | V21: 0 | W21: 0 | X21: 0 | Y21: 2690 | Z21: 0 | AA21: 0 | AB21: 214.35 | AC21: 323.5 | AD21: 1.5092139 | AE21: 2596.1667 | AF21: 0 | AG21: 483.20833 | AH21: 845.18333 | AI21: 0 | AJ21: 80 | AK21: 80 | AL21: 0 | AM21: 160 | AQ21: 0 | AW21: 3775.18 | AX21: 2740 | AY21: 上海合杰 | AZ21: 783.3 | BA21: 188 | BB21: 0 | BC21: =ROUND(AW21-AZ21-BA21+BB21-AA21-AK21-AT21-AM21,2) -> 2563.88 | BD21: =ROUND(IF(T21=U21,IF((BC21-BB21)<AX21,AX21-(BC21-BB21),0)),2) -> 176.12 | BE21: =ROUND(AW21-AZ21-BA21+BB21+BD21,2) -> 2980 | BF21: -5945.56 | BG21: 0 | BH21: 0 | BI21: 0 | BJ21: =ROUND(BF21+BE21-5000-(BH21-BI21),2) -> -7965.56 | BK21: =ROUND(MAX(BJ21*{0.03,0.1,0.2,0.25,0.3,0.35,0.45}-{0,2520,16920,31920,52920,85920,181920}-BG21,0),2) -> 0 | BL21: =BG21+BK21 -> 0 | BM21: =ROUND(BE21-BK21,2) -> 2980 | BN21: 0 | BO21: =BE21+BN21 -> 2980 | BP21: =AZ21+BA21 -> 971.3 | BQ21: =AS21+AU21 -> 0 | BR21: =VLOOKUP(H21,社保公积金账单!D:D,1,0) -> 410923198302047231 | BS21: =T21-U21 -> 0
A22: 17 | B22: 江沪 | C22: 上海KA | D22: 上海 | E22: 上海 | F22: 单导长促 | G22: 姚友美 | H22: 34122619830430352X | I22: 17355881696 | J22: NKA | K22: 直营 | L22: 欧发 | M22: 238976888 | N22: 大润发杨浦店 | O22: 44835 | Q22: 2690 | R22: 3 | S22: 0 | T22: 27 | U22: 27 | V22: 0 | W22: 0 | X22: 0 | Y22: 2690 | Z22: 0 | AA22: 0 | AB22: 214.35 | AC22: 323.5 | AD22: 1.5092139 | AE22: 2596.1667 | AF22: 0 | AG22: 483.20833 | AH22: 1267.775 | AI22: 0 | AJ22: 80 | AK22: 80 | AL22: 0 | AM22: 270 | AQ22: 0 | AW22: 4307.78 | AX22: 2740 | AY22: 上海合杰 | AZ22: 783.3 | BA22: 188 | BB22: 0 | BC22: =ROUND(AW22-AZ22-BA22+BB22-AA22-AK22-AT22-AM22,2) -> 2986.48 | BD22: =ROUND(IF(T22=U22,IF((BC22-BB22)<AX22,AX22-(BC22-BB22),0)),2) -> 0 | BE22: =ROUND(AW22-AZ22-BA22+BB22+BD22,2) -> 3336.48 | BF22: -4193.34 | BG22: 0 | BH22: 0 | BI22: 0 | BJ22: =ROUND(BF22+BE22-5000-(BH22-BI22),2) -> -5856.86 | BK22: =ROUND(MAX(BJ22*{0.03,0.1,0.2,0.25,0.3,0.35,0.45}-{0,2520,16920,31920,52920,85920,181920}-BG22,0),2) -> 0 | BL22: =BG22+BK22 -> 0 | BM22: =ROUND(BE22-BK22,2) -> 3336.48 | BN22: 0 | BO22: =BE22+BN22 -> 3336.48 | BP22: =AZ22+BA22 -> 971.3 | BQ22: =AS22+AU22 -> 0 | BR22: =VLOOKUP(H22,社保公积金账单!D:D,1,0) -> 34122619830430352X | BS22: =T22-U22 -> 0
A23: 18 | B23: 江沪 | C23: 上海KA | D23: 上海 | E23: 上海 | F23: 单导长促 | G23: 王丽莉 | H23: 342423197609202840 | I23: 15801729382 | J23: NKA | K23: 直营 | L23: 欧发 | M23: 238976866 | N23: 大润发大宁店 | O23: 43952 | Q23: 2690 | R23: 5 | S23: 0 | T23: 15 | U23: 13 | V23: 0 | W23: 2 | X23: 0 | Y23: 2331.3333 | Z23: 0 | AA23: 0 | AB23: 93.67 | AC23: 193 | AD23: 2.0604249 | AE23: 1428.25 | AF23: 0 | AG23: 181.91667 | AH23: 1246.33 | AI23: 0 | AJ23: 69.333333 | AK23: 69.333333 | AL23: 0 | AM23: 130 | AQ23: 0 | AW23: 3777 | AX23: 2740 | AY23: 上海合杰 | AZ23: 783.3 | BA23: 188 | BB23: 0 | BC23: =ROUND(AW23-AZ23-BA23+BB23-AA23-AK23-AT23-AM23,2) -> 2606.37 | BD23: =ROUND(IF(T23=U23,IF((BC23-BB23)<AX23,AX23-(BC23-BB23),0)),2) -> 0 | BE23: =ROUND(AW23-AZ23-BA23+BB23+BD23,2) -> 2805.7 | BF23: -3221.73 | BG23: 0 | BH23: 0 | BI23: 0 | BJ23: =ROUND(BF23+BE23-5000-(BH23-BI23),2) -> -5416.03 | BK23: =ROUND(MAX(BJ23*{0.03,0.1,0.2,0.25,0.3,0.35,0.45}-{0,2520,16920,31920,52920,85920,181920}-BG23,0),2) -> 0 | BL23: =BG23+BK23 -> 0 | BM23: =ROUND(BE23-BK23,2) -> 2805.7 | BN23: 0 | BO23: =BE23+BN23 -> 2805.7 | BP23: =AZ23+BA23 -> 971.3 | BQ23: =AS23+AU23 -> 0 | BR23: =VLOOKUP(H23,社保公积金账单!D:D,1,0) -> 342423197609202840 | BS23: =T23-U23 -> 2
A24: 19 | B24: 江沪 | C24: 上海KA | D24: 上海 | E24: 上海 | F24: 单导长促 | G24: 黄莹 | H24: 370481198807021823 | I24: 13585585049 | J24: NKA | K24: 直营 | L24: 欧发 | M24: 238976868 | N24: 大润发美兰湖店 | O24: 43333 | Q24: 2690 | R24: 7 | S24: 0 | T24: 16 | U24: 16 | V24: 0 | W24: 0 | X24: 0 | Y24: 2690 | Z24: 0 | AA24: 0 | AB24: 246.53 | AC24: 350.41667 | AD24: 1.4213956 | AE24: 2156.5833 | AF24: 0 | AG24: 281.20833 | AH24: 1875.375 | AI24: 0 | AJ24: 80 | AK24: 80 | AL24: 0 | AM24: 160 | AQ24: 0 | AW24: 4805.38 | AX24: 2740 | AY24: 上海合杰 | AZ24: 783.3 | BA24: 188 | BB24: 0 | BC24: =ROUND(AW24-AZ24-BA24+BB24-AA24-AK24-AT24-AM24,2) -> 3594.08 | BD24: =ROUND(IF(T24=U24,IF((BC24-BB24)<AX24,AX24-(BC24-BB24),0)),2) -> 0 | BE24: =ROUND(AW24-AZ24-BA24+BB24+BD24,2) -> 3834.08 | BF24: -692.73 | BG24: 4.15 | BH24: 0 | BI24: 0 | BJ24: =ROUND(BF24+BE24-5000-(BH24-BI24),2) -> -1858.65 | BK24: =ROUND(MAX(BJ24*{0.03,0.1,0.2,0.25,0.3,0.35,0.45}-{0,2520,16920,31920,52920,85920,181920}-BG24,0),2) -> 0 | BL24: =BG24+BK24 -> 4.15 | BM24: =ROUND(BE24-BK24,2) -> 3834.08 | BN24: 0 | BO24: =BE24+BN24 -> 3834.08 | BP24: =AZ24+BA24 -> 971.3 | BQ24: =AS24+AU24 -> 0 | BR24: =VLOOKUP(H24,社保公积金账单!D:D,1,0) -> 370481198807021823 | BS24: =T24-U24 -> 0
A25: 20 | B25: 江沪 | C25: 上海KA | D25: 上海 | E25: 上海 | F25: 单导长促 | G25: 刘宝连 | H25: 413026197908287553 | I25: 13671903482 | J25: NKA | K25: 直营 | L25: 欧发 | M25: 238976854 | N25: 大润发大华店 | O25: 42353 | Q25: 2690 | R25: 10 | S25: 0 | T25: 15 | U25: 15 | V25: 0 | W25: 0 | X25: 0 | Y25: 2690 | Z25: 0 | AA25: 0 | AB25: 182.17 | AC25: 255.94444 | AD25: 1.4049758 | AE25: 1625.4167 | AF25: 210 | AG25: 264.58333 | AH25: 1150.8333 | AI25: 0 | AJ25: 80 | AK25: 80 | AL25: 0 | AM25: 120 | AQ25: 0 | AW25: 4040.83 | AX25: 2740 | AY25: 上海合杰 | AZ25: 783.3 | BA25: 188 | BB25: 0 | BC25: =ROUND(AW25-AZ25-BA25+BB25-AA25-AK25-AT25-AM25,2) -> 2869.53 | BD25: =ROUND(IF(T25=U25,IF((BC25-BB25)<AX25,AX25-(BC25-BB25),0)),2) -> 0 | BE25: =ROUND(AW25-AZ25-BA25+BB25+BD25,2) -> 3069.53 | BF25: -3544.99 | BG25: 0 | BH25: 0 | BI25: 0 | BJ25: =ROUND(BF25+BE25-5000-(BH25-BI25),2) -> -5475.46 | BK25: =ROUND(MAX(BJ25*{0.03,0.1,0.2,0.25,0.3,0.35,0.45}-{0,2520,16920,31920,52920,85920,181920}-BG25,0),2) -> 0 | BL25: =BG25+BK25 -> 0 | BM25: =ROUND(BE25-BK25,2) -> 3069.53 | BN25: 0 | BO25: =BE25+BN25 -> 3069.53 | BP25: =AZ25+BA25 -> 971.3 | BQ25: =AS25+AU25 -> 0 | BR25: =VLOOKUP(H25,社保公积金账单!D:D,1,0) -> 413026197908287553 | BS25: =T25-U25 -> 0
A26: 21 | B26: 江沪 | C26: 上海KA | D26: 上海 | E26: 上海 | F26: 单导长促 | G26: 过小娟 | H26: 341622198311041341 | I26: 17717590761 | J26: NKA | K26: 直营 | L26: 欧发 | M26: 238976852 | N26: 大润发南翔店 | O26: 45545 | Q26: 2690 | R26: 1 | S26: 0 | T26: 15 | U26: 15 | V26: 0 | W26: 0 | X26: 0 | Y26: 2690 | Z26: 0 | AA26: 0 | AB26: 129.3 | AC26: 183.36111 | AD26: 1.418106 | AE26: 1228.0833 | AF26: 0 | AG26: 264.125 | AH26: 963.95833 | AI26: 0 | AJ26: 80 | AK26: 80 | AL26: 0 | AM26: 150 | AQ26: 0 | AW26: 3883.96 | AX26: 2740 | AY26: 上海合杰 | AZ26: 783.3 | BA26: 188 | BB26: 0 | BC26: =ROUND(AW26-AZ26-BA26+BB26-AA26-AK26-AT26-AM26,2) -> 2682.66 | BD26: =ROUND(IF(T26=U26,IF((BC26-BB26)<AX26,AX26-(BC26-BB26),0)),2) -> 57.34 | BE26: =ROUND(AW26-AZ26-BA26+BB26+BD26,2) -> 2970 | BF26: -4817.53 | BG26: 0 | BH26: 0 | BI26: 0 | BJ26: =ROUND(BF26+BE26-5000-(BH26-BI26),2) -> -6847.53 | BK26: =ROUND(MAX(BJ26*{0.03,0.1,0.2,0.25,0.3,0.35,0.45}-{0,2520,16920,31920,52920,85920,181920}-BG26,0),2) -> 0 | BL26: =BG26+BK26 -> 0 | BM26: =ROUND(BE26-BK26,2) -> 2970 | BN26: 0 | BO26: =BE26+BN26 -> 2970 | BP26: =AZ26+BA26 -> 971.3 | BQ26: =AS26+AU26 -> 0 | BR26: =VLOOKUP(H26,社保公积金账单!D:D,1,0) -> 341622198311041341 | BS26: =T26-U26 -> 0
A27: 22 | B27: 江沪 | C27: 上海KA | D27: 上海 | E27: 上海 | F27: 单导长促 | G27: 严洪玉 | H27: 320882197404083426 | I27: 15902185361 | J27: NKA | K27: 直营 | L27: 欧发 | M27: 238976862 | N27: 大润发三林店 | O27: 44501 | Q27: 2690 | R27: 4 | S27: 0 | T27: 15 | U27: 15 | V27: 0 | W27: 0 | X27: 0 | Y27: 2690 | Z27: 6 | AA27: 755.86207 | AB27: 199.99 | AC27: 275.5 | AD27: 1.3775689 | AE27: 1932 | AF27: 37.5 | AG27: 343.58333 | AH27: 1550.9167 | AI27: 0 | AJ27: 80 | AK27: 80 | AL27: 0 | AM27: 150 | AQ27: 0 | AW27: 5226.78 | AX27: 2740 | AY27: 上海合杰 | AZ27: 783.3 | BA27: 188 | BB27: 0 | BC27: =ROUND(AW27-AZ27-BA27+BB27-AA27-AK27-AT27-AM27,2) -> 3269.62 | BD27: =ROUND(IF(T27=U27,IF((BC27-BB27)<AX27,AX27-(BC27-BB27),0)),2) -> 0 | BE27: =ROUND(AW27-AZ27-BA27+BB27+BD27,2) -> 4255.48 | BF27: -1217.85 | BG27: 0 | BH27: 0 | BI27: 0 | BJ27: =ROUND(BF27+BE27-5000-(BH27-BI27),2) -> -1962.37 | BK27: =ROUND(MAX(BJ27*{0.03,0.1,0.2,0.25,0.3,0.35,0.45}-{0,2520,16920,31920,52920,85920,181920}-BG27,0),2) -> 0 | BL27: =BG27+BK27 -> 0 | BM27: =ROUND(BE27-BK27,2) -> 4255.48 | BN27: 0 | BO27: =BE27+BN27 -> 4255.48 | BP27: =AZ27+BA27 -> 971.3 | BQ27: =AS27+AU27 -> 0 | BR27: =VLOOKUP(H27,社保公积金账单!D:D,1,0) -> 320882197404083426 | BS27: =T27-U27 -> 0
A28: 23 | B28: 江沪 | C28: 上海KA | D28: 上海 | E28: 上海 | F28: 单导长促 | G28: 孟书丽 | H28: 511023197705278588 | I28: 15800379800 | J28: NKA | K28: 直营 | L28: 欧发 | M28: 238976856 | N28: 大润发闸北店 | O28: 44287 | Q28: 2690 | R28: 4 | S28: 0 | T28: 22 | U28: 22 | V28: 0 | W28: 0 | X28: 0 | Y28: 2690 | Z28: 0 | AA28: 0 | AB28: 293.65 | AC28: 434.66667 | AD28: 1.4802202 | AE28: 2929.8333 | AF28: 0 | AG28: 521.41667 | AH28: 1728.4167 | AI28: 0 | AJ28: 80 | AK28: 80 | AL28: 0 | AM28: 190 | AQ28: 0 | AW28: 4688.42 | AX28: 2740 | AY28: 上海合杰 | AZ28: 783.3 | BA28: 188 | BB28: 0 | BC28: =ROUND(AW28-AZ28-BA28+BB28-AA28-AK28-AT28-AM28,2) -> 3447.12 | BD28: =ROUND(IF(T28=U28,IF((BC28-BB28)<AX28,AX28-(BC28-BB28),0)),2) -> 0 | BE28: =ROUND(AW28-AZ28-BA28+BB28+BD28,2) -> 3717.12 | BF28: -1623.27 | BG28: 0 | BH28: 0 | BI28: 0 | BJ28: =ROUND(BF28+BE28-5000-(BH28-BI28),2) -> -2906.15 | BK28: =ROUND(MAX(BJ28*{0.03,0.1,0.2,0.25,0.3,0.35,0.45}-{0,2520,16920,31920,52920,85920,181920}-BG28,0),2) -> 0 | BL28: =BG28+BK28 -> 0 | BM28: =ROUND(BE28-BK28,2) -> 3717.12 | BN28: 0 | BO28: =BE28+BN28 -> 3717.12 | BP28: =AZ28+BA28 -> 971.3 | BQ28: =AS28+AU28 -> 0 | BR28: =VLOOKUP(H28,社保公积金账单!D:D,1,0) -> 511023197705278588 | BS28: =T28-U28 -> 0
A29: 24 | B29: 江沪 | C29: 上海KA | D29: 上海 | E29: 上海 | F29: 单导长促 | G29: 管兵娥 | H29: 362329198211245745 | I29: 15800762272 | J29: NKA | K29: 直营 | L29: 欧发 | M29: 238976862 | N29: 大润发安亭店 | O29: 39548 | Q29: 2690 | R29: 17 | S29: 0 | T29: 15 | U29: 15 | V29: 0 | W29: 0 | X29: 0 | Y29: 2690 | Z29: 0 | AA29: 0 | AB29: 141.35 | AC29: 259 | AD29: 1.8323311 | AE29: 1736.5 | AF29: 0 | AG29: 197.66667 | AH29: 1538.8333 | AI29: 0 | AJ29: 80 | AK29: 80 | AL29: 0 | AM29: 150 | AQ29: 0 | AW29: 4458.83 | AX29: 2740 | AY29: 上海合杰 | AZ29: 783.3 | BA29: 188 | BB29: 0 | BC29: =ROUND(AW29-AZ29-BA29+BB29-AA29-AK29-AT29-AM29,2) -> 3257.53 | BD29: =ROUND(IF(T29=U29,IF((BC29-BB29)<AX29,AX29-(BC29-BB29),0)),2) -> 0 | BE29: =ROUND(AW29-AZ29-BA29+BB29+BD29,2) -> 3487.53 | BF29: -2059.14 | BG29: 0 | BH29: 0 | BI29: 0 | BJ29: =ROUND(BF29+BE29-5000-(BH29-BI29),2) -> -3571.61 | BK29: =ROUND(MAX(BJ29*{0.03,0.1,0.2,0.25,0.3,0.35,0.45}-{0,2520,16920,31920,52920,85920,181920}-BG29,0),2) -> 0 | BL29: =BG29+BK29 -> 0 | BM29: =ROUND(BE29-BK29,2) -> 3487.53 | BN29: 0 | BO29: =BE29+BN29 -> 3487.53 | BP29: =AZ29+BA29 -> 971.3 | BQ29: =AS29+AU29 -> 0 | BR29: =VLOOKUP(H29,社保公积金账单!D:D,1,0) -> 362329198211245745 | BS29: =T29-U29 -> 0
A30: 25 | B30: 江沪 | C30: 上海KA | D30: 上海 | E30: 上海 | F30: 单导长促 | G30: 李春霞 | H30: 340222197807066625 | I30: 15821963037 | J30: NKA | K30: 直营 | L30: 欧发 | M30: 238976898 | N30: 欧尚澄浏店 | O30: 43160 | Q30: 2690 | R30: 8 | S30: 0 | T30: 16 | U30: 16 | V30: 0 | W30: 0 | X30: 0 | Y30: 2690 | Z30: 0 | AA30: 0 | AB30: 183.89 | AC30: 239.69444 | AD30: 1.3034664 | AE30: 1644.9167 | AF30: 467 | AG30: 177.375 | AH30: 1000.5417 | AI30: 0 | AJ30: 80 | AK30: 80 | AL30: 0 | AM30: 160 | AQ30: 0 | AW30: 3930.54 | AX30: 2740 | AY30: 上海合杰 | AZ30: 783.3 | BA30: 188 | BB30: 0 | BC30: =ROUND(AW30-AZ30-BA30+BB30-AA30-AK30-AT30-AM30,2) -> 2719.24 | BD30: =ROUND(IF(T30=U30,IF((BC30-BB30)<AX30,AX30-(BC30-BB30),0)),2) -> 20.76 | BE30: =ROUND(AW30-AZ30-BA30+BB30+BD30,2) -> 2980 | BF30: -2647.26 | BG30: 0 | BH30: 1600 | BI30: 1200 | BJ30: =ROUND(BF30+BE30-5000-(BH30-BI30),2) -> -5067.26 | BK30: =ROUND(MAX(BJ30*{0.03,0.1,0.2,0.25,0.3,0.35,0.45}-{0,2520,16920,31920,52920,85920,181920}-BG30,0),2) -> 0 | BL30: =BG30+BK30 -> 0 | BM30: =ROUND(BE30-BK30,2) -> 2980 | BN30: 0 | BO30: =BE30+BN30 -> 2980 | BP30: =AZ30+BA30 -> 971.3 | BQ30: =AS30+AU30 -> 0 | BR30: =VLOOKUP(H30,社保公积金账单!D:D,1,0) -> 340222197807066625 | BS30: =T30-U30 -> 0
A31: 26 | B31: 江沪 | C31: 上海KA | D31: 上海 | E31: 上海 | F31: 单导长促 | G31: 东港 | H31: 210422198201031424 | I31: 15000805616 | J31: NKA | K31: 直营 | L31: 欧发 | M31: 238976892 | N31: 欧尚嘉定店 | O31: 42821 | Q31: 2690 | R31: 8 | S31: 0 | T31: 16 | U31: 16 | V31: 0 | W31: 0 | X31: 0 | Y31: 2690 | Z31: 0 | AA31: 0 | AB31: 225.26 | AC31: 289.63889 | AD31: 1.2857981 | AE31: 1979.3333 | AF31: 0 | AG31: 256.25 | AH31: 861.54167 | AI31: 0 | AJ31: 80 | AK31: 80 | AL31: 0 | AM31: 160 | AQ31: 0 | AW31: 3791.54 | AX31: 2740 | AY31: 上海合杰 | AZ31: 783.3 | BA31: 188 | BB31: 0 | BC31: =ROUND(AW31-AZ31-BA31+BB31-AA31-AK31-AT31-AM31,2) -> 2580.24 | BD31: =ROUND(IF(T31=U31,IF((BC31-BB31)<AX31,AX31-(BC31-BB31),0)),2) -> 159.76 | BE31: =ROUND(AW31-AZ31-BA31+BB31+BD31,2) -> 2980 | BF31: -6679.09 | BG31: 0 | BH31: 0 | BI31: 0 | BJ31: =ROUND(BF31+BE31-5000-(BH31-BI31),2) -> -8699.09 | BK31: =ROUND(MAX(BJ31*{0.03,0.1,0.2,0.25,0.3,0.35,0.45}-{0,2520,16920,31920,52920,85920,181920}-BG31,0),2) -> 0 | BL31: =BG31+BK31 -> 0 | BM31: =ROUND(BE31-BK31,2) -> 2980 | BN31: 0 | BO31: =BE31+BN31 -> 2980 | BP31: =AZ31+BA31 -> 971.3 | BQ31: =AS31+AU31 -> 0 | BR31: =VLOOKUP(H31,社保公积金账单!D:D,1,0) -> 210422198201031424 | BS31: =T31-U31 -> 0
A32: 27 | B32: 江沪 | C32: 上海KA | D32: 上海 | E32: 上海 | F32: 单导长促 | G32: 王美芳 | H32: 310114197706063424 | I32: 15821178955 | J32: NKA | K32: 直营 | L32: 欧发 | M32: 238976892 | N32: 欧尚嘉定店 | O32: 39114 | Q32: 2690 | R32: 19 | S32: 0 | T32: 22 | U32: 22 | V32: 0 | W32: 0 | X32: 0 | Y32: 2690 | Z32: 0 | AA32: 0 | AB32: 225.26 | AC32: 289.63889 | AD32: 1.2857981 | AE32: 1979.3333 | AF32: 0 | AG32: 256.25 | AH32: 861.54167 | AI32: 0 | AJ32: 80 | AK32: 80 | AL32: 0 | AM32: 170 | AQ32: 0 | AW32: 3801.54 | AX32: 2740 | AY32: 上海合杰 | AZ32: 783.3 | BA32: 188 | BB32: 0 | BC32: =ROUND(AW32-AZ32-BA32+BB32-AA32-AK32-AT32-AM32,2) -> 2580.24 | BD32: =ROUND(IF(T32=U32,IF((BC32-BB32)<AX32,AX32-(BC32-BB32),0)),2) -> 159.76 | BE32: =ROUND(AW32-AZ32-BA32+BB32+BD32,2) -> 2990 | BF32: -4591.23 | BG32: 0 | BH32: 0 | BI32: 0 | BJ32: =ROUND(BF32+BE32-5000-(BH32-BI32),2) -> -6601.23 | BK32: =ROUND(MAX(BJ32*{0.03,0.1,0.2,0.25,0.3,0.35,0.45}-{0,2520,16920,31920,52920,85920,181920}-BG32,0),2) -> 0 | BL32: =BG32+BK32 -> 0 | BM32: =ROUND(BE32-BK32,2) -> 2990 | BN32: 0 | BO32: =BE32+BN32 -> 2990 | BP32: =AZ32+BA32 -> 971.3 | BQ32: =AS32+AU32 -> 0 | BR32: =VLOOKUP(H32,社保公积金账单!D:D,1,0) -> 310114197706063424 | BS32: =T32-U32 -> 0
A33: 28 | B33: 江沪 | C33: 上海KA | D33: 上海 | E33: 上海 | F33: 单导长促 | G33: 鲜秀英 | H33: 513030198510153427 | I33: 15601960086 | J33: NKA | K33: 直营 | L33: 欧发 | M33: 238977282 | N33: 欧尚金山店 | O33: 46093 | Q33: 2740 | R33: 0 | S33: 0 | T33: 15 | U33: 10 | V33: 0 | W33: 0 | X33: 0 | Y33: 1826.6667 | Z33: 0 | AA33: 0 | AB33: 218.92 | AC33: 290.97222 | AD33: 1.3291258 | AE33: 2139.8333 | AF33: 0 | AG33: 648.08333 | AH33: 1490.92 | AI33: 0 | AJ33: 53.333333 | AK33: 53.333333 | AL33: 0 | AM33: 100 | AQ33: 0 | AW33: 3470.92 | AX33: 2740 | AY33: 上海合杰 | AZ33: 783.3 | BA33: 192 | BB33: 0 | BC33: =ROUND(AW33-AZ33-BA33+BB33-AA33-AK33-AT33-AM33,2) -> 2342.29 | BD33: =ROUND(IF(T33=U33,IF((BC33-BB33)<AX33,AX33-(BC33-BB33),0)),2) -> 0 | BE33: =ROUND(AW33-AZ33-BA33+BB33+BD33,2) -> 2495.62 | BF33: 0 | BG33: 0 | BH33: 0 | BI33: 0 | BJ33: =ROUND(BF33+BE33-5000-(BH33-BI33),2) -> -2504.38 | BK33: =ROUND(MAX(BJ33*{0.03,0.1,0.2,0.25,0.3,0.35,0.45}-{0,2520,16920,31920,52920,85920,181920}-BG33,0),2) -> 0 | BL33: =BG33+BK33 -> 0 | BM33: =ROUND(BE33-BK33,2) -> 2495.62 | BN33: 0 | BO33: =BE33+BN33 -> 2495.62 | BP33: =AZ33+BA33 -> 975.3 | BQ33: =AS33+AU33 -> 0 | BR33: =VLOOKUP(H33,社保公积金账单!D:D,1,0) -> 513030198510153427 | BS33: =T33-U33 -> 5
A34: 29 | B34: 江沪 | C34: 上海KA | D34: 上海 | E34: 上海 | F34: 单导长促 | G34: 王霞芹 | H34: 310225198204112424 | I34: 15921030310 | J34: NKA | K34: 直营 | L34: 欧发 | M34: 238976894 | N34: 欧尚南汇店 | O34: 43160 | Q34: 2690 | R34: 8 | S34: 0 | T34: 15 | U34: 15 | V34: 0 | W34: 0 | X34: 0 | Y34: 2690 | Z34: 0 | AA34: 0 | AB34: 398.21 | AC34: 408.66667 | AD34: 1.0262592 | AE34: 3537.6667 | AF34: 0 | AG34: 616.33333 | AH34: 2921.3333 | AI34: 0 | AJ34: 80 | AK34: 80 | AL34: 0 | AM34: 140 | AQ34: 0 | AW34: 5831.33 | AX34: 2740 | AY34: 上海合杰 | AZ34: 783.3 | BA34: 188 | BB34: 0 | BC34: =ROUND(AW34-AZ34-BA34+BB34-AA34-AK34-AT34-AM34,2) -> 4640.03 | BD34: =ROUND(IF(T34=U34,IF((BC34-BB34)<AX34,AX34-(BC34-BB34),0)),2) -> 0 | BE34: =ROUND(AW34-AZ34-BA34+BB34+BD34,2) -> 4860.03 | BF34: 4504.83 | BG34: 135.14 | BH34: 0 | BI34: 0 | BJ34: =ROUND(BF34+BE34-5000-(BH34-BI34),2) -> 4364.86 | BK34: =ROUND(MAX(BJ34*{0.03,0.1,0.2,0.25,0.3,0.35,0.45}-{0,2520,16920,31920,52920,85920,181920}-BG34,0),2) -> 0 | BL34: =BG34+BK34 -> 135.14 | BM34: =ROUND(BE34-BK34,2) -> 4860.03 | BN34: 0 | BO34: =BE34+BN34 -> 4860.03 | BP34: =AZ34+BA34 -> 971.3 | BQ34: =AS34+AU34 -> 0 | BR34: =VLOOKUP(H34,社保公积金账单!D:D,1,0) -> 310225198204112424 | BS34: =T34-U34 -> 0
A35: 30 | B35: 江沪 | C35: 上海KA | D35: 上海 | E35: 上海 | F35: 单导长促 | G35: 邵旱萍 | H35: 342501197807188629 | I35: 15902181583 | J35: NKA | K35: 直营 | L35: 欧发 | M35: 238976886 | N35: 欧尚中原店 | O35: 45778 | Q35: 2690 | R35: 0 | S35: 0 | T35: 22 | U35: 22 | V35: 0 | W35: 0 | X35: 0 | Y35: 2690 | Z35: 0 | AA35: 0 | AB35: 275.26 | AC35: 387.44444 | AD35: 1.4075581 | AE35: 2975.6667 | AF35: 0 | AG35: 580.375 | AH35: 2395.2917 | AI35: 0 | AJ35: 80 | AK35: 80 | AL35: 0 | AM35: 220 | AQ35: 0 | AW35: 5385.29 | AX35: 2740 | AY35: 上海合杰 | AZ35: 783.3 | BA35: 188 | BB35: 0 | BC35: =ROUND(AW35-AZ35-BA35+BB35-AA35-AK35-AT35-AM35,2) -> 4113.99 | BD35: =ROUND(IF(T35=U35,IF((BC35-BB35)<AX35,AX35-(BC35-BB35),0)),2) -> 0 | BE35: =ROUND(AW35-AZ35-BA35+BB35+BD35,2) -> 4413.99 | BF35: 1350.06 | BG35: 40.5 | BH35: 0 | BI35: 0 | BJ35: =ROUND(BF35+BE35-5000-(BH35-BI35),2) -> 764.05 | BK35: =ROUND(MAX(BJ35*{0.03,0.1,0.2,0.25,0.3,0.35,0.45}-{0,2520,16920,31920,52920,85920,181920}-BG35,0),2) -> 0 | BL35: =BG35+BK35 -> 40.5 | BM35: =ROUND(BE35-BK35,2) -> 4413.99 | BN35: 0 | BO35: =BE35+BN35 -> 4413.99 | BP35: =AZ35+BA35 -> 971.3 | BQ35: =AS35+AU35 -> 0 | BR35: =VLOOKUP(H35,社保公积金账单!D:D,1,0) -> 342501197807188629 | BS35: =T35-U35 -> 0
A36: 31 | B36: 江沪 | C36: 上海KA | D36: 上海 | E36: 上海 | F36: 单导长促 | G36: 王运乐 | H36: 342423196808132393 | I36: 13524491885 | J36: NKA | K36: 直营 | L36: 欧发 | M36: 238976888 | N36: 欧尚长阳店 | O36: 38412 | Q36: 2690 | R36: 21 | S36: 0 | T36: 15 | U36: 15 | V36: 0 | W36: 0 | X36: 0 | Y36: 2690 | Z36: 0 | AA36: 0 | AB36: 106.88 | AC36: 158.47222 | AD36: 1.4827117 | AE36: 1144.3333 | AF36: 0 | AG36: 197.5 | AH36: 946.83333 | AI36: 0 | AJ36: 80 | AK36: 80 | AL36: 0 | AM36: 140 | AQ36: 0 | AW36: 3856.83 | AX36: 2740 | AY36: 上海合杰 | AZ36: 783.3 | BA36: 188 | BB36: 0 | BC36: =ROUND(AW36-AZ36-BA36+BB36-AA36-AK36-AT36-AM36,2) -> 2665.53 | BD36: =ROUND(IF(T36=U36,IF((BC36-BB36)<AX36,AX36-(BC36-BB36),0)),2) -> 74.47 | BE36: =ROUND(AW36-AZ36-BA36+BB36+BD36,2) -> 2960 | BF36: -5179.17 | BG36: 0 | BH36: 0 | BI36: 0 | BJ36: =ROUND(BF36+BE36-5000-(BH36-BI36),2) -> -7219.17 | BK36: =ROUND(MAX(BJ36*{0.03,0.1,0.2,0.25,0.3,0.35,0.45}-{0,2520,16920,31920,52920,85920,181920}-BG36,0),2) -> 0 | BL36: =BG36+BK36 -> 0 | BM36: =ROUND(BE36-BK36,2) -> 2960 | BN36: 0 | BO36: =BE36+BN36 -> 2960 | BP36: =AZ36+BA36 -> 971.3 | BQ36: =AS36+AU36 -> 0 | BR36: =VLOOKUP(H36,社保公积金账单!D:D,1,0) -> 342423196808132393 | BS36: =T36-U36 -> 0
A37: 32 | B37: 江沪 | C37: 上海KA | D37: 上海 | E37: 上海 | F37: 单导长促 | G37: 吴思堂 | H37: 342423197603062138 | I37: 13564265158 | J37: NKA | K37: 直营 | L37: 麦德龙 | M37: 238976874 | N37: 麦德龙闵行店 | O37: 42418 | Q37: 2690 | R37: 10 | S37: 0 | T37: 16 | U37: 16 | V37: 0 | W37: 0 | X37: 0 | Y37: 2690 | Z37: 0 | AA37: 0 | AB37: 89.62 | AC37: 120 | AD37: 1.3389868 | AE37: 1128.02 | AF37: 0 | AG37: 9.4166667 | AH37: 1118.6033 | AI37: 0 | AJ37: 80 | AK37: 80 | AL37: 100 | AM37: 160 | AQ37: 0 | AW37: 4148.6 | AX37: 2740 | AY37: 上海合杰 | AZ37: 783.3 | BA37: 188 | BB37: 0 | BC37: =ROUND(AW37-AZ37-BA37+BB37-AA37-AK37-AT37-AM37,2) -> 2937.3 | BD37: =ROUND(IF(T37=U37,IF((BC37-BB37)<AX37,AX37-(BC37-BB37),0)),2) -> 0 | BE37: =ROUND(AW37-AZ37-BA37+BB37+BD37,2) -> 3177.3 | BF37: -4677.34 | BG37: 0 | BH37: 0 | BI37: 0 | BJ37: =ROUND(BF37+BE37-5000-(BH37-BI37),2) -> -6500.04 | BK37: =ROUND(MAX(BJ37*{0.03,0.1,0.2,0.25,0.3,0.35,0.45}-{0,2520,16920,31920,52920,85920,181920}-BG37,0),2) -> 0 | BL37: =BG37+BK37 -> 0 | BM37: =ROUND(BE37-BK37,2) -> 3177.3 | BN37: 0 | BO37: =BE37+BN37 -> 3177.3 | BP37: =AZ37+BA37 -> 971.3 | BQ37: =AS37+AU37 -> 0 | BR37: =VLOOKUP(H37,社保公积金账单!D:D,1,0) -> 342423197603062138 | BS37: =T37-U37 -> 0
A38: 33 | B38: 江沪 | C38: 上海KA | D38: 上海 | E38: 上海 | F38: 单导长促 | G38: 王静 | H38: 340122198603201708 | I38: 18756591219 | J38: NKA | K38: 直营 | L38: 麦德龙 | M38: 238976876 | N38: 麦德龙浦东店 | O38: 45941 | Q38: 2740 | R38: 0 | S38: 0 | T38: 15 | U38: 10 | V38: 0 | W38: 0 | X38: 0 | Y38: 1826.6667 | Z38: 0 | AA38: 0 | AB38: 108.26 | AC38: 149.14 | AD38: 1.3776095 | AE38: 1379.62 | AF38: 0 | AG38: 8.625 | AH38: 1370.99 | AI38: 0 | AJ38: 53.333333 | AK38: 53.333333 | AL38: 0 | AM38: 100 | AQ38: 0 | AW38: 3350.99 | AX38: 2740 | AY38: 上海合杰 | AZ38: 783.3 | BA38: 192 | BB38: 0 | BC38: =ROUND(AW38-AZ38-BA38+BB38-AA38-AK38-AT38-AM38,2) -> 2222.36 | BD38: =ROUND(IF(T38=U38,IF((BC38-BB38)<AX38,AX38-(BC38-BB38),0)),2) -> 0 | BE38: =ROUND(AW38-AZ38-BA38+BB38+BD38,2) -> 2375.69 | BF38: -2888.7 | BG38: 0 | BH38: 0 | BI38: 0 | BJ38: =ROUND(BF38+BE38-5000-(BH38-BI38),2) -> -5513.01 | BK38: =ROUND(MAX(BJ38*{0.03,0.1,0.2,0.25,0.3,0.35,0.45}-{0,2520,16920,31920,52920,85920,181920}-BG38,0),2) -> 0 | BL38: =BG38+BK38 -> 0 | BM38: =ROUND(BE38-BK38,2) -> 2375.69 | BN38: 0 | BO38: =BE38+BN38 -> 2375.69 | BP38: =AZ38+BA38 -> 975.3 | BQ38: =AS38+AU38 -> 0 | BR38: =VLOOKUP(H38,社保公积金账单!D:D,1,0) -> 340122198603201708 | BS38: =T38-U38 -> 5
A39: 34 | B39: 江沪 | C39: 上海KA | D39: 上海 | E39: 上海 | F39: 单导长促 | G39: 杜雷军 | H39: 320923197303084257 | I39: 15300428327 | J39: NKA | K39: 直营 | L39: 麦德龙 | M39: 238976872 | N39: 麦德龙真北店 | O39: 45113 | Q39: 2690 | R39: 2 | S39: 0 | T39: 15 | U39: 15 | V39: 0 | W39: 0 | X39: 0 | Y39: 2690 | Z39: 0 | AA39: 0 | AB39: 134.74 | AC39: 200.95 | AD39: 1.4913908 | AE39: 1655.14 | AF39: 118.125 | AG39: 13.666667 | AH39: 1523.3483 | AI39: 0 | AJ39: 80 | AK39: 80 | AL39: 100 | AM39: 150 | AQ39: 0 | AW39: 4543.35 | AX39: 2740 | AY39: 上海合杰 | AZ39: 783.3 | BA39: 188 | BB39: 0 | BC39: =ROUND(AW39-AZ39-BA39+BB39-AA39-AK39-AT39-AM39,2) -> 3342.05 | BD39: =ROUND(IF(T39=U39,IF((BC39-BB39)<AX39,AX39-(BC39-BB39),0)),2) -> 0 | BE39: =ROUND(AW39-AZ39-BA39+BB39+BD39,2) -> 3572.05 | BF39: -117.63 | BG39: 19.01 | BH39: 0 | BI39: 0 | BJ39: =ROUND(BF39+BE39-5000-(BH39-BI39),2) -> -1545.58 | BK39: =ROUND(MAX(BJ39*{0.03,0.1,0.2,0.25,0.3,0.35,0.45}-{0,2520,16920,31920,52920,85920,181920}-BG39,0),2) -> 0 | BL39: =BG39+BK39 -> 19.01 | BM39: =ROUND(BE39-BK39,2) -> 3572.05 | BN39: 0 | BO39: =BE39+BN39 -> 3572.05 | BP39: =AZ39+BA39 -> 971.3 | BQ39: =AS39+AU39 -> 0 | BR39: =VLOOKUP(H39,社保公积金账单!D:D,1,0) -> 320923197303084257 | BS39: =T39-U39 -> 0
A40: 合计 | Q40: =SUM(Q6:Q39) -> 91610 | R40: =SUM(R6:R39) -> 202 | S40: =SUM(S6:S39) -> 0 | T40: =SUM(T6:T39) -> 598 | U40: =SUM(U6:U39) -> 583 | V40: =SUM(V6:V39) -> 3 | W40: =SUM(W6:W39) -> 2 | X40: =SUM(X6:X39) -> 261.54545 | ... BP40: =SUM(BP6:BP39) -> 33036.2

Sheet Sheet9
A1: 姓名 | B1: 身份证号码 | C1: 门店 | D1: 雇主责任险 | E1: 本月应缴金额 | I1: 补缴金额 | M1: 实缴金额
E2: 社保 | G2: 公积金 | I2: 社保 | K2: 公积金 | M2: 个人 | N2: 公司 | O2: 小计
E3: 个人 | F3: 公司 | G3: 个人 | H3: 公司 | I3: 个人 | J3: 公司 | K3: 个人 | L3: 公司 | M3: 个人 | N3: 公司 | O3: 小计
A4: 车文秀 | B4: 341623199710154424 | C4: 大润发松江店 | D4: 21 | E4: 684.6 | F4: 1744.5 | G4: 181 | H4: 181 | I4: 0 | J4: 0 | K4: 0 | L4: 0 | M4: 865.6 | N4: 1925.5 | O4: 2791.1
A5: 陈福娟 | B5: 342423197403292668 | C5: 大润发春申店 | D5: 21 | E5: 684.6 | F5: 1744.5 | G5: 181 | H5: 181 | I5: 0 | J5: 0 | K5: 0 | L5: 0 | M5: 865.6 | N5: 1925.5 | O5: 2791.1
A6: 陈敏 | B6: 310226197301243524 | C6: 大润发奉贤店 | D6: 21 | E6: 684.6 | F6: 1744.5 | G6: 181 | H6: 181 | I6: 0 | J6: 0 | K6: 0 | L6: 0 | M6: 865.6 | N6: 1925.5 | O6: 2791.1
A7: 东港 | B7: 210422198201031424 | C7: 欧尚嘉定店 | D7: 21 | E7: 684.6 | F7: 1744.5 | G7: 181 | H7: 181 | I7: 0 | J7: 0 | K7: 0 | L7: 0 | M7: 865.6 | N7: 1925.5 | O7: 2791.1
A8: 范祖容 | B8: 51253319820521484X | C8: 家乐福金桥店 | D8: 21 | E8: 684.6 | F8: 1744.5 | G8: 181 | H8: 181 | I8: 0 | J8: 0 | K8: 0 | L8: 0 | M8: 865.6 | N8: 1925.5 | O8: 2791.1
A9: 戈艳青 | B9: 32082319780513524X | C9: 家乐福中山店 | D9: 21 | E9: 684.6 | F9: 1744.5 | G9: 181 | H9: 181 | I9: 0 | J9: 0 | K9: 0 | L9: 0 | M9: 865.6 | N9: 1925.5 | O9: 2791.1
A10: 葛菊 | B10: 340421198104213042 | C10: 欧尚中原店 | D10: 21 | E10: 684.6 | F10: 1744.5 | G10: 181 | H10: 181 | I10: 0 | J10: 0 | K10: 0 | L10: 0 | M10: 865.6 | N10: 1925.5 | O10: 2791.1
A11: 顾建凤 | B11: 310226197704023526 | C11: 大润发奉贤店 | D11: 21 | E11: 684.6 | F11: 1744.5 | G11: 181 | H11: 181 | I11: 0 | J11: 0 | K11: 0 | L11: 0 | M11: 865.6 | N11: 1925.5 | O11: 2791.1
A12: 管兵娥 | B12: 362329198211245745 | C12: 大润发安亭店 | D12: 21 | E12: 684.6 | F12: 1744.5 | G12: 181 | H12: 181 | I12: 0 | J12: 0 | K12: 0 | L12: 0 | M12: 865.6 | N12: 1925.5 | O12: 2791.1
A13: 郭胜霞 | B13: 320925197905205821 | C13: 家乐福古北店 | D13: 21 | E13: 684.6 | F13: 1744.5 | G13: 181 | H13: 181 | I13: 0 | J13: 0 | K13: 0 | L13: 0 | M13: 865.6 | N13: 1925.5 | O13: 2791.1
A14: 过苗苗 | B14: 341224198812281328 | C14: 大润发平型关店 | D14: 21 | E14: 684.6 | F14: 1744.5 | G14: 181 | H14: 181 | I14: 0 | J14: 0 | K14: 0 | L14: 0 | M14: 865.6 | N14: 1925.5 | O14: 2791.1
A15: 洪艳 | B15: 342422197308163968 | C15: 沃尔玛南浦大桥店 | D15: 21 | E15: 684.6 | F15: 1744.5 | G15: 181 | H15: 181 | I15: 0 | J15: 0 | K15: 0 | L15: 0 | M15: 865.6 | N15: 1925.5 | O15: 2791.1
... A75: 姚友美 | B75: 34122619830430352X | C75: 大润发中原店 | D75: 21 | E75: 684.6 | F75: 1744.5 | G75: 181 | H75: 181 | I75: 0 | J75: 0 | K75: 0 | L75: 0 | M75: 865.6 | N75: 1925.5 | O75: 2791.1
A76: 耿良莉 | B76: 34242319840516738X | D76: 21 | E76: 415.49 | F76: 967.5 | G76: 182 | H76: 182 | I76: 0 | J76: 0 | K76: 0 | L76: 0 | M76: 597.49 | N76: 1149.5 | O76: 1746.99
A77: 霍雪 | B77: 41152819860103524X | D77: 21 | E77: 341.35 | F77: 977.05 | G77: 317 | H77: 317 | I77: 0 | J77: 0 | K77: 0 | L77: 0 | M77: 658.35 | N77: 1294.05 | O77: 1952.4
A78: 涂秀华 | B78: 511123197304307822 | D78: 21 | E78: 415.49 | F78: 967.5 | G78: 182 | H78: 182 | I78: 0 | J78: 0 | K78: 0 | L78: 0 | M78: 597.49 | N78: 1149.5 | O78: 1746.99
A79: 尹雪峰 | B79: 342224198109020741 | D79: 21 | E79: 415.49 | F79: 967.5 | G79: 182 | H79: 182 | I79: 0 | J79: 0 | K79: 0 | L79: 0 | M79: 597.49 | N79: 1149.5 | O79: 1746.99
A80: 丁小红 | B80: 321025197404040821 | D80: 21 | E80: 446.25 | F80: 1096.5 | G80: 0 | H80: 0 | I80: 0 | J80: 0 | K80: 0 | L80: 0 | M80: 446.25 | N80: 1096.5 | O80: 1542.75
A81: 顾宏 | B81: 320924197303033448 | D81: 21 | E81: 451.25 | F81: 1051.88 | G81: 340 | H81: 340 | I81: 0 | J81: 0 | K81: 36 | L81: 36 | M81: 827.25 | N81: 1427.88 | O81: 2255.13
A82: 孙开艳 | B82: 32092419760320718X | D82: 21 | E82: 446.25 | F82: 1096.5 | G82: 183 | H82: 183 | I82: 0 | J82: 0 | K82: 21 | L82: 21 | M82: 650.25 | N82: 1300.5 | O82: 1950.75
A83: 孙莉莉 | B83: 320922198304053645 | D83: 21 | E83: 446.25 | F83: 1096.5 | G83: 183 | H83: 183 | I83: 0 | J83: 0 | K83: 21 | L83: 21 | M83: 650.25 | N83: 1300.5 | O83: 1950.75
A84: 陶宝芹 | B84: 321023197201015869 | D84: 21 | E84: 446.25 | F84: 1096.5 | G84: 0 | H84: 0 | I84: 0 | J84: 0 | K84: 0 | L84: 0 | M84: 446.25 | N84: 1096.5 | O84: 1542.75
A85: 吴海珍 | B85: 321123197802191644 | D85: 21 | E85: 456.25 | F85: 1092.25 | G85: 0 | H85: 0 | I85: 0 | J85: 0 | K85: 0 | L85: 0 | M85: 456.25 | N85: 1092.25 | O85: 1548.5
A86: 吴永红 | B86: 42032319710815250X | D86: 21 | E86: 446.25 | F86: 1096.5 | G86: 183 | H86: 183 | I86: 0 | J86: 0 | K86: 21 | L86: 21 | M86: 650.25 | N86: 1300.5 | O86: 1950.75
A87: 谢如香 | B87: 321322198705145223 | D87: 21 | E87: 451.25 | F87: 1051.88 | G87: 340 | H87: 340 | I87: 0 | J87: 0 | K87: 36 | L87: 36 | M87: 827.25 | N87: 1427.88 | O87: 2255.13
A88: 徐婷 | B88: 320828197509113064 | D88: 21 | E88: 446.25 | F88: 1096.5 | G88: 183 | H88: 183 | I88: 0 | J88: 0 | K88: 0 | L88: 0 | M88: 629.25 | N88: 1279.5 | O88: 1908.75
D89: =SUM(D4:D88) -> 1785 | E89: =SUM(E4:E88) -> 54915.27 | F89: =SUM(F4:F88) -> 139258.56 | G89: =SUM(G4:G88) -> 15307 | H89: =SUM(H4:H88) -> 15307 | I89: =SUM(I4:I88) -> 0 | J89: =SUM(J4:J88) -> 0 | K89: =SUM(K4:K88) -> 135 | ... O89: =SUM(O4:O88) -> 225057.83
D92: 公司社保 | E92: =F89+J89 -> 139258.56
D93: 公司公积金 | E93: =H89+L89 -> 15442
D94: 个人社保 | E94: =E89+I89 -> 54915.27
D95: 个人公积金 | E95: =G89+K89 -> 15442

Sheet 社保公积金账单
H2: 养老 | O2: 医疗 | X2: 失业 | AE2: 住房 | AL2: 其他类社保 | BA2: 医疗生育 | BH2: 工伤 | BO2: 补充公积金 | BV2: 本月应缴金额 | BZ2: 补缴金额 | CD2: 实缴金额 | CH2: 社保个人 | CI2: 社保公司 | CJ2: 公积金个人 | CK2: 公积金公司
A3: 序号 | B3: 组织名称 | C3: 姓名 | D3: 身份证号码 | E3: 渠道 | F3: 门店名称 | G3: 雇主责任险 | H3: 基数 | I3: 公司 | L3: 个人 | O3: 基数 | P3: 公司 | T3: 个人 | X3: 基数 | Y3: 公司 | AB3: 个人 | AE3: 基数 | AF3: 公司 | AI3: 个人 | AL3: 大病公司 | AN3: 大病个人 | AP3: 采暖费 | AR3: 保障金 | AT3: 社保工会费 | AV3: 公司其他 | AX3: 个人其他 | AZ3: 备注 | BA3: 基数 | BB3: 公司 | BE3: 个人 | BH3: 基数 | BI3: 公司 | BL3: 个人 | BO3: 基数 | BP3: 公司 | BS3: 个人 | BV3: 社保 | BX3: 社保 | BZ3: 社保 | CB3: 公积金 | CD3: 个人 | CE3: 公司 | CF3: 小计
H4: 基数 | I4: 比例(%) | J4: 应缴 | K4: 补缴 | L4: 比例(%) | M4: 应缴 | N4: 补缴 | O4: 基数 | P4: 比例(%) | Q4: 固定 | R4: 应缴 | S4: 补缴 | T4: 比例(%) | U4: 固定 | V4: 应缴 | W4: 补缴 | X4: 基数 | Y4: 比例(%) | Z4: 应缴 | AA4: 补缴 | AB4: 比例(%) | AC4: 应缴 | AD4: 补缴 | AE4: 基数 | AF4: 比例(%) | AG4: 应缴 | AH4: 补缴 | AI4: 比例(%) | AJ4: 应缴 | AK4: 补缴 | AL4: 应缴 | AM4: 补缴 | AN4: 应缴 | AO4: 补缴 | AP4: 应缴 | AQ4: 补缴 | AR4: 应缴 | AS4: 补缴 | AT4: 应缴 | AU4: 补缴 | AV4: 应缴 | AW4: 补缴 | AX4: 应缴 | AY4: 补缴 | AZ4: 备注 | BA4: 基数 | BB4: 比例(%) | BC4: 应缴 | BD4: 补缴 | BE4: 比例(%) | BF4: 应缴 | BG4: 补缴 | BH4: 基数 | BI4: 比例(%) | BJ4: 应缴 | BK4: 补缴 | BL4: 比例(%) | BM4: 应缴 | BN4: 补缴 | BO4: 基数 | BP4: 比例(%) | BQ4: 应缴 | BR4: 补缴 | BS4: 比例(%) | BT4: 应缴 | BU4: 补缴 | BV4: 个人 | BW4: 公司 | BX4: 个人 | BY4: 公司 | BZ4: 个人 | CA4: 公司 | CB4: 个人 | CC4: 公司
A5: 1 | B5: 中粮上海导购 | C5: 车文秀 | D5: 341623199710154424 | E5: =VLOOKUP(D5,长促工资明细!H:P,3,0) -> NKA | F5: =VLOOKUP(D5,长促工资明细!H:P,7,0) -> 大润发松江店 | G5: 19.67 | H5: 7460 | I5: 16 | J5: 1193.6 | K5: 0 | L5: 8 | M5: 596.8 | N5: 0 | O5: 7460 | P5: 9 | R5: 671.4 | S5: 0 | T5: 2 | V5: 149.2 | W5: 0 | X5: 7460 | Y5: 0.5 | Z5: 37.3 | AA5: 0 | AB5: 0.5 | AC5: 37.3 | AD5: 0 | AE5: 2690 | AF5: 7 | AG5: 188 | AH5: 0 | AI5: 7 | AJ5: 188 | AK5: 0 | AL5: 0 | AM5: 0 | AN5: 0 | AO5: 0 | AP5: 0 | AQ5: 0 | AS5: 0 | AT5: 0 | AU5: 0 | AV5: 0 | AW5: 0 | AX5: 0 | AY5: 0 | BC5: 0 | BD5: 0 | BF5: 0 | BG5: 0 | BH5: 7460 | BI5: 0.32 | BJ5: 23.87 | BK5: 0 | BM5: 0 | BN5: 0 | BQ5: 0 | BR5: 0 | BT5: 0 | BU5: 0 | BV5: =M5+V5+AC5+AN5+AX5+BF5+BM5 -> 783.3 | BW5: =BJ5+BC5+AV5+AT5+AR5+AP5+AL5+Z5+R5+J5 -> 1926.17 | BX5: =AJ5 -> 188 | BY5: =AG5 -> 188 | BZ5: =N5+W5+AD5+AO5+AY5+BG5+BN5 -> 0 | CA5: =K5+S5+AA5+AM5+AQ5+AS5+AU5+AW5+BD5+BK5+BR5 -> 0 | CB5: =BU5+AK5 -> 0 | CC5: =BR5+AH5 -> 0 | CD5: =BV5+BX5+BZ5+CB5 -> 971.3 | CE5: =BW5+BY5+CA5+CC5 -> 2114.17 | CF5: =CD5+CE5 -> 3085.47 | CG5: 上海市； | CH5: =BV5+BZ5 -> 783.3 | CI5: =BW5+CA5 -> 1926.17 | CJ5: =BX5+CB5 -> 188 | CK5: =BY5+CC5 -> 188 | CL5: =CH5+CI5 -> 2709.47 | CM5: =CJ5+CK5 -> 376 | CN5: 本部 | CO5: =N5+M5 -> 596.8 | CP5: =V5+W5+AN5+AO5 -> 149.2 | CQ5: =AD5+AC5 -> 37.3 | CR5: =CQ5+CP5+CO5=CH5 -> TRUE | CS5: =VLOOKUP(C5,长促工资明细!G:G,1,0) -> 车文秀
A6: 2 | B6: 中粮上海导购 | C6: 东港 | D6: 210422198201031424 | E6: =VLOOKUP(D6,长促工资明细!H:P,3,0) -> NKA | F6: =VLOOKUP(D6,长促工资明细!H:P,7,0) -> 欧尚嘉定店 | G6: 19.67 | H6: 7460 | I6: 16 | J6: 1193.6 | K6: 0 | L6: 8 | M6: 596.8 | N6: 0 | O6: 7460 | P6: 9 | R6: 671.4 | S6: 0 | T6: 2 | V6: 149.2 | W6: 0 | X6: 7460 | Y6: 0.5 | Z6: 37.3 | AA6: 0 | AB6: 0.5 | AC6: 37.3 | AD6: 0 | AE6: 2690 | AF6: 7 | AG6: 188 | AH6: 0 | AI6: 7 | AJ6: 188 | AK6: 0 | AL6: 0 | AM6: 0 | AN6: 0 | AO6: 0 | AP6: 0 | AQ6: 0 | AS6: 0 | AT6: 0 | AU6: 0 | AV6: 0 | AW6: 0 | AX6: 0 | AY6: 0 | BC6: 0 | BD6: 0 | BF6: 0 | BG6: 0 | BH6: 7460 | BI6: 0.32 | BJ6: 23.87 | BK6: 0 | BM6: 0 | BN6: 0 | BQ6: 0 | BR6: 0 | BT6: 0 | BU6: 0 | BV6: =M6+V6+AC6+AN6+AX6+BF6+BM6 -> 783.3 | BW6: =BJ6+BC6+AV6+AT6+AR6+AP6+AL6+Z6+R6+J6 -> 1926.17 | BX6: =AJ6 -> 188 | BY6: =AG6 -> 188 | BZ6: =N6+W6+AD6+AO6+AY6+BG6+BN6 -> 0 | CA6: =K6+S6+AA6+AM6+AQ6+AS6+AU6+AW6+BD6+BK6+BR6 -> 0 | CB6: =BU6+AK6 -> 0 | CC6: =BR6+AH6 -> 0 | CD6: =BV6+BX6+BZ6+CB6 -> 971.3 | CE6: =BW6+BY6+CA6+CC6 -> 2114.17 | CF6: =CD6+CE6 -> 3085.47 | CG6: 上海市； | CH6: =BV6+BZ6 -> 783.3 | CI6: =BW6+CA6 -> 1926.17 | CJ6: =BX6+CB6 -> 188 | CK6: =BY6+CC6 -> 188 | CL6: =CH6+CI6 -> 2709.47 | CM6: =CJ6+CK6 -> 376 | CN6: 本部 | CO6: =N6+M6 -> 596.8 | CP6: =V6+W6+AN6+AO6 -> 149.2 | CQ6: =AD6+AC6 -> 37.3 | CR6: =CQ6+CP6+CO6=CH6 -> TRUE | CS6: =VLOOKUP(C6,长促工资明细!G:G,1,0) -> 东港
A7: 3 | B7: 中粮上海导购 | C7: 董燕芳 | D7: 31022519780512504X | E7: =VLOOKUP(D7,长促工资明细!H:P,3,0) -> NKA | F7: =VLOOKUP(D7,长促工资明细!H:P,7,0) -> 大润发泥城店 | G7: 19.67 | H7: 7460 | I7: 16 | J7: 1193.6 | K7: 0 | L7: 8 | M7: 596.8 | N7: 0 | O7: 7460 | P7: 9 | R7: 671.4 | S7: 0 | T7: 2 | V7: 149.2 | W7: 0 | X7: 7460 | Y7: 0.5 | Z7: 37.3 | AA7: 0 | AB7: 0.5 | AC7: 37.3 | AD7: 0 | AE7: 2690 | AF7: 7 | AG7: 188 | AH7: 0 | AI7: 7 | AJ7: 188 | AK7: 0 | AL7: 0 | AM7: 0 | AN7: 0 | AO7: 0 | AP7: 0 | AQ7: 0 | AS7: 0 | AT7: 0 | AU7: 0 | AV7: 0 | AW7: 0 | AX7: 0 | AY7: 0 | BC7: 0 | BD7: 0 | BF7: 0 | BG7: 0 | BH7: 7460 | BI7: 0.32 | BJ7: 23.87 | BK7: 0 | BM7: 0 | BN7: 0 | BQ7: 0 | BR7: 0 | BT7: 0 | BU7: 0 | BV7: =M7+V7+AC7+AN7+AX7+BF7+BM7 -> 783.3 | BW7: =BJ7+BC7+AV7+AT7+AR7+AP7+AL7+Z7+R7+J7 -> 1926.17 | BX7: =AJ7 -> 188 | BY7: =AG7 -> 188 | BZ7: =N7+W7+AD7+AO7+AY7+BG7+BN7 -> 0 | CA7: =K7+S7+AA7+AM7+AQ7+AS7+AU7+AW7+BD7+BK7+BR7 -> 0 | CB7: =BU7+AK7 -> 0 | CC7: =BR7+AH7 -> 0 | CD7: =BV7+BX7+BZ7+CB7 -> 971.3 | CE7: =BW7+BY7+CA7+CC7 -> 2114.17 | CF7: =CD7+CE7 -> 3085.47 | CG7: 上海市； | CH7: =BV7+BZ7 -> 783.3 | CI7: =BW7+CA7 -> 1926.17 | CJ7: =BX7+CB7 -> 188 | CK7: =BY7+CC7 -> 188 | CL7: =CH7+CI7 -> 2709.47 | CM7: =CJ7+CK7 -> 376 | CN7: 本部 | CO7: =N7+M7 -> 596.8 | CP7: =V7+W7+AN7+AO7 -> 149.2 | CQ7: =AD7+AC7 -> 37.3 | CR7: =CQ7+CP7+CO7=CH7 -> TRUE | CS7: =VLOOKUP(C7,长促工资明细!G:G,1,0) -> 董燕芳
A8: 4 | B8: 中粮上海导购 | C8: 杜雷军 | D8: 320923197303084257 | E8: =VLOOKUP(D8,长促工资明细!H:P,3,0) -> NKA | F8: =VLOOKUP(D8,长促工资明细!H:P,7,0) -> 麦德龙真北店 | G8: 19.67 | H8: 7460 | I8: 16 | J8: 1193.6 | K8: 0 | L8: 8 | M8: 596.8 | N8: 0 | O8: 7460 | P8: 9 | R8: 671.4 | S8: 0 | T8: 2 | V8: 149.2 | W8: 0 | X8: 7460 | Y8: 0.5 | Z8: 37.3 | AA8: 0 | AB8: 0.5 | AC8: 37.3 | AD8: 0 | AE8: 2690 | AF8: 7 | AG8: 188 | AH8: 0 | AI8: 7 | AJ8: 188 | AK8: 0 | AL8: 0 | AM8: 0 | AN8: 0 | AO8: 0 | AP8: 0 | AQ8: 0 | AS8: 0 | AT8: 0 | AU8: 0 | AV8: 0 | AW8: 0 | AX8: 0 | AY8: 0 | BC8: 0 | BD8: 0 | BF8: 0 | BG8: 0 | BH8: 7460 | BI8: 0.32 | BJ8: 23.87 | BK8: 0 | BM8: 0 | BN8: 0 | BQ8: 0 | BR8: 0 | BT8: 0 | BU8: 0 | BV8: =M8+V8+AC8+AN8+AX8+BF8+BM8 -> 783.3 | BW8: =BJ8+BC8+AV8+AT8+AR8+AP8+AL8+Z8+R8+J8 -> 1926.17 | BX8: =AJ8 -> 188 | BY8: =AG8 -> 188 | BZ8: =N8+W8+AD8+AO8+AY8+BG8+BN8 -> 0 | CA8: =K8+S8+AA8+AM8+AQ8+AS8+AU8+AW8+BD8+BK8+BR8 -> 0 | CB8: =BU8+AK8 -> 0 | CC8: =BR8+AH8 -> 0 | CD8: =BV8+BX8+BZ8+CB8 -> 971.3 | CE8: =BW8+BY8+CA8+CC8 -> 2114.17 | CF8: =CD8+CE8 -> 3085.47 | CG8: 上海市； | CH8: =BV8+BZ8 -> 783.3 | CI8: =BW8+CA8 -> 1926.17 | CJ8: =BX8+CB8 -> 188 | CK8: =BY8+CC8 -> 188 | CL8: =CH8+CI8 -> 2709.47 | CM8: =CJ8+CK8 -> 376 | CN8: 本部 | CO8: =N8+M8 -> 596.8 | CP8: =V8+W8+AN8+AO8 -> 149.2 | CQ8: =AD8+AC8 -> 37.3 | CR8: =CQ8+CP8+CO8=CH8 -> TRUE | CS8: =VLOOKUP(C8,长促工资明细!G:G,1,0) -> 杜雷军
A9: 5 | B9: 中粮上海导购 | C9: 杜以花 | D9: 371122198002227829 | E9: =VLOOKUP(D9,长促工资明细!H:P,3,0) -> NKA | F9: =VLOOKUP(D9,长促工资明细!H:P,7,0) -> 大润发泗泾店 | G9: 19.67 | H9: 7460 | I9: 16 | J9: 1193.6 | K9: 0 | L9: 8 | M9: 596.8 | N9: 0 | O9: 7460 | P9: 9 | R9: 671.4 | S9: 0 | T9: 2 | V9: 149.2 | W9: 0 | X9: 7460 | Y9: 0.5 | Z9: 37.3 | AA9: 0 | AB9: 0.5 | AC9: 37.3 | AD9: 0 | AE9: 2690 | AF9: 7 | AG9: 188 | AH9: 0 | AI9: 7 | AJ9: 188 | AK9: 0 | AL9: 0 | AM9: 0 | AN9: 0 | AO9: 0 | AP9: 0 | AQ9: 0 | AS9: 0 | AT9: 0 | AU9: 0 | AV9: 0 | AW9: 0 | AX9: 0 | AY9: 0 | BC9: 0 | BD9: 0 | BF9: 0 | BG9: 0 | BH9: 7460 | BI9: 0.32 | BJ9: 23.87 | BK9: 0 | BM9: 0 | BN9: 0 | BQ9: 0 | BR9: 0 | BT9: 0 | BU9: 0 | BV9: =M9+V9+AC9+AN9+AX9+BF9+BM9 -> 783.3 | BW9: =BJ9+BC9+AV9+AT9+AR9+AP9+AL9+Z9+R9+J9 -> 1926.17 | BX9: =AJ9 -> 188 | BY9: =AG9 -> 188 | BZ9: =N9+W9+AD9+AO9+AY9+BG9+BN9 -> 0 | CA9: =K9+S9+AA9+AM9+AQ9+AS9+AU9+AW9+BD9+BK9+BR9 -> 0 | CB9: =BU9+AK9 -> 0 | CC9: =BR9+AH9 -> 0 | CD9: =BV9+BX9+BZ9+CB9 -> 971.3 | CE9: =BW9+BY9+CA9+CC9 -> 2114.17 | CF9: =CD9+CE9 -> 3085.47 | CG9: 上海市； | CH9: =BV9+BZ9 -> 783.3 | CI9: =BW9+CA9 -> 1926.17 | CJ9: =BX9+CB9 -> 188 | CK9: =BY9+CC9 -> 188 | CL9: =CH9+CI9 -> 2709.47 | CM9: =CJ9+CK9 -> 376 | CN9: 本部 | CO9: =N9+M9 -> 596.8 | CP9: =V9+W9+AN9+AO9 -> 149.2 | CQ9: =AD9+AC9 -> 37.3 | CR9: =CQ9+CP9+CO9=CH9 -> TRUE | CS9: =VLOOKUP(C9,长促工资明细!G:G,1,0) -> 杜以花
A10: 6 | B10: 中粮上海导购 | C10: 戈艳青 | D10: 32082319780513524X | E10: =VLOOKUP(D10,长促工资明细!H:P,3,0) -> NKA | F10: =VLOOKUP(D10,长促工资明细!H:P,7,0) -> 大润发泗泾店 | G10: 19.67 | H10: 7460 | I10: 16 | J10: 1193.6 | K10: 0 | L10: 8 | M10: 596.8 | N10: 0 | O10: 7460 | P10: 9 | R10: 671.4 | S10: 0 | T10: 2 | V10: 149.2 | W10: 0 | X10: 7460 | Y10: 0.5 | Z10: 37.3 | AA10: 0 | AB10: 0.5 | AC10: 37.3 | AD10: 0 | AE10: 2690 | AF10: 7 | AG10: 188 | AH10: 0 | AI10: 7 | AJ10: 188 | AK10: 0 | AL10: 0 | AM10: 0 | AN10: 0 | AO10: 0 | AP10: 0 | AQ10: 0 | AS10: 0 | AT10: 0 | AU10: 0 | AV10: 0 | AW10: 0 | AX10: 0 | AY10: 0 | BC10: 0 | BD10: 0 | BF10: 0 | BG10: 0 | BH10: 7460 | BI10: 0.32 | BJ10: 23.87 | BK10: 0 | BM10: 0 | BN10: 0 | BQ10: 0 | BR10: 0 | BT10: 0 | BU10: 0 | BV10: =M10+V10+AC10+AN10+AX10+BF10+BM10 -> 783.3 | BW10: =BJ10+BC10+AV10+AT10+AR10+AP10+AL10+Z10+R10+J10 -> 1926.17 | BX10: =AJ10 -> 188 | BY10: =AG10 -> 188 | BZ10: =N10+W10+AD10+AO10+AY10+BG10+BN10 -> 0 | CA10: =K10+S10+AA10+AM10+AQ10+AS10+AU10+AW10+BD10+BK10+BR10 -> 0 | CB10: =BU10+AK10 -> 0 | CC10: =BR10+AH10 -> 0 | CD10: =BV10+BX10+BZ10+CB10 -> 971.3 | CE10: =BW10+BY10+CA10+CC10 -> 2114.17 | CF10: =CD10+CE10 -> 3085.47 | CG10: 上海市； | CH10: =BV10+BZ10 -> 783.3 | CI10: =BW10+CA10 -> 1926.17 | CJ10: =BX10+CB10 -> 188 | CK10: =BY10+CC10 -> 188 | CL10: =CH10+CI10 -> 2709.47 | CM10: =CJ10+CK10 -> 376 | CN10: 本部 | CO10: =N10+M10 -> 596.8 | CP10: =V10+W10+AN10+AO10 -> 149.2 | CQ10: =AD10+AC10 -> 37.3 | CR10: =CQ10+CP10+CO10=CH10 -> TRUE | CS10: =VLOOKUP(C10,长促工资明细!G:G,1,0) -> 戈艳青
A11: 7 | B11: 中粮上海导购 | C11: 管兵娥 | D11: 362329198211245745 | E11: =VLOOKUP(D11,长促工资明细!H:P,3,0) -> NKA | F11: =VLOOKUP(D11,长促工资明细!H:P,7,0) -> 大润发安亭店 | G11: 19.67 | H11: 7460 | I11: 16 | J11: 1193.6 | K11: 0 | L11: 8 | M11: 596.8 | N11: 0 | O11: 7460 | P11: 9 | R11: 671.4 | S11: 0 | T11: 2 | V11: 149.2 | W11: 0 | X11: 7460 | Y11: 0.5 | Z11: 37.3 | AA11: 0 | AB11: 0.5 | AC11: 37.3 | AD11: 0 | AE11: 2690 | AF11: 7 | AG11: 188 | AH11: 0 | AI11: 7 | AJ11: 188 | AK11: 0 | AL11: 0 | AM11: 0 | AN11: 0 | AO11: 0 | AP11: 0 | AQ11: 0 | AS11: 0 | AT11: 0 | AU11: 0 | AV11: 0 | AW11: 0 | AX11: 0 | AY11: 0 | BC11: 0 | BD11: 0 | BF11: 0 | BG11: 0 | BH11: 7460 | BI11: 0.32 | BJ11: 23.87 | BK11: 0 | BM11: 0 | BN11: 0 | BQ11: 0 | BR11: 0 | BT11: 0 | BU11: 0 | BV11: =M11+V11+AC11+AN11+AX11+BF11+BM11 -> 783.3 | BW11: =BJ11+BC11+AV11+AT11+AR11+AP11+AL11+Z11+R11+J11 -> 1926.17 | BX11: =AJ11 -> 188 | BY11: =AG11 -> 188 | BZ11: =N11+W11+AD11+AO11+AY11+BG11+BN11 -> 0 | CA11: =K11+S11+AA11+AM11+AQ11+AS11+AU11+AW11+BD11+BK11+BR11 -> 0 | CB11: =BU11+AK11 -> 0 | CC11: =BR11+AH11 -> 0 | CD11: =BV11+BX11+BZ11+CB11 -> 971.3 | CE11: =BW11+BY11+CA11+CC11 -> 2114.17 | CF11: =CD11+CE11 -> 3085.47 | CG11: 上海市； | CH11: =BV11+BZ11 -> 783.3 | CI11: =BW11+CA11 -> 1926.17 | CJ11: =BX11+CB11 -> 188 | CK11: =BY11+CC11 -> 188 | CL11: =CH11+CI11 -> 2709.47 | CM11: =CJ11+CK11 -> 376 | CN11: 本部 | CO11: =N11+M11 -> 596.8 | CP11: =V11+W11+AN11+AO11 -> 149.2 | CQ11: =AD11+AC11 -> 37.3 | CR11: =CQ11+CP11+CO11=CH11 -> TRUE | CS11: =VLOOKUP(C11,长促工资明细!G:G,1,0) -> 管兵娥
A12: 8 | B12: 中粮上海导购 | C12: 郭胜霞 | D12: 320925197905205821 | E12: =VLOOKUP(D12,长促工资明细!H:P,3,0) -> NKA | F12: =VLOOKUP(D12,长促工资明细!H:P,7,0) -> 大润发华漕店 | G12: 19.67 | H12: 7460 | I12: 16 | J12: 1193.6 | K12: 0 | L12: 8 | M12: 596.8 | N12: 0 | O12: 7460 | P12: 9 | R12: 671.4 | S12: 0 | T12: 2 | V12: 149.2 | W12: 0 | X12: 7460 | Y12: 0.5 | Z12: 37.3 | AA12: 0 | AB12: 0.5 | AC12: 37.3 | AD12: 0 | AE12: 2690 | AF12: 7 | AG12: 188 | AH12: 0 | AI12: 7 | AJ12: 188 | AK12: 0 | AL12: 0 | AM12: 0 | AN12: 0 | AO12: 0 | AP12: 0 | AQ12: 0 | AS12: 0 | AT12: 0 | AU12: 0 | AV12: 0 | AW12: 0 | AX12: 0 | AY12: 0 | BC12: 0 | BD12: 0 | BF12: 0 | BG12: 0 | BH12: 7460 | BI12: 0.32 | BJ12: 23.87 | BK12: 0 | BM12: 0 | BN12: 0 | BQ12: 0 | BR12: 0 | BT12: 0 | BU12: 0 | BV12: =M12+V12+AC12+AN12+AX12+BF12+BM12 -> 783.3 | BW12: =BJ12+BC12+AV12+AT12+AR12+AP12+AL12+Z12+R12+J12 -> 1926.17 | BX12: =AJ12 -> 188 | BY12: =AG12 -> 188 | BZ12: =N12+W12+AD12+AO12+AY12+BG12+BN12 -> 0 | CA12: =K12+S12+AA12+AM12+AQ12+AS12+AU12+AW12+BD12+BK12+BR12 -> 0 | CB12: =BU12+AK12 -> 0 | CC12: =BR12+AH12 -> 0 | CD12: =BV12+BX12+BZ12+CB12 -> 971.3 | CE12: =BW12+BY12+CA12+CC12 -> 2114.17 | CF12: =CD12+CE12 -> 3085.47 | CG12: 上海市； | CH12: =BV12+BZ12 -> 783.3 | CI12: =BW12+CA12 -> 1926.17 | CJ12: =BX12+CB12 -> 188 | CK12: =BY12+CC12 -> 188 | CL12: =CH12+CI12 -> 2709.47 | CM12: =CJ12+CK12 -> 376 | CN12: 本部 | CO12: =N12+M12 -> 596.8 | CP12: =V12+W12+AN12+AO12 -> 149.2 | CQ12: =AD12+AC12 -> 37.3 | CR12: =CQ12+CP12+CO12=CH12 -> TRUE | CS12: =VLOOKUP(C12,长促工资明细!G:G,1,0) -> 郭胜霞
A13: 9 | B13: 中粮上海导购 | C13: 过苗苗 | D13: 341224198812281328 | E13: =VLOOKUP(D13,长促工资明细!H:P,3,0) -> NKA | F13: =VLOOKUP(D13,长促工资明细!H:P,7,0) -> 大润发平型关店 | G13: 19.67 | H13: 7460 | I13: 16 | J13: 1193.6 | K13: 0 | L13: 8 | M13: 596.8 | N13: 0 | O13: 7460 | P13: 9 | R13: 671.4 | S13: 0 | T13: 2 | V13: 149.2 | W13: 0 | X13: 7460 | Y13: 0.5 | Z13: 37.3 | AA13: 0 | AB13: 0.5 | AC13: 37.3 | AD13: 0 | AE13: 2690 | AF13: 7 | AG13: 188 | AH13: 0 | AI13: 7 | AJ13: 188 | AK13: 0 | AL13: 0 | AM13: 0 | AN13: 0 | AO13: 0 | AP13: 0 | AQ13: 0 | AS13: 0 | AT13: 0 | AU13: 0 | AV13: 0 | AW13: 0 | AX13: 0 | AY13: 0 | BC13: 0 | BD13: 0 | BF13: 0 | BG13: 0 | BH13: 7460 | BI13: 0.32 | BJ13: 23.87 | BK13: 0 | BM13: 0 | BN13: 0 | BQ13: 0 | BR13: 0 | BT13: 0 | BU13: 0 | BV13: =M13+V13+AC13+AN13+AX13+BF13+BM13 -> 783.3 | BW13: =BJ13+BC13+AV13+AT13+AR13+AP13+AL13+Z13+R13+J13 -> 1926.17 | BX13: =AJ13 -> 188 | BY13: =AG13 -> 188 | BZ13: =N13+W13+AD13+AO13+AY13+BG13+BN13 -> 0 | CA13: =K13+S13+AA13+AM13+AQ13+AS13+AU13+AW13+BD13+BK13+BR13 -> 0 | CB13: =BU13+AK13 -> 0 | CC13: =BR13+AH13 -> 0 | CD13: =BV13+BX13+BZ13+CB13 -> 971.3 | CE13: =BW13+BY13+CA13+CC13 -> 2114.17 | CF13: =CD13+CE13 -> 3085.47 | CG13: 上海市； | CH13: =BV13+BZ13 -> 783.3 | CI13: =BW13+CA13 -> 1926.17 | CJ13: =BX13+CB13 -> 188 | CK13: =BY13+CC13 -> 188 | CL13: =CH13+CI13 -> 2709.47 | CM13: =CJ13+CK13 -> 376 | CN13: 本部 | CO13: =N13+M13 -> 596.8 | CP13: =V13+W13+AN13+AO13 -> 149.2 | CQ13: =AD13+AC13 -> 37.3 | CR13: =CQ13+CP13+CO13=CH13 -> TRUE | CS13: =VLOOKUP(C13,长促工资明细!G:G,1,0) -> 过苗苗
A14: 10 | B14: 中粮上海导购 | C14: 过小娟 | D14: 341622198311041341 | E14: =VLOOKUP(D14,长促工资明细!H:P,3,0) -> NKA | F14: =VLOOKUP(D14,长促工资明细!H:P,7,0) -> 大润发南翔店 | G14: 19.67 | H14: 7460 | I14: 16 | J14: 1193.6 | K14: 0 | L14: 8 | M14: 596.8 | N14: 0 | O14: 7460 | P14: 9 | R14: 671.4 | S14: 0 | T14: 2 | V14: 149.2 | W14: 0 | X14: 7460 | Y14: 0.5 | Z14: 37.3 | AA14: 0 | AB14: 0.5 | AC14: 37.3 | AD14: 0 | AE14: 2690 | AF14: 7 | AG14: 188 | AH14: 0 | AI14: 7 | AJ14: 188 | AK14: 0 | AL14: 0 | AM14: 0 | AN14: 0 | AO14: 0 | AP14: 0 | AQ14: 0 | AS14: 0 | AT14: 0 | AU14: 0 | AV14: 0 | AW14: 0 | AX14: 0 | AY14: 0 | BC14: 0 | BD14: 0 | BF14: 0 | BG14: 0 | BH14: 7460 | BI14: 0.32 | BJ14: 23.87 | BK14: 0 | BM14: 0 | BN14: 0 | BQ14: 0 | BR14: 0 | BT14: 0 | BU14: 0 | BV14: =M14+V14+AC14+AN14+AX14+BF14+BM14 -> 783.3 | BW14: =BJ14+BC14+AV14+AT14+AR14+AP14+AL14+Z14+R14+J14 -> 1926.17 | BX14: =AJ14 -> 188 | BY14: =AG14 -> 188 | BZ14: =N14+W14+AD14+AO14+AY14+BG14+BN14 -> 0 | CA14: =K14+S14+AA14+AM14+AQ14+AS14+AU14+AW14+BD14+BK14+BR14 -> 0 | CB14: =BU14+AK14 -> 0 | CC14: =BR14+AH14 -> 0 | CD14: =BV14+BX14+BZ14+CB14 -> 971.3 | CE14: =BW14+BY14+CA14+CC14 -> 2114.17 | CF14: =CD14+CE14 -> 3085.47 | CG14: 上海市； | CH14: =BV14+BZ14 -> 783.3 | CI14: =BW14+CA14 -> 1926.17 | CJ14: =BX14+CB14 -> 188 | CK14: =BY14+CC14 -> 188 | CL14: =CH14+CI14 -> 2709.47 | CM14: =CJ14+CK14 -> 376 | CN14: 本部 | CO14: =N14+M14 -> 596.8 | CP14: =V14+W14+AN14+AO14 -> 149.2 | CQ14: =AD14+AC14 -> 37.3 | CR14: =CQ14+CP14+CO14=CH14 -> TRUE | CS14: =VLOOKUP(C14,长促工资明细!G:G,1,0) -> 过小娟
A15: 11 | B15: 中粮上海导购 | C15: 黄莹 | D15: 370481198807021823 | E15: =VLOOKUP(D15,长促工资明细!H:P,3,0) -> NKA | F15: =VLOOKUP(D15,长促工资明细!H:P,7,0) -> 大润发美兰湖店 | G15: 19.67 | H15: 7460 | I15: 16 | J15: 1193.6 | K15: 0 | L15: 8 | M15: 596.8 | N15: 0 | O15: 7460 | P15: 9 | R15: 671.4 | S15: 0 | T15: 2 | V15: 149.2 | W15: 0 | X15: 7460 | Y15: 0.5 | Z15: 37.3 | AA15: 0 | AB15: 0.5 | AC15: 37.3 | AD15: 0 | AE15: 2690 | AF15: 7 | AG15: 188 | AH15: 0 | AI15: 7 | AJ15: 188 | AK15: 0 | AL15: 0 | AM15: 0 | AN15: 0 | AO15: 0 | AP15: 0 | AQ15: 0 | AS15: 0 | AT15: 0 | AU15: 0 | AV15: 0 | AW15: 0 | AX15: 0 | AY15: 0 | BC15: 0 | BD15: 0 | BF15: 0 | BG15: 0 | BH15: 7460 | BI15: 0.32 | BJ15: 23.87 | BK15: 0 | BM15: 0 | BN15: 0 | BQ15: 0 | BR15: 0 | BT15: 0 | BU15: 0 | BV15: =M15+V15+AC15+AN15+AX15+BF15+BM15 -> 783.3 | BW15: =BJ15+BC15+AV15+AT15+AR15+AP15+AL15+Z15+R15+J15 -> 1926.17 | BX15: =AJ15 -> 188 | BY15: =AG15 -> 188 | BZ15: =N15+W15+AD15+AO15+AY15+BG15+BN15 -> 0 | CA15: =K15+S15+AA15+AM15+AQ15+AS15+AU15+AW15+BD15+BK15+BR15 -> 0 | CB15: =BU15+AK15 -> 0 | CC15: =BR15+AH15 -> 0 | CD15: =BV15+BX15+BZ15+CB15 -> 971.3 | CE15: =BW15+BY15+CA15+CC15 -> 2114.17 | CF15: =CD15+CE15 -> 3085.47 | CG15: 上海市； | CH15: =BV15+BZ15 -> 783.3 | CI15: =BW15+CA15 -> 1926.17 | CJ15: =BX15+CB15 -> 188 | CK15: =BY15+CC15 -> 188 | CL15: =CH15+CI15 -> 2709.47 | CM15: =CJ15+CK15 -> 376 | CN15: 本部 | CO15: =N15+M15 -> 596.8 | CP15: =V15+W15+AN15+AO15 -> 149.2 | CQ15: =AD15+AC15 -> 37.3 | CR15: =CQ15+CP15+CO15=CH15 -> TRUE | CS15: =VLOOKUP(C15,长促工资明细!G:G,1,0) -> 黄莹
A16: 12 | B16: 中粮上海导购 | C16: 雷年枝 | D16: 342501198810062263 | E16: =VLOOKUP(D16,长促工资明细!H:P,3,0) -> NKA | F16: =VLOOKUP(D16,长促工资明细!H:P,7,0) -> 大润发奉贤店 | G16: 19.67 | H16: 7460 | I16: 16 | J16: 1193.6 | K16: 0 | L16: 8 | M16: 596.8 | N16: 0 | O16: 7460 | P16: 9 | R16: 671.4 | S16: 0 | T16: 2 | V16: 149.2 | W16: 0 | X16: 7460 | Y16: 0.5 | Z16: 37.3 | AA16: 0 | AB16: 0.5 | AC16: 37.3 | AD16: 0 | AE16: 2690 | AF16: 7 | AG16: 188 | AH16: 0 | AI16: 7 | AJ16: 188 | AK16: 0 | AL16: 0 | AM16: 0 | AN16: 0 | AO16: 0 | AP16: 0 | AQ16: 0 | AS16: 0 | AT16: 0 | AU16: 0 | AV16: 0 | AW16: 0 | AX16: 0 | AY16: 0 | BC16: 0 | BD16: 0 | BF16: 0 | BG16: 0 | BH16: 7460 | BI16: 0.32 | BJ16: 23.87 | BK16: 0 | BM16: 0 | BN16: 0 | BQ16: 0 | BR16: 0 | BT16: 0 | BU16: 0 | BV16: =M16+V16+AC16+AN16+AX16+BF16+BM16 -> 783.3 | BW16: =BJ16+BC16+AV16+AT16+AR16+AP16+AL16+Z16+R16+J16 -> 1926.17 | BX16: =AJ16 -> 188 | BY16: =AG16 -> 188 | BZ16: =N16+W16+AD16+AO16+AY16+BG16+BN16 -> 0 | CA16: =K16+S16+AA16+AM16+AQ16+AS16+AU16+AW16+BD16+BK16+BR16 -> 0 | CB16: =BU16+AK16 -> 0 | CC16: =BR16+AH16 -> 0 | CD16: =BV16+BX16+BZ16+CB16 -> 971.3 | CE16: =BW16+BY16+CA16+CC16 -> 2114.17 | CF16: =CD16+CE16 -> 3085.47 | CG16: 上海市； | CH16: =BV16+BZ16 -> 783.3 | CI16: =BW16+CA16 -> 1926.17 | CJ16: =BX16+CB16 -> 188 | CK16: =BY16+CC16 -> 188 | CL16: =CH16+CI16 -> 2709.47 | CM16: =CJ16+CK16 -> 376 | CN16: 本部 | CO16: =N16+M16 -> 596.8 | CP16: =V16+W16+AN16+AO16 -> 149.2 | CQ16: =AD16+AC16 -> 37.3 | CR16: =CQ16+CP16+CO16=CH16 -> TRUE | CS16: =VLOOKUP(C16,长促工资明细!G:G,1,0) -> 雷年枝
... A29: 25 | B29: 中粮上海导购 | C29: 鲜秀英 | D29: 513030198510153427 | E29: =VLOOKUP(D29,长促工资明细!H:P,3,0) -> NKA | F29: =VLOOKUP(D29,长促工资明细!H:P,7,0) -> 欧尚金山店 | G29: 0 | H29: 7460 | I29: 16 | J29: 1193.6 | K29: 0 | L29: 8 | M29: 596.8 | N29: 0 | O29: 7460 | P29: 9 | R29: 671.4 | S29: 0 | T29: 2 | V29: 149.2 | W29: 0 | X29: 7460 | Y29: 0.5 | Z29: 37.3 | AA29: 0 | AB29: 0.5 | AC29: 37.3 | AD29: 0 | AE29: 2740 | AF29: 7 | AG29: 192 | AH29: 0 | AI29: 7 | AJ29: 192 | AK29: 0 | AL29: 0 | AM29: 0 | AN29: 0 | AO29: 0 | AP29: 0 | AQ29: 0 | AS29: 0 | AT29: 0 | AU29: 0 | AV29: 0 | AW29: 0 | AX29: 0 | AY29: 0 | BC29: 0 | BD29: 0 | BF29: 0 | BG29: 0 | BH29: 7460 | BI29: 0.32 | BJ29: 23.87 | BK29: 0 | BM29: 0 | BN29: 0 | BQ29: 0 | BR29: 0 | BT29: 0 | BU29: 0 | BV29: =M29+V29+AC29+AN29+AX29+BF29+BM29 -> 783.3 | BW29: =BJ29+BC29+AV29+AT29+AR29+AP29+AL29+Z29+R29+J29 -> 1926.17 | BX29: =AJ29 -> 192 | BY29: =AG29 -> 192 | BZ29: =N29+W29+AD29+AO29+AY29+BG29+BN29 -> 0 | CA29: =K29+S29+AA29+AM29+AQ29+AS29+AU29+AW29+BD29+BK29+BR29 -> 0 | CB29: =BU29+AK29 -> 0 | CC29: =BR29+AH29 -> 0 | CD29: =BV29+BX29+BZ29+CB29 -> 975.3 | CE29: =BW29+BY29+CA29+CC29 -> 2118.17 | CF29: =CD29+CE29 -> 3093.47 | CG29: 上海市； | CH29: =BV29+BZ29 -> 783.3 | CI29: =BW29+CA29 -> 1926.17 | CJ29: =BX29+CB29 -> 192 | CK29: =BY29+CC29 -> 192 | CL29: =CH29+CI29 -> 2709.47 | CM29: =CJ29+CK29 -> 384 | CN29: 本部 | CO29: =N29+M29 -> 596.8 | CP29: =V29+W29+AN29+AO29 -> 149.2 | CQ29: =AD29+AC29 -> 37.3 | CR29: =CQ29+CP29+CO29=CH29 -> TRUE | CS29: =VLOOKUP(C29,长促工资明细!G:G,1,0) -> 鲜秀英
A30: 26 | B30: 中粮上海导购 | C30: 徐永华 | D30: 341226198411045044 | G30: 0 | H30: 7460 | I30: 16 | J30: 1193.6 | K30: 0 | L30: 8 | M30: 596.8 | N30: 0 | O30: 7460 | P30: 9 | R30: 671.4 | S30: 0 | T30: 2 | V30: 149.2 | W30: 0 | X30: 7460 | Y30: 0.5 | Z30: 37.3 | AA30: 0 | AB30: 0.5 | AC30: 37.3 | AD30: 0 | AE30: 2740 | AF30: 7 | AG30: 192 | AH30: 0 | AI30: 7 | AJ30: 192 | AK30: 0 | AL30: 0 | AM30: 0 | AN30: 0 | AO30: 0 | AP30: 0 | AQ30: 0 | AS30: 0 | AT30: 0 | AU30: 0 | AV30: 0 | AW30: 0 | AX30: 0 | AY30: 0 | BC30: 0 | BD30: 0 | BF30: 0 | BG30: 0 | BH30: 7460 | BI30: 0.32 | BJ30: 23.87 | BK30: 0 | BM30: 0 | BN30: 0 | BQ30: 0 | BR30: 0 | BT30: 0 | BU30: 0 | BV30: =M30+V30+AC30+AN30+AX30+BF30+BM30 -> 783.3 | BW30: =BJ30+BC30+AV30+AT30+AR30+AP30+AL30+Z30+R30+J30 -> 1926.17 | BX30: =AJ30 -> 192 | BY30: =AG30 -> 192 | BZ30: =N30+W30+AD30+AO30+AY30+BG30+BN30 -> 0 | CA30: =K30+S30+AA30+AM30+AQ30+AS30+AU30+AW30+BD30+BK30+BR30 -> 0 | CB30: =BU30+AK30 -> 0 | CC30: =BR30+AH30 -> 0 | CD30: =BV30+BX30+BZ30+CB30 -> 975.3 | CE30: =BW30+BY30+CA30+CC30 -> 2118.17 | CF30: =CD30+CE30 -> 3093.47 | CG30: 上海市； | CH30: =BV30+BZ30 -> 783.3 | CI30: =BW30+CA30 -> 1926.17 | CJ30: =BX30+CB30 -> 192 | CK30: =BY30+CC30 -> 192 | CL30: =CH30+CI30 -> 2709.47 | CM30: =CJ30+CK30 -> 384 | CN30: 本部 | CO30: =N30+M30 -> 596.8 | CP30: =V30+W30+AN30+AO30 -> 149.2 | CQ30: =AD30+AC30 -> 37.3 | CR30: =CQ30+CP30+CO30=CH30 -> TRUE | CS30: =VLOOKUP(C30,长促工资明细!G:G,1,0) -> #N/A
A31: 27 | B31: 中粮上海导购 | C31: 严洪玉 | D31: 320882197404083426 | E31: =VLOOKUP(D31,长促工资明细!H:P,3,0) -> NKA | F31: =VLOOKUP(D31,长促工资明细!H:P,7,0) -> 大润发三林店 | G31: 19.67 | H31: 7460 | I31: 16 | J31: 1193.6 | K31: 0 | L31: 8 | M31: 596.8 | N31: 0 | O31: 7460 | P31: 9 | R31: 671.4 | S31: 0 | T31: 2 | V31: 149.2 | W31: 0 | X31: 7460 | Y31: 0.5 | Z31: 37.3 | AA31: 0 | AB31: 0.5 | AC31: 37.3 | AD31: 0 | AE31: 2690 | AF31: 7 | AG31: 188 | AH31: 0 | AI31: 7 | AJ31: 188 | AK31: 0 | AL31: 0 | AM31: 0 | AN31: 0 | AO31: 0 | AP31: 0 | AQ31: 0 | AS31: 0 | AT31: 0 | AU31: 0 | AV31: 0 | AW31: 0 | AX31: 0 | AY31: 0 | BC31: 0 | BD31: 0 | BF31: 0 | BG31: 0 | BH31: 7460 | BI31: 0.32 | BJ31: 23.87 | BK31: 0 | BM31: 0 | BN31: 0 | BQ31: 0 | BR31: 0 | BT31: 0 | BU31: 0 | BV31: =M31+V31+AC31+AN31+AX31+BF31+BM31 -> 783.3 | BW31: =BJ31+BC31+AV31+AT31+AR31+AP31+AL31+Z31+R31+J31 -> 1926.17 | BX31: =AJ31 -> 188 | BY31: =AG31 -> 188 | BZ31: =N31+W31+AD31+AO31+AY31+BG31+BN31 -> 0 | CA31: =K31+S31+AA31+AM31+AQ31+AS31+AU31+AW31+BD31+BK31+BR31 -> 0 | CB31: =BU31+AK31 -> 0 | CC31: =BR31+AH31 -> 0 | CD31: =BV31+BX31+BZ31+CB31 -> 971.3 | CE31: =BW31+BY31+CA31+CC31 -> 2114.17 | CF31: =CD31+CE31 -> 3085.47 | CG31: 上海市； | CH31: =BV31+BZ31 -> 783.3 | CI31: =BW31+CA31 -> 1926.17 | CJ31: =BX31+CB31 -> 188 | CK31: =BY31+CC31 -> 188 | CL31: =CH31+CI31 -> 2709.47 | CM31: =CJ31+CK31 -> 376 | CN31: 本部 | CO31: =N31+M31 -> 596.8 | CP31: =V31+W31+AN31+AO31 -> 149.2 | CQ31: =AD31+AC31 -> 37.3 | CR31: =CQ31+CP31+CO31=CH31 -> TRUE | CS31: =VLOOKUP(C31,长促工资明细!G:G,1,0) -> 严洪玉
A32: 28 | B32: 中粮上海导购 | C32: 姚友美 | D32: 34122619830430352X | E32: =VLOOKUP(D32,长促工资明细!H:P,3,0) -> NKA | F32: =VLOOKUP(D32,长促工资明细!H:P,7,0) -> 大润发杨浦店 | G32: 19.67 | H32: 7460 | I32: 16 | J32: 1193.6 | K32: 0 | L32: 8 | M32: 596.8 | N32: 0 | O32: 7460 | P32: 9 | R32: 671.4 | S32: 0 | T32: 2 | V32: 149.2 | W32: 0 | X32: 7460 | Y32: 0.5 | Z32: 37.3 | AA32: 0 | AB32: 0.5 | AC32: 37.3 | AD32: 0 | AE32: 2690 | AF32: 7 | AG32: 188 | AH32: 0 | AI32: 7 | AJ32: 188 | AK32: 0 | AL32: 0 | AM32: 0 | AN32: 0 | AO32: 0 | AP32: 0 | AQ32: 0 | AS32: 0 | AT32: 0 | AU32: 0 | AV32: 0 | AW32: 0 | AX32: 0 | AY32: 0 | BC32: 0 | BD32: 0 | BF32: 0 | BG32: 0 | BH32: 7460 | BI32: 0.32 | BJ32: 23.87 | BK32: 0 | BM32: 0 | BN32: 0 | BQ32: 0 | BR32: 0 | BT32: 0 | BU32: 0 | BV32: =M32+V32+AC32+AN32+AX32+BF32+BM32 -> 783.3 | BW32: =BJ32+BC32+AV32+AT32+AR32+AP32+AL32+Z32+R32+J32 -> 1926.17 | BX32: =AJ32 -> 188 | BY32: =AG32 -> 188 | BZ32: =N32+W32+AD32+AO32+AY32+BG32+BN32 -> 0 | CA32: =K32+S32+AA32+AM32+AQ32+AS32+AU32+AW32+BD32+BK32+BR32 -> 0 | CB32: =BU32+AK32 -> 0 | CC32: =BR32+AH32 -> 0 | CD32: =BV32+BX32+BZ32+CB32 -> 971.3 | CE32: =BW32+BY32+CA32+CC32 -> 2114.17 | CF32: =CD32+CE32 -> 3085.47 | CG32: 上海市； | CH32: =BV32+BZ32 -> 783.3 | CI32: =BW32+CA32 -> 1926.17 | CJ32: =BX32+CB32 -> 188 | CK32: =BY32+CC32 -> 188 | CL32: =CH32+CI32 -> 2709.47 | CM32: =CJ32+CK32 -> 376 | CN32: 本部 | CO32: =N32+M32 -> 596.8 | CP32: =V32+W32+AN32+AO32 -> 149.2 | CQ32: =AD32+AC32 -> 37.3 | CR32: =CQ32+CP32+CO32=CH32 -> TRUE | CS32: =VLOOKUP(C32,长促工资明细!G:G,1,0) -> 姚友美
A33: 29 | B33: 中粮上海导购 | C33: 姚玉环 | D33: 342422198302204882 | E33: =VLOOKUP(D33,长促工资明细!H:P,3,0) -> NKA | F33: =VLOOKUP(D33,长促工资明细!H:P,7,0) -> 大润发奉贤店 | G33: 19.67 | H33: 7460 | I33: 16 | J33: 1193.6 | K33: 0 | L33: 8 | M33: 596.8 | N33: 0 | O33: 7460 | P33: 9 | R33: 671.4 | S33: 0 | T33: 2 | V33: 149.2 | W33: 0 | X33: 7460 | Y33: 0.5 | Z33: 37.3 | AA33: 0 | AB33: 0.5 | AC33: 37.3 | AD33: 0 | AE33: 2740 | AF33: 7 | AG33: 192 | AH33: 0 | AI33: 7 | AJ33: 192 | AK33: 0 | AL33: 0 | AM33: 0 | AN33: 0 | AO33: 0 | AP33: 0 | AQ33: 0 | AS33: 0 | AT33: 0 | AU33: 0 | AV33: 0 | AW33: 0 | AX33: 0 | AY33: 0 | BC33: 0 | BD33: 0 | BF33: 0 | BG33: 0 | BH33: 7460 | BI33: 0.32 | BJ33: 23.87 | BK33: 0 | BM33: 0 | BN33: 0 | BQ33: 0 | BR33: 0 | BT33: 0 | BU33: 0 | BV33: =M33+V33+AC33+AN33+AX33+BF33+BM33 -> 783.3 | BW33: =BJ33+BC33+AV33+AT33+AR33+AP33+AL33+Z33+R33+J33 -> 1926.17 | BX33: =AJ33 -> 192 | BY33: =AG33 -> 192 | BZ33: =N33+W33+AD33+AO33+AY33+BG33+BN33 -> 0 | CA33: =K33+S33+AA33+AM33+AQ33+AS33+AU33+AW33+BD33+BK33+BR33 -> 0 | CB33: =BU33+AK33 -> 0 | CC33: =BR33+AH33 -> 0 | CD33: =BV33+BX33+BZ33+CB33 -> 975.3 | CE33: =BW33+BY33+CA33+CC33 -> 2118.17 | CF33: =CD33+CE33 -> 3093.47 | CG33: 上海市； | CH33: =BV33+BZ33 -> 783.3 | CI33: =BW33+CA33 -> 1926.17 | CJ33: =BX33+CB33 -> 192 | CK33: =BY33+CC33 -> 192 | CL33: =CH33+CI33 -> 2709.47 | CM33: =CJ33+CK33 -> 384 | CN33: 本部 | CS33: =VLOOKUP(C33,长促工资明细!G:G,1,0) -> 姚玉环
A34: 30 | B34: 中粮上海导购 | C34: 张孝娟 | D34: 341226198305202763 | E34: =VLOOKUP(D34,长促工资明细!H:P,3,0) -> NKA | F34: =VLOOKUP(D34,长促工资明细!H:P,7,0) -> 大润发华漕店 | G34: 19.67 | H34: 7460 | I34: 16 | J34: 1193.6 | K34: 0 | L34: 8 | M34: 596.8 | N34: 0 | O34: 7460 | P34: 9 | R34: 671.4 | S34: 0 | T34: 2 | V34: 149.2 | W34: 0 | X34: 7460 | Y34: 0.5 | Z34: 37.3 | AA34: 0 | AB34: 0.5 | AC34: 37.3 | AD34: 0 | AE34: 2690 | AF34: 7 | AG34: 188 | AH34: 0 | AI34: 7 | AJ34: 188 | AK34: 0 | AL34: 0 | AM34: 0 | AN34: 0 | AO34: 0 | AP34: 0 | AQ34: 0 | AS34: 0 | AT34: 0 | AU34: 0 | AV34: 0 | AW34: 0 | AX34: 0 | AY34: 0 | BC34: 0 | BD34: 0 | BF34: 0 | BG34: 0 | BH34: 7460 | BI34: 0.32 | BJ34: 23.87 | BK34: 0 | BM34: 0 | BN34: 0 | BQ34: 0 | BR34: 0 | BT34: 0 | BU34: 0 | BV34: =M34+V34+AC34+AN34+AX34+BF34+BM34 -> 783.3 | BW34: =BJ34+BC34+AV34+AT34+AR34+AP34+AL34+Z34+R34+J34 -> 1926.17 | BX34: =AJ34 -> 188 | BY34: =AG34 -> 188 | BZ34: =N34+W34+AD34+AO34+AY34+BG34+BN34 -> 0 | CA34: =K34+S34+AA34+AM34+AQ34+AS34+AU34+AW34+BD34+BK34+BR34 -> 0 | CB34: =BU34+AK34 -> 0 | CC34: =BR34+AH34 -> 0 | CD34: =BV34+BX34+BZ34+CB34 -> 971.3 | CE34: =BW34+BY34+CA34+CC34 -> 2114.17 | CF34: =CD34+CE34 -> 3085.47 | CG34: 上海市； | CH34: =BV34+BZ34 -> 783.3 | CI34: =BW34+CA34 -> 1926.17 | CJ34: =BX34+CB34 -> 188 | CK34: =BY34+CC34 -> 188 | CL34: =CH34+CI34 -> 2709.47 | CM34: =CJ34+CK34 -> 376 | CN34: 本部 | CS34: =VLOOKUP(C34,长促工资明细!G:G,1,0) -> 张孝娟
A35: 31 | B35: 中粮上海导购 | C35: 赵志炜 | D35: 340826197611081813 | E35: =VLOOKUP(D35,长促工资明细!H:P,3,0) -> NKA | F35: =VLOOKUP(D35,长促工资明细!H:P,7,0) -> 大润发曹安店 | G35: 19.67 | H35: 7460 | I35: 16 | J35: 1193.6 | K35: 0 | L35: 8 | M35: 596.8 | N35: 0 | O35: 7460 | P35: 9 | R35: 671.4 | S35: 0 | T35: 2 | V35: 149.2 | W35: 0 | X35: 7460 | Y35: 0.5 | Z35: 37.3 | AA35: 0 | AB35: 0.5 | AC35: 37.3 | AD35: 0 | AE35: 2690 | AF35: 7 | AG35: 188 | AH35: 0 | AI35: 7 | AJ35: 188 | AK35: 0 | AL35: 0 | AM35: 0 | AN35: 0 | AO35: 0 | AP35: 0 | AQ35: 0 | AS35: 0 | AT35: 0 | AU35: 0 | AV35: 0 | AW35: 0 | AX35: 0 | AY35: 0 | BC35: 0 | BD35: 0 | BF35: 0 | BG35: 0 | BH35: 7460 | BI35: 0.32 | BJ35: 23.87 | BK35: 0 | BM35: 0 | BN35: 0 | BQ35: 0 | BR35: 0 | BT35: 0 | BU35: 0 | BV35: =M35+V35+AC35+AN35+AX35+BF35+BM35 -> 783.3 | BW35: =BJ35+BC35+AV35+AT35+AR35+AP35+AL35+Z35+R35+J35 -> 1926.17 | BX35: =AJ35 -> 188 | BY35: =AG35 -> 188 | BZ35: =N35+W35+AD35+AO35+AY35+BG35+BN35 -> 0 | CA35: =K35+S35+AA35+AM35+AQ35+AS35+AU35+AW35+BD35+BK35+BR35 -> 0 | CB35: =BU35+AK35 -> 0 | CC35: =BR35+AH35 -> 0 | CD35: =BV35+BX35+BZ35+CB35 -> 971.3 | CE35: =BW35+BY35+CA35+CC35 -> 2114.17 | CF35: =CD35+CE35 -> 3085.47 | CG35: 上海市； | CH35: =BV35+BZ35 -> 783.3 | CI35: =BW35+CA35 -> 1926.17 | CJ35: =BX35+CB35 -> 188 | CK35: =BY35+CC35 -> 188 | CL35: =CH35+CI35 -> 2709.47 | CM35: =CJ35+CK35 -> 376 | CN35: 本部 | CS35: =VLOOKUP(C35,长促工资明细!G:G,1,0) -> 赵志炜
A36: 32 | B36: 中粮上海导购 | C36: 周汝娜 | D36: 342422198208101764 | E36: =VLOOKUP(D36,长促工资明细!H:P,3,0) -> NKA | F36: =VLOOKUP(D36,长促工资明细!H:P,7,0) -> 大润发春申店 | G36: 19.67 | H36: 7460 | I36: 16 | J36: 1193.6 | K36: 0 | L36: 8 | M36: 596.8 | N36: 0 | O36: 7460 | P36: 9 | R36: 671.4 | S36: 0 | T36: 2 | V36: 149.2 | W36: 0 | X36: 7460 | Y36: 0.5 | Z36: 37.3 | AA36: 0 | AB36: 0.5 | AC36: 37.3 | AD36: 0 | AE36: 2690 | AF36: 7 | AG36: 188 | AH36: 0 | AI36: 7 | AJ36: 188 | AK36: 0 | AL36: 0 | AM36: 0 | AN36: 0 | AO36: 0 | AP36: 0 | AQ36: 0 | AS36: 0 | AT36: 0 | AU36: 0 | AV36: 0 | AW36: 0 | AX36: 0 | AY36: 0 | BC36: 0 | BD36: 0 | BF36: 0 | BG36: 0 | BH36: 7460 | BI36: 0.32 | BJ36: 23.87 | BK36: 0 | BM36: 0 | BN36: 0 | BQ36: 0 | BR36: 0 | BT36: 0 | BU36: 0 | BV36: =M36+V36+AC36+AN36+AX36+BF36+BM36 -> 783.3 | BW36: =BJ36+BC36+AV36+AT36+AR36+AP36+AL36+Z36+R36+J36 -> 1926.17 | BX36: =AJ36 -> 188 | BY36: =AG36 -> 188 | BZ36: =N36+W36+AD36+AO36+AY36+BG36+BN36 -> 0 | CA36: =K36+S36+AA36+AM36+AQ36+AS36+AU36+AW36+BD36+BK36+BR36 -> 0 | CB36: =BU36+AK36 -> 0 | CC36: =BR36+AH36 -> 0 | CD36: =BV36+BX36+BZ36+CB36 -> 971.3 | CE36: =BW36+BY36+CA36+CC36 -> 2114.17 | CF36: =CD36+CE36 -> 3085.47 | CG36: 上海市； | CH36: =BV36+BZ36 -> 783.3 | CI36: =BW36+CA36 -> 1926.17 | CJ36: =BX36+CB36 -> 188 | CK36: =BY36+CC36 -> 188 | CL36: =CH36+CI36 -> 2709.47 | CM36: =CJ36+CK36 -> 376 | CN36: 本部 | CS36: =VLOOKUP(C36,长促工资明细!G:G,1,0) -> 周汝娜
A37: 33 | B37: 流动导购KA | C37: 施美花 | D37: 310230198305175169 | E37: =VLOOKUP(D37,长促工资明细!H:P,3,0) -> NKA | F37: =VLOOKUP(D37,长促工资明细!H:P,7,0) -> 大润发康桥店 | G37: 19.67 | H37: 7460 | I37: 16 | J37: 1193.6 | K37: 0 | L37: 8 | M37: 596.8 | N37: 0 | O37: 7460 | P37: 9 | R37: 671.4 | S37: 0 | T37: 2 | V37: 149.2 | W37: 0 | X37: 7460 | Y37: 0.5 | Z37: 37.3 | AA37: 0 | AB37: 0.5 | AC37: 37.3 | AD37: 0 | AE37: 2690 | AF37: 7 | AG37: 188 | AH37: 0 | AI37: 7 | AJ37: 188 | AK37: 0 | AL37: 0 | AM37: 0 | AN37: 0 | AO37: 0 | AP37: 0 | AQ37: 0 | AS37: 0 | AT37: 0 | AU37: 0 | AV37: 0 | AW37: 0 | AX37: 0 | AY37: 0 | BC37: 0 | BD37: 0 | BF37: 0 | BG37: 0 | BH37: 7460 | BI37: 0.32 | BJ37: 23.87 | BK37: 0 | BM37: 0 | BN37: 0 | BQ37: 0 | BR37: 0 | BT37: 0 | BU37: 0 | BV37: =M37+V37+AC37+AN37+AX37+BF37+BM37 -> 783.3 | BW37: =BJ37+BC37+AV37+AT37+AR37+AP37+AL37+Z37+R37+J37 -> 1926.17 | BX37: =AJ37 -> 188 | BY37: =AG37 -> 188 | BZ37: =N37+W37+AD37+AO37+AY37+BG37+BN37 -> 0 | CA37: =K37+S37+AA37+AM37+AQ37+AS37+AU37+AW37+BD37+BK37+BR37 -> 0 | CB37: =BU37+AK37 -> 0 | CC37: =BR37+AH37 -> 0 | CD37: =BV37+BX37+BZ37+CB37 -> 971.3 | CE37: =BW37+BY37+CA37+CC37 -> 2114.17 | CF37: =CD37+CE37 -> 3085.47 | CG37: 上海市； | CH37: =BV37+BZ37 -> 783.3 | CI37: =BW37+CA37 -> 1926.17 | CJ37: =BX37+CB37 -> 188 | CK37: =BY37+CC37 -> 188 | CL37: =CH37+CI37 -> 2709.47 | CM37: =CJ37+CK37 -> 376 | CN37: 本部 | CS37: =VLOOKUP(C37,长促工资明细!G:G,1,0) -> 施美花
A38: 34 | B38: 流动导购KA | C38: 余应红 | D38: 342423197801132301 | E38: =VLOOKUP(D38,长促工资明细!H:P,3,0) -> NKA | F38: =VLOOKUP(D38,长促工资明细!H:P,7,0) -> 大润发春申店 | G38: 19.67 | H38: 7460 | I38: 16 | J38: 1193.6 | K38: 0 | L38: 8 | M38: 596.8 | N38: 0 | O38: 7460 | P38: 9 | R38: 671.4 | S38: 0 | T38: 2 | V38: 149.2 | W38: 0 | X38: 7460 | Y38: 0.5 | Z38: 37.3 | AA38: 0 | AB38: 0.5 | AC38: 37.3 | AD38: 0 | AE38: 2690 | AF38: 7 | AG38: 188 | AH38: 0 | AI38: 7 | AJ38: 188 | AK38: 0 | AL38: 0 | AM38: 0 | AN38: 0 | AO38: 0 | AP38: 0 | AQ38: 0 | AS38: 0 | AT38: 0 | AU38: 0 | AV38: 0 | AW38: 0 | AX38: 0 | AY38: 0 | BC38: 0 | BD38: 0 | BF38: 0 | BG38: 0 | BH38: 7460 | BI38: 0.32 | BJ38: 23.87 | BK38: 0 | BM38: 0 | BN38: 0 | BQ38: 0 | BR38: 0 | BT38: 0 | BU38: 0 | BV38: =M38+V38+AC38+AN38+AX38+BF38+BM38 -> 783.3 | BW38: =BJ38+BC38+AV38+AT38+AR38+AP38+AL38+Z38+R38+J38 -> 1926.17 | BX38: =AJ38 -> 188 | BY38: =AG38 -> 188 | BZ38: =N38+W38+AD38+AO38+AY38+BG38+BN38 -> 0 | CA38: =K38+S38+AA38+AM38+AQ38+AS38+AU38+AW38+BD38+BK38+BR38 -> 0 | CB38: =BU38+AK38 -> 0 | CC38: =BR38+AH38 -> 0 | CD38: =BV38+BX38+BZ38+CB38 -> 971.3 | CE38: =BW38+BY38+CA38+CC38 -> 2114.17 | CF38: =CD38+CE38 -> 3085.47 | CG38: 上海市； | CH38: =BV38+BZ38 -> 783.3 | CI38: =BW38+CA38 -> 1926.17 | CJ38: =BX38+CB38 -> 188 | CK38: =BY38+CC38 -> 188 | CL38: =CH38+CI38 -> 2709.47 | CM38: =CJ38+CK38 -> 376 | CN38: 本部 | CS38: =VLOOKUP(C38,长促工资明细!G:G,1,0) -> 余应红
B39: 流动导购KA | C39: 王静 | D39: 340122198603201708 | F39: 麦德龙 | G39: 19.67
A40: 合计 | G40: =SUM(G5:G39) -> 649.11 | H40: =SUM(H5:H39) -> 253640 | I40: =SUM(I5:I39) -> 544 | J40: =SUM(J5:J39) -> 40582.4 | K40: =SUM(K5:K39) -> 0 | L40: =SUM(L5:L39) -> 272 | M40: =SUM(M5:M39) -> 20291.2 | N40: =SUM(N5:N39) -> 0 | ... CM40: =SUM(CM5:CM39) -> 12808 | CN40: =SUM(CN5:CN38) -> 0

Sheet Sheet8
A1: 姓名 | B1: 雇主责任险 | C1: 本月应缴金额 | G1: 补缴金额 | K1: 实缴金额
C2: 社保 | E2: 公积金 | G2: 社保 | I2: 公积金 | K2: 个人 | L2: 公司 | M2: 小计
C3: 个人 | D3: 公司 | E3: 个人 | F3: 公司 | G3: 个人 | H3: 公司 | I3: 个人 | J3: 公司 | K3: 个人 | L3: 公司 | M3: 小计
A4: 车文秀 | B4: 21 | C4: 684.6 | D4: 1777.1 | E4: 181 | F4: 181 | G4: 0 | H4: 0 | I4: 0 | J4: 0 | K4: 865.6 | L4: 1958.1 | M4: 2823.7
A5: 陈福娟 | B5: 21 | C5: 684.6 | D5: 1777.1 | E5: 181 | F5: 181 | G5: 0 | H5: 0 | I5: 0 | J5: 0 | K5: 865.6 | L5: 1958.1 | M5: 2823.7
A6: 陈敏 | B6: 21 | C6: 684.6 | D6: 1777.1 | E6: 181 | F6: 181 | G6: 0 | H6: 0 | I6: 0 | J6: 0 | K6: 865.6 | L6: 1958.1 | M6: 2823.7
A7: 陈芹 | B7: 21 | C7: 684.6 | D7: 1777.1 | E7: 181 | F7: 181 | G7: 0 | H7: 0 | I7: 0 | J7: 0 | K7: 865.6 | L7: 1958.1 | M7: 2823.7
A8: 东港 | B8: 21 | C8: 684.6 | D8: 1777.1 | E8: 181 | F8: 181 | G8: 0 | H8: 0 | I8: 0 | J8: 0 | K8: 865.6 | L8: 1958.1 | M8: 2823.7
A9: 范祖容 | B9: 21 | C9: 684.6 | D9: 1777.1 | E9: 181 | F9: 181 | G9: 0 | H9: 0 | I9: 0 | J9: 0 | K9: 865.6 | L9: 1958.1 | M9: 2823.7
A10: 戈艳青 | B10: 21 | C10: 684.6 | D10: 1777.1 | E10: 181 | F10: 181 | G10: 0 | H10: 0 | I10: 0 | J10: 0 | K10: 865.6 | L10: 1958.1 | M10: 2823.7
A11: 葛菊 | B11: 21 | C11: 684.6 | D11: 1777.1 | E11: 181 | F11: 181 | G11: 0 | H11: 0 | I11: 0 | J11: 0 | K11: 865.6 | L11: 1958.1 | M11: 2823.7
A12: 顾建凤 | B12: 21 | C12: 684.6 | D12: 1777.1 | E12: 181 | F12: 181 | G12: 0 | H12: 0 | I12: 0 | J12: 0 | K12: 865.6 | L12: 1958.1 | M12: 2823.7
A13: 管兵娥 | B13: 21 | C13: 684.6 | D13: 1777.1 | E13: 181 | F13: 181 | G13: 0 | H13: 0 | I13: 0 | J13: 0 | K13: 865.6 | L13: 1958.1 | M13: 2823.7
A14: 郭胜霞 | B14: 21 | C14: 684.6 | D14: 1777.1 | E14: 181 | F14: 181 | G14: 0 | H14: 0 | I14: 0 | J14: 0 | K14: 865.6 | L14: 1958.1 | M14: 2823.7
A15: 过苗苗 | B15: 21 | C15: 684.6 | D15: 1777.1 | E15: 181 | F15: 181 | G15: 0 | H15: 0 | I15: 0 | J15: 0 | K15: 865.6 | L15: 1958.1 | M15: 2823.7
... A96: 王素芹 | B96: -21 | C96: -456.25 | D96: -1134.75 | E96: -274 | F96: -274 | G96: 0 | H96: 0 | I96: 0 | J96: 0 | K96: -730.25 | L96: -1408.75 | M96: -2139
B97: =SUM(B4:B96) -> 1911 | C97: =SUM(C4:C96) -> 60533.45 | D97: =SUM(D4:D96) -> 155897.59 | E97: =SUM(E4:E96) -> 17004 | F97: =SUM(F4:F96) -> 17004 | G97: =SUM(G4:G96) -> 0 | H97: =SUM(H4:H96) -> 0 | I97: =SUM(I4:I96) -> 171 | ... M97: =SUM(M4:M96) -> 250781.04
C100: 社保个人 | D100: =C97+G97 -> 60533.45
C101: 公积金个人 | D101: =E97+I97 -> 17175
C102: 社保公司 | D102: =D97+H97 -> 155897.59
C103: 公积金公司 | D103: =F97+J97 -> 17175

Sheet Sheet6
A1: 组织名称 | B1: 姓名 | C1: 身份证号码 | D1: 雇主责任险 | E1: 本月应缴金额 | I1: 补缴金额 | M1: 实缴金额
E2: 社保 | G2: 公积金 | I2: 社保 | K2: 公积金 | M2: 个人 | N2: 公司 | O2: 小计
E3: 个人 | F3: 公司 | G3: 个人 | H3: 公司 | I3: 个人 | J3: 公司 | K3: 个人 | L3: 公司 | M3: 个人 | N3: 公司 | O3: 小计
A4: 中粮福临门上海 | B4: 车文秀 | C4: 341623199710154424 | D4: 21 | E4: 684.6 | F4: 1777.1 | G4: 181 | H4: 181 | I4: 0 | J4: 0 | K4: 0 | L4: 0 | M4: 865.6 | N4: 1958.1 | O4: 2823.7
A5: 中粮福临门上海 | B5: 陈福娟 | C5: 342423197403292668 | D5: 21 | E5: 684.6 | F5: 1777.1 | G5: 181 | H5: 181 | I5: 0 | J5: 0 | K5: 0 | L5: 0 | M5: 865.6 | N5: 1958.1 | O5: 2823.7
A6: 中粮福临门上海 | B6: 陈敏 | C6: 310226197301243524 | D6: 21 | E6: 684.6 | F6: 1777.1 | G6: 181 | H6: 181 | I6: 0 | J6: 0 | K6: 0 | L6: 0 | M6: 865.6 | N6: 1958.1 | O6: 2823.7
A7: 中粮福临门上海 | B7: 陈芹 | C7: 511221198305230246 | D7: 21 | E7: 684.6 | F7: 1777.1 | G7: 181 | H7: 181 | I7: 0 | J7: 0 | K7: 0 | L7: 0 | M7: 865.6 | N7: 1958.1 | O7: 2823.7
A8: 中粮福临门上海 | B8: 邓辉 | C8: 652701197206262225 | D8: 0 | E8: 0 | F8: 0 | G8: 0 | H8: 0 | I8: 0 | J8: 0 | K8: 0 | L8: 0 | M8: 0 | N8: 0 | O8: 0
A9: 中粮福临门上海 | B9: 东港 | C9: 210422198201031424 | D9: 21 | E9: 684.6 | F9: 1777.1 | G9: 181 | H9: 181 | I9: 0 | J9: 0 | K9: 0 | L9: 0 | M9: 865.6 | N9: 1958.1 | O9: 2823.7
A10: 中粮福临门上海 | B10: 范祖容 | C10: 51253319820521484X | D10: 21 | E10: 684.6 | F10: 1777.1 | G10: 181 | H10: 181 | I10: 0 | J10: 0 | K10: 0 | L10: 0 | M10: 865.6 | N10: 1958.1 | O10: 2823.7
A11: 中粮福临门上海 | B11: 戈艳青 | C11: 32082319780513524X | D11: 21 | E11: 684.6 | F11: 1777.1 | G11: 181 | H11: 181 | I11: 0 | J11: 0 | K11: 0 | L11: 0 | M11: 865.6 | N11: 1958.1 | O11: 2823.7
A12: 中粮福临门上海 | B12: 葛菊 | C12: 340421198104213042 | D12: 21 | E12: 684.6 | F12: 1777.1 | G12: 181 | H12: 181 | I12: 0 | J12: 0 | K12: 0 | L12: 0 | M12: 865.6 | N12: 1958.1 | O12: 2823.7
A13: 中粮福临门上海 | B13: 顾建凤 | C13: 310226197704023526 | D13: 21 | E13: 684.6 | F13: 1777.1 | G13: 181 | H13: 181 | I13: 0 | J13: 0 | K13: 0 | L13: 0 | M13: 865.6 | N13: 1958.1 | O13: 2823.7
A14: 中粮福临门上海 | B14: 顾永芳 | C14: 31022819730201382X | D14: 21 | E14: 684.6 | F14: 1777.1 | G14: 181 | H14: 181 | I14: 0 | J14: 0 | K14: 0 | L14: 0 | M14: 865.6 | N14: 1958.1 | O14: 2823.7
A15: 中粮福临门上海 | B15: 管兵娥 | C15: 362329198211245745 | D15: 21 | E15: 684.6 | F15: 1777.1 | G15: 181 | H15: 181 | I15: 0 | J15: 0 | K15: 0 | L15: 0 | M15: 865.6 | N15: 1958.1 | O15: 2823.7
... A79: 中粮福临门上海 | B79: 孙艳 | C79: 34120319890120316X | D79: 0 | E79: 684.6 | F79: 1777.1 | G79: 181 | H79: 181 | I79: 0 | J79: 0 | K79: 0 | L79: 0 | M79: 865.6 | N79: 1958.1 | O79: 2823.7
A80: 中粮福临门上海 | B80: 孙艳 | C80: 34120319890120316X | D80: 21 | E80: 627.38 | F80: 1628.55 | G80: 181 | H80: 181 | I80: 0 | J80: 0 | K80: 0 | L80: 0 | M80: 808.38 | N80: 1809.55 | O80: 2617.93 | P80: =N79+N80 -> 3767.65 | Q80: =M79+M80 -> 1673.98
A81: 中粮-中粮江沪（合杰） | B81: 杜艳梅 | C81: 41272519740221784X | D81: 21 | E81: 415.45 | F81: 1007.02 | G81: 161 | H81: 161 | I81: 0 | J81: 0 | K81: 0 | L81: 0 | M81: 576.45 | N81: 1168.02 | O81: 1744.47
A82: 中粮-中粮江沪（合杰） | B82: 耿良莉 | C82: 34242319840516738X | D82: 21 | E82: 415.45 | F82: 1007.02 | G82: 161 | H82: 161 | I82: 0 | J82: 0 | K82: 0 | L82: 0 | M82: 576.45 | N82: 1168.02 | O82: 1744.47
A83: 中粮-中粮江沪（合杰） | B83: 霍雪 | C83: 41152819860103524X | D83: 21 | E83: 341.35 | F83: 977.05 | G83: 317 | H83: 317 | I83: 0 | J83: 39.57 | K83: 0 | L83: 0 | M83: 658.35 | N83: 1333.62 | O83: 1991.97
A84: 中粮-中粮江沪（合杰） | B84: 李芳 | C84: 41022119771110764X | D84: 21 | E84: 415.45 | F84: 1007.02 | G84: 161 | H84: 161 | I84: 0 | J84: 0 | K84: 0 | L84: 0 | M84: 576.45 | N84: 1168.02 | O84: 1744.47
A85: 中粮-中粮江沪（合杰） | B85: 涂秀华 | C85: 511123197304307822 | D85: 21 | E85: 415.45 | F85: 1007.02 | G85: 161 | H85: 161 | I85: 0 | J85: 0 | K85: 0 | L85: 0 | M85: 576.45 | N85: 1168.02 | O85: 1744.47
A86: 中粮-中粮江沪（合杰） | B86: 尹雪峰 | C86: 342224198109020741 | D86: 21 | E86: 415.45 | F86: 1007.02 | G86: 182 | H86: 182 | I86: 0 | J86: 0 | K86: 0 | L86: 0 | M86: 597.45 | N86: 1189.02 | O86: 1786.47
A87: 中粮-中粮江沪（合杰） | B87: 丁小红 | C87: 321025197404040821 | D87: 21 | E87: 446.25 | F87: 1096.5 | G87: 0 | H87: 0 | I87: 0 | J87: 0 | K87: 0 | L87: 0 | M87: 446.25 | N87: 1096.5 | O87: 1542.75
A88: 中粮-中粮江沪（合杰） | B88: 顾宏 | C88: 320924197303033448 | D88: 21 | E88: 451.25 | F88: 1051.88 | G88: 304 | H88: 304 | I88: 0 | J88: 0 | K88: 0 | L88: 0 | M88: 755.25 | N88: 1355.88 | O88: 2111.13
A89: 中粮-中粮江沪（合杰） | B89: 孙开艳 | C89: 32092419760320718X | D89: 21 | E89: 446.25 | F89: 1096.5 | G89: 162 | H89: 162 | I89: 0 | J89: 0 | K89: 0 | L89: 0 | M89: 608.25 | N89: 1258.5 | O89: 1866.75
A90: 中粮-中粮江沪（合杰） | B90: 孙莉莉 | C90: 320922198304053645 | D90: 21 | E90: 446.25 | F90: 1096.5 | G90: 162 | H90: 162 | I90: 0 | J90: 0 | K90: 0 | L90: 0 | M90: 608.25 | N90: 1258.5 | O90: 1866.75
A91: 中粮-中粮江沪（合杰） | B91: 陶宝芹 | C91: 321023197201015869 | D91: 21 | E91: 446.25 | F91: 1096.5 | G91: 0 | H91: 0 | I91: 0 | J91: 0 | K91: 0 | L91: 0 | M91: 446.25 | N91: 1096.5 | O91: 1542.75
A92: 中粮-中粮江沪（合杰） | B92: 王素芹 | C92: 320825197403144322 | D92: 21 | E92: 456.25 | F92: 1134.75 | G92: 274 | H92: 274 | I92: 0 | J92: 0 | K92: 0 | L92: 0 | M92: 730.25 | N92: 1408.75 | O92: 2139
... A98: 中粮-中粮江沪（合杰） | B98: 郑爱凤 | C98: 320423197203263023 | D98: 0 | E98: 0 | F98: 0 | G98: 0 | H98: 0 | I98: 0 | J98: 0 | K98: 0 | L98: 0 | M98: 0 | N98: 0 | O98: 0
D99: =SUM(D4:D98) -> 1932 | E99: =SUM(E4:E98) -> 57965.53 | F99: =SUM(F4:F98) -> 149373.14 | G99: =SUM(G4:G98) -> 16392 | H99: =SUM(H4:H98) -> 16392 | I99: =SUM(I4:I98) -> 0 | J99: =SUM(J4:J98) -> 39.57 | K99: =SUM(K4:K98) -> 0 | ... O99: =SUM(O4:O98) -> 240162.24
D103: 社保（个人） | E103: =E99 -> 57965.53
D104: 公积金（个人） | E104: =G99 -> 16392
D105: 社保公司 | E105: =F99+J99 -> 149412.71
D106: 公积金（公司） | E106: =H99 -> 16392

Sheet Sheet7
A1: 序号 | B1: 组织名称 | C1: 姓名 | D1: 身份证号码 | E1: 养老 | L1: 医疗 | U1: 失业 | AB1: 住房 | AI1: 其他类社保 | AX1: 生育 | BE1: 工伤 | BL1: 补充公积金 | BS1: 本月应缴金额 | BW1: 补缴金额 | CA1: 实缴金额 | CD1: 雇主责任险
E2: 基数 | F2: 公司 | I2: 个人 | L2: 基数 | M2: 公司 | Q2: 个人 | U2: 基数 | V2: 公司 | Y2: 个人 | AB2: 基数 | AC2: 公司 | AF2: 个人 | AI2: 大病公司 | AK2: 大病个人 | AM2: 采暖费 | AO2: 保障金 | AQ2: 社保工会费 | AS2: 公司其他 | AU2: 个人其他 | AW2: 备注 | AX2: 基数 | AY2: 公司 | BB2: 个人 | BE2: 基数 | BF2: 公司 | BI2: 个人 | BL2: 基数 | BM2: 公司 | BP2: 个人 | BS2: 社保 | BU2: 公积金 | BW2: 社保 | BY2: 公积金 | CA2: 个人 | CB2: 公司 | CC2: 小计
E3: 基数 | F3: 比例(%) | G3: 应缴 | H3: 补缴 | I3: 比例(%) | J3: 应缴 | K3: 补缴 | L3: 基数 | M3: 比例(%) | N3: 固定 | O3: 应缴 | P3: 补缴 | Q3: 比例(%) | R3: 固定 | S3: 应缴 | T3: 补缴 | U3: 基数 | V3: 比例(%) | W3: 应缴 | X3: 补缴 | Y3: 比例(%) | Z3: 应缴 | AA3: 补缴 | AB3: 基数 | AC3: 比例(%) | AD3: 应缴 | AE3: 补缴 | AF3: 比例(%) | AG3: 应缴 | AH3: 补缴 | AI3: 应缴 | AJ3: 补缴 | AK3: 应缴 | AL3: 补缴 | AM3: 应缴 | AN3: 补缴 | AO3: 应缴 | AP3: 补缴 | AQ3: 应缴 | AR3: 补缴 | AS3: 应缴 | AT3: 补缴 | AU3: 应缴 | AV3: 补缴 | AW3: 备注 | AX3: 基数 | AY3: 比例(%) | AZ3: 应缴 | BA3: 补缴 | BB3: 比例(%) | BC3: 应缴 | BD3: 补缴 | BE3: 基数 | BF3: 比例(%) | BG3: 应缴 | BH3: 补缴 | BI3: 比例(%) | BJ3: 应缴 | BK3: 补缴 | BL3: 基数 | BM3: 比例(%) | BN3: 应缴 | BO3: 补缴 | BP3: 比例(%) | BQ3: 应缴 | BR3: 补缴 | BS3: 个人 | BT3: 公司 | BU3: 个人 | BV3: 公司 | BW3: 个人 | BX3: 公司 | BY3: 个人 | BZ3: 公司 | CA3: 个人 | CB3: 公司 | CC3: 小计
A4: 6月 | B4: 中粮福临门上海 | C4: 车文秀 | D4: 341623199710154424 | E4: 6520 | F4: 16 | G4: 1043.2 | H4: 0 | I4: 8 | J4: 521.6 | K4: 0 | L4: 6520 | M4: 9.5 | O4: 619.4 | P4: 0 | Q4: 2 | S4: 130.4 | T4: 0 | U4: 6520 | V4: 0.5 | W4: 32.6 | X4: 0 | Y4: 0.5 | Z4: 32.6 | AA4: 0 | AB4: 2590 | AC4: 7 | AD4: 181 | AE4: 0 | AF4: 7 | AG4: 181 | AH4: 0 | AI4: 0 | AJ4: 0 | AK4: 0 | AL4: 0 | AM4: 0 | AN4: 0 | AO4: 0 | AP4: 0 | AQ4: 0 | AR4: 0 | AS4: 0 | AT4: 0 | AU4: 0 | AV4: 0 | AX4: 6520 | AY4: 1 | AZ4: 65.2 | BA4: 0 | BC4: 0 | BD4: 0 | BE4: 6520 | BF4: 0.256 | BG4: 16.7 | BH4: 0 | BJ4: 0 | BK4: 0 | BN4: 0 | BO4: 0 | BQ4: 0 | BR4: 0 | BS4: =J4+S4+Z4+AK4+AU4+BC4+BJ4 -> 684.6 | BT4: =G4+O4+W4+AI4+AM4+AO4+AQ4+AS4+AZ4+BG4 -> 1777.1 | BU4: =AG4 -> 181 | BV4: =AD4 -> 181 | BW4: 0 | BX4: =H4+P4+X4+BA4+BH4 -> 0 | BY4: 0 | BZ4: 0 | CA4: =BS4+BU4+BW4+BY4 -> 865.6 | CB4: =BT4+BV4+BX4+BZ4 -> 1958.1 | CC4: =CA4+CB4 -> 2823.7 | CD4: 21
A5: 6月 | B5: 中粮福临门上海 | C5: 陈福娟 | D5: 342423197403292668 | E5: 6520 | F5: 16 | G5: 1043.2 | H5: 0 | I5: 8 | J5: 521.6 | K5: 0 | L5: 6520 | M5: 9.5 | O5: 619.4 | P5: 0 | Q5: 2 | S5: 130.4 | T5: 0 | U5: 6520 | V5: 0.5 | W5: 32.6 | X5: 0 | Y5: 0.5 | Z5: 32.6 | AA5: 0 | AB5: 2590 | AC5: 7 | AD5: 181 | AE5: 0 | AF5: 7 | AG5: 181 | AH5: 0 | AI5: 0 | AJ5: 0 | AK5: 0 | AL5: 0 | AM5: 0 | AN5: 0 | AO5: 0 | AP5: 0 | AQ5: 0 | AR5: 0 | AS5: 0 | AT5: 0 | AU5: 0 | AV5: 0 | AX5: 6520 | AY5: 1 | AZ5: 65.2 | BA5: 0 | BC5: 0 | BD5: 0 | BE5: 6520 | BF5: 0.256 | BG5: 16.7 | BH5: 0 | BJ5: 0 | BK5: 0 | BN5: 0 | BO5: 0 | BQ5: 0 | BR5: 0 | BS5: =J5+S5+Z5+AK5+AU5+BC5+BJ5 -> 684.6 | BT5: =G5+O5+W5+AI5+AM5+AO5+AQ5+AS5+AZ5+BG5 -> 1777.1 | BU5: =AG5 -> 181 | BV5: =AD5 -> 181 | BW5: 0 | BX5: =H5+P5+X5+BA5+BH5 -> 0 | BY5: 0 | BZ5: 0 | CA5: =BS5+BU5+BW5+BY5 -> 865.6 | CB5: =BT5+BV5+BX5+BZ5 -> 1958.1 | CC5: =CA5+CB5 -> 2823.7 | CD5: 21
A6: 6月 | B6: 中粮福临门上海 | C6: 陈敏 | D6: 310226197301243524 | E6: 6520 | F6: 16 | G6: 1043.2 | H6: 0 | I6: 8 | J6: 521.6 | K6: 0 | L6: 6520 | M6: 9.5 | O6: 619.4 | P6: 0 | Q6: 2 | S6: 130.4 | T6: 0 | U6: 6520 | V6: 0.5 | W6: 32.6 | X6: 0 | Y6: 0.5 | Z6: 32.6 | AA6: 0 | AB6: 2590 | AC6: 7 | AD6: 181 | AE6: 0 | AF6: 7 | AG6: 181 | AH6: 0 | AI6: 0 | AJ6: 0 | AK6: 0 | AL6: 0 | AM6: 0 | AN6: 0 | AO6: 0 | AP6: 0 | AQ6: 0 | AR6: 0 | AS6: 0 | AT6: 0 | AU6: 0 | AV6: 0 | AX6: 6520 | AY6: 1 | AZ6: 65.2 | BA6: 0 | BC6: 0 | BD6: 0 | BE6: 6520 | BF6: 0.256 | BG6: 16.7 | BH6: 0 | BJ6: 0 | BK6: 0 | BN6: 0 | BO6: 0 | BQ6: 0 | BR6: 0 | BS6: =J6+S6+Z6+AK6+AU6+BC6+BJ6 -> 684.6 | BT6: =G6+O6+W6+AI6+AM6+AO6+AQ6+AS6+AZ6+BG6 -> 1777.1 | BU6: =AG6 -> 181 | BV6: =AD6 -> 181 | BW6: 0 | BX6: =H6+P6+X6+BA6+BH6 -> 0 | BY6: 0 | BZ6: 0 | CA6: =BS6+BU6+BW6+BY6 -> 865.6 | CB6: =BT6+BV6+BX6+BZ6 -> 1958.1 | CC6: =CA6+CB6 -> 2823.7 | CD6: 21
A7: 6月 | B7: 中粮福临门上海 | C7: 陈芹 | D7: 511221198305230246 | E7: 6520 | F7: 16 | G7: 1043.2 | H7: 0 | I7: 8 | J7: 521.6 | K7: 0 | L7: 6520 | M7: 9.5 | O7: 619.4 | P7: 0 | Q7: 2 | S7: 130.4 | T7: 0 | U7: 6520 | V7: 0.5 | W7: 32.6 | X7: 0 | Y7: 0.5 | Z7: 32.6 | AA7: 0 | AB7: 2590 | AC7: 7 | AD7: 181 | AE7: 0 | AF7: 7 | AG7: 181 | AH7: 0 | AI7: 0 | AJ7: 0 | AK7: 0 | AL7: 0 | AM7: 0 | AN7: 0 | AO7: 0 | AP7: 0 | AQ7: 0 | AR7: 0 | AS7: 0 | AT7: 0 | AU7: 0 | AV7: 0 | AX7: 6520 | AY7: 1 | AZ7: 65.2 | BA7: 0 | BC7: 0 | BD7: 0 | BE7: 6520 | BF7: 0.256 | BG7: 16.7 | BH7: 0 | BJ7: 0 | BK7: 0 | BN7: 0 | BO7: 0 | BQ7: 0 | BR7: 0 | BS7: =J7+S7+Z7+AK7+AU7+BC7+BJ7 -> 684.6 | BT7: =G7+O7+W7+AI7+AM7+AO7+AQ7+AS7+AZ7+BG7 -> 1777.1 | BU7: =AG7 -> 181 | BV7: =AD7 -> 181 | BW7: 0 | BX7: =H7+P7+X7+BA7+BH7 -> 0 | BY7: 0 | BZ7: 0 | CA7: =BS7+BU7+BW7+BY7 -> 865.6 | CB7: =BT7+BV7+BX7+BZ7 -> 1958.1 | CC7: =CA7+CB7 -> 2823.7 | CD7: 21
A8: 6月 | B8: 中粮福临门上海 | C8: 邓辉 | D8: 652701197206262225 | BS8: =J8+S8+Z8+AK8+AU8+BC8+BJ8 -> 0 | BT8: =G8+O8+W8+AI8+AM8+AO8+AQ8+AS8+AZ8+BG8 -> 0 | BU8: =AG8 -> 0 | BV8: =AD8 -> 0 | BW8: 0 | BX8: =H8+P8+X8+BA8+BH8 -> 0 | BY8: 0 | BZ8: 0 | CA8: =BS8+BU8+BW8+BY8 -> 0 | CB8: =BT8+BV8+BX8+BZ8 -> 0 | CC8: =CA8+CB8 -> 0 | CD8: 0
A9: 6月 | B9: 中粮福临门上海 | C9: 东港 | D9: 210422198201031424 | E9: 6520 | F9: 16 | G9: 1043.2 | H9: 0 | I9: 8 | J9: 521.6 | K9: 0 | L9: 6520 | M9: 9.5 | O9: 619.4 | P9: 0 | Q9: 2 | S9: 130.4 | T9: 0 | U9: 6520 | V9: 0.5 | W9: 32.6 | X9: 0 | Y9: 0.5 | Z9: 32.6 | AA9: 0 | AB9: 2590 | AC9: 7 | AD9: 181 | AE9: 0 | AF9: 7 | AG9: 181 | AH9: 0 | AI9: 0 | AJ9: 0 | AK9: 0 | AL9: 0 | AM9: 0 | AN9: 0 | AO9: 0 | AP9: 0 | AQ9: 0 | AR9: 0 | AS9: 0 | AT9: 0 | AU9: 0 | AV9: 0 | AX9: 6520 | AY9: 1 | AZ9: 65.2 | BA9: 0 | BC9: 0 | BD9: 0 | BE9: 6520 | BF9: 0.256 | BG9: 16.7 | BH9: 0 | BJ9: 0 | BK9: 0 | BN9: 0 | BO9: 0 | BQ9: 0 | BR9: 0 | BS9: =J9+S9+Z9+AK9+AU9+BC9+BJ9 -> 684.6 | BT9: =G9+O9+W9+AI9+AM9+AO9+AQ9+AS9+AZ9+BG9 -> 1777.1 | BU9: =AG9 -> 181 | BV9: =AD9 -> 181 | BW9: 0 | BX9: =H9+P9+X9+BA9+BH9 -> 0 | BY9: 0 | BZ9: 0 | CA9: =BS9+BU9+BW9+BY9 -> 865.6 | CB9: =BT9+BV9+BX9+BZ9 -> 1958.1 | CC9: =CA9+CB9 -> 2823.7 | CD9: 21
A10: 6月 | B10: 中粮福临门上海 | C10: 范祖容 | D10: 51253319820521484X | E10: 6520 | F10: 16 | G10: 1043.2 | H10: 0 | I10: 8 | J10: 521.6 | K10: 0 | L10: 6520 | M10: 9.5 | O10: 619.4 | P10: 0 | Q10: 2 | S10: 130.4 | T10: 0 | U10: 6520 | V10: 0.5 | W10: 32.6 | X10: 0 | Y10: 0.5 | Z10: 32.6 | AA10: 0 | AB10: 2590 | AC10: 7 | AD10: 181 | AE10: 0 | AF10: 7 | AG10: 181 | AH10: 0 | AI10: 0 | AJ10: 0 | AK10: 0 | AL10: 0 | AM10: 0 | AN10: 0 | AO10: 0 | AP10: 0 | AQ10: 0 | AR10: 0 | AS10: 0 | AT10: 0 | AU10: 0 | AV10: 0 | AX10: 6520 | AY10: 1 | AZ10: 65.2 | BA10: 0 | BC10: 0 | BD10: 0 | BE10: 6520 | BF10: 0.256 | BG10: 16.7 | BH10: 0 | BJ10: 0 | BK10: 0 | BN10: 0 | BO10: 0 | BQ10: 0 | BR10: 0 | BS10: =J10+S10+Z10+AK10+AU10+BC10+BJ10 -> 684.6 | BT10: =G10+O10+W10+AI10+AM10+AO10+AQ10+AS10+AZ10+BG10 -> 1777.1 | BU10: =AG10 -> 181 | BV10: =AD10 -> 181 | BW10: 0 | BX10: =H10+P10+X10+BA10+BH10 -> 0 | BY10: 0 | BZ10: 0 | CA10: =BS10+BU10+BW10+BY10 -> 865.6 | CB10: =BT10+BV10+BX10+BZ10 -> 1958.1 | CC10: =CA10+CB10 -> 2823.7 | CD10: 21
A11: 6月 | B11: 中粮福临门上海 | C11: 戈艳青 | D11: 32082319780513524X | E11: 6520 | F11: 16 | G11: 1043.2 | H11: 0 | I11: 8 | J11: 521.6 | K11: 0 | L11: 6520 | M11: 9.5 | O11: 619.4 | P11: 0 | Q11: 2 | S11: 130.4 | T11: 0 | U11: 6520 | V11: 0.5 | W11: 32.6 | X11: 0 | Y11: 0.5 | Z11: 32.6 | AA11: 0 | AB11: 2590 | AC11: 7 | AD11: 181 | AE11: 0 | AF11: 7 | AG11: 181 | AH11: 0 | AI11: 0 | AJ11: 0 | AK11: 0 | AL11: 0 | AM11: 0 | AN11: 0 | AO11: 0 | AP11: 0 | AQ11: 0 | AR11: 0 | AS11: 0 | AT11: 0 | AU11: 0 | AV11: 0 | AX11: 6520 | AY11: 1 | AZ11: 65.2 | BA11: 0 | BC11: 0 | BD11: 0 | BE11: 6520 | BF11: 0.256 | BG11: 16.7 | BH11: 0 | BJ11: 0 | BK11: 0 | BN11: 0 | BO11: 0 | BQ11: 0 | BR11: 0 | BS11: =J11+S11+Z11+AK11+AU11+BC11+BJ11 -> 684.6 | BT11: =G11+O11+W11+AI11+AM11+AO11+AQ11+AS11+AZ11+BG11 -> 1777.1 | BU11: =AG11 -> 181 | BV11: =AD11 -> 181 | BW11: 0 | BX11: =H11+P11+X11+BA11+BH11 -> 0 | BY11: 0 | BZ11: 0 | CA11: =BS11+BU11+BW11+BY11 -> 865.6 | CB11: =BT11+BV11+BX11+BZ11 -> 1958.1 | CC11: =CA11+CB11 -> 2823.7 | CD11: 21
A12: 6月 | B12: 中粮福临门上海 | C12: 葛菊 | D12: 340421198104213042 | E12: 6520 | F12: 16 | G12: 1043.2 | H12: 0 | I12: 8 | J12: 521.6 | K12: 0 | L12: 6520 | M12: 9.5 | O12: 619.4 | P12: 0 | Q12: 2 | S12: 130.4 | T12: 0 | U12: 6520 | V12: 0.5 | W12: 32.6 | X12: 0 | Y12: 0.5 | Z12: 32.6 | AA12: 0 | AB12: 2590 | AC12: 7 | AD12: 181 | AE12: 0 | AF12: 7 | AG12: 181 | AH12: 0 | AI12: 0 | AJ12: 0 | AK12: 0 | AL12: 0 | AM12: 0 | AN12: 0 | AO12: 0 | AP12: 0 | AQ12: 0 | AR12: 0 | AS12: 0 | AT12: 0 | AU12: 0 | AV12: 0 | AX12: 6520 | AY12: 1 | AZ12: 65.2 | BA12: 0 | BC12: 0 | BD12: 0 | BE12: 6520 | BF12: 0.256 | BG12: 16.7 | BH12: 0 | BJ12: 0 | BK12: 0 | BN12: 0 | BO12: 0 | BQ12: 0 | BR12: 0 | BS12: =J12+S12+Z12+AK12+AU12+BC12+BJ12 -> 684.6 | BT12: =G12+O12+W12+AI12+AM12+AO12+AQ12+AS12+AZ12+BG12 -> 1777.1 | BU12: =AG12 -> 181 | BV12: =AD12 -> 181 | BW12: 0 | BX12: =H12+P12+X12+BA12+BH12 -> 0 | BY12: 0 | BZ12: 0 | CA12: =BS12+BU12+BW12+BY12 -> 865.6 | CB12: =BT12+BV12+BX12+BZ12 -> 1958.1 | CC12: =CA12+CB12 -> 2823.7 | CD12: 21
A13: 6月 | B13: 中粮福临门上海 | C13: 顾建凤 | D13: 310226197704023526 | E13: 6520 | F13: 16 | G13: 1043.2 | H13: 0 | I13: 8 | J13: 521.6 | K13: 0 | L13: 6520 | M13: 9.5 | O13: 619.4 | P13: 0 | Q13: 2 | S13: 130.4 | T13: 0 | U13: 6520 | V13: 0.5 | W13: 32.6 | X13: 0 | Y13: 0.5 | Z13: 32.6 | AA13: 0 | AB13: 2590 | AC13: 7 | AD13: 181 | AE13: 0 | AF13: 7 | AG13: 181 | AH13: 0 | AI13: 0 | AJ13: 0 | AK13: 0 | AL13: 0 | AM13: 0 | AN13: 0 | AO13: 0 | AP13: 0 | AQ13: 0 | AR13: 0 | AS13: 0 | AT13: 0 | AU13: 0 | AV13: 0 | AX13: 6520 | AY13: 1 | AZ13: 65.2 | BA13: 0 | BC13: 0 | BD13: 0 | BE13: 6520 | BF13: 0.256 | BG13: 16.7 | BH13: 0 | BJ13: 0 | BK13: 0 | BN13: 0 | BO13: 0 | BQ13: 0 | BR13: 0 | BS13: =J13+S13+Z13+AK13+AU13+BC13+BJ13 -> 684.6 | BT13: =G13+O13+W13+AI13+AM13+AO13+AQ13+AS13+AZ13+BG13 -> 1777.1 | BU13: =AG13 -> 181 | BV13: =AD13 -> 181 | BW13: 0 | BX13: =H13+P13+X13+BA13+BH13 -> 0 | BY13: 0 | BZ13: 0 | CA13: =BS13+BU13+BW13+BY13 -> 865.6 | CB13: =BT13+BV13+BX13+BZ13 -> 1958.1 | CC13: =CA13+CB13 -> 2823.7 | CD13: 21
A14: 6月 | B14: 中粮福临门上海 | C14: 顾永芳 | D14: 31022819730201382X | E14: 6520 | F14: 16 | G14: 1043.2 | H14: 0 | I14: 8 | J14: 521.6 | K14: 0 | L14: 6520 | M14: 9.5 | O14: 619.4 | P14: 0 | Q14: 2 | S14: 130.4 | T14: 0 | U14: 6520 | V14: 0.5 | W14: 32.6 | X14: 0 | Y14: 0.5 | Z14: 32.6 | AA14: 0 | AB14: 2590 | AC14: 7 | AD14: 181 | AE14: 0 | AF14: 7 | AG14: 181 | AH14: 0 | AI14: 0 | AJ14: 0 | AK14: 0 | AL14: 0 | AM14: 0 | AN14: 0 | AO14: 0 | AP14: 0 | AQ14: 0 | AR14: 0 | AS14: 0 | AT14: 0 | AU14: 0 | AV14: 0 | AX14: 6520 | AY14: 1 | AZ14: 65.2 | BA14: 0 | BC14: 0 | BD14: 0 | BE14: 6520 | BF14: 0.256 | BG14: 16.7 | BH14: 0 | BJ14: 0 | BK14: 0 | BN14: 0 | BO14: 0 | BQ14: 0 | BR14: 0 | BS14: =J14+S14+Z14+AK14+AU14+BC14+BJ14 -> 684.6 | BT14: =G14+O14+W14+AI14+AM14+AO14+AQ14+AS14+AZ14+BG14 -> 1777.1 | BU14: =AG14 -> 181 | BV14: =AD14 -> 181 | BW14: 0 | BX14: =H14+P14+X14+BA14+BH14 -> 0 | BY14: 0 | BZ14: 0 | CA14: =BS14+BU14+BW14+BY14 -> 865.6 | CB14: =BT14+BV14+BX14+BZ14 -> 1958.1 | CC14: =CA14+CB14 -> 2823.7 | CD14: 21
A15: 6月 | B15: 中粮福临门上海 | C15: 管兵娥 | D15: 362329198211245745 | E15: 6520 | F15: 16 | G15: 1043.2 | H15: 0 | I15: 8 | J15: 521.6 | K15: 0 | L15: 6520 | M15: 9.5 | O15: 619.4 | P15: 0 | Q15: 2 | S15: 130.4 | T15: 0 | U15: 6520 | V15: 0.5 | W15: 32.6 | X15: 0 | Y15: 0.5 | Z15: 32.6 | AA15: 0 | AB15: 2590 | AC15: 7 | AD15: 181 | AE15: 0 | AF15: 7 | AG15: 181 | AH15: 0 | AI15: 0 | AJ15: 0 | AK15: 0 | AL15: 0 | AM15: 0 | AN15: 0 | AO15: 0 | AP15: 0 | AQ15: 0 | AR15: 0 | AS15: 0 | AT15: 0 | AU15: 0 | AV15: 0 | AX15: 6520 | AY15: 1 | AZ15: 65.2 | BA15: 0 | BC15: 0 | BD15: 0 | BE15: 6520 | BF15: 0.256 | BG15: 16.7 | BH15: 0 | BJ15: 0 | BK15: 0 | BN15: 0 | BO15: 0 | BQ15: 0 | BR15: 0 | BS15: =J15+S15+Z15+AK15+AU15+BC15+BJ15 -> 684.6 | BT15: =G15+O15+W15+AI15+AM15+AO15+AQ15+AS15+AZ15+BG15 -> 1777.1 | BU15: =AG15 -> 181 | BV15: =AD15 -> 181 | BW15: 0 | BX15: =H15+P15+X15+BA15+BH15 -> 0 | BY15: 0 | BZ15: 0 | CA15: =BS15+BU15+BW15+BY15 -> 865.6 | CB15: =BT15+BV15+BX15+BZ15 -> 1958.1 | CC15: =CA15+CB15 -> 2823.7 | CD15: 21
A16: 6月 | B16: 中粮福临门上海 | C16: 郭胜霞 | D16: 320925197905205821 | E16: 6520 | F16: 16 | G16: 1043.2 | H16: 0 | I16: 8 | J16: 521.6 | K16: 0 | L16: 6520 | M16: 9.5 | O16: 619.4 | P16: 0 | Q16: 2 | S16: 130.4 | T16: 0 | U16: 6520 | V16: 0.5 | W16: 32.6 | X16: 0 | Y16: 0.5 | Z16: 32.6 | AA16: 0 | AB16: 2590 | AC16: 7 | AD16: 181 | AE16: 0 | AF16: 7 | AG16: 181 | AH16: 0 | AI16: 0 | AJ16: 0 | AK16: 0 | AL16: 0 | AM16: 0 | AN16: 0 | AO16: 0 | AP16: 0 | AQ16: 0 | AR16: 0 | AS16: 0 | AT16: 0 | AU16: 0 | AV16: 0 | AX16: 6520 | AY16: 1 | AZ16: 65.2 | BA16: 0 | BC16: 0 | BD16: 0 | BE16: 6520 | BF16: 0.256 | BG16: 16.7 | BH16: 0 | BJ16: 0 | BK16: 0 | BN16: 0 | BO16: 0 | BQ16: 0 | BR16: 0 | BS16: =J16+S16+Z16+AK16+AU16+BC16+BJ16 -> 684.6 | BT16: =G16+O16+W16+AI16+AM16+AO16+AQ16+AS16+AZ16+BG16 -> 1777.1 | BU16: =AG16 -> 181 | BV16: =AD16 -> 181 | BW16: 0 | BX16: =H16+P16+X16+BA16+BH16 -> 0 | BY16: 0 | BZ16: 0 | CA16: =BS16+BU16+BW16+BY16 -> 865.6 | CB16: =BT16+BV16+BX16+BZ16 -> 1958.1 | CC16: =CA16+CB16 -> 2823.7 | CD16: 21
A17: 6月 | B17: 中粮福临门上海 | C17: 过苗苗 | D17: 341224198812281328 | E17: 6520 | F17: 16 | G17: 1043.2 | H17: 0 | I17: 8 | J17: 521.6 | K17: 0 | L17: 6520 | M17: 9.5 | O17: 619.4 | P17: 0 | Q17: 2 | S17: 130.4 | T17: 0 | U17: 6520 | V17: 0.5 | W17: 32.6 | X17: 0 | Y17: 0.5 | Z17: 32.6 | AA17: 0 | AB17: 2590 | AC17: 7 | AD17: 181 | AE17: 0 | AF17: 7 | AG17: 181 | AH17: 0 | AI17: 0 | AJ17: 0 | AK17: 0 | AL17: 0 | AM17: 0 | AN17: 0 | AO17: 0 | AP17: 0 | AQ17: 0 | AR17: 0 | AS17: 0 | AT17: 0 | AU17: 0 | AV17: 0 | AX17: 6520 | AY17: 1 | AZ17: 65.2 | BA17: 0 | BC17: 0 | BD17: 0 | BE17: 6520 | BF17: 0.256 | BG17: 16.7 | BH17: 0 | BJ17: 0 | BK17: 0 | BN17: 0 | BO17: 0 | BQ17: 0 | BR17: 0 | BS17: =J17+S17+Z17+AK17+AU17+BC17+BJ17 -> 684.6 | BT17: =G17+O17+W17+AI17+AM17+AO17+AQ17+AS17+AZ17+BG17 -> 1777.1 | BU17: =AG17 -> 181 | BV17: =AD17 -> 181 | BW17: 0 | BX17: =H17+P17+X17+BA17+BH17 -> 0 | BY17: 0 | BZ17: 0 | CA17: =BS17+BU17+BW17+BY17 -> 865.6 | CB17: =BT17+BV17+BX17+BZ17 -> 1958.1 | CC17: =CA17+CB17 -> 2823.7 | CD17: 21
A18: 6月 | B18: 中粮福临门上海 | C18: 洪艳 | D18: 342422197308163968 | E18: 6520 | F18: 16 | G18: 1043.2 | H18: 0 | I18: 8 | J18: 521.6 | K18: 0 | L18: 6520 | M18: 9.5 | O18: 619.4 | P18: 0 | Q18: 2 | S18: 130.4 | T18: 0 | U18: 6520 | V18: 0.5 | W18: 32.6 | X18: 0 | Y18: 0.5 | Z18: 32.6 | AA18: 0 | AB18: 2590 | AC18: 7 | AD18: 181 | AE18: 0 | AF18: 7 | AG18: 181 | AH18: 0 | AI18: 0 | AJ18: 0 | AK18: 0 | AL18: 0 | AM18: 0 | AN18: 0 | AO18: 0 | AP18: 0 | AQ18: 0 | AR18: 0 | AS18: 0 | AT18: 0 | AU18: 0 | AV18: 0 | AX18: 6520 | AY18: 1 | AZ18: 65.2 | BA18: 0 | BC18: 0 | BD18: 0 | BE18: 6520 | BF18: 0.256 | BG18: 16.7 | BH18: 0 | BJ18: 0 | BK18: 0 | BN18: 0 | BO18: 0 | BQ18: 0 | BR18: 0 | BS18: =J18+S18+Z18+AK18+AU18+BC18+BJ18 -> 684.6 | BT18: =G18+O18+W18+AI18+AM18+AO18+AQ18+AS18+AZ18+BG18 -> 1777.1 | BU18: =AG18 -> 181 | BV18: =AD18 -> 181 | BW18: 0 | BX18: =H18+P18+X18+BA18+BH18 -> 0 | BY18: 0 | BZ18: 0 | CA18: =BS18+BU18+BW18+BY18 -> 865.6 | CB18: =BT18+BV18+BX18+BZ18 -> 1958.1 | CC18: =CA18+CB18 -> 2823.7 | CD18: 21
A19: 6月 | B19: 中粮福临门上海 | C19: 候广勤 | D19: 341224197408091341 | E19: 6520 | F19: 16 | G19: 1043.2 | H19: 0 | I19: 8 | J19: 521.6 | K19: 0 | L19: 6520 | M19: 9.5 | O19: 619.4 | P19: 0 | Q19: 2 | S19: 130.4 | T19: 0 | U19: 6520 | V19: 0.5 | W19: 32.6 | X19: 0 | Y19: 0.5 | Z19: 32.6 | AA19: 0 | AB19: 2590 | AC19: 7 | AD19: 181 | AE19: 0 | AF19: 7 | AG19: 181 | AH19: 0 | AI19: 0 | AJ19: 0 | AK19: 0 | AL19: 0 | AM19: 0 | AN19: 0 | AO19: 0 | AP19: 0 | AQ19: 0 | AR19: 0 | AS19: 0 | AT19: 0 | AU19: 0 | AV19: 0 | AX19: 6520 | AY19: 1 | AZ19: 65.2 | BA19: 0 | BC19: 0 | BD19: 0 | BE19: 6520 | BF19: 0.256 | BG19: 16.7 | BH19: 0 | BJ19: 0 | BK19: 0 | BN19: 0 | BO19: 0 | BQ19: 0 | BR19: 0 | BS19: =J19+S19+Z19+AK19+AU19+BC19+BJ19 -> 684.6 | BT19: =G19+O19+W19+AI19+AM19+AO19+AQ19+AS19+AZ19+BG19 -> 1777.1 | BU19: =AG19 -> 181 | BV19: =AD19 -> 181 | BW19: 0 | BX19: =H19+P19+X19+BA19+BH19 -> 0 | BY19: 0 | BZ19: 0 | CA19: =BS19+BU19+BW19+BY19 -> 865.6 | CB19: =BT19+BV19+BX19+BZ19 -> 1958.1 | CC19: =CA19+CB19 -> 2823.7 | CD19: 21
A20: 6月 | B20: 中粮福临门上海 | C20: 黄维血 | D20: 511022197312203810 | E20: 6520 | F20: 16 | G20: 1043.2 | H20: 0 | I20: 8 | J20: 521.6 | K20: 0 | L20: 6520 | M20: 9.5 | O20: 619.4 | P20: 0 | Q20: 2 | S20: 130.4 | T20: 0 | U20: 6520 | V20: 0.5 | W20: 32.6 | X20: 0 | Y20: 0.5 | Z20: 32.6 | AA20: 0 | AB20: 2590 | AC20: 7 | AD20: 181 | AE20: 0 | AF20: 7 | AG20: 181 | AH20: 0 | AI20: 0 | AJ20: 0 | AK20: 0 | AL20: 0 | AM20: 0 | AN20: 0 | AO20: 0 | AP20: 0 | AQ20: 0 | AR20: 0 | AS20: 0 | AT20: 0 | AU20: 0 | AV20: 0 | AX20: 6520 | AY20: 1 | AZ20: 65.2 | BA20: 0 | BC20: 0 | BD20: 0 | BE20: 6520 | BF20: 0.256 | BG20: 16.7 | BH20: 0 | BJ20: 0 | BK20: 0 | BN20: 0 | BO20: 0 | BQ20: 0 | BR20: 0 | BS20: =J20+S20+Z20+AK20+AU20+BC20+BJ20 -> 684.6 | BT20: =G20+O20+W20+AI20+AM20+AO20+AQ20+AS20+AZ20+BG20 -> 1777.1 | BU20: =AG20 -> 181 | BV20: =AD20 -> 181 | BW20: 0 | BX20: =H20+P20+X20+BA20+BH20 -> 0 | BY20: 0 | BZ20: 0 | CA20: =BS20+BU20+BW20+BY20 -> 865.6 | CB20: =BT20+BV20+BX20+BZ20 -> 1958.1 | CC20: =CA20+CB20 -> 2823.7 | CD20: 21
... A62: 6月 | B62: 中粮福临门上海 | C62: 张继秀 | D62: 522130198205262420 | E62: 6520 | F62: 16 | G62: 1043.2 | H62: 0 | I62: 8 | J62: 521.6 | K62: 0 | L62: 6520 | M62: 9.5 | O62: 619.4 | P62: 0 | Q62: 2 | S62: 130.4 | T62: 0 | U62: 6520 | V62: 0.5 | W62: 32.6 | X62: 0 | Y62: 0.5 | Z62: 32.6 | AA62: 0 | AB62: 2590 | AC62: 7 | AD62: 181 | AE62: 0 | AF62: 7 | AG62: 181 | AH62: 0 | AI62: 0 | AJ62: 0 | AK62: 0 | AL62: 0 | AM62: 0 | AN62: 0 | AO62: 0 | AP62: 0 | AQ62: 0 | AR62: 0 | AS62: 0 | AT62: 0 | AU62: 0 | AV62: 0 | AX62: 6520 | AY62: 1 | AZ62: 65.2 | BA62: 0 | BC62: 0 | BD62: 0 | BE62: 6520 | BF62: 0.256 | BG62: 16.7 | BH62: 0 | BJ62: 0 | BK62: 0 | BN62: 0 | BO62: 0 | BQ62: 0 | BR62: 0 | BS62: =J62+S62+Z62+AK62+AU62+BC62+BJ62 -> 684.6 | BT62: =G62+O62+W62+AI62+AM62+AO62+AQ62+AS62+AZ62+BG62 -> 1777.1 | BU62: =AG62 -> 181 | BV62: =AD62 -> 181 | BW62: 0 | BX62: =H62+P62+X62+BA62+BH62 -> 0 | BY62: 0 | BZ62: 0 | CA62: =BS62+BU62+BW62+BY62 -> 865.6 | CB62: =BT62+BV62+BX62+BZ62 -> 1958.1 | CC62: =CA62+CB62 -> 2823.7 | CD62: 21
A63: 6月 | B63: 中粮福临门上海 | C63: 张梅芳 | D63: 350524197902232522 | BS63: =J63+S63+Z63+AK63+AU63+BC63+BJ63 -> 0 | BT63: =G63+O63+W63+AI63+AM63+AO63+AQ63+AS63+AZ63+BG63 -> 0 | BU63: =AG63 -> 0 | BV63: =AD63 -> 0 | BW63: 0 | BX63: =H63+P63+X63+BA63+BH63 -> 0 | BY63: 0 | BZ63: 0 | CA63: =BS63+BU63+BW63+BY63 -> 0 | CB63: =BT63+BV63+BX63+BZ63 -> 0 | CC63: =CA63+CB63 -> 0 | CD63: 21
A64: 6月 | B64: 中粮福临门上海 | C64: 张学良 | D64: 34232619651217271X | E64: 6520 | F64: 16 | G64: 1043.2 | H64: 0 | I64: 8 | J64: 521.6 | K64: 0 | L64: 6520 | M64: 9.5 | O64: 619.4 | P64: 0 | Q64: 2 | S64: 130.4 | T64: 0 | U64: 6520 | V64: 0.5 | W64: 32.6 | X64: 0 | Y64: 0.5 | Z64: 32.6 | AA64: 0 | AB64: 2590 | AC64: 7 | AD64: 181 | AE64: 0 | AF64: 7 | AG64: 181 | AH64: 0 | AI64: 0 | AJ64: 0 | AK64: 0 | AL64: 0 | AM64: 0 | AN64: 0 | AO64: 0 | AP64: 0 | AQ64: 0 | AR64: 0 | AS64: 0 | AT64: 0 | AU64: 0 | AV64: 0 | AX64: 6520 | AY64: 1 | AZ64: 65.2 | BA64: 0 | BC64: 0 | BD64: 0 | BE64: 6520 | BF64: 0.256 | BG64: 16.7 | BH64: 0 | BJ64: 0 | BK64: 0 | BN64: 0 | BO64: 0 | BQ64: 0 | BR64: 0 | BS64: =J64+S64+Z64+AK64+AU64+BC64+BJ64 -> 684.6 | BT64: =G64+O64+W64+AI64+AM64+AO64+AQ64+AS64+AZ64+BG64 -> 1777.1 | BU64: =AG64 -> 181 | BV64: =AD64 -> 181 | BW64: 0 | BX64: =H64+P64+X64+BA64+BH64 -> 0 | BY64: 0 | BZ64: 0 | CA64: =BS64+BU64+BW64+BY64 -> 865.6 | CB64: =BT64+BV64+BX64+BZ64 -> 1958.1 | CC64: =CA64+CB64 -> 2823.7 | CD64: 21
A65: 6月 | B65: 中粮福临门上海 | C65: 赵荣 | D65: 412823196707112887 | E65: 6520 | F65: 16 | G65: 1043.2 | H65: 0 | I65: 8 | J65: 521.6 | K65: 0 | L65: 6520 | M65: 9.5 | O65: 619.4 | P65: 0 | Q65: 2 | S65: 130.4 | T65: 0 | U65: 6520 | V65: 0.5 | W65: 32.6 | X65: 0 | Y65: 0.5 | Z65: 32.6 | AA65: 0 | AB65: 2590 | AC65: 7 | AD65: 181 | AE65: 0 | AF65: 7 | AG65: 181 | AH65: 0 | AI65: 0 | AJ65: 0 | AK65: 0 | AL65: 0 | AM65: 0 | AN65: 0 | AO65: 0 | AP65: 0 | AQ65: 0 | AR65: 0 | AS65: 0 | AT65: 0 | AU65: 0 | AV65: 0 | AX65: 6520 | AY65: 1 | AZ65: 65.2 | BA65: 0 | BC65: 0 | BD65: 0 | BE65: 6520 | BF65: 0.256 | BG65: 16.7 | BH65: 0 | BJ65: 0 | BK65: 0 | BN65: 0 | BO65: 0 | BQ65: 0 | BR65: 0 | BS65: =J65+S65+Z65+AK65+AU65+BC65+BJ65 -> 684.6 | BT65: =G65+O65+W65+AI65+AM65+AO65+AQ65+AS65+AZ65+BG65 -> 1777.1 | BU65: =AG65 -> 181 | BV65: =AD65 -> 181 | BW65: 0 | BX65: =H65+P65+X65+BA65+BH65 -> 0 | BY65: 0 | BZ65: 0 | CA65: =BS65+BU65+BW65+BY65 -> 865.6 | CB65: =BT65+BV65+BX65+BZ65 -> 1958.1 | CC65: =CA65+CB65 -> 2823.7 | CD65: 21
A66: 6月 | B66: 中粮福临门上海 | C66: 赵志炜 | D66: 340826197611081813 | E66: 6520 | F66: 16 | G66: 1043.2 | H66: 0 | I66: 8 | J66: 521.6 | K66: 0 | L66: 6520 | M66: 9.5 | O66: 619.4 | P66: 0 | Q66: 2 | S66: 130.4 | T66: 0 | U66: 6520 | V66: 0.5 | W66: 32.6 | X66: 0 | Y66: 0.5 | Z66: 32.6 | AA66: 0 | AB66: 2590 | AC66: 7 | AD66: 181 | AE66: 0 | AF66: 7 | AG66: 181 | AH66: 0 | AI66: 0 | AJ66: 0 | AK66: 0 | AL66: 0 | AM66: 0 | AN66: 0 | AO66: 0 | AP66: 0 | AQ66: 0 | AR66: 0 | AS66: 0 | AT66: 0 | AU66: 0 | AV66: 0 | AX66: 6520 | AY66: 1 | AZ66: 65.2 | BA66: 0 | BC66: 0 | BD66: 0 | BE66: 6520 | BF66: 0.256 | BG66: 16.7 | BH66: 0 | BJ66: 0 | BK66: 0 | BN66: 0 | BO66: 0 | BQ66: 0 | BR66: 0 | BS66: =J66+S66+Z66+AK66+AU66+BC66+BJ66 -> 684.6 | BT66: =G66+O66+W66+AI66+AM66+AO66+AQ66+AS66+AZ66+BG66 -> 1777.1 | BU66: =AG66 -> 181 | BV66: =AD66 -> 181 | BW66: 0 | BX66: =H66+P66+X66+BA66+BH66 -> 0 | BY66: 0 | BZ66: 0 | CA66: =BS66+BU66+BW66+BY66 -> 865.6 | CB66: =BT66+BV66+BX66+BZ66 -> 1958.1 | CC66: =CA66+CB66 -> 2823.7 | CD66: 21
A67: 6月 | B67: 中粮福临门上海 | C67: 周菊 | D67: 320626197312144445 | E67: 6520 | F67: 16 | G67: 1043.2 | H67: 0 | I67: 8 | J67: 521.6 | K67: 0 | L67: 6520 | M67: 9.5 | O67: 619.4 | P67: 0 | Q67: 2 | S67: 130.4 | T67: 0 | U67: 6520 | V67: 0.5 | W67: 32.6 | X67: 0 | Y67: 0.5 | Z67: 32.6 | AA67: 0 | AB67: 2590 | AC67: 7 | AD67: 181 | AE67: 0 | AF67: 7 | AG67: 181 | AH67: 0 | AI67: 0 | AJ67: 0 | AK67: 0 | AL67: 0 | AM67: 0 | AN67: 0 | AO67: 0 | AP67: 0 | AQ67: 0 | AR67: 0 | AS67: 0 | AT67: 0 | AU67: 0 | AV67: 0 | AX67: 6520 | AY67: 1 | AZ67: 65.2 | BA67: 0 | BC67: 0 | BD67: 0 | BE67: 6520 | BF67: 0.256 | BG67: 16.7 | BH67: 0 | BJ67: 0 | BK67: 0 | BN67: 0 | BO67: 0 | BQ67: 0 | BR67: 0 | BS67: =J67+S67+Z67+AK67+AU67+BC67+BJ67 -> 684.6 | BT67: =G67+O67+W67+AI67+AM67+AO67+AQ67+AS67+AZ67+BG67 -> 1777.1 | BU67: =AG67 -> 181 | BV67: =AD67 -> 181 | BW67: 0 | BX67: =H67+P67+X67+BA67+BH67 -> 0 | BY67: 0 | BZ67: 0 | CA67: =BS67+BU67+BW67+BY67 -> 865.6 | CB67: =BT67+BV67+BX67+BZ67 -> 1958.1 | CC67: =CA67+CB67 -> 2823.7 | CD67: 21
A68: 6月 | B68: 中粮福临门上海 | C68: 朱大玉 | D68: 341224197303209243 | E68: 6520 | F68: 16 | G68: 1043.2 | H68: 0 | I68: 8 | J68: 521.6 | K68: 0 | L68: 6520 | M68: 9.5 | O68: 619.4 | P68: 0 | Q68: 2 | S68: 130.4 | T68: 0 | U68: 6520 | V68: 0.5 | W68: 32.6 | X68: 0 | Y68: 0.5 | Z68: 32.6 | AA68: 0 | AB68: 2590 | AC68: 7 | AD68: 181 | AE68: 0 | AF68: 7 | AG68: 181 | AH68: 0 | AI68: 0 | AJ68: 0 | AK68: 0 | AL68: 0 | AM68: 0 | AN68: 0 | AO68: 0 | AP68: 0 | AQ68: 0 | AR68: 0 | AS68: 0 | AT68: 0 | AU68: 0 | AV68: 0 | AX68: 6520 | AY68: 1 | AZ68: 65.2 | BA68: 0 | BC68: 0 | BD68: 0 | BE68: 6520 | BF68: 0.256 | BG68: 16.7 | BH68: 0 | BJ68: 0 | BK68: 0 | BN68: 0 | BO68: 0 | BQ68: 0 | BR68: 0 | BS68: =J68+S68+Z68+AK68+AU68+BC68+BJ68 -> 684.6 | BT68: =G68+O68+W68+AI68+AM68+AO68+AQ68+AS68+AZ68+BG68 -> 1777.1 | BU68: =AG68 -> 181 | BV68: =AD68 -> 181 | BW68: 0 | BX68: =H68+P68+X68+BA68+BH68 -> 0 | BY68: 0 | BZ68: 0 | CA68: =BS68+BU68+BW68+BY68 -> 865.6 | CB68: =BT68+BV68+BX68+BZ68 -> 1958.1 | CC68: =CA68+CB68 -> 2823.7 | CD68: 21
A69: 6月 | B69: 中粮福临门上海 | C69: 朱国丽 | D69: 342423197506147180 | E69: 6520 | F69: 16 | G69: 1043.2 | H69: 0 | I69: 8 | J69: 521.6 | K69: 0 | L69: 6520 | M69: 9.5 | O69: 619.4 | P69: 0 | Q69: 2 | S69: 130.4 | T69: 0 | U69: 6520 | V69: 0.5 | W69: 32.6 | X69: 0 | Y69: 0.5 | Z69: 32.6 | AA69: 0 | AB69: 2590 | AC69: 7 | AD69: 181 | AE69: 0 | AF69: 7 | AG69: 181 | AH69: 0 | AI69: 0 | AJ69: 0 | AK69: 0 | AL69: 0 | AM69: 0 | AN69: 0 | AO69: 0 | AP69: 0 | AQ69: 0 | AR69: 0 | AS69: 0 | AT69: 0 | AU69: 0 | AV69: 0 | AX69: 6520 | AY69: 1 | AZ69: 65.2 | BA69: 0 | BC69: 0 | BD69: 0 | BE69: 6520 | BF69: 0.256 | BG69: 16.7 | BH69: 0 | BJ69: 0 | BK69: 0 | BN69: 0 | BO69: 0 | BQ69: 0 | BR69: 0 | BS69: =J69+S69+Z69+AK69+AU69+BC69+BJ69 -> 684.6 | BT69: =G69+O69+W69+AI69+AM69+AO69+AQ69+AS69+AZ69+BG69 -> 1777.1 | BU69: =AG69 -> 181 | BV69: =AD69 -> 181 | BW69: 0 | BX69: =H69+P69+X69+BA69+BH69 -> 0 | BY69: 0 | BZ69: 0 | CA69: =BS69+BU69+BW69+BY69 -> 865.6 | CB69: =BT69+BV69+BX69+BZ69 -> 1958.1 | CC69: =CA69+CB69 -> 2823.7 | CD69: 21
A70: 6月 | B70: 中粮福临门上海 | C70: 宗霞 | D70: 413021197503305029 | E70: 6520 | F70: 16 | G70: 1043.2 | H70: 0 | I70: 8 | J70: 521.6 | K70: 0 | L70: 6520 | M70: 9.5 | O70: 619.4 | P70: 0 | Q70: 2 | S70: 130.4 | T70: 0 | U70: 6520 | V70: 0.5 | W70: 32.6 | X70: 0 | Y70: 0.5 | Z70: 32.6 | AA70: 0 | AB70: 2590 | AC70: 7 | AD70: 181 | AE70: 0 | AF70: 7 | AG70: 181 | AH70: 0 | AI70: 0 | AJ70: 0 | AK70: 0 | AL70: 0 | AM70: 0 | AN70: 0 | AO70: 0 | AP70: 0 | AQ70: 0 | AR70: 0 | AS70: 0 | AT70: 0 | AU70: 0 | AV70: 0 | AX70: 6520 | AY70: 1 | AZ70: 65.2 | BA70: 0 | BC70: 0 | BD70: 0 | BE70: 6520 | BF70: 0.256 | BG70: 16.7 | BH70: 0 | BJ70: 0 | BK70: 0 | BN70: 0 | BO70: 0 | BQ70: 0 | BR70: 0 | BS70: =J70+S70+Z70+AK70+AU70+BC70+BJ70 -> 684.6 | BT70: =G70+O70+W70+AI70+AM70+AO70+AQ70+AS70+AZ70+BG70 -> 1777.1 | BU70: =AG70 -> 181 | BV70: =AD70 -> 181 | BW70: 0 | BX70: =H70+P70+X70+BA70+BH70 -> 0 | BY70: 0 | BZ70: 0 | CA70: =BS70+BU70+BW70+BY70 -> 865.6 | CB70: =BT70+BV70+BX70+BZ70 -> 1958.1 | CC70: =CA70+CB70 -> 2823.7 | CD70: 21
A71: 6月 | B71: 中粮福临门上海 | C71: 晏章翠 | D71: 342322196810135823 | E71: 6520 | F71: 16 | G71: 1043.2 | H71: 0 | I71: 8 | J71: 521.6 | K71: 0 | L71: 6520 | M71: 9.5 | O71: 619.4 | P71: 0 | Q71: 2 | S71: 130.4 | T71: 0 | U71: 6520 | V71: 0.5 | W71: 32.6 | X71: 0 | Y71: 0.5 | Z71: 32.6 | AA71: 0 | AB71: 2590 | AC71: 7 | AD71: 181 | AE71: 0 | AF71: 7 | AG71: 181 | AH71: 0 | AI71: 0 | AJ71: 0 | AK71: 0 | AL71: 0 | AM71: 0 | AN71: 0 | AO71: 0 | AP71: 0 | AQ71: 0 | AR71: 0 | AS71: 0 | AT71: 0 | AU71: 0 | AV71: 0 | AX71: 6520 | AY71: 1 | AZ71: 65.2 | BA71: 0 | BC71: 0 | BD71: 0 | BE71: 6520 | BF71: 0.256 | BG71: 16.7 | BH71: 0 | BJ71: 0 | BK71: 0 | BN71: 0 | BO71: 0 | BQ71: 0 | BR71: 0 | BS71: =J71+S71+Z71+AK71+AU71+BC71+BJ71 -> 684.6 | BT71: =G71+O71+W71+AI71+AM71+AO71+AQ71+AS71+AZ71+BG71 -> 1777.1 | BU71: =AG71 -> 181 | BV71: =AD71 -> 181 | BW71: 0 | BX71: =H71+P71+X71+BA71+BH71 -> 0 | BY71: 0 | BZ71: 0 | CA71: =BS71+BU71+BW71+BY71 -> 865.6 | CB71: =BT71+BV71+BX71+BZ71 -> 1958.1 | CC71: =CA71+CB71 -> 2823.7 | CD71: 21
A72: 6月 | B72: 中粮福临门上海 | C72: 顾雅芳 | D72: 310222197410262024 | E72: 6520 | F72: 16 | G72: 1043.2 | H72: 0 | I72: 8 | J72: 521.6 | K72: 0 | L72: 6520 | M72: 9.5 | O72: 619.4 | P72: 0 | Q72: 2 | S72: 130.4 | T72: 0 | U72: 6520 | V72: 0.5 | W72: 32.6 | X72: 0 | Y72: 0.5 | Z72: 32.6 | AA72: 0 | AB72: 2590 | AC72: 7 | AD72: 181 | AE72: 0 | AF72: 7 | AG72: 181 | AH72: 0 | AI72: 0 | AJ72: 0 | AK72: 0 | AL72: 0 | AM72: 0 | AN72: 0 | AO72: 0 | AP72: 0 | AQ72: 0 | AR72: 0 | AS72: 0 | AT72: 0 | AU72: 0 | AV72: 0 | AX72: 6520 | AY72: 1 | AZ72: 65.2 | BA72: 0 | BC72: 0 | BD72: 0 | BE72: 6520 | BF72: 0.256 | BG72: 16.7 | BH72: 0 | BJ72: 0 | BK72: 0 | BN72: 0 | BO72: 0 | BQ72: 0 | BR72: 0 | BS72: =J72+S72+Z72+AK72+AU72+BC72+BJ72 -> 684.6 | BT72: =G72+O72+W72+AI72+AM72+AO72+AQ72+AS72+AZ72+BG72 -> 1777.1 | BU72: =AG72 -> 181 | BV72: =AD72 -> 181 | BW72: 0 | BX72: =H72+P72+X72+BA72+BH72 -> 0 | BY72: 0 | BZ72: 0 | CA72: =BS72+BU72+BW72+BY72 -> 865.6 | CB72: =BT72+BV72+BX72+BZ72 -> 1958.1 | CC72: =CA72+CB72 -> 2823.7 | CD72: 21
A73: 6月 | B73: 中粮福临门上海 | C73: 刘会兰 | D73: 36012119790812198X | E73: 6520 | F73: 16 | G73: 1043.2 | H73: 0 | I73: 8 | J73: 521.6 | K73: 0 | L73: 6520 | M73: 9.5 | O73: 619.4 | P73: 0 | Q73: 2 | S73: 130.4 | T73: 0 | U73: 6520 | V73: 0.5 | W73: 32.6 | X73: 0 | Y73: 0.5 | Z73: 32.6 | AA73: 0 | AB73: 2590 | AC73: 7 | AD73: 181 | AE73: 0 | AF73: 7 | AG73: 181 | AH73: 0 | AI73: 0 | AJ73: 0 | AK73: 0 | AL73: 0 | AM73: 0 | AN73: 0 | AO73: 0 | AP73: 0 | AQ73: 0 | AR73: 0 | AS73: 0 | AT73: 0 | AU73: 0 | AV73: 0 | AX73: 6520 | AY73: 1 | AZ73: 65.2 | BA73: 0 | BC73: 0 | BD73: 0 | BE73: 6520 | BF73: 0.256 | BG73: 16.7 | BH73: 0 | BJ73: 0 | BK73: 0 | BN73: 0 | BO73: 0 | BQ73: 0 | BR73: 0 | BS73: =J73+S73+Z73+AK73+AU73+BC73+BJ73 -> 684.6 | BT73: =G73+O73+W73+AI73+AM73+AO73+AQ73+AS73+AZ73+BG73 -> 1777.1 | BU73: =AG73 -> 181 | BV73: =AD73 -> 181 | BW73: 0 | BX73: =H73+P73+X73+BA73+BH73 -> 0 | BY73: 0 | BZ73: 0 | CA73: =BS73+BU73+BW73+BY73 -> 865.6 | CB73: =BT73+BV73+BX73+BZ73 -> 1958.1 | CC73: =CA73+CB73 -> 2823.7 | CD73: 21
A74: 6月 | B74: 中粮福临门上海 | C74: 严洪玉 | D74: 320882197404083426 | E74: 6520 | F74: 16 | G74: 1043.2 | H74: 0 | I74: 8 | J74: 521.6 | K74: 0 | L74: 6520 | M74: 9.5 | O74: 619.4 | P74: 0 | Q74: 2 | S74: 130.4 | T74: 0 | U74: 6520 | V74: 0.5 | W74: 32.6 | X74: 0 | Y74: 0.5 | Z74: 32.6 | AA74: 0 | AB74: 2590 | AC74: 7 | AD74: 181 | AE74: 0 | AF74: 7 | AG74: 181 | AH74: 0 | AI74: 0 | AJ74: 0 | AK74: 0 | AL74: 0 | AM74: 0 | AN74: 0 | AO74: 0 | AP74: 0 | AQ74: 0 | AR74: 0 | AS74: 0 | AT74: 0 | AU74: 0 | AV74: 0 | AX74: 6520 | AY74: 1 | AZ74: 65.2 | BA74: 0 | BC74: 0 | BD74: 0 | BE74: 6520 | BF74: 0.256 | BG74: 16.7 | BH74: 0 | BJ74: 0 | BK74: 0 | BN74: 0 | BO74: 0 | BQ74: 0 | BR74: 0 | BS74: =J74+S74+Z74+AK74+AU74+BC74+BJ74 -> 684.6 | BT74: =G74+O74+W74+AI74+AM74+AO74+AQ74+AS74+AZ74+BG74 -> 1777.1 | BU74: =AG74 -> 181 | BV74: =AD74 -> 181 | BW74: 0 | BX74: =H74+P74+X74+BA74+BH74 -> 0 | BY74: 0 | BZ74: 0 | CA74: =BS74+BU74+BW74+BY74 -> 865.6 | CB74: =BT74+BV74+BX74+BZ74 -> 1958.1 | CC74: =CA74+CB74 -> 2823.7 | CD74: 21
A75: 6月 | B75: 中粮福临门上海 | C75: 尤英 | D75: 342422197311202382 | E75: 6520 | F75: 16 | G75: 1043.2 | H75: 0 | I75: 8 | J75: 521.6 | K75: 0 | L75: 6520 | M75: 9.5 | O75: 619.4 | P75: 0 | Q75: 2 | S75: 130.4 | T75: 0 | U75: 6520 | V75: 0.5 | W75: 32.6 | X75: 0 | Y75: 0.5 | Z75: 32.6 | AA75: 0 | AB75: 2590 | AC75: 7 | AD75: 181 | AE75: 0 | AF75: 7 | AG75: 181 | AH75: 0 | AI75: 0 | AJ75: 0 | AK75: 0 | AL75: 0 | AM75: 0 | AN75: 0 | AO75: 0 | AP75: 0 | AQ75: 0 | AR75: 0 | AS75: 0 | AT75: 0 | AU75: 0 | AV75: 0 | AX75: 6520 | AY75: 1 | AZ75: 65.2 | BA75: 0 | BC75: 0 | BD75: 0 | BE75: 6520 | BF75: 0.256 | BG75: 16.7 | BH75: 0 | BJ75: 0 | BK75: 0 | BN75: 0 | BO75: 0 | BQ75: 0 | BR75: 0 | BS75: =J75+S75+Z75+AK75+AU75+BC75+BJ75 -> 684.6 | BT75: =G75+O75+W75+AI75+AM75+AO75+AQ75+AS75+AZ75+BG75 -> 1777.1 | BU75: =AG75 -> 181 | BV75: =AD75 -> 181 | BW75: 0 | BX75: =H75+P75+X75+BA75+BH75 -> 0 | BY75: 0 | BZ75: 0 | CA75: =BS75+BU75+BW75+BY75 -> 865.6 | CB75: =BT75+BV75+BX75+BZ75 -> 1958.1 | CC75: =CA75+CB75 -> 2823.7 | CD75: 21
A76: 6月 | B76: 中粮福临门上海 | C76: 姚友美 | D76: 34122619830430352x | BS76: =J76+S76+Z76+AK76+AU76+BC76+BJ76 -> 0 | BT76: =G76+O76+W76+AI76+AM76+AO76+AQ76+AS76+AZ76+BG76 -> 0 | BU76: =AG76 -> 0 | BV76: =AD76 -> 0 | BW76: 0 | BX76: =H76+P76+X76+BA76+BH76 -> 0 | BY76: 0 | BZ76: 0 | CA76: =BS76+BU76+BW76+BY76 -> 0 | CB76: =BT76+BV76+BX76+BZ76 -> 0 | CC76: =CA76+CB76 -> 0 | CD76: 21
A77: 6月 | B77: 中粮福临门上海 | C77: 张孝娟 | D77: 341226198305202763 | E77: 6520 | F77: 16 | G77: 1043.2 | H77: 0 | I77: 8 | J77: 521.6 | K77: 0 | L77: 6520 | M77: 9.5 | O77: 619.4 | P77: 0 | Q77: 2 | S77: 130.4 | T77: 0 | U77: 6520 | V77: 0.5 | W77: 32.6 | X77: 0 | Y77: 0.5 | Z77: 32.6 | AA77: 0 | AB77: 2590 | AC77: 7 | AD77: 181 | AE77: 0 | AF77: 7 | AG77: 181 | AH77: 0 | AI77: 0 | AJ77: 0 | AK77: 0 | AL77: 0 | AM77: 0 | AN77: 0 | AO77: 0 | AP77: 0 | AQ77: 0 | AR77: 0 | AS77: 0 | AT77: 0 | AU77: 0 | AV77: 0 | AX77: 6520 | AY77: 1 | AZ77: 65.2 | BA77: 0 | BC77: 0 | BD77: 0 | BE77: 6520 | BF77: 0.256 | BG77: 16.7 | BH77: 0 | BJ77: 0 | BK77: 0 | BN77: 0 | BO77: 0 | BQ77: 0 | BR77: 0 | BS77: =J77+S77+Z77+AK77+AU77+BC77+BJ77 -> 684.6 | BT77: =G77+O77+W77+AI77+AM77+AO77+AQ77+AS77+AZ77+BG77 -> 1777.1 | BU77: =AG77 -> 181 | BV77: =AD77 -> 181 | BW77: 0 | BX77: =H77+P77+X77+BA77+BH77 -> 0 | BY77: 0 | BZ77: 0 | CA77: =BS77+BU77+BW77+BY77 -> 865.6 | CB77: =BT77+BV77+BX77+BZ77 -> 1958.1 | CC77: =CA77+CB77 -> 2823.7 | CD77: 21
A78: 6月 | B78: 中粮福临门上海 | C78: 汪肖肖 | D78: 34222119881006652X | E78: 6520 | F78: 16 | G78: 1043.2 | H78: 0 | I78: 8 | J78: 521.6 | K78: 0 | L78: 6520 | M78: 9.5 | O78: 619.4 | P78: 0 | Q78: 2 | S78: 130.4 | T78: 0 | U78: 6520 | V78: 0.5 | W78: 32.6 | X78: 0 | Y78: 0.5 | Z78: 32.6 | AA78: 0 | AB78: 2590 | AC78: 7 | AD78: 181 | AE78: 0 | AF78: 7 | AG78: 181 | AH78: 0 | AI78: 0 | AJ78: 0 | AK78: 0 | AL78: 0 | AM78: 0 | AN78: 0 | AO78: 0 | AP78: 0 | AQ78: 0 | AR78: 0 | AS78: 0 | AT78: 0 | AU78: 0 | AV78: 0 | AX78: 6520 | AY78: 1 | AZ78: 65.2 | BA78: 0 | BC78: 0 | BD78: 0 | BE78: 6520 | BF78: 0.256 | BG78: 16.7 | BH78: 0 | BJ78: 0 | BK78: 0 | BN78: 0 | BO78: 0 | BQ78: 0 | BR78: 0 | BS78: =J78+S78+Z78+AK78+AU78+BC78+BJ78 -> 684.6 | BT78: =G78+O78+W78+AI78+AM78+AO78+AQ78+AS78+AZ78+BG78 -> 1777.1 | BU78: =AG78 -> 181 | BV78: =AD78 -> 181 | BW78: 0 | BX78: =H78+P78+X78+BA78+BH78 -> 0 | BY78: 0 | BZ78: 0 | CA78: =BS78+BU78+BW78+BY78 -> 865.6 | CB78: =BT78+BV78+BX78+BZ78 -> 1958.1 | CC78: =CA78+CB78 -> 2823.7 | CD78: 21
A79: 6月 | B79: 中粮福临门上海 | C79: 孙艳 | D79: 34120319890120316X | E79: 6520 | F79: 16 | G79: 1043.2 | H79: 0 | I79: 8 | J79: 521.6 | K79: 0 | L79: 6520 | M79: 9.5 | O79: 619.4 | P79: 0 | Q79: 2 | S79: 130.4 | T79: 0 | U79: 6520 | V79: 0.5 | W79: 32.6 | X79: 0 | Y79: 0.5 | Z79: 32.6 | AA79: 0 | AB79: 2590 | AC79: 7 | AD79: 181 | AE79: 0 | AF79: 7 | AG79: 181 | AH79: 0 | AI79: 0 | AJ79: 0 | AK79: 0 | AL79: 0 | AM79: 0 | AN79: 0 | AO79: 0 | AP79: 0 | AQ79: 0 | AR79: 0 | AS79: 0 | AT79: 0 | AU79: 0 | AV79: 0 | AX79: 6520 | AY79: 1 | AZ79: 65.2 | BA79: 0 | BC79: 0 | BD79: 0 | BE79: 6520 | BF79: 0.256 | BG79: 16.7 | BH79: 0 | BJ79: 0 | BK79: 0 | BN79: 0 | BO79: 0 | BQ79: 0 | BR79: 0 | BS79: =J79+S79+Z79+AK79+AU79+BC79+BJ79 -> 684.6 | BT79: =G79+O79+W79+AI79+AM79+AO79+AQ79+AS79+AZ79+BG79 -> 1777.1 | BU79: =AG79 -> 181 | BV79: =AD79 -> 181 | BW79: 0 | BX79: =H79+P79+X79+BA79+BH79 -> 0 | BY79: 0 | BZ79: 0 | CA79: =BS79+BU79+BW79+BY79 -> 865.6 | CB79: =BT79+BV79+BX79+BZ79 -> 1958.1 | CC79: =CA79+CB79 -> 2823.7 | CD79: 0
A80: 6月 | B80: 中粮福临门上海 | C80: 孙艳 | D80: 34120319890120316X | E80: 5975 | F80: 16 | G80: 956 | H80: 0 | I80: 8 | J80: 478 | K80: 0 | L80: 5975 | M80: 9.5 | O80: 567.63 | P80: 0 | Q80: 2 | S80: 119.5 | T80: 0 | U80: 5975 | V80: 0.5 | W80: 29.87 | X80: 0 | Y80: 0.5 | Z80: 29.88 | AA80: 0 | AB80: 2590 | AC80: 7 | AD80: 181 | AE80: 0 | AF80: 7 | AG80: 181 | AH80: 0 | AI80: 0 | AJ80: 0 | AK80: 0 | AL80: 0 | AM80: 0 | AN80: 0 | AO80: 0 | AP80: 0 | AQ80: 0 | AR80: 0 | AS80: 0 | AT80: 0 | AU80: 0 | AV80: 0 | AX80: 5975 | AY80: 1 | AZ80: 59.75 | BA80: 0 | BC80: 0 | BD80: 0 | BE80: 5975 | BF80: 0.256 | BG80: 15.3 | BH80: 0 | BJ80: 0 | BK80: 0 | BN80: 0 | BO80: 0 | BQ80: 0 | BR80: 0 | BS80: =J80+S80+Z80+AK80+AU80+BC80+BJ80 -> 627.38 | BT80: =G80+O80+W80+AI80+AM80+AO80+AQ80+AS80+AZ80+BG80 -> 1628.55 | BU80: =AG80 -> 181 | BV80: =AD80 -> 181 | BW80: 0 | BX80: =H80+P80+X80+BA80+BH80 -> 0 | BY80: 0 | BZ80: 0 | CA80: =BS80+BU80+BW80+BY80 -> 808.38 | CB80: =BT80+BV80+BX80+BZ80 -> 1809.55 | CC80: =CA80+CB80 -> 2617.93 | CD80: 21
A81: 6月 | B81: 中粮-中粮江沪（合杰） | C81: 杜艳梅 | D81: 41272519740221784X | E81: 3957 | F81: 16 | G81: 633.12 | H81: 0 | I81: 8 | J81: 316.56 | K81: 0 | L81: 3957 | M81: 8.5 | N81: 0 | O81: 336.3 | P81: 0 | Q81: 2 | R81: 0 | S81: 79.1 | T81: 0 | U81: 3957 | V81: 0.5 | W81: 19.79 | X81: 0 | Y81: 0.5 | Z81: 19.79 | AA81: 0 | AB81: 2010 | AC81: 8 | AD81: 161 | AE81: 0 | AF81: 8 | AG81: 161 | AH81: 0 | AI81: 0 | AJ81: 0 | AK81: 0 | AL81: 0 | AM81: 0 | AN81: 0 | AO81: 0 | AP81: 0 | AQ81: 0 | AR81: 0 | AS81: 0 | AT81: 0 | AU81: 0 | AV81: 0 | AZ81: 0 | BA81: 0 | BC81: 0 | BD81: 0 | BE81: 3957 | BF81: 0.45 | BG81: 17.81 | BH81: 0 | BI81: 0 | BJ81: 0 | BK81: 0 | BN81: 0 | BO81: 0 | BQ81: 0 | BR81: 0 | BS81: 415.45 | BT81: 1007.02 | BU81: 161 | BV81: 161 | BW81: 0 | BX81: 0 | BY81: 0 | BZ81: 0 | CA81: 576.45 | CB81: 1168.02 | CC81: 1744.47 | CD81: 21 | CF81: 415.45 | CG81: 1007.02 | CH81: 161 | CI81: 161
A82: 6月 | B82: 中粮-中粮江沪（合杰） | C82: 耿良莉 | D82: 34242319840516738X | E82: 3957 | F82: 16 | G82: 633.12 | H82: 0 | I82: 8 | J82: 316.56 | K82: 0 | L82: 3957 | M82: 8.5 | N82: 0 | O82: 336.3 | P82: 0 | Q82: 2 | R82: 0 | S82: 79.1 | T82: 0 | U82: 3957 | V82: 0.5 | W82: 19.79 | X82: 0 | Y82: 0.5 | Z82: 19.79 | AA82: 0 | AB82: 2010 | AC82: 8 | AD82: 161 | AE82: 0 | AF82: 8 | AG82: 161 | AH82: 0 | AI82: 0 | AJ82: 0 | AK82: 0 | AL82: 0 | AM82: 0 | AN82: 0 | AO82: 0 | AP82: 0 | AQ82: 0 | AR82: 0 | AS82: 0 | AT82: 0 | AU82: 0 | AV82: 0 | AZ82: 0 | BA82: 0 | BC82: 0 | BD82: 0 | BE82: 3957 | BF82: 0.45 | BG82: 17.81 | BH82: 0 | BI82: 0 | BJ82: 0 | BK82: 0 | BN82: 0 | BO82: 0 | BQ82: 0 | BR82: 0 | BS82: 415.45 | BT82: 1007.02 | BU82: 161 | BV82: 161 | BW82: 0 | BX82: 0 | BY82: 0 | BZ82: 0 | CA82: 576.45 | CB82: 1168.02 | CC82: 1744.47 | CD82: 21 | CF82: 415.45 | CG82: 1007.02 | CH82: 161 | CI82: 161
A83: 6月 | B83: 中粮-中粮江沪（合杰） | C83: 霍雪 | D83: 41152819860103524X | E83: 3957 | F83: 15 | G83: 593.55 | H83: 39.57 | I83: 8 | J83: 316.56 | K83: 0 | L83: 5930 | M83: 6 | N83: 0 | O83: 355.8 | P83: 0 | Q83: 0 | R83: 0 | S83: 0 | T83: 0 | U83: 3957 | V83: 0.5 | W83: 19.79 | X83: 0 | Y83: 0.5 | Z83: 19.79 | AA83: 0 | AB83: 3957 | AC83: 8 | AD83: 317 | AE83: 0 | AF83: 8 | AG83: 317 | AH83: 0 | AI83: 0 | AJ83: 0 | AK83: 5 | AL83: 0 | AM83: 0 | AN83: 0 | AO83: 0 | AP83: 0 | AQ83: 0 | AR83: 0 | AS83: 0 | AT83: 0 | AU83: 0 | AV83: 0 | AZ83: 0 | BA83: 0 | BC83: 0 | BD83: 0 | BE83: 3957 | BF83: 0.2 | BG83: 7.91 | BH83: 0 | BI83: 0 | BJ83: 0 | BK83: 0 | BN83: 0 | BO83: 0 | BQ83: 0 | BR83: 0 | BS83: 341.35 | BT83: 977.05 | BU83: 317 | BV83: 317 | BW83: 0 | BX83: 39.57 | BY83: 0 | BZ83: 0 | CA83: 658.35 | CB83: 1333.62 | CC83: 1991.97 | CD83: 21 | CF83: 341.35 | CG83: 1016.62 | CH83: 317 | CI83: 317
A84: 6月 | B84: 中粮-中粮江沪（合杰） | C84: 李芳 | D84: 41022119771110764X | E84: 3957 | F84: 16 | G84: 633.12 | H84: 0 | I84: 8 | J84: 316.56 | K84: 0 | L84: 3957 | M84: 8.5 | N84: 0 | O84: 336.3 | P84: 0 | Q84: 2 | R84: 0 | S84: 79.1 | T84: 0 | U84: 3957 | V84: 0.5 | W84: 19.79 | X84: 0 | Y84: 0.5 | Z84: 19.79 | AA84: 0 | AB84: 2010 | AC84: 8 | AD84: 161 | AE84: 0 | AF84: 8 | AG84: 161 | AH84: 0 | AI84: 0 | AJ84: 0 | AK84: 0 | AL84: 0 | AM84: 0 | AN84: 0 | AO84: 0 | AP84: 0 | AQ84: 0 | AR84: 0 | AS84: 0 | AT84: 0 | AU84: 0 | AV84: 0 | AZ84: 0 | BA84: 0 | BC84: 0 | BD84: 0 | BE84: 3957 | BF84: 0.45 | BG84: 17.81 | BH84: 0 | BI84: 0 | BJ84: 0 | BK84: 0 | BN84: 0 | BO84: 0 | BQ84: 0 | BR84: 0 | BS84: 415.45 | BT84: 1007.02 | BU84: 161 | BV84: 161 | BW84: 0 | BX84: 0 | BY84: 0 | BZ84: 0 | CA84: 576.45 | CB84: 1168.02 | CC84: 1744.47 | CD84: 21 | CF84: 415.45 | CG84: 1007.02 | CH84: 161 | CI84: 161
A85: 6月 | B85: 中粮-中粮江沪（合杰） | C85: 涂秀华 | D85: 511123197304307822 | E85: 3957 | F85: 16 | G85: 633.12 | H85: 0 | I85: 8 | J85: 316.56 | K85: 0 | L85: 3957 | M85: 8.5 | N85: 0 | O85: 336.3 | P85: 0 | Q85: 2 | R85: 0 | S85: 79.1 | T85: 0 | U85: 3957 | V85: 0.5 | W85: 19.79 | X85: 0 | Y85: 0.5 | Z85: 19.79 | AA85: 0 | AB85: 2010 | AC85: 8 | AD85: 161 | AE85: 0 | AF85: 8 | AG85: 161 | AH85: 0 | AI85: 0 | AJ85: 0 | AK85: 0 | AL85: 0 | AM85: 0 | AN85: 0 | AO85: 0 | AP85: 0 | AQ85: 0 | AR85: 0 | AS85: 0 | AT85: 0 | AU85: 0 | AV85: 0 | AZ85: 0 | BA85: 0 | BC85: 0 | BD85: 0 | BE85: 3957 | BF85: 0.45 | BG85: 17.81 | BH85: 0 | BI85: 0 | BJ85: 0 | BK85: 0 | BN85: 0 | BO85: 0 | BQ85: 0 | BR85: 0 | BS85: 415.45 | BT85: 1007.02 | BU85: 161 | BV85: 161 | BW85: 0 | BX85: 0 | BY85: 0 | BZ85: 0 | CA85: 576.45 | CB85: 1168.02 | CC85: 1744.47 | CD85: 21 | CF85: 415.45 | CG85: 1007.02 | CH85: 161 | CI85: 161
A86: 6月 | B86: 中粮-中粮江沪（合杰） | C86: 尹雪峰 | D86: 342224198109020741 | E86: 3957 | F86: 16 | G86: 633.12 | H86: 0 | I86: 8 | J86: 316.56 | K86: 0 | L86: 3957 | M86: 8.5 | N86: 0 | O86: 336.3 | P86: 0 | Q86: 2 | R86: 0 | S86: 79.1 | T86: 0 | U86: 3957 | V86: 0.5 | W86: 19.79 | X86: 0 | Y86: 0.5 | Z86: 19.79 | AA86: 0 | AB86: 2280 | AC86: 8 | AD86: 182 | AE86: 0 | AF86: 8 | AG86: 182 | AH86: 0 | AI86: 0 | AJ86: 0 | AK86: 0 | AL86: 0 | AM86: 0 | AN86: 0 | AO86: 0 | AP86: 0 | AQ86: 0 | AR86: 0 | AS86: 0 | AT86: 0 | AU86: 0 | AV86: 0 | AZ86: 0 | BA86: 0 | BC86: 0 | BD86: 0 | BE86: 3957 | BF86: 0.45 | BG86: 17.81 | BH86: 0 | BI86: 0 | BJ86: 0 | BK86: 0 | BN86: 0 | BO86: 0 | BQ86: 0 | BR86: 0 | BS86: 415.45 | BT86: 1007.02 | BU86: 182 | BV86: 182 | BW86: 0 | BX86: 0 | BY86: 0 | BZ86: 0 | CA86: 597.45 | CB86: 1189.02 | CC86: 1786.47 | CD86: 21 | CF86: 415.45 | CG86: 1007.02 | CH86: 182 | CI86: 182
A87: 6月 | B87: 中粮-中粮江沪（合杰） | C87: 丁小红 | D87: 321025197404040821 | E87: 4250 | F87: 16 | G87: 680 | H87: 0 | I87: 8 | J87: 340 | K87: 0 | L87: 4250 | M87: 7.6 | N87: 0 | O87: 323 | P87: 0 | Q87: 2 | S87: 85 | T87: 0 | U87: 4250 | V87: 0.5 | W87: 21.25 | X87: 0 | Y87: 0.5 | Z87: 21.25 | AA87: 0 | AD87: 0 | AE87: 0 | AG87: 0 | AH87: 0 | AI87: 0 | AJ87: 0 | AK87: 0 | AL87: 0 | AM87: 0 | AN87: 0 | AO87: 0 | AP87: 0 | AQ87: 0 | AR87: 0 | AS87: 0 | AT87: 0 | AU87: 0 | AV87: 0 | AX87: 4250 | AY87: 0.8 | AZ87: 34 | BA87: 0 | BB87: 0 | BC87: 0 | BD87: 0 | BE87: 4250 | BF87: 0.9 | BG87: 38.25 | BH87: 0 | BI87: 0 | BJ87: 0 | BK87: 0 | BN87: 0 | BO87: 0 | BQ87: 0 | BR87: 0 | BS87: 446.25 | BT87: 1096.5 | BU87: 0 | BV87: 0 | BW87: 0 | BX87: 0 | BY87: 0 | BZ87: 0 | CA87: 446.25 | CB87: 1096.5 | CC87: 1542.75 | CD87: 21 | CF87: 446.25 | CG87: 1096.5 | CH87: 0 | CI87: 0
A88: 6月 | B88: 中粮-中粮江沪（合杰） | C88: 顾宏 | D88: 320924197303033448 | E88: 4250 | F88: 16 | G88: 680 | H88: 0 | I88: 8 | J88: 340 | K88: 0 | L88: 4250 | M88: 7 | N88: 0 | O88: 297.5 | P88: 0 | Q88: 2 | R88: 0 | S88: 85 | T88: 0 | U88: 4250 | V88: 0.5 | W88: 21.25 | X88: 0 | Y88: 0.5 | Z88: 21.25 | AA88: 0 | AB88: 3800 | AC88: 8 | AD88: 304 | AE88: 0 | AF88: 8 | AG88: 304 | AH88: 0 | AI88: 0 | AJ88: 0 | AK88: 5 | AL88: 0 | AM88: 0 | AN88: 0 | AO88: 0 | AP88: 0 | AQ88: 0 | AR88: 0 | AS88: 0 | AT88: 0 | AU88: 0 | AV88: 0 | AX88: 4250 | AY88: 0.8 | AZ88: 34 | BA88: 0 | BB88: 0 | BC88: 0 | BD88: 0 | BE88: 4250 | BF88: 0.45 | BG88: 19.13 | BH88: 0 | BI88: 0 | BJ88: 0 | BK88: 0 | BN88: 0 | BO88: 0 | BQ88: 0 | BR88: 0 | BS88: 451.25 | BT88: 1051.88 | BU88: 304 | BV88: 304 | BW88: 0 | BX88: 0 | BY88: 0 | BZ88: 0 | CA88: 755.25 | CB88: 1355.88 | CC88: 2111.13 | CD88: 21 | CF88: 451.25 | CG88: 1051.88 | CH88: 304 | CI88: 304
A89: 6月 | B89: 中粮-中粮江沪（合杰） | C89: 孙开艳 | D89: 32092419760320718X | E89: 4250 | F89: 16 | G89: 680 | H89: 0 | I89: 8 | J89: 340 | K89: 0 | L89: 4250 | M89: 7.6 | N89: 0 | O89: 323 | P89: 0 | Q89: 2 | S89: 85 | T89: 0 | U89: 4250 | V89: 0.5 | W89: 21.25 | X89: 0 | Y89: 0.5 | Z89: 21.25 | AA89: 0 | AB89: 2020 | AC89: 8 | AD89: 162 | AE89: 0 | AF89: 8 | AG89: 162 | AH89: 0 | AI89: 0 | AJ89: 0 | AK89: 0 | AL89: 0 | AM89: 0 | AN89: 0 | AO89: 0 | AP89: 0 | AQ89: 0 | AR89: 0 | AS89: 0 | AT89: 0 | AU89: 0 | AV89: 0 | AX89: 4250 | AY89: 0.8 | AZ89: 34 | BA89: 0 | BB89: 0 | BC89: 0 | BD89: 0 | BE89: 4250 | BF89: 0.9 | BG89: 38.25 | BH89: 0 | BI89: 0 | BJ89: 0 | BK89: 0 | BN89: 0 | BO89: 0 | BQ89: 0 | BR89: 0 | BS89: 446.25 | BT89: 1096.5 | BU89: 162 | BV89: 162 | BW89: 0 | BX89: 0 | BY89: 0 | BZ89: 0 | CA89: 608.25 | CB89: 1258.5 | CC89: 1866.75 | CD89: 21 | CF89: 446.25 | CG89: 1096.5 | CH89: 162 | CI89: 162
A90: 6月 | B90: 中粮-中粮江沪（合杰） | C90: 孙莉莉 | D90: 320922198304053645 | E90: 4250 | F90: 16 | G90: 680 | H90: 0 | I90: 8 | J90: 340 | K90: 0 | L90: 4250 | M90: 7.6 | N90: 0 | O90: 323 | P90: 0 | Q90: 2 | S90: 85 | T90: 0 | U90: 4250 | V90: 0.5 | W90: 21.25 | X90: 0 | Y90: 0.5 | Z90: 21.25 | AA90: 0 | AB90: 2020 | AC90: 8 | AD90: 162 | AE90: 0 | AF90: 8 | AG90: 162 | AH90: 0 | AI90: 0 | AJ90: 0 | AK90: 0 | AL90: 0 | AM90: 0 | AN90: 0 | AO90: 0 | AP90: 0 | AQ90: 0 | AR90: 0 | AS90: 0 | AT90: 0 | AU90: 0 | AV90: 0 | AX90: 4250 | AY90: 0.8 | AZ90: 34 | BA90: 0 | BB90: 0 | BC90: 0 | BD90: 0 | BE90: 4250 | BF90: 0.9 | BG90: 38.25 | BH90: 0 | BI90: 0 | BJ90: 0 | BK90: 0 | BN90: 0 | BO90: 0 | BQ90: 0 | BR90: 0 | BS90: 446.25 | BT90: 1096.5 | BU90: 162 | BV90: 162 | BW90: 0 | BX90: 0 | BY90: 0 | BZ90: 0 | CA90: 608.25 | CB90: 1258.5 | CC90: 1866.75 | CD90: 21 | CF90: 446.25 | CG90: 1096.5 | CH90: 162 | CI90: 162
A91: 6月 | B91: 中粮-中粮江沪（合杰） | C91: 陶宝芹 | D91: 321023197201015869 | E91: 4250 | F91: 16 | G91: 680 | H91: 0 | I91: 8 | J91: 340 | K91: 0 | L91: 4250 | M91: 7.6 | N91: 0 | O91: 323 | P91: 0 | Q91: 2 | S91: 85 | T91: 0 | U91: 4250 | V91: 0.5 | W91: 21.25 | X91: 0 | Y91: 0.5 | Z91: 21.25 | AA91: 0 | AD91: 0 | AE91: 0 | AG91: 0 | AH91: 0 | AI91: 0 | AJ91: 0 | AK91: 0 | AL91: 0 | AM91: 0 | AN91: 0 | AO91: 0 | AP91: 0 | AQ91: 0 | AR91: 0 | AS91: 0 | AT91: 0 | AU91: 0 | AV91: 0 | AX91: 4250 | AY91: 0.8 | AZ91: 34 | BA91: 0 | BB91: 0 | BC91: 0 | BD91: 0 | BE91: 4250 | BF91: 0.9 | BG91: 38.25 | BH91: 0 | BI91: 0 | BJ91: 0 | BK91: 0 | BN91: 0 | BO91: 0 | BQ91: 0 | BR91: 0 | BS91: 446.25 | BT91: 1096.5 | BU91: 0 | BV91: 0 | BW91: 0 | BX91: 0 | BY91: 0 | BZ91: 0 | CA91: 446.25 | CB91: 1096.5 | CC91: 1542.75 | CD91: 21 | CF91: 446.25 | CG91: 1096.5 | CH91: 0 | CI91: 0
A92: 6月 | B92: 中粮-中粮江沪（合杰） | C92: 王素芹 | D92: 320825197403144322 | E92: 4250 | F92: 16 | G92: 680 | H92: 0 | I92: 8 | J92: 340 | K92: 0 | L92: 4250 | M92: 9 | N92: 0 | O92: 382.5 | P92: 0 | Q92: 2 | R92: 0 | S92: 85 | T92: 0 | U92: 4250 | V92: 0.5 | W92: 21.25 | X92: 0 | Y92: 0.5 | Z92: 21.25 | AA92: 0 | AB92: 2280 | AC92: 12 | AD92: 274 | AE92: 0 | AF92: 12 | AG92: 274 | AH92: 0 | AI92: 0 | AJ92: 0 | AK92: 10 | AL92: 0 | AM92: 0 | AN92: 0 | AO92: 0 | AP92: 0 | AQ92: 0 | AR92: 0 | AS92: 0 | AT92: 0 | AU92: 0 | AV92: 0 | AX92: 4250 | AY92: 0.8 | AZ92: 34 | BA92: 0 | BB92: 0 | BC92: 0 | BD92: 0 | BE92: 4250 | BF92: 0.4 | BG92: 17 | BH92: 0 | BI92: 0 | BJ92: 0 | BK92: 0 | BN92: 0 | BO92: 0 | BQ92: 0 | BR92: 0 | BS92: 456.25 | BT92: 1134.75 | BU92: 274 | BV92: 274 | BW92: 0 | BX92: 0 | BY92: 0 | BZ92: 0 | CA92: 730.25 | CB92: 1408.75 | CC92: 2139 | CD92: 21 | CF92: 456.25 | CG92: 1134.75 | CH92: 274 | CI92: 274
A93: 6月 | B93: 中粮-中粮江沪（合杰） | C93: 吴海珍 | D93: 321123197802191644 | E93: 4250 | F93: 16 | G93: 680 | H93: 0 | I93: 8 | J93: 340 | K93: 0 | L93: 4250 | M93: 9 | N93: 0 | O93: 382.5 | P93: 0 | Q93: 2 | R93: 0 | S93: 85 | T93: 0 | U93: 4250 | V93: 0.5 | W93: 21.25 | X93: 0 | Y93: 0.5 | Z93: 21.25 | AA93: 0 | AD93: 0 | AE93: 0 | AG93: 0 | AH93: 0 | AI93: 0 | AJ93: 0 | AK93: 10 | AL93: 0 | AM93: 0 | AN93: 0 | AO93: 0 | AP93: 0 | AQ93: 0 | AR93: 0 | AS93: 0 | AT93: 0 | AU93: 0 | AV93: 0 | AX93: 4250 | AY93: 0.8 | AZ93: 34 | BA93: 0 | BB93: 0 | BC93: 0 | BD93: 0 | BE93: 4250 | BF93: 0.4 | BG93: 17 | BH93: 0 | BI93: 0 | BJ93: 0 | BK93: 0 | BN93: 0 | BO93: 0 | BQ93: 0 | BR93: 0 | BS93: 456.25 | BT93: 1134.75 | BU93: 0 | BV93: 0 | BW93: 0 | BX93: 0 | BY93: 0 | BZ93: 0 | CA93: 456.25 | CB93: 1134.75 | CC93: 1591 | CD93: 21 | CF93: 456.25 | CG93: 1134.75 | CH93: 0 | CI93: 0
A94: 6月 | B94: 中粮-中粮江沪（合杰） | C94: 吴永红 | D94: 42032319710815250X | E94: 4250 | F94: 16 | G94: 680 | H94: 0 | I94: 8 | J94: 340 | K94: 0 | L94: 4250 | M94: 7.6 | N94: 0 | O94: 323 | P94: 0 | Q94: 2 | S94: 85 | T94: 0 | U94: 4250 | V94: 0.5 | W94: 21.25 | X94: 0 | Y94: 0.5 | Z94: 21.25 | AA94: 0 | AB94: 2020 | AC94: 8 | AD94: 162 | AE94: 0 | AF94: 8 | AG94: 162 | AH94: 0 | AI94: 0 | AJ94: 0 | AK94: 0 | AL94: 0 | AM94: 0 | AN94: 0 | AO94: 0 | AP94: 0 | AQ94: 0 | AR94: 0 | AS94: 0 | AT94: 0 | AU94: 0 | AV94: 0 | AX94: 4250 | AY94: 0.8 | AZ94: 34 | BA94: 0 | BB94: 0 | BC94: 0 | BD94: 0 | BE94: 4250 | BF94: 0.9 | BG94: 38.25 | BH94: 0 | BI94: 0 | BJ94: 0 | BK94: 0 | BN94: 0 | BO94: 0 | BQ94: 0 | BR94: 0 | BS94: 446.25 | BT94: 1096.5 | BU94: 162 | BV94: 162 | BW94: 0 | BX94: 0 | BY94: 0 | BZ94: 0 | CA94: 608.25 | CB94: 1258.5 | CC94: 1866.75 | CD94: 21 | CF94: 446.25 | CG94: 1096.5 | CH94: 162 | CI94: 162
A95: 6月 | B95: 中粮-中粮江沪（合杰） | C95: 谢如香 | D95: 321322198705145223 | E95: 4250 | F95: 16 | G95: 680 | H95: 0 | I95: 8 | J95: 340 | K95: 0 | L95: 4250 | M95: 7 | N95: 0 | O95: 297.5 | P95: 0 | Q95: 2 | R95: 0 | S95: 85 | T95: 0 | U95: 4250 | V95: 0.5 | W95: 21.25 | X95: 0 | Y95: 0.5 | Z95: 21.25 | AA95: 0 | AB95: 3800 | AC95: 8 | AD95: 304 | AE95: 0 | AF95: 8 | AG95: 304 | AH95: 0 | AI95: 0 | AJ95: 0 | AK95: 5 | AL95: 0 | AM95: 0 | AN95: 0 | AO95: 0 | AP95: 0 | AQ95: 0 | AR95: 0 | AS95: 0 | AT95: 0 | AU95: 0 | AV95: 0 | AX95: 4250 | AY95: 0.8 | AZ95: 34 | BA95: 0 | BB95: 0 | BC95: 0 | BD95: 0 | BE95: 4250 | BF95: 0.45 | BG95: 19.13 | BH95: 0 | BI95: 0 | BJ95: 0 | BK95: 0 | BN95: 0 | BO95: 0 | BQ95: 0 | BR95: 0 | BS95: 451.25 | BT95: 1051.88 | BU95: 304 | BV95: 304 | BW95: 0 | BX95: 0 | BY95: 0 | BZ95: 0 | CA95: 755.25 | CB95: 1355.88 | CC95: 2111.13 | CD95: 21 | CF95: 451.25 | CG95: 1051.88 | CH95: 304 | CI95: 304
A96: 6月 | B96: 中粮-中粮江沪（合杰） | C96: 余春阳 | D96: 413027196812100055 | E96: 4250 | F96: 16 | G96: 680 | H96: 0 | I96: 8 | J96: 340 | K96: 0 | L96: 4250 | M96: 7 | N96: 0 | O96: 297.5 | P96: 0 | Q96: 2 | R96: 0 | S96: 85 | T96: 0 | U96: 4250 | V96: 0.5 | W96: 21.25 | X96: 0 | Y96: 0.5 | Z96: 21.25 | AA96: 0 | AB96: 3800 | AC96: 8 | AD96: 304 | AE96: 0 | AF96: 8 | AG96: 304 | AH96: 0 | AI96: 0 | AJ96: 0 | AK96: 5 | AL96: 0 | AM96: 0 | AN96: 0 | AO96: 0 | AP96: 0 | AQ96: 0 | AR96: 0 | AS96: 0 | AT96: 0 | AU96: 0 | AV96: 0 | AX96: 4250 | AY96: 0.8 | AZ96: 34 | BA96: 0 | BB96: 0 | BC96: 0 | BD96: 0 | BE96: 4250 | BF96: 0.45 | BG96: 19.13 | BH96: 0 | BI96: 0 | BJ96: 0 | BK96: 0 | BN96: 0 | BO96: 0 | BQ96: 0 | BR96: 0 | BS96: 451.25 | BT96: 1051.88 | BU96: 304 | BV96: 304 | BW96: 0 | BX96: 0 | BY96: 0 | BZ96: 0 | CA96: 755.25 | CB96: 1355.88 | CC96: 2111.13 | CD96: 21 | CF96: 451.25 | CG96: 1051.88 | CH96: 304 | CI96: 304
A97: 6月 | B97: 中粮-中粮江沪（合杰） | C97: 徐婷 | D97: 320828197509113064 | E97: 4250 | F97: 16 | G97: 680 | H97: 0 | I97: 8 | J97: 340 | K97: 0 | L97: 4250 | M97: 7.6 | N97: 0 | O97: 323 | P97: 0 | Q97: 2 | R97: 0 | S97: 85 | T97: 0 | U97: 4250 | V97: 0.5 | W97: 21.25 | X97: 0 | Y97: 0.5 | Z97: 21.25 | AA97: 0 | AB97: 2280 | AC97: 8 | AD97: 183 | AE97: 0 | AF97: 8 | AG97: 183 | AH97: 0 | AI97: 0 | AJ97: 0 | AK97: 0 | AL97: 0 | AM97: 0 | AN97: 0 | AO97: 0 | AP97: 0 | AQ97: 0 | AR97: 0 | AS97: 0 | AT97: 0 | AU97: 0 | AV97: 0 | AX97: 4250 | AY97: 0.8 | AZ97: 34 | BA97: 0 | BB97: 0 | BC97: 0 | BD97: 0 | BE97: 4250 | BF97: 0.9 | BG97: 38.25 | BH97: 0 | BI97: 0 | BJ97: 0 | BK97: 0 | BN97: 0 | BO97: 0 | BQ97: 0 | BR97: 0 | BS97: 446.25 | BT97: 1096.5 | BU97: 183 | BV97: 183 | BW97: 0 | BX97: 0 | BY97: 0 | BZ97: 0 | CA97: 629.25 | CB97: 1279.5 | CC97: 1908.75 | CD97: 21 | CF97: 446.25 | CG97: 1096.5 | CH97: 183 | CI97: 183
A98: 6月 | B98: 中粮-中粮江沪（合杰） | C98: 郑爱凤 | D98: 320423197203263023 | E98: 0 | F98: 0 | G98: 0 | H98: 0 | I98: 0 | J98: 0 | K98: 0 | L98: 0 | M98: 0 | N98: 0 | O98: 0 | P98: 0 | Q98: 0 | R98: 0 | S98: 0 | T98: 0 | U98: 0 | V98: 0 | W98: 0 | X98: 0 | Y98: 0 | Z98: 0 | AA98: 0 | AB98: 0 | AC98: 0 | AD98: 0 | AE98: 0 | AF98: 0 | AG98: 0 | AH98: 0 | AI98: 0 | AJ98: 0 | AK98: 0 | AL98: 0 | AM98: 0 | AN98: 0 | AO98: 0 | AP98: 0 | AQ98: 0 | AR98: 0 | AS98: 0 | AT98: 0 | AU98: 0 | AV98: 0 | AW98: 0 | AX98: 0 | AY98: 0 | AZ98: 0 | BA98: 0 | BB98: 0 | BC98: 0 | BD98: 0 | BE98: 0 | BF98: 0 | BG98: 0 | BH98: 0 | BI98: 0 | BJ98: 0 | BK98: 0 | BL98: 0 | BM98: 0 | BN98: 0 | BO98: 0 | BP98: 0 | BQ98: 0 | BR98: 0 | BS98: 0 | BT98: 0 | BU98: 0 | BV98: 0 | BW98: 0 | BX98: 0 | BY98: 0 | BZ98: 0 | CA98: 0 | CB98: 0 | CC98: 0 | CD98: 0 | CE98: 退休返聘，雇主年付 | CF98: 0 | CG98: 0 | CH98: 0 | CI98: 0

Sheet Sheet4
A1: 姓名 | B1: 雇主责任险 | C1: 本月应缴金额 | G1: 补缴金额 | K1: 实缴金额
C2: 社保 | E2: 公积金 | G2: 社保 | I2: 公积金 | K2: 个人 | L2: 公司 | M2: 小计
C3: 个人 | D3: 公司 | E3: 个人 | F3: 公司 | G3: 个人 | H3: 公司 | I3: 个人 | J3: 公司 | K3: 个人 | L3: 公司 | M3: 小计
A4: 车文秀 | B4: 21 | C4: 627.38 | D4: 1628.55 | E4: 174 | F4: 174 | G4: 0 | H4: 0 | I4: 0 | J4: 0 | K4: 801.38 | L4: 1802.55 | M4: 2603.93
A5: 陈福娟 | B5: 21 | C5: 627.38 | D5: 1628.55 | E5: 174 | F5: 174 | G5: 0 | H5: 0 | I5: 0 | J5: 0 | K5: 801.38 | L5: 1802.55 | M5: 2603.93
A6: 陈敏 | B6: 21 | C6: 627.38 | D6: 1628.55 | E6: 174 | F6: 174 | G6: 0 | H6: 0 | I6: 0 | J6: 0 | K6: 801.38 | L6: 1802.55 | M6: 2603.93
A7: 陈芹 | B7: 21 | C7: 627.38 | D7: 1628.55 | E7: 174 | F7: 174 | G7: 0 | H7: 0 | I7: 0 | J7: 0 | K7: 801.38 | L7: 1802.55 | M7: 2603.93
A8: 邓辉 | B8: 21 | C8: 627.38 | D8: 1628.55 | E8: 174 | F8: 174 | G8: 0 | H8: 0 | I8: 0 | J8: 0 | K8: 801.38 | L8: 1802.55 | M8: 2603.93
A9: 东港 | B9: 21 | C9: 627.38 | D9: 1628.55 | E9: 174 | F9: 174 | G9: 0 | H9: 0 | I9: 0 | J9: 0 | K9: 801.38 | L9: 1802.55 | M9: 2603.93
A10: 范祖容 | B10: 21 | C10: 627.38 | D10: 1628.55 | E10: 174 | F10: 174 | G10: 0 | H10: 0 | I10: 0 | J10: 0 | K10: 801.38 | L10: 1802.55 | M10: 2603.93
A11: 戈艳青 | B11: 21 | C11: 627.38 | D11: 1628.55 | E11: 174 | F11: 174 | G11: 0 | H11: 0 | I11: 0 | J11: 0 | K11: 801.38 | L11: 1802.55 | M11: 2603.93
A12: 葛菊 | B12: 21 | C12: 627.38 | D12: 1628.55 | E12: 174 | F12: 174 | G12: 0 | H12: 0 | I12: 0 | J12: 0 | K12: 801.38 | L12: 1802.55 | M12: 2603.93
A13: 顾建凤 | B13: 21 | C13: 627.38 | D13: 1628.55 | E13: 181 | F13: 181 | G13: 0 | H13: 0 | I13: 0 | J13: 0 | K13: 808.38 | L13: 1809.55 | M13: 2617.93
A14: 顾永芳 | B14: 21 | C14: 627.38 | D14: 1628.55 | E14: 174 | F14: 174 | G14: 0 | H14: 0 | I14: 0 | J14: 0 | K14: 801.38 | L14: 1802.55 | M14: 2603.93
A15: 管兵娥 | B15: 21 | C15: 627.38 | D15: 1628.55 | E15: 174 | F15: 174 | G15: 0 | H15: 0 | I15: 0 | J15: 0 | K15: 801.38 | L15: 1802.55 | M15: 2603.93
... A44: 孙会会 | B44: 21 | C44: 627.38 | D44: 1628.55 | E44: 174 | F44: 174 | G44: 0 | H44: 0 | I44: 0 | J44: 0 | K44: 801.38 | L44: 1802.55 | M44: 2603.93
A45: 王冬梅 | B45: 21 | G45: 0 | H45: 0 | I45: 0 | J45: 0
A46: 王红 | B46: 21 | C46: 627.38 | D46: 1628.55 | E46: 174 | F46: 174 | G46: 0 | H46: 0 | I46: 0 | J46: 0 | K46: 801.38 | L46: 1802.55 | M46: 2603.93
A47: 王丽莉 | B47: 21 | C47: 627.38 | D47: 1628.55 | E47: 174 | F47: 174 | G47: 0 | H47: 0 | I47: 0 | J47: 0 | K47: 801.38 | L47: 1802.55 | M47: 2603.93
A48: 王美芳 | B48: 21 | C48: 627.38 | D48: 1628.55 | E48: 174 | F48: 174 | G48: 0 | H48: 0 | I48: 0 | J48: 0 | K48: 801.38 | L48: 1802.55 | M48: 2603.93
A49: 王琴 | B49: 21 | C49: 627.38 | D49: 1628.55 | E49: 174 | F49: 174 | G49: 0 | H49: 0 | I49: 0 | J49: 0 | K49: 801.38 | L49: 1802.55 | M49: 2603.93
A50: 王琴芬 | B50: 21 | C50: 627.38 | D50: 1628.55 | E50: 174 | F50: 174 | G50: 0 | H50: 0 | I50: 0 | J50: 0 | K50: 801.38 | L50: 1802.55 | M50: 2603.93
A51: 王霞芹 | B51: 21 | C51: 627.38 | D51: 1628.55 | E51: 174 | F51: 174 | G51: 0 | H51: 0 | I51: 0 | J51: 0 | K51: 801.38 | L51: 1802.55 | M51: 2603.93
A52: 王先芬 | B52: 21 | C52: 627.38 | D52: 1628.55 | E52: 181 | F52: 181 | G52: 0 | H52: 0 | I52: 0 | J52: 0 | K52: 808.38 | L52: 1809.55 | M52: 2617.93
A53: 王小玉 | B53: 21 | C53: 627.38 | D53: 1628.55 | E53: 174 | F53: 174 | G53: 0 | H53: 0 | I53: 0 | J53: 0 | K53: 801.38 | L53: 1802.55 | M53: 2603.93
A54: 王永富 | B54: 21 | C54: 627.38 | D54: 1628.55 | E54: 174 | F54: 174 | G54: 0 | H54: 0 | I54: 0 | J54: 0 | K54: 801.38 | L54: 1802.55 | M54: 2603.93
A55: 王运乐 | B55: 21 | C55: 627.38 | D55: 1628.55 | E55: 174 | F55: 174 | G55: 0 | H55: 0 | I55: 0 | J55: 0 | K55: 801.38 | L55: 1802.55 | M55: 2603.93
A56: 魏永慧 | B56: 21 | C56: 627.38 | D56: 1628.55 | E56: 174 | F56: 174 | G56: 0 | H56: 0 | I56: 0 | J56: 0 | K56: 801.38 | L56: 1802.55 | M56: 2603.93
A57: 温标 | B57: 21 | C57: 627.38 | D57: 1628.55 | E57: 174 | F57: 174 | G57: 0 | H57: 0 | I57: 0 | J57: 0 | K57: 801.38 | L57: 1802.55 | M57: 2603.93
... A59: 许敏 | B59: 21 | C59: 627.38 | D59: 1628.55 | E59: 174 | F59: 174 | G59: 0 | H59: 0 | I59: 0 | J59: 0 | K59: 801.38 | L59: 1802.55 | M59: 2603.93
A60: 严师飞 | B60: 21
A61: 杨金祥 | B61: 21 | C61: 627.38 | D61: 1628.55 | E61: 174 | F61: 174 | G61: 0 | H61: 0 | I61: 0 | J61: 0 | K61: 801.38 | L61: 1802.55 | M61: 2603.93
A62: 杨艺江 | B62: 21 | C62: 627.38 | D62: 1628.55 | E62: 174 | F62: 174 | G62: 0 | H62: 0 | I62: 0 | J62: 0 | K62: 801.38 | L62: 1802.55 | M62: 2603.93
A63: 叶红梅 | B63: 21 | C63: 627.38 | D63: 1628.55 | E63: 174 | F63: 174 | G63: 0 | H63: 0 | I63: 0 | J63: 0 | K63: 801.38 | L63: 1802.55 | M63: 2603.93
A64: 禹海霞 | B64: 21 | C64: 627.38 | D64: 1628.55 | E64: 174 | F64: 174 | G64: 0 | H64: 0 | I64: 0 | J64: 0 | K64: 801.38 | L64: 1802.55 | M64: 2603.93
A65: 曾红梅 | B65: 21 | C65: 627.38 | D65: 1628.55 | E65: 174 | F65: 174 | G65: 0 | H65: 0 | I65: 0 | J65: 0 | K65: 801.38 | L65: 1802.55 | M65: 2603.93
A66: 张丹 | B66: 21 | C66: 627.38 | D66: 1628.55 | E66: 174 | F66: 174 | G66: 0 | H66: 0 | I66: 0 | J66: 0 | K66: 801.38 | L66: 1802.55 | M66: 2603.93
A67: 张海霞 | B67: 21 | C67: 627.38 | D67: 1628.55 | E67: 174 | F67: 174 | G67: 0 | H67: 0 | I67: 0 | J67: 0 | K67: 801.38 | L67: 1802.55 | M67: 2603.93
A68: 张花丽 | B68: 21 | C68: 627.38 | D68: 1628.55 | E68: 174 | F68: 174 | G68: 0 | H68: 0 | I68: 0 | J68: 0 | K68: 801.38 | L68: 1802.55 | M68: 2603.93
A69: 张继秀 | B69: 21 | C69: 627.38 | D69: 1628.55 | E69: 174 | F69: 174 | G69: 0 | H69: 0 | I69: 0 | J69: 0 | K69: 801.38 | L69: 1802.55 | M69: 2603.93
A70: 张梅芳 | B70: 21 | C70: 627.38 | D70: 1628.55 | E70: 174 | F70: 174 | G70: 0 | H70: 0 | I70: 0 | J70: 0 | K70: 801.38 | L70: 1802.55 | M70: 2603.93
A71: 张学良 | B71: 21 | C71: 627.38 | D71: 1628.55 | E71: 174 | F71: 174 | G71: 0 | H71: 0 | I71: 0 | J71: 0 | K71: 801.38 | L71: 1802.55 | M71: 2603.93
A72: 赵荣 | B72: 21 | C72: 627.38 | D72: 1628.55 | E72: 174 | F72: 174 | G72: 0 | H72: 0 | I72: 0 | J72: 0 | K72: 801.38 | L72: 1802.55 | M72: 2603.93
... A74: 周菊 | B74: 21 | C74: 627.38 | D74: 1628.55 | E74: 174 | F74: 174 | G74: 0 | H74: 0 | I74: 0 | J74: 0 | K74: 801.38 | L74: 1802.55 | M74: 2603.93
A75: 周梦梦 | B75: 21
A76: 朱大玉 | B76: 21 | C76: 627.38 | D76: 1628.55 | E76: 174 | F76: 174 | G76: 0 | H76: 0 | I76: 0 | J76: 0 | K76: 801.38 | L76: 1802.55 | M76: 2603.93
A77: 朱国丽 | B77: 21 | C77: 627.38 | D77: 1628.55 | E77: 174 | F77: 174 | G77: 0 | H77: 0 | I77: 0 | J77: 0 | K77: 801.38 | L77: 1802.55 | M77: 2603.93
A78: 朱浩 | B78: 21
A79: 宗霞 | B79: 21 | C79: 627.38 | D79: 1628.55 | E79: 174 | F79: 174 | G79: 0 | H79: 0 | I79: 0 | J79: 0 | K79: 801.38 | L79: 1802.55 | M79: 2603.93
A80: 晏章翠 | B80: 21 | C80: 627.38 | D80: 1628.55 | E80: 174 | F80: 174 | G80: 0 | H80: 0 | I80: 0 | J80: 0 | K80: 801.38 | L80: 1802.55 | M80: 2603.93
A81: 顾雅芳 | B81: 21 | C81: 627.38 | D81: 1628.55 | E81: 181 | F81: 181 | G81: 0 | H81: 0 | I81: 0 | J81: 0 | K81: 808.38 | L81: 1809.55 | M81: 2617.93
A82: 刘会兰 | B82: 21 | C82: 627.38 | D82: 1628.55 | E82: 181 | F82: 181 | G82: 0 | H82: 0 | I82: 0 | J82: 0 | K82: 808.38 | L82: 1809.55 | M82: 2617.93
A83: 严洪玉 | B83: 21 | C83: 627.38 | D83: 1628.55 | E83: 181 | F83: 181 | G83: 0 | H83: 0 | I83: 0 | J83: 0 | K83: 808.38 | L83: 1809.55 | M83: 2617.93
A84: 尤英 | B84: 21 | C84: 627.38 | D84: 1628.55 | E84: 181 | F84: 181 | G84: 0 | H84: 0 | I84: 0 | J84: 0 | K84: 808.38 | L84: 1809.55 | M84: 2617.93
A85: 姚友美 | B85: 0 | C85: 627.38 | D85: 1628.55 | E85: 181 | F85: 181 | G85: 0 | H85: 0 | I85: 0 | J85: 0 | K85: 808.38 | L85: 1809.55 | M85: 2617.93
A86: 张孝娟 | B86: 0 | C86: 627.38 | D86: 1628.55 | E86: 181 | F86: 181 | G86: 0 | H86: 0 | I86: 0 | J86: 0 | K86: 808.38 | L86: 1809.55 | M86: 2617.93
A87: 杜艳梅 | B87: 21 | C87: 415.45 | D87: 1007.02 | E87: 161 | F87: 161 | G87: 0 | H87: 0 | I87: 0 | J87: 0 | K87: 576.45 | L87: 1168.02 | M87: 1744.47
A88: 耿良莉 | B88: 21 | C88: 415.45 | D88: 1007.02 | E88: 161 | F88: 161 | G88: 0 | H88: 0 | I88: 0 | J88: 0 | K88: 576.45 | L88: 1168.02 | M88: 1744.47
A89: 霍雪 | B89: 21 | C89: 341.35 | D89: 977.05 | E89: 317 | F89: 317 | G89: 0 | H89: 39.57 | I89: 0 | J89: 0 | K89: 658.35 | L89: 1333.62 | M89: 1991.97
A90: 李芳 | B90: 21 | C90: 415.45 | D90: 1007.02 | E90: 161 | F90: 161 | G90: 0 | H90: 0 | I90: 0 | J90: 0 | K90: 576.45 | L90: 1168.02 | M90: 1744.47
... A104: 毛彩仙 | B104: 900 | C104: 0 | D104: 0 | E104: 0 | F104: 0 | G104: 451.25 | H104: 1051.88 | I104: 0 | J104: 0 | K104: 451.25 | L104: 1051.88 | M104: 1503.13
B105: =SUM(B4:B104) -> 2958 | C105: =SUM(C4:C104) -> 56925.37 | D105: =SUM(D4:D104) -> 146671.74 | E105: =SUM(E4:E104) -> 16624 | F105: =SUM(F4:F104) -> 16624 | G105: =SUM(G4:G104) -> 687.5 | H105: =SUM(H4:H104) -> 1665.89 | I105: =SUM(I4:I104) -> 0 | ... M105: =SUM(M4:M104) -> 239198.5
C108: =C105+G105 -> 57612.87 | D108: =D105+H105 -> 148337.63 | E108: =E105+I105 -> 16624 | F108: =F105 -> 16624
B113: =21*11 -> 231
B114: =B105-B113 -> 2727

Sheet Sheet3
A1: 姓名 | B1: 门店 | C1: 本月应缴金额 | G1: 补缴金额 | K1: 实缴金额
C2: 社保 | E2: 公积金 | G2: 社保 | I2: 公积金 | K2: 个人 | L2: 公司 | M2: 小计
C3: 个人 | D3: 公司 | E3: 个人 | F3: 公司 | G3: 个人 | H3: 公司 | I3: 个人 | J3: 公司 | K3: 个人 | L3: 公司 | M3: 小计
A4: 车文秀 | B4: 21 | C4: 627.38 | D4: 1628.55 | E4: 174 | F4: 174 | G4: 0 | H4: 0 | I4: 0 | J4: 0 | K4: 801.38 | L4: 1802.55 | M4: 2603.93
A5: 陈福娟 | B5: 21 | C5: 627.38 | D5: 1628.55 | E5: 174 | F5: 174 | G5: 0 | H5: 0 | I5: 0 | J5: 0 | K5: 801.38 | L5: 1802.55 | M5: 2603.93
A6: 陈敏 | B6: 21 | C6: 627.38 | D6: 1628.55 | E6: 174 | F6: 174 | G6: 0 | H6: 0 | I6: 0 | J6: 0 | K6: 801.38 | L6: 1802.55 | M6: 2603.93
A7: 陈芹 | B7: 21 | C7: 627.38 | D7: 1628.55 | E7: 174 | F7: 174 | G7: 0 | H7: 0 | I7: 0 | J7: 0 | K7: 801.38 | L7: 1802.55 | M7: 2603.93
A8: 邓辉 | B8: 21 | C8: 627.38 | D8: 1628.55 | E8: 174 | F8: 174 | G8: 0 | H8: 0 | I8: 0 | J8: 0 | K8: 801.38 | L8: 1802.55 | M8: 2603.93
A9: 东港 | B9: 21 | C9: 627.38 | D9: 1628.55 | E9: 174 | F9: 174 | G9: 0 | H9: 0 | I9: 0 | J9: 0 | K9: 801.38 | L9: 1802.55 | M9: 2603.93
A10: 范祖容 | B10: 21 | C10: 627.38 | D10: 1628.55 | E10: 174 | F10: 174 | G10: 0 | H10: 0 | I10: 0 | J10: 0 | K10: 801.38 | L10: 1802.55 | M10: 2603.93
A11: 戈艳青 | B11: 21 | C11: 627.38 | D11: 1628.55 | E11: 174 | F11: 174 | G11: 0 | H11: 0 | I11: 0 | J11: 0 | K11: 801.38 | L11: 1802.55 | M11: 2603.93
A12: 葛菊 | B12: 21 | C12: 627.38 | D12: 1628.55 | E12: 174 | F12: 174 | G12: 0 | H12: 0 | I12: 0 | J12: 0 | K12: 801.38 | L12: 1802.55 | M12: 2603.93
A13: 顾建凤 | B13: 0 | C13: 627.38 | D13: 1628.55 | E13: 181 | F13: 181 | G13: 0 | H13: 0 | I13: 0 | J13: 0 | K13: 808.38 | L13: 1809.55 | M13: 2617.93
A14: 顾永芳 | B14: 21 | C14: 627.38 | D14: 1628.55 | E14: 174 | F14: 174 | G14: 0 | H14: 0 | I14: 0 | J14: 0 | K14: 801.38 | L14: 1802.55 | M14: 2603.93
A15: 管兵娥 | B15: 21 | C15: 627.38 | D15: 1628.55 | E15: 174 | F15: 174 | G15: 0 | H15: 0 | I15: 0 | J15: 0 | K15: 801.38 | L15: 1802.55 | M15: 2603.93
... A115: 郑爱凤 | B115: 21 | C115: 399 | D115: 980.4 | E115: 0 | F115: 0 | G115: 0 | H115: 0 | I115: 0 | J115: 0 | K115: 399 | L115: 980.4 | M115: 1379.4
B116: =SUM(B4:B115) -> 2205 | C116: =SUM(C4:C115) -> 59413.52 | D116: =SUM(D4:D115) -> 152885.67 | E116: =SUM(E4:E115) -> 17432 | F116: =SUM(F4:F115) -> 17432 | G116: =SUM(G4:G115) -> 0 | H116: =SUM(H4:H115) -> 0 | I116: =SUM(I4:I115) -> 0 | ... M116: =SUM(M4:M115) -> 247163.19
K118: =K116+L116 -> 247163.19 | L118: 244545.26 | M118: =K118-L118 -> 2617.93

Sheet Sheet2
A1: 姓名 | D1: 雇主责任险 | E1: 本月应缴金额 | I1: 补缴金额 | M1: 实缴金额
E2: 社保 | G2: 公积金 | I2: 社保 | K2: 公积金 | M2: 个人 | N2: 公司 | O2: 小计
E3: 个人 | F3: 公司 | G3: 个人 | H3: 公司 | I3: 个人 | J3: 公司 | K3: 个人 | L3: 公司 | M3: 个人 | N3: 公司 | O3: 小计
A4: 车文秀 | B4: NKA | D4: 21 | E4: 517.34 | F4: 1342.9 | G4: 174 | H4: 174 | I4: 0 | J4: 0 | K4: 0 | L4: 0 | M4: 691.34 | N4: 1516.9 | O4: 2208.24 | P4: =N4+D4 -> 1537.9
A5: 陈敏 | B5: NKA | D5: 21 | E5: 517.34 | F5: 1342.9 | G5: 174 | H5: 174 | I5: 0 | J5: 0 | K5: 0 | L5: 0 | M5: 691.34 | N5: 1516.9 | O5: 2208.24 | P5: =N5+D5 -> 1537.9
A6: 陈芹 | B6: NKA | D6: 21 | E6: 517.34 | F6: 1342.9 | G6: 174 | H6: 174 | I6: 0 | J6: 0 | K6: 0 | L6: 0 | M6: 691.34 | N6: 1516.9 | O6: 2208.24 | P6: =N6+D6 -> 1537.9
A7: 邓辉 | B7: DT | D7: 21 | E7: 517.34 | F7: 1342.9 | G7: 174 | H7: 174 | I7: 0 | J7: 0 | K7: 0 | L7: 0 | M7: 691.34 | N7: 1516.9 | O7: 2208.24 | P7: =N7+D7 -> 1537.9
A8: 东港 | B8: NKA | D8: 21 | E8: 517.34 | F8: 1342.9 | G8: 174 | H8: 174 | I8: 0 | J8: 0 | K8: 0 | L8: 0 | M8: 691.34 | N8: 1516.9 | O8: 2208.24 | P8: =N8+D8 -> 1537.9
A9: 范祖容 | B9: NKA | D9: 21 | E9: 517.34 | F9: 1342.9 | G9: 174 | H9: 174 | I9: 0 | J9: 0 | K9: 0 | L9: 0 | M9: 691.34 | N9: 1516.9 | O9: 2208.24 | P9: =N9+D9 -> 1537.9
A10: 戈艳青 | B10: NKA | D10: 21 | E10: 517.34 | F10: 1342.9 | G10: 174 | H10: 174 | I10: 0 | J10: 0 | K10: 0 | L10: 0 | M10: 691.34 | N10: 1516.9 | O10: 2208.24 | P10: =N10+D10 -> 1537.9
A11: 顾永芳 | B11: LKA | D11: 21 | E11: 517.34 | F11: 1342.9 | G11: 174 | H11: 174 | I11: 0 | J11: 0 | K11: 0 | L11: 0 | M11: 691.34 | N11: 1516.9 | O11: 2208.24 | P11: =N11+D11 -> 1537.9
A12: 管兵娥 | B12: NKA | D12: 21 | E12: 517.34 | F12: 1342.9 | G12: 174 | H12: 174 | I12: 0 | J12: 0 | K12: 0 | L12: 0 | M12: 691.34 | N12: 1516.9 | O12: 2208.24 | P12: =N12+D12 -> 1537.9
A13: 郭胜霞 | B13: NKA | D13: 21 | E13: 517.34 | F13: 1342.9 | G13: 174 | H13: 174 | I13: 0 | J13: 0 | K13: 0 | L13: 0 | M13: 691.34 | N13: 1516.9 | O13: 2208.24 | P13: =N13+D13 -> 1537.9
A14: 洪艳 | B14: 专促补贴 | D14: 21 | E14: 517.34 | F14: 1342.9 | G14: 174 | H14: 174 | I14: 0 | J14: 0 | K14: 0 | L14: 0 | M14: 691.34 | N14: 1516.9 | O14: 2208.24 | P14: =N14+D14 -> 1537.9
A15: 候广勤 | B15: NKA | D15: 21 | E15: 517.34 | F15: 1342.9 | G15: 174 | H15: 174 | I15: 0 | J15: 0 | K15: 0 | L15: 0 | M15: 691.34 | N15: 1516.9 | O15: 2208.24 | P15: =N15+D15 -> 1537.9
... A121: 孙开艳 | B121: 专促补贴 | D121: 21 | E121: 353.64 | F121: 868.94 | G121: 162 | H121: 162 | I121: 0 | J121: 0 | K121: 0 | L121: 0 | M121: 515.64 | N121: 1030.94 | O121: 1546.58 | P121: =N121+D121 -> 1051.94
D122: =SUM(D4:D121) -> 2415 | E122: =SUM(E4:E121) -> 57709.55 | F122: =SUM(F4:F121) -> 148471.63 | G122: =SUM(G4:G121) -> 20459 | H122: =SUM(H4:H121) -> 20459 | I122: =SUM(I4:I121) -> -67.36 | J122: =SUM(J4:J121) -> -20.21 | K122: =SUM(K4:K121) -> 0 | ... O122: =SUM(O4:O121) -> 247011.61 | P122: =N122+D122 -> 171325.42
O123: 244803 | P123: =N123+D123 -> 0

Sheet 赵多多社保明细
A1: 账务年月 | B1: 大区 | C1: 省区 | D1: 城市群 | E1: 城市 | F1: 城市级别 | G1: 姓名 | H1: 身份证号 | I1: 导购员级别(金牌/银牌/铜牌/合格） | J1: 渠道 （NKA/LKA/DT） | K1: 系统性质 （直营/经销） | L1: 门店名称 | M1: 门店所属系统 | N1: 社保个人扣款
A3: 201812 | B3: 江沪 | C3: 上海-KA | D3: 上海 | E3: 上海 | F3: 一类 | G3: 赵多多 | H3: 34222119930308404X | I3: 合格 | J3: NKA | K3: 直营 | L3: 家乐福联洋店 | M3: 家乐福 | N3: 610.4
A4: 201901 | B4: 江沪 | C4: 上海-KA | D4: 上海 | E4: 上海 | F4: 一类 | G4: 赵多多 | H4: 34222119930308404X | I4: 合格 | J4: NKA | K4: 直营 | L4: 家乐福联洋店 | M4: 家乐福 | N4: 610.4
A5: 201902 | B5: 江沪 | C5: 上海-KA | D5: 上海 | E5: 上海 | F5: 一类 | G5: 赵多多 | H5: 34222119930308404X | I5: 合格 | J5: NKA | K5: 直营 | L5: 家乐福联洋店 | M5: 家乐福 | N5: 610.4
A6: 201903 | B6: 江沪 | C6: 上海-KA | D6: 上海 | E6: 上海 | F6: 一类 | G6: 赵多多 | H6: 34222119930308404X | I6: 合格 | J6: NKA | K6: 直营 | L6: 家乐福联洋店 | M6: 家乐福 | N6: 610.4
A7: 合计 | N7: =SUM(N3:N6) -> 2441.6

Sheet 增减情况
A1: 序号 | B1: 姓名 | C1: 身份证号码 | D1: 服务年月 | E1: 备注
A4: 1 | B4: 徐永华 | C4: 341226198411045044 | D4: 46113 | E4: 新入职
A5: 2
A6: 3
A7: 4

Sheet 开票通知书
A1: 开票通知书
A4: 主数据代码：
A5: 收款单位:上海合杰人才服务有限公司 | K5: 提前开票
A6: 发票号码：__________________
A7: 付款单位：中粮福临门食品营销有限公司上海分公司
A8: 开票时间：__________________
A9: 所属时间：202401
A10: 企业性质：中央国企
A12: 行业 | B12: 产品线 | C12: 风险类型 | D12: 工资 | E12: 社保（2023307） | F12: 公积金（202307） | G12: 离岗补贴 | H12: 奖金 | I12: 代垫费用 | J12: 代报销 | K12: 代报销附加税 | L12: 服务费 | M12: 外划服务费 | N12: 其他 | O12: 小计 | P12: 附加税 | Q12: 不含税金额 | R12: 增值税 | S12: 发票总金额 | T12: 备注
A13: 零售服务 | B13: 岗位外包 | C13: 风险后置 | D13: =付款通知书!D13 -> 114589.63 | E13: =付款通知书!D14 -> 92121.98 | F13: =付款通知书!D15 -> 12808 | L13: =付款通知书!D16 -> 4390.39 | M13: 0 | N13: =付款通知书!D17 -> 649.11 | O13: =ROUND(SUM(D13:N13),2) -> 224559.11 | P13: =ROUND(Q13-O13,2) -> 1652.42 | Q13: =ROUND(S13/(1+6%),2) -> 226211.53 | R13: =ROUND(Q13*6%,2) -> 13572.69 | S13: =ROUND(O13*(1+6.78%),2) -> 239784.22 | T13: 上海分-长促KA | U13: =R13+Q13-S13 -> 0 | V13: =O13+P13-Q13 -> 0
A15: 合计 | D15: =SUM(D13:D13) -> 114589.63 | E15: =SUM(E13:E13) -> 92121.98 | F15: =SUM(F13:F13) -> 12808 | G15: =SUM(G13:G13) -> 0 | H15: =SUM(H13:H13) -> 0 | I15: =SUM(I13:I13) -> 0 | J15: =SUM(J13:J13) -> 0 | K15: =SUM(K13:K13) -> 0 | ... S15: =SUM(S13:S13) -> 239784.22
A21: 备注： | L21: 部门： | M21: 业务二部
L22: 制单人： | M22: 宋晓燕
A23: 本地保障服务费 | L23: 申请日期： | M23: =TODAY() -> 46132
A24: 外地保障服务费 | L24: 部门主管：
A25: 雇主责任险 | D25: 0

Sheet Sheet1
A1: 姓名 | B1: 雇主责任险 | C1: 实缴金额
C2: 个人 | D2: 公司 | E2: 小计
C3: 个人 | D3: 公司 | E3: 小计
A4: 车文秀 | B4: 21 | C4: 801.38 | D4: 1802.55 | E4: 2603.93
A5: 陈福娟 | B5: 21 | C5: 801.38 | D5: 1802.55 | E5: 2603.93
A6: 陈敏 | B6: 21 | C6: 801.38 | D6: 1802.55 | E6: 2603.93
A7: 陈芹 | B7: 21 | C7: 801.38 | D7: 1802.55 | E7: 2603.93
A8: 邓辉 | B8: 21 | C8: 801.38 | D8: 1802.55 | E8: 2603.93
A9: 东港 | B9: 21 | C9: 801.38 | D9: 1802.55 | E9: 2603.93
A10: 范祖容 | B10: 21 | C10: 801.38 | D10: 1802.55 | E10: 2603.93
A11: 戈艳青 | B11: 21 | C11: 801.38 | D11: 1802.55 | E11: 2603.93
A12: 葛菊 | B12: 21 | C12: 801.38 | D12: 1802.55 | E12: 2603.93
A13: 顾建凤 | B13: 0 | C13: 808.38 | D13: 1809.55 | E13: 2617.93
A14: 顾永芳 | B14: 21 | C14: 801.38 | D14: 1802.55 | E14: 2603.93
A15: 管兵娥 | B15: 21 | C15: 801.38 | D15: 1802.55 | E15: 2603.93
... A117: 陶宝芹 | B117: 21 | C117: 399 | D117: 980.4 | E117: 1379.4

Sheet Sheet5
A1: 姓名 | B1: 雇主责任险 | C1: 本月应缴金额 | G1: 补缴金额 | K1: 实缴金额
C2: 社保 | E2: 公积金 | G2: 社保 | I2: 公积金 | K2: 个人 | L2: 公司 | M2: 小计
C3: 个人 | D3: 公司 | E3: 个人 | F3: 公司 | G3: 个人 | H3: 公司 | I3: 个人 | J3: 公司 | K3: 个人 | L3: 公司 | M3: 小计
A4: 车文秀 | B4: 21 | C4: 627.38 | D4: 1628.55 | E4: 174 | F4: 174 | G4: 0 | H4: 0 | I4: 0 | J4: 0 | K4: 801.38 | L4: 1802.55 | M4: 2603.93
A5: 陈福娟 | B5: 21 | C5: 627.38 | D5: 1628.55 | E5: 174 | F5: 174 | G5: 0 | H5: 0 | I5: 0 | J5: 0 | K5: 801.38 | L5: 1802.55 | M5: 2603.93
A6: 陈敏 | B6: 21 | C6: 627.38 | D6: 1628.55 | E6: 174 | F6: 174 | G6: 0 | H6: 0 | I6: 0 | J6: 0 | K6: 801.38 | L6: 1802.55 | M6: 2603.93
A7: 陈芹 | B7: 21 | C7: 627.38 | D7: 1628.55 | E7: 174 | F7: 174 | G7: 0 | H7: 0 | I7: 0 | J7: 0 | K7: 801.38 | L7: 1802.55 | M7: 2603.93
A8: 邓辉 | B8: 21 | C8: 627.38 | D8: 1628.55 | E8: 174 | F8: 174 | G8: 0 | H8: 0 | I8: 0 | J8: 0 | K8: 801.38 | L8: 1802.55 | M8: 2603.93
A9: 东港 | B9: 21 | C9: 627.38 | D9: 1628.55 | E9: 174 | F9: 174 | G9: 0 | H9: 0 | I9: 0 | J9: 0 | K9: 801.38 | L9: 1802.55 | M9: 2603.93
A10: 范祖容 | B10: 21 | C10: 627.38 | D10: 1628.55 | E10: 174 | F10: 174 | G10: 0 | H10: 0 | I10: 0 | J10: 0 | K10: 801.38 | L10: 1802.55 | M10: 2603.93
A11: 戈艳青 | B11: 21 | C11: 627.38 | D11: 1628.55 | E11: 174 | F11: 174 | G11: 0 | H11: 0 | I11: 0 | J11: 0 | K11: 801.38 | L11: 1802.55 | M11: 2603.93
A12: 葛菊 | B12: 21 | C12: 627.38 | D12: 1628.55 | E12: 174 | F12: 174 | G12: 0 | H12: 0 | I12: 0 | J12: 0 | K12: 801.38 | L12: 1802.55 | M12: 2603.93
A13: 顾建凤 | B13: 21 | C13: 627.38 | D13: 1628.55 | E13: 181 | F13: 181 | G13: 0 | H13: 0 | I13: 0 | J13: 0 | K13: 808.38 | L13: 1809.55 | M13: 2617.93
A14: 顾永芳 | B14: 21 | C14: 627.38 | D14: 1628.55 | E14: 174 | F14: 174 | G14: 0 | H14: 0 | I14: 0 | J14: 0 | K14: 801.38 | L14: 1802.55 | M14: 2603.93
A15: 管兵娥 | B15: 21 | C15: 627.38 | D15: 1628.55 | E15: 174 | F15: 174 | G15: 0 | H15: 0 | I15: 0 | J15: 0 | K15: 801.38 | L15: 1802.55 | M15: 2603.93
... A98: 郑爱凤 | B98: 21 | C98: 0 | D98: 0 | E98: 0 | F98: 0 | G98: 0 | H98: 0 | I98: 0 | J98: 0 | K98: 0 | L98: 0 | M98: 0
B99: =SUM(B4:B98) -> 1974 | C99: =SUM(C4:C98) -> 55224.36 | D99: =SUM(D4:D98) -> 142318.14 | E99: =SUM(E4:E98) -> 16283 | F99: =SUM(F4:F98) -> 16283 | G99: =SUM(G4:G98) -> 0 | H99: =SUM(H4:H98) -> 67.26 | I99: =SUM(I4:I98) -> 0 | ... M99: =SUM(M4:M98) -> 230175.76
C101: =C99+D99+H99 -> 197609.76
C102: =E99+F99 -> 32566
