Workbook

Sheet 结果报表
A1: 薪资年月 | B1: 薪资月 | C1: 主体 | D1: 合同所属地 | E1: 所属薪资包 | F1: 职能块 | G1: 部门 | H1: 门店 | I1: 账单供应商 | J1: 人数 | K1: 工号 | L1: 中文姓名 | M1: 职位 | N1: 聘用日期 | O1: 最后工作日期 | P1: 员工性质 | Q1: 实际出勤工时数 | R1: 月薪 | S1: 小时薪资 | T1: 实发月薪 | U1: 实发小时薪资 | V1: 岗位津贴 | W1: 补贴合计 | X1: 其它补贴 | Y1: 外派补贴 | Z1: 交通补贴 | AA1: 住房补贴 | AB1: 加班费 | AC1: 平时加班费 | AD1: 周末加班费 | AE1: 国假出勤工时 | AF1: 国假加班费合计 | AG1: 外送奖金 | AH1: 奖金 | AI1: 月度绩效奖金 | AJ1: 季度奖金 | AK1: 开发/工程/网规奖金 | AL1: 其他奖金1 | AM1: 其他奖金2 | AN1: 员工推荐奖金 | AO1: 补产假工资 | AP1: OJE酬劳 | AQ1: 年终奖 | AR1: 年度绩效考评奖 | AS1: 年度其它奖金 | AT1: 离职补偿金 | AU1: 税前调整 | AV1: 年假工资 | AW1: 病假工资 | AX1: 全薪假期工资 | AY1: 事假扣款 | AZ1: 病假扣款 | BA1: 产假扣款 | BB1: 税前扣减 | BC1: 年假折现 | BD1: 工会费个人 | BE1: 工会费公司 | BF1: 其它项补税 | BG1: 税后调整 | BH1: 服务费合计 | BI1: 税前工资总额 | BJ1: 养老金个人 | BK1: 医疗金个人 | BL1: 失业金个人 | BM1: 公积金个人 | BN1: 大病个人 | BO1: 补缴养老金个人 | BP1: 补缴医疗金个人 | BQ1: 补缴失业金个人 | BR1: 补缴公积金个人 | BS1: 补缴大病个人 | BT1: 社保合计个人 | BU1: 个人所得税 | BV1: 年终奖税 | BW1: 离职补偿税 | BX1: 个税合计 | BY1: 净收入 | BZ1: 养老金公司 | CA1: 医疗金公司 | CB1: 公积金公司 | CC1: 失业金公司 | CD1: 工伤金公司 | CE1: 生育金公司 | CF1: 大病公司 | CG1: 补缴养老金公司 | CH1: 补缴医疗金公司 | CI1: 补缴失业金公司 | CJ1: 补缴公积金 | CK1: 补缴工伤金公司 | CL1: 补缴生育金公司 | CM1: 补缴大病公司 | CN1: 社保合计公司 | CO1: 公司成本 | CP1: 计提残疾人保障金 | CQ1: 计提商业保险 | CR1: 计提雇主责任险 | CS1: 计提年终奖 | CT1: 计提营运奖金 | CU1: 养老金基数 | CV1: 公积金基数 | CW1: 医疗保险基数 | CX1: 失业保险基数 | CY1: 工伤保险基数 | CZ1: 生育保险基数 | DA1: 财务入账工资 | DB1: 财务入账总费用 | DC1: 开户银行 | DD1: 银行账号 | DE1: 开户银行明确支行 | DF1: 身份证号码 | DG1: 手机号码 | DH1: 工作地 | DI1: 子女教育支出 | DJ1: 住房租金支出 | DK1: 住房贷款利息支出 | DL1: 赡养老人支出 | DM1: 继续教育支出 | DN1: 婴幼儿照护费用 | DO1: 累计税基数 | DP1: 累计税 | DQ1: 累计免扣除数 | DR1: 中间项
A2: =参数!$B$2 -> 2025 | B2: =参数!$B$3 -> 12 | D2: 上海达美乐 | E2: 店铺营运 | F2: =IFERROR(VLOOKUP(K2,源_7银行卡表_Sheet1!$A:$J,6,FALSE),"") -> 华东营运 | G2: 上海2 | H2: 新村店 | I2: 外服-上海门店全职 | J2: 1 | K2: 26123001 | L2: 龚忆秋 | M2: 餐厅经理 | N2: 2012-03-20 | O2: 2025-12-04 | P2: 门店管理组 | Q2: =IF(P2="门店全职",IFERROR(VLOOKUP(K2,源_3考勤报表_考勤表!$F:$BG,34,FALSE),0)+IFERROR(VLOOKUP(K2,源_8补工时表_补当月工时!$A:$AC,14,FALSE),0),IF(P2="门店管理组",IF(IFERROR(VLOOKUP(K2,源_3考勤报表_考勤表!$F:$BG,34,FALSE),0)+IFERROR(VLOOKUP(K2,源_8补工时表_补当月工时!$A:$AC,14,FALSE),0)+IFERROR(VLOOKUP(K2,源_3考勤报表_考勤表!$F:$BG,37,FALSE),0)+IFERROR(VLOOKUP(K2,源_8补工时表_补当月工时!$A:$AC,15,FALSE),0)+IFERROR(VLOOKUP(K2,源_3考勤报表_考勤表!$F:$BG,38,FALSE),0)+IFERROR(VLOOKUP(K2,源_8补工时表_补当月工时!$A:$AC,17,FALSE),0)+IFERROR(VLOOKUP(K2,源_3考勤报表_考勤表!$F:$BG,40,FALSE),0)+IFERROR(VLOOKUP(K2,源_8补工时表_补当月工时!$A:$AC,20,FALSE),0)+IFERROR(VLOOKUP(K2,源_8补工时表_补当月工时!$A:$AC,22,FALSE),0)+IFERROR(VLOOKUP(K2,源_3考勤报表_考勤表!$F:$BG,41,FALSE),0)+IFERROR(VLOOKUP(K2,源_8补工时表_补当月工时!$A:$AC,18,FALSE),0)+IFERROR(VLOOKUP(K2,源_3考勤报表_考勤表!$F:$BG,44,FALSE),0)+IFERROR(VLOOKUP(K2,源_8补工时表_补当月工时!$A:$AC,16,FALSE),0)+IFERROR(VLOOKUP(K2,源_3考勤报表_考勤表!$F:$BG,45,FALSE),0)>=参数!$B$4,参数!$B$4-IFERROR(VLOOKUP(K2,源_3考勤报表_考勤表!$F:$BG,37,FALSE),0)-IFERROR(VLOOKUP(K2,源_8补工时表_补当月工时!$A:$AC,15,FALSE),0)-IFERROR(VLOOKUP(K2,源_3考勤报表_考勤表!$F:$BG,38,FALSE),0)-IFERROR(VLOOKUP(K2,源_8补工时表_补当月工时!$A:$AC,17,FALSE),0)-IFERROR(VLOOKUP(K2,源_3考勤报表_考勤表!$F:$BG,40,FALSE),0)-IFERROR(VLOOKUP(K2,源_8补工时表_补当月工时!$A:$AC,20,FALSE),0)-IFERROR(VLOOKUP(K2,源_8补工时表_补当月工时!$A:$AC,22,FALSE),0)-IFERROR(VLOOKUP(K2,源_3考勤报表_考勤表!$F:$BG,41,FALSE),0)-IFERROR(VLOOKUP(K2,源_8补工时表_补当月工时!$A:$AC,18,FALSE),0)-IFERROR(VLOOKUP(K2,源_3考勤报表_考勤表!$F:$BG,44,FALSE),0)-IFERROR(VLOOKUP(K2,源_8补工时表_补当月工时!$A:$AC,16,FALSE),0)-IFERROR(VLOOKUP(K2,源_3考勤报表_考勤表!$F:$BG,45,FALSE),0),IFERROR(VLOOKUP(K2,源_3考勤报表_考勤表!$F:$BG,34,FALSE),0)+IFERROR(VLOOKUP(K2,源_8补工时表_补当月工时!$A:$AC,14,FALSE),0)),0)) -> 168 | R2: 7514 | S2: 0 | T2: =IF(P2="门店全职",R2/参数!$B$4*(Q2-MAX(IFERROR(VLOOKUP(K2,源_3考勤报表_考勤表!$F:$BG,34,FALSE),0)+IFERROR(VLOOKUP(K2,源_8补工时表_补当月工时!$A:$AC,14,FALSE),0)+IFERROR(VLOOKUP(K2,源_3考勤报表_考勤表!$F:$BG,37,FALSE),0)+IFERROR(VLOOKUP(K2,源_8补工时表_补当月工时!$A:$AC,15,FALSE),0)+IFERROR(VLOOKUP(K2,源_3考勤报表_考勤表!$F:$BG,38,FALSE),0)+IFERROR(VLOOKUP(K2,源_8补工时表_补当月工时!$A:$AC,17,FALSE),0)+IFERROR(VLOOKUP(K2,源_3考勤报表_考勤表!$F:$BG,40,FALSE),0)+IFERROR(VLOOKUP(K2,源_8补工时表_补当月工时!$A:$AC,20,FALSE),0)+IFERROR(VLOOKUP(K2,源_8补工时表_补当月工时!$A:$AC,22,FALSE),0)+IFERROR(VLOOKUP(K2,源_3考勤报表_考勤表!$F:$BG,41,FALSE),0)+IFERROR(VLOOKUP(K2,源_8补工时表_补当月工时!$A:$AC,18,FALSE),0)+IFERROR(VLOOKUP(K2,源_3考勤报表_考勤表!$F:$BG,42,FALSE),0)+IFERROR(VLOOKUP(K2,源_8补工时表_补当月工时!$A:$AC,19,FALSE),0)+IFERROR(VLOOKUP(K2,源_3考勤报表_考勤表!$F:$BG,44,FALSE),0)+IFERROR(VLOOKUP(K2,源_8补工时表_补当月工时!$A:$AC,16,FALSE),0)+IFERROR(VLOOKUP(K2,源_3考勤报表_考勤表!$F:$BG,45,FALSE),0)-参数!$B$4,0)),R2/参数!$B$4*Q2) -> 6860.6087 | U2: 0 | V2: 0 | W2: =X2+Y2+Z2+AA2 -> 25.5 | X2: =IFERROR(VLOOKUP(K2,源_4奖金汇总表_拆分手工算!$A:$N,8,FALSE),0) -> 25.5 | Y2: =IFERROR(VLOOKUP(K2,源_5薪资备忘录_工资调整项!$A:$AC,14,FALSE),0) -> 0 | Z2: =IFERROR(VLOOKUP(K2,源_5薪资备忘录_工资调整项!$A:$AC,16,FALSE),0) -> 0 | AA2: =IFERROR(VLOOKUP(K2,源_5薪资备忘录_工资调整项!$A:$AC,15,FALSE),0) -> 0 | AB2: =AC2+AD2+AF2 -> 0 | AC2: =IF(P2="门店全职",R2/174*MAX(IFERROR(VLOOKUP(K2,源_3考勤报表_考勤表!$F:$BG,34,FALSE),0)+IFERROR(VLOOKUP(K2,源_8补工时表_补当月工时!$A:$AC,14,FALSE),0)+IFERROR(VLOOKUP(K2,源_3考勤报表_考勤表!$F:$BG,37,FALSE),0)+IFERROR(VLOOKUP(K2,源_8补工时表_补当月工时!$A:$AC,15,FALSE),0)+IFERROR(VLOOKUP(K2,源_3考勤报表_考勤表!$F:$BG,38,FALSE),0)+IFERROR(VLOOKUP(K2,源_8补工时表_补当月工时!$A:$AC,17,FALSE),0)+IFERROR(VLOOKUP(K2,源_3考勤报表_考勤表!$F:$BG,40,FALSE),0)+IFERROR(VLOOKUP(K2,源_8补工时表_补当月工时!$A:$AC,20,FALSE),0)+IFERROR(VLOOKUP(K2,源_8补工时表_补当月工时!$A:$AC,22,FALSE),0)+IFERROR(VLOOKUP(K2,源_3考勤报表_考勤表!$F:$BG,41,FALSE),0)+IFERROR(VLOOKUP(K2,源_8补工时表_补当月工时!$A:$AC,18,FALSE),0)+IFERROR(VLOOKUP(K2,源_3考勤报表_考勤表!$F:$BG,42,FALSE),0)+IFERROR(VLOOKUP(K2,源_8补工时表_补当月工时!$A:$AC,19,FALSE),0)+IFERROR(VLOOKUP(K2,源_3考勤报表_考勤表!$F:$BG,44,FALSE),0)+IFERROR(VLOOKUP(K2,源_8补工时表_补当月工时!$A:$AC,16,FALSE),0)+IFERROR(VLOOKUP(K2,源_3考勤报表_考勤表!$F:$BG,45,FALSE),0)-参数!$B$4,0)*1.5,0) -> 0 | AD2: 0 | AE2: =IFERROR(VLOOKUP(K2,源_3考勤报表_考勤表!$F:$BG,46,FALSE),0)+IFERROR(VLOOKUP(K2,源_8补工时表_补当月工时!$A:$AC,25,FALSE),0) -> 0 | AF2: =R2/174*AE2*3 -> 0 | AG2: =IFERROR(VLOOKUP(K2,源_4奖金汇总表_拆分手工算!$A:$N,10,FALSE),0) -> 0 | AH2: =IFERROR(VLOOKUP(K2,源_4奖金汇总表_拆分手工算!$A:$N,5,FALSE),0) -> 0 | AI2: =IFERROR(VLOOKUP(K2,源_4奖金汇总表_拆分手工算!$A:$N,11,FALSE),0) -> 2000 | AJ2: =IFERROR(VLOOKUP(K2,源_4奖金汇总表_拆分手工算!$A:$N,4,FALSE),0) -> 1500 | AK2: =IFERROR(VLOOKUP(K2,源_4奖金汇总表_拆分手工算!$A:$N,3,FALSE),0) -> 9000 | AL2: =IFERROR(VLOOKUP(K2,源_4奖金汇总表_拆分手工算!$A:$N,6,FALSE),0) -> 0 | AM2: =IFERROR(VLOOKUP(K2,源_5薪资备忘录_工资调整项!$A:$AC,18,FALSE),0)+IFERROR(VLOOKUP(K2,源_4奖金汇总表_拆分手工算!$A:$N,7,FALSE),0) -> 0 | AN2: =IFERROR(VLOOKUP(K2,源_5薪资备忘录_工资调整项!$A:$AC,17,FALSE),0) -> 0 | AO2: =IF(OR(IFERROR(VLOOKUP(K2,源_3考勤报表_考勤表!$F:$BG,39,FALSE),0)+IFERROR(VLOOKUP(K2,源_8补工时表_补当月工时!$A:$AC,24,FALSE),0)>0,IFERROR(VLOOKUP(K2,源_3考勤报表_考勤表!$F:$BG,43,FALSE),0)+IFERROR(VLOOKUP(K2,源_8补工时表_补当月工时!$A:$AC,26,FALSE),0)>0),IF(IFERROR(VLOOKUP(DH2,源_11产假政策_Sheet1!$C:$F,4,FALSE),"")="是",R2/参数!$B$4*(IFERROR(VLOOKUP(K2,源_3考勤报表_考勤表!$F:$BG,39,FALSE),0)+IFERROR(VLOOKUP(K2,源_8补工时表_补当月工时!$A:$AC,24,FALSE),0)+IFERROR(VLOOKUP(K2,源_3考勤报表_考勤表!$F:$BG,43,FALSE),0)+IFERROR(VLOOKUP(K2,源_8补工时表_补当月工时!$A:$AC,26,FALSE),0)),IFERROR(VLOOKUP(K2,源_5薪资备忘录_工资调整项!$A:$AC,19,FALSE),0)),0) -> 0 | AP2: 0 | AQ2: =IFERROR(VLOOKUP(K2,源_4奖金汇总表_拆分手工算!$A:$N,12,FALSE),0)+IFERROR(VLOOKUP(K2,源_9年终奖表_Sheet1!$A:$E,3,FALSE),0) -> 0 | AR2: =IFERROR(VLOOKUP(K2,源_4奖金汇总表_拆分手工算!$A:$N,13,FALSE),0)+IFERROR(VLOOKUP(K2,源_9年终奖表_Sheet1!$A:$E,4,FALSE),0) -> 0 | AS2: =IFERROR(VLOOKUP(K2,源_4奖金汇总表_拆分手工算!$A:$N,14,FALSE),0)+IFERROR(VLOOKUP(K2,源_9年终奖表_Sheet1!$A:$E,5,FALSE),0) -> 0 | AT2: =IFERROR(VLOOKUP(K2,源_5薪资备忘录_工资调整项!$A:$AC,20,FALSE),0) -> 0 | AU2: =IFERROR(VLOOKUP(K2,源_5薪资备忘录_工资调整项!$A:$AC,21,FALSE),0)+IFERROR(VLOOKUP(K2,源_4奖金汇总表_拆分手工算!$A:$N,9,FALSE),0) -> 1733.79 | AV2: =R2/参数!$B$4*(IFERROR(VLOOKUP(K2,源_3考勤报表_考勤表!$F:$BG,37,FALSE),0)+IFERROR(VLOOKUP(K2,源_8补工时表_补当月工时!$A:$AC,15,FALSE),0)) -> 653.3913 | AW2: =R2/174*MIN(IFERROR(VLOOKUP(K2,源_3考勤报表_考勤表!$F:$BG,35,FALSE),0),174)*IF(DATEDIF(N2,DATE(参数!$B$2,参数!$B$3+1,0),"Y")<2,0.6,IF(DATEDIF(N2,DATE(参数!$B$2,参数!$B$3+1,0),"Y")<4,0.7,IF(DATEDIF(N2,DATE(参数!$B$2,参数!$B$3+1,0),"Y")<6,0.8,IF(DATEDIF(N2,DATE(参数!$B$2,参数!$B$3+1,0),"Y")<8,0.9,1)))) -> 0 | AX2: =IF(Q2+IFERROR(VLOOKUP(K2,源_3考勤报表_考勤表!$F:$BG,37,FALSE),0)+IFERROR(VLOOKUP(K2,源_8补工时表_补当月工时!$A:$AC,15,FALSE),0)>=参数!$B$4,0,IF(Q2+IFERROR(VLOOKUP(K2,源_3考勤报表_考勤表!$F:$BG,37,FALSE),0)+IFERROR(VLOOKUP(K2,源_8补工时表_补当月工时!$A:$AC,15,FALSE),0)+IFERROR(VLOOKUP(K2,源_3考勤报表_考勤表!$F:$BG,38,FALSE),0)+IFERROR(VLOOKUP(K2,源_8补工时表_补当月工时!$A:$AC,17,FALSE),0)+IFERROR(VLOOKUP(K2,源_3考勤报表_考勤表!$F:$BG,40,FALSE),0)+IFERROR(VLOOKUP(K2,源_8补工时表_补当月工时!$A:$AC,20,FALSE),0)+IFERROR(VLOOKUP(K2,源_8补工时表_补当月工时!$A:$AC,22,FALSE),0)+IFERROR(VLOOKUP(K2,源_3考勤报表_考勤表!$F:$BG,41,FALSE),0)+IFERROR(VLOOKUP(K2,源_8补工时表_补当月工时!$A:$AC,18,FALSE),0)+IFERROR(VLOOKUP(K2,源_3考勤报表_考勤表!$F:$BG,42,FALSE),0)+IFERROR(VLOOKUP(K2,源_8补工时表_补当月工时!$A:$AC,19,FALSE),0)+IFERROR(VLOOKUP(K2,源_3考勤报表_考勤表!$F:$BG,44,FALSE),0)+IFERROR(VLOOKUP(K2,源_8补工时表_补当月工时!$A:$AC,16,FALSE),0)+IFERROR(VLOOKUP(K2,源_3考勤报表_考勤表!$F:$BG,45,FALSE),0)<=参数!$B$4,R2/参数!$B$4*(IFERROR(VLOOKUP(K2,源_3考勤报表_考勤表!$F:$BG,38,FALSE),0)+IFERROR(VLOOKUP(K2,源_8补工时表_补当月工时!$A:$AC,17,FALSE),0)+IFERROR(VLOOKUP(K2,源_3考勤报表_考勤表!$F:$BG,40,FALSE),0)+IFERROR(VLOOKUP(K2,源_8补工时表_补当月工时!$A:$AC,20,FALSE),0)+IFERROR(VLOOKUP(K2,源_8补工时表_补当月工时!$A:$AC,22,FALSE),0)+IFERROR(VLOOKUP(K2,源_3考勤报表_考勤表!$F:$BG,41,FALSE),0)+IFERROR(VLOOKUP(K2,源_8补工时表_补当月工时!$A:$AC,18,FALSE),0)+IFERROR(VLOOKUP(K2,源_3考勤报表_考勤表!$F:$BG,42,FALSE),0)+IFERROR(VLOOKUP(K2,源_8补工时表_补当月工时!$A:$AC,19,FALSE),0)+IFERROR(VLOOKUP(K2,源_3考勤报表_考勤表!$F:$BG,44,FALSE),0)+IFERROR(VLOOKUP(K2,源_8补工时表_补当月工时!$A:$AC,16,FALSE),0)+IFERROR(VLOOKUP(K2,源_3考勤报表_考勤表!$F:$BG,45,FALSE),0)),0)) -> 0 | AY2: 0 | AZ2: 0 | BA2: 0 | BB2: 0 | BC2: =IFERROR(VLOOKUP(K2,源_5薪资备忘录_工资调整项!$A:$AC,25,FALSE),0) -> 0 | BD2: 0 | BE2: 0 | BF2: 0 | BG2: =IFERROR(VLOOKUP(K2,源_5薪资备忘录_工资调整项!$A:$AC,22,FALSE),0)+IFERROR(VLOOKUP(K2,源_5薪资备忘录_工资调整项!$A:$AC,23,FALSE),0)+IFERROR(VLOOKUP(K2,源_5薪资备忘录_工资调整项!$A:$AC,24,FALSE),0) -> 0 | BH2: =IFERROR(VLOOKUP(DF2,源_6社保表_Sheet1!$C:$CD,80,FALSE),0)+4.5 -> 6.5 | BI2: =T2+W2+AB2+AG2+AH2+AI2+AJ2+AK2+AL2+AM2+AN2+AO2+AP2+AQ2+AR2+AS2+AT2+AU2+AV2+AW2+AX2+BC2 -> 21773.29 | BJ2: =IFERROR(VLOOKUP(DF2,源_6社保表_Sheet1!$C:$BZ,26,FALSE),0) -> 782.96 | BK2: =IFERROR(VLOOKUP(DF2,源_6社保表_Sheet1!$C:$BZ,27,FALSE),0) -> 195.74 | BL2: =IFERROR(VLOOKUP(DF2,源_6社保表_Sheet1!$C:$BZ,28,FALSE),0) -> 48.935 | BM2: =IFERROR(VLOOKUP(DF2,源_6社保表_Sheet1!$C:$BZ,30,FALSE),0) -> 685.09 | BN2: =IFERROR(VLOOKUP(DF2,源_6社保表_Sheet1!$C:$BZ,29,FALSE),0) -> 0 | BO2: =IFERROR(VLOOKUP(DF2,源_6社保表_Sheet1!$C:$BZ,40,FALSE),0) -> 700.96 | BP2: =IFERROR(VLOOKUP(DF2,源_6社保表_Sheet1!$C:$BZ,41,FALSE),0) -> 100.74 | BQ2: =IFERROR(VLOOKUP(DF2,源_6社保表_Sheet1!$C:$BZ,42,FALSE),0) -> 40.935 | BR2: =IFERROR(VLOOKUP(DF2,源_6社保表_Sheet1!$C:$BZ,44,FALSE),0) -> 600.09 | BS2: =IFERROR(VLOOKUP(DF2,源_6社保表_Sheet1!$C:$BZ,43,FALSE),0) -> 0 | BT2: =BJ2+BK2+BL2+BM2+BN2+BO2+BP2+BQ2+BR2+BS2 -> 3155.45 | BU2: 0 | BV2: 0 | BW2: 0 | BX2: =BU2+BV2+BW2 -> 0 | BY2: 0 | BZ2: =IFERROR(VLOOKUP(DF2,源_6社保表_Sheet1!$C:$BZ,18,FALSE),0) -> 1565.92 | CA2: =IFERROR(VLOOKUP(DF2,源_6社保表_Sheet1!$C:$BZ,19,FALSE),0) -> 880.83 | CB2: =IFERROR(VLOOKUP(DF2,源_6社保表_Sheet1!$C:$BZ,24,FALSE),0) -> 685.09 | CC2: =IFERROR(VLOOKUP(DF2,源_6社保表_Sheet1!$C:$BZ,20,FALSE),0) -> 48.935 | CD2: =IFERROR(VLOOKUP(DF2,源_6社保表_Sheet1!$C:$BZ,21,FALSE),0) -> 31.3184 | CE2: =IFERROR(VLOOKUP(DF2,源_6社保表_Sheet1!$C:$BZ,22,FALSE),0) -> 0 | CF2: =IFERROR(VLOOKUP(DF2,源_6社保表_Sheet1!$C:$BZ,23,FALSE),0) -> 0 | CG2: =IFERROR(VLOOKUP(DF2,源_6社保表_Sheet1!$C:$BZ,32,FALSE),0) -> 1500.92 | CH2: =IFERROR(VLOOKUP(DF2,源_6社保表_Sheet1!$C:$BZ,33,FALSE),0) -> 800.83 | CI2: =IFERROR(VLOOKUP(DF2,源_6社保表_Sheet1!$C:$BZ,34,FALSE),0) -> 40.935 | CJ2: =IFERROR(VLOOKUP(DF2,源_6社保表_Sheet1!$C:$BZ,38,FALSE),0) -> 600.09 | CK2: =IFERROR(VLOOKUP(DF2,源_6社保表_Sheet1!$C:$BZ,35,FALSE),0) -> 30.3184 | CL2: =IFERROR(VLOOKUP(DF2,源_6社保表_Sheet1!$C:$BZ,36,FALSE),0) -> 0 | CM2: =IFERROR(VLOOKUP(DF2,源_6社保表_Sheet1!$C:$BZ,37,FALSE),0) -> 0 | CN2: =BZ2+CA2+CB2+CC2+CD2+CE2+CF2+CG2+CH2+CI2+CJ2+CK2+CL2+CM2 -> 6185.1868 | CO2: =BI2+BG2+CN2+BE2+BH2 -> 27964.977 | CP2: =IF(IFERROR(VLOOKUP(K2,源_13残疾人信息_残疾人信息!$A:$M,1,FALSE),"")<>"",0,IF(OR(P2="门店全职",P2="门店管理组",P2="全职(非门店)"),(BI2-AT2)*IFERROR(VLOOKUP(D2,源_12计提残保金规则_Sheet1!$A:$E,4,FALSE),0)*IFERROR(VLOOKUP(D2,源_12计提残保金规则_Sheet1!$A:$E,5,FALSE),0),0)) -> 293.93942 | CQ2: =IF(M2="行政",0,16.05) -> 16.05 | CR2: =IF(M2="门卫",0,20.67) -> 20.67 | CS2: =IF(DATEVALUE(N2)>DATE(参数!$B$2,9,30),0,IF(M2="行政",0,IF(O2="",R2/12,IF(MONTH(DATEVALUE(O2))=参数!$B$3,0,IF(DATEVALUE(O2)<DATE(参数!$B$2,参数!$B$3,1),0,R2/12))))) -> 0 | CT2: =IF(P2="门店管理组",R2*0.12*0.85,0) -> 766.428 | CU2: =IFERROR(VLOOKUP(DF2,源_6社保表_Sheet1!$C:$I,2,FALSE),0) -> 9787 | CV2: =IFERROR(VLOOKUP(DF2,源_6社保表_Sheet1!$C:$I,7,FALSE),0) -> 9787 | CW2: =IFERROR(VLOOKUP(DF2,源_6社保表_Sheet1!$C:$I,3,FALSE),0) -> 9787 | CX2: =IFERROR(VLOOKUP(DF2,源_6社保表_Sheet1!$C:$I,4,FALSE),0) -> 9787 | CY2: =IFERROR(VLOOKUP(DF2,源_6社保表_Sheet1!$C:$I,5,FALSE),0) -> 9787 | CZ2: =IFERROR(VLOOKUP(DF2,源_6社保表_Sheet1!$C:$I,6,FALSE),0) -> 0 | DA2: =BI2+CN2-AG2-AH2-AI2-AJ2-AK2-AL2-AM2-AQ2-AR2-AS2-AT2 -> 15458.477 | DB2: =DA2+CP2+CQ2+CR2+CS2+CT2+BH2 -> 16562.064 | DC2: =IFERROR(VLOOKUP(K2,源_7银行卡表_Sheet1!$A:$J,8,FALSE),"") -> 招商银行 | DD2: =IFERROR(VLOOKUP(K2,源_7银行卡表_Sheet1!$A:$J,9,FALSE),"") -> 6684906511538095695 | DE2: =IFERROR(VLOOKUP(K2,源_7银行卡表_Sheet1!$A:$J,10,FALSE),"") -> 东莞滨海湾新区支行 | DF2: 140000197007051683 | DG2: 16755985896 | DH2: 上海 | DI2: 0 | DJ2: 0 | DK2: 0 | DL2: 0 | DM2: 0 | DN2: 0 | DO2: 0 | DP2: 0 | DQ2: 0 | DR2: =IF(OR(IFERROR(VLOOKUP(K2,源_3考勤报表_考勤表!$F:$BG,39,FALSE),0)+IFERROR(VLOOKUP(K2,源_8补工时表_补当月工时!$A:$AC,24,FALSE),0)=0,IFERROR(VLOOKUP(K2,源_3考勤报表_考勤表!$F:$BG,43,FALSE),0)+IFERROR(VLOOKUP(K2,源_8补工时表_补当月工时!$A:$AC,26,FALSE),0)=0),IF(BI2+BG2-BT2<0,BI2+BG2-BT2,0),0) -> 0
A3: =参数!$B$2 -> 2025 | B3: =参数!$B$3 -> 12 | D3: 上海达美乐 | E3: 店铺营运 | F3: =IFERROR(VLOOKUP(K3,源_7银行卡表_Sheet1!$A:$J,6,FALSE),"") -> 华东营运 | G3: 上海2 | H3: 龙华西路店 | I3: 外服-上海门店全职 | J3: 1 | K3: 26123002 | L3: 程绍辉 | M3: 餐厅经理 | N3: 2014-06-18 | P3: 门店管理组 | Q3: =IF(P3="门店全职",IFERROR(VLOOKUP(K3,源_3考勤报表_考勤表!$F:$BG,34,FALSE),0)+IFERROR(VLOOKUP(K3,源_8补工时表_补当月工时!$A:$AC,14,FALSE),0),IF(P3="门店管理组",IF(IFERROR(VLOOKUP(K3,源_3考勤报表_考勤表!$F:$BG,34,FALSE),0)+IFERROR(VLOOKUP(K3,源_8补工时表_补当月工时!$A:$AC,14,FALSE),0)+IFERROR(VLOOKUP(K3,源_3考勤报表_考勤表!$F:$BG,37,FALSE),0)+IFERROR(VLOOKUP(K3,源_8补工时表_补当月工时!$A:$AC,15,FALSE),0)+IFERROR(VLOOKUP(K3,源_3考勤报表_考勤表!$F:$BG,38,FALSE),0)+IFERROR(VLOOKUP(K3,源_8补工时表_补当月工时!$A:$AC,17,FALSE),0)+IFERROR(VLOOKUP(K3,源_3考勤报表_考勤表!$F:$BG,40,FALSE),0)+IFERROR(VLOOKUP(K3,源_8补工时表_补当月工时!$A:$AC,20,FALSE),0)+IFERROR(VLOOKUP(K3,源_8补工时表_补当月工时!$A:$AC,22,FALSE),0)+IFERROR(VLOOKUP(K3,源_3考勤报表_考勤表!$F:$BG,41,FALSE),0)+IFERROR(VLOOKUP(K3,源_8补工时表_补当月工时!$A:$AC,18,FALSE),0)+IFERROR(VLOOKUP(K3,源_3考勤报表_考勤表!$F:$BG,44,FALSE),0)+IFERROR(VLOOKUP(K3,源_8补工时表_补当月工时!$A:$AC,16,FALSE),0)+IFERROR(VLOOKUP(K3,源_3考勤报表_考勤表!$F:$BG,45,FALSE),0)>=参数!$B$4,参数!$B$4-IFERROR(VLOOKUP(K3,源_3考勤报表_考勤表!$F:$BG,37,FALSE),0)-IFERROR(VLOOKUP(K3,源_8补工时表_补当月工时!$A:$AC,15,FALSE),0)-IFERROR(VLOOKUP(K3,源_3考勤报表_考勤表!$F:$BG,38,FALSE),0)-IFERROR(VLOOKUP(K3,源_8补工时表_补当月工时!$A:$AC,17,FALSE),0)-IFERROR(VLOOKUP(K3,源_3考勤报表_考勤表!$F:$BG,40,FALSE),0)-IFERROR(VLOOKUP(K3,源_8补工时表_补当月工时!$A:$AC,20,FALSE),0)-IFERROR(VLOOKUP(K3,源_8补工时表_补当月工时!$A:$AC,22,FALSE),0)-IFERROR(VLOOKUP(K3,源_3考勤报表_考勤表!$F:$BG,41,FALSE),0)-IFERROR(VLOOKUP(K3,源_8补工时表_补当月工时!$A:$AC,18,FALSE),0)-IFERROR(VLOOKUP(K3,源_3考勤报表_考勤表!$F:$BG,44,FALSE),0)-IFERROR(VLOOKUP(K3,源_8补工时表_补当月工时!$A:$AC,16,FALSE),0)-IFERROR(VLOOKUP(K3,源_3考勤报表_考勤表!$F:$BG,45,FALSE),0),IFERROR(VLOOKUP(K3,源_3考勤报表_考勤表!$F:$BG,34,FALSE),0)+IFERROR(VLOOKUP(K3,源_8补工时表_补当月工时!$A:$AC,14,FALSE),0)),0)) -> 184 | R3: 7809 | S3: 0 | T3: =IF(P3="门店全职",R3/参数!$B$4*(Q3-MAX(IFERROR(VLOOKUP(K3,源_3考勤报表_考勤表!$F:$BG,34,FALSE),0)+IFERROR(VLOOKUP(K3,源_8补工时表_补当月工时!$A:$AC,14,FALSE),0)+IFERROR(VLOOKUP(K3,源_3考勤报表_考勤表!$F:$BG,37,FALSE),0)+IFERROR(VLOOKUP(K3,源_8补工时表_补当月工时!$A:$AC,15,FALSE),0)+IFERROR(VLOOKUP(K3,源_3考勤报表_考勤表!$F:$BG,38,FALSE),0)+IFERROR(VLOOKUP(K3,源_8补工时表_补当月工时!$A:$AC,17,FALSE),0)+IFERROR(VLOOKUP(K3,源_3考勤报表_考勤表!$F:$BG,40,FALSE),0)+IFERROR(VLOOKUP(K3,源_8补工时表_补当月工时!$A:$AC,20,FALSE),0)+IFERROR(VLOOKUP(K3,源_8补工时表_补当月工时!$A:$AC,22,FALSE),0)+IFERROR(VLOOKUP(K3,源_3考勤报表_考勤表!$F:$BG,41,FALSE),0)+IFERROR(VLOOKUP(K3,源_8补工时表_补当月工时!$A:$AC,18,FALSE),0)+IFERROR(VLOOKUP(K3,源_3考勤报表_考勤表!$F:$BG,42,FALSE),0)+IFERROR(VLOOKUP(K3,源_8补工时表_补当月工时!$A:$AC,19,FALSE),0)+IFERROR(VLOOKUP(K3,源_3考勤报表_考勤表!$F:$BG,44,FALSE),0)+IFERROR(VLOOKUP(K3,源_8补工时表_补当月工时!$A:$AC,16,FALSE),0)+IFERROR(VLOOKUP(K3,源_3考勤报表_考勤表!$F:$BG,45,FALSE),0)-参数!$B$4,0)),R3/参数!$B$4*Q3) -> 7809 | U3: 0 | V3: 0 | W3: =X3+Y3+Z3+AA3 -> 7 | X3: =IFERROR(VLOOKUP(K3,源_4奖金汇总表_拆分手工算!$A:$N,8,FALSE),0) -> 7 | Y3: =IFERROR(VLOOKUP(K3,源_5薪资备忘录_工资调整项!$A:$AC,14,FALSE),0) -> 0 | Z3: =IFERROR(VLOOKUP(K3,源_5薪资备忘录_工资调整项!$A:$AC,16,FALSE),0) -> 0 | AA3: =IFERROR(VLOOKUP(K3,源_5薪资备忘录_工资调整项!$A:$AC,15,FALSE),0) -> 0 | AB3: =AC3+AD3+AF3 -> 0 | AC3: =IF(P3="门店全职",R3/174*MAX(IFERROR(VLOOKUP(K3,源_3考勤报表_考勤表!$F:$BG,34,FALSE),0)+IFERROR(VLOOKUP(K3,源_8补工时表_补当月工时!$A:$AC,14,FALSE),0)+IFERROR(VLOOKUP(K3,源_3考勤报表_考勤表!$F:$BG,37,FALSE),0)+IFERROR(VLOOKUP(K3,源_8补工时表_补当月工时!$A:$AC,15,FALSE),0)+IFERROR(VLOOKUP(K3,源_3考勤报表_考勤表!$F:$BG,38,FALSE),0)+IFERROR(VLOOKUP(K3,源_8补工时表_补当月工时!$A:$AC,17,FALSE),0)+IFERROR(VLOOKUP(K3,源_3考勤报表_考勤表!$F:$BG,40,FALSE),0)+IFERROR(VLOOKUP(K3,源_8补工时表_补当月工时!$A:$AC,20,FALSE),0)+IFERROR(VLOOKUP(K3,源_8补工时表_补当月工时!$A:$AC,22,FALSE),0)+IFERROR(VLOOKUP(K3,源_3考勤报表_考勤表!$F:$BG,41,FALSE),0)+IFERROR(VLOOKUP(K3,源_8补工时表_补当月工时!$A:$AC,18,FALSE),0)+IFERROR(VLOOKUP(K3,源_3考勤报表_考勤表!$F:$BG,42,FALSE),0)+IFERROR(VLOOKUP(K3,源_8补工时表_补当月工时!$A:$AC,19,FALSE),0)+IFERROR(VLOOKUP(K3,源_3考勤报表_考勤表!$F:$BG,44,FALSE),0)+IFERROR(VLOOKUP(K3,源_8补工时表_补当月工时!$A:$AC,16,FALSE),0)+IFERROR(VLOOKUP(K3,源_3考勤报表_考勤表!$F:$BG,45,FALSE),0)-参数!$B$4,0)*1.5,0) -> 0 | AD3: 0 | AE3: =IFERROR(VLOOKUP(K3,源_3考勤报表_考勤表!$F:$BG,46,FALSE),0)+IFERROR(VLOOKUP(K3,源_8补工时表_补当月工时!$A:$AC,25,FALSE),0) -> 0 | AF3: =R3/174*AE3*3 -> 0 | AG3: =IFERROR(VLOOKUP(K3,源_4奖金汇总表_拆分手工算!$A:$N,10,FALSE),0) -> 0 | AH3: =IFERROR(VLOOKUP(K3,源_4奖金汇总表_拆分手工算!$A:$N,5,FALSE),0) -> 0 | AI3: =IFERROR(VLOOKUP(K3,源_4奖金汇总表_拆分手工算!$A:$N,11,FALSE),0) -> 1500 | AJ3: =IFERROR(VLOOKUP(K3,源_4奖金汇总表_拆分手工算!$A:$N,4,FALSE),0) -> 1000 | AK3: =IFERROR(VLOOKUP(K3,源_4奖金汇总表_拆分手工算!$A:$N,3,FALSE),0) -> 7000 | AL3: =IFERROR(VLOOKUP(K3,源_4奖金汇总表_拆分手工算!$A:$N,6,FALSE),0) -> 100 | AM3: =IFERROR(VLOOKUP(K3,源_5薪资备忘录_工资调整项!$A:$AC,18,FALSE),0)+IFERROR(VLOOKUP(K3,源_4奖金汇总表_拆分手工算!$A:$N,7,FALSE),0) -> 200 | AN3: =IFERROR(VLOOKUP(K3,源_5薪资备忘录_工资调整项!$A:$AC,17,FALSE),0) -> 0 | AO3: =IF(OR(IFERROR(VLOOKUP(K3,源_3考勤报表_考勤表!$F:$BG,39,FALSE),0)+IFERROR(VLOOKUP(K3,源_8补工时表_补当月工时!$A:$AC,24,FALSE),0)>0,IFERROR(VLOOKUP(K3,源_3考勤报表_考勤表!$F:$BG,43,FALSE),0)+IFERROR(VLOOKUP(K3,源_8补工时表_补当月工时!$A:$AC,26,FALSE),0)>0),IF(IFERROR(VLOOKUP(DH3,源_11产假政策_Sheet1!$C:$F,4,FALSE),"")="是",R3/参数!$B$4*(IFERROR(VLOOKUP(K3,源_3考勤报表_考勤表!$F:$BG,39,FALSE),0)+IFERROR(VLOOKUP(K3,源_8补工时表_补当月工时!$A:$AC,24,FALSE),0)+IFERROR(VLOOKUP(K3,源_3考勤报表_考勤表!$F:$BG,43,FALSE),0)+IFERROR(VLOOKUP(K3,源_8补工时表_补当月工时!$A:$AC,26,FALSE),0)),IFERROR(VLOOKUP(K3,源_5薪资备忘录_工资调整项!$A:$AC,19,FALSE),0)),0) -> 0 | AP3: 0 | AQ3: =IFERROR(VLOOKUP(K3,源_4奖金汇总表_拆分手工算!$A:$N,12,FALSE),0)+IFERROR(VLOOKUP(K3,源_9年终奖表_Sheet1!$A:$E,3,FALSE),0) -> 1200 | AR3: =IFERROR(VLOOKUP(K3,源_4奖金汇总表_拆分手工算!$A:$N,13,FALSE),0)+IFERROR(VLOOKUP(K3,源_9年终奖表_Sheet1!$A:$E,4,FALSE),0) -> 600 | AS3: =IFERROR(VLOOKUP(K3,源_4奖金汇总表_拆分手工算!$A:$N,14,FALSE),0)+IFERROR(VLOOKUP(K3,源_9年终奖表_Sheet1!$A:$E,5,FALSE),0) -> 111 | AT3: =IFERROR(VLOOKUP(K3,源_5薪资备忘录_工资调整项!$A:$AC,20,FALSE),0) -> 0 | AU3: =IFERROR(VLOOKUP(K3,源_5薪资备忘录_工资调整项!$A:$AC,21,FALSE),0)+IFERROR(VLOOKUP(K3,源_4奖金汇总表_拆分手工算!$A:$N,9,FALSE),0) -> 0 | AV3: =R3/参数!$B$4*(IFERROR(VLOOKUP(K3,源_3考勤报表_考勤表!$F:$BG,37,FALSE),0)+IFERROR(VLOOKUP(K3,源_8补工时表_补当月工时!$A:$AC,15,FALSE),0)) -> 0 | AW3: =R3/174*MIN(IFERROR(VLOOKUP(K3,源_3考勤报表_考勤表!$F:$BG,35,FALSE),0),174)*IF(DATEDIF(N3,DATE(参数!$B$2,参数!$B$3+1,0),"Y")<2,0.6,IF(DATEDIF(N3,DATE(参数!$B$2,参数!$B$3+1,0),"Y")<4,0.7,IF(DATEDIF(N3,DATE(参数!$B$2,参数!$B$3+1,0),"Y")<6,0.8,IF(DATEDIF(N3,DATE(参数!$B$2,参数!$B$3+1,0),"Y")<8,0.9,1)))) -> 0 | AX3: =IF(Q3+IFERROR(VLOOKUP(K3,源_3考勤报表_考勤表!$F:$BG,37,FALSE),0)+IFERROR(VLOOKUP(K3,源_8补工时表_补当月工时!$A:$AC,15,FALSE),0)>=参数!$B$4,0,IF(Q3+IFERROR(VLOOKUP(K3,源_3考勤报表_考勤表!$F:$BG,37,FALSE),0)+IFERROR(VLOOKUP(K3,源_8补工时表_补当月工时!$A:$AC,15,FALSE),0)+IFERROR(VLOOKUP(K3,源_3考勤报表_考勤表!$F:$BG,38,FALSE),0)+IFERROR(VLOOKUP(K3,源_8补工时表_补当月工时!$A:$AC,17,FALSE),0)+IFERROR(VLOOKUP(K3,源_3考勤报表_考勤表!$F:$BG,40,FALSE),0)+IFERROR(VLOOKUP(K3,源_8补工时表_补当月工时!$A:$AC,20,FALSE),0)+IFERROR(VLOOKUP(K3,源_8补工时表_补当月工时!$A:$AC,22,FALSE),0)+IFERROR(VLOOKUP(K3,源_3考勤报表_考勤表!$F:$BG,41,FALSE),0)+IFERROR(VLOOKUP(K3,源_8补工时表_补当月工时!$A:$AC,18,FALSE),0)+IFERROR(VLOOKUP(K3,源_3考勤报表_考勤表!$F:$BG,42,FALSE),0)+IFERROR(VLOOKUP(K3,源_8补工时表_补当月工时!$A:$AC,19,FALSE),0)+IFERROR(VLOOKUP(K3,源_3考勤报表_考勤表!$F:$BG,44,FALSE),0)+IFERROR(VLOOKUP(K3,源_8补工时表_补当月工时!$A:$AC,16,FALSE),0)+IFERROR(VLOOKUP(K3,源_3考勤报表_考勤表!$F:$BG,45,FALSE),0)<=参数!$B$4,R3/参数!$B$4*(IFERROR(VLOOKUP(K3,源_3考勤报表_考勤表!$F:$BG,38,FALSE),0)+IFERROR(VLOOKUP(K3,源_8补工时表_补当月工时!$A:$AC,17,FALSE),0)+IFERROR(VLOOKUP(K3,源_3考勤报表_考勤表!$F:$BG,40,FALSE),0)+IFERROR(VLOOKUP(K3,源_8补工时表_补当月工时!$A:$AC,20,FALSE),0)+IFERROR(VLOOKUP(K3,源_8补工时表_补当月工时!$A:$AC,22,FALSE),0)+IFERROR(VLOOKUP(K3,源_3考勤报表_考勤表!$F:$BG,41,FALSE),0)+IFERROR(VLOOKUP(K3,源_8补工时表_补当月工时!$A:$AC,18,FALSE),0)+IFERROR(VLOOKUP(K3,源_3考勤报表_考勤表!$F:$BG,42,FALSE),0)+IFERROR(VLOOKUP(K3,源_8补工时表_补当月工时!$A:$AC,19,FALSE),0)+IFERROR(VLOOKUP(K3,源_3考勤报表_考勤表!$F:$BG,44,FALSE),0)+IFERROR(VLOOKUP(K3,源_8补工时表_补当月工时!$A:$AC,16,FALSE),0)+IFERROR(VLOOKUP(K3,源_3考勤报表_考勤表!$F:$BG,45,FALSE),0)),0)) -> 0 | AY3: 0 | AZ3: 0 | BA3: 0 | BB3: 0 | BC3: =IFERROR(VLOOKUP(K3,源_5薪资备忘录_工资调整项!$A:$AC,25,FALSE),0) -> 0 | BD3: 0 | BE3: 0 | BF3: 0 | BG3: =IFERROR(VLOOKUP(K3,源_5薪资备忘录_工资调整项!$A:$AC,22,FALSE),0)+IFERROR(VLOOKUP(K3,源_5薪资备忘录_工资调整项!$A:$AC,23,FALSE),0)+IFERROR(VLOOKUP(K3,源_5薪资备忘录_工资调整项!$A:$AC,24,FALSE),0) -> 0 | BH3: =IFERROR(VLOOKUP(DF3,源_6社保表_Sheet1!$C:$CD,80,FALSE),0)+4.5 -> 6.5 | BI3: =T3+W3+AB3+AG3+AH3+AI3+AJ3+AK3+AL3+AM3+AN3+AO3+AP3+AQ3+AR3+AS3+AT3+AU3+AV3+AW3+AX3+BC3 -> 19527 | BJ3: =IFERROR(VLOOKUP(DF3,源_6社保表_Sheet1!$C:$BZ,26,FALSE),0) -> 797.68 | BK3: =IFERROR(VLOOKUP(DF3,源_6社保表_Sheet1!$C:$BZ,27,FALSE),0) -> 199.42 | BL3: =IFERROR(VLOOKUP(DF3,源_6社保表_Sheet1!$C:$BZ,28,FALSE),0) -> 49.855 | BM3: =IFERROR(VLOOKUP(DF3,源_6社保表_Sheet1!$C:$BZ,30,FALSE),0) -> 697.97 | BN3: =IFERROR(VLOOKUP(DF3,源_6社保表_Sheet1!$C:$BZ,29,FALSE),0) -> 0 | BO3: =IFERROR(VLOOKUP(DF3,源_6社保表_Sheet1!$C:$BZ,40,FALSE),0) -> 0 | BP3: =IFERROR(VLOOKUP(DF3,源_6社保表_Sheet1!$C:$BZ,41,FALSE),0) -> 0 | BQ3: =IFERROR(VLOOKUP(DF3,源_6社保表_Sheet1!$C:$BZ,42,FALSE),0) -> 0 | BR3: =IFERROR(VLOOKUP(DF3,源_6社保表_Sheet1!$C:$BZ,44,FALSE),0) -> 0 | BS3: =IFERROR(VLOOKUP(DF3,源_6社保表_Sheet1!$C:$BZ,43,FALSE),0) -> 0 | BT3: =BJ3+BK3+BL3+BM3+BN3+BO3+BP3+BQ3+BR3+BS3 -> 1744.925 | BU3: 0 | BV3: 0 | BW3: 0 | BX3: =BU3+BV3+BW3 -> 0 | BY3: 0 | BZ3: =IFERROR(VLOOKUP(DF3,源_6社保表_Sheet1!$C:$BZ,18,FALSE),0) -> 1595.36 | CA3: =IFERROR(VLOOKUP(DF3,源_6社保表_Sheet1!$C:$BZ,19,FALSE),0) -> 897.39 | CB3: =IFERROR(VLOOKUP(DF3,源_6社保表_Sheet1!$C:$BZ,24,FALSE),0) -> 697.97 | CC3: =IFERROR(VLOOKUP(DF3,源_6社保表_Sheet1!$C:$BZ,20,FALSE),0) -> 49.855 | CD3: =IFERROR(VLOOKUP(DF3,源_6社保表_Sheet1!$C:$BZ,21,FALSE),0) -> 31.9072 | CE3: =IFERROR(VLOOKUP(DF3,源_6社保表_Sheet1!$C:$BZ,22,FALSE),0) -> 0 | CF3: =IFERROR(VLOOKUP(DF3,源_6社保表_Sheet1!$C:$BZ,23,FALSE),0) -> 0 | CG3: =IFERROR(VLOOKUP(DF3,源_6社保表_Sheet1!$C:$BZ,32,FALSE),0) -> 0 | CH3: =IFERROR(VLOOKUP(DF3,源_6社保表_Sheet1!$C:$BZ,33,FALSE),0) -> 0 | CI3: =IFERROR(VLOOKUP(DF3,源_6社保表_Sheet1!$C:$BZ,34,FALSE),0) -> 0 | CJ3: =IFERROR(VLOOKUP(DF3,源_6社保表_Sheet1!$C:$BZ,38,FALSE),0) -> 0 | CK3: =IFERROR(VLOOKUP(DF3,源_6社保表_Sheet1!$C:$BZ,35,FALSE),0) -> 0 | CL3: =IFERROR(VLOOKUP(DF3,源_6社保表_Sheet1!$C:$BZ,36,FALSE),0) -> 0 | CM3: =IFERROR(VLOOKUP(DF3,源_6社保表_Sheet1!$C:$BZ,37,FALSE),0) -> 0 | CN3: =BZ3+CA3+CB3+CC3+CD3+CE3+CF3+CG3+CH3+CI3+CJ3+CK3+CL3+CM3 -> 3272.4822 | CO3: =BI3+BG3+CN3+BE3+BH3 -> 22805.982 | CP3: =IF(IFERROR(VLOOKUP(K3,源_13残疾人信息_残疾人信息!$A:$M,1,FALSE),"")<>"",0,IF(OR(P3="门店全职",P3="门店管理组",P3="全职(非门店)"),(BI3-AT3)*IFERROR(VLOOKUP(D3,源_12计提残保金规则_Sheet1!$A:$E,4,FALSE),0)*IFERROR(VLOOKUP(D3,源_12计提残保金规则_Sheet1!$A:$E,5,FALSE),0),0)) -> 263.6145 | CQ3: =IF(M3="行政",0,16.05) -> 16.05 | CR3: =IF(M3="门卫",0,20.67) -> 20.67 | CS3: =IF(DATEVALUE(N3)>DATE(参数!$B$2,9,30),0,IF(M3="行政",0,IF(O3="",R3/12,IF(MONTH(DATEVALUE(O3))=参数!$B$3,0,IF(DATEVALUE(O3)<DATE(参数!$B$2,参数!$B$3,1),0,R3/12))))) -> 650.75 | CT3: =IF(P3="门店管理组",R3*0.12*0.85,0) -> 796.518 | CU3: =IFERROR(VLOOKUP(DF3,源_6社保表_Sheet1!$C:$I,2,FALSE),0) -> 9971 | CV3: =IFERROR(VLOOKUP(DF3,源_6社保表_Sheet1!$C:$I,7,FALSE),0) -> 9971 | CW3: =IFERROR(VLOOKUP(DF3,源_6社保表_Sheet1!$C:$I,3,FALSE),0) -> 9971 | CX3: =IFERROR(VLOOKUP(DF3,源_6社保表_Sheet1!$C:$I,4,FALSE),0) -> 9971 | CY3: =IFERROR(VLOOKUP(DF3,源_6社保表_Sheet1!$C:$I,5,FALSE),0) -> 9971 | CZ3: =IFERROR(VLOOKUP(DF3,源_6社保表_Sheet1!$C:$I,6,FALSE),0) -> 0 | DA3: =BI3+CN3-AG3-AH3-AI3-AJ3-AK3-AL3-AM3-AQ3-AR3-AS3-AT3 -> 11088.482 | DB3: =DA3+CP3+CQ3+CR3+CS3+CT3+BH3 -> 12842.585 | DC3: =IFERROR(VLOOKUP(K3,源_7银行卡表_Sheet1!$A:$J,8,FALSE),"") -> 招商银行 | DD3: =IFERROR(VLOOKUP(K3,源_7银行卡表_Sheet1!$A:$J,9,FALSE),"") -> 6686494367435887888 | DE3: =IFERROR(VLOOKUP(K3,源_7银行卡表_Sheet1!$A:$J,10,FALSE),"") -> 广西自贸试验区南宁片区五 | DF3: 130000195301178797 | DG3: 13789690671 | DH3: 上海 | DI3: 0 | DJ3: 0 | DK3: 0 | DL3: 0 | DM3: 0 | DN3: 0 | DO3: 0 | DP3: 0 | DQ3: 0 | DR3: =IF(OR(IFERROR(VLOOKUP(K3,源_3考勤报表_考勤表!$F:$BG,39,FALSE),0)+IFERROR(VLOOKUP(K3,源_8补工时表_补当月工时!$A:$AC,24,FALSE),0)=0,IFERROR(VLOOKUP(K3,源_3考勤报表_考勤表!$F:$BG,43,FALSE),0)+IFERROR(VLOOKUP(K3,源_8补工时表_补当月工时!$A:$AC,26,FALSE),0)=0),IF(BI3+BG3-BT3<0,BI3+BG3-BT3,0),0) -> 0
A4: =参数!$B$2 -> 2025 | B4: =参数!$B$3 -> 12 | D4: 上海达美乐 | E4: 店铺营运 | F4: =IFERROR(VLOOKUP(K4,源_7银行卡表_Sheet1!$A:$J,6,FALSE),"") -> 华东营运 | G4: 上海2 | H4: 桂林路店 | I4: 外服-上海门店全职 | J4: 1 | K4: 26123003 | L4: 董晚樱 | M4: 餐厅副理 | N4: 2015-07-09 | P4: 门店管理组 | Q4: =IF(P4="门店全职",IFERROR(VLOOKUP(K4,源_3考勤报表_考勤表!$F:$BG,34,FALSE),0)+IFERROR(VLOOKUP(K4,源_8补工时表_补当月工时!$A:$AC,14,FALSE),0),IF(P4="门店管理组",IF(IFERROR(VLOOKUP(K4,源_3考勤报表_考勤表!$F:$BG,34,FALSE),0)+IFERROR(VLOOKUP(K4,源_8补工时表_补当月工时!$A:$AC,14,FALSE),0)+IFERROR(VLOOKUP(K4,源_3考勤报表_考勤表!$F:$BG,37,FALSE),0)+IFERROR(VLOOKUP(K4,源_8补工时表_补当月工时!$A:$AC,15,FALSE),0)+IFERROR(VLOOKUP(K4,源_3考勤报表_考勤表!$F:$BG,38,FALSE),0)+IFERROR(VLOOKUP(K4,源_8补工时表_补当月工时!$A:$AC,17,FALSE),0)+IFERROR(VLOOKUP(K4,源_3考勤报表_考勤表!$F:$BG,40,FALSE),0)+IFERROR(VLOOKUP(K4,源_8补工时表_补当月工时!$A:$AC,20,FALSE),0)+IFERROR(VLOOKUP(K4,源_8补工时表_补当月工时!$A:$AC,22,FALSE),0)+IFERROR(VLOOKUP(K4,源_3考勤报表_考勤表!$F:$BG,41,FALSE),0)+IFERROR(VLOOKUP(K4,源_8补工时表_补当月工时!$A:$AC,18,FALSE),0)+IFERROR(VLOOKUP(K4,源_3考勤报表_考勤表!$F:$BG,44,FALSE),0)+IFERROR(VLOOKUP(K4,源_8补工时表_补当月工时!$A:$AC,16,FALSE),0)+IFERROR(VLOOKUP(K4,源_3考勤报表_考勤表!$F:$BG,45,FALSE),0)>=参数!$B$4,参数!$B$4-IFERROR(VLOOKUP(K4,源_3考勤报表_考勤表!$F:$BG,37,FALSE),0)-IFERROR(VLOOKUP(K4,源_8补工时表_补当月工时!$A:$AC,15,FALSE),0)-IFERROR(VLOOKUP(K4,源_3考勤报表_考勤表!$F:$BG,38,FALSE),0)-IFERROR(VLOOKUP(K4,源_8补工时表_补当月工时!$A:$AC,17,FALSE),0)-IFERROR(VLOOKUP(K4,源_3考勤报表_考勤表!$F:$BG,40,FALSE),0)-IFERROR(VLOOKUP(K4,源_8补工时表_补当月工时!$A:$AC,20,FALSE),0)-IFERROR(VLOOKUP(K4,源_8补工时表_补当月工时!$A:$AC,22,FALSE),0)-IFERROR(VLOOKUP(K4,源_3考勤报表_考勤表!$F:$BG,41,FALSE),0)-IFERROR(VLOOKUP(K4,源_8补工时表_补当月工时!$A:$AC,18,FALSE),0)-IFERROR(VLOOKUP(K4,源_3考勤报表_考勤表!$F:$BG,44,FALSE),0)-IFERROR(VLOOKUP(K4,源_8补工时表_补当月工时!$A:$AC,16,FALSE),0)-IFERROR(VLOOKUP(K4,源_3考勤报表_考勤表!$F:$BG,45,FALSE),0),IFERROR(VLOOKUP(K4,源_3考勤报表_考勤表!$F:$BG,34,FALSE),0)+IFERROR(VLOOKUP(K4,源_8补工时表_补当月工时!$A:$AC,14,FALSE),0)),0)) -> 110 | R4: 5693 | S4: 0 | T4: =IF(P4="门店全职",R4/参数!$B$4*(Q4-MAX(IFERROR(VLOOKUP(K4,源_3考勤报表_考勤表!$F:$BG,34,FALSE),0)+IFERROR(VLOOKUP(K4,源_8补工时表_补当月工时!$A:$AC,14,FALSE),0)+IFERROR(VLOOKUP(K4,源_3考勤报表_考勤表!$F:$BG,37,FALSE),0)+IFERROR(VLOOKUP(K4,源_8补工时表_补当月工时!$A:$AC,15,FALSE),0)+IFERROR(VLOOKUP(K4,源_3考勤报表_考勤表!$F:$BG,38,FALSE),0)+IFERROR(VLOOKUP(K4,源_8补工时表_补当月工时!$A:$AC,17,FALSE),0)+IFERROR(VLOOKUP(K4,源_3考勤报表_考勤表!$F:$BG,40,FALSE),0)+IFERROR(VLOOKUP(K4,源_8补工时表_补当月工时!$A:$AC,20,FALSE),0)+IFERROR(VLOOKUP(K4,源_8补工时表_补当月工时!$A:$AC,22,FALSE),0)+IFERROR(VLOOKUP(K4,源_3考勤报表_考勤表!$F:$BG,41,FALSE),0)+IFERROR(VLOOKUP(K4,源_8补工时表_补当月工时!$A:$AC,18,FALSE),0)+IFERROR(VLOOKUP(K4,源_3考勤报表_考勤表!$F:$BG,42,FALSE),0)+IFERROR(VLOOKUP(K4,源_8补工时表_补当月工时!$A:$AC,19,FALSE),0)+IFERROR(VLOOKUP(K4,源_3考勤报表_考勤表!$F:$BG,44,FALSE),0)+IFERROR(VLOOKUP(K4,源_8补工时表_补当月工时!$A:$AC,16,FALSE),0)+IFERROR(VLOOKUP(K4,源_3考勤报表_考勤表!$F:$BG,45,FALSE),0)-参数!$B$4,0)),R4/参数!$B$4*Q4) -> 3403.4239 | U4: 0 | V4: 0 | W4: =X4+Y4+Z4+AA4 -> 11.5 | X4: =IFERROR(VLOOKUP(K4,源_4奖金汇总表_拆分手工算!$A:$N,8,FALSE),0) -> 11.5 | Y4: =IFERROR(VLOOKUP(K4,源_5薪资备忘录_工资调整项!$A:$AC,14,FALSE),0) -> 0 | Z4: =IFERROR(VLOOKUP(K4,源_5薪资备忘录_工资调整项!$A:$AC,16,FALSE),0) -> 0 | AA4: =IFERROR(VLOOKUP(K4,源_5薪资备忘录_工资调整项!$A:$AC,15,FALSE),0) -> 0 | AB4: =AC4+AD4+AF4 -> 294.46552 | AC4: =IF(P4="门店全职",R4/174*MAX(IFERROR(VLOOKUP(K4,源_3考勤报表_考勤表!$F:$BG,34,FALSE),0)+IFERROR(VLOOKUP(K4,源_8补工时表_补当月工时!$A:$AC,14,FALSE),0)+IFERROR(VLOOKUP(K4,源_3考勤报表_考勤表!$F:$BG,37,FALSE),0)+IFERROR(VLOOKUP(K4,源_8补工时表_补当月工时!$A:$AC,15,FALSE),0)+IFERROR(VLOOKUP(K4,源_3考勤报表_考勤表!$F:$BG,38,FALSE),0)+IFERROR(VLOOKUP(K4,源_8补工时表_补当月工时!$A:$AC,17,FALSE),0)+IFERROR(VLOOKUP(K4,源_3考勤报表_考勤表!$F:$BG,40,FALSE),0)+IFERROR(VLOOKUP(K4,源_8补工时表_补当月工时!$A:$AC,20,FALSE),0)+IFERROR(VLOOKUP(K4,源_8补工时表_补当月工时!$A:$AC,22,FALSE),0)+IFERROR(VLOOKUP(K4,源_3考勤报表_考勤表!$F:$BG,41,FALSE),0)+IFERROR(VLOOKUP(K4,源_8补工时表_补当月工时!$A:$AC,18,FALSE),0)+IFERROR(VLOOKUP(K4,源_3考勤报表_考勤表!$F:$BG,42,FALSE),0)+IFERROR(VLOOKUP(K4,源_8补工时表_补当月工时!$A:$AC,19,FALSE),0)+IFERROR(VLOOKUP(K4,源_3考勤报表_考勤表!$F:$BG,44,FALSE),0)+IFERROR(VLOOKUP(K4,源_8补工时表_补当月工时!$A:$AC,16,FALSE),0)+IFERROR(VLOOKUP(K4,源_3考勤报表_考勤表!$F:$BG,45,FALSE),0)-参数!$B$4,0)*1.5,0) -> 0 | AD4: 0 | AE4: =IFERROR(VLOOKUP(K4,源_3考勤报表_考勤表!$F:$BG,46,FALSE),0)+IFERROR(VLOOKUP(K4,源_8补工时表_补当月工时!$A:$AC,25,FALSE),0) -> 3 | AF4: =R4/174*AE4*3 -> 294.46552 | AG4: =IFERROR(VLOOKUP(K4,源_4奖金汇总表_拆分手工算!$A:$N,10,FALSE),0) -> 0 | AH4: =IFERROR(VLOOKUP(K4,源_4奖金汇总表_拆分手工算!$A:$N,5,FALSE),0) -> 0 | AI4: =IFERROR(VLOOKUP(K4,源_4奖金汇总表_拆分手工算!$A:$N,11,FALSE),0) -> 0 | AJ4: =IFERROR(VLOOKUP(K4,源_4奖金汇总表_拆分手工算!$A:$N,4,FALSE),0) -> 0 | AK4: =IFERROR(VLOOKUP(K4,源_4奖金汇总表_拆分手工算!$A:$N,3,FALSE),0) -> 0 | AL4: =IFERROR(VLOOKUP(K4,源_4奖金汇总表_拆分手工算!$A:$N,6,FALSE),0) -> 212.5 | AM4: =IFERROR(VLOOKUP(K4,源_5薪资备忘录_工资调整项!$A:$AC,18,FALSE),0)+IFERROR(VLOOKUP(K4,源_4奖金汇总表_拆分手工算!$A:$N,7,FALSE),0) -> 200 | AN4: =IFERROR(VLOOKUP(K4,源_5薪资备忘录_工资调整项!$A:$AC,17,FALSE),0) -> 0 | AO4: =IF(OR(IFERROR(VLOOKUP(K4,源_3考勤报表_考勤表!$F:$BG,39,FALSE),0)+IFERROR(VLOOKUP(K4,源_8补工时表_补当月工时!$A:$AC,24,FALSE),0)>0,IFERROR(VLOOKUP(K4,源_3考勤报表_考勤表!$F:$BG,43,FALSE),0)+IFERROR(VLOOKUP(K4,源_8补工时表_补当月工时!$A:$AC,26,FALSE),0)>0),IF(IFERROR(VLOOKUP(DH4,源_11产假政策_Sheet1!$C:$F,4,FALSE),"")="是",R4/参数!$B$4*(IFERROR(VLOOKUP(K4,源_3考勤报表_考勤表!$F:$BG,39,FALSE),0)+IFERROR(VLOOKUP(K4,源_8补工时表_补当月工时!$A:$AC,24,FALSE),0)+IFERROR(VLOOKUP(K4,源_3考勤报表_考勤表!$F:$BG,43,FALSE),0)+IFERROR(VLOOKUP(K4,源_8补工时表_补当月工时!$A:$AC,26,FALSE),0)),IFERROR(VLOOKUP(K4,源_5薪资备忘录_工资调整项!$A:$AC,19,FALSE),0)),0) -> 0 | AP4: 0 | AQ4: =IFERROR(VLOOKUP(K4,源_4奖金汇总表_拆分手工算!$A:$N,12,FALSE),0)+IFERROR(VLOOKUP(K4,源_9年终奖表_Sheet1!$A:$E,3,FALSE),0) -> 1200 | AR4: =IFERROR(VLOOKUP(K4,源_4奖金汇总表_拆分手工算!$A:$N,13,FALSE),0)+IFERROR(VLOOKUP(K4,源_9年终奖表_Sheet1!$A:$E,4,FALSE),0) -> 600 | AS4: =IFERROR(VLOOKUP(K4,源_4奖金汇总表_拆分手工算!$A:$N,14,FALSE),0)+IFERROR(VLOOKUP(K4,源_9年终奖表_Sheet1!$A:$E,5,FALSE),0) -> 222 | AT4: =IFERROR(VLOOKUP(K4,源_5薪资备忘录_工资调整项!$A:$AC,20,FALSE),0) -> 0 | AU4: =IFERROR(VLOOKUP(K4,源_5薪资备忘录_工资调整项!$A:$AC,21,FALSE),0)+IFERROR(VLOOKUP(K4,源_4奖金汇总表_拆分手工算!$A:$N,9,FALSE),0) -> 0 | AV4: =R4/参数!$B$4*(IFERROR(VLOOKUP(K4,源_3考勤报表_考勤表!$F:$BG,37,FALSE),0)+IFERROR(VLOOKUP(K4,源_8补工时表_补当月工时!$A:$AC,15,FALSE),0)) -> 0 | AW4: =R4/174*MIN(IFERROR(VLOOKUP(K4,源_3考勤报表_考勤表!$F:$BG,35,FALSE),0),174)*IF(DATEDIF(N4,DATE(参数!$B$2,参数!$B$3+1,0),"Y")<2,0.6,IF(DATEDIF(N4,DATE(参数!$B$2,参数!$B$3+1,0),"Y")<4,0.7,IF(DATEDIF(N4,DATE(参数!$B$2,参数!$B$3+1,0),"Y")<6,0.8,IF(DATEDIF(N4,DATE(参数!$B$2,参数!$B$3+1,0),"Y")<8,0.9,1)))) -> 261.74713 | AX4: =IF(Q4+IFERROR(VLOOKUP(K4,源_3考勤报表_考勤表!$F:$BG,37,FALSE),0)+IFERROR(VLOOKUP(K4,源_8补工时表_补当月工时!$A:$AC,15,FALSE),0)>=参数!$B$4,0,IF(Q4+IFERROR(VLOOKUP(K4,源_3考勤报表_考勤表!$F:$BG,37,FALSE),0)+IFERROR(VLOOKUP(K4,源_8补工时表_补当月工时!$A:$AC,15,FALSE),0)+IFERROR(VLOOKUP(K4,源_3考勤报表_考勤表!$F:$BG,38,FALSE),0)+IFERROR(VLOOKUP(K4,源_8补工时表_补当月工时!$A:$AC,17,FALSE),0)+IFERROR(VLOOKUP(K4,源_3考勤报表_考勤表!$F:$BG,40,FALSE),0)+IFERROR(VLOOKUP(K4,源_8补工时表_补当月工时!$A:$AC,20,FALSE),0)+IFERROR(VLOOKUP(K4,源_8补工时表_补当月工时!$A:$AC,22,FALSE),0)+IFERROR(VLOOKUP(K4,源_3考勤报表_考勤表!$F:$BG,41,FALSE),0)+IFERROR(VLOOKUP(K4,源_8补工时表_补当月工时!$A:$AC,18,FALSE),0)+IFERROR(VLOOKUP(K4,源_3考勤报表_考勤表!$F:$BG,42,FALSE),0)+IFERROR(VLOOKUP(K4,源_8补工时表_补当月工时!$A:$AC,19,FALSE),0)+IFERROR(VLOOKUP(K4,源_3考勤报表_考勤表!$F:$BG,44,FALSE),0)+IFERROR(VLOOKUP(K4,源_8补工时表_补当月工时!$A:$AC,16,FALSE),0)+IFERROR(VLOOKUP(K4,源_3考勤报表_考勤表!$F:$BG,45,FALSE),0)<=参数!$B$4,R4/参数!$B$4*(IFERROR(VLOOKUP(K4,源_3考勤报表_考勤表!$F:$BG,38,FALSE),0)+IFERROR(VLOOKUP(K4,源_8补工时表_补当月工时!$A:$AC,17,FALSE),0)+IFERROR(VLOOKUP(K4,源_3考勤报表_考勤表!$F:$BG,40,FALSE),0)+IFERROR(VLOOKUP(K4,源_8补工时表_补当月工时!$A:$AC,20,FALSE),0)+IFERROR(VLOOKUP(K4,源_8补工时表_补当月工时!$A:$AC,22,FALSE),0)+IFERROR(VLOOKUP(K4,源_3考勤报表_考勤表!$F:$BG,41,FALSE),0)+IFERROR(VLOOKUP(K4,源_8补工时表_补当月工时!$A:$AC,18,FALSE),0)+IFERROR(VLOOKUP(K4,源_3考勤报表_考勤表!$F:$BG,42,FALSE),0)+IFERROR(VLOOKUP(K4,源_8补工时表_补当月工时!$A:$AC,19,FALSE),0)+IFERROR(VLOOKUP(K4,源_3考勤报表_考勤表!$F:$BG,44,FALSE),0)+IFERROR(VLOOKUP(K4,源_8补工时表_补当月工时!$A:$AC,16,FALSE),0)+IFERROR(VLOOKUP(K4,源_3考勤报表_考勤表!$F:$BG,45,FALSE),0)),0)) -> 0 | AY4: 0 | AZ4: 0 | BA4: 0 | BB4: 0 | BC4: =IFERROR(VLOOKUP(K4,源_5薪资备忘录_工资调整项!$A:$AC,25,FALSE),0) -> 0 | BD4: 0 | BE4: 0 | BF4: 0 | BG4: =IFERROR(VLOOKUP(K4,源_5薪资备忘录_工资调整项!$A:$AC,22,FALSE),0)+IFERROR(VLOOKUP(K4,源_5薪资备忘录_工资调整项!$A:$AC,23,FALSE),0)+IFERROR(VLOOKUP(K4,源_5薪资备忘录_工资调整项!$A:$AC,24,FALSE),0) -> 0 | BH4: =IFERROR(VLOOKUP(DF4,源_6社保表_Sheet1!$C:$CD,80,FALSE),0)+4.5 -> 6.5 | BI4: =T4+W4+AB4+AG4+AH4+AI4+AJ4+AK4+AL4+AM4+AN4+AO4+AP4+AQ4+AR4+AS4+AT4+AU4+AV4+AW4+AX4+BC4 -> 6405.6366 | BJ4: =IFERROR(VLOOKUP(DF4,源_6社保表_Sheet1!$C:$BZ,26,FALSE),0) -> 522.2 | BK4: =IFERROR(VLOOKUP(DF4,源_6社保表_Sheet1!$C:$BZ,27,FALSE),0) -> 74.6 | BL4: =IFERROR(VLOOKUP(DF4,源_6社保表_Sheet1!$C:$BZ,28,FALSE),0) -> 37.3 | BM4: =IFERROR(VLOOKUP(DF4,源_6社保表_Sheet1!$C:$BZ,30,FALSE),0) -> 437.04 | BN4: =IFERROR(VLOOKUP(DF4,源_6社保表_Sheet1!$C:$BZ,29,FALSE),0) -> 0 | BO4: =IFERROR(VLOOKUP(DF4,源_6社保表_Sheet1!$C:$BZ,40,FALSE),0) -> 0 | BP4: =IFERROR(VLOOKUP(DF4,源_6社保表_Sheet1!$C:$BZ,41,FALSE),0) -> 0 | BQ4: =IFERROR(VLOOKUP(DF4,源_6社保表_Sheet1!$C:$BZ,42,FALSE),0) -> 0 | BR4: =IFERROR(VLOOKUP(DF4,源_6社保表_Sheet1!$C:$BZ,44,FALSE),0) -> 0 | BS4: =IFERROR(VLOOKUP(DF4,源_6社保表_Sheet1!$C:$BZ,43,FALSE),0) -> 0 | BT4: =BJ4+BK4+BL4+BM4+BN4+BO4+BP4+BQ4+BR4+BS4 -> 1071.14 | BU4: 0 | BV4: 0 | BW4: 0 | BX4: =BU4+BV4+BW4 -> 0 | BY4: 0 | BZ4: =IFERROR(VLOOKUP(DF4,源_6社保表_Sheet1!$C:$BZ,18,FALSE),0) -> 1119 | CA4: =IFERROR(VLOOKUP(DF4,源_6社保表_Sheet1!$C:$BZ,19,FALSE),0) -> 596.8 | CB4: =IFERROR(VLOOKUP(DF4,源_6社保表_Sheet1!$C:$BZ,24,FALSE),0) -> 437.04 | CC4: =IFERROR(VLOOKUP(DF4,源_6社保表_Sheet1!$C:$BZ,20,FALSE),0) -> 37.3 | CD4: =IFERROR(VLOOKUP(DF4,源_6社保表_Sheet1!$C:$BZ,21,FALSE),0) -> 23.872 | CE4: =IFERROR(VLOOKUP(DF4,源_6社保表_Sheet1!$C:$BZ,22,FALSE),0) -> 0 | CF4: =IFERROR(VLOOKUP(DF4,源_6社保表_Sheet1!$C:$BZ,23,FALSE),0) -> 0 | CG4: =IFERROR(VLOOKUP(DF4,源_6社保表_Sheet1!$C:$BZ,32,FALSE),0) -> 0 | CH4: =IFERROR(VLOOKUP(DF4,源_6社保表_Sheet1!$C:$BZ,33,FALSE),0) -> 0 | CI4: =IFERROR(VLOOKUP(DF4,源_6社保表_Sheet1!$C:$BZ,34,FALSE),0) -> 0 | CJ4: =IFERROR(VLOOKUP(DF4,源_6社保表_Sheet1!$C:$BZ,38,FALSE),0) -> 0 | CK4: =IFERROR(VLOOKUP(DF4,源_6社保表_Sheet1!$C:$BZ,35,FALSE),0) -> 0 | CL4: =IFERROR(VLOOKUP(DF4,源_6社保表_Sheet1!$C:$BZ,36,FALSE),0) -> 0 | CM4: =IFERROR(VLOOKUP(DF4,源_6社保表_Sheet1!$C:$BZ,37,FALSE),0) -> 0 | CN4: =BZ4+CA4+CB4+CC4+CD4+CE4+CF4+CG4+CH4+CI4+CJ4+CK4+CL4+CM4 -> 2214.012 | CO4: =BI4+BG4+CN4+BE4+BH4 -> 8626.1486 | CP4: =IF(IFERROR(VLOOKUP(K4,源_13残疾人信息_残疾人信息!$A:$M,1,FALSE),"")<>"",0,IF(OR(P4="门店全职",P4="门店管理组",P4="全职(非门店)"),(BI4-AT4)*IFERROR(VLOOKUP(D4,源_12计提残保金规则_Sheet1!$A:$E,4,FALSE),0)*IFERROR(VLOOKUP(D4,源_12计提残保金规则_Sheet1!$A:$E,5,FALSE),0),0)) -> 86.476094 | CQ4: =IF(M4="行政",0,16.05) -> 16.05 | CR4: =IF(M4="门卫",0,20.67) -> 20.67 | CS4: =IF(DATEVALUE(N4)>DATE(参数!$B$2,9,30),0,IF(M4="行政",0,IF(O4="",R4/12,IF(MONTH(DATEVALUE(O4))=参数!$B$3,0,IF(DATEVALUE(O4)<DATE(参数!$B$2,参数!$B$3,1),0,R4/12))))) -> 474.41667 | CT4: =IF(P4="门店管理组",R4*0.12*0.85,0) -> 580.686 | CU4: =IFERROR(VLOOKUP(DF4,源_6社保表_Sheet1!$C:$I,2,FALSE),0) -> 7460 | CV4: =IFERROR(VLOOKUP(DF4,源_6社保表_Sheet1!$C:$I,7,FALSE),0) -> 7284 | CW4: =IFERROR(VLOOKUP(DF4,源_6社保表_Sheet1!$C:$I,3,FALSE),0) -> 7460 | CX4: =IFERROR(VLOOKUP(DF4,源_6社保表_Sheet1!$C:$I,4,FALSE),0) -> 7460 | CY4: =IFERROR(VLOOKUP(DF4,源_6社保表_Sheet1!$C:$I,5,FALSE),0) -> 7460 | CZ4: =IFERROR(VLOOKUP(DF4,源_6社保表_Sheet1!$C:$I,6,FALSE),0) -> 0 | DA4: =BI4+CN4-AG4-AH4-AI4-AJ4-AK4-AL4-AM4-AQ4-AR4-AS4-AT4 -> 6185.1486 | DB4: =DA4+CP4+CQ4+CR4+CS4+CT4+BH4 -> 7369.9473 | DC4: =IFERROR(VLOOKUP(K4,源_7银行卡表_Sheet1!$A:$J,8,FALSE),"") -> 招商银行 | DD4: =IFERROR(VLOOKUP(K4,源_7银行卡表_Sheet1!$A:$J,9,FALSE),"") -> 6687807193600801610 | DE4: =IFERROR(VLOOKUP(K4,源_7银行卡表_Sheet1!$A:$J,10,FALSE),"") -> 成都蜀都中心支行 | DF4: 110000198902241890 | DG4: 17603289482 | DH4: 上海 | DI4: 0 | DJ4: 0 | DK4: 0 | DL4: 0 | DM4: 0 | DN4: 0 | DO4: 0 | DP4: 0 | DQ4: 0 | DR4: =IF(OR(IFERROR(VLOOKUP(K4,源_3考勤报表_考勤表!$F:$BG,39,FALSE),0)+IFERROR(VLOOKUP(K4,源_8补工时表_补当月工时!$A:$AC,24,FALSE),0)=0,IFERROR(VLOOKUP(K4,源_3考勤报表_考勤表!$F:$BG,43,FALSE),0)+IFERROR(VLOOKUP(K4,源_8补工时表_补当月工时!$A:$AC,26,FALSE),0)=0),IF(BI4+BG4-BT4<0,BI4+BG4-BT4,0),0) -> 0
A5: =参数!$B$2 -> 2025 | B5: =参数!$B$3 -> 12 | D5: 上海达美乐 | E5: 店铺营运 | F5: =IFERROR(VLOOKUP(K5,源_7银行卡表_Sheet1!$A:$J,6,FALSE),"") -> 华东营运 | G5: 上海2 | H5: 崧泽大道店 | I5: 外服-上海门店全职 | J5: 1 | K5: 26123004 | L5: 元曼柔 | M5: 餐厅经理 | N5: 2017-07-01 | P5: 门店管理组 | Q5: =IF(P5="门店全职",IFERROR(VLOOKUP(K5,源_3考勤报表_考勤表!$F:$BG,34,FALSE),0)+IFERROR(VLOOKUP(K5,源_8补工时表_补当月工时!$A:$AC,14,FALSE),0),IF(P5="门店管理组",IF(IFERROR(VLOOKUP(K5,源_3考勤报表_考勤表!$F:$BG,34,FALSE),0)+IFERROR(VLOOKUP(K5,源_8补工时表_补当月工时!$A:$AC,14,FALSE),0)+IFERROR(VLOOKUP(K5,源_3考勤报表_考勤表!$F:$BG,37,FALSE),0)+IFERROR(VLOOKUP(K5,源_8补工时表_补当月工时!$A:$AC,15,FALSE),0)+IFERROR(VLOOKUP(K5,源_3考勤报表_考勤表!$F:$BG,38,FALSE),0)+IFERROR(VLOOKUP(K5,源_8补工时表_补当月工时!$A:$AC,17,FALSE),0)+IFERROR(VLOOKUP(K5,源_3考勤报表_考勤表!$F:$BG,40,FALSE),0)+IFERROR(VLOOKUP(K5,源_8补工时表_补当月工时!$A:$AC,20,FALSE),0)+IFERROR(VLOOKUP(K5,源_8补工时表_补当月工时!$A:$AC,22,FALSE),0)+IFERROR(VLOOKUP(K5,源_3考勤报表_考勤表!$F:$BG,41,FALSE),0)+IFERROR(VLOOKUP(K5,源_8补工时表_补当月工时!$A:$AC,18,FALSE),0)+IFERROR(VLOOKUP(K5,源_3考勤报表_考勤表!$F:$BG,44,FALSE),0)+IFERROR(VLOOKUP(K5,源_8补工时表_补当月工时!$A:$AC,16,FALSE),0)+IFERROR(VLOOKUP(K5,源_3考勤报表_考勤表!$F:$BG,45,FALSE),0)>=参数!$B$4,参数!$B$4-IFERROR(VLOOKUP(K5,源_3考勤报表_考勤表!$F:$BG,37,FALSE),0)-IFERROR(VLOOKUP(K5,源_8补工时表_补当月工时!$A:$AC,15,FALSE),0)-IFERROR(VLOOKUP(K5,源_3考勤报表_考勤表!$F:$BG,38,FALSE),0)-IFERROR(VLOOKUP(K5,源_8补工时表_补当月工时!$A:$AC,17,FALSE),0)-IFERROR(VLOOKUP(K5,源_3考勤报表_考勤表!$F:$BG,40,FALSE),0)-IFERROR(VLOOKUP(K5,源_8补工时表_补当月工时!$A:$AC,20,FALSE),0)-IFERROR(VLOOKUP(K5,源_8补工时表_补当月工时!$A:$AC,22,FALSE),0)-IFERROR(VLOOKUP(K5,源_3考勤报表_考勤表!$F:$BG,41,FALSE),0)-IFERROR(VLOOKUP(K5,源_8补工时表_补当月工时!$A:$AC,18,FALSE),0)-IFERROR(VLOOKUP(K5,源_3考勤报表_考勤表!$F:$BG,44,FALSE),0)-IFERROR(VLOOKUP(K5,源_8补工时表_补当月工时!$A:$AC,16,FALSE),0)-IFERROR(VLOOKUP(K5,源_3考勤报表_考勤表!$F:$BG,45,FALSE),0),IFERROR(VLOOKUP(K5,源_3考勤报表_考勤表!$F:$BG,34,FALSE),0)+IFERROR(VLOOKUP(K5,源_8补工时表_补当月工时!$A:$AC,14,FALSE),0)),0)) -> 184 | R5: 7980 | S5: 0 | T5: =IF(P5="门店全职",R5/参数!$B$4*(Q5-MAX(IFERROR(VLOOKUP(K5,源_3考勤报表_考勤表!$F:$BG,34,FALSE),0)+IFERROR(VLOOKUP(K5,源_8补工时表_补当月工时!$A:$AC,14,FALSE),0)+IFERROR(VLOOKUP(K5,源_3考勤报表_考勤表!$F:$BG,37,FALSE),0)+IFERROR(VLOOKUP(K5,源_8补工时表_补当月工时!$A:$AC,15,FALSE),0)+IFERROR(VLOOKUP(K5,源_3考勤报表_考勤表!$F:$BG,38,FALSE),0)+IFERROR(VLOOKUP(K5,源_8补工时表_补当月工时!$A:$AC,17,FALSE),0)+IFERROR(VLOOKUP(K5,源_3考勤报表_考勤表!$F:$BG,40,FALSE),0)+IFERROR(VLOOKUP(K5,源_8补工时表_补当月工时!$A:$AC,20,FALSE),0)+IFERROR(VLOOKUP(K5,源_8补工时表_补当月工时!$A:$AC,22,FALSE),0)+IFERROR(VLOOKUP(K5,源_3考勤报表_考勤表!$F:$BG,41,FALSE),0)+IFERROR(VLOOKUP(K5,源_8补工时表_补当月工时!$A:$AC,18,FALSE),0)+IFERROR(VLOOKUP(K5,源_3考勤报表_考勤表!$F:$BG,42,FALSE),0)+IFERROR(VLOOKUP(K5,源_8补工时表_补当月工时!$A:$AC,19,FALSE),0)+IFERROR(VLOOKUP(K5,源_3考勤报表_考勤表!$F:$BG,44,FALSE),0)+IFERROR(VLOOKUP(K5,源_8补工时表_补当月工时!$A:$AC,16,FALSE),0)+IFERROR(VLOOKUP(K5,源_3考勤报表_考勤表!$F:$BG,45,FALSE),0)-参数!$B$4,0)),R5/参数!$B$4*Q5) -> 7980 | U5: 0 | V5: 0 | W5: =X5+Y5+Z5+AA5 -> 53 | X5: =IFERROR(VLOOKUP(K5,源_4奖金汇总表_拆分手工算!$A:$N,8,FALSE),0) -> 53 | Y5: =IFERROR(VLOOKUP(K5,源_5薪资备忘录_工资调整项!$A:$AC,14,FALSE),0) -> 0 | Z5: =IFERROR(VLOOKUP(K5,源_5薪资备忘录_工资调整项!$A:$AC,16,FALSE),0) -> 0 | AA5: =IFERROR(VLOOKUP(K5,源_5薪资备忘录_工资调整项!$A:$AC,15,FALSE),0) -> 0 | AB5: =AC5+AD5+AF5 -> 0 | AC5: =IF(P5="门店全职",R5/174*MAX(IFERROR(VLOOKUP(K5,源_3考勤报表_考勤表!$F:$BG,34,FALSE),0)+IFERROR(VLOOKUP(K5,源_8补工时表_补当月工时!$A:$AC,14,FALSE),0)+IFERROR(VLOOKUP(K5,源_3考勤报表_考勤表!$F:$BG,37,FALSE),0)+IFERROR(VLOOKUP(K5,源_8补工时表_补当月工时!$A:$AC,15,FALSE),0)+IFERROR(VLOOKUP(K5,源_3考勤报表_考勤表!$F:$BG,38,FALSE),0)+IFERROR(VLOOKUP(K5,源_8补工时表_补当月工时!$A:$AC,17,FALSE),0)+IFERROR(VLOOKUP(K5,源_3考勤报表_考勤表!$F:$BG,40,FALSE),0)+IFERROR(VLOOKUP(K5,源_8补工时表_补当月工时!$A:$AC,20,FALSE),0)+IFERROR(VLOOKUP(K5,源_8补工时表_补当月工时!$A:$AC,22,FALSE),0)+IFERROR(VLOOKUP(K5,源_3考勤报表_考勤表!$F:$BG,41,FALSE),0)+IFERROR(VLOOKUP(K5,源_8补工时表_补当月工时!$A:$AC,18,FALSE),0)+IFERROR(VLOOKUP(K5,源_3考勤报表_考勤表!$F:$BG,42,FALSE),0)+IFERROR(VLOOKUP(K5,源_8补工时表_补当月工时!$A:$AC,19,FALSE),0)+IFERROR(VLOOKUP(K5,源_3考勤报表_考勤表!$F:$BG,44,FALSE),0)+IFERROR(VLOOKUP(K5,源_8补工时表_补当月工时!$A:$AC,16,FALSE),0)+IFERROR(VLOOKUP(K5,源_3考勤报表_考勤表!$F:$BG,45,FALSE),0)-参数!$B$4,0)*1.5,0) -> 0 | AD5: 0 | AE5: =IFERROR(VLOOKUP(K5,源_3考勤报表_考勤表!$F:$BG,46,FALSE),0)+IFERROR(VLOOKUP(K5,源_8补工时表_补当月工时!$A:$AC,25,FALSE),0) -> 0 | AF5: =R5/174*AE5*3 -> 0 | AG5: =IFERROR(VLOOKUP(K5,源_4奖金汇总表_拆分手工算!$A:$N,10,FALSE),0) -> 0 | AH5: =IFERROR(VLOOKUP(K5,源_4奖金汇总表_拆分手工算!$A:$N,5,FALSE),0) -> 250 | AI5: =IFERROR(VLOOKUP(K5,源_4奖金汇总表_拆分手工算!$A:$N,11,FALSE),0) -> 0 | AJ5: =IFERROR(VLOOKUP(K5,源_4奖金汇总表_拆分手工算!$A:$N,4,FALSE),0) -> 0 | AK5: =IFERROR(VLOOKUP(K5,源_4奖金汇总表_拆分手工算!$A:$N,3,FALSE),0) -> 0 | AL5: =IFERROR(VLOOKUP(K5,源_4奖金汇总表_拆分手工算!$A:$N,6,FALSE),0) -> 0 | AM5: =IFERROR(VLOOKUP(K5,源_5薪资备忘录_工资调整项!$A:$AC,18,FALSE),0)+IFERROR(VLOOKUP(K5,源_4奖金汇总表_拆分手工算!$A:$N,7,FALSE),0) -> 0 | AN5: =IFERROR(VLOOKUP(K5,源_5薪资备忘录_工资调整项!$A:$AC,17,FALSE),0) -> 0 | AO5: =IF(OR(IFERROR(VLOOKUP(K5,源_3考勤报表_考勤表!$F:$BG,39,FALSE),0)+IFERROR(VLOOKUP(K5,源_8补工时表_补当月工时!$A:$AC,24,FALSE),0)>0,IFERROR(VLOOKUP(K5,源_3考勤报表_考勤表!$F:$BG,43,FALSE),0)+IFERROR(VLOOKUP(K5,源_8补工时表_补当月工时!$A:$AC,26,FALSE),0)>0),IF(IFERROR(VLOOKUP(DH5,源_11产假政策_Sheet1!$C:$F,4,FALSE),"")="是",R5/参数!$B$4*(IFERROR(VLOOKUP(K5,源_3考勤报表_考勤表!$F:$BG,39,FALSE),0)+IFERROR(VLOOKUP(K5,源_8补工时表_补当月工时!$A:$AC,24,FALSE),0)+IFERROR(VLOOKUP(K5,源_3考勤报表_考勤表!$F:$BG,43,FALSE),0)+IFERROR(VLOOKUP(K5,源_8补工时表_补当月工时!$A:$AC,26,FALSE),0)),IFERROR(VLOOKUP(K5,源_5薪资备忘录_工资调整项!$A:$AC,19,FALSE),0)),0) -> 0 | AP5: 0 | AQ5: =IFERROR(VLOOKUP(K5,源_4奖金汇总表_拆分手工算!$A:$N,12,FALSE),0)+IFERROR(VLOOKUP(K5,源_9年终奖表_Sheet1!$A:$E,3,FALSE),0) -> 1200 | AR5: =IFERROR(VLOOKUP(K5,源_4奖金汇总表_拆分手工算!$A:$N,13,FALSE),0)+IFERROR(VLOOKUP(K5,源_9年终奖表_Sheet1!$A:$E,4,FALSE),0) -> 600 | AS5: =IFERROR(VLOOKUP(K5,源_4奖金汇总表_拆分手工算!$A:$N,14,FALSE),0)+IFERROR(VLOOKUP(K5,源_9年终奖表_Sheet1!$A:$E,5,FALSE),0) -> 111 | AT5: =IFERROR(VLOOKUP(K5,源_5薪资备忘录_工资调整项!$A:$AC,20,FALSE),0) -> 0 | AU5: =IFERROR(VLOOKUP(K5,源_5薪资备忘录_工资调整项!$A:$AC,21,FALSE),0)+IFERROR(VLOOKUP(K5,源_4奖金汇总表_拆分手工算!$A:$N,9,FALSE),0) -> 1456.81 | AV5: =R5/参数!$B$4*(IFERROR(VLOOKUP(K5,源_3考勤报表_考勤表!$F:$BG,37,FALSE),0)+IFERROR(VLOOKUP(K5,源_8补工时表_补当月工时!$A:$AC,15,FALSE),0)) -> 0 | AW5: =R5/174*MIN(IFERROR(VLOOKUP(K5,源_3考勤报表_考勤表!$F:$BG,35,FALSE),0),174)*IF(DATEDIF(N5,DATE(参数!$B$2,参数!$B$3+1,0),"Y")<2,0.6,IF(DATEDIF(N5,DATE(参数!$B$2,参数!$B$3+1,0),"Y")<4,0.7,IF(DATEDIF(N5,DATE(参数!$B$2,参数!$B$3+1,0),"Y")<6,0.8,IF(DATEDIF(N5,DATE(参数!$B$2,参数!$B$3+1,0),"Y")<8,0.9,1)))) -> 0 | AX5: =IF(Q5+IFERROR(VLOOKUP(K5,源_3考勤报表_考勤表!$F:$BG,37,FALSE),0)+IFERROR(VLOOKUP(K5,源_8补工时表_补当月工时!$A:$AC,15,FALSE),0)>=参数!$B$4,0,IF(Q5+IFERROR(VLOOKUP(K5,源_3考勤报表_考勤表!$F:$BG,37,FALSE),0)+IFERROR(VLOOKUP(K5,源_8补工时表_补当月工时!$A:$AC,15,FALSE),0)+IFERROR(VLOOKUP(K5,源_3考勤报表_考勤表!$F:$BG,38,FALSE),0)+IFERROR(VLOOKUP(K5,源_8补工时表_补当月工时!$A:$AC,17,FALSE),0)+IFERROR(VLOOKUP(K5,源_3考勤报表_考勤表!$F:$BG,40,FALSE),0)+IFERROR(VLOOKUP(K5,源_8补工时表_补当月工时!$A:$AC,20,FALSE),0)+IFERROR(VLOOKUP(K5,源_8补工时表_补当月工时!$A:$AC,22,FALSE),0)+IFERROR(VLOOKUP(K5,源_3考勤报表_考勤表!$F:$BG,41,FALSE),0)+IFERROR(VLOOKUP(K5,源_8补工时表_补当月工时!$A:$AC,18,FALSE),0)+IFERROR(VLOOKUP(K5,源_3考勤报表_考勤表!$F:$BG,42,FALSE),0)+IFERROR(VLOOKUP(K5,源_8补工时表_补当月工时!$A:$AC,19,FALSE),0)+IFERROR(VLOOKUP(K5,源_3考勤报表_考勤表!$F:$BG,44,FALSE),0)+IFERROR(VLOOKUP(K5,源_8补工时表_补当月工时!$A:$AC,16,FALSE),0)+IFERROR(VLOOKUP(K5,源_3考勤报表_考勤表!$F:$BG,45,FALSE),0)<=参数!$B$4,R5/参数!$B$4*(IFERROR(VLOOKUP(K5,源_3考勤报表_考勤表!$F:$BG,38,FALSE),0)+IFERROR(VLOOKUP(K5,源_8补工时表_补当月工时!$A:$AC,17,FALSE),0)+IFERROR(VLOOKUP(K5,源_3考勤报表_考勤表!$F:$BG,40,FALSE),0)+IFERROR(VLOOKUP(K5,源_8补工时表_补当月工时!$A:$AC,20,FALSE),0)+IFERROR(VLOOKUP(K5,源_8补工时表_补当月工时!$A:$AC,22,FALSE),0)+IFERROR(VLOOKUP(K5,源_3考勤报表_考勤表!$F:$BG,41,FALSE),0)+IFERROR(VLOOKUP(K5,源_8补工时表_补当月工时!$A:$AC,18,FALSE),0)+IFERROR(VLOOKUP(K5,源_3考勤报表_考勤表!$F:$BG,42,FALSE),0)+IFERROR(VLOOKUP(K5,源_8补工时表_补当月工时!$A:$AC,19,FALSE),0)+IFERROR(VLOOKUP(K5,源_3考勤报表_考勤表!$F:$BG,44,FALSE),0)+IFERROR(VLOOKUP(K5,源_8补工时表_补当月工时!$A:$AC,16,FALSE),0)+IFERROR(VLOOKUP(K5,源_3考勤报表_考勤表!$F:$BG,45,FALSE),0)),0)) -> 0 | AY5: 0 | AZ5: 0 | BA5: 0 | BB5: 0 | BC5: =IFERROR(VLOOKUP(K5,源_5薪资备忘录_工资调整项!$A:$AC,25,FALSE),0) -> 0 | BD5: 0 | BE5: 0 | BF5: 0 | BG5: =IFERROR(VLOOKUP(K5,源_5薪资备忘录_工资调整项!$A:$AC,22,FALSE),0)+IFERROR(VLOOKUP(K5,源_5薪资备忘录_工资调整项!$A:$AC,23,FALSE),0)+IFERROR(VLOOKUP(K5,源_5薪资备忘录_工资调整项!$A:$AC,24,FALSE),0) -> 0 | BH5: =IFERROR(VLOOKUP(DF5,源_6社保表_Sheet1!$C:$CD,80,FALSE),0)+4.5 -> 6.5 | BI5: =T5+W5+AB5+AG5+AH5+AI5+AJ5+AK5+AL5+AM5+AN5+AO5+AP5+AQ5+AR5+AS5+AT5+AU5+AV5+AW5+AX5+BC5 -> 11650.81 | BJ5: =IFERROR(VLOOKUP(DF5,源_6社保表_Sheet1!$C:$BZ,26,FALSE),0) -> 671.76 | BK5: =IFERROR(VLOOKUP(DF5,源_6社保表_Sheet1!$C:$BZ,27,FALSE),0) -> 167.94 | BL5: =IFERROR(VLOOKUP(DF5,源_6社保表_Sheet1!$C:$BZ,28,FALSE),0) -> 41.985 | BM5: =IFERROR(VLOOKUP(DF5,源_6社保表_Sheet1!$C:$BZ,30,FALSE),0) -> 587.79 | BN5: =IFERROR(VLOOKUP(DF5,源_6社保表_Sheet1!$C:$BZ,29,FALSE),0) -> 0 | BO5: =IFERROR(VLOOKUP(DF5,源_6社保表_Sheet1!$C:$BZ,40,FALSE),0) -> 0 | BP5: =IFERROR(VLOOKUP(DF5,源_6社保表_Sheet1!$C:$BZ,41,FALSE),0) -> 0 | BQ5: =IFERROR(VLOOKUP(DF5,源_6社保表_Sheet1!$C:$BZ,42,FALSE),0) -> 0 | BR5: =IFERROR(VLOOKUP(DF5,源_6社保表_Sheet1!$C:$BZ,44,FALSE),0) -> 0 | BS5: =IFERROR(VLOOKUP(DF5,源_6社保表_Sheet1!$C:$BZ,43,FALSE),0) -> 0 | BT5: =BJ5+BK5+BL5+BM5+BN5+BO5+BP5+BQ5+BR5+BS5 -> 1469.475 | BU5: 0 | BV5: 0 | BW5: 0 | BX5: =BU5+BV5+BW5 -> 0 | BY5: 0 | BZ5: =IFERROR(VLOOKUP(DF5,源_6社保表_Sheet1!$C:$BZ,18,FALSE),0) -> 1343.52 | CA5: =IFERROR(VLOOKUP(DF5,源_6社保表_Sheet1!$C:$BZ,19,FALSE),0) -> 755.73 | CB5: =IFERROR(VLOOKUP(DF5,源_6社保表_Sheet1!$C:$BZ,24,FALSE),0) -> 587.79 | CC5: =IFERROR(VLOOKUP(DF5,源_6社保表_Sheet1!$C:$BZ,20,FALSE),0) -> 41.985 | CD5: =IFERROR(VLOOKUP(DF5,源_6社保表_Sheet1!$C:$BZ,21,FALSE),0) -> 26.8704 | CE5: =IFERROR(VLOOKUP(DF5,源_6社保表_Sheet1!$C:$BZ,22,FALSE),0) -> 0 | CF5: =IFERROR(VLOOKUP(DF5,源_6社保表_Sheet1!$C:$BZ,23,FALSE),0) -> 0 | CG5: =IFERROR(VLOOKUP(DF5,源_6社保表_Sheet1!$C:$BZ,32,FALSE),0) -> 0 | CH5: =IFERROR(VLOOKUP(DF5,源_6社保表_Sheet1!$C:$BZ,33,FALSE),0) -> 0 | CI5: =IFERROR(VLOOKUP(DF5,源_6社保表_Sheet1!$C:$BZ,34,FALSE),0) -> 0 | CJ5: =IFERROR(VLOOKUP(DF5,源_6社保表_Sheet1!$C:$BZ,38,FALSE),0) -> 0 | CK5: =IFERROR(VLOOKUP(DF5,源_6社保表_Sheet1!$C:$BZ,35,FALSE),0) -> 0 | CL5: =IFERROR(VLOOKUP(DF5,源_6社保表_Sheet1!$C:$BZ,36,FALSE),0) -> 0 | CM5: =IFERROR(VLOOKUP(DF5,源_6社保表_Sheet1!$C:$BZ,37,FALSE),0) -> 0 | CN5: =BZ5+CA5+CB5+CC5+CD5+CE5+CF5+CG5+CH5+CI5+CJ5+CK5+CL5+CM5 -> 2755.8954 | CO5: =BI5+BG5+CN5+BE5+BH5 -> 14413.205 | CP5: =IF(IFERROR(VLOOKUP(K5,源_13残疾人信息_残疾人信息!$A:$M,1,FALSE),"")<>"",0,IF(OR(P5="门店全职",P5="门店管理组",P5="全职(非门店)"),(BI5-AT5)*IFERROR(VLOOKUP(D5,源_12计提残保金规则_Sheet1!$A:$E,4,FALSE),0)*IFERROR(VLOOKUP(D5,源_12计提残保金规则_Sheet1!$A:$E,5,FALSE),0),0)) -> 157.28593 | CQ5: =IF(M5="行政",0,16.05) -> 16.05 | CR5: =IF(M5="门卫",0,20.67) -> 20.67 | CS5: =IF(DATEVALUE(N5)>DATE(参数!$B$2,9,30),0,IF(M5="行政",0,IF(O5="",R5/12,IF(MONTH(DATEVALUE(O5))=参数!$B$3,0,IF(DATEVALUE(O5)<DATE(参数!$B$2,参数!$B$3,1),0,R5/12))))) -> 665 | CT5: =IF(P5="门店管理组",R5*0.12*0.85,0) -> 813.96 | CU5: =IFERROR(VLOOKUP(DF5,源_6社保表_Sheet1!$C:$I,2,FALSE),0) -> 8397 | CV5: =IFERROR(VLOOKUP(DF5,源_6社保表_Sheet1!$C:$I,7,FALSE),0) -> 8397 | CW5: =IFERROR(VLOOKUP(DF5,源_6社保表_Sheet1!$C:$I,3,FALSE),0) -> 8397 | CX5: =IFERROR(VLOOKUP(DF5,源_6社保表_Sheet1!$C:$I,4,FALSE),0) -> 8397 | CY5: =IFERROR(VLOOKUP(DF5,源_6社保表_Sheet1!$C:$I,5,FALSE),0) -> 8397 | CZ5: =IFERROR(VLOOKUP(DF5,源_6社保表_Sheet1!$C:$I,6,FALSE),0) -> 0 | DA5: =BI5+CN5-AG5-AH5-AI5-AJ5-AK5-AL5-AM5-AQ5-AR5-AS5-AT5 -> 12245.705 | DB5: =DA5+CP5+CQ5+CR5+CS5+CT5+BH5 -> 13925.171 | DC5: =IFERROR(VLOOKUP(K5,源_7银行卡表_Sheet1!$A:$J,8,FALSE),"") -> 招商银行 | DD5: =IFERROR(VLOOKUP(K5,源_7银行卡表_Sheet1!$A:$J,9,FALSE),"") -> 6681360063544614654 | DE5: =IFERROR(VLOOKUP(K5,源_7银行卡表_Sheet1!$A:$J,10,FALSE),"") -> 成都星宸国际支行 | DF5: 140000198209249885 | DG5: 13793270325 | DH5: 上海 | DI5: 0 | DJ5: 0 | DK5: 0 | DL5: 0 | DM5: 0 | DN5: 0 | DO5: 0 | DP5: 0 | DQ5: 0 | DR5: =IF(OR(IFERROR(VLOOKUP(K5,源_3考勤报表_考勤表!$F:$BG,39,FALSE),0)+IFERROR(VLOOKUP(K5,源_8补工时表_补当月工时!$A:$AC,24,FALSE),0)=0,IFERROR(VLOOKUP(K5,源_3考勤报表_考勤表!$F:$BG,43,FALSE),0)+IFERROR(VLOOKUP(K5,源_8补工时表_补当月工时!$A:$AC,26,FALSE),0)=0),IF(BI5+BG5-BT5<0,BI5+BG5-BT5,0),0) -> 0
A6: =参数!$B$2 -> 2025 | B6: =参数!$B$3 -> 12 | D6: 北京达美乐 | E6: 店铺营运 | F6: =IFERROR(VLOOKUP(K6,源_7银行卡表_Sheet1!$A:$J,6,FALSE),"") -> 华北营运 | G6: 北京 | H6: 通州万达店 | I6: 外服-北京门店全职 | J6: 1 | K6: 26123005 | L6: 姚夜安 | M6: 训练员 | N6: 2018-03-01 | P6: 门店全职 | Q6: =IF(P6="门店全职",IFERROR(VLOOKUP(K6,源_3考勤报表_考勤表!$F:$BG,34,FALSE),0)+IFERROR(VLOOKUP(K6,源_8补工时表_补当月工时!$A:$AC,14,FALSE),0),IF(P6="门店管理组",IF(IFERROR(VLOOKUP(K6,源_3考勤报表_考勤表!$F:$BG,34,FALSE),0)+IFERROR(VLOOKUP(K6,源_8补工时表_补当月工时!$A:$AC,14,FALSE),0)+IFERROR(VLOOKUP(K6,源_3考勤报表_考勤表!$F:$BG,37,FALSE),0)+IFERROR(VLOOKUP(K6,源_8补工时表_补当月工时!$A:$AC,15,FALSE),0)+IFERROR(VLOOKUP(K6,源_3考勤报表_考勤表!$F:$BG,38,FALSE),0)+IFERROR(VLOOKUP(K6,源_8补工时表_补当月工时!$A:$AC,17,FALSE),0)+IFERROR(VLOOKUP(K6,源_3考勤报表_考勤表!$F:$BG,40,FALSE),0)+IFERROR(VLOOKUP(K6,源_8补工时表_补当月工时!$A:$AC,20,FALSE),0)+IFERROR(VLOOKUP(K6,源_8补工时表_补当月工时!$A:$AC,22,FALSE),0)+IFERROR(VLOOKUP(K6,源_3考勤报表_考勤表!$F:$BG,41,FALSE),0)+IFERROR(VLOOKUP(K6,源_8补工时表_补当月工时!$A:$AC,18,FALSE),0)+IFERROR(VLOOKUP(K6,源_3考勤报表_考勤表!$F:$BG,44,FALSE),0)+IFERROR(VLOOKUP(K6,源_8补工时表_补当月工时!$A:$AC,16,FALSE),0)+IFERROR(VLOOKUP(K6,源_3考勤报表_考勤表!$F:$BG,45,FALSE),0)>=参数!$B$4,参数!$B$4-IFERROR(VLOOKUP(K6,源_3考勤报表_考勤表!$F:$BG,37,FALSE),0)-IFERROR(VLOOKUP(K6,源_8补工时表_补当月工时!$A:$AC,15,FALSE),0)-IFERROR(VLOOKUP(K6,源_3考勤报表_考勤表!$F:$BG,38,FALSE),0)-IFERROR(VLOOKUP(K6,源_8补工时表_补当月工时!$A:$AC,17,FALSE),0)-IFERROR(VLOOKUP(K6,源_3考勤报表_考勤表!$F:$BG,40,FALSE),0)-IFERROR(VLOOKUP(K6,源_8补工时表_补当月工时!$A:$AC,20,FALSE),0)-IFERROR(VLOOKUP(K6,源_8补工时表_补当月工时!$A:$AC,22,FALSE),0)-IFERROR(VLOOKUP(K6,源_3考勤报表_考勤表!$F:$BG,41,FALSE),0)-IFERROR(VLOOKUP(K6,源_8补工时表_补当月工时!$A:$AC,18,FALSE),0)-IFERROR(VLOOKUP(K6,源_3考勤报表_考勤表!$F:$BG,44,FALSE),0)-IFERROR(VLOOKUP(K6,源_8补工时表_补当月工时!$A:$AC,16,FALSE),0)-IFERROR(VLOOKUP(K6,源_3考勤报表_考勤表!$F:$BG,45,FALSE),0),IFERROR(VLOOKUP(K6,源_3考勤报表_考勤表!$F:$BG,34,FALSE),0)+IFERROR(VLOOKUP(K6,源_8补工时表_补当月工时!$A:$AC,14,FALSE),0)),0)) -> 200 | R6: 3861 | S6: 0 | T6: =IF(P6="门店全职",R6/参数!$B$4*(Q6-MAX(IFERROR(VLOOKUP(K6,源_3考勤报表_考勤表!$F:$BG,34,FALSE),0)+IFERROR(VLOOKUP(K6,源_8补工时表_补当月工时!$A:$AC,14,FALSE),0)+IFERROR(VLOOKUP(K6,源_3考勤报表_考勤表!$F:$BG,37,FALSE),0)+IFERROR(VLOOKUP(K6,源_8补工时表_补当月工时!$A:$AC,15,FALSE),0)+IFERROR(VLOOKUP(K6,源_3考勤报表_考勤表!$F:$BG,38,FALSE),0)+IFERROR(VLOOKUP(K6,源_8补工时表_补当月工时!$A:$AC,17,FALSE),0)+IFERROR(VLOOKUP(K6,源_3考勤报表_考勤表!$F:$BG,40,FALSE),0)+IFERROR(VLOOKUP(K6,源_8补工时表_补当月工时!$A:$AC,20,FALSE),0)+IFERROR(VLOOKUP(K6,源_8补工时表_补当月工时!$A:$AC,22,FALSE),0)+IFERROR(VLOOKUP(K6,源_3考勤报表_考勤表!$F:$BG,41,FALSE),0)+IFERROR(VLOOKUP(K6,源_8补工时表_补当月工时!$A:$AC,18,FALSE),0)+IFERROR(VLOOKUP(K6,源_3考勤报表_考勤表!$F:$BG,42,FALSE),0)+IFERROR(VLOOKUP(K6,源_8补工时表_补当月工时!$A:$AC,19,FALSE),0)+IFERROR(VLOOKUP(K6,源_3考勤报表_考勤表!$F:$BG,44,FALSE),0)+IFERROR(VLOOKUP(K6,源_8补工时表_补当月工时!$A:$AC,16,FALSE),0)+IFERROR(VLOOKUP(K6,源_3考勤报表_考勤表!$F:$BG,45,FALSE),0)-参数!$B$4,0)),R6/参数!$B$4*Q6) -> 3861 | U6: 0 | V6: 0 | W6: =X6+Y6+Z6+AA6 -> 0 | X6: =IFERROR(VLOOKUP(K6,源_4奖金汇总表_拆分手工算!$A:$N,8,FALSE),0) -> 0 | Y6: =IFERROR(VLOOKUP(K6,源_5薪资备忘录_工资调整项!$A:$AC,14,FALSE),0) -> 0 | Z6: =IFERROR(VLOOKUP(K6,源_5薪资备忘录_工资调整项!$A:$AC,16,FALSE),0) -> 0 | AA6: =IFERROR(VLOOKUP(K6,源_5薪资备忘录_工资调整项!$A:$AC,15,FALSE),0) -> 0 | AB6: =AC6+AD6+AF6 -> 532.55172 | AC6: =IF(P6="门店全职",R6/174*MAX(IFERROR(VLOOKUP(K6,源_3考勤报表_考勤表!$F:$BG,34,FALSE),0)+IFERROR(VLOOKUP(K6,源_8补工时表_补当月工时!$A:$AC,14,FALSE),0)+IFERROR(VLOOKUP(K6,源_3考勤报表_考勤表!$F:$BG,37,FALSE),0)+IFERROR(VLOOKUP(K6,源_8补工时表_补当月工时!$A:$AC,15,FALSE),0)+IFERROR(VLOOKUP(K6,源_3考勤报表_考勤表!$F:$BG,38,FALSE),0)+IFERROR(VLOOKUP(K6,源_8补工时表_补当月工时!$A:$AC,17,FALSE),0)+IFERROR(VLOOKUP(K6,源_3考勤报表_考勤表!$F:$BG,40,FALSE),0)+IFERROR(VLOOKUP(K6,源_8补工时表_补当月工时!$A:$AC,20,FALSE),0)+IFERROR(VLOOKUP(K6,源_8补工时表_补当月工时!$A:$AC,22,FALSE),0)+IFERROR(VLOOKUP(K6,源_3考勤报表_考勤表!$F:$BG,41,FALSE),0)+IFERROR(VLOOKUP(K6,源_8补工时表_补当月工时!$A:$AC,18,FALSE),0)+IFERROR(VLOOKUP(K6,源_3考勤报表_考勤表!$F:$BG,42,FALSE),0)+IFERROR(VLOOKUP(K6,源_8补工时表_补当月工时!$A:$AC,19,FALSE),0)+IFERROR(VLOOKUP(K6,源_3考勤报表_考勤表!$F:$BG,44,FALSE),0)+IFERROR(VLOOKUP(K6,源_8补工时表_补当月工时!$A:$AC,16,FALSE),0)+IFERROR(VLOOKUP(K6,源_3考勤报表_考勤表!$F:$BG,45,FALSE),0)-参数!$B$4,0)*1.5,0) -> 532.55172 | AD6: 0 | AE6: =IFERROR(VLOOKUP(K6,源_3考勤报表_考勤表!$F:$BG,46,FALSE),0)+IFERROR(VLOOKUP(K6,源_8补工时表_补当月工时!$A:$AC,25,FALSE),0) -> 0 | AF6: =R6/174*AE6*3 -> 0 | AG6: =IFERROR(VLOOKUP(K6,源_4奖金汇总表_拆分手工算!$A:$N,10,FALSE),0) -> 3 | AH6: =IFERROR(VLOOKUP(K6,源_4奖金汇总表_拆分手工算!$A:$N,5,FALSE),0) -> 0 | AI6: =IFERROR(VLOOKUP(K6,源_4奖金汇总表_拆分手工算!$A:$N,11,FALSE),0) -> 0 | AJ6: =IFERROR(VLOOKUP(K6,源_4奖金汇总表_拆分手工算!$A:$N,4,FALSE),0) -> 0 | AK6: =IFERROR(VLOOKUP(K6,源_4奖金汇总表_拆分手工算!$A:$N,3,FALSE),0) -> 0 | AL6: =IFERROR(VLOOKUP(K6,源_4奖金汇总表_拆分手工算!$A:$N,6,FALSE),0) -> 0 | AM6: =IFERROR(VLOOKUP(K6,源_5薪资备忘录_工资调整项!$A:$AC,18,FALSE),0)+IFERROR(VLOOKUP(K6,源_4奖金汇总表_拆分手工算!$A:$N,7,FALSE),0) -> 0 | AN6: =IFERROR(VLOOKUP(K6,源_5薪资备忘录_工资调整项!$A:$AC,17,FALSE),0) -> 0 | AO6: =IF(OR(IFERROR(VLOOKUP(K6,源_3考勤报表_考勤表!$F:$BG,39,FALSE),0)+IFERROR(VLOOKUP(K6,源_8补工时表_补当月工时!$A:$AC,24,FALSE),0)>0,IFERROR(VLOOKUP(K6,源_3考勤报表_考勤表!$F:$BG,43,FALSE),0)+IFERROR(VLOOKUP(K6,源_8补工时表_补当月工时!$A:$AC,26,FALSE),0)>0),IF(IFERROR(VLOOKUP(DH6,源_11产假政策_Sheet1!$C:$F,4,FALSE),"")="是",R6/参数!$B$4*(IFERROR(VLOOKUP(K6,源_3考勤报表_考勤表!$F:$BG,39,FALSE),0)+IFERROR(VLOOKUP(K6,源_8补工时表_补当月工时!$A:$AC,24,FALSE),0)+IFERROR(VLOOKUP(K6,源_3考勤报表_考勤表!$F:$BG,43,FALSE),0)+IFERROR(VLOOKUP(K6,源_8补工时表_补当月工时!$A:$AC,26,FALSE),0)),IFERROR(VLOOKUP(K6,源_5薪资备忘录_工资调整项!$A:$AC,19,FALSE),0)),0) -> 0 | AP6: 0 | AQ6: =IFERROR(VLOOKUP(K6,源_4奖金汇总表_拆分手工算!$A:$N,12,FALSE),0)+IFERROR(VLOOKUP(K6,源_9年终奖表_Sheet1!$A:$E,3,FALSE),0) -> 0 | AR6: =IFERROR(VLOOKUP(K6,源_4奖金汇总表_拆分手工算!$A:$N,13,FALSE),0)+IFERROR(VLOOKUP(K6,源_9年终奖表_Sheet1!$A:$E,4,FALSE),0) -> 0 | AS6: =IFERROR(VLOOKUP(K6,源_4奖金汇总表_拆分手工算!$A:$N,14,FALSE),0)+IFERROR(VLOOKUP(K6,源_9年终奖表_Sheet1!$A:$E,5,FALSE),0) -> 0 | AT6: =IFERROR(VLOOKUP(K6,源_5薪资备忘录_工资调整项!$A:$AC,20,FALSE),0) -> 0 | AU6: =IFERROR(VLOOKUP(K6,源_5薪资备忘录_工资调整项!$A:$AC,21,FALSE),0)+IFERROR(VLOOKUP(K6,源_4奖金汇总表_拆分手工算!$A:$N,9,FALSE),0) -> 1456.81 | AV6: =R6/参数!$B$4*(IFERROR(VLOOKUP(K6,源_3考勤报表_考勤表!$F:$BG,37,FALSE),0)+IFERROR(VLOOKUP(K6,源_8补工时表_补当月工时!$A:$AC,15,FALSE),0)) -> 0 | AW6: =R6/174*MIN(IFERROR(VLOOKUP(K6,源_3考勤报表_考勤表!$F:$BG,35,FALSE),0),174)*IF(DATEDIF(N6,DATE(参数!$B$2,参数!$B$3+1,0),"Y")<2,0.6,IF(DATEDIF(N6,DATE(参数!$B$2,参数!$B$3+1,0),"Y")<4,0.7,IF(DATEDIF(N6,DATE(参数!$B$2,参数!$B$3+1,0),"Y")<6,0.8,IF(DATEDIF(N6,DATE(参数!$B$2,参数!$B$3+1,0),"Y")<8,0.9,1)))) -> 0 | AX6: =IF(Q6+IFERROR(VLOOKUP(K6,源_3考勤报表_考勤表!$F:$BG,37,FALSE),0)+IFERROR(VLOOKUP(K6,源_8补工时表_补当月工时!$A:$AC,15,FALSE),0)>=参数!$B$4,0,IF(Q6+IFERROR(VLOOKUP(K6,源_3考勤报表_考勤表!$F:$BG,37,FALSE),0)+IFERROR(VLOOKUP(K6,源_8补工时表_补当月工时!$A:$AC,15,FALSE),0)+IFERROR(VLOOKUP(K6,源_3考勤报表_考勤表!$F:$BG,38,FALSE),0)+IFERROR(VLOOKUP(K6,源_8补工时表_补当月工时!$A:$AC,17,FALSE),0)+IFERROR(VLOOKUP(K6,源_3考勤报表_考勤表!$F:$BG,40,FALSE),0)+IFERROR(VLOOKUP(K6,源_8补工时表_补当月工时!$A:$AC,20,FALSE),0)+IFERROR(VLOOKUP(K6,源_8补工时表_补当月工时!$A:$AC,22,FALSE),0)+IFERROR(VLOOKUP(K6,源_3考勤报表_考勤表!$F:$BG,41,FALSE),0)+IFERROR(VLOOKUP(K6,源_8补工时表_补当月工时!$A:$AC,18,FALSE),0)+IFERROR(VLOOKUP(K6,源_3考勤报表_考勤表!$F:$BG,42,FALSE),0)+IFERROR(VLOOKUP(K6,源_8补工时表_补当月工时!$A:$AC,19,FALSE),0)+IFERROR(VLOOKUP(K6,源_3考勤报表_考勤表!$F:$BG,44,FALSE),0)+IFERROR(VLOOKUP(K6,源_8补工时表_补当月工时!$A:$AC,16,FALSE),0)+IFERROR(VLOOKUP(K6,源_3考勤报表_考勤表!$F:$BG,45,FALSE),0)<=参数!$B$4,R6/参数!$B$4*(IFERROR(VLOOKUP(K6,源_3考勤报表_考勤表!$F:$BG,38,FALSE),0)+IFERROR(VLOOKUP(K6,源_8补工时表_补当月工时!$A:$AC,17,FALSE),0)+IFERROR(VLOOKUP(K6,源_3考勤报表_考勤表!$F:$BG,40,FALSE),0)+IFERROR(VLOOKUP(K6,源_8补工时表_补当月工时!$A:$AC,20,FALSE),0)+IFERROR(VLOOKUP(K6,源_8补工时表_补当月工时!$A:$AC,22,FALSE),0)+IFERROR(VLOOKUP(K6,源_3考勤报表_考勤表!$F:$BG,41,FALSE),0)+IFERROR(VLOOKUP(K6,源_8补工时表_补当月工时!$A:$AC,18,FALSE),0)+IFERROR(VLOOKUP(K6,源_3考勤报表_考勤表!$F:$BG,42,FALSE),0)+IFERROR(VLOOKUP(K6,源_8补工时表_补当月工时!$A:$AC,19,FALSE),0)+IFERROR(VLOOKUP(K6,源_3考勤报表_考勤表!$F:$BG,44,FALSE),0)+IFERROR(VLOOKUP(K6,源_8补工时表_补当月工时!$A:$AC,16,FALSE),0)+IFERROR(VLOOKUP(K6,源_3考勤报表_考勤表!$F:$BG,45,FALSE),0)),0)) -> 0 | AY6: 0 | AZ6: 0 | BA6: 0 | BB6: 0 | BC6: =IFERROR(VLOOKUP(K6,源_5薪资备忘录_工资调整项!$A:$AC,25,FALSE),0) -> 0 | BD6: 0 | BE6: =(T6+W6+AB6+AG6+AH6+AI6+AJ6+AK6+AL6+AM6+AN6+AO6+AP6+AU6+AV6+AW6+AX6+BC6-IFERROR(VLOOKUP(DF6,源_6社保表_Sheet1!$C:$BZ,76,FALSE),0))*0.02 -> 97.834634 | BF6: 0 | BG6: =IFERROR(VLOOKUP(K6,源_5薪资备忘录_工资调整项!$A:$AC,22,FALSE),0)+IFERROR(VLOOKUP(K6,源_5薪资备忘录_工资调整项!$A:$AC,23,FALSE),0)+IFERROR(VLOOKUP(K6,源_5薪资备忘录_工资调整项!$A:$AC,24,FALSE),0) -> 0 | BH6: =IFERROR(VLOOKUP(DF6,源_6社保表_Sheet1!$C:$CD,80,FALSE),0)+4.5 -> 6.5 | BI6: =T6+W6+AB6+AG6+AH6+AI6+AJ6+AK6+AL6+AM6+AN6+AO6+AP6+AQ6+AR6+AS6+AT6+AU6+AV6+AW6+AX6+BC6 -> 5853.3617 | BJ6: =IFERROR(VLOOKUP(DF6,源_6社保表_Sheet1!$C:$BZ,26,FALSE),0) -> 501.34 | BK6: =IFERROR(VLOOKUP(DF6,源_6社保表_Sheet1!$C:$BZ,27,FALSE),0) -> 71.62 | BL6: =IFERROR(VLOOKUP(DF6,源_6社保表_Sheet1!$C:$BZ,28,FALSE),0) -> 35.81 | BM6: =IFERROR(VLOOKUP(DF6,源_6社保表_Sheet1!$C:$BZ,30,FALSE),0) -> 352.86 | BN6: =IFERROR(VLOOKUP(DF6,源_6社保表_Sheet1!$C:$BZ,29,FALSE),0) -> 0 | BO6: =IFERROR(VLOOKUP(DF6,源_6社保表_Sheet1!$C:$BZ,40,FALSE),0) -> 0 | BP6: =IFERROR(VLOOKUP(DF6,源_6社保表_Sheet1!$C:$BZ,41,FALSE),0) -> 0 | BQ6: =IFERROR(VLOOKUP(DF6,源_6社保表_Sheet1!$C:$BZ,42,FALSE),0) -> 0 | BR6: =IFERROR(VLOOKUP(DF6,源_6社保表_Sheet1!$C:$BZ,44,FALSE),0) -> 0 | BS6: =IFERROR(VLOOKUP(DF6,源_6社保表_Sheet1!$C:$BZ,43,FALSE),0) -> 0 | BT6: =BJ6+BK6+BL6+BM6+BN6+BO6+BP6+BQ6+BR6+BS6 -> 961.63 | BU6: 0 | BV6: 0 | BW6: 0 | BX6: =BU6+BV6+BW6 -> 0 | BY6: 0 | BZ6: =IFERROR(VLOOKUP(DF6,源_6社保表_Sheet1!$C:$BZ,18,FALSE),0) -> 1074.3 | CA6: =IFERROR(VLOOKUP(DF6,源_6社保表_Sheet1!$C:$BZ,19,FALSE),0) -> 572.96 | CB6: =IFERROR(VLOOKUP(DF6,源_6社保表_Sheet1!$C:$BZ,24,FALSE),0) -> 352.86 | CC6: =IFERROR(VLOOKUP(DF6,源_6社保表_Sheet1!$C:$BZ,20,FALSE),0) -> 35.81 | CD6: =IFERROR(VLOOKUP(DF6,源_6社保表_Sheet1!$C:$BZ,21,FALSE),0) -> 22.9184 | CE6: =IFERROR(VLOOKUP(DF6,源_6社保表_Sheet1!$C:$BZ,22,FALSE),0) -> 0 | CF6: =IFERROR(VLOOKUP(DF6,源_6社保表_Sheet1!$C:$BZ,23,FALSE),0) -> 0 | CG6: =IFERROR(VLOOKUP(DF6,源_6社保表_Sheet1!$C:$BZ,32,FALSE),0) -> 0 | CH6: =IFERROR(VLOOKUP(DF6,源_6社保表_Sheet1!$C:$BZ,33,FALSE),0) -> 0 | CI6: =IFERROR(VLOOKUP(DF6,源_6社保表_Sheet1!$C:$BZ,34,FALSE),0) -> 0 | CJ6: =IFERROR(VLOOKUP(DF6,源_6社保表_Sheet1!$C:$BZ,38,FALSE),0) -> 0 | CK6: =IFERROR(VLOOKUP(DF6,源_6社保表_Sheet1!$C:$BZ,35,FALSE),0) -> 0 | CL6: =IFERROR(VLOOKUP(DF6,源_6社保表_Sheet1!$C:$BZ,36,FALSE),0) -> 0 | CM6: =IFERROR(VLOOKUP(DF6,源_6社保表_Sheet1!$C:$BZ,37,FALSE),0) -> 0 | CN6: =BZ6+CA6+CB6+CC6+CD6+CE6+CF6+CG6+CH6+CI6+CJ6+CK6+CL6+CM6 -> 2058.8484 | CO6: =BI6+BG6+CN6+BE6+BH6 -> 8016.5448 | CP6: =IF(IFERROR(VLOOKUP(K6,源_13残疾人信息_残疾人信息!$A:$M,1,FALSE),"")<>"",0,IF(OR(P6="门店全职",P6="门店管理组",P6="全职(非门店)"),(BI6-AT6)*IFERROR(VLOOKUP(D6,源_12计提残保金规则_Sheet1!$A:$E,4,FALSE),0)*IFERROR(VLOOKUP(D6,源_12计提残保金规则_Sheet1!$A:$E,5,FALSE),0),0)) -> 79.020383 | CQ6: =IF(M6="行政",0,16.05) -> 16.05 | CR6: =IF(M6="门卫",0,20.67) -> 20.67 | CS6: =IF(DATEVALUE(N6)>DATE(参数!$B$2,9,30),0,IF(M6="行政",0,IF(O6="",R6/12,IF(MONTH(DATEVALUE(O6))=参数!$B$3,0,IF(DATEVALUE(O6)<DATE(参数!$B$2,参数!$B$3,1),0,R6/12))))) -> 321.75 | CT6: =IF(P6="门店管理组",R6*0.12*0.85,0) -> 0 | CU6: =IFERROR(VLOOKUP(DF6,源_6社保表_Sheet1!$C:$I,2,FALSE),0) -> 7162 | CV6: =IFERROR(VLOOKUP(DF6,源_6社保表_Sheet1!$C:$I,7,FALSE),0) -> 5881 | CW6: =IFERROR(VLOOKUP(DF6,源_6社保表_Sheet1!$C:$I,3,FALSE),0) -> 7162 | CX6: =IFERROR(VLOOKUP(DF6,源_6社保表_Sheet1!$C:$I,4,FALSE),0) -> 7162 | CY6: =IFERROR(VLOOKUP(DF6,源_6社保表_Sheet1!$C:$I,5,FALSE),0) -> 7162 | CZ6: =IFERROR(VLOOKUP(DF6,源_6社保表_Sheet1!$C:$I,6,FALSE),0) -> 0 | DA6: =BI6+CN6-AG6-AH6-AI6-AJ6-AK6-AL6-AM6-AQ6-AR6-AS6-AT6 -> 7909.2101 | DB6: =DA6+CP6+CQ6+CR6+CS6+CT6+BH6 -> 8353.2005 | DC6: =IFERROR(VLOOKUP(K6,源_7银行卡表_Sheet1!$A:$J,8,FALSE),"") -> 招商银行 | DD6: =IFERROR(VLOOKUP(K6,源_7银行卡表_Sheet1!$A:$J,9,FALSE),"") -> 6688666641373608696 | DE6: =IFERROR(VLOOKUP(K6,源_7银行卡表_Sheet1!$A:$J,10,FALSE),"") -> 重庆永川支行 | DF6: 110000195008233655 | DG6: 15659025342 | DH6: 北京 | DI6: 0 | DJ6: 0 | DK6: 0 | DL6: 0 | DM6: 0 | DN6: 0 | DO6: 0 | DP6: 0 | DQ6: 0 | DR6: =IF(OR(IFERROR(VLOOKUP(K6,源_3考勤报表_考勤表!$F:$BG,39,FALSE),0)+IFERROR(VLOOKUP(K6,源_8补工时表_补当月工时!$A:$AC,24,FALSE),0)=0,IFERROR(VLOOKUP(K6,源_3考勤报表_考勤表!$F:$BG,43,FALSE),0)+IFERROR(VLOOKUP(K6,源_8补工时表_补当月工时!$A:$AC,26,FALSE),0)=0),IF(BI6+BG6-BT6<0,BI6+BG6-BT6,0),0) -> 0
A7: =参数!$B$2 -> 2025 | B7: =参数!$B$3 -> 12 | D7: 上海达美乐 | E7: 店铺营运 | F7: =IFERROR(VLOOKUP(K7,源_7银行卡表_Sheet1!$A:$J,6,FALSE),"") -> 华东营运 | G7: 上海1 | H7: 七莘路店 | I7: 外服-上海门店全职 | J7: 1 | K7: 26123006 | L7: 严俊铭 | M7: 餐厅经理 | N7: 2020-10-12 | P7: 门店管理组 | Q7: =IF(P7="门店全职",IFERROR(VLOOKUP(K7,源_3考勤报表_考勤表!$F:$BG,34,FALSE),0)+IFERROR(VLOOKUP(K7,源_8补工时表_补当月工时!$A:$AC,14,FALSE),0),IF(P7="门店管理组",IF(IFERROR(VLOOKUP(K7,源_3考勤报表_考勤表!$F:$BG,34,FALSE),0)+IFERROR(VLOOKUP(K7,源_8补工时表_补当月工时!$A:$AC,14,FALSE),0)+IFERROR(VLOOKUP(K7,源_3考勤报表_考勤表!$F:$BG,37,FALSE),0)+IFERROR(VLOOKUP(K7,源_8补工时表_补当月工时!$A:$AC,15,FALSE),0)+IFERROR(VLOOKUP(K7,源_3考勤报表_考勤表!$F:$BG,38,FALSE),0)+IFERROR(VLOOKUP(K7,源_8补工时表_补当月工时!$A:$AC,17,FALSE),0)+IFERROR(VLOOKUP(K7,源_3考勤报表_考勤表!$F:$BG,40,FALSE),0)+IFERROR(VLOOKUP(K7,源_8补工时表_补当月工时!$A:$AC,20,FALSE),0)+IFERROR(VLOOKUP(K7,源_8补工时表_补当月工时!$A:$AC,22,FALSE),0)+IFERROR(VLOOKUP(K7,源_3考勤报表_考勤表!$F:$BG,41,FALSE),0)+IFERROR(VLOOKUP(K7,源_8补工时表_补当月工时!$A:$AC,18,FALSE),0)+IFERROR(VLOOKUP(K7,源_3考勤报表_考勤表!$F:$BG,44,FALSE),0)+IFERROR(VLOOKUP(K7,源_8补工时表_补当月工时!$A:$AC,16,FALSE),0)+IFERROR(VLOOKUP(K7,源_3考勤报表_考勤表!$F:$BG,45,FALSE),0)>=参数!$B$4,参数!$B$4-IFERROR(VLOOKUP(K7,源_3考勤报表_考勤表!$F:$BG,37,FALSE),0)-IFERROR(VLOOKUP(K7,源_8补工时表_补当月工时!$A:$AC,15,FALSE),0)-IFERROR(VLOOKUP(K7,源_3考勤报表_考勤表!$F:$BG,38,FALSE),0)-IFERROR(VLOOKUP(K7,源_8补工时表_补当月工时!$A:$AC,17,FALSE),0)-IFERROR(VLOOKUP(K7,源_3考勤报表_考勤表!$F:$BG,40,FALSE),0)-IFERROR(VLOOKUP(K7,源_8补工时表_补当月工时!$A:$AC,20,FALSE),0)-IFERROR(VLOOKUP(K7,源_8补工时表_补当月工时!$A:$AC,22,FALSE),0)-IFERROR(VLOOKUP(K7,源_3考勤报表_考勤表!$F:$BG,41,FALSE),0)-IFERROR(VLOOKUP(K7,源_8补工时表_补当月工时!$A:$AC,18,FALSE),0)-IFERROR(VLOOKUP(K7,源_3考勤报表_考勤表!$F:$BG,44,FALSE),0)-IFERROR(VLOOKUP(K7,源_8补工时表_补当月工时!$A:$AC,16,FALSE),0)-IFERROR(VLOOKUP(K7,源_3考勤报表_考勤表!$F:$BG,45,FALSE),0),IFERROR(VLOOKUP(K7,源_3考勤报表_考勤表!$F:$BG,34,FALSE),0)+IFERROR(VLOOKUP(K7,源_8补工时表_补当月工时!$A:$AC,14,FALSE),0)),0)) -> 182 | R7: 8039 | S7: 20 | T7: =IF(P7="门店全职",R7/参数!$B$4*(Q7-MAX(IFERROR(VLOOKUP(K7,源_3考勤报表_考勤表!$F:$BG,34,FALSE),0)+IFERROR(VLOOKUP(K7,源_8补工时表_补当月工时!$A:$AC,14,FALSE),0)+IFERROR(VLOOKUP(K7,源_3考勤报表_考勤表!$F:$BG,37,FALSE),0)+IFERROR(VLOOKUP(K7,源_8补工时表_补当月工时!$A:$AC,15,FALSE),0)+IFERROR(VLOOKUP(K7,源_3考勤报表_考勤表!$F:$BG,38,FALSE),0)+IFERROR(VLOOKUP(K7,源_8补工时表_补当月工时!$A:$AC,17,FALSE),0)+IFERROR(VLOOKUP(K7,源_3考勤报表_考勤表!$F:$BG,40,FALSE),0)+IFERROR(VLOOKUP(K7,源_8补工时表_补当月工时!$A:$AC,20,FALSE),0)+IFERROR(VLOOKUP(K7,源_8补工时表_补当月工时!$A:$AC,22,FALSE),0)+IFERROR(VLOOKUP(K7,源_3考勤报表_考勤表!$F:$BG,41,FALSE),0)+IFERROR(VLOOKUP(K7,源_8补工时表_补当月工时!$A:$AC,18,FALSE),0)+IFERROR(VLOOKUP(K7,源_3考勤报表_考勤表!$F:$BG,42,FALSE),0)+IFERROR(VLOOKUP(K7,源_8补工时表_补当月工时!$A:$AC,19,FALSE),0)+IFERROR(VLOOKUP(K7,源_3考勤报表_考勤表!$F:$BG,44,FALSE),0)+IFERROR(VLOOKUP(K7,源_8补工时表_补当月工时!$A:$AC,16,FALSE),0)+IFERROR(VLOOKUP(K7,源_3考勤报表_考勤表!$F:$BG,45,FALSE),0)-参数!$B$4,0)),R7/参数!$B$4*Q7) -> 7951.6196 | U7: 0 | V7: 0 | W7: =X7+Y7+Z7+AA7 -> 19 | X7: =IFERROR(VLOOKUP(K7,源_4奖金汇总表_拆分手工算!$A:$N,8,FALSE),0) -> 19 | Y7: =IFERROR(VLOOKUP(K7,源_5薪资备忘录_工资调整项!$A:$AC,14,FALSE),0) -> 0 | Z7: =IFERROR(VLOOKUP(K7,源_5薪资备忘录_工资调整项!$A:$AC,16,FALSE),0) -> 0 | AA7: =IFERROR(VLOOKUP(K7,源_5薪资备忘录_工资调整项!$A:$AC,15,FALSE),0) -> 0 | AB7: =AC7+AD7+AF7 -> 0 | AC7: =IF(P7="门店全职",R7/174*MAX(IFERROR(VLOOKUP(K7,源_3考勤报表_考勤表!$F:$BG,34,FALSE),0)+IFERROR(VLOOKUP(K7,源_8补工时表_补当月工时!$A:$AC,14,FALSE),0)+IFERROR(VLOOKUP(K7,源_3考勤报表_考勤表!$F:$BG,37,FALSE),0)+IFERROR(VLOOKUP(K7,源_8补工时表_补当月工时!$A:$AC,15,FALSE),0)+IFERROR(VLOOKUP(K7,源_3考勤报表_考勤表!$F:$BG,38,FALSE),0)+IFERROR(VLOOKUP(K7,源_8补工时表_补当月工时!$A:$AC,17,FALSE),0)+IFERROR(VLOOKUP(K7,源_3考勤报表_考勤表!$F:$BG,40,FALSE),0)+IFERROR(VLOOKUP(K7,源_8补工时表_补当月工时!$A:$AC,20,FALSE),0)+IFERROR(VLOOKUP(K7,源_8补工时表_补当月工时!$A:$AC,22,FALSE),0)+IFERROR(VLOOKUP(K7,源_3考勤报表_考勤表!$F:$BG,41,FALSE),0)+IFERROR(VLOOKUP(K7,源_8补工时表_补当月工时!$A:$AC,18,FALSE),0)+IFERROR(VLOOKUP(K7,源_3考勤报表_考勤表!$F:$BG,42,FALSE),0)+IFERROR(VLOOKUP(K7,源_8补工时表_补当月工时!$A:$AC,19,FALSE),0)+IFERROR(VLOOKUP(K7,源_3考勤报表_考勤表!$F:$BG,44,FALSE),0)+IFERROR(VLOOKUP(K7,源_8补工时表_补当月工时!$A:$AC,16,FALSE),0)+IFERROR(VLOOKUP(K7,源_3考勤报表_考勤表!$F:$BG,45,FALSE),0)-参数!$B$4,0)*1.5,0) -> 0 | AD7: 0 | AE7: =IFERROR(VLOOKUP(K7,源_3考勤报表_考勤表!$F:$BG,46,FALSE),0)+IFERROR(VLOOKUP(K7,源_8补工时表_补当月工时!$A:$AC,25,FALSE),0) -> 0 | AF7: =R7/174*AE7*3 -> 0 | AG7: =IFERROR(VLOOKUP(K7,源_4奖金汇总表_拆分手工算!$A:$N,10,FALSE),0) -> 0 | AH7: =IFERROR(VLOOKUP(K7,源_4奖金汇总表_拆分手工算!$A:$N,5,FALSE),0) -> 0 | AI7: =IFERROR(VLOOKUP(K7,源_4奖金汇总表_拆分手工算!$A:$N,11,FALSE),0) -> 0 | AJ7: =IFERROR(VLOOKUP(K7,源_4奖金汇总表_拆分手工算!$A:$N,4,FALSE),0) -> 0 | AK7: =IFERROR(VLOOKUP(K7,源_4奖金汇总表_拆分手工算!$A:$N,3,FALSE),0) -> 0 | AL7: =IFERROR(VLOOKUP(K7,源_4奖金汇总表_拆分手工算!$A:$N,6,FALSE),0) -> 80 | AM7: =IFERROR(VLOOKUP(K7,源_5薪资备忘录_工资调整项!$A:$AC,18,FALSE),0)+IFERROR(VLOOKUP(K7,源_4奖金汇总表_拆分手工算!$A:$N,7,FALSE),0) -> 0 | AN7: =IFERROR(VLOOKUP(K7,源_5薪资备忘录_工资调整项!$A:$AC,17,FALSE),0) -> 0 | AO7: =IF(OR(IFERROR(VLOOKUP(K7,源_3考勤报表_考勤表!$F:$BG,39,FALSE),0)+IFERROR(VLOOKUP(K7,源_8补工时表_补当月工时!$A:$AC,24,FALSE),0)>0,IFERROR(VLOOKUP(K7,源_3考勤报表_考勤表!$F:$BG,43,FALSE),0)+IFERROR(VLOOKUP(K7,源_8补工时表_补当月工时!$A:$AC,26,FALSE),0)>0),IF(IFERROR(VLOOKUP(DH7,源_11产假政策_Sheet1!$C:$F,4,FALSE),"")="是",R7/参数!$B$4*(IFERROR(VLOOKUP(K7,源_3考勤报表_考勤表!$F:$BG,39,FALSE),0)+IFERROR(VLOOKUP(K7,源_8补工时表_补当月工时!$A:$AC,24,FALSE),0)+IFERROR(VLOOKUP(K7,源_3考勤报表_考勤表!$F:$BG,43,FALSE),0)+IFERROR(VLOOKUP(K7,源_8补工时表_补当月工时!$A:$AC,26,FALSE),0)),IFERROR(VLOOKUP(K7,源_5薪资备忘录_工资调整项!$A:$AC,19,FALSE),0)),0) -> 0 | AP7: 0 | AQ7: =IFERROR(VLOOKUP(K7,源_4奖金汇总表_拆分手工算!$A:$N,12,FALSE),0)+IFERROR(VLOOKUP(K7,源_9年终奖表_Sheet1!$A:$E,3,FALSE),0) -> 1200 | AR7: =IFERROR(VLOOKUP(K7,源_4奖金汇总表_拆分手工算!$A:$N,13,FALSE),0)+IFERROR(VLOOKUP(K7,源_9年终奖表_Sheet1!$A:$E,4,FALSE),0) -> 600 | AS7: =IFERROR(VLOOKUP(K7,源_4奖金汇总表_拆分手工算!$A:$N,14,FALSE),0)+IFERROR(VLOOKUP(K7,源_9年终奖表_Sheet1!$A:$E,5,FALSE),0) -> 222 | AT7: =IFERROR(VLOOKUP(K7,源_5薪资备忘录_工资调整项!$A:$AC,20,FALSE),0) -> 0 | AU7: =IFERROR(VLOOKUP(K7,源_5薪资备忘录_工资调整项!$A:$AC,21,FALSE),0)+IFERROR(VLOOKUP(K7,源_4奖金汇总表_拆分手工算!$A:$N,9,FALSE),0) -> 692.2 | AV7: =R7/参数!$B$4*(IFERROR(VLOOKUP(K7,源_3考勤报表_考勤表!$F:$BG,37,FALSE),0)+IFERROR(VLOOKUP(K7,源_8补工时表_补当月工时!$A:$AC,15,FALSE),0)) -> 0 | AW7: =R7/174*MIN(IFERROR(VLOOKUP(K7,源_3考勤报表_考勤表!$F:$BG,35,FALSE),0),174)*IF(DATEDIF(N7,DATE(参数!$B$2,参数!$B$3+1,0),"Y")<2,0.6,IF(DATEDIF(N7,DATE(参数!$B$2,参数!$B$3+1,0),"Y")<4,0.7,IF(DATEDIF(N7,DATE(参数!$B$2,参数!$B$3+1,0),"Y")<6,0.8,IF(DATEDIF(N7,DATE(参数!$B$2,参数!$B$3+1,0),"Y")<8,0.9,1)))) -> 0 | AX7: =IF(Q7+IFERROR(VLOOKUP(K7,源_3考勤报表_考勤表!$F:$BG,37,FALSE),0)+IFERROR(VLOOKUP(K7,源_8补工时表_补当月工时!$A:$AC,15,FALSE),0)>=参数!$B$4,0,IF(Q7+IFERROR(VLOOKUP(K7,源_3考勤报表_考勤表!$F:$BG,37,FALSE),0)+IFERROR(VLOOKUP(K7,源_8补工时表_补当月工时!$A:$AC,15,FALSE),0)+IFERROR(VLOOKUP(K7,源_3考勤报表_考勤表!$F:$BG,38,FALSE),0)+IFERROR(VLOOKUP(K7,源_8补工时表_补当月工时!$A:$AC,17,FALSE),0)+IFERROR(VLOOKUP(K7,源_3考勤报表_考勤表!$F:$BG,40,FALSE),0)+IFERROR(VLOOKUP(K7,源_8补工时表_补当月工时!$A:$AC,20,FALSE),0)+IFERROR(VLOOKUP(K7,源_8补工时表_补当月工时!$A:$AC,22,FALSE),0)+IFERROR(VLOOKUP(K7,源_3考勤报表_考勤表!$F:$BG,41,FALSE),0)+IFERROR(VLOOKUP(K7,源_8补工时表_补当月工时!$A:$AC,18,FALSE),0)+IFERROR(VLOOKUP(K7,源_3考勤报表_考勤表!$F:$BG,42,FALSE),0)+IFERROR(VLOOKUP(K7,源_8补工时表_补当月工时!$A:$AC,19,FALSE),0)+IFERROR(VLOOKUP(K7,源_3考勤报表_考勤表!$F:$BG,44,FALSE),0)+IFERROR(VLOOKUP(K7,源_8补工时表_补当月工时!$A:$AC,16,FALSE),0)+IFERROR(VLOOKUP(K7,源_3考勤报表_考勤表!$F:$BG,45,FALSE),0)<=参数!$B$4,R7/参数!$B$4*(IFERROR(VLOOKUP(K7,源_3考勤报表_考勤表!$F:$BG,38,FALSE),0)+IFERROR(VLOOKUP(K7,源_8补工时表_补当月工时!$A:$AC,17,FALSE),0)+IFERROR(VLOOKUP(K7,源_3考勤报表_考勤表!$F:$BG,40,FALSE),0)+IFERROR(VLOOKUP(K7,源_8补工时表_补当月工时!$A:$AC,20,FALSE),0)+IFERROR(VLOOKUP(K7,源_8补工时表_补当月工时!$A:$AC,22,FALSE),0)+IFERROR(VLOOKUP(K7,源_3考勤报表_考勤表!$F:$BG,41,FALSE),0)+IFERROR(VLOOKUP(K7,源_8补工时表_补当月工时!$A:$AC,18,FALSE),0)+IFERROR(VLOOKUP(K7,源_3考勤报表_考勤表!$F:$BG,42,FALSE),0)+IFERROR(VLOOKUP(K7,源_8补工时表_补当月工时!$A:$AC,19,FALSE),0)+IFERROR(VLOOKUP(K7,源_3考勤报表_考勤表!$F:$BG,44,FALSE),0)+IFERROR(VLOOKUP(K7,源_8补工时表_补当月工时!$A:$AC,16,FALSE),0)+IFERROR(VLOOKUP(K7,源_3考勤报表_考勤表!$F:$BG,45,FALSE),0)),0)) -> 87.380435 | AY7: 0 | AZ7: 0 | BA7: 0 | BB7: 0 | BC7: =IFERROR(VLOOKUP(K7,源_5薪资备忘录_工资调整项!$A:$AC,25,FALSE),0) -> 0 | BD7: 0 | BE7: 0 | BF7: 0 | BG7: =IFERROR(VLOOKUP(K7,源_5薪资备忘录_工资调整项!$A:$AC,22,FALSE),0)+IFERROR(VLOOKUP(K7,源_5薪资备忘录_工资调整项!$A:$AC,23,FALSE),0)+IFERROR(VLOOKUP(K7,源_5薪资备忘录_工资调整项!$A:$AC,24,FALSE),0) -> 0 | BH7: =IFERROR(VLOOKUP(DF7,源_6社保表_Sheet1!$C:$CD,80,FALSE),0)+4.5 -> 6.5 | BI7: =T7+W7+AB7+AG7+AH7+AI7+AJ7+AK7+AL7+AM7+AN7+AO7+AP7+AQ7+AR7+AS7+AT7+AU7+AV7+AW7+AX7+BC7 -> 10852.2 | BJ7: =IFERROR(VLOOKUP(DF7,源_6社保表_Sheet1!$C:$BZ,26,FALSE),0) -> 782.72 | BK7: =IFERROR(VLOOKUP(DF7,源_6社保表_Sheet1!$C:$BZ,27,FALSE),0) -> 195.68 | BL7: =IFERROR(VLOOKUP(DF7,源_6社保表_Sheet1!$C:$BZ,28,FALSE),0) -> 48.92 | BM7: =IFERROR(VLOOKUP(DF7,源_6社保表_Sheet1!$C:$BZ,30,FALSE),0) -> 684.88 | BN7: =IFERROR(VLOOKUP(DF7,源_6社保表_Sheet1!$C:$BZ,29,FALSE),0) -> 0 | BO7: =IFERROR(VLOOKUP(DF7,源_6社保表_Sheet1!$C:$BZ,40,FALSE),0) -> 0 | BP7: =IFERROR(VLOOKUP(DF7,源_6社保表_Sheet1!$C:$BZ,41,FALSE),0) -> 0 | BQ7: =IFERROR(VLOOKUP(DF7,源_6社保表_Sheet1!$C:$BZ,42,FALSE),0) -> 0 | BR7: =IFERROR(VLOOKUP(DF7,源_6社保表_Sheet1!$C:$BZ,44,FALSE),0) -> 0 | BS7: =IFERROR(VLOOKUP(DF7,源_6社保表_Sheet1!$C:$BZ,43,FALSE),0) -> 0 | BT7: =BJ7+BK7+BL7+BM7+BN7+BO7+BP7+BQ7+BR7+BS7 -> 1712.2 | BU7: 0 | BV7: 0 | BW7: 0 | BX7: =BU7+BV7+BW7 -> 0 | BY7: 0 | BZ7: =IFERROR(VLOOKUP(DF7,源_6社保表_Sheet1!$C:$BZ,18,FALSE),0) -> 1565.44 | CA7: =IFERROR(VLOOKUP(DF7,源_6社保表_Sheet1!$C:$BZ,19,FALSE),0) -> 880.56 | CB7: =IFERROR(VLOOKUP(DF7,源_6社保表_Sheet1!$C:$BZ,24,FALSE),0) -> 684.88 | CC7: =IFERROR(VLOOKUP(DF7,源_6社保表_Sheet1!$C:$BZ,20,FALSE),0) -> 48.92 | CD7: =IFERROR(VLOOKUP(DF7,源_6社保表_Sheet1!$C:$BZ,21,FALSE),0) -> 31.3088 | CE7: =IFERROR(VLOOKUP(DF7,源_6社保表_Sheet1!$C:$BZ,22,FALSE),0) -> 0 | CF7: =IFERROR(VLOOKUP(DF7,源_6社保表_Sheet1!$C:$BZ,23,FALSE),0) -> 0 | CG7: =IFERROR(VLOOKUP(DF7,源_6社保表_Sheet1!$C:$BZ,32,FALSE),0) -> 0 | CH7: =IFERROR(VLOOKUP(DF7,源_6社保表_Sheet1!$C:$BZ,33,FALSE),0) -> 0 | CI7: =IFERROR(VLOOKUP(DF7,源_6社保表_Sheet1!$C:$BZ,34,FALSE),0) -> 0 | CJ7: =IFERROR(VLOOKUP(DF7,源_6社保表_Sheet1!$C:$BZ,38,FALSE),0) -> 0 | CK7: =IFERROR(VLOOKUP(DF7,源_6社保表_Sheet1!$C:$BZ,35,FALSE),0) -> 0 | CL7: =IFERROR(VLOOKUP(DF7,源_6社保表_Sheet1!$C:$BZ,36,FALSE),0) -> 0 | CM7: =IFERROR(VLOOKUP(DF7,源_6社保表_Sheet1!$C:$BZ,37,FALSE),0) -> 0 | CN7: =BZ7+CA7+CB7+CC7+CD7+CE7+CF7+CG7+CH7+CI7+CJ7+CK7+CL7+CM7 -> 3211.1088 | CO7: =BI7+BG7+CN7+BE7+BH7 -> 14069.809 | CP7: =IF(IFERROR(VLOOKUP(K7,源_13残疾人信息_残疾人信息!$A:$M,1,FALSE),"")<>"",0,IF(OR(P7="门店全职",P7="门店管理组",P7="全职(非门店)"),(BI7-AT7)*IFERROR(VLOOKUP(D7,源_12计提残保金规则_Sheet1!$A:$E,4,FALSE),0)*IFERROR(VLOOKUP(D7,源_12计提残保金规则_Sheet1!$A:$E,5,FALSE),0),0)) -> 146.5047 | CQ7: =IF(M7="行政",0,16.05) -> 16.05 | CR7: =IF(M7="门卫",0,20.67) -> 20.67 | CS7: =IF(DATEVALUE(N7)>DATE(参数!$B$2,9,30),0,IF(M7="行政",0,IF(O7="",R7/12,IF(MONTH(DATEVALUE(O7))=参数!$B$3,0,IF(DATEVALUE(O7)<DATE(参数!$B$2,参数!$B$3,1),0,R7/12))))) -> 669.91667 | CT7: =IF(P7="门店管理组",R7*0.12*0.85,0) -> 819.978 | CU7: =IFERROR(VLOOKUP(DF7,源_6社保表_Sheet1!$C:$I,2,FALSE),0) -> 9784 | CV7: =IFERROR(VLOOKUP(DF7,源_6社保表_Sheet1!$C:$I,7,FALSE),0) -> 9784 | CW7: =IFERROR(VLOOKUP(DF7,源_6社保表_Sheet1!$C:$I,3,FALSE),0) -> 9784 | CX7: =IFERROR(VLOOKUP(DF7,源_6社保表_Sheet1!$C:$I,4,FALSE),0) -> 9784 | CY7: =IFERROR(VLOOKUP(DF7,源_6社保表_Sheet1!$C:$I,5,FALSE),0) -> 9784 | CZ7: =IFERROR(VLOOKUP(DF7,源_6社保表_Sheet1!$C:$I,6,FALSE),0) -> 0 | DA7: =BI7+CN7-AG7-AH7-AI7-AJ7-AK7-AL7-AM7-AQ7-AR7-AS7-AT7 -> 11961.309 | DB7: =DA7+CP7+CQ7+CR7+CS7+CT7+BH7 -> 13640.928 | DC7: =IFERROR(VLOOKUP(K7,源_7银行卡表_Sheet1!$A:$J,8,FALSE),"") -> 招商银行 | DD7: =IFERROR(VLOOKUP(K7,源_7银行卡表_Sheet1!$A:$J,9,FALSE),"") -> 6684067585518680718 | DE7: =IFERROR(VLOOKUP(K7,源_7银行卡表_Sheet1!$A:$J,10,FALSE),"") -> 泸州江阳支行 | DF7: 110000195410162001 | DG7: 17632896120 | DH7: 上海 | DI7: 0 | DJ7: 0 | DK7: 0 | DL7: 0 | DM7: 0 | DN7: 0 | DO7: 0 | DP7: 0 | DQ7: 0 | DR7: =IF(OR(IFERROR(VLOOKUP(K7,源_3考勤报表_考勤表!$F:$BG,39,FALSE),0)+IFERROR(VLOOKUP(K7,源_8补工时表_补当月工时!$A:$AC,24,FALSE),0)=0,IFERROR(VLOOKUP(K7,源_3考勤报表_考勤表!$F:$BG,43,FALSE),0)+IFERROR(VLOOKUP(K7,源_8补工时表_补当月工时!$A:$AC,26,FALSE),0)=0),IF(BI7+BG7-BT7<0,BI7+BG7-BT7,0),0) -> 0
A8: =参数!$B$2 -> 2025 | B8: =参数!$B$3 -> 12 | D8: 北京达美乐 | E8: 店铺营运 | F8: =IFERROR(VLOOKUP(K8,源_7银行卡表_Sheet1!$A:$J,6,FALSE),"") -> 华北营运 | G8: 北京 | H8: 万丰店 | I8: 外服-北京门店全职 | J8: 1 | K8: 26123007 | L8: 韦紫青 | M8: 餐厅副理 | N8: 2019-01-02 | P8: 门店管理组 | Q8: =IF(P8="门店全职",IFERROR(VLOOKUP(K8,源_3考勤报表_考勤表!$F:$BG,34,FALSE),0)+IFERROR(VLOOKUP(K8,源_8补工时表_补当月工时!$A:$AC,14,FALSE),0),IF(P8="门店管理组",IF(IFERROR(VLOOKUP(K8,源_3考勤报表_考勤表!$F:$BG,34,FALSE),0)+IFERROR(VLOOKUP(K8,源_8补工时表_补当月工时!$A:$AC,14,FALSE),0)+IFERROR(VLOOKUP(K8,源_3考勤报表_考勤表!$F:$BG,37,FALSE),0)+IFERROR(VLOOKUP(K8,源_8补工时表_补当月工时!$A:$AC,15,FALSE),0)+IFERROR(VLOOKUP(K8,源_3考勤报表_考勤表!$F:$BG,38,FALSE),0)+IFERROR(VLOOKUP(K8,源_8补工时表_补当月工时!$A:$AC,17,FALSE),0)+IFERROR(VLOOKUP(K8,源_3考勤报表_考勤表!$F:$BG,40,FALSE),0)+IFERROR(VLOOKUP(K8,源_8补工时表_补当月工时!$A:$AC,20,FALSE),0)+IFERROR(VLOOKUP(K8,源_8补工时表_补当月工时!$A:$AC,22,FALSE),0)+IFERROR(VLOOKUP(K8,源_3考勤报表_考勤表!$F:$BG,41,FALSE),0)+IFERROR(VLOOKUP(K8,源_8补工时表_补当月工时!$A:$AC,18,FALSE),0)+IFERROR(VLOOKUP(K8,源_3考勤报表_考勤表!$F:$BG,44,FALSE),0)+IFERROR(VLOOKUP(K8,源_8补工时表_补当月工时!$A:$AC,16,FALSE),0)+IFERROR(VLOOKUP(K8,源_3考勤报表_考勤表!$F:$BG,45,FALSE),0)>=参数!$B$4,参数!$B$4-IFERROR(VLOOKUP(K8,源_3考勤报表_考勤表!$F:$BG,37,FALSE),0)-IFERROR(VLOOKUP(K8,源_8补工时表_补当月工时!$A:$AC,15,FALSE),0)-IFERROR(VLOOKUP(K8,源_3考勤报表_考勤表!$F:$BG,38,FALSE),0)-IFERROR(VLOOKUP(K8,源_8补工时表_补当月工时!$A:$AC,17,FALSE),0)-IFERROR(VLOOKUP(K8,源_3考勤报表_考勤表!$F:$BG,40,FALSE),0)-IFERROR(VLOOKUP(K8,源_8补工时表_补当月工时!$A:$AC,20,FALSE),0)-IFERROR(VLOOKUP(K8,源_8补工时表_补当月工时!$A:$AC,22,FALSE),0)-IFERROR(VLOOKUP(K8,源_3考勤报表_考勤表!$F:$BG,41,FALSE),0)-IFERROR(VLOOKUP(K8,源_8补工时表_补当月工时!$A:$AC,18,FALSE),0)-IFERROR(VLOOKUP(K8,源_3考勤报表_考勤表!$F:$BG,44,FALSE),0)-IFERROR(VLOOKUP(K8,源_8补工时表_补当月工时!$A:$AC,16,FALSE),0)-IFERROR(VLOOKUP(K8,源_3考勤报表_考勤表!$F:$BG,45,FALSE),0),IFERROR(VLOOKUP(K8,源_3考勤报表_考勤表!$F:$BG,34,FALSE),0)+IFERROR(VLOOKUP(K8,源_8补工时表_补当月工时!$A:$AC,14,FALSE),0)),0)) -> 184 | R8: 5600 | S8: 0 | T8: =IF(P8="门店全职",R8/参数!$B$4*(Q8-MAX(IFERROR(VLOOKUP(K8,源_3考勤报表_考勤表!$F:$BG,34,FALSE),0)+IFERROR(VLOOKUP(K8,源_8补工时表_补当月工时!$A:$AC,14,FALSE),0)+IFERROR(VLOOKUP(K8,源_3考勤报表_考勤表!$F:$BG,37,FALSE),0)+IFERROR(VLOOKUP(K8,源_8补工时表_补当月工时!$A:$AC,15,FALSE),0)+IFERROR(VLOOKUP(K8,源_3考勤报表_考勤表!$F:$BG,38,FALSE),0)+IFERROR(VLOOKUP(K8,源_8补工时表_补当月工时!$A:$AC,17,FALSE),0)+IFERROR(VLOOKUP(K8,源_3考勤报表_考勤表!$F:$BG,40,FALSE),0)+IFERROR(VLOOKUP(K8,源_8补工时表_补当月工时!$A:$AC,20,FALSE),0)+IFERROR(VLOOKUP(K8,源_8补工时表_补当月工时!$A:$AC,22,FALSE),0)+IFERROR(VLOOKUP(K8,源_3考勤报表_考勤表!$F:$BG,41,FALSE),0)+IFERROR(VLOOKUP(K8,源_8补工时表_补当月工时!$A:$AC,18,FALSE),0)+IFERROR(VLOOKUP(K8,源_3考勤报表_考勤表!$F:$BG,42,FALSE),0)+IFERROR(VLOOKUP(K8,源_8补工时表_补当月工时!$A:$AC,19,FALSE),0)+IFERROR(VLOOKUP(K8,源_3考勤报表_考勤表!$F:$BG,44,FALSE),0)+IFERROR(VLOOKUP(K8,源_8补工时表_补当月工时!$A:$AC,16,FALSE),0)+IFERROR(VLOOKUP(K8,源_3考勤报表_考勤表!$F:$BG,45,FALSE),0)-参数!$B$4,0)),R8/参数!$B$4*Q8) -> 5600 | U8: 0 | V8: 0 | W8: =X8+Y8+Z8+AA8 -> 11.5 | X8: =IFERROR(VLOOKUP(K8,源_4奖金汇总表_拆分手工算!$A:$N,8,FALSE),0) -> 11.5 | Y8: =IFERROR(VLOOKUP(K8,源_5薪资备忘录_工资调整项!$A:$AC,14,FALSE),0) -> 0 | Z8: =IFERROR(VLOOKUP(K8,源_5薪资备忘录_工资调整项!$A:$AC,16,FALSE),0) -> 0 | AA8: =IFERROR(VLOOKUP(K8,源_5薪资备忘录_工资调整项!$A:$AC,15,FALSE),0) -> 0 | AB8: =AC8+AD8+AF8 -> 0 | AC8: =IF(P8="门店全职",R8/174*MAX(IFERROR(VLOOKUP(K8,源_3考勤报表_考勤表!$F:$BG,34,FALSE),0)+IFERROR(VLOOKUP(K8,源_8补工时表_补当月工时!$A:$AC,14,FALSE),0)+IFERROR(VLOOKUP(K8,源_3考勤报表_考勤表!$F:$BG,37,FALSE),0)+IFERROR(VLOOKUP(K8,源_8补工时表_补当月工时!$A:$AC,15,FALSE),0)+IFERROR(VLOOKUP(K8,源_3考勤报表_考勤表!$F:$BG,38,FALSE),0)+IFERROR(VLOOKUP(K8,源_8补工时表_补当月工时!$A:$AC,17,FALSE),0)+IFERROR(VLOOKUP(K8,源_3考勤报表_考勤表!$F:$BG,40,FALSE),0)+IFERROR(VLOOKUP(K8,源_8补工时表_补当月工时!$A:$AC,20,FALSE),0)+IFERROR(VLOOKUP(K8,源_8补工时表_补当月工时!$A:$AC,22,FALSE),0)+IFERROR(VLOOKUP(K8,源_3考勤报表_考勤表!$F:$BG,41,FALSE),0)+IFERROR(VLOOKUP(K8,源_8补工时表_补当月工时!$A:$AC,18,FALSE),0)+IFERROR(VLOOKUP(K8,源_3考勤报表_考勤表!$F:$BG,42,FALSE),0)+IFERROR(VLOOKUP(K8,源_8补工时表_补当月工时!$A:$AC,19,FALSE),0)+IFERROR(VLOOKUP(K8,源_3考勤报表_考勤表!$F:$BG,44,FALSE),0)+IFERROR(VLOOKUP(K8,源_8补工时表_补当月工时!$A:$AC,16,FALSE),0)+IFERROR(VLOOKUP(K8,源_3考勤报表_考勤表!$F:$BG,45,FALSE),0)-参数!$B$4,0)*1.5,0) -> 0 | AD8: 0 | AE8: =IFERROR(VLOOKUP(K8,源_3考勤报表_考勤表!$F:$BG,46,FALSE),0)+IFERROR(VLOOKUP(K8,源_8补工时表_补当月工时!$A:$AC,25,FALSE),0) -> 0 | AF8: =R8/174*AE8*3 -> 0 | AG8: =IFERROR(VLOOKUP(K8,源_4奖金汇总表_拆分手工算!$A:$N,10,FALSE),0) -> 0 | AH8: =IFERROR(VLOOKUP(K8,源_4奖金汇总表_拆分手工算!$A:$N,5,FALSE),0) -> 0 | AI8: =IFERROR(VLOOKUP(K8,源_4奖金汇总表_拆分手工算!$A:$N,11,FALSE),0) -> 0 | AJ8: =IFERROR(VLOOKUP(K8,源_4奖金汇总表_拆分手工算!$A:$N,4,FALSE),0) -> 0 | AK8: =IFERROR(VLOOKUP(K8,源_4奖金汇总表_拆分手工算!$A:$N,3,FALSE),0) -> 6000 | AL8: =IFERROR(VLOOKUP(K8,源_4奖金汇总表_拆分手工算!$A:$N,6,FALSE),0) -> 100 | AM8: =IFERROR(VLOOKUP(K8,源_5薪资备忘录_工资调整项!$A:$AC,18,FALSE),0)+IFERROR(VLOOKUP(K8,源_4奖金汇总表_拆分手工算!$A:$N,7,FALSE),0) -> 800 | AN8: =IFERROR(VLOOKUP(K8,源_5薪资备忘录_工资调整项!$A:$AC,17,FALSE),0) -> 0 | AO8: =IF(OR(IFERROR(VLOOKUP(K8,源_3考勤报表_考勤表!$F:$BG,39,FALSE),0)+IFERROR(VLOOKUP(K8,源_8补工时表_补当月工时!$A:$AC,24,FALSE),0)>0,IFERROR(VLOOKUP(K8,源_3考勤报表_考勤表!$F:$BG,43,FALSE),0)+IFERROR(VLOOKUP(K8,源_8补工时表_补当月工时!$A:$AC,26,FALSE),0)>0),IF(IFERROR(VLOOKUP(DH8,源_11产假政策_Sheet1!$C:$F,4,FALSE),"")="是",R8/参数!$B$4*(IFERROR(VLOOKUP(K8,源_3考勤报表_考勤表!$F:$BG,39,FALSE),0)+IFERROR(VLOOKUP(K8,源_8补工时表_补当月工时!$A:$AC,24,FALSE),0)+IFERROR(VLOOKUP(K8,源_3考勤报表_考勤表!$F:$BG,43,FALSE),0)+IFERROR(VLOOKUP(K8,源_8补工时表_补当月工时!$A:$AC,26,FALSE),0)),IFERROR(VLOOKUP(K8,源_5薪资备忘录_工资调整项!$A:$AC,19,FALSE),0)),0) -> 0 | AP8: 0 | AQ8: =IFERROR(VLOOKUP(K8,源_4奖金汇总表_拆分手工算!$A:$N,12,FALSE),0)+IFERROR(VLOOKUP(K8,源_9年终奖表_Sheet1!$A:$E,3,FALSE),0) -> 1200 | AR8: =IFERROR(VLOOKUP(K8,源_4奖金汇总表_拆分手工算!$A:$N,13,FALSE),0)+IFERROR(VLOOKUP(K8,源_9年终奖表_Sheet1!$A:$E,4,FALSE),0) -> 600 | AS8: =IFERROR(VLOOKUP(K8,源_4奖金汇总表_拆分手工算!$A:$N,14,FALSE),0)+IFERROR(VLOOKUP(K8,源_9年终奖表_Sheet1!$A:$E,5,FALSE),0) -> 111 | AT8: =IFERROR(VLOOKUP(K8,源_5薪资备忘录_工资调整项!$A:$AC,20,FALSE),0) -> 0 | AU8: =IFERROR(VLOOKUP(K8,源_5薪资备忘录_工资调整项!$A:$AC,21,FALSE),0)+IFERROR(VLOOKUP(K8,源_4奖金汇总表_拆分手工算!$A:$N,9,FALSE),0) -> 0 | AV8: =R8/参数!$B$4*(IFERROR(VLOOKUP(K8,源_3考勤报表_考勤表!$F:$BG,37,FALSE),0)+IFERROR(VLOOKUP(K8,源_8补工时表_补当月工时!$A:$AC,15,FALSE),0)) -> 0 | AW8: =R8/174*MIN(IFERROR(VLOOKUP(K8,源_3考勤报表_考勤表!$F:$BG,35,FALSE),0),174)*IF(DATEDIF(N8,DATE(参数!$B$2,参数!$B$3+1,0),"Y")<2,0.6,IF(DATEDIF(N8,DATE(参数!$B$2,参数!$B$3+1,0),"Y")<4,0.7,IF(DATEDIF(N8,DATE(参数!$B$2,参数!$B$3+1,0),"Y")<6,0.8,IF(DATEDIF(N8,DATE(参数!$B$2,参数!$B$3+1,0),"Y")<8,0.9,1)))) -> 0 | AX8: =IF(Q8+IFERROR(VLOOKUP(K8,源_3考勤报表_考勤表!$F:$BG,37,FALSE),0)+IFERROR(VLOOKUP(K8,源_8补工时表_补当月工时!$A:$AC,15,FALSE),0)>=参数!$B$4,0,IF(Q8+IFERROR(VLOOKUP(K8,源_3考勤报表_考勤表!$F:$BG,37,FALSE),0)+IFERROR(VLOOKUP(K8,源_8补工时表_补当月工时!$A:$AC,15,FALSE),0)+IFERROR(VLOOKUP(K8,源_3考勤报表_考勤表!$F:$BG,38,FALSE),0)+IFERROR(VLOOKUP(K8,源_8补工时表_补当月工时!$A:$AC,17,FALSE),0)+IFERROR(VLOOKUP(K8,源_3考勤报表_考勤表!$F:$BG,40,FALSE),0)+IFERROR(VLOOKUP(K8,源_8补工时表_补当月工时!$A:$AC,20,FALSE),0)+IFERROR(VLOOKUP(K8,源_8补工时表_补当月工时!$A:$AC,22,FALSE),0)+IFERROR(VLOOKUP(K8,源_3考勤报表_考勤表!$F:$BG,41,FALSE),0)+IFERROR(VLOOKUP(K8,源_8补工时表_补当月工时!$A:$AC,18,FALSE),0)+IFERROR(VLOOKUP(K8,源_3考勤报表_考勤表!$F:$BG,42,FALSE),0)+IFERROR(VLOOKUP(K8,源_8补工时表_补当月工时!$A:$AC,19,FALSE),0)+IFERROR(VLOOKUP(K8,源_3考勤报表_考勤表!$F:$BG,44,FALSE),0)+IFERROR(VLOOKUP(K8,源_8补工时表_补当月工时!$A:$AC,16,FALSE),0)+IFERROR(VLOOKUP(K8,源_3考勤报表_考勤表!$F:$BG,45,FALSE),0)<=参数!$B$4,R8/参数!$B$4*(IFERROR(VLOOKUP(K8,源_3考勤报表_考勤表!$F:$BG,38,FALSE),0)+IFERROR(VLOOKUP(K8,源_8补工时表_补当月工时!$A:$AC,17,FALSE),0)+IFERROR(VLOOKUP(K8,源_3考勤报表_考勤表!$F:$BG,40,FALSE),0)+IFERROR(VLOOKUP(K8,源_8补工时表_补当月工时!$A:$AC,20,FALSE),0)+IFERROR(VLOOKUP(K8,源_8补工时表_补当月工时!$A:$AC,22,FALSE),0)+IFERROR(VLOOKUP(K8,源_3考勤报表_考勤表!$F:$BG,41,FALSE),0)+IFERROR(VLOOKUP(K8,源_8补工时表_补当月工时!$A:$AC,18,FALSE),0)+IFERROR(VLOOKUP(K8,源_3考勤报表_考勤表!$F:$BG,42,FALSE),0)+IFERROR(VLOOKUP(K8,源_8补工时表_补当月工时!$A:$AC,19,FALSE),0)+IFERROR(VLOOKUP(K8,源_3考勤报表_考勤表!$F:$BG,44,FALSE),0)+IFERROR(VLOOKUP(K8,源_8补工时表_补当月工时!$A:$AC,16,FALSE),0)+IFERROR(VLOOKUP(K8,源_3考勤报表_考勤表!$F:$BG,45,FALSE),0)),0)) -> 0 | AY8: 0 | AZ8: 0 | BA8: 0 | BB8: 0 | BC8: =IFERROR(VLOOKUP(K8,源_5薪资备忘录_工资调整项!$A:$AC,25,FALSE),0) -> 0 | BD8: 0 | BE8: =(T8+W8+AB8+AG8+AH8+AI8+AJ8+AK8+AL8+AM8+AN8+AO8+AP8+AU8+AV8+AW8+AX8+BC8-IFERROR(VLOOKUP(DF8,源_6社保表_Sheet1!$C:$BZ,76,FALSE),0))*0.02 -> 230.3938 | BF8: 0 | BG8: =IFERROR(VLOOKUP(K8,源_5薪资备忘录_工资调整项!$A:$AC,22,FALSE),0)+IFERROR(VLOOKUP(K8,源_5薪资备忘录_工资调整项!$A:$AC,23,FALSE),0)+IFERROR(VLOOKUP(K8,源_5薪资备忘录_工资调整项!$A:$AC,24,FALSE),0) -> 0 | BH8: =IFERROR(VLOOKUP(DF8,源_6社保表_Sheet1!$C:$CD,80,FALSE),0)+4.5 -> 6.5 | BI8: =T8+W8+AB8+AG8+AH8+AI8+AJ8+AK8+AL8+AM8+AN8+AO8+AP8+AQ8+AR8+AS8+AT8+AU8+AV8+AW8+AX8+BC8 -> 14422.5 | BJ8: =IFERROR(VLOOKUP(DF8,源_6社保表_Sheet1!$C:$BZ,26,FALSE),0) -> 501.34 | BK8: =IFERROR(VLOOKUP(DF8,源_6社保表_Sheet1!$C:$BZ,27,FALSE),0) -> 71.62 | BL8: =IFERROR(VLOOKUP(DF8,源_6社保表_Sheet1!$C:$BZ,28,FALSE),0) -> 35.81 | BM8: =IFERROR(VLOOKUP(DF8,源_6社保表_Sheet1!$C:$BZ,30,FALSE),0) -> 383.04 | BN8: =IFERROR(VLOOKUP(DF8,源_6社保表_Sheet1!$C:$BZ,29,FALSE),0) -> 0 | BO8: =IFERROR(VLOOKUP(DF8,源_6社保表_Sheet1!$C:$BZ,40,FALSE),0) -> 0 | BP8: =IFERROR(VLOOKUP(DF8,源_6社保表_Sheet1!$C:$BZ,41,FALSE),0) -> 0 | BQ8: =IFERROR(VLOOKUP(DF8,源_6社保表_Sheet1!$C:$BZ,42,FALSE),0) -> 0 | BR8: =IFERROR(VLOOKUP(DF8,源_6社保表_Sheet1!$C:$BZ,44,FALSE),0) -> 0 | BS8: =IFERROR(VLOOKUP(DF8,源_6社保表_Sheet1!$C:$BZ,43,FALSE),0) -> 0 | BT8: =BJ8+BK8+BL8+BM8+BN8+BO8+BP8+BQ8+BR8+BS8 -> 991.81 | BU8: 0 | BV8: 0 | BW8: 0 | BX8: =BU8+BV8+BW8 -> 0 | BY8: 0 | BZ8: =IFERROR(VLOOKUP(DF8,源_6社保表_Sheet1!$C:$BZ,18,FALSE),0) -> 1074.3 | CA8: =IFERROR(VLOOKUP(DF8,源_6社保表_Sheet1!$C:$BZ,19,FALSE),0) -> 572.96 | CB8: =IFERROR(VLOOKUP(DF8,源_6社保表_Sheet1!$C:$BZ,24,FALSE),0) -> 383.04 | CC8: =IFERROR(VLOOKUP(DF8,源_6社保表_Sheet1!$C:$BZ,20,FALSE),0) -> 35.81 | CD8: =IFERROR(VLOOKUP(DF8,源_6社保表_Sheet1!$C:$BZ,21,FALSE),0) -> 22.9184 | CE8: =IFERROR(VLOOKUP(DF8,源_6社保表_Sheet1!$C:$BZ,22,FALSE),0) -> 0 | CF8: =IFERROR(VLOOKUP(DF8,源_6社保表_Sheet1!$C:$BZ,23,FALSE),0) -> 0 | CG8: =IFERROR(VLOOKUP(DF8,源_6社保表_Sheet1!$C:$BZ,32,FALSE),0) -> 0 | CH8: =IFERROR(VLOOKUP(DF8,源_6社保表_Sheet1!$C:$BZ,33,FALSE),0) -> 0 | CI8: =IFERROR(VLOOKUP(DF8,源_6社保表_Sheet1!$C:$BZ,34,FALSE),0) -> 0 | CJ8: =IFERROR(VLOOKUP(DF8,源_6社保表_Sheet1!$C:$BZ,38,FALSE),0) -> 0 | CK8: =IFERROR(VLOOKUP(DF8,源_6社保表_Sheet1!$C:$BZ,35,FALSE),0) -> 0 | CL8: =IFERROR(VLOOKUP(DF8,源_6社保表_Sheet1!$C:$BZ,36,FALSE),0) -> 0 | CM8: =IFERROR(VLOOKUP(DF8,源_6社保表_Sheet1!$C:$BZ,37,FALSE),0) -> 0 | CN8: =BZ8+CA8+CB8+CC8+CD8+CE8+CF8+CG8+CH8+CI8+CJ8+CK8+CL8+CM8 -> 2089.0284 | CO8: =BI8+BG8+CN8+BE8+BH8 -> 16748.422 | CP8: =IF(IFERROR(VLOOKUP(K8,源_13残疾人信息_残疾人信息!$A:$M,1,FALSE),"")<>"",0,IF(OR(P8="门店全职",P8="门店管理组",P8="全职(非门店)"),(BI8-AT8)*IFERROR(VLOOKUP(D8,源_12计提残保金规则_Sheet1!$A:$E,4,FALSE),0)*IFERROR(VLOOKUP(D8,源_12计提残保金规则_Sheet1!$A:$E,5,FALSE),0),0)) -> 194.70375 | CQ8: =IF(M8="行政",0,16.05) -> 16.05 | CR8: =IF(M8="门卫",0,20.67) -> 20.67 | CS8: =IF(DATEVALUE(N8)>DATE(参数!$B$2,9,30),0,IF(M8="行政",0,IF(O8="",R8/12,IF(MONTH(DATEVALUE(O8))=参数!$B$3,0,IF(DATEVALUE(O8)<DATE(参数!$B$2,参数!$B$3,1),0,R8/12))))) -> 466.66667 | CT8: =IF(P8="门店管理组",R8*0.12*0.85,0) -> 571.2 | CU8: =IFERROR(VLOOKUP(DF8,源_6社保表_Sheet1!$C:$I,2,FALSE),0) -> 7162 | CV8: =IFERROR(VLOOKUP(DF8,源_6社保表_Sheet1!$C:$I,7,FALSE),0) -> 6384 | CW8: =IFERROR(VLOOKUP(DF8,源_6社保表_Sheet1!$C:$I,3,FALSE),0) -> 7162 | CX8: =IFERROR(VLOOKUP(DF8,源_6社保表_Sheet1!$C:$I,4,FALSE),0) -> 7162 | CY8: =IFERROR(VLOOKUP(DF8,源_6社保表_Sheet1!$C:$I,5,FALSE),0) -> 7162 | CZ8: =IFERROR(VLOOKUP(DF8,源_6社保表_Sheet1!$C:$I,6,FALSE),0) -> 0 | DA8: =BI8+CN8-AG8-AH8-AI8-AJ8-AK8-AL8-AM8-AQ8-AR8-AS8-AT8 -> 7700.5284 | DB8: =DA8+CP8+CQ8+CR8+CS8+CT8+BH8 -> 8976.3188 | DC8: =IFERROR(VLOOKUP(K8,源_7银行卡表_Sheet1!$A:$J,8,FALSE),"") -> 农业银行 | DD8: =IFERROR(VLOOKUP(K8,源_7银行卡表_Sheet1!$A:$J,9,FALSE),"") -> 6684663836620784469 | DE8: =IFERROR(VLOOKUP(K8,源_7银行卡表_Sheet1!$A:$J,10,FALSE),"") -> 中国农业银行太原西中环路支行 | DF8: 14000019770328217X | DG8: 18306627579 | DH8: 北京 | DI8: 0 | DJ8: 0 | DK8: 0 | DL8: 0 | DM8: 0 | DN8: 0 | DO8: 0 | DP8: 0 | DQ8: 0 | DR8: =IF(OR(IFERROR(VLOOKUP(K8,源_3考勤报表_考勤表!$F:$BG,39,FALSE),0)+IFERROR(VLOOKUP(K8,源_8补工时表_补当月工时!$A:$AC,24,FALSE),0)=0,IFERROR(VLOOKUP(K8,源_3考勤报表_考勤表!$F:$BG,43,FALSE),0)+IFERROR(VLOOKUP(K8,源_8补工时表_补当月工时!$A:$AC,26,FALSE),0)=0),IF(BI8+BG8-BT8<0,BI8+BG8-BT8,0),0) -> 0
A9: =参数!$B$2 -> 2025 | B9: =参数!$B$3 -> 12 | D9: 北京达美乐天津分公司 | E9: 店铺营运 | F9: =IFERROR(VLOOKUP(K9,源_7银行卡表_Sheet1!$A:$J,6,FALSE),"") -> 华北营运 | G9: 天津 | H9: 嘉华店 | I9: 外服-天津门店全职 | J9: 1 | K9: 26123008 | L9: 韩景睿 | M9: 服务员 | N9: 2023-09-14 | P9: 门店全职 | Q9: =IF(P9="门店全职",IFERROR(VLOOKUP(K9,源_3考勤报表_考勤表!$F:$BG,34,FALSE),0)+IFERROR(VLOOKUP(K9,源_8补工时表_补当月工时!$A:$AC,14,FALSE),0),IF(P9="门店管理组",IF(IFERROR(VLOOKUP(K9,源_3考勤报表_考勤表!$F:$BG,34,FALSE),0)+IFERROR(VLOOKUP(K9,源_8补工时表_补当月工时!$A:$AC,14,FALSE),0)+IFERROR(VLOOKUP(K9,源_3考勤报表_考勤表!$F:$BG,37,FALSE),0)+IFERROR(VLOOKUP(K9,源_8补工时表_补当月工时!$A:$AC,15,FALSE),0)+IFERROR(VLOOKUP(K9,源_3考勤报表_考勤表!$F:$BG,38,FALSE),0)+IFERROR(VLOOKUP(K9,源_8补工时表_补当月工时!$A:$AC,17,FALSE),0)+IFERROR(VLOOKUP(K9,源_3考勤报表_考勤表!$F:$BG,40,FALSE),0)+IFERROR(VLOOKUP(K9,源_8补工时表_补当月工时!$A:$AC,20,FALSE),0)+IFERROR(VLOOKUP(K9,源_8补工时表_补当月工时!$A:$AC,22,FALSE),0)+IFERROR(VLOOKUP(K9,源_3考勤报表_考勤表!$F:$BG,41,FALSE),0)+IFERROR(VLOOKUP(K9,源_8补工时表_补当月工时!$A:$AC,18,FALSE),0)+IFERROR(VLOOKUP(K9,源_3考勤报表_考勤表!$F:$BG,44,FALSE),0)+IFERROR(VLOOKUP(K9,源_8补工时表_补当月工时!$A:$AC,16,FALSE),0)+IFERROR(VLOOKUP(K9,源_3考勤报表_考勤表!$F:$BG,45,FALSE),0)>=参数!$B$4,参数!$B$4-IFERROR(VLOOKUP(K9,源_3考勤报表_考勤表!$F:$BG,37,FALSE),0)-IFERROR(VLOOKUP(K9,源_8补工时表_补当月工时!$A:$AC,15,FALSE),0)-IFERROR(VLOOKUP(K9,源_3考勤报表_考勤表!$F:$BG,38,FALSE),0)-IFERROR(VLOOKUP(K9,源_8补工时表_补当月工时!$A:$AC,17,FALSE),0)-IFERROR(VLOOKUP(K9,源_3考勤报表_考勤表!$F:$BG,40,FALSE),0)-IFERROR(VLOOKUP(K9,源_8补工时表_补当月工时!$A:$AC,20,FALSE),0)-IFERROR(VLOOKUP(K9,源_8补工时表_补当月工时!$A:$AC,22,FALSE),0)-IFERROR(VLOOKUP(K9,源_3考勤报表_考勤表!$F:$BG,41,FALSE),0)-IFERROR(VLOOKUP(K9,源_8补工时表_补当月工时!$A:$AC,18,FALSE),0)-IFERROR(VLOOKUP(K9,源_3考勤报表_考勤表!$F:$BG,44,FALSE),0)-IFERROR(VLOOKUP(K9,源_8补工时表_补当月工时!$A:$AC,16,FALSE),0)-IFERROR(VLOOKUP(K9,源_3考勤报表_考勤表!$F:$BG,45,FALSE),0),IFERROR(VLOOKUP(K9,源_3考勤报表_考勤表!$F:$BG,34,FALSE),0)+IFERROR(VLOOKUP(K9,源_8补工时表_补当月工时!$A:$AC,14,FALSE),0)),0)) -> 184 | R9: 3130 | S9: 0 | T9: =IF(P9="门店全职",R9/参数!$B$4*(Q9-MAX(IFERROR(VLOOKUP(K9,源_3考勤报表_考勤表!$F:$BG,34,FALSE),0)+IFERROR(VLOOKUP(K9,源_8补工时表_补当月工时!$A:$AC,14,FALSE),0)+IFERROR(VLOOKUP(K9,源_3考勤报表_考勤表!$F:$BG,37,FALSE),0)+IFERROR(VLOOKUP(K9,源_8补工时表_补当月工时!$A:$AC,15,FALSE),0)+IFERROR(VLOOKUP(K9,源_3考勤报表_考勤表!$F:$BG,38,FALSE),0)+IFERROR(VLOOKUP(K9,源_8补工时表_补当月工时!$A:$AC,17,FALSE),0)+IFERROR(VLOOKUP(K9,源_3考勤报表_考勤表!$F:$BG,40,FALSE),0)+IFERROR(VLOOKUP(K9,源_8补工时表_补当月工时!$A:$AC,20,FALSE),0)+IFERROR(VLOOKUP(K9,源_8补工时表_补当月工时!$A:$AC,22,FALSE),0)+IFERROR(VLOOKUP(K9,源_3考勤报表_考勤表!$F:$BG,41,FALSE),0)+IFERROR(VLOOKUP(K9,源_8补工时表_补当月工时!$A:$AC,18,FALSE),0)+IFERROR(VLOOKUP(K9,源_3考勤报表_考勤表!$F:$BG,42,FALSE),0)+IFERROR(VLOOKUP(K9,源_8补工时表_补当月工时!$A:$AC,19,FALSE),0)+IFERROR(VLOOKUP(K9,源_3考勤报表_考勤表!$F:$BG,44,FALSE),0)+IFERROR(VLOOKUP(K9,源_8补工时表_补当月工时!$A:$AC,16,FALSE),0)+IFERROR(VLOOKUP(K9,源_3考勤报表_考勤表!$F:$BG,45,FALSE),0)-参数!$B$4,0)),R9/参数!$B$4*Q9) -> 3130 | U9: 0 | V9: 0 | W9: =X9+Y9+Z9+AA9 -> 0 | X9: =IFERROR(VLOOKUP(K9,源_4奖金汇总表_拆分手工算!$A:$N,8,FALSE),0) -> 0 | Y9: =IFERROR(VLOOKUP(K9,源_5薪资备忘录_工资调整项!$A:$AC,14,FALSE),0) -> 0 | Z9: =IFERROR(VLOOKUP(K9,源_5薪资备忘录_工资调整项!$A:$AC,16,FALSE),0) -> 0 | AA9: =IFERROR(VLOOKUP(K9,源_5薪资备忘录_工资调整项!$A:$AC,15,FALSE),0) -> 0 | AB9: =AC9+AD9+AF9 -> 0 | AC9: =IF(P9="门店全职",R9/174*MAX(IFERROR(VLOOKUP(K9,源_3考勤报表_考勤表!$F:$BG,34,FALSE),0)+IFERROR(VLOOKUP(K9,源_8补工时表_补当月工时!$A:$AC,14,FALSE),0)+IFERROR(VLOOKUP(K9,源_3考勤报表_考勤表!$F:$BG,37,FALSE),0)+IFERROR(VLOOKUP(K9,源_8补工时表_补当月工时!$A:$AC,15,FALSE),0)+IFERROR(VLOOKUP(K9,源_3考勤报表_考勤表!$F:$BG,38,FALSE),0)+IFERROR(VLOOKUP(K9,源_8补工时表_补当月工时!$A:$AC,17,FALSE),0)+IFERROR(VLOOKUP(K9,源_3考勤报表_考勤表!$F:$BG,40,FALSE),0)+IFERROR(VLOOKUP(K9,源_8补工时表_补当月工时!$A:$AC,20,FALSE),0)+IFERROR(VLOOKUP(K9,源_8补工时表_补当月工时!$A:$AC,22,FALSE),0)+IFERROR(VLOOKUP(K9,源_3考勤报表_考勤表!$F:$BG,41,FALSE),0)+IFERROR(VLOOKUP(K9,源_8补工时表_补当月工时!$A:$AC,18,FALSE),0)+IFERROR(VLOOKUP(K9,源_3考勤报表_考勤表!$F:$BG,42,FALSE),0)+IFERROR(VLOOKUP(K9,源_8补工时表_补当月工时!$A:$AC,19,FALSE),0)+IFERROR(VLOOKUP(K9,源_3考勤报表_考勤表!$F:$BG,44,FALSE),0)+IFERROR(VLOOKUP(K9,源_8补工时表_补当月工时!$A:$AC,16,FALSE),0)+IFERROR(VLOOKUP(K9,源_3考勤报表_考勤表!$F:$BG,45,FALSE),0)-参数!$B$4,0)*1.5,0) -> 0 | AD9: 0 | AE9: =IFERROR(VLOOKUP(K9,源_3考勤报表_考勤表!$F:$BG,46,FALSE),0)+IFERROR(VLOOKUP(K9,源_8补工时表_补当月工时!$A:$AC,25,FALSE),0) -> 0 | AF9: =R9/174*AE9*3 -> 0 | AG9: =IFERROR(VLOOKUP(K9,源_4奖金汇总表_拆分手工算!$A:$N,10,FALSE),0) -> 96 | AH9: =IFERROR(VLOOKUP(K9,源_4奖金汇总表_拆分手工算!$A:$N,5,FALSE),0) -> 0 | AI9: =IFERROR(VLOOKUP(K9,源_4奖金汇总表_拆分手工算!$A:$N,11,FALSE),0) -> 0 | AJ9: =IFERROR(VLOOKUP(K9,源_4奖金汇总表_拆分手工算!$A:$N,4,FALSE),0) -> 0 | AK9: =IFERROR(VLOOKUP(K9,源_4奖金汇总表_拆分手工算!$A:$N,3,FALSE),0) -> 0 | AL9: =IFERROR(VLOOKUP(K9,源_4奖金汇总表_拆分手工算!$A:$N,6,FALSE),0) -> 0 | AM9: =IFERROR(VLOOKUP(K9,源_5薪资备忘录_工资调整项!$A:$AC,18,FALSE),0)+IFERROR(VLOOKUP(K9,源_4奖金汇总表_拆分手工算!$A:$N,7,FALSE),0) -> 0 | AN9: =IFERROR(VLOOKUP(K9,源_5薪资备忘录_工资调整项!$A:$AC,17,FALSE),0) -> 0 | AO9: =IF(OR(IFERROR(VLOOKUP(K9,源_3考勤报表_考勤表!$F:$BG,39,FALSE),0)+IFERROR(VLOOKUP(K9,源_8补工时表_补当月工时!$A:$AC,24,FALSE),0)>0,IFERROR(VLOOKUP(K9,源_3考勤报表_考勤表!$F:$BG,43,FALSE),0)+IFERROR(VLOOKUP(K9,源_8补工时表_补当月工时!$A:$AC,26,FALSE),0)>0),IF(IFERROR(VLOOKUP(DH9,源_11产假政策_Sheet1!$C:$F,4,FALSE),"")="是",R9/参数!$B$4*(IFERROR(VLOOKUP(K9,源_3考勤报表_考勤表!$F:$BG,39,FALSE),0)+IFERROR(VLOOKUP(K9,源_8补工时表_补当月工时!$A:$AC,24,FALSE),0)+IFERROR(VLOOKUP(K9,源_3考勤报表_考勤表!$F:$BG,43,FALSE),0)+IFERROR(VLOOKUP(K9,源_8补工时表_补当月工时!$A:$AC,26,FALSE),0)),IFERROR(VLOOKUP(K9,源_5薪资备忘录_工资调整项!$A:$AC,19,FALSE),0)),0) -> 0 | AP9: 0 | AQ9: =IFERROR(VLOOKUP(K9,源_4奖金汇总表_拆分手工算!$A:$N,12,FALSE),0)+IFERROR(VLOOKUP(K9,源_9年终奖表_Sheet1!$A:$E,3,FALSE),0) -> 0 | AR9: =IFERROR(VLOOKUP(K9,源_4奖金汇总表_拆分手工算!$A:$N,13,FALSE),0)+IFERROR(VLOOKUP(K9,源_9年终奖表_Sheet1!$A:$E,4,FALSE),0) -> 0 | AS9: =IFERROR(VLOOKUP(K9,源_4奖金汇总表_拆分手工算!$A:$N,14,FALSE),0)+IFERROR(VLOOKUP(K9,源_9年终奖表_Sheet1!$A:$E,5,FALSE),0) -> 0 | AT9: =IFERROR(VLOOKUP(K9,源_5薪资备忘录_工资调整项!$A:$AC,20,FALSE),0) -> 0 | AU9: =IFERROR(VLOOKUP(K9,源_5薪资备忘录_工资调整项!$A:$AC,21,FALSE),0)+IFERROR(VLOOKUP(K9,源_4奖金汇总表_拆分手工算!$A:$N,9,FALSE),0) -> 0 | AV9: =R9/参数!$B$4*(IFERROR(VLOOKUP(K9,源_3考勤报表_考勤表!$F:$BG,37,FALSE),0)+IFERROR(VLOOKUP(K9,源_8补工时表_补当月工时!$A:$AC,15,FALSE),0)) -> 0 | AW9: =R9/174*MIN(IFERROR(VLOOKUP(K9,源_3考勤报表_考勤表!$F:$BG,35,FALSE),0),174)*IF(DATEDIF(N9,DATE(参数!$B$2,参数!$B$3+1,0),"Y")<2,0.6,IF(DATEDIF(N9,DATE(参数!$B$2,参数!$B$3+1,0),"Y")<4,0.7,IF(DATEDIF(N9,DATE(参数!$B$2,参数!$B$3+1,0),"Y")<6,0.8,IF(DATEDIF(N9,DATE(参数!$B$2,参数!$B$3+1,0),"Y")<8,0.9,1)))) -> 0 | AX9: =IF(Q9+IFERROR(VLOOKUP(K9,源_3考勤报表_考勤表!$F:$BG,37,FALSE),0)+IFERROR(VLOOKUP(K9,源_8补工时表_补当月工时!$A:$AC,15,FALSE),0)>=参数!$B$4,0,IF(Q9+IFERROR(VLOOKUP(K9,源_3考勤报表_考勤表!$F:$BG,37,FALSE),0)+IFERROR(VLOOKUP(K9,源_8补工时表_补当月工时!$A:$AC,15,FALSE),0)+IFERROR(VLOOKUP(K9,源_3考勤报表_考勤表!$F:$BG,38,FALSE),0)+IFERROR(VLOOKUP(K9,源_8补工时表_补当月工时!$A:$AC,17,FALSE),0)+IFERROR(VLOOKUP(K9,源_3考勤报表_考勤表!$F:$BG,40,FALSE),0)+IFERROR(VLOOKUP(K9,源_8补工时表_补当月工时!$A:$AC,20,FALSE),0)+IFERROR(VLOOKUP(K9,源_8补工时表_补当月工时!$A:$AC,22,FALSE),0)+IFERROR(VLOOKUP(K9,源_3考勤报表_考勤表!$F:$BG,41,FALSE),0)+IFERROR(VLOOKUP(K9,源_8补工时表_补当月工时!$A:$AC,18,FALSE),0)+IFERROR(VLOOKUP(K9,源_3考勤报表_考勤表!$F:$BG,42,FALSE),0)+IFERROR(VLOOKUP(K9,源_8补工时表_补当月工时!$A:$AC,19,FALSE),0)+IFERROR(VLOOKUP(K9,源_3考勤报表_考勤表!$F:$BG,44,FALSE),0)+IFERROR(VLOOKUP(K9,源_8补工时表_补当月工时!$A:$AC,16,FALSE),0)+IFERROR(VLOOKUP(K9,源_3考勤报表_考勤表!$F:$BG,45,FALSE),0)<=参数!$B$4,R9/参数!$B$4*(IFERROR(VLOOKUP(K9,源_3考勤报表_考勤表!$F:$BG,38,FALSE),0)+IFERROR(VLOOKUP(K9,源_8补工时表_补当月工时!$A:$AC,17,FALSE),0)+IFERROR(VLOOKUP(K9,源_3考勤报表_考勤表!$F:$BG,40,FALSE),0)+IFERROR(VLOOKUP(K9,源_8补工时表_补当月工时!$A:$AC,20,FALSE),0)+IFERROR(VLOOKUP(K9,源_8补工时表_补当月工时!$A:$AC,22,FALSE),0)+IFERROR(VLOOKUP(K9,源_3考勤报表_考勤表!$F:$BG,41,FALSE),0)+IFERROR(VLOOKUP(K9,源_8补工时表_补当月工时!$A:$AC,18,FALSE),0)+IFERROR(VLOOKUP(K9,源_3考勤报表_考勤表!$F:$BG,42,FALSE),0)+IFERROR(VLOOKUP(K9,源_8补工时表_补当月工时!$A:$AC,19,FALSE),0)+IFERROR(VLOOKUP(K9,源_3考勤报表_考勤表!$F:$BG,44,FALSE),0)+IFERROR(VLOOKUP(K9,源_8补工时表_补当月工时!$A:$AC,16,FALSE),0)+IFERROR(VLOOKUP(K9,源_3考勤报表_考勤表!$F:$BG,45,FALSE),0)),0)) -> 0 | AY9: 0 | AZ9: 0 | BA9: 0 | BB9: 0 | BC9: =IFERROR(VLOOKUP(K9,源_5薪资备忘录_工资调整项!$A:$AC,25,FALSE),0) -> 0 | BD9: 0 | BE9: 0 | BF9: 0 | BG9: =IFERROR(VLOOKUP(K9,源_5薪资备忘录_工资调整项!$A:$AC,22,FALSE),0)+IFERROR(VLOOKUP(K9,源_5薪资备忘录_工资调整项!$A:$AC,23,FALSE),0)+IFERROR(VLOOKUP(K9,源_5薪资备忘录_工资调整项!$A:$AC,24,FALSE),0) -> 0 | BH9: =IFERROR(VLOOKUP(DF9,源_6社保表_Sheet1!$C:$CD,80,FALSE),0)+4.5 -> 6.5 | BI9: =T9+W9+AB9+AG9+AH9+AI9+AJ9+AK9+AL9+AM9+AN9+AO9+AP9+AQ9+AR9+AS9+AT9+AU9+AV9+AW9+AX9+BC9 -> 3226 | BJ9: =IFERROR(VLOOKUP(DF9,源_6社保表_Sheet1!$C:$BZ,26,FALSE),0) -> 358.68 | BK9: =IFERROR(VLOOKUP(DF9,源_6社保表_Sheet1!$C:$BZ,27,FALSE),0) -> 51.24 | BL9: =IFERROR(VLOOKUP(DF9,源_6社保表_Sheet1!$C:$BZ,28,FALSE),0) -> 25.62 | BM9: =IFERROR(VLOOKUP(DF9,源_6社保表_Sheet1!$C:$BZ,30,FALSE),0) -> 252.9 | BN9: =IFERROR(VLOOKUP(DF9,源_6社保表_Sheet1!$C:$BZ,29,FALSE),0) -> 0 | BO9: =IFERROR(VLOOKUP(DF9,源_6社保表_Sheet1!$C:$BZ,40,FALSE),0) -> 0 | BP9: =IFERROR(VLOOKUP(DF9,源_6社保表_Sheet1!$C:$BZ,41,FALSE),0) -> 0 | BQ9: =IFERROR(VLOOKUP(DF9,源_6社保表_Sheet1!$C:$BZ,42,FALSE),0) -> 0 | BR9: =IFERROR(VLOOKUP(DF9,源_6社保表_Sheet1!$C:$BZ,44,FALSE),0) -> 0 | BS9: =IFERROR(VLOOKUP(DF9,源_6社保表_Sheet1!$C:$BZ,43,FALSE),0) -> 0 | BT9: =BJ9+BK9+BL9+BM9+BN9+BO9+BP9+BQ9+BR9+BS9 -> 688.44 | BU9: 0 | BV9: 0 | BW9: 0 | BX9: =BU9+BV9+BW9 -> 0 | BY9: 0 | BZ9: =IFERROR(VLOOKUP(DF9,源_6社保表_Sheet1!$C:$BZ,18,FALSE),0) -> 768.6 | CA9: =IFERROR(VLOOKUP(DF9,源_6社保表_Sheet1!$C:$BZ,19,FALSE),0) -> 409.92 | CB9: =IFERROR(VLOOKUP(DF9,源_6社保表_Sheet1!$C:$BZ,24,FALSE),0) -> 252.9 | CC9: =IFERROR(VLOOKUP(DF9,源_6社保表_Sheet1!$C:$BZ,20,FALSE),0) -> 25.62 | CD9: =IFERROR(VLOOKUP(DF9,源_6社保表_Sheet1!$C:$BZ,21,FALSE),0) -> 16.3968 | CE9: =IFERROR(VLOOKUP(DF9,源_6社保表_Sheet1!$C:$BZ,22,FALSE),0) -> 0 | CF9: =IFERROR(VLOOKUP(DF9,源_6社保表_Sheet1!$C:$BZ,23,FALSE),0) -> 0 | CG9: =IFERROR(VLOOKUP(DF9,源_6社保表_Sheet1!$C:$BZ,32,FALSE),0) -> 0 | CH9: =IFERROR(VLOOKUP(DF9,源_6社保表_Sheet1!$C:$BZ,33,FALSE),0) -> 0 | CI9: =IFERROR(VLOOKUP(DF9,源_6社保表_Sheet1!$C:$BZ,34,FALSE),0) -> 0 | CJ9: =IFERROR(VLOOKUP(DF9,源_6社保表_Sheet1!$C:$BZ,38,FALSE),0) -> 0 | CK9: =IFERROR(VLOOKUP(DF9,源_6社保表_Sheet1!$C:$BZ,35,FALSE),0) -> 0 | CL9: =IFERROR(VLOOKUP(DF9,源_6社保表_Sheet1!$C:$BZ,36,FALSE),0) -> 0 | CM9: =IFERROR(VLOOKUP(DF9,源_6社保表_Sheet1!$C:$BZ,37,FALSE),0) -> 0 | CN9: =BZ9+CA9+CB9+CC9+CD9+CE9+CF9+CG9+CH9+CI9+CJ9+CK9+CL9+CM9 -> 1473.4368 | CO9: =BI9+BG9+CN9+BE9+BH9 -> 4705.9368 | CP9: =IF(IFERROR(VLOOKUP(K9,源_13残疾人信息_残疾人信息!$A:$M,1,FALSE),"")<>"",0,IF(OR(P9="门店全职",P9="门店管理组",P9="全职(非门店)"),(BI9-AT9)*IFERROR(VLOOKUP(D9,源_12计提残保金规则_Sheet1!$A:$E,4,FALSE),0)*IFERROR(VLOOKUP(D9,源_12计提残保金规则_Sheet1!$A:$E,5,FALSE),0),0)) -> 43.551 | CQ9: =IF(M9="行政",0,16.05) -> 16.05 | CR9: =IF(M9="门卫",0,20.67) -> 20.67 | CS9: =IF(DATEVALUE(N9)>DATE(参数!$B$2,9,30),0,IF(M9="行政",0,IF(O9="",R9/12,IF(MONTH(DATEVALUE(O9))=参数!$B$3,0,IF(DATEVALUE(O9)<DATE(参数!$B$2,参数!$B$3,1),0,R9/12))))) -> 260.83333 | CT9: =IF(P9="门店管理组",R9*0.12*0.85,0) -> 0 | CU9: =IFERROR(VLOOKUP(DF9,源_6社保表_Sheet1!$C:$I,2,FALSE),0) -> 5124 | CV9: =IFERROR(VLOOKUP(DF9,源_6社保表_Sheet1!$C:$I,7,FALSE),0) -> 4215 | CW9: =IFERROR(VLOOKUP(DF9,源_6社保表_Sheet1!$C:$I,3,FALSE),0) -> 5124 | CX9: =IFERROR(VLOOKUP(DF9,源_6社保表_Sheet1!$C:$I,4,FALSE),0) -> 5124 | CY9: =IFERROR(VLOOKUP(DF9,源_6社保表_Sheet1!$C:$I,5,FALSE),0) -> 5124 | CZ9: =IFERROR(VLOOKUP(DF9,源_6社保表_Sheet1!$C:$I,6,FALSE),0) -> 0 | DA9: =BI9+CN9-AG9-AH9-AI9-AJ9-AK9-AL9-AM9-AQ9-AR9-AS9-AT9 -> 4603.4368 | DB9: =DA9+CP9+CQ9+CR9+CS9+CT9+BH9 -> 4951.0411 | DC9: =IFERROR(VLOOKUP(K9,源_7银行卡表_Sheet1!$A:$J,8,FALSE),"") -> 农业银行 | DD9: =IFERROR(VLOOKUP(K9,源_7银行卡表_Sheet1!$A:$J,9,FALSE),"") -> 6687209669546365542 | DE9: =IFERROR(VLOOKUP(K9,源_7银行卡表_Sheet1!$A:$J,10,FALSE),"") -> 中国农业银行娄烦云水支行 | DF9: 110000195612254793 | DG9: 18731710130 | DH9: 天津 | DI9: 0 | DJ9: 0 | DK9: 0 | DL9: 0 | DM9: 0 | DN9: 0 | DO9: 0 | DP9: 0 | DQ9: 0 | DR9: =IF(OR(IFERROR(VLOOKUP(K9,源_3考勤报表_考勤表!$F:$BG,39,FALSE),0)+IFERROR(VLOOKUP(K9,源_8补工时表_补当月工时!$A:$AC,24,FALSE),0)=0,IFERROR(VLOOKUP(K9,源_3考勤报表_考勤表!$F:$BG,43,FALSE),0)+IFERROR(VLOOKUP(K9,源_8补工时表_补当月工时!$A:$AC,26,FALSE),0)=0),IF(BI9+BG9-BT9<0,BI9+BG9-BT9,0),0) -> 0
A10: =参数!$B$2 -> 2025 | B10: =参数!$B$3 -> 12 | D10: 杭州达美乐 | E10: 店铺营运 | F10: =IFERROR(VLOOKUP(K10,源_7银行卡表_Sheet1!$A:$J,6,FALSE),"") -> 华东营运 | G10: 绍兴 | H10: 绍兴金帝银泰城店 | I10: 外服-杭州门店全职 | J10: 1 | K10: 26123009 | L10: 单睿轩 | M10: 餐厅副理 | N10: 2020-03-01 | P10: 门店管理组 | Q10: =IF(P10="门店全职",IFERROR(VLOOKUP(K10,源_3考勤报表_考勤表!$F:$BG,34,FALSE),0)+IFERROR(VLOOKUP(K10,源_8补工时表_补当月工时!$A:$AC,14,FALSE),0),IF(P10="门店管理组",IF(IFERROR(VLOOKUP(K10,源_3考勤报表_考勤表!$F:$BG,34,FALSE),0)+IFERROR(VLOOKUP(K10,源_8补工时表_补当月工时!$A:$AC,14,FALSE),0)+IFERROR(VLOOKUP(K10,源_3考勤报表_考勤表!$F:$BG,37,FALSE),0)+IFERROR(VLOOKUP(K10,源_8补工时表_补当月工时!$A:$AC,15,FALSE),0)+IFERROR(VLOOKUP(K10,源_3考勤报表_考勤表!$F:$BG,38,FALSE),0)+IFERROR(VLOOKUP(K10,源_8补工时表_补当月工时!$A:$AC,17,FALSE),0)+IFERROR(VLOOKUP(K10,源_3考勤报表_考勤表!$F:$BG,40,FALSE),0)+IFERROR(VLOOKUP(K10,源_8补工时表_补当月工时!$A:$AC,20,FALSE),0)+IFERROR(VLOOKUP(K10,源_8补工时表_补当月工时!$A:$AC,22,FALSE),0)+IFERROR(VLOOKUP(K10,源_3考勤报表_考勤表!$F:$BG,41,FALSE),0)+IFERROR(VLOOKUP(K10,源_8补工时表_补当月工时!$A:$AC,18,FALSE),0)+IFERROR(VLOOKUP(K10,源_3考勤报表_考勤表!$F:$BG,44,FALSE),0)+IFERROR(VLOOKUP(K10,源_8补工时表_补当月工时!$A:$AC,16,FALSE),0)+IFERROR(VLOOKUP(K10,源_3考勤报表_考勤表!$F:$BG,45,FALSE),0)>=参数!$B$4,参数!$B$4-IFERROR(VLOOKUP(K10,源_3考勤报表_考勤表!$F:$BG,37,FALSE),0)-IFERROR(VLOOKUP(K10,源_8补工时表_补当月工时!$A:$AC,15,FALSE),0)-IFERROR(VLOOKUP(K10,源_3考勤报表_考勤表!$F:$BG,38,FALSE),0)-IFERROR(VLOOKUP(K10,源_8补工时表_补当月工时!$A:$AC,17,FALSE),0)-IFERROR(VLOOKUP(K10,源_3考勤报表_考勤表!$F:$BG,40,FALSE),0)-IFERROR(VLOOKUP(K10,源_8补工时表_补当月工时!$A:$AC,20,FALSE),0)-IFERROR(VLOOKUP(K10,源_8补工时表_补当月工时!$A:$AC,22,FALSE),0)-IFERROR(VLOOKUP(K10,源_3考勤报表_考勤表!$F:$BG,41,FALSE),0)-IFERROR(VLOOKUP(K10,源_8补工时表_补当月工时!$A:$AC,18,FALSE),0)-IFERROR(VLOOKUP(K10,源_3考勤报表_考勤表!$F:$BG,44,FALSE),0)-IFERROR(VLOOKUP(K10,源_8补工时表_补当月工时!$A:$AC,16,FALSE),0)-IFERROR(VLOOKUP(K10,源_3考勤报表_考勤表!$F:$BG,45,FALSE),0),IFERROR(VLOOKUP(K10,源_3考勤报表_考勤表!$F:$BG,34,FALSE),0)+IFERROR(VLOOKUP(K10,源_8补工时表_补当月工时!$A:$AC,14,FALSE),0)),0)) -> 170 | R10: 5468 | S10: 0 | T10: =IF(P10="门店全职",R10/参数!$B$4*(Q10-MAX(IFERROR(VLOOKUP(K10,源_3考勤报表_考勤表!$F:$BG,34,FALSE),0)+IFERROR(VLOOKUP(K10,源_8补工时表_补当月工时!$A:$AC,14,FALSE),0)+IFERROR(VLOOKUP(K10,源_3考勤报表_考勤表!$F:$BG,37,FALSE),0)+IFERROR(VLOOKUP(K10,源_8补工时表_补当月工时!$A:$AC,15,FALSE),0)+IFERROR(VLOOKUP(K10,源_3考勤报表_考勤表!$F:$BG,38,FALSE),0)+IFERROR(VLOOKUP(K10,源_8补工时表_补当月工时!$A:$AC,17,FALSE),0)+IFERROR(VLOOKUP(K10,源_3考勤报表_考勤表!$F:$BG,40,FALSE),0)+IFERROR(VLOOKUP(K10,源_8补工时表_补当月工时!$A:$AC,20,FALSE),0)+IFERROR(VLOOKUP(K10,源_8补工时表_补当月工时!$A:$AC,22,FALSE),0)+IFERROR(VLOOKUP(K10,源_3考勤报表_考勤表!$F:$BG,41,FALSE),0)+IFERROR(VLOOKUP(K10,源_8补工时表_补当月工时!$A:$AC,18,FALSE),0)+IFERROR(VLOOKUP(K10,源_3考勤报表_考勤表!$F:$BG,42,FALSE),0)+IFERROR(VLOOKUP(K10,源_8补工时表_补当月工时!$A:$AC,19,FALSE),0)+IFERROR(VLOOKUP(K10,源_3考勤报表_考勤表!$F:$BG,44,FALSE),0)+IFERROR(VLOOKUP(K10,源_8补工时表_补当月工时!$A:$AC,16,FALSE),0)+IFERROR(VLOOKUP(K10,源_3考勤报表_考勤表!$F:$BG,45,FALSE),0)-参数!$B$4,0)),R10/参数!$B$4*Q10) -> 5051.9565 | U10: 0 | V10: 0 | W10: =X10+Y10+Z10+AA10 -> 0 | X10: =IFERROR(VLOOKUP(K10,源_4奖金汇总表_拆分手工算!$A:$N,8,FALSE),0) -> 0 | Y10: =IFERROR(VLOOKUP(K10,源_5薪资备忘录_工资调整项!$A:$AC,14,FALSE),0) -> 0 | Z10: =IFERROR(VLOOKUP(K10,源_5薪资备忘录_工资调整项!$A:$AC,16,FALSE),0) -> 0 | AA10: =IFERROR(VLOOKUP(K10,源_5薪资备忘录_工资调整项!$A:$AC,15,FALSE),0) -> 0 | AB10: =AC10+AD10+AF10 -> 0 | AC10: =IF(P10="门店全职",R10/174*MAX(IFERROR(VLOOKUP(K10,源_3考勤报表_考勤表!$F:$BG,34,FALSE),0)+IFERROR(VLOOKUP(K10,源_8补工时表_补当月工时!$A:$AC,14,FALSE),0)+IFERROR(VLOOKUP(K10,源_3考勤报表_考勤表!$F:$BG,37,FALSE),0)+IFERROR(VLOOKUP(K10,源_8补工时表_补当月工时!$A:$AC,15,FALSE),0)+IFERROR(VLOOKUP(K10,源_3考勤报表_考勤表!$F:$BG,38,FALSE),0)+IFERROR(VLOOKUP(K10,源_8补工时表_补当月工时!$A:$AC,17,FALSE),0)+IFERROR(VLOOKUP(K10,源_3考勤报表_考勤表!$F:$BG,40,FALSE),0)+IFERROR(VLOOKUP(K10,源_8补工时表_补当月工时!$A:$AC,20,FALSE),0)+IFERROR(VLOOKUP(K10,源_8补工时表_补当月工时!$A:$AC,22,FALSE),0)+IFERROR(VLOOKUP(K10,源_3考勤报表_考勤表!$F:$BG,41,FALSE),0)+IFERROR(VLOOKUP(K10,源_8补工时表_补当月工时!$A:$AC,18,FALSE),0)+IFERROR(VLOOKUP(K10,源_3考勤报表_考勤表!$F:$BG,42,FALSE),0)+IFERROR(VLOOKUP(K10,源_8补工时表_补当月工时!$A:$AC,19,FALSE),0)+IFERROR(VLOOKUP(K10,源_3考勤报表_考勤表!$F:$BG,44,FALSE),0)+IFERROR(VLOOKUP(K10,源_8补工时表_补当月工时!$A:$AC,16,FALSE),0)+IFERROR(VLOOKUP(K10,源_3考勤报表_考勤表!$F:$BG,45,FALSE),0)-参数!$B$4,0)*1.5,0) -> 0 | AD10: 0 | AE10: =IFERROR(VLOOKUP(K10,源_3考勤报表_考勤表!$F:$BG,46,FALSE),0)+IFERROR(VLOOKUP(K10,源_8补工时表_补当月工时!$A:$AC,25,FALSE),0) -> 0 | AF10: =R10/174*AE10*3 -> 0 | AG10: =IFERROR(VLOOKUP(K10,源_4奖金汇总表_拆分手工算!$A:$N,10,FALSE),0) -> 0 | AH10: =IFERROR(VLOOKUP(K10,源_4奖金汇总表_拆分手工算!$A:$N,5,FALSE),0) -> 0 | AI10: =IFERROR(VLOOKUP(K10,源_4奖金汇总表_拆分手工算!$A:$N,11,FALSE),0) -> 1500 | AJ10: =IFERROR(VLOOKUP(K10,源_4奖金汇总表_拆分手工算!$A:$N,4,FALSE),0) -> 1500 | AK10: =IFERROR(VLOOKUP(K10,源_4奖金汇总表_拆分手工算!$A:$N,3,FALSE),0) -> 0 | AL10: =IFERROR(VLOOKUP(K10,源_4奖金汇总表_拆分手工算!$A:$N,6,FALSE),0) -> 0 | AM10: =IFERROR(VLOOKUP(K10,源_5薪资备忘录_工资调整项!$A:$AC,18,FALSE),0)+IFERROR(VLOOKUP(K10,源_4奖金汇总表_拆分手工算!$A:$N,7,FALSE),0) -> 0 | AN10: =IFERROR(VLOOKUP(K10,源_5薪资备忘录_工资调整项!$A:$AC,17,FALSE),0) -> 0 | AO10: =IF(OR(IFERROR(VLOOKUP(K10,源_3考勤报表_考勤表!$F:$BG,39,FALSE),0)+IFERROR(VLOOKUP(K10,源_8补工时表_补当月工时!$A:$AC,24,FALSE),0)>0,IFERROR(VLOOKUP(K10,源_3考勤报表_考勤表!$F:$BG,43,FALSE),0)+IFERROR(VLOOKUP(K10,源_8补工时表_补当月工时!$A:$AC,26,FALSE),0)>0),IF(IFERROR(VLOOKUP(DH10,源_11产假政策_Sheet1!$C:$F,4,FALSE),"")="是",R10/参数!$B$4*(IFERROR(VLOOKUP(K10,源_3考勤报表_考勤表!$F:$BG,39,FALSE),0)+IFERROR(VLOOKUP(K10,源_8补工时表_补当月工时!$A:$AC,24,FALSE),0)+IFERROR(VLOOKUP(K10,源_3考勤报表_考勤表!$F:$BG,43,FALSE),0)+IFERROR(VLOOKUP(K10,源_8补工时表_补当月工时!$A:$AC,26,FALSE),0)),IFERROR(VLOOKUP(K10,源_5薪资备忘录_工资调整项!$A:$AC,19,FALSE),0)),0) -> 0 | AP10: 0 | AQ10: =IFERROR(VLOOKUP(K10,源_4奖金汇总表_拆分手工算!$A:$N,12,FALSE),0)+IFERROR(VLOOKUP(K10,源_9年终奖表_Sheet1!$A:$E,3,FALSE),0) -> 1200 | AR10: =IFERROR(VLOOKUP(K10,源_4奖金汇总表_拆分手工算!$A:$N,13,FALSE),0)+IFERROR(VLOOKUP(K10,源_9年终奖表_Sheet1!$A:$E,4,FALSE),0) -> 600 | AS10: =IFERROR(VLOOKUP(K10,源_4奖金汇总表_拆分手工算!$A:$N,14,FALSE),0)+IFERROR(VLOOKUP(K10,源_9年终奖表_Sheet1!$A:$E,5,FALSE),0) -> 222 | AT10: =IFERROR(VLOOKUP(K10,源_5薪资备忘录_工资调整项!$A:$AC,20,FALSE),0) -> 0 | AU10: =IFERROR(VLOOKUP(K10,源_5薪资备忘录_工资调整项!$A:$AC,21,FALSE),0)+IFERROR(VLOOKUP(K10,源_4奖金汇总表_拆分手工算!$A:$N,9,FALSE),0) -> 0 | AV10: =R10/参数!$B$4*(IFERROR(VLOOKUP(K10,源_3考勤报表_考勤表!$F:$BG,37,FALSE),0)+IFERROR(VLOOKUP(K10,源_8补工时表_补当月工时!$A:$AC,15,FALSE),0)) -> 356.6087 | AW10: =R10/174*MIN(IFERROR(VLOOKUP(K10,源_3考勤报表_考勤表!$F:$BG,35,FALSE),0),174)*IF(DATEDIF(N10,DATE(参数!$B$2,参数!$B$3+1,0),"Y")<2,0.6,IF(DATEDIF(N10,DATE(参数!$B$2,参数!$B$3+1,0),"Y")<4,0.7,IF(DATEDIF(N10,DATE(参数!$B$2,参数!$B$3+1,0),"Y")<6,0.8,IF(DATEDIF(N10,DATE(参数!$B$2,参数!$B$3+1,0),"Y")<8,0.9,1)))) -> 0 | AX10: =IF(Q10+IFERROR(VLOOKUP(K10,源_3考勤报表_考勤表!$F:$BG,37,FALSE),0)+IFERROR(VLOOKUP(K10,源_8补工时表_补当月工时!$A:$AC,15,FALSE),0)>=参数!$B$4,0,IF(Q10+IFERROR(VLOOKUP(K10,源_3考勤报表_考勤表!$F:$BG,37,FALSE),0)+IFERROR(VLOOKUP(K10,源_8补工时表_补当月工时!$A:$AC,15,FALSE),0)+IFERROR(VLOOKUP(K10,源_3考勤报表_考勤表!$F:$BG,38,FALSE),0)+IFERROR(VLOOKUP(K10,源_8补工时表_补当月工时!$A:$AC,17,FALSE),0)+IFERROR(VLOOKUP(K10,源_3考勤报表_考勤表!$F:$BG,40,FALSE),0)+IFERROR(VLOOKUP(K10,源_8补工时表_补当月工时!$A:$AC,20,FALSE),0)+IFERROR(VLOOKUP(K10,源_8补工时表_补当月工时!$A:$AC,22,FALSE),0)+IFERROR(VLOOKUP(K10,源_3考勤报表_考勤表!$F:$BG,41,FALSE),0)+IFERROR(VLOOKUP(K10,源_8补工时表_补当月工时!$A:$AC,18,FALSE),0)+IFERROR(VLOOKUP(K10,源_3考勤报表_考勤表!$F:$BG,42,FALSE),0)+IFERROR(VLOOKUP(K10,源_8补工时表_补当月工时!$A:$AC,19,FALSE),0)+IFERROR(VLOOKUP(K10,源_3考勤报表_考勤表!$F:$BG,44,FALSE),0)+IFERROR(VLOOKUP(K10,源_8补工时表_补当月工时!$A:$AC,16,FALSE),0)+IFERROR(VLOOKUP(K10,源_3考勤报表_考勤表!$F:$BG,45,FALSE),0)<=参数!$B$4,R10/参数!$B$4*(IFERROR(VLOOKUP(K10,源_3考勤报表_考勤表!$F:$BG,38,FALSE),0)+IFERROR(VLOOKUP(K10,源_8补工时表_补当月工时!$A:$AC,17,FALSE),0)+IFERROR(VLOOKUP(K10,源_3考勤报表_考勤表!$F:$BG,40,FALSE),0)+IFERROR(VLOOKUP(K10,源_8补工时表_补当月工时!$A:$AC,20,FALSE),0)+IFERROR(VLOOKUP(K10,源_8补工时表_补当月工时!$A:$AC,22,FALSE),0)+IFERROR(VLOOKUP(K10,源_3考勤报表_考勤表!$F:$BG,41,FALSE),0)+IFERROR(VLOOKUP(K10,源_8补工时表_补当月工时!$A:$AC,18,FALSE),0)+IFERROR(VLOOKUP(K10,源_3考勤报表_考勤表!$F:$BG,42,FALSE),0)+IFERROR(VLOOKUP(K10,源_8补工时表_补当月工时!$A:$AC,19,FALSE),0)+IFERROR(VLOOKUP(K10,源_3考勤报表_考勤表!$F:$BG,44,FALSE),0)+IFERROR(VLOOKUP(K10,源_8补工时表_补当月工时!$A:$AC,16,FALSE),0)+IFERROR(VLOOKUP(K10,源_3考勤报表_考勤表!$F:$BG,45,FALSE),0)),0)) -> 59.434783 | AY10: 0 | AZ10: 0 | BA10: 0 | BB10: 0 | BC10: =IFERROR(VLOOKUP(K10,源_5薪资备忘录_工资调整项!$A:$AC,25,FALSE),0) -> 0 | BD10: 0 | BE10: 0 | BF10: 0 | BG10: =IFERROR(VLOOKUP(K10,源_5薪资备忘录_工资调整项!$A:$AC,22,FALSE),0)+IFERROR(VLOOKUP(K10,源_5薪资备忘录_工资调整项!$A:$AC,23,FALSE),0)+IFERROR(VLOOKUP(K10,源_5薪资备忘录_工资调整项!$A:$AC,24,FALSE),0) -> 0 | BH10: =IFERROR(VLOOKUP(DF10,源_6社保表_Sheet1!$C:$CD,80,FALSE),0)+4.5 -> 6.5 | BI10: =T10+W10+AB10+AG10+AH10+AI10+AJ10+AK10+AL10+AM10+AN10+AO10+AP10+AQ10+AR10+AS10+AT10+AU10+AV10+AW10+AX10+BC10 -> 10490 | BJ10: =IFERROR(VLOOKUP(DF10,源_6社保表_Sheet1!$C:$BZ,26,FALSE),0) -> 482.3 | BK10: =IFERROR(VLOOKUP(DF10,源_6社保表_Sheet1!$C:$BZ,27,FALSE),0) -> 68.9 | BL10: =IFERROR(VLOOKUP(DF10,源_6社保表_Sheet1!$C:$BZ,28,FALSE),0) -> 34.45 | BM10: =IFERROR(VLOOKUP(DF10,源_6社保表_Sheet1!$C:$BZ,30,FALSE),0) -> 413.4 | BN10: =IFERROR(VLOOKUP(DF10,源_6社保表_Sheet1!$C:$BZ,29,FALSE),0) -> 0 | BO10: =IFERROR(VLOOKUP(DF10,源_6社保表_Sheet1!$C:$BZ,40,FALSE),0) -> 0 | BP10: =IFERROR(VLOOKUP(DF10,源_6社保表_Sheet1!$C:$BZ,41,FALSE),0) -> 0 | BQ10: =IFERROR(VLOOKUP(DF10,源_6社保表_Sheet1!$C:$BZ,42,FALSE),0) -> 0 | BR10: =IFERROR(VLOOKUP(DF10,源_6社保表_Sheet1!$C:$BZ,44,FALSE),0) -> 0 | BS10: =IFERROR(VLOOKUP(DF10,源_6社保表_Sheet1!$C:$BZ,43,FALSE),0) -> 0 | BT10: =BJ10+BK10+BL10+BM10+BN10+BO10+BP10+BQ10+BR10+BS10 -> 999.05 | BU10: 0 | BV10: 0 | BW10: 0 | BX10: =BU10+BV10+BW10 -> 0 | BY10: 0 | BZ10: =IFERROR(VLOOKUP(DF10,源_6社保表_Sheet1!$C:$BZ,18,FALSE),0) -> 1033.5 | CA10: =IFERROR(VLOOKUP(DF10,源_6社保表_Sheet1!$C:$BZ,19,FALSE),0) -> 551.2 | CB10: =IFERROR(VLOOKUP(DF10,源_6社保表_Sheet1!$C:$BZ,24,FALSE),0) -> 413.4 | CC10: =IFERROR(VLOOKUP(DF10,源_6社保表_Sheet1!$C:$BZ,20,FALSE),0) -> 34.45 | CD10: =IFERROR(VLOOKUP(DF10,源_6社保表_Sheet1!$C:$BZ,21,FALSE),0) -> 22.048 | CE10: =IFERROR(VLOOKUP(DF10,源_6社保表_Sheet1!$C:$BZ,22,FALSE),0) -> 0 | CF10: =IFERROR(VLOOKUP(DF10,源_6社保表_Sheet1!$C:$BZ,23,FALSE),0) -> 0 | CG10: =IFERROR(VLOOKUP(DF10,源_6社保表_Sheet1!$C:$BZ,32,FALSE),0) -> 0 | CH10: =IFERROR(VLOOKUP(DF10,源_6社保表_Sheet1!$C:$BZ,33,FALSE),0) -> 0 | CI10: =IFERROR(VLOOKUP(DF10,源_6社保表_Sheet1!$C:$BZ,34,FALSE),0) -> 0 | CJ10: =IFERROR(VLOOKUP(DF10,源_6社保表_Sheet1!$C:$BZ,38,FALSE),0) -> 0 | CK10: =IFERROR(VLOOKUP(DF10,源_6社保表_Sheet1!$C:$BZ,35,FALSE),0) -> 0 | CL10: =IFERROR(VLOOKUP(DF10,源_6社保表_Sheet1!$C:$BZ,36,FALSE),0) -> 0 | CM10: =IFERROR(VLOOKUP(DF10,源_6社保表_Sheet1!$C:$BZ,37,FALSE),0) -> 0 | CN10: =BZ10+CA10+CB10+CC10+CD10+CE10+CF10+CG10+CH10+CI10+CJ10+CK10+CL10+CM10 -> 2054.598 | CO10: =BI10+BG10+CN10+BE10+BH10 -> 12551.098 | CP10: =IF(IFERROR(VLOOKUP(K10,源_13残疾人信息_残疾人信息!$A:$M,1,FALSE),"")<>"",0,IF(OR(P10="门店全职",P10="门店管理组",P10="全职(非门店)"),(BI10-AT10)*IFERROR(VLOOKUP(D10,源_12计提残保金规则_Sheet1!$A:$E,4,FALSE),0)*IFERROR(VLOOKUP(D10,源_12计提残保金规则_Sheet1!$A:$E,5,FALSE),0),0)) -> 141.615 | CQ10: =IF(M10="行政",0,16.05) -> 16.05 | CR10: =IF(M10="门卫",0,20.67) -> 20.67 | CS10: =IF(DATEVALUE(N10)>DATE(参数!$B$2,9,30),0,IF(M10="行政",0,IF(O10="",R10/12,IF(MONTH(DATEVALUE(O10))=参数!$B$3,0,IF(DATEVALUE(O10)<DATE(参数!$B$2,参数!$B$3,1),0,R10/12))))) -> 455.66667 | CT10: =IF(P10="门店管理组",R10*0.12*0.85,0) -> 557.736 | CU10: =IFERROR(VLOOKUP(DF10,源_6社保表_Sheet1!$C:$I,2,FALSE),0) -> 6890 | CV10: =IFERROR(VLOOKUP(DF10,源_6社保表_Sheet1!$C:$I,7,FALSE),0) -> 6890 | CW10: =IFERROR(VLOOKUP(DF10,源_6社保表_Sheet1!$C:$I,3,FALSE),0) -> 6890 | CX10: =IFERROR(VLOOKUP(DF10,源_6社保表_Sheet1!$C:$I,4,FALSE),0) -> 6890 | CY10: =IFERROR(VLOOKUP(DF10,源_6社保表_Sheet1!$C:$I,5,FALSE),0) -> 6890 | CZ10: =IFERROR(VLOOKUP(DF10,源_6社保表_Sheet1!$C:$I,6,FALSE),0) -> 0 | DA10: =BI10+CN10-AG10-AH10-AI10-AJ10-AK10-AL10-AM10-AQ10-AR10-AS10-AT10 -> 7522.598 | DB10: =DA10+CP10+CQ10+CR10+CS10+CT10+BH10 -> 8720.8357 | DC10: =IFERROR(VLOOKUP(K10,源_7银行卡表_Sheet1!$A:$J,8,FALSE),"") -> 农业银行 | DD10: =IFERROR(VLOOKUP(K10,源_7银行卡表_Sheet1!$A:$J,9,FALSE),"") -> 6686205549557568463 | DE10: =IFERROR(VLOOKUP(K10,源_7银行卡表_Sheet1!$A:$J,10,FALSE),"") -> 中国农业银行太原黑土巷支行 | DF10: 150000197707137157 | DG10: 15696434652 | DH10: 杭州 | DI10: 0 | DJ10: 0 | DK10: 0 | DL10: 0 | DM10: 0 | DN10: 0 | DO10: 0 | DP10: 0 | DQ10: 0 | DR10: =IF(OR(IFERROR(VLOOKUP(K10,源_3考勤报表_考勤表!$F:$BG,39,FALSE),0)+IFERROR(VLOOKUP(K10,源_8补工时表_补当月工时!$A:$AC,24,FALSE),0)=0,IFERROR(VLOOKUP(K10,源_3考勤报表_考勤表!$F:$BG,43,FALSE),0)+IFERROR(VLOOKUP(K10,源_8补工时表_补当月工时!$A:$AC,26,FALSE),0)=0),IF(BI10+BG10-BT10<0,BI10+BG10-BT10,0),0) -> 0
A11: =参数!$B$2 -> 2025 | B11: =参数!$B$3 -> 12 | D11: 北京达美乐 | E11: 店铺营运 | F11: =IFERROR(VLOOKUP(K11,源_7银行卡表_Sheet1!$A:$J,6,FALSE),"") -> 华北营运 | G11: 北京 | H11: 天宫院店 | I11: 外服-北京门店全职 | J11: 1 | K11: 26123010 | L11: 傅晨宇 | M11: 训练员 | N11: 2022-01-20 | P11: 门店全职 | Q11: =IF(P11="门店全职",IFERROR(VLOOKUP(K11,源_3考勤报表_考勤表!$F:$BG,34,FALSE),0)+IFERROR(VLOOKUP(K11,源_8补工时表_补当月工时!$A:$AC,14,FALSE),0),IF(P11="门店管理组",IF(IFERROR(VLOOKUP(K11,源_3考勤报表_考勤表!$F:$BG,34,FALSE),0)+IFERROR(VLOOKUP(K11,源_8补工时表_补当月工时!$A:$AC,14,FALSE),0)+IFERROR(VLOOKUP(K11,源_3考勤报表_考勤表!$F:$BG,37,FALSE),0)+IFERROR(VLOOKUP(K11,源_8补工时表_补当月工时!$A:$AC,15,FALSE),0)+IFERROR(VLOOKUP(K11,源_3考勤报表_考勤表!$F:$BG,38,FALSE),0)+IFERROR(VLOOKUP(K11,源_8补工时表_补当月工时!$A:$AC,17,FALSE),0)+IFERROR(VLOOKUP(K11,源_3考勤报表_考勤表!$F:$BG,40,FALSE),0)+IFERROR(VLOOKUP(K11,源_8补工时表_补当月工时!$A:$AC,20,FALSE),0)+IFERROR(VLOOKUP(K11,源_8补工时表_补当月工时!$A:$AC,22,FALSE),0)+IFERROR(VLOOKUP(K11,源_3考勤报表_考勤表!$F:$BG,41,FALSE),0)+IFERROR(VLOOKUP(K11,源_8补工时表_补当月工时!$A:$AC,18,FALSE),0)+IFERROR(VLOOKUP(K11,源_3考勤报表_考勤表!$F:$BG,44,FALSE),0)+IFERROR(VLOOKUP(K11,源_8补工时表_补当月工时!$A:$AC,16,FALSE),0)+IFERROR(VLOOKUP(K11,源_3考勤报表_考勤表!$F:$BG,45,FALSE),0)>=参数!$B$4,参数!$B$4-IFERROR(VLOOKUP(K11,源_3考勤报表_考勤表!$F:$BG,37,FALSE),0)-IFERROR(VLOOKUP(K11,源_8补工时表_补当月工时!$A:$AC,15,FALSE),0)-IFERROR(VLOOKUP(K11,源_3考勤报表_考勤表!$F:$BG,38,FALSE),0)-IFERROR(VLOOKUP(K11,源_8补工时表_补当月工时!$A:$AC,17,FALSE),0)-IFERROR(VLOOKUP(K11,源_3考勤报表_考勤表!$F:$BG,40,FALSE),0)-IFERROR(VLOOKUP(K11,源_8补工时表_补当月工时!$A:$AC,20,FALSE),0)-IFERROR(VLOOKUP(K11,源_8补工时表_补当月工时!$A:$AC,22,FALSE),0)-IFERROR(VLOOKUP(K11,源_3考勤报表_考勤表!$F:$BG,41,FALSE),0)-IFERROR(VLOOKUP(K11,源_8补工时表_补当月工时!$A:$AC,18,FALSE),0)-IFERROR(VLOOKUP(K11,源_3考勤报表_考勤表!$F:$BG,44,FALSE),0)-IFERROR(VLOOKUP(K11,源_8补工时表_补当月工时!$A:$AC,16,FALSE),0)-IFERROR(VLOOKUP(K11,源_3考勤报表_考勤表!$F:$BG,45,FALSE),0),IFERROR(VLOOKUP(K11,源_3考勤报表_考勤表!$F:$BG,34,FALSE),0)+IFERROR(VLOOKUP(K11,源_8补工时表_补当月工时!$A:$AC,14,FALSE),0)),0)) -> 0 | R11: 3730 | S11: 0 | T11: =IF(P11="门店全职",R11/参数!$B$4*(Q11-MAX(IFERROR(VLOOKUP(K11,源_3考勤报表_考勤表!$F:$BG,34,FALSE),0)+IFERROR(VLOOKUP(K11,源_8补工时表_补当月工时!$A:$AC,14,FALSE),0)+IFERROR(VLOOKUP(K11,源_3考勤报表_考勤表!$F:$BG,37,FALSE),0)+IFERROR(VLOOKUP(K11,源_8补工时表_补当月工时!$A:$AC,15,FALSE),0)+IFERROR(VLOOKUP(K11,源_3考勤报表_考勤表!$F:$BG,38,FALSE),0)+IFERROR(VLOOKUP(K11,源_8补工时表_补当月工时!$A:$AC,17,FALSE),0)+IFERROR(VLOOKUP(K11,源_3考勤报表_考勤表!$F:$BG,40,FALSE),0)+IFERROR(VLOOKUP(K11,源_8补工时表_补当月工时!$A:$AC,20,FALSE),0)+IFERROR(VLOOKUP(K11,源_8补工时表_补当月工时!$A:$AC,22,FALSE),0)+IFERROR(VLOOKUP(K11,源_3考勤报表_考勤表!$F:$BG,41,FALSE),0)+IFERROR(VLOOKUP(K11,源_8补工时表_补当月工时!$A:$AC,18,FALSE),0)+IFERROR(VLOOKUP(K11,源_3考勤报表_考勤表!$F:$BG,42,FALSE),0)+IFERROR(VLOOKUP(K11,源_8补工时表_补当月工时!$A:$AC,19,FALSE),0)+IFERROR(VLOOKUP(K11,源_3考勤报表_考勤表!$F:$BG,44,FALSE),0)+IFERROR(VLOOKUP(K11,源_8补工时表_补当月工时!$A:$AC,16,FALSE),0)+IFERROR(VLOOKUP(K11,源_3考勤报表_考勤表!$F:$BG,45,FALSE),0)-参数!$B$4,0)),R11/参数!$B$4*Q11) -> 0 | U11: 0 | V11: 0 | W11: =X11+Y11+Z11+AA11 -> 0 | X11: =IFERROR(VLOOKUP(K11,源_4奖金汇总表_拆分手工算!$A:$N,8,FALSE),0) -> 0 | Y11: =IFERROR(VLOOKUP(K11,源_5薪资备忘录_工资调整项!$A:$AC,14,FALSE),0) -> 0 | Z11: =IFERROR(VLOOKUP(K11,源_5薪资备忘录_工资调整项!$A:$AC,16,FALSE),0) -> 0 | AA11: =IFERROR(VLOOKUP(K11,源_5薪资备忘录_工资调整项!$A:$AC,15,FALSE),0) -> 0 | AB11: =AC11+AD11+AF11 -> 0 | AC11: =IF(P11="门店全职",R11/174*MAX(IFERROR(VLOOKUP(K11,源_3考勤报表_考勤表!$F:$BG,34,FALSE),0)+IFERROR(VLOOKUP(K11,源_8补工时表_补当月工时!$A:$AC,14,FALSE),0)+IFERROR(VLOOKUP(K11,源_3考勤报表_考勤表!$F:$BG,37,FALSE),0)+IFERROR(VLOOKUP(K11,源_8补工时表_补当月工时!$A:$AC,15,FALSE),0)+IFERROR(VLOOKUP(K11,源_3考勤报表_考勤表!$F:$BG,38,FALSE),0)+IFERROR(VLOOKUP(K11,源_8补工时表_补当月工时!$A:$AC,17,FALSE),0)+IFERROR(VLOOKUP(K11,源_3考勤报表_考勤表!$F:$BG,40,FALSE),0)+IFERROR(VLOOKUP(K11,源_8补工时表_补当月工时!$A:$AC,20,FALSE),0)+IFERROR(VLOOKUP(K11,源_8补工时表_补当月工时!$A:$AC,22,FALSE),0)+IFERROR(VLOOKUP(K11,源_3考勤报表_考勤表!$F:$BG,41,FALSE),0)+IFERROR(VLOOKUP(K11,源_8补工时表_补当月工时!$A:$AC,18,FALSE),0)+IFERROR(VLOOKUP(K11,源_3考勤报表_考勤表!$F:$BG,42,FALSE),0)+IFERROR(VLOOKUP(K11,源_8补工时表_补当月工时!$A:$AC,19,FALSE),0)+IFERROR(VLOOKUP(K11,源_3考勤报表_考勤表!$F:$BG,44,FALSE),0)+IFERROR(VLOOKUP(K11,源_8补工时表_补当月工时!$A:$AC,16,FALSE),0)+IFERROR(VLOOKUP(K11,源_3考勤报表_考勤表!$F:$BG,45,FALSE),0)-参数!$B$4,0)*1.5,0) -> 0 | AD11: 0 | AE11: =IFERROR(VLOOKUP(K11,源_3考勤报表_考勤表!$F:$BG,46,FALSE),0)+IFERROR(VLOOKUP(K11,源_8补工时表_补当月工时!$A:$AC,25,FALSE),0) -> 0 | AF11: =R11/174*AE11*3 -> 0 | AG11: =IFERROR(VLOOKUP(K11,源_4奖金汇总表_拆分手工算!$A:$N,10,FALSE),0) -> 9 | AH11: =IFERROR(VLOOKUP(K11,源_4奖金汇总表_拆分手工算!$A:$N,5,FALSE),0) -> 0 | AI11: =IFERROR(VLOOKUP(K11,源_4奖金汇总表_拆分手工算!$A:$N,11,FALSE),0) -> 0 | AJ11: =IFERROR(VLOOKUP(K11,源_4奖金汇总表_拆分手工算!$A:$N,4,FALSE),0) -> 0 | AK11: =IFERROR(VLOOKUP(K11,源_4奖金汇总表_拆分手工算!$A:$N,3,FALSE),0) -> 0 | AL11: =IFERROR(VLOOKUP(K11,源_4奖金汇总表_拆分手工算!$A:$N,6,FALSE),0) -> 0 | AM11: =IFERROR(VLOOKUP(K11,源_5薪资备忘录_工资调整项!$A:$AC,18,FALSE),0)+IFERROR(VLOOKUP(K11,源_4奖金汇总表_拆分手工算!$A:$N,7,FALSE),0) -> 0 | AN11: =IFERROR(VLOOKUP(K11,源_5薪资备忘录_工资调整项!$A:$AC,17,FALSE),0) -> 0 | AO11: =IF(OR(IFERROR(VLOOKUP(K11,源_3考勤报表_考勤表!$F:$BG,39,FALSE),0)+IFERROR(VLOOKUP(K11,源_8补工时表_补当月工时!$A:$AC,24,FALSE),0)>0,IFERROR(VLOOKUP(K11,源_3考勤报表_考勤表!$F:$BG,43,FALSE),0)+IFERROR(VLOOKUP(K11,源_8补工时表_补当月工时!$A:$AC,26,FALSE),0)>0),IF(IFERROR(VLOOKUP(DH11,源_11产假政策_Sheet1!$C:$F,4,FALSE),"")="是",R11/参数!$B$4*(IFERROR(VLOOKUP(K11,源_3考勤报表_考勤表!$F:$BG,39,FALSE),0)+IFERROR(VLOOKUP(K11,源_8补工时表_补当月工时!$A:$AC,24,FALSE),0)+IFERROR(VLOOKUP(K11,源_3考勤报表_考勤表!$F:$BG,43,FALSE),0)+IFERROR(VLOOKUP(K11,源_8补工时表_补当月工时!$A:$AC,26,FALSE),0)),IFERROR(VLOOKUP(K11,源_5薪资备忘录_工资调整项!$A:$AC,19,FALSE),0)),0) -> 0 | AP11: 0 | AQ11: =IFERROR(VLOOKUP(K11,源_4奖金汇总表_拆分手工算!$A:$N,12,FALSE),0)+IFERROR(VLOOKUP(K11,源_9年终奖表_Sheet1!$A:$E,3,FALSE),0) -> 0 | AR11: =IFERROR(VLOOKUP(K11,源_4奖金汇总表_拆分手工算!$A:$N,13,FALSE),0)+IFERROR(VLOOKUP(K11,源_9年终奖表_Sheet1!$A:$E,4,FALSE),0) -> 0 | AS11: =IFERROR(VLOOKUP(K11,源_4奖金汇总表_拆分手工算!$A:$N,14,FALSE),0)+IFERROR(VLOOKUP(K11,源_9年终奖表_Sheet1!$A:$E,5,FALSE),0) -> 0 | AT11: =IFERROR(VLOOKUP(K11,源_5薪资备忘录_工资调整项!$A:$AC,20,FALSE),0) -> 0 | AU11: =IFERROR(VLOOKUP(K11,源_5薪资备忘录_工资调整项!$A:$AC,21,FALSE),0)+IFERROR(VLOOKUP(K11,源_4奖金汇总表_拆分手工算!$A:$N,9,FALSE),0) -> 0 | AV11: =R11/参数!$B$4*(IFERROR(VLOOKUP(K11,源_3考勤报表_考勤表!$F:$BG,37,FALSE),0)+IFERROR(VLOOKUP(K11,源_8补工时表_补当月工时!$A:$AC,15,FALSE),0)) -> 0 | AW11: =R11/174*MIN(IFERROR(VLOOKUP(K11,源_3考勤报表_考勤表!$F:$BG,35,FALSE),0),174)*IF(DATEDIF(N11,DATE(参数!$B$2,参数!$B$3+1,0),"Y")<2,0.6,IF(DATEDIF(N11,DATE(参数!$B$2,参数!$B$3+1,0),"Y")<4,0.7,IF(DATEDIF(N11,DATE(参数!$B$2,参数!$B$3+1,0),"Y")<6,0.8,IF(DATEDIF(N11,DATE(参数!$B$2,参数!$B$3+1,0),"Y")<8,0.9,1)))) -> 0 | AX11: =IF(Q11+IFERROR(VLOOKUP(K11,源_3考勤报表_考勤表!$F:$BG,37,FALSE),0)+IFERROR(VLOOKUP(K11,源_8补工时表_补当月工时!$A:$AC,15,FALSE),0)>=参数!$B$4,0,IF(Q11+IFERROR(VLOOKUP(K11,源_3考勤报表_考勤表!$F:$BG,37,FALSE),0)+IFERROR(VLOOKUP(K11,源_8补工时表_补当月工时!$A:$AC,15,FALSE),0)+IFERROR(VLOOKUP(K11,源_3考勤报表_考勤表!$F:$BG,38,FALSE),0)+IFERROR(VLOOKUP(K11,源_8补工时表_补当月工时!$A:$AC,17,FALSE),0)+IFERROR(VLOOKUP(K11,源_3考勤报表_考勤表!$F:$BG,40,FALSE),0)+IFERROR(VLOOKUP(K11,源_8补工时表_补当月工时!$A:$AC,20,FALSE),0)+IFERROR(VLOOKUP(K11,源_8补工时表_补当月工时!$A:$AC,22,FALSE),0)+IFERROR(VLOOKUP(K11,源_3考勤报表_考勤表!$F:$BG,41,FALSE),0)+IFERROR(VLOOKUP(K11,源_8补工时表_补当月工时!$A:$AC,18,FALSE),0)+IFERROR(VLOOKUP(K11,源_3考勤报表_考勤表!$F:$BG,42,FALSE),0)+IFERROR(VLOOKUP(K11,源_8补工时表_补当月工时!$A:$AC,19,FALSE),0)+IFERROR(VLOOKUP(K11,源_3考勤报表_考勤表!$F:$BG,44,FALSE),0)+IFERROR(VLOOKUP(K11,源_8补工时表_补当月工时!$A:$AC,16,FALSE),0)+IFERROR(VLOOKUP(K11,源_3考勤报表_考勤表!$F:$BG,45,FALSE),0)<=参数!$B$4,R11/参数!$B$4*(IFERROR(VLOOKUP(K11,源_3考勤报表_考勤表!$F:$BG,38,FALSE),0)+IFERROR(VLOOKUP(K11,源_8补工时表_补当月工时!$A:$AC,17,FALSE),0)+IFERROR(VLOOKUP(K11,源_3考勤报表_考勤表!$F:$BG,40,FALSE),0)+IFERROR(VLOOKUP(K11,源_8补工时表_补当月工时!$A:$AC,20,FALSE),0)+IFERROR(VLOOKUP(K11,源_8补工时表_补当月工时!$A:$AC,22,FALSE),0)+IFERROR(VLOOKUP(K11,源_3考勤报表_考勤表!$F:$BG,41,FALSE),0)+IFERROR(VLOOKUP(K11,源_8补工时表_补当月工时!$A:$AC,18,FALSE),0)+IFERROR(VLOOKUP(K11,源_3考勤报表_考勤表!$F:$BG,42,FALSE),0)+IFERROR(VLOOKUP(K11,源_8补工时表_补当月工时!$A:$AC,19,FALSE),0)+IFERROR(VLOOKUP(K11,源_3考勤报表_考勤表!$F:$BG,44,FALSE),0)+IFERROR(VLOOKUP(K11,源_8补工时表_补当月工时!$A:$AC,16,FALSE),0)+IFERROR(VLOOKUP(K11,源_3考勤报表_考勤表!$F:$BG,45,FALSE),0)),0)) -> 0 | AY11: 0 | AZ11: 0 | BA11: 0 | BB11: 0 | BC11: =IFERROR(VLOOKUP(K11,源_5薪资备忘录_工资调整项!$A:$AC,25,FALSE),0) -> 0 | BD11: 0 | BE11: =(T11+W11+AB11+AG11+AH11+AI11+AJ11+AK11+AL11+AM11+AN11+AO11+AP11+AU11+AV11+AW11+AX11+BC11-IFERROR(VLOOKUP(DF11,源_6社保表_Sheet1!$C:$BZ,76,FALSE),0))*0.02 -> -17.381 | BF11: 0 | BG11: =IFERROR(VLOOKUP(K11,源_5薪资备忘录_工资调整项!$A:$AC,22,FALSE),0)+IFERROR(VLOOKUP(K11,源_5薪资备忘录_工资调整项!$A:$AC,23,FALSE),0)+IFERROR(VLOOKUP(K11,源_5薪资备忘录_工资调整项!$A:$AC,24,FALSE),0) -> 0 | BH11: =IFERROR(VLOOKUP(DF11,源_6社保表_Sheet1!$C:$CD,80,FALSE),0)+4.5 -> 6.5 | BI11: =T11+W11+AB11+AG11+AH11+AI11+AJ11+AK11+AL11+AM11+AN11+AO11+AP11+AQ11+AR11+AS11+AT11+AU11+AV11+AW11+AX11+BC11 -> 9 | BJ11: =IFERROR(VLOOKUP(DF11,源_6社保表_Sheet1!$C:$BZ,26,FALSE),0) -> 501.34 | BK11: =IFERROR(VLOOKUP(DF11,源_6社保表_Sheet1!$C:$BZ,27,FALSE),0) -> 71.62 | BL11: =IFERROR(VLOOKUP(DF11,源_6社保表_Sheet1!$C:$BZ,28,FALSE),0) -> 35.81 | BM11: =IFERROR(VLOOKUP(DF11,源_6社保表_Sheet1!$C:$BZ,30,FALSE),0) -> 269.28 | BN11: =IFERROR(VLOOKUP(DF11,源_6社保表_Sheet1!$C:$BZ,29,FALSE),0) -> 0 | BO11: =IFERROR(VLOOKUP(DF11,源_6社保表_Sheet1!$C:$BZ,40,FALSE),0) -> 0 | BP11: =IFERROR(VLOOKUP(DF11,源_6社保表_Sheet1!$C:$BZ,41,FALSE),0) -> 0 | BQ11: =IFERROR(VLOOKUP(DF11,源_6社保表_Sheet1!$C:$BZ,42,FALSE),0) -> 0 | BR11: =IFERROR(VLOOKUP(DF11,源_6社保表_Sheet1!$C:$BZ,44,FALSE),0) -> 0 | BS11: =IFERROR(VLOOKUP(DF11,源_6社保表_Sheet1!$C:$BZ,43,FALSE),0) -> 0 | BT11: =BJ11+BK11+BL11+BM11+BN11+BO11+BP11+BQ11+BR11+BS11 -> 878.05 | BU11: 0 | BV11: 0 | BW11: 0 | BX11: =BU11+BV11+BW11 -> 0 | BY11: 0 | BZ11: =IFERROR(VLOOKUP(DF11,源_6社保表_Sheet1!$C:$BZ,18,FALSE),0) -> 1074.3 | CA11: =IFERROR(VLOOKUP(DF11,源_6社保表_Sheet1!$C:$BZ,19,FALSE),0) -> 572.96 | CB11: =IFERROR(VLOOKUP(DF11,源_6社保表_Sheet1!$C:$BZ,24,FALSE),0) -> 269.28 | CC11: =IFERROR(VLOOKUP(DF11,源_6社保表_Sheet1!$C:$BZ,20,FALSE),0) -> 35.81 | CD11: =IFERROR(VLOOKUP(DF11,源_6社保表_Sheet1!$C:$BZ,21,FALSE),0) -> 22.9184 | CE11: =IFERROR(VLOOKUP(DF11,源_6社保表_Sheet1!$C:$BZ,22,FALSE),0) -> 0 | CF11: =IFERROR(VLOOKUP(DF11,源_6社保表_Sheet1!$C:$BZ,23,FALSE),0) -> 0 | CG11: =IFERROR(VLOOKUP(DF11,源_6社保表_Sheet1!$C:$BZ,32,FALSE),0) -> 0 | CH11: =IFERROR(VLOOKUP(DF11,源_6社保表_Sheet1!$C:$BZ,33,FALSE),0) -> 0 | CI11: =IFERROR(VLOOKUP(DF11,源_6社保表_Sheet1!$C:$BZ,34,FALSE),0) -> 0 | CJ11: =IFERROR(VLOOKUP(DF11,源_6社保表_Sheet1!$C:$BZ,38,FALSE),0) -> 0 | CK11: =IFERROR(VLOOKUP(DF11,源_6社保表_Sheet1!$C:$BZ,35,FALSE),0) -> 0 | CL11: =IFERROR(VLOOKUP(DF11,源_6社保表_Sheet1!$C:$BZ,36,FALSE),0) -> 0 | CM11: =IFERROR(VLOOKUP(DF11,源_6社保表_Sheet1!$C:$BZ,37,FALSE),0) -> 0 | CN11: =BZ11+CA11+CB11+CC11+CD11+CE11+CF11+CG11+CH11+CI11+CJ11+CK11+CL11+CM11 -> 1975.2684 | CO11: =BI11+BG11+CN11+BE11+BH11 -> 1973.3874 | CP11: =IF(IFERROR(VLOOKUP(K11,源_13残疾人信息_残疾人信息!$A:$M,1,FALSE),"")<>"",0,IF(OR(P11="门店全职",P11="门店管理组",P11="全职(非门店)"),(BI11-AT11)*IFERROR(VLOOKUP(D11,源_12计提残保金规则_Sheet1!$A:$E,4,FALSE),0)*IFERROR(VLOOKUP(D11,源_12计提残保金规则_Sheet1!$A:$E,5,FALSE),0),0)) -> 0 | CQ11: =IF(M11="行政",0,16.05) -> 16.05 | CR11: =IF(M11="门卫",0,20.67) -> 20.67 | CS11: =IF(DATEVALUE(N11)>DATE(参数!$B$2,9,30),0,IF(M11="行政",0,IF(O11="",R11/12,IF(MONTH(DATEVALUE(O11))=参数!$B$3,0,IF(DATEVALUE(O11)<DATE(参数!$B$2,参数!$B$3,1),0,R11/12))))) -> 310.83333 | CT11: =IF(P11="门店管理组",R11*0.12*0.85,0) -> 0 | CU11: =IFERROR(VLOOKUP(DF11,源_6社保表_Sheet1!$C:$I,2,FALSE),0) -> 7162 | CV11: =IFERROR(VLOOKUP(DF11,源_6社保表_Sheet1!$C:$I,7,FALSE),0) -> 4488 | CW11: =IFERROR(VLOOKUP(DF11,源_6社保表_Sheet1!$C:$I,3,FALSE),0) -> 7162 | CX11: =IFERROR(VLOOKUP(DF11,源_6社保表_Sheet1!$C:$I,4,FALSE),0) -> 7162 | CY11: =IFERROR(VLOOKUP(DF11,源_6社保表_Sheet1!$C:$I,5,FALSE),0) -> 7162 | CZ11: =IFERROR(VLOOKUP(DF11,源_6社保表_Sheet1!$C:$I,6,FALSE),0) -> 0 | DA11: =BI11+CN11-AG11-AH11-AI11-AJ11-AK11-AL11-AM11-AQ11-AR11-AS11-AT11 -> 1975.2684 | DB11: =DA11+CP11+CQ11+CR11+CS11+CT11+BH11 -> 2329.3217 | DC11: =IFERROR(VLOOKUP(K11,源_7银行卡表_Sheet1!$A:$J,8,FALSE),"") -> 农业银行 | DD11: =IFERROR(VLOOKUP(K11,源_7银行卡表_Sheet1!$A:$J,9,FALSE),"") -> 6688893450796909070 | DE11: =IFERROR(VLOOKUP(K11,源_7银行卡表_Sheet1!$A:$J,10,FALSE),"") -> 中国农业银行长治北郊分理处 | DF11: 120000196003107346 | DG11: 13802615927 | DH11: 北京 | DI11: 0 | DJ11: 0 | DK11: 0 | DL11: 0 | DM11: 0 | DN11: 0 | DO11: 0 | DP11: 0 | DQ11: 0 | DR11: =IF(OR(IFERROR(VLOOKUP(K11,源_3考勤报表_考勤表!$F:$BG,39,FALSE),0)+IFERROR(VLOOKUP(K11,源_8补工时表_补当月工时!$A:$AC,24,FALSE),0)=0,IFERROR(VLOOKUP(K11,源_3考勤报表_考勤表!$F:$BG,43,FALSE),0)+IFERROR(VLOOKUP(K11,源_8补工时表_补当月工时!$A:$AC,26,FALSE),0)=0),IF(BI11+BG11-BT11<0,BI11+BG11-BT11,0),0) -> -869.05
A12: =参数!$B$2 -> 2025 | B12: =参数!$B$3 -> 12 | D12: 上海达美乐 | E12: 店铺营运 | F12: =IFERROR(VLOOKUP(K12,源_7银行卡表_Sheet1!$A:$J,6,FALSE),"") -> 华东营运 | G12: 上海1 | H12: 南亭公路店 | I12: 外服-上海门店全职 | J12: 1 | K12: 26123011 | L12: 常寒安 | M12: 员工组长 | N12: 2023-12-01 | P12: 门店全职 | Q12: =IF(P12="门店全职",IFERROR(VLOOKUP(K12,源_3考勤报表_考勤表!$F:$BG,34,FALSE),0)+IFERROR(VLOOKUP(K12,源_8补工时表_补当月工时!$A:$AC,14,FALSE),0),IF(P12="门店管理组",IF(IFERROR(VLOOKUP(K12,源_3考勤报表_考勤表!$F:$BG,34,FALSE),0)+IFERROR(VLOOKUP(K12,源_8补工时表_补当月工时!$A:$AC,14,FALSE),0)+IFERROR(VLOOKUP(K12,源_3考勤报表_考勤表!$F:$BG,37,FALSE),0)+IFERROR(VLOOKUP(K12,源_8补工时表_补当月工时!$A:$AC,15,FALSE),0)+IFERROR(VLOOKUP(K12,源_3考勤报表_考勤表!$F:$BG,38,FALSE),0)+IFERROR(VLOOKUP(K12,源_8补工时表_补当月工时!$A:$AC,17,FALSE),0)+IFERROR(VLOOKUP(K12,源_3考勤报表_考勤表!$F:$BG,40,FALSE),0)+IFERROR(VLOOKUP(K12,源_8补工时表_补当月工时!$A:$AC,20,FALSE),0)+IFERROR(VLOOKUP(K12,源_8补工时表_补当月工时!$A:$AC,22,FALSE),0)+IFERROR(VLOOKUP(K12,源_3考勤报表_考勤表!$F:$BG,41,FALSE),0)+IFERROR(VLOOKUP(K12,源_8补工时表_补当月工时!$A:$AC,18,FALSE),0)+IFERROR(VLOOKUP(K12,源_3考勤报表_考勤表!$F:$BG,44,FALSE),0)+IFERROR(VLOOKUP(K12,源_8补工时表_补当月工时!$A:$AC,16,FALSE),0)+IFERROR(VLOOKUP(K12,源_3考勤报表_考勤表!$F:$BG,45,FALSE),0)>=参数!$B$4,参数!$B$4-IFERROR(VLOOKUP(K12,源_3考勤报表_考勤表!$F:$BG,37,FALSE),0)-IFERROR(VLOOKUP(K12,源_8补工时表_补当月工时!$A:$AC,15,FALSE),0)-IFERROR(VLOOKUP(K12,源_3考勤报表_考勤表!$F:$BG,38,FALSE),0)-IFERROR(VLOOKUP(K12,源_8补工时表_补当月工时!$A:$AC,17,FALSE),0)-IFERROR(VLOOKUP(K12,源_3考勤报表_考勤表!$F:$BG,40,FALSE),0)-IFERROR(VLOOKUP(K12,源_8补工时表_补当月工时!$A:$AC,20,FALSE),0)-IFERROR(VLOOKUP(K12,源_8补工时表_补当月工时!$A:$AC,22,FALSE),0)-IFERROR(VLOOKUP(K12,源_3考勤报表_考勤表!$F:$BG,41,FALSE),0)-IFERROR(VLOOKUP(K12,源_8补工时表_补当月工时!$A:$AC,18,FALSE),0)-IFERROR(VLOOKUP(K12,源_3考勤报表_考勤表!$F:$BG,44,FALSE),0)-IFERROR(VLOOKUP(K12,源_8补工时表_补当月工时!$A:$AC,16,FALSE),0)-IFERROR(VLOOKUP(K12,源_3考勤报表_考勤表!$F:$BG,45,FALSE),0),IFERROR(VLOOKUP(K12,源_3考勤报表_考勤表!$F:$BG,34,FALSE),0)+IFERROR(VLOOKUP(K12,源_8补工时表_补当月工时!$A:$AC,14,FALSE),0)),0)) -> 0 | R12: 4190 | S12: 21 | T12: =IF(P12="门店全职",R12/参数!$B$4*(Q12-MAX(IFERROR(VLOOKUP(K12,源_3考勤报表_考勤表!$F:$BG,34,FALSE),0)+IFERROR(VLOOKUP(K12,源_8补工时表_补当月工时!$A:$AC,14,FALSE),0)+IFERROR(VLOOKUP(K12,源_3考勤报表_考勤表!$F:$BG,37,FALSE),0)+IFERROR(VLOOKUP(K12,源_8补工时表_补当月工时!$A:$AC,15,FALSE),0)+IFERROR(VLOOKUP(K12,源_3考勤报表_考勤表!$F:$BG,38,FALSE),0)+IFERROR(VLOOKUP(K12,源_8补工时表_补当月工时!$A:$AC,17,FALSE),0)+IFERROR(VLOOKUP(K12,源_3考勤报表_考勤表!$F:$BG,40,FALSE),0)+IFERROR(VLOOKUP(K12,源_8补工时表_补当月工时!$A:$AC,20,FALSE),0)+IFERROR(VLOOKUP(K12,源_8补工时表_补当月工时!$A:$AC,22,FALSE),0)+IFERROR(VLOOKUP(K12,源_3考勤报表_考勤表!$F:$BG,41,FALSE),0)+IFERROR(VLOOKUP(K12,源_8补工时表_补当月工时!$A:$AC,18,FALSE),0)+IFERROR(VLOOKUP(K12,源_3考勤报表_考勤表!$F:$BG,42,FALSE),0)+IFERROR(VLOOKUP(K12,源_8补工时表_补当月工时!$A:$AC,19,FALSE),0)+IFERROR(VLOOKUP(K12,源_3考勤报表_考勤表!$F:$BG,44,FALSE),0)+IFERROR(VLOOKUP(K12,源_8补工时表_补当月工时!$A:$AC,16,FALSE),0)+IFERROR(VLOOKUP(K12,源_3考勤报表_考勤表!$F:$BG,45,FALSE),0)-参数!$B$4,0)),R12/参数!$B$4*Q12) -> 0 | U12: 0 | V12: 0 | W12: =X12+Y12+Z12+AA12 -> 0 | X12: =IFERROR(VLOOKUP(K12,源_4奖金汇总表_拆分手工算!$A:$N,8,FALSE),0) -> 0 | Y12: =IFERROR(VLOOKUP(K12,源_5薪资备忘录_工资调整项!$A:$AC,14,FALSE),0) -> 0 | Z12: =IFERROR(VLOOKUP(K12,源_5薪资备忘录_工资调整项!$A:$AC,16,FALSE),0) -> 0 | AA12: =IFERROR(VLOOKUP(K12,源_5薪资备忘录_工资调整项!$A:$AC,15,FALSE),0) -> 0 | AB12: =AC12+AD12+AF12 -> 0 | AC12: =IF(P12="门店全职",R12/174*MAX(IFERROR(VLOOKUP(K12,源_3考勤报表_考勤表!$F:$BG,34,FALSE),0)+IFERROR(VLOOKUP(K12,源_8补工时表_补当月工时!$A:$AC,14,FALSE),0)+IFERROR(VLOOKUP(K12,源_3考勤报表_考勤表!$F:$BG,37,FALSE),0)+IFERROR(VLOOKUP(K12,源_8补工时表_补当月工时!$A:$AC,15,FALSE),0)+IFERROR(VLOOKUP(K12,源_3考勤报表_考勤表!$F:$BG,38,FALSE),0)+IFERROR(VLOOKUP(K12,源_8补工时表_补当月工时!$A:$AC,17,FALSE),0)+IFERROR(VLOOKUP(K12,源_3考勤报表_考勤表!$F:$BG,40,FALSE),0)+IFERROR(VLOOKUP(K12,源_8补工时表_补当月工时!$A:$AC,20,FALSE),0)+IFERROR(VLOOKUP(K12,源_8补工时表_补当月工时!$A:$AC,22,FALSE),0)+IFERROR(VLOOKUP(K12,源_3考勤报表_考勤表!$F:$BG,41,FALSE),0)+IFERROR(VLOOKUP(K12,源_8补工时表_补当月工时!$A:$AC,18,FALSE),0)+IFERROR(VLOOKUP(K12,源_3考勤报表_考勤表!$F:$BG,42,FALSE),0)+IFERROR(VLOOKUP(K12,源_8补工时表_补当月工时!$A:$AC,19,FALSE),0)+IFERROR(VLOOKUP(K12,源_3考勤报表_考勤表!$F:$BG,44,FALSE),0)+IFERROR(VLOOKUP(K12,源_8补工时表_补当月工时!$A:$AC,16,FALSE),0)+IFERROR(VLOOKUP(K12,源_3考勤报表_考勤表!$F:$BG,45,FALSE),0)-参数!$B$4,0)*1.5,0) -> 0 | AD12: 0 | AE12: =IFERROR(VLOOKUP(K12,源_3考勤报表_考勤表!$F:$BG,46,FALSE),0)+IFERROR(VLOOKUP(K12,源_8补工时表_补当月工时!$A:$AC,25,FALSE),0) -> 0 | AF12: =R12/174*AE12*3 -> 0 | AG12: =IFERROR(VLOOKUP(K12,源_4奖金汇总表_拆分手工算!$A:$N,10,FALSE),0) -> 36 | AH12: =IFERROR(VLOOKUP(K12,源_4奖金汇总表_拆分手工算!$A:$N,5,FALSE),0) -> 0 | AI12: =IFERROR(VLOOKUP(K12,源_4奖金汇总表_拆分手工算!$A:$N,11,FALSE),0) -> 0 | AJ12: =IFERROR(VLOOKUP(K12,源_4奖金汇总表_拆分手工算!$A:$N,4,FALSE),0) -> 0 | AK12: =IFERROR(VLOOKUP(K12,源_4奖金汇总表_拆分手工算!$A:$N,3,FALSE),0) -> 0 | AL12: =IFERROR(VLOOKUP(K12,源_4奖金汇总表_拆分手工算!$A:$N,6,FALSE),0) -> 0 | AM12: =IFERROR(VLOOKUP(K12,源_5薪资备忘录_工资调整项!$A:$AC,18,FALSE),0)+IFERROR(VLOOKUP(K12,源_4奖金汇总表_拆分手工算!$A:$N,7,FALSE),0) -> 0 | AN12: =IFERROR(VLOOKUP(K12,源_5薪资备忘录_工资调整项!$A:$AC,17,FALSE),0) -> 0 | AO12: =IF(OR(IFERROR(VLOOKUP(K12,源_3考勤报表_考勤表!$F:$BG,39,FALSE),0)+IFERROR(VLOOKUP(K12,源_8补工时表_补当月工时!$A:$AC,24,FALSE),0)>0,IFERROR(VLOOKUP(K12,源_3考勤报表_考勤表!$F:$BG,43,FALSE),0)+IFERROR(VLOOKUP(K12,源_8补工时表_补当月工时!$A:$AC,26,FALSE),0)>0),IF(IFERROR(VLOOKUP(DH12,源_11产假政策_Sheet1!$C:$F,4,FALSE),"")="是",R12/参数!$B$4*(IFERROR(VLOOKUP(K12,源_3考勤报表_考勤表!$F:$BG,39,FALSE),0)+IFERROR(VLOOKUP(K12,源_8补工时表_补当月工时!$A:$AC,24,FALSE),0)+IFERROR(VLOOKUP(K12,源_3考勤报表_考勤表!$F:$BG,43,FALSE),0)+IFERROR(VLOOKUP(K12,源_8补工时表_补当月工时!$A:$AC,26,FALSE),0)),IFERROR(VLOOKUP(K12,源_5薪资备忘录_工资调整项!$A:$AC,19,FALSE),0)),0) -> 0 | AP12: 0 | AQ12: =IFERROR(VLOOKUP(K12,源_4奖金汇总表_拆分手工算!$A:$N,12,FALSE),0)+IFERROR(VLOOKUP(K12,源_9年终奖表_Sheet1!$A:$E,3,FALSE),0) -> 0 | AR12: =IFERROR(VLOOKUP(K12,源_4奖金汇总表_拆分手工算!$A:$N,13,FALSE),0)+IFERROR(VLOOKUP(K12,源_9年终奖表_Sheet1!$A:$E,4,FALSE),0) -> 0 | AS12: =IFERROR(VLOOKUP(K12,源_4奖金汇总表_拆分手工算!$A:$N,14,FALSE),0)+IFERROR(VLOOKUP(K12,源_9年终奖表_Sheet1!$A:$E,5,FALSE),0) -> 0 | AT12: =IFERROR(VLOOKUP(K12,源_5薪资备忘录_工资调整项!$A:$AC,20,FALSE),0) -> 0 | AU12: =IFERROR(VLOOKUP(K12,源_5薪资备忘录_工资调整项!$A:$AC,21,FALSE),0)+IFERROR(VLOOKUP(K12,源_4奖金汇总表_拆分手工算!$A:$N,9,FALSE),0) -> 0 | AV12: =R12/参数!$B$4*(IFERROR(VLOOKUP(K12,源_3考勤报表_考勤表!$F:$BG,37,FALSE),0)+IFERROR(VLOOKUP(K12,源_8补工时表_补当月工时!$A:$AC,15,FALSE),0)) -> 0 | AW12: =R12/174*MIN(IFERROR(VLOOKUP(K12,源_3考勤报表_考勤表!$F:$BG,35,FALSE),0),174)*IF(DATEDIF(N12,DATE(参数!$B$2,参数!$B$3+1,0),"Y")<2,0.6,IF(DATEDIF(N12,DATE(参数!$B$2,参数!$B$3+1,0),"Y")<4,0.7,IF(DATEDIF(N12,DATE(参数!$B$2,参数!$B$3+1,0),"Y")<6,0.8,IF(DATEDIF(N12,DATE(参数!$B$2,参数!$B$3+1,0),"Y")<8,0.9,1)))) -> 0 | AX12: =IF(Q12+IFERROR(VLOOKUP(K12,源_3考勤报表_考勤表!$F:$BG,37,FALSE),0)+IFERROR(VLOOKUP(K12,源_8补工时表_补当月工时!$A:$AC,15,FALSE),0)>=参数!$B$4,0,IF(Q12+IFERROR(VLOOKUP(K12,源_3考勤报表_考勤表!$F:$BG,37,FALSE),0)+IFERROR(VLOOKUP(K12,源_8补工时表_补当月工时!$A:$AC,15,FALSE),0)+IFERROR(VLOOKUP(K12,源_3考勤报表_考勤表!$F:$BG,38,FALSE),0)+IFERROR(VLOOKUP(K12,源_8补工时表_补当月工时!$A:$AC,17,FALSE),0)+IFERROR(VLOOKUP(K12,源_3考勤报表_考勤表!$F:$BG,40,FALSE),0)+IFERROR(VLOOKUP(K12,源_8补工时表_补当月工时!$A:$AC,20,FALSE),0)+IFERROR(VLOOKUP(K12,源_8补工时表_补当月工时!$A:$AC,22,FALSE),0)+IFERROR(VLOOKUP(K12,源_3考勤报表_考勤表!$F:$BG,41,FALSE),0)+IFERROR(VLOOKUP(K12,源_8补工时表_补当月工时!$A:$AC,18,FALSE),0)+IFERROR(VLOOKUP(K12,源_3考勤报表_考勤表!$F:$BG,42,FALSE),0)+IFERROR(VLOOKUP(K12,源_8补工时表_补当月工时!$A:$AC,19,FALSE),0)+IFERROR(VLOOKUP(K12,源_3考勤报表_考勤表!$F:$BG,44,FALSE),0)+IFERROR(VLOOKUP(K12,源_8补工时表_补当月工时!$A:$AC,16,FALSE),0)+IFERROR(VLOOKUP(K12,源_3考勤报表_考勤表!$F:$BG,45,FALSE),0)<=参数!$B$4,R12/参数!$B$4*(IFERROR(VLOOKUP(K12,源_3考勤报表_考勤表!$F:$BG,38,FALSE),0)+IFERROR(VLOOKUP(K12,源_8补工时表_补当月工时!$A:$AC,17,FALSE),0)+IFERROR(VLOOKUP(K12,源_3考勤报表_考勤表!$F:$BG,40,FALSE),0)+IFERROR(VLOOKUP(K12,源_8补工时表_补当月工时!$A:$AC,20,FALSE),0)+IFERROR(VLOOKUP(K12,源_8补工时表_补当月工时!$A:$AC,22,FALSE),0)+IFERROR(VLOOKUP(K12,源_3考勤报表_考勤表!$F:$BG,41,FALSE),0)+IFERROR(VLOOKUP(K12,源_8补工时表_补当月工时!$A:$AC,18,FALSE),0)+IFERROR(VLOOKUP(K12,源_3考勤报表_考勤表!$F:$BG,42,FALSE),0)+IFERROR(VLOOKUP(K12,源_8补工时表_补当月工时!$A:$AC,19,FALSE),0)+IFERROR(VLOOKUP(K12,源_3考勤报表_考勤表!$F:$BG,44,FALSE),0)+IFERROR(VLOOKUP(K12,源_8补工时表_补当月工时!$A:$AC,16,FALSE),0)+IFERROR(VLOOKUP(K12,源_3考勤报表_考勤表!$F:$BG,45,FALSE),0)),0)) -> 0 | AY12: 0 | AZ12: 0 | BA12: 0 | BB12: 0 | BC12: =IFERROR(VLOOKUP(K12,源_5薪资备忘录_工资调整项!$A:$AC,25,FALSE),0) -> 0 | BD12: 0 | BE12: 0 | BF12: 0 | BG12: =IFERROR(VLOOKUP(K12,源_5薪资备忘录_工资调整项!$A:$AC,22,FALSE),0)+IFERROR(VLOOKUP(K12,源_5薪资备忘录_工资调整项!$A:$AC,23,FALSE),0)+IFERROR(VLOOKUP(K12,源_5薪资备忘录_工资调整项!$A:$AC,24,FALSE),0) -> 0 | BH12: =IFERROR(VLOOKUP(DF12,源_6社保表_Sheet1!$C:$CD,80,FALSE),0)+4.5 -> 6.5 | BI12: =T12+W12+AB12+AG12+AH12+AI12+AJ12+AK12+AL12+AM12+AN12+AO12+AP12+AQ12+AR12+AS12+AT12+AU12+AV12+AW12+AX12+BC12 -> 36 | BJ12: =IFERROR(VLOOKUP(DF12,源_6社保表_Sheet1!$C:$BZ,26,FALSE),0) -> 522.2 | BK12: =IFERROR(VLOOKUP(DF12,源_6社保表_Sheet1!$C:$BZ,27,FALSE),0) -> 74.6 | BL12: =IFERROR(VLOOKUP(DF12,源_6社保表_Sheet1!$C:$BZ,28,FALSE),0) -> 37.3 | BM12: =IFERROR(VLOOKUP(DF12,源_6社保表_Sheet1!$C:$BZ,30,FALSE),0) -> 281.1 | BN12: =IFERROR(VLOOKUP(DF12,源_6社保表_Sheet1!$C:$BZ,29,FALSE),0) -> 0 | BO12: =IFERROR(VLOOKUP(DF12,源_6社保表_Sheet1!$C:$BZ,40,FALSE),0) -> 0 | BP12: =IFERROR(VLOOKUP(DF12,源_6社保表_Sheet1!$C:$BZ,41,FALSE),0) -> 0 | BQ12: =IFERROR(VLOOKUP(DF12,源_6社保表_Sheet1!$C:$BZ,42,FALSE),0) -> 0 | BR12: =IFERROR(VLOOKUP(DF12,源_6社保表_Sheet1!$C:$BZ,44,FALSE),0) -> 0 | BS12: =IFERROR(VLOOKUP(DF12,源_6社保表_Sheet1!$C:$BZ,43,FALSE),0) -> 0 | BT12: =BJ12+BK12+BL12+BM12+BN12+BO12+BP12+BQ12+BR12+BS12 -> 915.2 | BU12: 0 | BV12: 0 | BW12: 0 | BX12: =BU12+BV12+BW12 -> 0 | BY12: 0 | BZ12: =IFERROR(VLOOKUP(DF12,源_6社保表_Sheet1!$C:$BZ,18,FALSE),0) -> 1119 | CA12: =IFERROR(VLOOKUP(DF12,源_6社保表_Sheet1!$C:$BZ,19,FALSE),0) -> 596.8 | CB12: =IFERROR(VLOOKUP(DF12,源_6社保表_Sheet1!$C:$BZ,24,FALSE),0) -> 281.1 | CC12: =IFERROR(VLOOKUP(DF12,源_6社保表_Sheet1!$C:$BZ,20,FALSE),0) -> 37.3 | CD12: =IFERROR(VLOOKUP(DF12,源_6社保表_Sheet1!$C:$BZ,21,FALSE),0) -> 23.872 | CE12: =IFERROR(VLOOKUP(DF12,源_6社保表_Sheet1!$C:$BZ,22,FALSE),0) -> 0 | CF12: =IFERROR(VLOOKUP(DF12,源_6社保表_Sheet1!$C:$BZ,23,FALSE),0) -> 0 | CG12: =IFERROR(VLOOKUP(DF12,源_6社保表_Sheet1!$C:$BZ,32,FALSE),0) -> 0 | CH12: =IFERROR(VLOOKUP(DF12,源_6社保表_Sheet1!$C:$BZ,33,FALSE),0) -> 0 | CI12: =IFERROR(VLOOKUP(DF12,源_6社保表_Sheet1!$C:$BZ,34,FALSE),0) -> 0 | CJ12: =IFERROR(VLOOKUP(DF12,源_6社保表_Sheet1!$C:$BZ,38,FALSE),0) -> 0 | CK12: =IFERROR(VLOOKUP(DF12,源_6社保表_Sheet1!$C:$BZ,35,FALSE),0) -> 0 | CL12: =IFERROR(VLOOKUP(DF12,源_6社保表_Sheet1!$C:$BZ,36,FALSE),0) -> 0 | CM12: =IFERROR(VLOOKUP(DF12,源_6社保表_Sheet1!$C:$BZ,37,FALSE),0) -> 0 | CN12: =BZ12+CA12+CB12+CC12+CD12+CE12+CF12+CG12+CH12+CI12+CJ12+CK12+CL12+CM12 -> 2058.072 | CO12: =BI12+BG12+CN12+BE12+BH12 -> 2100.572 | CP12: =IF(IFERROR(VLOOKUP(K12,源_13残疾人信息_残疾人信息!$A:$M,1,FALSE),"")<>"",0,IF(OR(P12="门店全职",P12="门店管理组",P12="全职(非门店)"),(BI12-AT12)*IFERROR(VLOOKUP(D12,源_12计提残保金规则_Sheet1!$A:$E,4,FALSE),0)*IFERROR(VLOOKUP(D12,源_12计提残保金规则_Sheet1!$A:$E,5,FALSE),0),0)) -> 0 | CQ12: =IF(M12="行政",0,16.05) -> 16.05 | CR12: =IF(M12="门卫",0,20.67) -> 20.67 | CS12: =IF(DATEVALUE(N12)>DATE(参数!$B$2,9,30),0,IF(M12="行政",0,IF(O12="",R12/12,IF(MONTH(DATEVALUE(O12))=参数!$B$3,0,IF(DATEVALUE(O12)<DATE(参数!$B$2,参数!$B$3,1),0,R12/12))))) -> 349.16667 | CT12: =IF(P12="门店管理组",R12*0.12*0.85,0) -> 0 | CU12: =IFERROR(VLOOKUP(DF12,源_6社保表_Sheet1!$C:$I,2,FALSE),0) -> 7460 | CV12: =IFERROR(VLOOKUP(DF12,源_6社保表_Sheet1!$C:$I,7,FALSE),0) -> 4685 | CW12: =IFERROR(VLOOKUP(DF12,源_6社保表_Sheet1!$C:$I,3,FALSE),0) -> 7460 | CX12: =IFERROR(VLOOKUP(DF12,源_6社保表_Sheet1!$C:$I,4,FALSE),0) -> 7460 | CY12: =IFERROR(VLOOKUP(DF12,源_6社保表_Sheet1!$C:$I,5,FALSE),0) -> 7460 | CZ12: =IFERROR(VLOOKUP(DF12,源_6社保表_Sheet1!$C:$I,6,FALSE),0) -> 0 | DA12: =BI12+CN12-AG12-AH12-AI12-AJ12-AK12-AL12-AM12-AQ12-AR12-AS12-AT12 -> 2058.072 | DB12: =DA12+CP12+CQ12+CR12+CS12+CT12+BH12 -> 2450.4587 | DC12: =IFERROR(VLOOKUP(K12,源_7银行卡表_Sheet1!$A:$J,8,FALSE),"") -> 农业银行 | DD12: =IFERROR(VLOOKUP(K12,源_7银行卡表_Sheet1!$A:$J,9,FALSE),"") -> 6686635752998250677 | DE12: =IFERROR(VLOOKUP(K12,源_7银行卡表_Sheet1!$A:$J,10,FALSE),"") -> 中国农业银行长治鹿家庄分理处 | DF12: 13000019630106267X | DG12: 15355302246 | DH12: 上海 | DI12: 0 | DJ12: 0 | DK12: 0 | DL12: 0 | DM12: 0 | DN12: 0 | DO12: 0 | DP12: 0 | DQ12: 0 | DR12: =IF(OR(IFERROR(VLOOKUP(K12,源_3考勤报表_考勤表!$F:$BG,39,FALSE),0)+IFERROR(VLOOKUP(K12,源_8补工时表_补当月工时!$A:$AC,24,FALSE),0)=0,IFERROR(VLOOKUP(K12,源_3考勤报表_考勤表!$F:$BG,43,FALSE),0)+IFERROR(VLOOKUP(K12,源_8补工时表_补当月工时!$A:$AC,26,FALSE),0)=0),IF(BI12+BG12-BT12<0,BI12+BG12-BT12,0),0) -> -879.2
A13: =参数!$B$2 -> 2025 | B13: =参数!$B$3 -> 12 | D13: 北京达美乐天津分公司 | E13: 店铺营运 | F13: =IFERROR(VLOOKUP(K13,源_7银行卡表_Sheet1!$A:$J,6,FALSE),"") -> 华北营运 | G13: 天津 | H13: 南京路店 | I13: 外服-天津门店全职 | J13: 1 | K13: 26123012 | L13: 龙睿阳 | M13: 餐厅副理 | N13: 2020-08-26 | P13: 门店管理组 | Q13: =IF(P13="门店全职",IFERROR(VLOOKUP(K13,源_3考勤报表_考勤表!$F:$BG,34,FALSE),0)+IFERROR(VLOOKUP(K13,源_8补工时表_补当月工时!$A:$AC,14,FALSE),0),IF(P13="门店管理组",IF(IFERROR(VLOOKUP(K13,源_3考勤报表_考勤表!$F:$BG,34,FALSE),0)+IFERROR(VLOOKUP(K13,源_8补工时表_补当月工时!$A:$AC,14,FALSE),0)+IFERROR(VLOOKUP(K13,源_3考勤报表_考勤表!$F:$BG,37,FALSE),0)+IFERROR(VLOOKUP(K13,源_8补工时表_补当月工时!$A:$AC,15,FALSE),0)+IFERROR(VLOOKUP(K13,源_3考勤报表_考勤表!$F:$BG,38,FALSE),0)+IFERROR(VLOOKUP(K13,源_8补工时表_补当月工时!$A:$AC,17,FALSE),0)+IFERROR(VLOOKUP(K13,源_3考勤报表_考勤表!$F:$BG,40,FALSE),0)+IFERROR(VLOOKUP(K13,源_8补工时表_补当月工时!$A:$AC,20,FALSE),0)+IFERROR(VLOOKUP(K13,源_8补工时表_补当月工时!$A:$AC,22,FALSE),0)+IFERROR(VLOOKUP(K13,源_3考勤报表_考勤表!$F:$BG,41,FALSE),0)+IFERROR(VLOOKUP(K13,源_8补工时表_补当月工时!$A:$AC,18,FALSE),0)+IFERROR(VLOOKUP(K13,源_3考勤报表_考勤表!$F:$BG,44,FALSE),0)+IFERROR(VLOOKUP(K13,源_8补工时表_补当月工时!$A:$AC,16,FALSE),0)+IFERROR(VLOOKUP(K13,源_3考勤报表_考勤表!$F:$BG,45,FALSE),0)>=参数!$B$4,参数!$B$4-IFERROR(VLOOKUP(K13,源_3考勤报表_考勤表!$F:$BG,37,FALSE),0)-IFERROR(VLOOKUP(K13,源_8补工时表_补当月工时!$A:$AC,15,FALSE),0)-IFERROR(VLOOKUP(K13,源_3考勤报表_考勤表!$F:$BG,38,FALSE),0)-IFERROR(VLOOKUP(K13,源_8补工时表_补当月工时!$A:$AC,17,FALSE),0)-IFERROR(VLOOKUP(K13,源_3考勤报表_考勤表!$F:$BG,40,FALSE),0)-IFERROR(VLOOKUP(K13,源_8补工时表_补当月工时!$A:$AC,20,FALSE),0)-IFERROR(VLOOKUP(K13,源_8补工时表_补当月工时!$A:$AC,22,FALSE),0)-IFERROR(VLOOKUP(K13,源_3考勤报表_考勤表!$F:$BG,41,FALSE),0)-IFERROR(VLOOKUP(K13,源_8补工时表_补当月工时!$A:$AC,18,FALSE),0)-IFERROR(VLOOKUP(K13,源_3考勤报表_考勤表!$F:$BG,44,FALSE),0)-IFERROR(VLOOKUP(K13,源_8补工时表_补当月工时!$A:$AC,16,FALSE),0)-IFERROR(VLOOKUP(K13,源_3考勤报表_考勤表!$F:$BG,45,FALSE),0),IFERROR(VLOOKUP(K13,源_3考勤报表_考勤表!$F:$BG,34,FALSE),0)+IFERROR(VLOOKUP(K13,源_8补工时表_补当月工时!$A:$AC,14,FALSE),0)),0)) -> 0 | R13: 5431 | S13: 0 | T13: =IF(P13="门店全职",R13/参数!$B$4*(Q13-MAX(IFERROR(VLOOKUP(K13,源_3考勤报表_考勤表!$F:$BG,34,FALSE),0)+IFERROR(VLOOKUP(K13,源_8补工时表_补当月工时!$A:$AC,14,FALSE),0)+IFERROR(VLOOKUP(K13,源_3考勤报表_考勤表!$F:$BG,37,FALSE),0)+IFERROR(VLOOKUP(K13,源_8补工时表_补当月工时!$A:$AC,15,FALSE),0)+IFERROR(VLOOKUP(K13,源_3考勤报表_考勤表!$F:$BG,38,FALSE),0)+IFERROR(VLOOKUP(K13,源_8补工时表_补当月工时!$A:$AC,17,FALSE),0)+IFERROR(VLOOKUP(K13,源_3考勤报表_考勤表!$F:$BG,40,FALSE),0)+IFERROR(VLOOKUP(K13,源_8补工时表_补当月工时!$A:$AC,20,FALSE),0)+IFERROR(VLOOKUP(K13,源_8补工时表_补当月工时!$A:$AC,22,FALSE),0)+IFERROR(VLOOKUP(K13,源_3考勤报表_考勤表!$F:$BG,41,FALSE),0)+IFERROR(VLOOKUP(K13,源_8补工时表_补当月工时!$A:$AC,18,FALSE),0)+IFERROR(VLOOKUP(K13,源_3考勤报表_考勤表!$F:$BG,42,FALSE),0)+IFERROR(VLOOKUP(K13,源_8补工时表_补当月工时!$A:$AC,19,FALSE),0)+IFERROR(VLOOKUP(K13,源_3考勤报表_考勤表!$F:$BG,44,FALSE),0)+IFERROR(VLOOKUP(K13,源_8补工时表_补当月工时!$A:$AC,16,FALSE),0)+IFERROR(VLOOKUP(K13,源_3考勤报表_考勤表!$F:$BG,45,FALSE),0)-参数!$B$4,0)),R13/参数!$B$4*Q13) -> 0 | U13: 0 | V13: 0 | W13: =X13+Y13+Z13+AA13 -> 102 | X13: =IFERROR(VLOOKUP(K13,源_4奖金汇总表_拆分手工算!$A:$N,8,FALSE),0) -> 102 | Y13: =IFERROR(VLOOKUP(K13,源_5薪资备忘录_工资调整项!$A:$AC,14,FALSE),0) -> 0 | Z13: =IFERROR(VLOOKUP(K13,源_5薪资备忘录_工资调整项!$A:$AC,16,FALSE),0) -> 0 | AA13: =IFERROR(VLOOKUP(K13,源_5薪资备忘录_工资调整项!$A:$AC,15,FALSE),0) -> 0 | AB13: =AC13+AD13+AF13 -> 0 | AC13: =IF(P13="门店全职",R13/174*MAX(IFERROR(VLOOKUP(K13,源_3考勤报表_考勤表!$F:$BG,34,FALSE),0)+IFERROR(VLOOKUP(K13,源_8补工时表_补当月工时!$A:$AC,14,FALSE),0)+IFERROR(VLOOKUP(K13,源_3考勤报表_考勤表!$F:$BG,37,FALSE),0)+IFERROR(VLOOKUP(K13,源_8补工时表_补当月工时!$A:$AC,15,FALSE),0)+IFERROR(VLOOKUP(K13,源_3考勤报表_考勤表!$F:$BG,38,FALSE),0)+IFERROR(VLOOKUP(K13,源_8补工时表_补当月工时!$A:$AC,17,FALSE),0)+IFERROR(VLOOKUP(K13,源_3考勤报表_考勤表!$F:$BG,40,FALSE),0)+IFERROR(VLOOKUP(K13,源_8补工时表_补当月工时!$A:$AC,20,FALSE),0)+IFERROR(VLOOKUP(K13,源_8补工时表_补当月工时!$A:$AC,22,FALSE),0)+IFERROR(VLOOKUP(K13,源_3考勤报表_考勤表!$F:$BG,41,FALSE),0)+IFERROR(VLOOKUP(K13,源_8补工时表_补当月工时!$A:$AC,18,FALSE),0)+IFERROR(VLOOKUP(K13,源_3考勤报表_考勤表!$F:$BG,42,FALSE),0)+IFERROR(VLOOKUP(K13,源_8补工时表_补当月工时!$A:$AC,19,FALSE),0)+IFERROR(VLOOKUP(K13,源_3考勤报表_考勤表!$F:$BG,44,FALSE),0)+IFERROR(VLOOKUP(K13,源_8补工时表_补当月工时!$A:$AC,16,FALSE),0)+IFERROR(VLOOKUP(K13,源_3考勤报表_考勤表!$F:$BG,45,FALSE),0)-参数!$B$4,0)*1.5,0) -> 0 | AD13: 0 | AE13: =IFERROR(VLOOKUP(K13,源_3考勤报表_考勤表!$F:$BG,46,FALSE),0)+IFERROR(VLOOKUP(K13,源_8补工时表_补当月工时!$A:$AC,25,FALSE),0) -> 0 | AF13: =R13/174*AE13*3 -> 0 | AG13: =IFERROR(VLOOKUP(K13,源_4奖金汇总表_拆分手工算!$A:$N,10,FALSE),0) -> 0 | AH13: =IFERROR(VLOOKUP(K13,源_4奖金汇总表_拆分手工算!$A:$N,5,FALSE),0) -> 0 | AI13: =IFERROR(VLOOKUP(K13,源_4奖金汇总表_拆分手工算!$A:$N,11,FALSE),0) -> 0 | AJ13: =IFERROR(VLOOKUP(K13,源_4奖金汇总表_拆分手工算!$A:$N,4,FALSE),0) -> 0 | AK13: =IFERROR(VLOOKUP(K13,源_4奖金汇总表_拆分手工算!$A:$N,3,FALSE),0) -> 0 | AL13: =IFERROR(VLOOKUP(K13,源_4奖金汇总表_拆分手工算!$A:$N,6,FALSE),0) -> 150 | AM13: =IFERROR(VLOOKUP(K13,源_5薪资备忘录_工资调整项!$A:$AC,18,FALSE),0)+IFERROR(VLOOKUP(K13,源_4奖金汇总表_拆分手工算!$A:$N,7,FALSE),0) -> 0 | AN13: =IFERROR(VLOOKUP(K13,源_5薪资备忘录_工资调整项!$A:$AC,17,FALSE),0) -> 0 | AO13: =IF(OR(IFERROR(VLOOKUP(K13,源_3考勤报表_考勤表!$F:$BG,39,FALSE),0)+IFERROR(VLOOKUP(K13,源_8补工时表_补当月工时!$A:$AC,24,FALSE),0)>0,IFERROR(VLOOKUP(K13,源_3考勤报表_考勤表!$F:$BG,43,FALSE),0)+IFERROR(VLOOKUP(K13,源_8补工时表_补当月工时!$A:$AC,26,FALSE),0)>0),IF(IFERROR(VLOOKUP(DH13,源_11产假政策_Sheet1!$C:$F,4,FALSE),"")="是",R13/参数!$B$4*(IFERROR(VLOOKUP(K13,源_3考勤报表_考勤表!$F:$BG,39,FALSE),0)+IFERROR(VLOOKUP(K13,源_8补工时表_补当月工时!$A:$AC,24,FALSE),0)+IFERROR(VLOOKUP(K13,源_3考勤报表_考勤表!$F:$BG,43,FALSE),0)+IFERROR(VLOOKUP(K13,源_8补工时表_补当月工时!$A:$AC,26,FALSE),0)),IFERROR(VLOOKUP(K13,源_5薪资备忘录_工资调整项!$A:$AC,19,FALSE),0)),0) -> 0 | AP13: 0 | AQ13: =IFERROR(VLOOKUP(K13,源_4奖金汇总表_拆分手工算!$A:$N,12,FALSE),0)+IFERROR(VLOOKUP(K13,源_9年终奖表_Sheet1!$A:$E,3,FALSE),0) -> 1000 | AR13: =IFERROR(VLOOKUP(K13,源_4奖金汇总表_拆分手工算!$A:$N,13,FALSE),0)+IFERROR(VLOOKUP(K13,源_9年终奖表_Sheet1!$A:$E,4,FALSE),0) -> 600 | AS13: =IFERROR(VLOOKUP(K13,源_4奖金汇总表_拆分手工算!$A:$N,14,FALSE),0)+IFERROR(VLOOKUP(K13,源_9年终奖表_Sheet1!$A:$E,5,FALSE),0) -> 111 | AT13: =IFERROR(VLOOKUP(K13,源_5薪资备忘录_工资调整项!$A:$AC,20,FALSE),0) -> 0 | AU13: =IFERROR(VLOOKUP(K13,源_5薪资备忘录_工资调整项!$A:$AC,21,FALSE),0)+IFERROR(VLOOKUP(K13,源_4奖金汇总表_拆分手工算!$A:$N,9,FALSE),0) -> 1733.79 | AV13: =R13/参数!$B$4*(IFERROR(VLOOKUP(K13,源_3考勤报表_考勤表!$F:$BG,37,FALSE),0)+IFERROR(VLOOKUP(K13,源_8补工时表_补当月工时!$A:$AC,15,FALSE),0)) -> 0 | AW13: =R13/174*MIN(IFERROR(VLOOKUP(K13,源_3考勤报表_考勤表!$F:$BG,35,FALSE),0),174)*IF(DATEDIF(N13,DATE(参数!$B$2,参数!$B$3+1,0),"Y")<2,0.6,IF(DATEDIF(N13,DATE(参数!$B$2,参数!$B$3+1,0),"Y")<4,0.7,IF(DATEDIF(N13,DATE(参数!$B$2,参数!$B$3+1,0),"Y")<6,0.8,IF(DATEDIF(N13,DATE(参数!$B$2,参数!$B$3+1,0),"Y")<8,0.9,1)))) -> 0 | AX13: =IF(Q13+IFERROR(VLOOKUP(K13,源_3考勤报表_考勤表!$F:$BG,37,FALSE),0)+IFERROR(VLOOKUP(K13,源_8补工时表_补当月工时!$A:$AC,15,FALSE),0)>=参数!$B$4,0,IF(Q13+IFERROR(VLOOKUP(K13,源_3考勤报表_考勤表!$F:$BG,37,FALSE),0)+IFERROR(VLOOKUP(K13,源_8补工时表_补当月工时!$A:$AC,15,FALSE),0)+IFERROR(VLOOKUP(K13,源_3考勤报表_考勤表!$F:$BG,38,FALSE),0)+IFERROR(VLOOKUP(K13,源_8补工时表_补当月工时!$A:$AC,17,FALSE),0)+IFERROR(VLOOKUP(K13,源_3考勤报表_考勤表!$F:$BG,40,FALSE),0)+IFERROR(VLOOKUP(K13,源_8补工时表_补当月工时!$A:$AC,20,FALSE),0)+IFERROR(VLOOKUP(K13,源_8补工时表_补当月工时!$A:$AC,22,FALSE),0)+IFERROR(VLOOKUP(K13,源_3考勤报表_考勤表!$F:$BG,41,FALSE),0)+IFERROR(VLOOKUP(K13,源_8补工时表_补当月工时!$A:$AC,18,FALSE),0)+IFERROR(VLOOKUP(K13,源_3考勤报表_考勤表!$F:$BG,42,FALSE),0)+IFERROR(VLOOKUP(K13,源_8补工时表_补当月工时!$A:$AC,19,FALSE),0)+IFERROR(VLOOKUP(K13,源_3考勤报表_考勤表!$F:$BG,44,FALSE),0)+IFERROR(VLOOKUP(K13,源_8补工时表_补当月工时!$A:$AC,16,FALSE),0)+IFERROR(VLOOKUP(K13,源_3考勤报表_考勤表!$F:$BG,45,FALSE),0)<=参数!$B$4,R13/参数!$B$4*(IFERROR(VLOOKUP(K13,源_3考勤报表_考勤表!$F:$BG,38,FALSE),0)+IFERROR(VLOOKUP(K13,源_8补工时表_补当月工时!$A:$AC,17,FALSE),0)+IFERROR(VLOOKUP(K13,源_3考勤报表_考勤表!$F:$BG,40,FALSE),0)+IFERROR(VLOOKUP(K13,源_8补工时表_补当月工时!$A:$AC,20,FALSE),0)+IFERROR(VLOOKUP(K13,源_8补工时表_补当月工时!$A:$AC,22,FALSE),0)+IFERROR(VLOOKUP(K13,源_3考勤报表_考勤表!$F:$BG,41,FALSE),0)+IFERROR(VLOOKUP(K13,源_8补工时表_补当月工时!$A:$AC,18,FALSE),0)+IFERROR(VLOOKUP(K13,源_3考勤报表_考勤表!$F:$BG,42,FALSE),0)+IFERROR(VLOOKUP(K13,源_8补工时表_补当月工时!$A:$AC,19,FALSE),0)+IFERROR(VLOOKUP(K13,源_3考勤报表_考勤表!$F:$BG,44,FALSE),0)+IFERROR(VLOOKUP(K13,源_8补工时表_补当月工时!$A:$AC,16,FALSE),0)+IFERROR(VLOOKUP(K13,源_3考勤报表_考勤表!$F:$BG,45,FALSE),0)),0)) -> 0 | AY13: 0 | AZ13: 0 | BA13: 0 | BB13: 0 | BC13: =IFERROR(VLOOKUP(K13,源_5薪资备忘录_工资调整项!$A:$AC,25,FALSE),0) -> 0 | BD13: 0 | BE13: 0 | BF13: 0 | BG13: =IFERROR(VLOOKUP(K13,源_5薪资备忘录_工资调整项!$A:$AC,22,FALSE),0)+IFERROR(VLOOKUP(K13,源_5薪资备忘录_工资调整项!$A:$AC,23,FALSE),0)+IFERROR(VLOOKUP(K13,源_5薪资备忘录_工资调整项!$A:$AC,24,FALSE),0) -> 0 | BH13: =IFERROR(VLOOKUP(DF13,源_6社保表_Sheet1!$C:$CD,80,FALSE),0)+4.5 -> 6.5 | BI13: =T13+W13+AB13+AG13+AH13+AI13+AJ13+AK13+AL13+AM13+AN13+AO13+AP13+AQ13+AR13+AS13+AT13+AU13+AV13+AW13+AX13+BC13 -> 3696.79 | BJ13: =IFERROR(VLOOKUP(DF13,源_6社保表_Sheet1!$C:$BZ,26,FALSE),0) -> 557.13 | BK13: =IFERROR(VLOOKUP(DF13,源_6社保表_Sheet1!$C:$BZ,27,FALSE),0) -> 79.59 | BL13: =IFERROR(VLOOKUP(DF13,源_6社保表_Sheet1!$C:$BZ,28,FALSE),0) -> 39.795 | BM13: =IFERROR(VLOOKUP(DF13,源_6社保表_Sheet1!$C:$BZ,30,FALSE),0) -> 477.54 | BN13: =IFERROR(VLOOKUP(DF13,源_6社保表_Sheet1!$C:$BZ,29,FALSE),0) -> 0 | BO13: =IFERROR(VLOOKUP(DF13,源_6社保表_Sheet1!$C:$BZ,40,FALSE),0) -> 0 | BP13: =IFERROR(VLOOKUP(DF13,源_6社保表_Sheet1!$C:$BZ,41,FALSE),0) -> 0 | BQ13: =IFERROR(VLOOKUP(DF13,源_6社保表_Sheet1!$C:$BZ,42,FALSE),0) -> 0 | BR13: =IFERROR(VLOOKUP(DF13,源_6社保表_Sheet1!$C:$BZ,44,FALSE),0) -> 0 | BS13: =IFERROR(VLOOKUP(DF13,源_6社保表_Sheet1!$C:$BZ,43,FALSE),0) -> 0 | BT13: =BJ13+BK13+BL13+BM13+BN13+BO13+BP13+BQ13+BR13+BS13 -> 1154.055 | BU13: 0 | BV13: 0 | BW13: 0 | BX13: =BU13+BV13+BW13 -> 0 | BY13: 0 | BZ13: =IFERROR(VLOOKUP(DF13,源_6社保表_Sheet1!$C:$BZ,18,FALSE),0) -> 1193.85 | CA13: =IFERROR(VLOOKUP(DF13,源_6社保表_Sheet1!$C:$BZ,19,FALSE),0) -> 636.72 | CB13: =IFERROR(VLOOKUP(DF13,源_6社保表_Sheet1!$C:$BZ,24,FALSE),0) -> 477.54 | CC13: =IFERROR(VLOOKUP(DF13,源_6社保表_Sheet1!$C:$BZ,20,FALSE),0) -> 39.795 | CD13: =IFERROR(VLOOKUP(DF13,源_6社保表_Sheet1!$C:$BZ,21,FALSE),0) -> 25.4688 | CE13: =IFERROR(VLOOKUP(DF13,源_6社保表_Sheet1!$C:$BZ,22,FALSE),0) -> 0 | CF13: =IFERROR(VLOOKUP(DF13,源_6社保表_Sheet1!$C:$BZ,23,FALSE),0) -> 0 | CG13: =IFERROR(VLOOKUP(DF13,源_6社保表_Sheet1!$C:$BZ,32,FALSE),0) -> 0 | CH13: =IFERROR(VLOOKUP(DF13,源_6社保表_Sheet1!$C:$BZ,33,FALSE),0) -> 0 | CI13: =IFERROR(VLOOKUP(DF13,源_6社保表_Sheet1!$C:$BZ,34,FALSE),0) -> 0 | CJ13: =IFERROR(VLOOKUP(DF13,源_6社保表_Sheet1!$C:$BZ,38,FALSE),0) -> 0 | CK13: =IFERROR(VLOOKUP(DF13,源_6社保表_Sheet1!$C:$BZ,35,FALSE),0) -> 0 | CL13: =IFERROR(VLOOKUP(DF13,源_6社保表_Sheet1!$C:$BZ,36,FALSE),0) -> 0 | CM13: =IFERROR(VLOOKUP(DF13,源_6社保表_Sheet1!$C:$BZ,37,FALSE),0) -> 0 | CN13: =BZ13+CA13+CB13+CC13+CD13+CE13+CF13+CG13+CH13+CI13+CJ13+CK13+CL13+CM13 -> 2373.3738 | CO13: =BI13+BG13+CN13+BE13+BH13 -> 6076.6638 | CP13: =IF(IFERROR(VLOOKUP(K13,源_13残疾人信息_残疾人信息!$A:$M,1,FALSE),"")<>"",0,IF(OR(P13="门店全职",P13="门店管理组",P13="全职(非门店)"),(BI13-AT13)*IFERROR(VLOOKUP(D13,源_12计提残保金规则_Sheet1!$A:$E,4,FALSE),0)*IFERROR(VLOOKUP(D13,源_12计提残保金规则_Sheet1!$A:$E,5,FALSE),0),0)) -> 49.906665 | CQ13: =IF(M13="行政",0,16.05) -> 16.05 | CR13: =IF(M13="门卫",0,20.67) -> 20.67 | CS13: =IF(DATEVALUE(N13)>DATE(参数!$B$2,9,30),0,IF(M13="行政",0,IF(O13="",R13/12,IF(MONTH(DATEVALUE(O13))=参数!$B$3,0,IF(DATEVALUE(O13)<DATE(参数!$B$2,参数!$B$3,1),0,R13/12))))) -> 452.58333 | CT13: =IF(P13="门店管理组",R13*0.12*0.85,0) -> 553.962 | CU13: =IFERROR(VLOOKUP(DF13,源_6社保表_Sheet1!$C:$I,2,FALSE),0) -> 7959 | CV13: =IFERROR(VLOOKUP(DF13,源_6社保表_Sheet1!$C:$I,7,FALSE),0) -> 7959 | CW13: =IFERROR(VLOOKUP(DF13,源_6社保表_Sheet1!$C:$I,3,FALSE),0) -> 7959 | CX13: =IFERROR(VLOOKUP(DF13,源_6社保表_Sheet1!$C:$I,4,FALSE),0) -> 7959 | CY13: =IFERROR(VLOOKUP(DF13,源_6社保表_Sheet1!$C:$I,5,FALSE),0) -> 7959 | CZ13: =IFERROR(VLOOKUP(DF13,源_6社保表_Sheet1!$C:$I,6,FALSE),0) -> 0 | DA13: =BI13+CN13-AG13-AH13-AI13-AJ13-AK13-AL13-AM13-AQ13-AR13-AS13-AT13 -> 4209.1638 | DB13: =DA13+CP13+CQ13+CR13+CS13+CT13+BH13 -> 5308.8358 | DC13: =IFERROR(VLOOKUP(K13,源_7银行卡表_Sheet1!$A:$J,8,FALSE),"") -> 农业银行 | DD13: =IFERROR(VLOOKUP(K13,源_7银行卡表_Sheet1!$A:$J,9,FALSE),"") -> 6688665832537793920 | DE13: =IFERROR(VLOOKUP(K13,源_7银行卡表_Sheet1!$A:$J,10,FALSE),"") -> 中国农业银行长治故县支行 | DF13: 120000198101098496 | DG13: 18682732412 | DH13: 天津 | DI13: 0 | DJ13: 0 | DK13: 0 | DL13: 0 | DM13: 0 | DN13: 0 | DO13: 0 | DP13: 0 | DQ13: 0 | DR13: =IF(OR(IFERROR(VLOOKUP(K13,源_3考勤报表_考勤表!$F:$BG,39,FALSE),0)+IFERROR(VLOOKUP(K13,源_8补工时表_补当月工时!$A:$AC,24,FALSE),0)=0,IFERROR(VLOOKUP(K13,源_3考勤报表_考勤表!$F:$BG,43,FALSE),0)+IFERROR(VLOOKUP(K13,源_8补工时表_补当月工时!$A:$AC,26,FALSE),0)=0),IF(BI13+BG13-BT13<0,BI13+BG13-BT13,0),0) -> 0
A14: =参数!$B$2 -> 2025 | B14: =参数!$B$3 -> 12 | D14: 北京达美乐 | E14: 店铺营运 | F14: =IFERROR(VLOOKUP(K14,源_7银行卡表_Sheet1!$A:$J,6,FALSE),"") -> 华北营运 | G14: 北京 | H14: 马泉营店 | I14: 外服-北京门店全职 | J14: 1 | K14: 26123013 | L14: 魏嘉阳 | M14: 餐厅经理 | N14: 2020-10-21 | P14: 门店管理组 | Q14: =IF(P14="门店全职",IFERROR(VLOOKUP(K14,源_3考勤报表_考勤表!$F:$BG,34,FALSE),0)+IFERROR(VLOOKUP(K14,源_8补工时表_补当月工时!$A:$AC,14,FALSE),0),IF(P14="门店管理组",IF(IFERROR(VLOOKUP(K14,源_3考勤报表_考勤表!$F:$BG,34,FALSE),0)+IFERROR(VLOOKUP(K14,源_8补工时表_补当月工时!$A:$AC,14,FALSE),0)+IFERROR(VLOOKUP(K14,源_3考勤报表_考勤表!$F:$BG,37,FALSE),0)+IFERROR(VLOOKUP(K14,源_8补工时表_补当月工时!$A:$AC,15,FALSE),0)+IFERROR(VLOOKUP(K14,源_3考勤报表_考勤表!$F:$BG,38,FALSE),0)+IFERROR(VLOOKUP(K14,源_8补工时表_补当月工时!$A:$AC,17,FALSE),0)+IFERROR(VLOOKUP(K14,源_3考勤报表_考勤表!$F:$BG,40,FALSE),0)+IFERROR(VLOOKUP(K14,源_8补工时表_补当月工时!$A:$AC,20,FALSE),0)+IFERROR(VLOOKUP(K14,源_8补工时表_补当月工时!$A:$AC,22,FALSE),0)+IFERROR(VLOOKUP(K14,源_3考勤报表_考勤表!$F:$BG,41,FALSE),0)+IFERROR(VLOOKUP(K14,源_8补工时表_补当月工时!$A:$AC,18,FALSE),0)+IFERROR(VLOOKUP(K14,源_3考勤报表_考勤表!$F:$BG,44,FALSE),0)+IFERROR(VLOOKUP(K14,源_8补工时表_补当月工时!$A:$AC,16,FALSE),0)+IFERROR(VLOOKUP(K14,源_3考勤报表_考勤表!$F:$BG,45,FALSE),0)>=参数!$B$4,参数!$B$4-IFERROR(VLOOKUP(K14,源_3考勤报表_考勤表!$F:$BG,37,FALSE),0)-IFERROR(VLOOKUP(K14,源_8补工时表_补当月工时!$A:$AC,15,FALSE),0)-IFERROR(VLOOKUP(K14,源_3考勤报表_考勤表!$F:$BG,38,FALSE),0)-IFERROR(VLOOKUP(K14,源_8补工时表_补当月工时!$A:$AC,17,FALSE),0)-IFERROR(VLOOKUP(K14,源_3考勤报表_考勤表!$F:$BG,40,FALSE),0)-IFERROR(VLOOKUP(K14,源_8补工时表_补当月工时!$A:$AC,20,FALSE),0)-IFERROR(VLOOKUP(K14,源_8补工时表_补当月工时!$A:$AC,22,FALSE),0)-IFERROR(VLOOKUP(K14,源_3考勤报表_考勤表!$F:$BG,41,FALSE),0)-IFERROR(VLOOKUP(K14,源_8补工时表_补当月工时!$A:$AC,18,FALSE),0)-IFERROR(VLOOKUP(K14,源_3考勤报表_考勤表!$F:$BG,44,FALSE),0)-IFERROR(VLOOKUP(K14,源_8补工时表_补当月工时!$A:$AC,16,FALSE),0)-IFERROR(VLOOKUP(K14,源_3考勤报表_考勤表!$F:$BG,45,FALSE),0),IFERROR(VLOOKUP(K14,源_3考勤报表_考勤表!$F:$BG,34,FALSE),0)+IFERROR(VLOOKUP(K14,源_8补工时表_补当月工时!$A:$AC,14,FALSE),0)),0)) -> 184 | R14: 7352 | S14: 0 | T14: =IF(P14="门店全职",R14/参数!$B$4*(Q14-MAX(IFERROR(VLOOKUP(K14,源_3考勤报表_考勤表!$F:$BG,34,FALSE),0)+IFERROR(VLOOKUP(K14,源_8补工时表_补当月工时!$A:$AC,14,FALSE),0)+IFERROR(VLOOKUP(K14,源_3考勤报表_考勤表!$F:$BG,37,FALSE),0)+IFERROR(VLOOKUP(K14,源_8补工时表_补当月工时!$A:$AC,15,FALSE),0)+IFERROR(VLOOKUP(K14,源_3考勤报表_考勤表!$F:$BG,38,FALSE),0)+IFERROR(VLOOKUP(K14,源_8补工时表_补当月工时!$A:$AC,17,FALSE),0)+IFERROR(VLOOKUP(K14,源_3考勤报表_考勤表!$F:$BG,40,FALSE),0)+IFERROR(VLOOKUP(K14,源_8补工时表_补当月工时!$A:$AC,20,FALSE),0)+IFERROR(VLOOKUP(K14,源_8补工时表_补当月工时!$A:$AC,22,FALSE),0)+IFERROR(VLOOKUP(K14,源_3考勤报表_考勤表!$F:$BG,41,FALSE),0)+IFERROR(VLOOKUP(K14,源_8补工时表_补当月工时!$A:$AC,18,FALSE),0)+IFERROR(VLOOKUP(K14,源_3考勤报表_考勤表!$F:$BG,42,FALSE),0)+IFERROR(VLOOKUP(K14,源_8补工时表_补当月工时!$A:$AC,19,FALSE),0)+IFERROR(VLOOKUP(K14,源_3考勤报表_考勤表!$F:$BG,44,FALSE),0)+IFERROR(VLOOKUP(K14,源_8补工时表_补当月工时!$A:$AC,16,FALSE),0)+IFERROR(VLOOKUP(K14,源_3考勤报表_考勤表!$F:$BG,45,FALSE),0)-参数!$B$4,0)),R14/参数!$B$4*Q14) -> 7352 | U14: 0 | V14: 0 | W14: =X14+Y14+Z14+AA14 -> 0 | X14: =IFERROR(VLOOKUP(K14,源_4奖金汇总表_拆分手工算!$A:$N,8,FALSE),0) -> 0 | Y14: =IFERROR(VLOOKUP(K14,源_5薪资备忘录_工资调整项!$A:$AC,14,FALSE),0) -> 0 | Z14: =IFERROR(VLOOKUP(K14,源_5薪资备忘录_工资调整项!$A:$AC,16,FALSE),0) -> 0 | AA14: =IFERROR(VLOOKUP(K14,源_5薪资备忘录_工资调整项!$A:$AC,15,FALSE),0) -> 0 | AB14: =AC14+AD14+AF14 -> 0 | AC14: =IF(P14="门店全职",R14/174*MAX(IFERROR(VLOOKUP(K14,源_3考勤报表_考勤表!$F:$BG,34,FALSE),0)+IFERROR(VLOOKUP(K14,源_8补工时表_补当月工时!$A:$AC,14,FALSE),0)+IFERROR(VLOOKUP(K14,源_3考勤报表_考勤表!$F:$BG,37,FALSE),0)+IFERROR(VLOOKUP(K14,源_8补工时表_补当月工时!$A:$AC,15,FALSE),0)+IFERROR(VLOOKUP(K14,源_3考勤报表_考勤表!$F:$BG,38,FALSE),0)+IFERROR(VLOOKUP(K14,源_8补工时表_补当月工时!$A:$AC,17,FALSE),0)+IFERROR(VLOOKUP(K14,源_3考勤报表_考勤表!$F:$BG,40,FALSE),0)+IFERROR(VLOOKUP(K14,源_8补工时表_补当月工时!$A:$AC,20,FALSE),0)+IFERROR(VLOOKUP(K14,源_8补工时表_补当月工时!$A:$AC,22,FALSE),0)+IFERROR(VLOOKUP(K14,源_3考勤报表_考勤表!$F:$BG,41,FALSE),0)+IFERROR(VLOOKUP(K14,源_8补工时表_补当月工时!$A:$AC,18,FALSE),0)+IFERROR(VLOOKUP(K14,源_3考勤报表_考勤表!$F:$BG,42,FALSE),0)+IFERROR(VLOOKUP(K14,源_8补工时表_补当月工时!$A:$AC,19,FALSE),0)+IFERROR(VLOOKUP(K14,源_3考勤报表_考勤表!$F:$BG,44,FALSE),0)+IFERROR(VLOOKUP(K14,源_8补工时表_补当月工时!$A:$AC,16,FALSE),0)+IFERROR(VLOOKUP(K14,源_3考勤报表_考勤表!$F:$BG,45,FALSE),0)-参数!$B$4,0)*1.5,0) -> 0 | AD14: 0 | AE14: =IFERROR(VLOOKUP(K14,源_3考勤报表_考勤表!$F:$BG,46,FALSE),0)+IFERROR(VLOOKUP(K14,源_8补工时表_补当月工时!$A:$AC,25,FALSE),0) -> 0 | AF14: =R14/174*AE14*3 -> 0 | AG14: =IFERROR(VLOOKUP(K14,源_4奖金汇总表_拆分手工算!$A:$N,10,FALSE),0) -> 0 | AH14: =IFERROR(VLOOKUP(K14,源_4奖金汇总表_拆分手工算!$A:$N,5,FALSE),0) -> 0 | AI14: =IFERROR(VLOOKUP(K14,源_4奖金汇总表_拆分手工算!$A:$N,11,FALSE),0) -> 1500 | AJ14: =IFERROR(VLOOKUP(K14,源_4奖金汇总表_拆分手工算!$A:$N,4,FALSE),0) -> 0 | AK14: =IFERROR(VLOOKUP(K14,源_4奖金汇总表_拆分手工算!$A:$N,3,FALSE),0) -> 0 | AL14: =IFERROR(VLOOKUP(K14,源_4奖金汇总表_拆分手工算!$A:$N,6,FALSE),0) -> 0 | AM14: =IFERROR(VLOOKUP(K14,源_5薪资备忘录_工资调整项!$A:$AC,18,FALSE),0)+IFERROR(VLOOKUP(K14,源_4奖金汇总表_拆分手工算!$A:$N,7,FALSE),0) -> 0 | AN14: =IFERROR(VLOOKUP(K14,源_5薪资备忘录_工资调整项!$A:$AC,17,FALSE),0) -> 0 | AO14: =IF(OR(IFERROR(VLOOKUP(K14,源_3考勤报表_考勤表!$F:$BG,39,FALSE),0)+IFERROR(VLOOKUP(K14,源_8补工时表_补当月工时!$A:$AC,24,FALSE),0)>0,IFERROR(VLOOKUP(K14,源_3考勤报表_考勤表!$F:$BG,43,FALSE),0)+IFERROR(VLOOKUP(K14,源_8补工时表_补当月工时!$A:$AC,26,FALSE),0)>0),IF(IFERROR(VLOOKUP(DH14,源_11产假政策_Sheet1!$C:$F,4,FALSE),"")="是",R14/参数!$B$4*(IFERROR(VLOOKUP(K14,源_3考勤报表_考勤表!$F:$BG,39,FALSE),0)+IFERROR(VLOOKUP(K14,源_8补工时表_补当月工时!$A:$AC,24,FALSE),0)+IFERROR(VLOOKUP(K14,源_3考勤报表_考勤表!$F:$BG,43,FALSE),0)+IFERROR(VLOOKUP(K14,源_8补工时表_补当月工时!$A:$AC,26,FALSE),0)),IFERROR(VLOOKUP(K14,源_5薪资备忘录_工资调整项!$A:$AC,19,FALSE),0)),0) -> 0 | AP14: 0 | AQ14: =IFERROR(VLOOKUP(K14,源_4奖金汇总表_拆分手工算!$A:$N,12,FALSE),0)+IFERROR(VLOOKUP(K14,源_9年终奖表_Sheet1!$A:$E,3,FALSE),0) -> 0 | AR14: =IFERROR(VLOOKUP(K14,源_4奖金汇总表_拆分手工算!$A:$N,13,FALSE),0)+IFERROR(VLOOKUP(K14,源_9年终奖表_Sheet1!$A:$E,4,FALSE),0) -> 0 | AS14: =IFERROR(VLOOKUP(K14,源_4奖金汇总表_拆分手工算!$A:$N,14,FALSE),0)+IFERROR(VLOOKUP(K14,源_9年终奖表_Sheet1!$A:$E,5,FALSE),0) -> 0 | AT14: =IFERROR(VLOOKUP(K14,源_5薪资备忘录_工资调整项!$A:$AC,20,FALSE),0) -> 0 | AU14: =IFERROR(VLOOKUP(K14,源_5薪资备忘录_工资调整项!$A:$AC,21,FALSE),0)+IFERROR(VLOOKUP(K14,源_4奖金汇总表_拆分手工算!$A:$N,9,FALSE),0) -> 7418.55 | AV14: =R14/参数!$B$4*(IFERROR(VLOOKUP(K14,源_3考勤报表_考勤表!$F:$BG,37,FALSE),0)+IFERROR(VLOOKUP(K14,源_8补工时表_补当月工时!$A:$AC,15,FALSE),0)) -> 0 | AW14: =R14/174*MIN(IFERROR(VLOOKUP(K14,源_3考勤报表_考勤表!$F:$BG,35,FALSE),0),174)*IF(DATEDIF(N14,DATE(参数!$B$2,参数!$B$3+1,0),"Y")<2,0.6,IF(DATEDIF(N14,DATE(参数!$B$2,参数!$B$3+1,0),"Y")<4,0.7,IF(DATEDIF(N14,DATE(参数!$B$2,参数!$B$3+1,0),"Y")<6,0.8,IF(DATEDIF(N14,DATE(参数!$B$2,参数!$B$3+1,0),"Y")<8,0.9,1)))) -> 0 | AX14: =IF(Q14+IFERROR(VLOOKUP(K14,源_3考勤报表_考勤表!$F:$BG,37,FALSE),0)+IFERROR(VLOOKUP(K14,源_8补工时表_补当月工时!$A:$AC,15,FALSE),0)>=参数!$B$4,0,IF(Q14+IFERROR(VLOOKUP(K14,源_3考勤报表_考勤表!$F:$BG,37,FALSE),0)+IFERROR(VLOOKUP(K14,源_8补工时表_补当月工时!$A:$AC,15,FALSE),0)+IFERROR(VLOOKUP(K14,源_3考勤报表_考勤表!$F:$BG,38,FALSE),0)+IFERROR(VLOOKUP(K14,源_8补工时表_补当月工时!$A:$AC,17,FALSE),0)+IFERROR(VLOOKUP(K14,源_3考勤报表_考勤表!$F:$BG,40,FALSE),0)+IFERROR(VLOOKUP(K14,源_8补工时表_补当月工时!$A:$AC,20,FALSE),0)+IFERROR(VLOOKUP(K14,源_8补工时表_补当月工时!$A:$AC,22,FALSE),0)+IFERROR(VLOOKUP(K14,源_3考勤报表_考勤表!$F:$BG,41,FALSE),0)+IFERROR(VLOOKUP(K14,源_8补工时表_补当月工时!$A:$AC,18,FALSE),0)+IFERROR(VLOOKUP(K14,源_3考勤报表_考勤表!$F:$BG,42,FALSE),0)+IFERROR(VLOOKUP(K14,源_8补工时表_补当月工时!$A:$AC,19,FALSE),0)+IFERROR(VLOOKUP(K14,源_3考勤报表_考勤表!$F:$BG,44,FALSE),0)+IFERROR(VLOOKUP(K14,源_8补工时表_补当月工时!$A:$AC,16,FALSE),0)+IFERROR(VLOOKUP(K14,源_3考勤报表_考勤表!$F:$BG,45,FALSE),0)<=参数!$B$4,R14/参数!$B$4*(IFERROR(VLOOKUP(K14,源_3考勤报表_考勤表!$F:$BG,38,FALSE),0)+IFERROR(VLOOKUP(K14,源_8补工时表_补当月工时!$A:$AC,17,FALSE),0)+IFERROR(VLOOKUP(K14,源_3考勤报表_考勤表!$F:$BG,40,FALSE),0)+IFERROR(VLOOKUP(K14,源_8补工时表_补当月工时!$A:$AC,20,FALSE),0)+IFERROR(VLOOKUP(K14,源_8补工时表_补当月工时!$A:$AC,22,FALSE),0)+IFERROR(VLOOKUP(K14,源_3考勤报表_考勤表!$F:$BG,41,FALSE),0)+IFERROR(VLOOKUP(K14,源_8补工时表_补当月工时!$A:$AC,18,FALSE),0)+IFERROR(VLOOKUP(K14,源_3考勤报表_考勤表!$F:$BG,42,FALSE),0)+IFERROR(VLOOKUP(K14,源_8补工时表_补当月工时!$A:$AC,19,FALSE),0)+IFERROR(VLOOKUP(K14,源_3考勤报表_考勤表!$F:$BG,44,FALSE),0)+IFERROR(VLOOKUP(K14,源_8补工时表_补当月工时!$A:$AC,16,FALSE),0)+IFERROR(VLOOKUP(K14,源_3考勤报表_考勤表!$F:$BG,45,FALSE),0)),0)) -> 0 | AY14: 0 | AZ14: 0 | BA14: 0 | BB14: 0 | BC14: =IFERROR(VLOOKUP(K14,源_5薪资备忘录_工资调整项!$A:$AC,25,FALSE),0) -> 0 | BD14: =IF(R14<=1000,5,IF(R14<=2000,6,IF(R14<=3000,7,8))) -> 8 | BE14: =(T14+W14+AB14+AG14+AH14+AI14+AJ14+AK14+AL14+AM14+AN14+AO14+AP14+AU14+AV14+AW14+AX14+BC14-IFERROR(VLOOKUP(DF14,源_6社保表_Sheet1!$C:$BZ,76,FALSE),0))*0.02 -> 292.777 | BF14: 0 | BG14: =IFERROR(VLOOKUP(K14,源_5薪资备忘录_工资调整项!$A:$AC,22,FALSE),0)+IFERROR(VLOOKUP(K14,源_5薪资备忘录_工资调整项!$A:$AC,23,FALSE),0)+IFERROR(VLOOKUP(K14,源_5薪资备忘录_工资调整项!$A:$AC,24,FALSE),0) -> 0 | BH14: =IFERROR(VLOOKUP(DF14,源_6社保表_Sheet1!$C:$CD,80,FALSE),0)+4.5 -> 6.5 | BI14: =T14+W14+AB14+AG14+AH14+AI14+AJ14+AK14+AL14+AM14+AN14+AO14+AP14+AQ14+AR14+AS14+AT14+AU14+AV14+AW14+AX14+BC14 -> 16270.55 | BJ14: =IFERROR(VLOOKUP(DF14,源_6社保表_Sheet1!$C:$BZ,26,FALSE),0) -> 745.92 | BK14: =IFERROR(VLOOKUP(DF14,源_6社保表_Sheet1!$C:$BZ,27,FALSE),0) -> 186.48 | BL14: =IFERROR(VLOOKUP(DF14,源_6社保表_Sheet1!$C:$BZ,28,FALSE),0) -> 46.62 | BM14: =IFERROR(VLOOKUP(DF14,源_6社保表_Sheet1!$C:$BZ,30,FALSE),0) -> 652.68 | BN14: =IFERROR(VLOOKUP(DF14,源_6社保表_Sheet1!$C:$BZ,29,FALSE),0) -> 0 | BO14: =IFERROR(VLOOKUP(DF14,源_6社保表_Sheet1!$C:$BZ,40,FALSE),0) -> 0 | BP14: =IFERROR(VLOOKUP(DF14,源_6社保表_Sheet1!$C:$BZ,41,FALSE),0) -> 0 | BQ14: =IFERROR(VLOOKUP(DF14,源_6社保表_Sheet1!$C:$BZ,42,FALSE),0) -> 0 | BR14: =IFERROR(VLOOKUP(DF14,源_6社保表_Sheet1!$C:$BZ,44,FALSE),0) -> 0 | BS14: =IFERROR(VLOOKUP(DF14,源_6社保表_Sheet1!$C:$BZ,43,FALSE),0) -> 0 | BT14: =BJ14+BK14+BL14+BM14+BN14+BO14+BP14+BQ14+BR14+BS14 -> 1631.7 | BU14: 0 | BV14: 0 | BW14: 0 | BX14: =BU14+BV14+BW14 -> 0 | BY14: 0 | BZ14: =IFERROR(VLOOKUP(DF14,源_6社保表_Sheet1!$C:$BZ,18,FALSE),0) -> 1491.84 | CA14: =IFERROR(VLOOKUP(DF14,源_6社保表_Sheet1!$C:$BZ,19,FALSE),0) -> 839.16 | CB14: =IFERROR(VLOOKUP(DF14,源_6社保表_Sheet1!$C:$BZ,24,FALSE),0) -> 652.68 | CC14: =IFERROR(VLOOKUP(DF14,源_6社保表_Sheet1!$C:$BZ,20,FALSE),0) -> 46.62 | CD14: =IFERROR(VLOOKUP(DF14,源_6社保表_Sheet1!$C:$BZ,21,FALSE),0) -> 29.8368 | CE14: =IFERROR(VLOOKUP(DF14,源_6社保表_Sheet1!$C:$BZ,22,FALSE),0) -> 0 | CF14: =IFERROR(VLOOKUP(DF14,源_6社保表_Sheet1!$C:$BZ,23,FALSE),0) -> 0 | CG14: =IFERROR(VLOOKUP(DF14,源_6社保表_Sheet1!$C:$BZ,32,FALSE),0) -> 0 | CH14: =IFERROR(VLOOKUP(DF14,源_6社保表_Sheet1!$C:$BZ,33,FALSE),0) -> 0 | CI14: =IFERROR(VLOOKUP(DF14,源_6社保表_Sheet1!$C:$BZ,34,FALSE),0) -> 0 | CJ14: =IFERROR(VLOOKUP(DF14,源_6社保表_Sheet1!$C:$BZ,38,FALSE),0) -> 0 | CK14: =IFERROR(VLOOKUP(DF14,源_6社保表_Sheet1!$C:$BZ,35,FALSE),0) -> 0 | CL14: =IFERROR(VLOOKUP(DF14,源_6社保表_Sheet1!$C:$BZ,36,FALSE),0) -> 0 | CM14: =IFERROR(VLOOKUP(DF14,源_6社保表_Sheet1!$C:$BZ,37,FALSE),0) -> 0 | CN14: =BZ14+CA14+CB14+CC14+CD14+CE14+CF14+CG14+CH14+CI14+CJ14+CK14+CL14+CM14 -> 3060.1368 | CO14: =BI14+BG14+CN14+BE14+BH14 -> 19629.964 | CP14: =IF(IFERROR(VLOOKUP(K14,源_13残疾人信息_残疾人信息!$A:$M,1,FALSE),"")<>"",0,IF(OR(P14="门店全职",P14="门店管理组",P14="全职(非门店)"),(BI14-AT14)*IFERROR(VLOOKUP(D14,源_12计提残保金规则_Sheet1!$A:$E,4,FALSE),0)*IFERROR(VLOOKUP(D14,源_12计提残保金规则_Sheet1!$A:$E,5,FALSE),0),0)) -> 219.65242 | CQ14: =IF(M14="行政",0,16.05) -> 16.05 | CR14: =IF(M14="门卫",0,20.67) -> 20.67 | CS14: =IF(DATEVALUE(N14)>DATE(参数!$B$2,9,30),0,IF(M14="行政",0,IF(O14="",R14/12,IF(MONTH(DATEVALUE(O14))=参数!$B$3,0,IF(DATEVALUE(O14)<DATE(参数!$B$2,参数!$B$3,1),0,R14/12))))) -> 612.66667 | CT14: =IF(P14="门店管理组",R14*0.12*0.85,0) -> 749.904 | CU14: =IFERROR(VLOOKUP(DF14,源_6社保表_Sheet1!$C:$I,2,FALSE),0) -> 9324 | CV14: =IFERROR(VLOOKUP(DF14,源_6社保表_Sheet1!$C:$I,7,FALSE),0) -> 9324 | CW14: =IFERROR(VLOOKUP(DF14,源_6社保表_Sheet1!$C:$I,3,FALSE),0) -> 9324 | CX14: =IFERROR(VLOOKUP(DF14,源_6社保表_Sheet1!$C:$I,4,FALSE),0) -> 9324 | CY14: =IFERROR(VLOOKUP(DF14,源_6社保表_Sheet1!$C:$I,5,FALSE),0) -> 9324 | CZ14: =IFERROR(VLOOKUP(DF14,源_6社保表_Sheet1!$C:$I,6,FALSE),0) -> 0 | DA14: =BI14+CN14-AG14-AH14-AI14-AJ14-AK14-AL14-AM14-AQ14-AR14-AS14-AT14 -> 17830.687 | DB14: =DA14+CP14+CQ14+CR14+CS14+CT14+BH14 -> 19456.13 | DC14: =IFERROR(VLOOKUP(K14,源_7银行卡表_Sheet1!$A:$J,8,FALSE),"") -> 农业银行 | DD14: =IFERROR(VLOOKUP(K14,源_7银行卡表_Sheet1!$A:$J,9,FALSE),"") -> 6682462769453468066 | DE14: =IFERROR(VLOOKUP(K14,源_7银行卡表_Sheet1!$A:$J,10,FALSE),"") -> 中国农业银行武乡广场分理处 | DF14: 120000197707211254 | DG14: 17394807156 | DH14: 北京 | DI14: 0 | DJ14: 0 | DK14: 0 | DL14: 0 | DM14: 0 | DN14: 0 | DO14: 0 | DP14: 0 | DQ14: 0 | DR14: =IF(OR(IFERROR(VLOOKUP(K14,源_3考勤报表_考勤表!$F:$BG,39,FALSE),0)+IFERROR(VLOOKUP(K14,源_8补工时表_补当月工时!$A:$AC,24,FALSE),0)=0,IFERROR(VLOOKUP(K14,源_3考勤报表_考勤表!$F:$BG,43,FALSE),0)+IFERROR(VLOOKUP(K14,源_8补工时表_补当月工时!$A:$AC,26,FALSE),0)=0),IF(BI14+BG14-BT14<0,BI14+BG14-BT14,0),0) -> 0
A15: =参数!$B$2 -> 2025 | B15: =参数!$B$3 -> 12 | D15: 杭州达美乐 | E15: 店铺营运 | F15: =IFERROR(VLOOKUP(K15,源_7银行卡表_Sheet1!$A:$J,6,FALSE),"") -> 华东营运 | G15: 杭州 | H15: 市心南路店 | I15: 外服-杭州门店全职 | J15: 1 | K15: 26123014 | L15: 唐谷冬 | M15: 餐厅经理 | N15: 2022-09-02 | P15: 门店管理组 | Q15: =IF(P15="门店全职",IFERROR(VLOOKUP(K15,源_3考勤报表_考勤表!$F:$BG,34,FALSE),0)+IFERROR(VLOOKUP(K15,源_8补工时表_补当月工时!$A:$AC,14,FALSE),0),IF(P15="门店管理组",IF(IFERROR(VLOOKUP(K15,源_3考勤报表_考勤表!$F:$BG,34,FALSE),0)+IFERROR(VLOOKUP(K15,源_8补工时表_补当月工时!$A:$AC,14,FALSE),0)+IFERROR(VLOOKUP(K15,源_3考勤报表_考勤表!$F:$BG,37,FALSE),0)+IFERROR(VLOOKUP(K15,源_8补工时表_补当月工时!$A:$AC,15,FALSE),0)+IFERROR(VLOOKUP(K15,源_3考勤报表_考勤表!$F:$BG,38,FALSE),0)+IFERROR(VLOOKUP(K15,源_8补工时表_补当月工时!$A:$AC,17,FALSE),0)+IFERROR(VLOOKUP(K15,源_3考勤报表_考勤表!$F:$BG,40,FALSE),0)+IFERROR(VLOOKUP(K15,源_8补工时表_补当月工时!$A:$AC,20,FALSE),0)+IFERROR(VLOOKUP(K15,源_8补工时表_补当月工时!$A:$AC,22,FALSE),0)+IFERROR(VLOOKUP(K15,源_3考勤报表_考勤表!$F:$BG,41,FALSE),0)+IFERROR(VLOOKUP(K15,源_8补工时表_补当月工时!$A:$AC,18,FALSE),0)+IFERROR(VLOOKUP(K15,源_3考勤报表_考勤表!$F:$BG,44,FALSE),0)+IFERROR(VLOOKUP(K15,源_8补工时表_补当月工时!$A:$AC,16,FALSE),0)+IFERROR(VLOOKUP(K15,源_3考勤报表_考勤表!$F:$BG,45,FALSE),0)>=参数!$B$4,参数!$B$4-IFERROR(VLOOKUP(K15,源_3考勤报表_考勤表!$F:$BG,37,FALSE),0)-IFERROR(VLOOKUP(K15,源_8补工时表_补当月工时!$A:$AC,15,FALSE),0)-IFERROR(VLOOKUP(K15,源_3考勤报表_考勤表!$F:$BG,38,FALSE),0)-IFERROR(VLOOKUP(K15,源_8补工时表_补当月工时!$A:$AC,17,FALSE),0)-IFERROR(VLOOKUP(K15,源_3考勤报表_考勤表!$F:$BG,40,FALSE),0)-IFERROR(VLOOKUP(K15,源_8补工时表_补当月工时!$A:$AC,20,FALSE),0)-IFERROR(VLOOKUP(K15,源_8补工时表_补当月工时!$A:$AC,22,FALSE),0)-IFERROR(VLOOKUP(K15,源_3考勤报表_考勤表!$F:$BG,41,FALSE),0)-IFERROR(VLOOKUP(K15,源_8补工时表_补当月工时!$A:$AC,18,FALSE),0)-IFERROR(VLOOKUP(K15,源_3考勤报表_考勤表!$F:$BG,44,FALSE),0)-IFERROR(VLOOKUP(K15,源_8补工时表_补当月工时!$A:$AC,16,FALSE),0)-IFERROR(VLOOKUP(K15,源_3考勤报表_考勤表!$F:$BG,45,FALSE),0),IFERROR(VLOOKUP(K15,源_3考勤报表_考勤表!$F:$BG,34,FALSE),0)+IFERROR(VLOOKUP(K15,源_8补工时表_补当月工时!$A:$AC,14,FALSE),0)),0)) -> 160 | R15: 6948 | S15: 19 | T15: =IF(P15="门店全职",R15/参数!$B$4*(Q15-MAX(IFERROR(VLOOKUP(K15,源_3考勤报表_考勤表!$F:$BG,34,FALSE),0)+IFERROR(VLOOKUP(K15,源_8补工时表_补当月工时!$A:$AC,14,FALSE),0)+IFERROR(VLOOKUP(K15,源_3考勤报表_考勤表!$F:$BG,37,FALSE),0)+IFERROR(VLOOKUP(K15,源_8补工时表_补当月工时!$A:$AC,15,FALSE),0)+IFERROR(VLOOKUP(K15,源_3考勤报表_考勤表!$F:$BG,38,FALSE),0)+IFERROR(VLOOKUP(K15,源_8补工时表_补当月工时!$A:$AC,17,FALSE),0)+IFERROR(VLOOKUP(K15,源_3考勤报表_考勤表!$F:$BG,40,FALSE),0)+IFERROR(VLOOKUP(K15,源_8补工时表_补当月工时!$A:$AC,20,FALSE),0)+IFERROR(VLOOKUP(K15,源_8补工时表_补当月工时!$A:$AC,22,FALSE),0)+IFERROR(VLOOKUP(K15,源_3考勤报表_考勤表!$F:$BG,41,FALSE),0)+IFERROR(VLOOKUP(K15,源_8补工时表_补当月工时!$A:$AC,18,FALSE),0)+IFERROR(VLOOKUP(K15,源_3考勤报表_考勤表!$F:$BG,42,FALSE),0)+IFERROR(VLOOKUP(K15,源_8补工时表_补当月工时!$A:$AC,19,FALSE),0)+IFERROR(VLOOKUP(K15,源_3考勤报表_考勤表!$F:$BG,44,FALSE),0)+IFERROR(VLOOKUP(K15,源_8补工时表_补当月工时!$A:$AC,16,FALSE),0)+IFERROR(VLOOKUP(K15,源_3考勤报表_考勤表!$F:$BG,45,FALSE),0)-参数!$B$4,0)),R15/参数!$B$4*Q15) -> 6041.7391 | U15: 0 | V15: 0 | W15: =X15+Y15+Z15+AA15 -> 25.5 | X15: =IFERROR(VLOOKUP(K15,源_4奖金汇总表_拆分手工算!$A:$N,8,FALSE),0) -> 25.5 | Y15: =IFERROR(VLOOKUP(K15,源_5薪资备忘录_工资调整项!$A:$AC,14,FALSE),0) -> 0 | Z15: =IFERROR(VLOOKUP(K15,源_5薪资备忘录_工资调整项!$A:$AC,16,FALSE),0) -> 0 | AA15: =IFERROR(VLOOKUP(K15,源_5薪资备忘录_工资调整项!$A:$AC,15,FALSE),0) -> 0 | AB15: =AC15+AD15+AF15 -> 0 | AC15: =IF(P15="门店全职",R15/174*MAX(IFERROR(VLOOKUP(K15,源_3考勤报表_考勤表!$F:$BG,34,FALSE),0)+IFERROR(VLOOKUP(K15,源_8补工时表_补当月工时!$A:$AC,14,FALSE),0)+IFERROR(VLOOKUP(K15,源_3考勤报表_考勤表!$F:$BG,37,FALSE),0)+IFERROR(VLOOKUP(K15,源_8补工时表_补当月工时!$A:$AC,15,FALSE),0)+IFERROR(VLOOKUP(K15,源_3考勤报表_考勤表!$F:$BG,38,FALSE),0)+IFERROR(VLOOKUP(K15,源_8补工时表_补当月工时!$A:$AC,17,FALSE),0)+IFERROR(VLOOKUP(K15,源_3考勤报表_考勤表!$F:$BG,40,FALSE),0)+IFERROR(VLOOKUP(K15,源_8补工时表_补当月工时!$A:$AC,20,FALSE),0)+IFERROR(VLOOKUP(K15,源_8补工时表_补当月工时!$A:$AC,22,FALSE),0)+IFERROR(VLOOKUP(K15,源_3考勤报表_考勤表!$F:$BG,41,FALSE),0)+IFERROR(VLOOKUP(K15,源_8补工时表_补当月工时!$A:$AC,18,FALSE),0)+IFERROR(VLOOKUP(K15,源_3考勤报表_考勤表!$F:$BG,42,FALSE),0)+IFERROR(VLOOKUP(K15,源_8补工时表_补当月工时!$A:$AC,19,FALSE),0)+IFERROR(VLOOKUP(K15,源_3考勤报表_考勤表!$F:$BG,44,FALSE),0)+IFERROR(VLOOKUP(K15,源_8补工时表_补当月工时!$A:$AC,16,FALSE),0)+IFERROR(VLOOKUP(K15,源_3考勤报表_考勤表!$F:$BG,45,FALSE),0)-参数!$B$4,0)*1.5,0) -> 0 | AD15: 0 | AE15: =IFERROR(VLOOKUP(K15,源_3考勤报表_考勤表!$F:$BG,46,FALSE),0)+IFERROR(VLOOKUP(K15,源_8补工时表_补当月工时!$A:$AC,25,FALSE),0) -> 0 | AF15: =R15/174*AE15*3 -> 0 | AG15: =IFERROR(VLOOKUP(K15,源_4奖金汇总表_拆分手工算!$A:$N,10,FALSE),0) -> 0 | AH15: =IFERROR(VLOOKUP(K15,源_4奖金汇总表_拆分手工算!$A:$N,5,FALSE),0) -> 0 | AI15: =IFERROR(VLOOKUP(K15,源_4奖金汇总表_拆分手工算!$A:$N,11,FALSE),0) -> 0 | AJ15: =IFERROR(VLOOKUP(K15,源_4奖金汇总表_拆分手工算!$A:$N,4,FALSE),0) -> 0 | AK15: =IFERROR(VLOOKUP(K15,源_4奖金汇总表_拆分手工算!$A:$N,3,FALSE),0) -> 0 | AL15: =IFERROR(VLOOKUP(K15,源_4奖金汇总表_拆分手工算!$A:$N,6,FALSE),0) -> 0 | AM15: =IFERROR(VLOOKUP(K15,源_5薪资备忘录_工资调整项!$A:$AC,18,FALSE),0)+IFERROR(VLOOKUP(K15,源_4奖金汇总表_拆分手工算!$A:$N,7,FALSE),0) -> 66 | AN15: =IFERROR(VLOOKUP(K15,源_5薪资备忘录_工资调整项!$A:$AC,17,FALSE),0) -> 100 | AO15: =IF(OR(IFERROR(VLOOKUP(K15,源_3考勤报表_考勤表!$F:$BG,39,FALSE),0)+IFERROR(VLOOKUP(K15,源_8补工时表_补当月工时!$A:$AC,24,FALSE),0)>0,IFERROR(VLOOKUP(K15,源_3考勤报表_考勤表!$F:$BG,43,FALSE),0)+IFERROR(VLOOKUP(K15,源_8补工时表_补当月工时!$A:$AC,26,FALSE),0)>0),IF(IFERROR(VLOOKUP(DH15,源_11产假政策_Sheet1!$C:$F,4,FALSE),"")="是",R15/参数!$B$4*(IFERROR(VLOOKUP(K15,源_3考勤报表_考勤表!$F:$BG,39,FALSE),0)+IFERROR(VLOOKUP(K15,源_8补工时表_补当月工时!$A:$AC,24,FALSE),0)+IFERROR(VLOOKUP(K15,源_3考勤报表_考勤表!$F:$BG,43,FALSE),0)+IFERROR(VLOOKUP(K15,源_8补工时表_补当月工时!$A:$AC,26,FALSE),0)),IFERROR(VLOOKUP(K15,源_5薪资备忘录_工资调整项!$A:$AC,19,FALSE),0)),0) -> 0 | AP15: 0 | AQ15: =IFERROR(VLOOKUP(K15,源_4奖金汇总表_拆分手工算!$A:$N,12,FALSE),0)+IFERROR(VLOOKUP(K15,源_9年终奖表_Sheet1!$A:$E,3,FALSE),0) -> 0 | AR15: =IFERROR(VLOOKUP(K15,源_4奖金汇总表_拆分手工算!$A:$N,13,FALSE),0)+IFERROR(VLOOKUP(K15,源_9年终奖表_Sheet1!$A:$E,4,FALSE),0) -> 0 | AS15: =IFERROR(VLOOKUP(K15,源_4奖金汇总表_拆分手工算!$A:$N,14,FALSE),0)+IFERROR(VLOOKUP(K15,源_9年终奖表_Sheet1!$A:$E,5,FALSE),0) -> 0 | AT15: =IFERROR(VLOOKUP(K15,源_5薪资备忘录_工资调整项!$A:$AC,20,FALSE),0) -> 0 | AU15: =IFERROR(VLOOKUP(K15,源_5薪资备忘录_工资调整项!$A:$AC,21,FALSE),0)+IFERROR(VLOOKUP(K15,源_4奖金汇总表_拆分手工算!$A:$N,9,FALSE),0) -> 0 | AV15: =R15/参数!$B$4*(IFERROR(VLOOKUP(K15,源_3考勤报表_考勤表!$F:$BG,37,FALSE),0)+IFERROR(VLOOKUP(K15,源_8补工时表_补当月工时!$A:$AC,15,FALSE),0)) -> 302.08696 | AW15: =R15/174*MIN(IFERROR(VLOOKUP(K15,源_3考勤报表_考勤表!$F:$BG,35,FALSE),0),174)*IF(DATEDIF(N15,DATE(参数!$B$2,参数!$B$3+1,0),"Y")<2,0.6,IF(DATEDIF(N15,DATE(参数!$B$2,参数!$B$3+1,0),"Y")<4,0.7,IF(DATEDIF(N15,DATE(参数!$B$2,参数!$B$3+1,0),"Y")<6,0.8,IF(DATEDIF(N15,DATE(参数!$B$2,参数!$B$3+1,0),"Y")<8,0.9,1)))) -> 4695.8897 | AX15: =IF(Q15+IFERROR(VLOOKUP(K15,源_3考勤报表_考勤表!$F:$BG,37,FALSE),0)+IFERROR(VLOOKUP(K15,源_8补工时表_补当月工时!$A:$AC,15,FALSE),0)>=参数!$B$4,0,IF(Q15+IFERROR(VLOOKUP(K15,源_3考勤报表_考勤表!$F:$BG,37,FALSE),0)+IFERROR(VLOOKUP(K15,源_8补工时表_补当月工时!$A:$AC,15,FALSE),0)+IFERROR(VLOOKUP(K15,源_3考勤报表_考勤表!$F:$BG,38,FALSE),0)+IFERROR(VLOOKUP(K15,源_8补工时表_补当月工时!$A:$AC,17,FALSE),0)+IFERROR(VLOOKUP(K15,源_3考勤报表_考勤表!$F:$BG,40,FALSE),0)+IFERROR(VLOOKUP(K15,源_8补工时表_补当月工时!$A:$AC,20,FALSE),0)+IFERROR(VLOOKUP(K15,源_8补工时表_补当月工时!$A:$AC,22,FALSE),0)+IFERROR(VLOOKUP(K15,源_3考勤报表_考勤表!$F:$BG,41,FALSE),0)+IFERROR(VLOOKUP(K15,源_8补工时表_补当月工时!$A:$AC,18,FALSE),0)+IFERROR(VLOOKUP(K15,源_3考勤报表_考勤表!$F:$BG,42,FALSE),0)+IFERROR(VLOOKUP(K15,源_8补工时表_补当月工时!$A:$AC,19,FALSE),0)+IFERROR(VLOOKUP(K15,源_3考勤报表_考勤表!$F:$BG,44,FALSE),0)+IFERROR(VLOOKUP(K15,源_8补工时表_补当月工时!$A:$AC,16,FALSE),0)+IFERROR(VLOOKUP(K15,源_3考勤报表_考勤表!$F:$BG,45,FALSE),0)<=参数!$B$4,R15/参数!$B$4*(IFERROR(VLOOKUP(K15,源_3考勤报表_考勤表!$F:$BG,38,FALSE),0)+IFERROR(VLOOKUP(K15,源_8补工时表_补当月工时!$A:$AC,17,FALSE),0)+IFERROR(VLOOKUP(K15,源_3考勤报表_考勤表!$F:$BG,40,FALSE),0)+IFERROR(VLOOKUP(K15,源_8补工时表_补当月工时!$A:$AC,20,FALSE),0)+IFERROR(VLOOKUP(K15,源_8补工时表_补当月工时!$A:$AC,22,FALSE),0)+IFERROR(VLOOKUP(K15,源_3考勤报表_考勤表!$F:$BG,41,FALSE),0)+IFERROR(VLOOKUP(K15,源_8补工时表_补当月工时!$A:$AC,18,FALSE),0)+IFERROR(VLOOKUP(K15,源_3考勤报表_考勤表!$F:$BG,42,FALSE),0)+IFERROR(VLOOKUP(K15,源_8补工时表_补当月工时!$A:$AC,19,FALSE),0)+IFERROR(VLOOKUP(K15,源_3考勤报表_考勤表!$F:$BG,44,FALSE),0)+IFERROR(VLOOKUP(K15,源_8补工时表_补当月工时!$A:$AC,16,FALSE),0)+IFERROR(VLOOKUP(K15,源_3考勤报表_考勤表!$F:$BG,45,FALSE),0)),0)) -> 0 | AY15: 0 | AZ15: 0 | BA15: 0 | BB15: 0 | BC15: =IFERROR(VLOOKUP(K15,源_5薪资备忘录_工资调整项!$A:$AC,25,FALSE),0) -> 0 | BD15: 0 | BE15: 0 | BF15: 0 | BG15: =IFERROR(VLOOKUP(K15,源_5薪资备忘录_工资调整项!$A:$AC,22,FALSE),0)+IFERROR(VLOOKUP(K15,源_5薪资备忘录_工资调整项!$A:$AC,23,FALSE),0)+IFERROR(VLOOKUP(K15,源_5薪资备忘录_工资调整项!$A:$AC,24,FALSE),0) -> 0 | BH15: =IFERROR(VLOOKUP(DF15,源_6社保表_Sheet1!$C:$CD,80,FALSE),0)+4.5 -> 6.5 | BI15: =T15+W15+AB15+AG15+AH15+AI15+AJ15+AK15+AL15+AM15+AN15+AO15+AP15+AQ15+AR15+AS15+AT15+AU15+AV15+AW15+AX15+BC15 -> 11231.216 | BJ15: =IFERROR(VLOOKUP(DF15,源_6社保表_Sheet1!$C:$BZ,26,FALSE),0) -> 707.36 | BK15: =IFERROR(VLOOKUP(DF15,源_6社保表_Sheet1!$C:$BZ,27,FALSE),0) -> 176.84 | BL15: =IFERROR(VLOOKUP(DF15,源_6社保表_Sheet1!$C:$BZ,28,FALSE),0) -> 44.21 | BM15: =IFERROR(VLOOKUP(DF15,源_6社保表_Sheet1!$C:$BZ,30,FALSE),0) -> 618.94 | BN15: =IFERROR(VLOOKUP(DF15,源_6社保表_Sheet1!$C:$BZ,29,FALSE),0) -> 0 | BO15: =IFERROR(VLOOKUP(DF15,源_6社保表_Sheet1!$C:$BZ,40,FALSE),0) -> 0 | BP15: =IFERROR(VLOOKUP(DF15,源_6社保表_Sheet1!$C:$BZ,41,FALSE),0) -> 0 | BQ15: =IFERROR(VLOOKUP(DF15,源_6社保表_Sheet1!$C:$BZ,42,FALSE),0) -> 0 | BR15: =IFERROR(VLOOKUP(DF15,源_6社保表_Sheet1!$C:$BZ,44,FALSE),0) -> 0 | BS15: =IFERROR(VLOOKUP(DF15,源_6社保表_Sheet1!$C:$BZ,43,FALSE),0) -> 0 | BT15: =BJ15+BK15+BL15+BM15+BN15+BO15+BP15+BQ15+BR15+BS15 -> 1547.35 | BU15: 0 | BV15: 0 | BW15: 0 | BX15: =BU15+BV15+BW15 -> 0 | BY15: 0 | BZ15: =IFERROR(VLOOKUP(DF15,源_6社保表_Sheet1!$C:$BZ,18,FALSE),0) -> 1414.72 | CA15: =IFERROR(VLOOKUP(DF15,源_6社保表_Sheet1!$C:$BZ,19,FALSE),0) -> 795.78 | CB15: =IFERROR(VLOOKUP(DF15,源_6社保表_Sheet1!$C:$BZ,24,FALSE),0) -> 618.94 | CC15: =IFERROR(VLOOKUP(DF15,源_6社保表_Sheet1!$C:$BZ,20,FALSE),0) -> 44.21 | CD15: =IFERROR(VLOOKUP(DF15,源_6社保表_Sheet1!$C:$BZ,21,FALSE),0) -> 28.2944 | CE15: =IFERROR(VLOOKUP(DF15,源_6社保表_Sheet1!$C:$BZ,22,FALSE),0) -> 0 | CF15: =IFERROR(VLOOKUP(DF15,源_6社保表_Sheet1!$C:$BZ,23,FALSE),0) -> 0 | CG15: =IFERROR(VLOOKUP(DF15,源_6社保表_Sheet1!$C:$BZ,32,FALSE),0) -> 0 | CH15: =IFERROR(VLOOKUP(DF15,源_6社保表_Sheet1!$C:$BZ,33,FALSE),0) -> 0 | CI15: =IFERROR(VLOOKUP(DF15,源_6社保表_Sheet1!$C:$BZ,34,FALSE),0) -> 0 | CJ15: =IFERROR(VLOOKUP(DF15,源_6社保表_Sheet1!$C:$BZ,38,FALSE),0) -> 0 | CK15: =IFERROR(VLOOKUP(DF15,源_6社保表_Sheet1!$C:$BZ,35,FALSE),0) -> 0 | CL15: =IFERROR(VLOOKUP(DF15,源_6社保表_Sheet1!$C:$BZ,36,FALSE),0) -> 0 | CM15: =IFERROR(VLOOKUP(DF15,源_6社保表_Sheet1!$C:$BZ,37,FALSE),0) -> 0 | CN15: =BZ15+CA15+CB15+CC15+CD15+CE15+CF15+CG15+CH15+CI15+CJ15+CK15+CL15+CM15 -> 2901.9444 | CO15: =BI15+BG15+CN15+BE15+BH15 -> 14139.66 | CP15: =IF(IFERROR(VLOOKUP(K15,源_13残疾人信息_残疾人信息!$A:$M,1,FALSE),"")<>"",0,IF(OR(P15="门店全职",P15="门店管理组",P15="全职(非门店)"),(BI15-AT15)*IFERROR(VLOOKUP(D15,源_12计提残保金规则_Sheet1!$A:$E,4,FALSE),0)*IFERROR(VLOOKUP(D15,源_12计提残保金规则_Sheet1!$A:$E,5,FALSE),0),0)) -> 151.62141 | CQ15: =IF(M15="行政",0,16.05) -> 16.05 | CR15: =IF(M15="门卫",0,20.67) -> 20.67 | CS15: =IF(DATEVALUE(N15)>DATE(参数!$B$2,9,30),0,IF(M15="行政",0,IF(O15="",R15/12,IF(MONTH(DATEVALUE(O15))=参数!$B$3,0,IF(DATEVALUE(O15)<DATE(参数!$B$2,参数!$B$3,1),0,R15/12))))) -> 579 | CT15: =IF(P15="门店管理组",R15*0.12*0.85,0) -> 708.696 | CU15: =IFERROR(VLOOKUP(DF15,源_6社保表_Sheet1!$C:$I,2,FALSE),0) -> 8842 | CV15: =IFERROR(VLOOKUP(DF15,源_6社保表_Sheet1!$C:$I,7,FALSE),0) -> 8842 | CW15: =IFERROR(VLOOKUP(DF15,源_6社保表_Sheet1!$C:$I,3,FALSE),0) -> 8842 | CX15: =IFERROR(VLOOKUP(DF15,源_6社保表_Sheet1!$C:$I,4,FALSE),0) -> 8842 | CY15: =IFERROR(VLOOKUP(DF15,源_6社保表_Sheet1!$C:$I,5,FALSE),0) -> 8842 | CZ15: =IFERROR(VLOOKUP(DF15,源_6社保表_Sheet1!$C:$I,6,FALSE),0) -> 0 | DA15: =BI15+CN15-AG15-AH15-AI15-AJ15-AK15-AL15-AM15-AQ15-AR15-AS15-AT15 -> 14067.16 | DB15: =DA15+CP15+CQ15+CR15+CS15+CT15+BH15 -> 15549.698 | DC15: =IFERROR(VLOOKUP(K15,源_7银行卡表_Sheet1!$A:$J,8,FALSE),"") -> 农业银行 | DD15: =IFERROR(VLOOKUP(K15,源_7银行卡表_Sheet1!$A:$J,9,FALSE),"") -> 6682600495578259256 | DE15: =IFERROR(VLOOKUP(K15,源_7银行卡表_Sheet1!$A:$J,10,FALSE),"") -> 中国农业银行忻州经济开发区支行 | DF15: 130000196310156128 | DG15: 16385630324 | DH15: 杭州 | DI15: 0 | DJ15: 0 | DK15: 0 | DL15: 0 | DM15: 0 | DN15: 0 | DO15: 0 | DP15: 0 | DQ15: 0 | DR15: =IF(OR(IFERROR(VLOOKUP(K15,源_3考勤报表_考勤表!$F:$BG,39,FALSE),0)+IFERROR(VLOOKUP(K15,源_8补工时表_补当月工时!$A:$AC,24,FALSE),0)=0,IFERROR(VLOOKUP(K15,源_3考勤报表_考勤表!$F:$BG,43,FALSE),0)+IFERROR(VLOOKUP(K15,源_8补工时表_补当月工时!$A:$AC,26,FALSE),0)=0),IF(BI15+BG15-BT15<0,BI15+BG15-BT15,0),0) -> 0
A16: =参数!$B$2 -> 2025 | B16: =参数!$B$3 -> 12 | D16: 苏州达美乐-外服派遣 | E16: 店铺营运 | F16: =IFERROR(VLOOKUP(K16,源_7银行卡表_Sheet1!$A:$J,6,FALSE),"") -> 华东营运 | G16: 苏州 | H16: 西二环路店 | I16: 外服-苏州门店全职（派遣） | J16: 1 | K16: 26123015 | L16: 杨景辉 | M16: 餐厅经理 | N16: 2024-07-01 | P16: 门店管理组 | Q16: =IF(P16="门店全职",IFERROR(VLOOKUP(K16,源_3考勤报表_考勤表!$F:$BG,34,FALSE),0)+IFERROR(VLOOKUP(K16,源_8补工时表_补当月工时!$A:$AC,14,FALSE),0),IF(P16="门店管理组",IF(IFERROR(VLOOKUP(K16,源_3考勤报表_考勤表!$F:$BG,34,FALSE),0)+IFERROR(VLOOKUP(K16,源_8补工时表_补当月工时!$A:$AC,14,FALSE),0)+IFERROR(VLOOKUP(K16,源_3考勤报表_考勤表!$F:$BG,37,FALSE),0)+IFERROR(VLOOKUP(K16,源_8补工时表_补当月工时!$A:$AC,15,FALSE),0)+IFERROR(VLOOKUP(K16,源_3考勤报表_考勤表!$F:$BG,38,FALSE),0)+IFERROR(VLOOKUP(K16,源_8补工时表_补当月工时!$A:$AC,17,FALSE),0)+IFERROR(VLOOKUP(K16,源_3考勤报表_考勤表!$F:$BG,40,FALSE),0)+IFERROR(VLOOKUP(K16,源_8补工时表_补当月工时!$A:$AC,20,FALSE),0)+IFERROR(VLOOKUP(K16,源_8补工时表_补当月工时!$A:$AC,22,FALSE),0)+IFERROR(VLOOKUP(K16,源_3考勤报表_考勤表!$F:$BG,41,FALSE),0)+IFERROR(VLOOKUP(K16,源_8补工时表_补当月工时!$A:$AC,18,FALSE),0)+IFERROR(VLOOKUP(K16,源_3考勤报表_考勤表!$F:$BG,44,FALSE),0)+IFERROR(VLOOKUP(K16,源_8补工时表_补当月工时!$A:$AC,16,FALSE),0)+IFERROR(VLOOKUP(K16,源_3考勤报表_考勤表!$F:$BG,45,FALSE),0)>=参数!$B$4,参数!$B$4-IFERROR(VLOOKUP(K16,源_3考勤报表_考勤表!$F:$BG,37,FALSE),0)-IFERROR(VLOOKUP(K16,源_8补工时表_补当月工时!$A:$AC,15,FALSE),0)-IFERROR(VLOOKUP(K16,源_3考勤报表_考勤表!$F:$BG,38,FALSE),0)-IFERROR(VLOOKUP(K16,源_8补工时表_补当月工时!$A:$AC,17,FALSE),0)-IFERROR(VLOOKUP(K16,源_3考勤报表_考勤表!$F:$BG,40,FALSE),0)-IFERROR(VLOOKUP(K16,源_8补工时表_补当月工时!$A:$AC,20,FALSE),0)-IFERROR(VLOOKUP(K16,源_8补工时表_补当月工时!$A:$AC,22,FALSE),0)-IFERROR(VLOOKUP(K16,源_3考勤报表_考勤表!$F:$BG,41,FALSE),0)-IFERROR(VLOOKUP(K16,源_8补工时表_补当月工时!$A:$AC,18,FALSE),0)-IFERROR(VLOOKUP(K16,源_3考勤报表_考勤表!$F:$BG,44,FALSE),0)-IFERROR(VLOOKUP(K16,源_8补工时表_补当月工时!$A:$AC,16,FALSE),0)-IFERROR(VLOOKUP(K16,源_3考勤报表_考勤表!$F:$BG,45,FALSE),0),IFERROR(VLOOKUP(K16,源_3考勤报表_考勤表!$F:$BG,34,FALSE),0)+IFERROR(VLOOKUP(K16,源_8补工时表_补当月工时!$A:$AC,14,FALSE),0)),0)) -> 116 | R16: 6500 | S16: 24 | T16: =IF(P16="门店全职",R16/参数!$B$4*(Q16-MAX(IFERROR(VLOOKUP(K16,源_3考勤报表_考勤表!$F:$BG,34,FALSE),0)+IFERROR(VLOOKUP(K16,源_8补工时表_补当月工时!$A:$AC,14,FALSE),0)+IFERROR(VLOOKUP(K16,源_3考勤报表_考勤表!$F:$BG,37,FALSE),0)+IFERROR(VLOOKUP(K16,源_8补工时表_补当月工时!$A:$AC,15,FALSE),0)+IFERROR(VLOOKUP(K16,源_3考勤报表_考勤表!$F:$BG,38,FALSE),0)+IFERROR(VLOOKUP(K16,源_8补工时表_补当月工时!$A:$AC,17,FALSE),0)+IFERROR(VLOOKUP(K16,源_3考勤报表_考勤表!$F:$BG,40,FALSE),0)+IFERROR(VLOOKUP(K16,源_8补工时表_补当月工时!$A:$AC,20,FALSE),0)+IFERROR(VLOOKUP(K16,源_8补工时表_补当月工时!$A:$AC,22,FALSE),0)+IFERROR(VLOOKUP(K16,源_3考勤报表_考勤表!$F:$BG,41,FALSE),0)+IFERROR(VLOOKUP(K16,源_8补工时表_补当月工时!$A:$AC,18,FALSE),0)+IFERROR(VLOOKUP(K16,源_3考勤报表_考勤表!$F:$BG,42,FALSE),0)+IFERROR(VLOOKUP(K16,源_8补工时表_补当月工时!$A:$AC,19,FALSE),0)+IFERROR(VLOOKUP(K16,源_3考勤报表_考勤表!$F:$BG,44,FALSE),0)+IFERROR(VLOOKUP(K16,源_8补工时表_补当月工时!$A:$AC,16,FALSE),0)+IFERROR(VLOOKUP(K16,源_3考勤报表_考勤表!$F:$BG,45,FALSE),0)-参数!$B$4,0)),R16/参数!$B$4*Q16) -> 4097.8261 | U16: 0 | V16: 0 | W16: =X16+Y16+Z16+AA16 -> 1000 | X16: =IFERROR(VLOOKUP(K16,源_4奖金汇总表_拆分手工算!$A:$N,8,FALSE),0) -> 0 | Y16: =IFERROR(VLOOKUP(K16,源_5薪资备忘录_工资调整项!$A:$AC,14,FALSE),0) -> 0 | Z16: =IFERROR(VLOOKUP(K16,源_5薪资备忘录_工资调整项!$A:$AC,16,FALSE),0) -> 0 | AA16: =IFERROR(VLOOKUP(K16,源_5薪资备忘录_工资调整项!$A:$AC,15,FALSE),0) -> 1000 | AB16: =AC16+AD16+AF16 -> 896.55172 | AC16: =IF(P16="门店全职",R16/174*MAX(IFERROR(VLOOKUP(K16,源_3考勤报表_考勤表!$F:$BG,34,FALSE),0)+IFERROR(VLOOKUP(K16,源_8补工时表_补当月工时!$A:$AC,14,FALSE),0)+IFERROR(VLOOKUP(K16,源_3考勤报表_考勤表!$F:$BG,37,FALSE),0)+IFERROR(VLOOKUP(K16,源_8补工时表_补当月工时!$A:$AC,15,FALSE),0)+IFERROR(VLOOKUP(K16,源_3考勤报表_考勤表!$F:$BG,38,FALSE),0)+IFERROR(VLOOKUP(K16,源_8补工时表_补当月工时!$A:$AC,17,FALSE),0)+IFERROR(VLOOKUP(K16,源_3考勤报表_考勤表!$F:$BG,40,FALSE),0)+IFERROR(VLOOKUP(K16,源_8补工时表_补当月工时!$A:$AC,20,FALSE),0)+IFERROR(VLOOKUP(K16,源_8补工时表_补当月工时!$A:$AC,22,FALSE),0)+IFERROR(VLOOKUP(K16,源_3考勤报表_考勤表!$F:$BG,41,FALSE),0)+IFERROR(VLOOKUP(K16,源_8补工时表_补当月工时!$A:$AC,18,FALSE),0)+IFERROR(VLOOKUP(K16,源_3考勤报表_考勤表!$F:$BG,42,FALSE),0)+IFERROR(VLOOKUP(K16,源_8补工时表_补当月工时!$A:$AC,19,FALSE),0)+IFERROR(VLOOKUP(K16,源_3考勤报表_考勤表!$F:$BG,44,FALSE),0)+IFERROR(VLOOKUP(K16,源_8补工时表_补当月工时!$A:$AC,16,FALSE),0)+IFERROR(VLOOKUP(K16,源_3考勤报表_考勤表!$F:$BG,45,FALSE),0)-参数!$B$4,0)*1.5,0) -> 0 | AD16: 0 | AE16: =IFERROR(VLOOKUP(K16,源_3考勤报表_考勤表!$F:$BG,46,FALSE),0)+IFERROR(VLOOKUP(K16,源_8补工时表_补当月工时!$A:$AC,25,FALSE),0) -> 8 | AF16: =R16/174*AE16*3 -> 896.55172 | AG16: =IFERROR(VLOOKUP(K16,源_4奖金汇总表_拆分手工算!$A:$N,10,FALSE),0) -> 0 | AH16: =IFERROR(VLOOKUP(K16,源_4奖金汇总表_拆分手工算!$A:$N,5,FALSE),0) -> 0 | AI16: =IFERROR(VLOOKUP(K16,源_4奖金汇总表_拆分手工算!$A:$N,11,FALSE),0) -> 0 | AJ16: =IFERROR(VLOOKUP(K16,源_4奖金汇总表_拆分手工算!$A:$N,4,FALSE),0) -> 0 | AK16: =IFERROR(VLOOKUP(K16,源_4奖金汇总表_拆分手工算!$A:$N,3,FALSE),0) -> 0 | AL16: =IFERROR(VLOOKUP(K16,源_4奖金汇总表_拆分手工算!$A:$N,6,FALSE),0) -> 0 | AM16: =IFERROR(VLOOKUP(K16,源_5薪资备忘录_工资调整项!$A:$AC,18,FALSE),0)+IFERROR(VLOOKUP(K16,源_4奖金汇总表_拆分手工算!$A:$N,7,FALSE),0) -> 200 | AN16: =IFERROR(VLOOKUP(K16,源_5薪资备忘录_工资调整项!$A:$AC,17,FALSE),0) -> 0 | AO16: =IF(OR(IFERROR(VLOOKUP(K16,源_3考勤报表_考勤表!$F:$BG,39,FALSE),0)+IFERROR(VLOOKUP(K16,源_8补工时表_补当月工时!$A:$AC,24,FALSE),0)>0,IFERROR(VLOOKUP(K16,源_3考勤报表_考勤表!$F:$BG,43,FALSE),0)+IFERROR(VLOOKUP(K16,源_8补工时表_补当月工时!$A:$AC,26,FALSE),0)>0),IF(IFERROR(VLOOKUP(DH16,源_11产假政策_Sheet1!$C:$F,4,FALSE),"")="是",R16/参数!$B$4*(IFERROR(VLOOKUP(K16,源_3考勤报表_考勤表!$F:$BG,39,FALSE),0)+IFERROR(VLOOKUP(K16,源_8补工时表_补当月工时!$A:$AC,24,FALSE),0)+IFERROR(VLOOKUP(K16,源_3考勤报表_考勤表!$F:$BG,43,FALSE),0)+IFERROR(VLOOKUP(K16,源_8补工时表_补当月工时!$A:$AC,26,FALSE),0)),IFERROR(VLOOKUP(K16,源_5薪资备忘录_工资调整项!$A:$AC,19,FALSE),0)),0) -> 0 | AP16: 0 | AQ16: =IFERROR(VLOOKUP(K16,源_4奖金汇总表_拆分手工算!$A:$N,12,FALSE),0)+IFERROR(VLOOKUP(K16,源_9年终奖表_Sheet1!$A:$E,3,FALSE),0) -> 0 | AR16: =IFERROR(VLOOKUP(K16,源_4奖金汇总表_拆分手工算!$A:$N,13,FALSE),0)+IFERROR(VLOOKUP(K16,源_9年终奖表_Sheet1!$A:$E,4,FALSE),0) -> 0 | AS16: =IFERROR(VLOOKUP(K16,源_4奖金汇总表_拆分手工算!$A:$N,14,FALSE),0)+IFERROR(VLOOKUP(K16,源_9年终奖表_Sheet1!$A:$E,5,FALSE),0) -> 0 | AT16: =IFERROR(VLOOKUP(K16,源_5薪资备忘录_工资调整项!$A:$AC,20,FALSE),0) -> 100 | AU16: =IFERROR(VLOOKUP(K16,源_5薪资备忘录_工资调整项!$A:$AC,21,FALSE),0)+IFERROR(VLOOKUP(K16,源_4奖金汇总表_拆分手工算!$A:$N,9,FALSE),0) -> 0 | AV16: =R16/参数!$B$4*(IFERROR(VLOOKUP(K16,源_3考勤报表_考勤表!$F:$BG,37,FALSE),0)+IFERROR(VLOOKUP(K16,源_8补工时表_补当月工时!$A:$AC,15,FALSE),0)) -> 1413.0435 | AW16: =R16/174*MIN(IFERROR(VLOOKUP(K16,源_3考勤报表_考勤表!$F:$BG,35,FALSE),0),174)*IF(DATEDIF(N16,DATE(参数!$B$2,参数!$B$3+1,0),"Y")<2,0.6,IF(DATEDIF(N16,DATE(参数!$B$2,参数!$B$3+1,0),"Y")<4,0.7,IF(DATEDIF(N16,DATE(参数!$B$2,参数!$B$3+1,0),"Y")<6,0.8,IF(DATEDIF(N16,DATE(参数!$B$2,参数!$B$3+1,0),"Y")<8,0.9,1)))) -> 627.58621 | AX16: =IF(Q16+IFERROR(VLOOKUP(K16,源_3考勤报表_考勤表!$F:$BG,37,FALSE),0)+IFERROR(VLOOKUP(K16,源_8补工时表_补当月工时!$A:$AC,15,FALSE),0)>=参数!$B$4,0,IF(Q16+IFERROR(VLOOKUP(K16,源_3考勤报表_考勤表!$F:$BG,37,FALSE),0)+IFERROR(VLOOKUP(K16,源_8补工时表_补当月工时!$A:$AC,15,FALSE),0)+IFERROR(VLOOKUP(K16,源_3考勤报表_考勤表!$F:$BG,38,FALSE),0)+IFERROR(VLOOKUP(K16,源_8补工时表_补当月工时!$A:$AC,17,FALSE),0)+IFERROR(VLOOKUP(K16,源_3考勤报表_考勤表!$F:$BG,40,FALSE),0)+IFERROR(VLOOKUP(K16,源_8补工时表_补当月工时!$A:$AC,20,FALSE),0)+IFERROR(VLOOKUP(K16,源_8补工时表_补当月工时!$A:$AC,22,FALSE),0)+IFERROR(VLOOKUP(K16,源_3考勤报表_考勤表!$F:$BG,41,FALSE),0)+IFERROR(VLOOKUP(K16,源_8补工时表_补当月工时!$A:$AC,18,FALSE),0)+IFERROR(VLOOKUP(K16,源_3考勤报表_考勤表!$F:$BG,42,FALSE),0)+IFERROR(VLOOKUP(K16,源_8补工时表_补当月工时!$A:$AC,19,FALSE),0)+IFERROR(VLOOKUP(K16,源_3考勤报表_考勤表!$F:$BG,44,FALSE),0)+IFERROR(VLOOKUP(K16,源_8补工时表_补当月工时!$A:$AC,16,FALSE),0)+IFERROR(VLOOKUP(K16,源_3考勤报表_考勤表!$F:$BG,45,FALSE),0)<=参数!$B$4,R16/参数!$B$4*(IFERROR(VLOOKUP(K16,源_3考勤报表_考勤表!$F:$BG,38,FALSE),0)+IFERROR(VLOOKUP(K16,源_8补工时表_补当月工时!$A:$AC,17,FALSE),0)+IFERROR(VLOOKUP(K16,源_3考勤报表_考勤表!$F:$BG,40,FALSE),0)+IFERROR(VLOOKUP(K16,源_8补工时表_补当月工时!$A:$AC,20,FALSE),0)+IFERROR(VLOOKUP(K16,源_8补工时表_补当月工时!$A:$AC,22,FALSE),0)+IFERROR(VLOOKUP(K16,源_3考勤报表_考勤表!$F:$BG,41,FALSE),0)+IFERROR(VLOOKUP(K16,源_8补工时表_补当月工时!$A:$AC,18,FALSE),0)+IFERROR(VLOOKUP(K16,源_3考勤报表_考勤表!$F:$BG,42,FALSE),0)+IFERROR(VLOOKUP(K16,源_8补工时表_补当月工时!$A:$AC,19,FALSE),0)+IFERROR(VLOOKUP(K16,源_3考勤报表_考勤表!$F:$BG,44,FALSE),0)+IFERROR(VLOOKUP(K16,源_8补工时表_补当月工时!$A:$AC,16,FALSE),0)+IFERROR(VLOOKUP(K16,源_3考勤报表_考勤表!$F:$BG,45,FALSE),0)),0)) -> 0 | AY16: 0 | AZ16: 0 | BA16: 0 | BB16: 0 | BC16: =IFERROR(VLOOKUP(K16,源_5薪资备忘录_工资调整项!$A:$AC,25,FALSE),0) -> 600 | BD16: 0 | BE16: 0 | BF16: 0 | BG16: =IFERROR(VLOOKUP(K16,源_5薪资备忘录_工资调整项!$A:$AC,22,FALSE),0)+IFERROR(VLOOKUP(K16,源_5薪资备忘录_工资调整项!$A:$AC,23,FALSE),0)+IFERROR(VLOOKUP(K16,源_5薪资备忘录_工资调整项!$A:$AC,24,FALSE),0) -> 0 | BH16: =IFERROR(VLOOKUP(DF16,源_6社保表_Sheet1!$C:$CD,80,FALSE),0)+4.5 -> 6.5 | BI16: =T16+W16+AB16+AG16+AH16+AI16+AJ16+AK16+AL16+AM16+AN16+AO16+AP16+AQ16+AR16+AS16+AT16+AU16+AV16+AW16+AX16+BC16 -> 8935.0075 | BJ16: =IFERROR(VLOOKUP(DF16,源_6社保表_Sheet1!$C:$BZ,26,FALSE),0) -> 434.84 | BK16: =IFERROR(VLOOKUP(DF16,源_6社保表_Sheet1!$C:$BZ,27,FALSE),0) -> 62.12 | BL16: =IFERROR(VLOOKUP(DF16,源_6社保表_Sheet1!$C:$BZ,28,FALSE),0) -> 31.06 | BM16: =IFERROR(VLOOKUP(DF16,源_6社保表_Sheet1!$C:$BZ,30,FALSE),0) -> 372.72 | BN16: =IFERROR(VLOOKUP(DF16,源_6社保表_Sheet1!$C:$BZ,29,FALSE),0) -> 0 | BO16: =IFERROR(VLOOKUP(DF16,源_6社保表_Sheet1!$C:$BZ,40,FALSE),0) -> 0 | BP16: =IFERROR(VLOOKUP(DF16,源_6社保表_Sheet1!$C:$BZ,41,FALSE),0) -> 0 | BQ16: =IFERROR(VLOOKUP(DF16,源_6社保表_Sheet1!$C:$BZ,42,FALSE),0) -> 0 | BR16: =IFERROR(VLOOKUP(DF16,源_6社保表_Sheet1!$C:$BZ,44,FALSE),0) -> 0 | BS16: =IFERROR(VLOOKUP(DF16,源_6社保表_Sheet1!$C:$BZ,43,FALSE),0) -> 0 | BT16: =BJ16+BK16+BL16+BM16+BN16+BO16+BP16+BQ16+BR16+BS16 -> 900.74 | BU16: 0 | BV16: 0 | BW16: 0 | BX16: =BU16+BV16+BW16 -> 0 | BY16: 0 | BZ16: =IFERROR(VLOOKUP(DF16,源_6社保表_Sheet1!$C:$BZ,18,FALSE),0) -> 931.8 | CA16: =IFERROR(VLOOKUP(DF16,源_6社保表_Sheet1!$C:$BZ,19,FALSE),0) -> 496.96 | CB16: =IFERROR(VLOOKUP(DF16,源_6社保表_Sheet1!$C:$BZ,24,FALSE),0) -> 372.72 | CC16: =IFERROR(VLOOKUP(DF16,源_6社保表_Sheet1!$C:$BZ,20,FALSE),0) -> 31.06 | CD16: =IFERROR(VLOOKUP(DF16,源_6社保表_Sheet1!$C:$BZ,21,FALSE),0) -> 19.8784 | CE16: =IFERROR(VLOOKUP(DF16,源_6社保表_Sheet1!$C:$BZ,22,FALSE),0) -> 0 | CF16: =IFERROR(VLOOKUP(DF16,源_6社保表_Sheet1!$C:$BZ,23,FALSE),0) -> 0 | CG16: =IFERROR(VLOOKUP(DF16,源_6社保表_Sheet1!$C:$BZ,32,FALSE),0) -> 0 | CH16: =IFERROR(VLOOKUP(DF16,源_6社保表_Sheet1!$C:$BZ,33,FALSE),0) -> 0 | CI16: =IFERROR(VLOOKUP(DF16,源_6社保表_Sheet1!$C:$BZ,34,FALSE),0) -> 0 | CJ16: =IFERROR(VLOOKUP(DF16,源_6社保表_Sheet1!$C:$BZ,38,FALSE),0) -> 0 | CK16: =IFERROR(VLOOKUP(DF16,源_6社保表_Sheet1!$C:$BZ,35,FALSE),0) -> 0 | CL16: =IFERROR(VLOOKUP(DF16,源_6社保表_Sheet1!$C:$BZ,36,FALSE),0) -> 0 | CM16: =IFERROR(VLOOKUP(DF16,源_6社保表_Sheet1!$C:$BZ,37,FALSE),0) -> 0 | CN16: =BZ16+CA16+CB16+CC16+CD16+CE16+CF16+CG16+CH16+CI16+CJ16+CK16+CL16+CM16 -> 1852.4184 | CO16: =BI16+BG16+CN16+BE16+BH16 -> 10793.926 | CP16: =IF(IFERROR(VLOOKUP(K16,源_13残疾人信息_残疾人信息!$A:$M,1,FALSE),"")<>"",0,IF(OR(P16="门店全职",P16="门店管理组",P16="全职(非门店)"),(BI16-AT16)*IFERROR(VLOOKUP(D16,源_12计提残保金规则_Sheet1!$A:$E,4,FALSE),0)*IFERROR(VLOOKUP(D16,源_12计提残保金规则_Sheet1!$A:$E,5,FALSE),0),0)) -> 18.553516 | CQ16: =IF(M16="行政",0,16.05) -> 16.05 | CR16: =IF(M16="门卫",0,20.67) -> 20.67 | CS16: =IF(DATEVALUE(N16)>DATE(参数!$B$2,9,30),0,IF(M16="行政",0,IF(O16="",R16/12,IF(MONTH(DATEVALUE(O16))=参数!$B$3,0,IF(DATEVALUE(O16)<DATE(参数!$B$2,参数!$B$3,1),0,R16/12))))) -> 541.66667 | CT16: =IF(P16="门店管理组",R16*0.12*0.85,0) -> 663 | CU16: =IFERROR(VLOOKUP(DF16,源_6社保表_Sheet1!$C:$I,2,FALSE),0) -> 6212 | CV16: =IFERROR(VLOOKUP(DF16,源_6社保表_Sheet1!$C:$I,7,FALSE),0) -> 6212 | CW16: =IFERROR(VLOOKUP(DF16,源_6社保表_Sheet1!$C:$I,3,FALSE),0) -> 6212 | CX16: =IFERROR(VLOOKUP(DF16,源_6社保表_Sheet1!$C:$I,4,FALSE),0) -> 6212 | CY16: =IFERROR(VLOOKUP(DF16,源_6社保表_Sheet1!$C:$I,5,FALSE),0) -> 6212 | CZ16: =IFERROR(VLOOKUP(DF16,源_6社保表_Sheet1!$C:$I,6,FALSE),0) -> 0 | DA16: =BI16+CN16-AG16-AH16-AI16-AJ16-AK16-AL16-AM16-AQ16-AR16-AS16-AT16 -> 10487.426 | DB16: =DA16+CP16+CQ16+CR16+CS16+CT16+BH16 -> 11753.866 | DC16: =IFERROR(VLOOKUP(K16,源_7银行卡表_Sheet1!$A:$J,8,FALSE),"") -> 农业银行 | DD16: =IFERROR(VLOOKUP(K16,源_7银行卡表_Sheet1!$A:$J,9,FALSE),"") -> 6687537249068003598 | DE16: =IFERROR(VLOOKUP(K16,源_7银行卡表_Sheet1!$A:$J,10,FALSE),"") -> 中国农业银行五寨三岔镇支行 | DF16: 130000197202059960 | DG16: 13419259843 | DH16: 苏州 | DI16: 0 | DJ16: 0 | DK16: 0 | DL16: 0 | DM16: 0 | DN16: 0 | DO16: 0 | DP16: 0 | DQ16: 0 | DR16: =IF(OR(IFERROR(VLOOKUP(K16,源_3考勤报表_考勤表!$F:$BG,39,FALSE),0)+IFERROR(VLOOKUP(K16,源_8补工时表_补当月工时!$A:$AC,24,FALSE),0)=0,IFERROR(VLOOKUP(K16,源_3考勤报表_考勤表!$F:$BG,43,FALSE),0)+IFERROR(VLOOKUP(K16,源_8补工时表_补当月工时!$A:$AC,26,FALSE),0)=0),IF(BI16+BG16-BT16<0,BI16+BG16-BT16,0),0) -> 0
A17: =参数!$B$2 -> 2025 | B17: =参数!$B$3 -> 12 | D17: 上海达美乐南京分公司 | E17: 店铺营运 | F17: =IFERROR(VLOOKUP(K17,源_7银行卡表_Sheet1!$A:$J,6,FALSE),"") -> 华东营运 | G17: 南京 | H17: 珠江路店 | I17: 外服-南京门店全职 | J17: 1 | K17: 26123016 | L17: 唐苑博 | M17: 餐厅副理 | N17: 2022-11-01 | P17: 门店管理组 | Q17: =IF(P17="门店全职",IFERROR(VLOOKUP(K17,源_3考勤报表_考勤表!$F:$BG,34,FALSE),0)+IFERROR(VLOOKUP(K17,源_8补工时表_补当月工时!$A:$AC,14,FALSE),0),IF(P17="门店管理组",IF(IFERROR(VLOOKUP(K17,源_3考勤报表_考勤表!$F:$BG,34,FALSE),0)+IFERROR(VLOOKUP(K17,源_8补工时表_补当月工时!$A:$AC,14,FALSE),0)+IFERROR(VLOOKUP(K17,源_3考勤报表_考勤表!$F:$BG,37,FALSE),0)+IFERROR(VLOOKUP(K17,源_8补工时表_补当月工时!$A:$AC,15,FALSE),0)+IFERROR(VLOOKUP(K17,源_3考勤报表_考勤表!$F:$BG,38,FALSE),0)+IFERROR(VLOOKUP(K17,源_8补工时表_补当月工时!$A:$AC,17,FALSE),0)+IFERROR(VLOOKUP(K17,源_3考勤报表_考勤表!$F:$BG,40,FALSE),0)+IFERROR(VLOOKUP(K17,源_8补工时表_补当月工时!$A:$AC,20,FALSE),0)+IFERROR(VLOOKUP(K17,源_8补工时表_补当月工时!$A:$AC,22,FALSE),0)+IFERROR(VLOOKUP(K17,源_3考勤报表_考勤表!$F:$BG,41,FALSE),0)+IFERROR(VLOOKUP(K17,源_8补工时表_补当月工时!$A:$AC,18,FALSE),0)+IFERROR(VLOOKUP(K17,源_3考勤报表_考勤表!$F:$BG,44,FALSE),0)+IFERROR(VLOOKUP(K17,源_8补工时表_补当月工时!$A:$AC,16,FALSE),0)+IFERROR(VLOOKUP(K17,源_3考勤报表_考勤表!$F:$BG,45,FALSE),0)>=参数!$B$4,参数!$B$4-IFERROR(VLOOKUP(K17,源_3考勤报表_考勤表!$F:$BG,37,FALSE),0)-IFERROR(VLOOKUP(K17,源_8补工时表_补当月工时!$A:$AC,15,FALSE),0)-IFERROR(VLOOKUP(K17,源_3考勤报表_考勤表!$F:$BG,38,FALSE),0)-IFERROR(VLOOKUP(K17,源_8补工时表_补当月工时!$A:$AC,17,FALSE),0)-IFERROR(VLOOKUP(K17,源_3考勤报表_考勤表!$F:$BG,40,FALSE),0)-IFERROR(VLOOKUP(K17,源_8补工时表_补当月工时!$A:$AC,20,FALSE),0)-IFERROR(VLOOKUP(K17,源_8补工时表_补当月工时!$A:$AC,22,FALSE),0)-IFERROR(VLOOKUP(K17,源_3考勤报表_考勤表!$F:$BG,41,FALSE),0)-IFERROR(VLOOKUP(K17,源_8补工时表_补当月工时!$A:$AC,18,FALSE),0)-IFERROR(VLOOKUP(K17,源_3考勤报表_考勤表!$F:$BG,44,FALSE),0)-IFERROR(VLOOKUP(K17,源_8补工时表_补当月工时!$A:$AC,16,FALSE),0)-IFERROR(VLOOKUP(K17,源_3考勤报表_考勤表!$F:$BG,45,FALSE),0),IFERROR(VLOOKUP(K17,源_3考勤报表_考勤表!$F:$BG,34,FALSE),0)+IFERROR(VLOOKUP(K17,源_8补工时表_补当月工时!$A:$AC,14,FALSE),0)),0)) -> 30 | R17: 5309 | S17: 22 | T17: =IF(P17="门店全职",R17/参数!$B$4*(Q17-MAX(IFERROR(VLOOKUP(K17,源_3考勤报表_考勤表!$F:$BG,34,FALSE),0)+IFERROR(VLOOKUP(K17,源_8补工时表_补当月工时!$A:$AC,14,FALSE),0)+IFERROR(VLOOKUP(K17,源_3考勤报表_考勤表!$F:$BG,37,FALSE),0)+IFERROR(VLOOKUP(K17,源_8补工时表_补当月工时!$A:$AC,15,FALSE),0)+IFERROR(VLOOKUP(K17,源_3考勤报表_考勤表!$F:$BG,38,FALSE),0)+IFERROR(VLOOKUP(K17,源_8补工时表_补当月工时!$A:$AC,17,FALSE),0)+IFERROR(VLOOKUP(K17,源_3考勤报表_考勤表!$F:$BG,40,FALSE),0)+IFERROR(VLOOKUP(K17,源_8补工时表_补当月工时!$A:$AC,20,FALSE),0)+IFERROR(VLOOKUP(K17,源_8补工时表_补当月工时!$A:$AC,22,FALSE),0)+IFERROR(VLOOKUP(K17,源_3考勤报表_考勤表!$F:$BG,41,FALSE),0)+IFERROR(VLOOKUP(K17,源_8补工时表_补当月工时!$A:$AC,18,FALSE),0)+IFERROR(VLOOKUP(K17,源_3考勤报表_考勤表!$F:$BG,42,FALSE),0)+IFERROR(VLOOKUP(K17,源_8补工时表_补当月工时!$A:$AC,19,FALSE),0)+IFERROR(VLOOKUP(K17,源_3考勤报表_考勤表!$F:$BG,44,FALSE),0)+IFERROR(VLOOKUP(K17,源_8补工时表_补当月工时!$A:$AC,16,FALSE),0)+IFERROR(VLOOKUP(K17,源_3考勤报表_考勤表!$F:$BG,45,FALSE),0)-参数!$B$4,0)),R17/参数!$B$4*Q17) -> 865.59783 | U17: 0 | V17: 0 | W17: =X17+Y17+Z17+AA17 -> 300 | X17: =IFERROR(VLOOKUP(K17,源_4奖金汇总表_拆分手工算!$A:$N,8,FALSE),0) -> 0 | Y17: =IFERROR(VLOOKUP(K17,源_5薪资备忘录_工资调整项!$A:$AC,14,FALSE),0) -> 300 | Z17: =IFERROR(VLOOKUP(K17,源_5薪资备忘录_工资调整项!$A:$AC,16,FALSE),0) -> 0 | AA17: =IFERROR(VLOOKUP(K17,源_5薪资备忘录_工资调整项!$A:$AC,15,FALSE),0) -> 0 | AB17: =AC17+AD17+AF17 -> 0 | AC17: =IF(P17="门店全职",R17/174*MAX(IFERROR(VLOOKUP(K17,源_3考勤报表_考勤表!$F:$BG,34,FALSE),0)+IFERROR(VLOOKUP(K17,源_8补工时表_补当月工时!$A:$AC,14,FALSE),0)+IFERROR(VLOOKUP(K17,源_3考勤报表_考勤表!$F:$BG,37,FALSE),0)+IFERROR(VLOOKUP(K17,源_8补工时表_补当月工时!$A:$AC,15,FALSE),0)+IFERROR(VLOOKUP(K17,源_3考勤报表_考勤表!$F:$BG,38,FALSE),0)+IFERROR(VLOOKUP(K17,源_8补工时表_补当月工时!$A:$AC,17,FALSE),0)+IFERROR(VLOOKUP(K17,源_3考勤报表_考勤表!$F:$BG,40,FALSE),0)+IFERROR(VLOOKUP(K17,源_8补工时表_补当月工时!$A:$AC,20,FALSE),0)+IFERROR(VLOOKUP(K17,源_8补工时表_补当月工时!$A:$AC,22,FALSE),0)+IFERROR(VLOOKUP(K17,源_3考勤报表_考勤表!$F:$BG,41,FALSE),0)+IFERROR(VLOOKUP(K17,源_8补工时表_补当月工时!$A:$AC,18,FALSE),0)+IFERROR(VLOOKUP(K17,源_3考勤报表_考勤表!$F:$BG,42,FALSE),0)+IFERROR(VLOOKUP(K17,源_8补工时表_补当月工时!$A:$AC,19,FALSE),0)+IFERROR(VLOOKUP(K17,源_3考勤报表_考勤表!$F:$BG,44,FALSE),0)+IFERROR(VLOOKUP(K17,源_8补工时表_补当月工时!$A:$AC,16,FALSE),0)+IFERROR(VLOOKUP(K17,源_3考勤报表_考勤表!$F:$BG,45,FALSE),0)-参数!$B$4,0)*1.5,0) -> 0 | AD17: 0 | AE17: =IFERROR(VLOOKUP(K17,源_3考勤报表_考勤表!$F:$BG,46,FALSE),0)+IFERROR(VLOOKUP(K17,源_8补工时表_补当月工时!$A:$AC,25,FALSE),0) -> 0 | AF17: =R17/174*AE17*3 -> 0 | AG17: =IFERROR(VLOOKUP(K17,源_4奖金汇总表_拆分手工算!$A:$N,10,FALSE),0) -> 0 | AH17: =IFERROR(VLOOKUP(K17,源_4奖金汇总表_拆分手工算!$A:$N,5,FALSE),0) -> 0 | AI17: =IFERROR(VLOOKUP(K17,源_4奖金汇总表_拆分手工算!$A:$N,11,FALSE),0) -> 0 | AJ17: =IFERROR(VLOOKUP(K17,源_4奖金汇总表_拆分手工算!$A:$N,4,FALSE),0) -> 0 | AK17: =IFERROR(VLOOKUP(K17,源_4奖金汇总表_拆分手工算!$A:$N,3,FALSE),0) -> 0 | AL17: =IFERROR(VLOOKUP(K17,源_4奖金汇总表_拆分手工算!$A:$N,6,FALSE),0) -> 212.5 | AM17: =IFERROR(VLOOKUP(K17,源_5薪资备忘录_工资调整项!$A:$AC,18,FALSE),0)+IFERROR(VLOOKUP(K17,源_4奖金汇总表_拆分手工算!$A:$N,7,FALSE),0) -> 222.22 | AN17: =IFERROR(VLOOKUP(K17,源_5薪资备忘录_工资调整项!$A:$AC,17,FALSE),0) -> 0 | AO17: =IF(OR(IFERROR(VLOOKUP(K17,源_3考勤报表_考勤表!$F:$BG,39,FALSE),0)+IFERROR(VLOOKUP(K17,源_8补工时表_补当月工时!$A:$AC,24,FALSE),0)>0,IFERROR(VLOOKUP(K17,源_3考勤报表_考勤表!$F:$BG,43,FALSE),0)+IFERROR(VLOOKUP(K17,源_8补工时表_补当月工时!$A:$AC,26,FALSE),0)>0),IF(IFERROR(VLOOKUP(DH17,源_11产假政策_Sheet1!$C:$F,4,FALSE),"")="是",R17/参数!$B$4*(IFERROR(VLOOKUP(K17,源_3考勤报表_考勤表!$F:$BG,39,FALSE),0)+IFERROR(VLOOKUP(K17,源_8补工时表_补当月工时!$A:$AC,24,FALSE),0)+IFERROR(VLOOKUP(K17,源_3考勤报表_考勤表!$F:$BG,43,FALSE),0)+IFERROR(VLOOKUP(K17,源_8补工时表_补当月工时!$A:$AC,26,FALSE),0)),IFERROR(VLOOKUP(K17,源_5薪资备忘录_工资调整项!$A:$AC,19,FALSE),0)),0) -> 0 | AP17: 0 | AQ17: =IFERROR(VLOOKUP(K17,源_4奖金汇总表_拆分手工算!$A:$N,12,FALSE),0)+IFERROR(VLOOKUP(K17,源_9年终奖表_Sheet1!$A:$E,3,FALSE),0) -> 0 | AR17: =IFERROR(VLOOKUP(K17,源_4奖金汇总表_拆分手工算!$A:$N,13,FALSE),0)+IFERROR(VLOOKUP(K17,源_9年终奖表_Sheet1!$A:$E,4,FALSE),0) -> 0 | AS17: =IFERROR(VLOOKUP(K17,源_4奖金汇总表_拆分手工算!$A:$N,14,FALSE),0)+IFERROR(VLOOKUP(K17,源_9年终奖表_Sheet1!$A:$E,5,FALSE),0) -> 0 | AT17: =IFERROR(VLOOKUP(K17,源_5薪资备忘录_工资调整项!$A:$AC,20,FALSE),0) -> 0 | AU17: =IFERROR(VLOOKUP(K17,源_5薪资备忘录_工资调整项!$A:$AC,21,FALSE),0)+IFERROR(VLOOKUP(K17,源_4奖金汇总表_拆分手工算!$A:$N,9,FALSE),0) -> 0 | AV17: =R17/参数!$B$4*(IFERROR(VLOOKUP(K17,源_3考勤报表_考勤表!$F:$BG,37,FALSE),0)+IFERROR(VLOOKUP(K17,源_8补工时表_补当月工时!$A:$AC,15,FALSE),0)) -> 1154.1304 | AW17: =R17/174*MIN(IFERROR(VLOOKUP(K17,源_3考勤报表_考勤表!$F:$BG,35,FALSE),0),174)*IF(DATEDIF(N17,DATE(参数!$B$2,参数!$B$3+1,0),"Y")<2,0.6,IF(DATEDIF(N17,DATE(参数!$B$2,参数!$B$3+1,0),"Y")<4,0.7,IF(DATEDIF(N17,DATE(参数!$B$2,参数!$B$3+1,0),"Y")<6,0.8,IF(DATEDIF(N17,DATE(参数!$B$2,参数!$B$3+1,0),"Y")<8,0.9,1)))) -> 2434.8172 | AX17: =IF(Q17+IFERROR(VLOOKUP(K17,源_3考勤报表_考勤表!$F:$BG,37,FALSE),0)+IFERROR(VLOOKUP(K17,源_8补工时表_补当月工时!$A:$AC,15,FALSE),0)>=参数!$B$4,0,IF(Q17+IFERROR(VLOOKUP(K17,源_3考勤报表_考勤表!$F:$BG,37,FALSE),0)+IFERROR(VLOOKUP(K17,源_8补工时表_补当月工时!$A:$AC,15,FALSE),0)+IFERROR(VLOOKUP(K17,源_3考勤报表_考勤表!$F:$BG,38,FALSE),0)+IFERROR(VLOOKUP(K17,源_8补工时表_补当月工时!$A:$AC,17,FALSE),0)+IFERROR(VLOOKUP(K17,源_3考勤报表_考勤表!$F:$BG,40,FALSE),0)+IFERROR(VLOOKUP(K17,源_8补工时表_补当月工时!$A:$AC,20,FALSE),0)+IFERROR(VLOOKUP(K17,源_8补工时表_补当月工时!$A:$AC,22,FALSE),0)+IFERROR(VLOOKUP(K17,源_3考勤报表_考勤表!$F:$BG,41,FALSE),0)+IFERROR(VLOOKUP(K17,源_8补工时表_补当月工时!$A:$AC,18,FALSE),0)+IFERROR(VLOOKUP(K17,源_3考勤报表_考勤表!$F:$BG,42,FALSE),0)+IFERROR(VLOOKUP(K17,源_8补工时表_补当月工时!$A:$AC,19,FALSE),0)+IFERROR(VLOOKUP(K17,源_3考勤报表_考勤表!$F:$BG,44,FALSE),0)+IFERROR(VLOOKUP(K17,源_8补工时表_补当月工时!$A:$AC,16,FALSE),0)+IFERROR(VLOOKUP(K17,源_3考勤报表_考勤表!$F:$BG,45,FALSE),0)<=参数!$B$4,R17/参数!$B$4*(IFERROR(VLOOKUP(K17,源_3考勤报表_考勤表!$F:$BG,38,FALSE),0)+IFERROR(VLOOKUP(K17,源_8补工时表_补当月工时!$A:$AC,17,FALSE),0)+IFERROR(VLOOKUP(K17,源_3考勤报表_考勤表!$F:$BG,40,FALSE),0)+IFERROR(VLOOKUP(K17,源_8补工时表_补当月工时!$A:$AC,20,FALSE),0)+IFERROR(VLOOKUP(K17,源_8补工时表_补当月工时!$A:$AC,22,FALSE),0)+IFERROR(VLOOKUP(K17,源_3考勤报表_考勤表!$F:$BG,41,FALSE),0)+IFERROR(VLOOKUP(K17,源_8补工时表_补当月工时!$A:$AC,18,FALSE),0)+IFERROR(VLOOKUP(K17,源_3考勤报表_考勤表!$F:$BG,42,FALSE),0)+IFERROR(VLOOKUP(K17,源_8补工时表_补当月工时!$A:$AC,19,FALSE),0)+IFERROR(VLOOKUP(K17,源_3考勤报表_考勤表!$F:$BG,44,FALSE),0)+IFERROR(VLOOKUP(K17,源_8补工时表_补当月工时!$A:$AC,16,FALSE),0)+IFERROR(VLOOKUP(K17,源_3考勤报表_考勤表!$F:$BG,45,FALSE),0)),0)) -> 0 | AY17: 0 | AZ17: 0 | BA17: 0 | BB17: 0 | BC17: =IFERROR(VLOOKUP(K17,源_5薪资备忘录_工资调整项!$A:$AC,25,FALSE),0) -> 0 | BD17: 0 | BE17: 0 | BF17: 0 | BG17: =IFERROR(VLOOKUP(K17,源_5薪资备忘录_工资调整项!$A:$AC,22,FALSE),0)+IFERROR(VLOOKUP(K17,源_5薪资备忘录_工资调整项!$A:$AC,23,FALSE),0)+IFERROR(VLOOKUP(K17,源_5薪资备忘录_工资调整项!$A:$AC,24,FALSE),0) -> 333.33 | BH17: =IFERROR(VLOOKUP(DF17,源_6社保表_Sheet1!$C:$CD,80,FALSE),0)+4.5 -> 6.5 | BI17: =T17+W17+AB17+AG17+AH17+AI17+AJ17+AK17+AL17+AM17+AN17+AO17+AP17+AQ17+AR17+AS17+AT17+AU17+AV17+AW17+AX17+BC17 -> 5189.2655 | BJ17: =IFERROR(VLOOKUP(DF17,源_6社保表_Sheet1!$C:$BZ,26,FALSE),0) -> 515.27 | BK17: =IFERROR(VLOOKUP(DF17,源_6社保表_Sheet1!$C:$BZ,27,FALSE),0) -> 73.61 | BL17: =IFERROR(VLOOKUP(DF17,源_6社保表_Sheet1!$C:$BZ,28,FALSE),0) -> 36.805 | BM17: =IFERROR(VLOOKUP(DF17,源_6社保表_Sheet1!$C:$BZ,30,FALSE),0) -> 441.66 | BN17: =IFERROR(VLOOKUP(DF17,源_6社保表_Sheet1!$C:$BZ,29,FALSE),0) -> 0 | BO17: =IFERROR(VLOOKUP(DF17,源_6社保表_Sheet1!$C:$BZ,40,FALSE),0) -> 0 | BP17: =IFERROR(VLOOKUP(DF17,源_6社保表_Sheet1!$C:$BZ,41,FALSE),0) -> 0 | BQ17: =IFERROR(VLOOKUP(DF17,源_6社保表_Sheet1!$C:$BZ,42,FALSE),0) -> 0 | BR17: =IFERROR(VLOOKUP(DF17,源_6社保表_Sheet1!$C:$BZ,44,FALSE),0) -> 0 | BS17: =IFERROR(VLOOKUP(DF17,源_6社保表_Sheet1!$C:$BZ,43,FALSE),0) -> 0 | BT17: =BJ17+BK17+BL17+BM17+BN17+BO17+BP17+BQ17+BR17+BS17 -> 1067.345 | BU17: 0 | BV17: 0 | BW17: 0 | BX17: =BU17+BV17+BW17 -> 0 | BY17: 0 | BZ17: =IFERROR(VLOOKUP(DF17,源_6社保表_Sheet1!$C:$BZ,18,FALSE),0) -> 1104.15 | CA17: =IFERROR(VLOOKUP(DF17,源_6社保表_Sheet1!$C:$BZ,19,FALSE),0) -> 588.88 | CB17: =IFERROR(VLOOKUP(DF17,源_6社保表_Sheet1!$C:$BZ,24,FALSE),0) -> 441.66 | CC17: =IFERROR(VLOOKUP(DF17,源_6社保表_Sheet1!$C:$BZ,20,FALSE),0) -> 36.805 | CD17: =IFERROR(VLOOKUP(DF17,源_6社保表_Sheet1!$C:$BZ,21,FALSE),0) -> 23.5552 | CE17: =IFERROR(VLOOKUP(DF17,源_6社保表_Sheet1!$C:$BZ,22,FALSE),0) -> 0 | CF17: =IFERROR(VLOOKUP(DF17,源_6社保表_Sheet1!$C:$BZ,23,FALSE),0) -> 0 | CG17: =IFERROR(VLOOKUP(DF17,源_6社保表_Sheet1!$C:$BZ,32,FALSE),0) -> 0 | CH17: =IFERROR(VLOOKUP(DF17,源_6社保表_Sheet1!$C:$BZ,33,FALSE),0) -> 0 | CI17: =IFERROR(VLOOKUP(DF17,源_6社保表_Sheet1!$C:$BZ,34,FALSE),0) -> 0 | CJ17: =IFERROR(VLOOKUP(DF17,源_6社保表_Sheet1!$C:$BZ,38,FALSE),0) -> 0 | CK17: =IFERROR(VLOOKUP(DF17,源_6社保表_Sheet1!$C:$BZ,35,FALSE),0) -> 0 | CL17: =IFERROR(VLOOKUP(DF17,源_6社保表_Sheet1!$C:$BZ,36,FALSE),0) -> 0 | CM17: =IFERROR(VLOOKUP(DF17,源_6社保表_Sheet1!$C:$BZ,37,FALSE),0) -> 0 | CN17: =BZ17+CA17+CB17+CC17+CD17+CE17+CF17+CG17+CH17+CI17+CJ17+CK17+CL17+CM17 -> 2195.0502 | CO17: =BI17+BG17+CN17+BE17+BH17 -> 7724.1457 | CP17: =IF(IFERROR(VLOOKUP(K17,源_13残疾人信息_残疾人信息!$A:$M,1,FALSE),"")<>"",0,IF(OR(P17="门店全职",P17="门店管理组",P17="全职(非门店)"),(BI17-AT17)*IFERROR(VLOOKUP(D17,源_12计提残保金规则_Sheet1!$A:$E,4,FALSE),0)*IFERROR(VLOOKUP(D17,源_12计提残保金规则_Sheet1!$A:$E,5,FALSE),0),0)) -> 31.135593 | CQ17: =IF(M17="行政",0,16.05) -> 16.05 | CR17: =IF(M17="门卫",0,20.67) -> 20.67 | CS17: =IF(DATEVALUE(N17)>DATE(参数!$B$2,9,30),0,IF(M17="行政",0,IF(O17="",R17/12,IF(MONTH(DATEVALUE(O17))=参数!$B$3,0,IF(DATEVALUE(O17)<DATE(参数!$B$2,参数!$B$3,1),0,R17/12))))) -> 442.41667 | CT17: =IF(P17="门店管理组",R17*0.12*0.85,0) -> 541.518 | CU17: =IFERROR(VLOOKUP(DF17,源_6社保表_Sheet1!$C:$I,2,FALSE),0) -> 7361 | CV17: =IFERROR(VLOOKUP(DF17,源_6社保表_Sheet1!$C:$I,7,FALSE),0) -> 7361 | CW17: =IFERROR(VLOOKUP(DF17,源_6社保表_Sheet1!$C:$I,3,FALSE),0) -> 7361 | CX17: =IFERROR(VLOOKUP(DF17,源_6社保表_Sheet1!$C:$I,4,FALSE),0) -> 7361 | CY17: =IFERROR(VLOOKUP(DF17,源_6社保表_Sheet1!$C:$I,5,FALSE),0) -> 7361 | CZ17: =IFERROR(VLOOKUP(DF17,源_6社保表_Sheet1!$C:$I,6,FALSE),0) -> 0 | DA17: =BI17+CN17-AG17-AH17-AI17-AJ17-AK17-AL17-AM17-AQ17-AR17-AS17-AT17 -> 6949.5957 | DB17: =DA17+CP17+CQ17+CR17+CS17+CT17+BH17 -> 8007.886 | DC17: =IFERROR(VLOOKUP(K17,源_7银行卡表_Sheet1!$A:$J,8,FALSE),"") -> 农业银行 | DD17: =IFERROR(VLOOKUP(K17,源_7银行卡表_Sheet1!$A:$J,9,FALSE),"") -> 6684682572664386666 | DE17: =IFERROR(VLOOKUP(K17,源_7银行卡表_Sheet1!$A:$J,10,FALSE),"") -> 中国农业银行临汾中大街分理处 | DF17: 130000195507080205 | DG17: 18370920073 | DH17: 南京 | DI17: 0 | DJ17: 0 | DK17: 0 | DL17: 0 | DM17: 0 | DN17: 0 | DO17: 0 | DP17: 0 | DQ17: 0 | DR17: =IF(OR(IFERROR(VLOOKUP(K17,源_3考勤报表_考勤表!$F:$BG,39,FALSE),0)+IFERROR(VLOOKUP(K17,源_8补工时表_补当月工时!$A:$AC,24,FALSE),0)=0,IFERROR(VLOOKUP(K17,源_3考勤报表_考勤表!$F:$BG,43,FALSE),0)+IFERROR(VLOOKUP(K17,源_8补工时表_补当月工时!$A:$AC,26,FALSE),0)=0),IF(BI17+BG17-BT17<0,BI17+BG17-BT17,0),0) -> 0
