Workbook

Sheet 付款通知书
A1: 上海外服合杰企业服务有限公司 付款通知书
A3: 46054
A5: 公司名称:安迪苏生命科学制品（上海）有限公司
A8: 城市 | B8: 社会保险类 | I8: 工资类 | L8: 报销 | M8: 服务费 | O8: 招聘费 | P8: 小计 | Q8: 增值税 | R8: 发票总金额
B9: 人数 | C9: 公司缴纳金额 | D9: 个人缴纳金额 | E9: 补缴人数 | F9: 公司补缴金额 | G9: 个人补缴金额 | H9: 社保类小计 | I9: 人数 | J9: 工资请款 | K9: 年终奖请款 | L9: 报销请款 | M9: 人数 | N9: 收费
A10: 上海 | B10: 1 | C10: =工资明细!AX9+工资明细!AY9+工资明细!AZ9+工资明细!BA9+工资明细!BB9+工资明细!AW9 -> 0 | D10: =工资明细!AB9+工资明细!AC9+工资明细!AD9+工资明细!AE9 -> 0 | E10: 0 | F10: 0 | G10: 0 | H10: =C10+D10 -> 0 | I10: =B10 -> 1 | J10: =工资明细!AG9+工资明细!AP9 -> 0 | K10: =工资明细!AQ9 -> 0 | L10: =工资明细!AU7+工资明细!AV7 -> 0 | M10: =B10 -> 1 | N10: =工资明细!BC9 -> 300 | O10: =工资明细!AV6 -> 0 | P10: =H10+J10+N10+K10+O10+L10 -> 300 | Q10: =ROUND(P10*6.77%,2) -> 20.31 | R10: =ROUND(P10*(1+6.77%),2) -> 320.31
A11: 汇总 | B11: =SUM(B10:B10) -> 1 | C11: =SUM(C10:C10) -> 0 | D11: =SUM(D10:D10) -> 0 | E11: =SUM(E10:E10) -> 0 | F11: =SUM(F10:F10) -> 0 | G11: =SUM(G10:G10) -> 0 | H11: =SUM(H10:H10) -> 0 | I11: =SUM(I10:I10) -> 1 | ... R11: =SUM(R10:R10) -> 320.31
A13: 本月总计： | B13: =IF(R11<=0,,"人民币"&IF(INT(R11)=0,,TEXT(INT(R11),"[dbnum2]")&"圆")&IF(INT(R11*10)-INT(R11)*10=0,IF(INT(R11)*(INT(R11*100)-INT(R11*10)*10)=0,"","零"),TEXT(INT(R11*10)-INT(R11)*10,"[dbnum2]")&"角")&IF((INT(R11*100)-INT(R11*10)*10)=0,"整",TEXT((INT(R11*100)-INT(R11*10)*10),"[dbnum2]")&"分")) -> 人民币叁佰贰拾圆叁角壹分
A15: 制单人：徐靖 | D15: 制单日期：2026-2
A18: 户名：上海外服合杰企业服务有限公司
A19: 开户银行：中国工商银行上海市金钟支行
A20: 人民币银行帐号：RMB 1001199409006536383

Sheet 工资明细
A3: 1 | B3: 2 | C3: 3 | D3: 4 | E3: 5 | F3: 6 | G3: 7 | H3: 8 | I3: 9 | J3: 10 | K3: 11 | L3: 12 | M3: 13 | N3: 14 | O3: 15 | P3: 16 | Q3: 17 | R3: 18 | S3: 19 | T3: 20 | U3: 21 | V3: 22 | W3: 23 | X3: 24 | Y3: 25 | Z3: 26 | AA3: 27 | AB3: 28 | AC3: 29 | AD3: 30 | AE3: 31 | AF3: 32 | AG3: 33 | AH3: 34 | AI3: 35 | AJ3: 36 | AK3: 37 | AL3: 38 | AM3: 39 | AN3: 40 | AO3: 41 | AP3: 42 | AQ3: 43 | AR3: 44 | AS3: 45 | AT3: 46 | AU3: 47 | AV3: 48 | AW3: 49 | AX3: 50 | AY3: 51 | AZ3: 52 | BA3: 53 | BB3: 54 | BC3: 55 | BE3: 56 | BF3: 57
A5: 序号 | B5: 日期 | C5: 城市 | D5: 姓名 | E5: 身份证 | F5: 入职日期 | G5: 离职日期 | H5: 工龄 | I5: 岗位 | J5: 事假 | K5: 产假 | L5: 婚假 | M5: 病假 | N5: 年假 | O5: 旷工 | P5: 入离职缺勤 | Q5: 平日加班 | R5: 周末加班 | S5: 节假日加班 | T5: 社保基数 | U5: 基本工资 | V5: 出勤天数 | W5: 实际工资 | X5: 病假工资 | Y5: 其他 | Z5: 津贴&加班费 | AA5: 应发工资 | AB5: 养老 (个人) | AC5: 医疗 (个人) | AD5: 失业 (个人) | AE5: 公积金 (个人) | AF5: 四金补差 | AG5: 税前工资 | AH5: 上月合并计税工资 | AI5: 上个月个税 | AJ5: 累积个税 | AK5: 专项扣除 (累计） | AL5: 专项扣除 (上月） | AM5: 本月合计计税工资 | AN5: 个人所得税 | AO5: 前月个税累计计算值 | AP5: 税后补差 | AQ5: 税前年终奖 | AR5: 年终奖个税 | AS5: 实得年终奖 | AT5: 实发工资 | AU5: 报销 | AV5: 报销企业所得税（餐费） | AW5: 残保金 | AX5: 养老 (公司) | AY5: 医疗 (公司) | AZ5: 失业 (公司) | BA5: 意外险 | BB5: 公积金 (公司) | BC5: 服务费 | BD5: 小计 | BE5: 增值税 | BF5: 总成本 | BH5: 备注
A6: 1 | B6: 2026-02 | C6: 上海 | D6: 王怀桃 | E6: 342422196905101429 | F6: 45839 | H6: =IF(G6>0,ROUND(DATEDIF(F6,G6,"d")/365,2),ROUND(DATEDIF(F6,DATE(2026,2,28),"d")/365,2)) -> 0.66 | V6: 23 | AA6: =ROUND(W6+X6+Y6+Z6,2) -> 0 | AB6: =$T$6*8% -> 0 | AC6: =T6*2% -> 0 | AD6: =$T$6*0.5% -> 0 | AE6: =$T$6*7% -> 0 | AG6: =ROUND(AA6-AB6-AC6-AD6-AE6-AF6,2) -> 0 | AM6: =ROUND(AG6+AH6-5000-(AK6-AL6),2) -> -5000 | AN6: {=ROUND(MAX(AM6*{0.03,0.1,0.2,0.25,0.3,0.35,0.45}-{0,2520,16920,31920,52920,85920,181920}-(AI6+AJ6),0),2)} -> 0 | AO6: =ROUND(AI6+AJ6,2) -> 0 | AR6: =ROUND(LOOKUP(MAX(0.0001,AQ6/12),{0;6;24;50;70;110;160}*500+0.0001,5*MAX(0,AQ6)*{0.6;2;4;5;6;7;9}%-10*{0;21;141;266;441;716;1516}),2) -> 0 | AS6: =ROUND(AQ6-AR6,2) -> 0 | AT6: =ROUND(AG6-AN6+AP6+AS6,2) -> 0 | AW6: =$T$6*1.5% -> 0 | AX6: =$T$6*16% -> 0 | AY6: =$T$6*9% -> 0 | AZ6: =$T$6*0.5% -> 0 | BB6: =U6*7% -> 0 | BC6: 300 | BD6: =AA6+AW6+AX6+AY6+AZ6+BA6+BB6+BC6+AV6+AQ6 -> 300 | BE6: =ROUND((AA6+AQ6+AX6+AY6+AZ6+BA6+BB6+AW6+BC6+AV6+AP6)*6.77%,2) -> 20.31 | BF6: =ROUND(AA6+AQ6+AV6+AX6+AY6+AZ6+BA6+BB6+AW6+BC6+BE6+AP6,2) -> 320.31
BC8: =(AU8+AV8)*6% -> 0 | BD8: =AU8+AV8 -> 0 | BE8: =ROUND((BD8+BC8)*6.78%,2) -> 0 | BF8: =ROUND(BD8+BE8+BC8,2) -> 0
A9: Total: | W9: =SUM(W6:W8) -> 0 | X9: =SUM(X6:X8) -> 0 | Y9: =SUM(Y6:Y8) -> 0 | Z9: =SUM(Z6:Z8) -> 0 | AA9: =SUM(AA6:AA8) -> 0 | AB9: =SUM(AB6:AB8) -> 0 | AC9: =SUM(AC6:AC8) -> 0 | AD9: =SUM(AD6:AD8) -> 0 | ... BF9: =SUM(BF6:BF8) -> 320.31

Sheet 开票通知书（新）
A2: 开票通知书
P3: 序号( )
A4: 主数据编号:_ 1000049446______
A5: 收款单位:_ 上海合杰人才服务有限公司______
A6: 发票号码：___________________________
A7: 付款单位：
A8: 开票时间：_________安迪苏生命科学制品（上海）有限公司__________________
A9: 所属期间：__________2024年12月________
A10: 客户企业类型：三资企业
B13: 行业 | C13: 产品线 | D13: 风险类型 | E13: 工资 | F13: 社保 | G13: 公积金 | H13: 年终奖 | I13: 代垫费用 | J13: 代报销 | K13: 代报销附加税 | L13: 服务费 | M13: 外划服务费 | N13: 其他 | O13: 小计 | P13: 附加税 | Q13: 不含税金额 | R13: 增值税 | S13: 发票总金额
B14: 零售服务 | C14: 岗位外包 | D14: 风险后置 | E14: =工资明细!AG9+工资明细!AP9 -> 0 | F14: =工资明细!AB9+工资明细!AC9+工资明细!AD9+工资明细!AX9+工资明细!AY9+工资明细!AZ9+工资明细!BA9 -> 0 | G14: =工资明细!AE9+工资明细!BB9 -> 0 | H14: =工资明细!AQ9 -> 0 | J14: =工资明细!AU7 -> 0 | K14: =工资明细!AV7 -> 0 | L14: =(工资明细!BC6+工资明细!BC7)-M14 -> 300 | M14: 0 | N14: =C20 -> 0 | O14: =ROUND(SUM(E14:N14),2) -> 300 | P14: =ROUND(Q14-O14,2) -> 2.18 | Q14: =ROUND(S14/(1+6%),2) -> 302.18 | R14: =ROUND(Q14*6%,2) -> 18.13 | S14: =ROUND(O14*(1+6.77%),2) -> 320.31
B16: 合计 | E16: =SUM(E14:E15) -> 0 | F16: =SUM(F14:F15) -> 0 | G16: =SUM(G14:G15) -> 0 | H16: =SUM(H14:H15) -> 0 | I16: =SUM(I14:I15) -> 0 | J16: =SUM(J14:J15) -> 0 | K16: =SUM(K14:K15) -> 0 | L16: =SUM(L14:L15) -> 300 | ... S16: =SUM(S14:S15) -> 320.31
B18: 备注：
B20: 本地保障服务费 | C20: =工资明细!AW9 -> 0
B21: 外地保障服务费 | J21: 部门： | L21: 业务二部
B22: MBP | J22: 制单人：
J23: 申请日期： | L23: 45427
J24: 部门主管：

Sheet 供应商明细表
A2: 客户名称：安迪苏生命科学制品（上海）有限公司
A4: 所属期： 2024年12月
A6: 供应商 | B6: 工资（含个税） | C6: 社保 | D6: 公积金 | E6: 社保公积金合计 | F6: 年终奖 | G6: 外划服务费 | H6: 代垫费用 | I6: 代报销 | J6: 外地保障服务费
A7: 本部 | B7: ='开票通知书（新）'!E14 -> 0 | F7: ='开票通知书（新）'!H14 -> 0 | I7: =工资明细!AU7 -> 0
A8: 上海市人力资源和社会保障局 | C8: =工资明细!AB6+工资明细!AC6+工资明细!AD6+工资明细!AX6+工资明细!AY6+工资明细!AZ6+工资明细!BA6 -> 0
A9: 上海公积金中心 | D9: =工资明细!AE6+工资明细!BB6 -> 0 | E9: =C8+D9 -> 0
C10: =工资明细!AB7+工资明细!AC7+工资明细!AD7+工资明细!AX7+工资明细!AY7+工资明细!AZ7+工资明细!BA7 -> 0 | D10: =工资明细!AE7+工资明细!BB7 -> 0 | E10: =C10+D10 -> 0
A16: 合计 | B16: =SUM(B7:B15) -> 0 | C16: =SUM(C7:C15) -> 0 | D16: =SUM(D7:D15) -> 0 | E16: =SUM(E7:E15) -> 0 | F16: =SUM(F7:F15) -> 0 | G16: =SUM(G7:G15) -> 0 | H16: =SUM(H7:H15) -> 0 | I16: =SUM(I7:I15) -> 0 | J16: =SUM(J7:J15) -> 0
A20: 开票金额 | B20: ='开票通知书（新）'!E14 -> 0 | C20: ='开票通知书（新）'!F14 -> 0 | D20: ='开票通知书（新）'!G14 -> 0 | E20: =C20+D20 -> 0 | F20: ='开票通知书（新）'!H14 -> 0 | G20: ='开票通知书（新）'!M14 -> 0 | H20: ='开票通知书（新）'!I14 -> 0 | I20: ='开票通知书（新）'!J14 -> 0 | J20: ='开票通知书（新）'!C21 -> 0
A21: 稽核 | B21: =+B16-B20 -> 0 | C21: =+C16-C20 -> 0 | D21: =+D16-D20 -> 0 | E21: =+E16-E20 -> 0 | F21: =+F16-F20 -> 0 | G21: =+G16-G20 -> 0 | H21: =+H16-H20 -> 0 | I21: =+I16-I20 -> 0 | J21: =+J16-J20 -> 0
